{
  "type": "Feature",
  "properties": {
    "gn:admin1_code":"25",
    "gn:asciiname":"Phum Sranal",
    "gn:country_code":"KH",
    "gn:dem":10,
    "gn:feature_class":"P",
    "gn:feature_code":"PPL",
    "gn:name":"Phum Sr\u00e2nal",
    "gn:population":0,
    "gn:timezone":"Asia/Phnom_Penh",
    "iso:country":"KH",
    "name:khm_x_preferred":[
        "Phum Sr\u00e2nal"
    ],
    "name:khm_x_variant":[
        "\u1797\u17bc\u1798\u17b7 \u179f\u17d2\u179a\u178e\u17b6\u179b"
    ],
    "name:und_x_variant":[
        "Phum\u012d Sr\u00e2nal"
    ],
    "wof:name":"Phum Sranal",
    "wof:placetype":"locality"
},
  "geometry": {"coordinates":[103.17658,13.43128],"type":"Point"}
}