{
  "type": "Feature",
  "properties": {
    "gn:admin1_code":"04",
    "gn:asciiname":"Phumi Kampong Tram",
    "gn:country_code":"KH",
    "gn:dem":24,
    "gn:feature_class":"P",
    "gn:feature_code":"PPL",
    "gn:name":"Phum\u012d K\u00e2mp\u00f3ng Tr\u0103m",
    "gn:population":0,
    "gn:timezone":"Asia/Phnom_Penh",
    "iso:country":"KH",
    "name:und_x_variant":[
        "Kompong Tram",
        "Phum\u012d K\u00e2mp\u00f3ng Tr\u0103m"
    ],
    "wof:name":"Phumi Kampong Tram",
    "wof:placetype":"locality"
},
  "geometry": {"coordinates":[104.65683,11.44359],"type":"Point"}
}