{
  "type": "Feature",
  "properties": {
    "gn:admin1_code":"07",
    "gn:asciiname":"Phumi Prek Ta Kong",
    "gn:country_code":"KH",
    "gn:dem":15,
    "gn:feature_class":"P",
    "gn:feature_code":"PPL",
    "gn:name":"Phum\u012d Pr\u00eak Ta K\u00f3ng",
    "gn:population":0,
    "gn:timezone":"Asia/Phnom_Penh",
    "iso:country":"KH",
    "name:und_x_variant":[
        "Pr\u00eak Takong",
        "Phum\u012d Pr\u00eak Ta K\u016dng",
        "Phum\u012d Pr\u00eak Ta K\u00f3ng"
    ],
    "wof:name":"Phumi Prek Ta Kong",
    "wof:placetype":"locality"
},
  "geometry": {"coordinates":[105.02358,11.76466],"type":"Point"}
}