{
  "type": "Feature",
  "properties": {
    "gn:admin1_code":"12",
    "gn:asciiname":"Phum Kleng Puos",
    "gn:country_code":"KH",
    "gn:dem":18,
    "gn:feature_class":"P",
    "gn:feature_code":"PPL",
    "gn:name":"Phum Kl\u00eang Pu\u014fs",
    "gn:population":0,
    "gn:timezone":"Asia/Phnom_Penh",
    "iso:country":"KH",
    "name:khm_x_preferred":[
        "Phum Kl\u00eang Pu\u014fs"
    ],
    "name:khm_x_variant":[
        "\u1797\u17bc\u1798\u17b7 \u1780\u17d2\u179b\u1784\u1796\u179f\u17cb"
    ],
    "name:und_x_variant":[
        "P\u2019um Prei Kpo",
        "Phum\u012d Kl\u00eang Pu\u014fs",
        "Phum\u012d Kl\u00eang P\u00f3s"
    ],
    "wof:name":"Phum Kleng Puos",
    "wof:placetype":"locality"
},
  "geometry": {"coordinates":[103.85898,12.60114],"type":"Point"}
}