{
  "type": "Feature",
  "properties": {
    "gn:admin1_code":"22",
    "gn:asciiname":"Sak Sampov",
    "gn:country_code":"KH",
    "gn:dem":16,
    "gn:feature_class":"P",
    "gn:feature_code":"PPL",
    "gn:name":"Sak Sampov",
    "gn:population":0,
    "gn:timezone":"Asia/Phnom_Penh",
    "iso:country":"KH",
    "name:khm_x_preferred":[
        "Sak Sampov"
    ],
    "wof:name":"Sak Sampov",
    "wof:placetype":"locality"
},
  "geometry": {"coordinates":[104.85942,11.45777],"type":"Point"}
}