{
  "type": "Feature",
  "properties": {
    "gn:admin1_code":"9.0",
    "gn:asciiname":"Khnach",
    "gn:country_code":"KH",
    "gn:dem":49,
    "gn:feature_class":"P",
    "gn:feature_code":"PPL",
    "gn:name":"Khnach",
    "gn:population":0,
    "gn:timezone":"Asia/Phnom_Penh",
    "iso:country":"KH",
    "name:khm_x_preferred":[
        "Khnach"
    ],
    "name:khm_x_variant":[
        "Phum Khnach Toch",
        "\u1797\u17bc\u1798\u17b7 \u1781\u17d2\u1793\u17b6\u1785\u178f\u17bc\u1785"
    ],
    "wof:name":"Khnach",
    "wof:placetype":"locality"
},
  "geometry": {"coordinates":[106.23075,12.51074],"type":"Point"}
}