{
  "type": "Feature",
  "properties": {
    "gn:admin1_code":"12",
    "gn:asciiname":"Phum O Spean",
    "gn:country_code":"KH",
    "gn:dem":47,
    "gn:feature_class":"P",
    "gn:feature_code":"PPL",
    "gn:name":"Phum O Sp\u00e9an",
    "gn:population":0,
    "gn:timezone":"Asia/Phnom_Penh",
    "iso:country":"KH",
    "name:khm_x_preferred":[
        "Phum O Sp\u00e9an"
    ],
    "name:khm_x_variant":[
        "\u1797\u17bc\u1798\u17b7 \u17a2\u17bc\u179a\u179f\u17d2\u1796\u17b6\u1793"
    ],
    "name:und_x_variant":[
        "Phum\u012d O Sp\u00e9an"
    ],
    "wof:name":"Phum O Spean",
    "wof:placetype":"locality"
},
  "geometry": {"coordinates":[104.10566,12.37223],"type":"Point"}
}