{
  "type": "Feature",
  "properties": {
    "gn:admin1_code":"17.0",
    "gn:asciiname":"Chrab",
    "gn:country_code":"KH",
    "gn:dem":108,
    "gn:feature_class":"P",
    "gn:feature_code":"PPL",
    "gn:name":"Chrab",
    "gn:population":0,
    "gn:timezone":"Asia/Phnom_Penh",
    "iso:country":"KH",
    "name:khm_x_preferred":[
        "Chrab"
    ],
    "name:khm_x_variant":[
        "\u1797\u17bc\u1798\u17b7 \u1785\u17d2\u179a\u1794",
        "Phum Chr\u00e2p"
    ],
    "wof:name":"Chrab",
    "wof:placetype":"locality"
},
  "geometry": {"coordinates":[106.26554,13.41634],"type":"Point"}
}