{
  "type": "Feature",
  "properties": {
    "gn:admin1_code":"25",
    "gn:asciiname":"Thmei",
    "gn:country_code":"KH",
    "gn:dem":52,
    "gn:feature_class":"P",
    "gn:feature_code":"PPL",
    "gn:name":"Thmei",
    "gn:population":0,
    "gn:timezone":"Asia/Phnom_Penh",
    "iso:country":"KH",
    "name:khm_x_preferred":[
        "Thmei"
    ],
    "name:und_x_variant":[
        "Phum\u012d Thmei"
    ],
    "wof:name":"Thmei",
    "wof:placetype":"locality"
},
  "geometry": {"coordinates":[102.96861,13.99754],"type":"Point"}
}