{
  "type": "Feature",
  "properties": {
    "gn:admin1_code":"24",
    "gn:asciiname":"Kouk Doung",
    "gn:country_code":"KH",
    "gn:dem":42,
    "gn:feature_class":"P",
    "gn:feature_code":"PPL",
    "gn:name":"Kouk Doung",
    "gn:population":0,
    "gn:timezone":"Asia/Phnom_Penh",
    "iso:country":"KH",
    "name:khm_x_preferred":[
        "Kouk Doung"
    ],
    "name:khm_x_variant":[
        "\u1797\u17bc\u1798\u17b7 \u1782\u17c4\u1780\u178a\u17bc\u1784",
        "Phum\u012d Ko\u016dk Dong",
        "Phum Ko\u016dk Dong"
    ],
    "wof:name":"Kouk Doung",
    "wof:placetype":"locality"
},
  "geometry": {"coordinates":[103.76644,13.67635],"type":"Point"}
}