{
  "type": "Feature",
  "properties": {
    "gn:admin1_code":"29",
    "gn:asciiname":"Tuol Ta Aek",
    "gn:country_code":"KH",
    "gn:dem":17,
    "gn:feature_class":"P",
    "gn:feature_code":"PPL",
    "gn:name":"Tuol Ta Aek",
    "gn:population":0,
    "gn:timezone":"Asia/Phnom_Penh",
    "iso:country":"KH",
    "name:khm_x_preferred":[
        "Tuol Ta Aek"
    ],
    "name:khm_x_variant":[
        "Phum\u012d D\u00e2ngka\u00f4 T\u00e9ap",
        "\u1797\u17bc\u1798\u17b7 \u178a\u1784\u17d2\u1780\u17c4 \u1791\u17b6\u1794"
    ],
    "wof:name":"Tuol Ta Aek",
    "wof:placetype":"locality"
},
  "geometry": {"coordinates":[103.1872,13.08465],"type":"Point"}
}