{
  "type": "Feature",
  "properties": {
    "gn:admin1_code":"12",
    "gn:asciiname":"Phumi Sre Dang",
    "gn:country_code":"KH",
    "gn:dem":30,
    "gn:feature_class":"P",
    "gn:feature_code":"PPL",
    "gn:name":"Phum\u012d Sr\u00ea D\u00e2ng",
    "gn:population":0,
    "gn:timezone":"Asia/Phnom_Penh",
    "iso:country":"KH",
    "name:und_x_variant":[
        "Sre Chong",
        "Phum\u012d Sr\u00ea D\u00e2ng"
    ],
    "wof:name":"Phumi Sre Dang",
    "wof:placetype":"locality"
},
  "geometry": {"coordinates":[103.76882000000001,12.42433],"type":"Point"}
}