{
  "type": "Feature",
  "properties": {
    "gn:admin1_code":"14",
    "gn:asciiname":"Prey Moan",
    "gn:country_code":"KH",
    "gn:dem":8,
    "gn:feature_class":"P",
    "gn:feature_code":"PPL",
    "gn:name":"Prey Moan",
    "gn:population":0,
    "gn:timezone":"Asia/Phnom_Penh",
    "iso:country":"KH",
    "name:khm_x_preferred":[
        "Prey Moan"
    ],
    "wof:name":"Prey Moan",
    "wof:placetype":"locality"
},
  "geometry": {"coordinates":[105.31717,10.99616],"type":"Point"}
}