{
  "type": "Feature",
  "properties": {
    "gn:admin1_code":"05",
    "gn:asciiname":"Phumi Pring",
    "gn:country_code":"KH",
    "gn:dem":58,
    "gn:feature_class":"P",
    "gn:feature_code":"PPL",
    "gn:name":"Phum\u012d Pring",
    "gn:population":0,
    "gn:timezone":"Asia/Phnom_Penh",
    "iso:country":"KH",
    "wof:name":"Phumi Pring",
    "wof:placetype":"locality"
},
  "geometry": {"coordinates":[105.07816,13.58105],"type":"Point"}
}