{
  "type": "Feature",
  "properties": {
    "gn:admin1_code":"13",
    "gn:asciiname":"Pou Teab",
    "gn:country_code":"KH",
    "gn:dem":78,
    "gn:feature_class":"P",
    "gn:feature_code":"PPL",
    "gn:name":"Pou Teab",
    "gn:population":0,
    "gn:timezone":"Asia/Phnom_Penh",
    "iso:country":"KH",
    "name:khm_x_preferred":[
        "Pou Teab"
    ],
    "name:und_x_variant":[
        "Poteap",
        "Phum\u012d Po\u016d T\u00e9ap",
        "Phum\u012d Po\u016dth\u012d T\u00e9ab"
    ],
    "wof:name":"Pou Teab",
    "wof:placetype":"locality"
},
  "geometry": {"coordinates":[105.24766,13.82543],"type":"Point"}
}