{
  "type": "Feature",
  "properties": {
    "gn:admin1_code":"19",
    "gn:asciiname":"Phumi Kramum Chang",
    "gn:country_code":"KH",
    "gn:dem":7,
    "gn:feature_class":"P",
    "gn:feature_code":"PPL",
    "gn:name":"Phum\u012d Kr\u00e2m\u016dm Ch\u00e1ng",
    "gn:population":0,
    "gn:timezone":"Asia/Phnom_Penh",
    "iso:country":"KH",
    "name:und_x_variant":[
        "Phum Kramon Chang",
        "Phum\u012d Kr\u00e2mom Ch\u00e2ng (2)",
        "Phum\u012d Kr\u00e2m\u016dm Ch\u00e1ng"
    ],
    "wof:name":"Phumi Kramum Chang",
    "wof:placetype":"locality"
},
  "geometry": {"coordinates":[104.9277,11.09144],"type":"Point"}
}