{
  "type": "Feature",
  "properties": {
    "gn:admin1_code":"25",
    "gn:asciiname":"Nam Tau",
    "gn:country_code":"KH",
    "gn:dem":25,
    "gn:feature_class":"P",
    "gn:feature_code":"PPL",
    "gn:name":"Nam Tau",
    "gn:population":0,
    "gn:timezone":"Asia/Phnom_Penh",
    "iso:country":"KH",
    "name:ceb_x_preferred":[
        "Nam Tau"
    ],
    "name:khm_x_preferred":[
        "\u1797\u17bc\u1798\u17b7 \u178e\u17b6\u17c6\u178f\u17c5"
    ],
    "name:khm_x_variant":[
        "Phum N\u0103m Tau"
    ],
    "name:swe_x_preferred":[
        "Nam Tau"
    ],
    "name:und_x_variant":[
        "Phum\u012d N\u0103m Tau"
    ],
    "wof:name":"Nam Tau",
    "wof:placetype":"locality"
},
  "geometry": {"coordinates":[103.39919999999999,13.8447],"type":"Point"}
}