{
  "type": "Feature",
  "properties": {
    "gn:admin1_code":"08",
    "gn:asciiname":"Thma Sar",
    "gn:country_code":"KH",
    "gn:dem":24,
    "gn:feature_class":"P",
    "gn:feature_code":"PPL",
    "gn:name":"Thma Sar",
    "gn:population":0,
    "gn:timezone":"Asia/Phnom_Penh",
    "iso:country":"KH",
    "name:khm_x_preferred":[
        "Thma Sar"
    ],
    "name:khm_x_variant":[
        "\u1797\u17bc\u1798\u17b7 \u1790\u17d2\u1798\u179f\u179a \u1798\u17bd\u1799",
        "Phum Thm\u00e2 S\u00e2"
    ],
    "name:und_x_variant":[
        "Che Ko",
        "Phum Cheko",
        "Chamlang Ko",
        "Phum\u012d Thm\u00e2 S\u00e2",
        "Thmar Sur",
        "Phum\u012d Thm\u00e2 S\u00e2r"
    ],
    "wof:name":"Thma Sar",
    "wof:placetype":"locality"
},
  "geometry": {"coordinates":[103.4066,10.89601],"type":"Point"}
}