{
  "type": "Feature",
  "properties": {
    "gn:admin1_code":"31.0",
    "gn:asciiname":"Phum Kaoh Krabei",
    "gn:country_code":"KH",
    "gn:dem":26,
    "gn:feature_class":"P",
    "gn:feature_code":"PPL",
    "gn:name":"Phum Ka\u00f4h Kr\u00e2bei",
    "gn:population":0,
    "gn:timezone":"Asia/Phnom_Penh",
    "iso:country":"KH",
    "name:khm_x_preferred":[
        "Phum Ka\u00f4h Kr\u00e2bei"
    ],
    "name:khm_x_variant":[
        "\u1797\u17bc\u1798\u17b7 \u1780\u17c4\u17c7\u1780\u17d2\u179a\u1794\u17b8"
    ],
    "wof:name":"Phum Kaoh Krabei",
    "wof:placetype":"locality"
},
  "geometry": {"coordinates":[105.54557,12.15789],"type":"Point"}
}