{
  "type": "Feature",
  "properties": {
    "gn:admin1_code":"29",
    "gn:asciiname":"Phum Damnak Kathen",
    "gn:country_code":"KH",
    "gn:dem":15,
    "gn:feature_class":"P",
    "gn:feature_code":"PPL",
    "gn:name":"Phum D\u00e2mn\u0103k K\u00e2th\u0115n",
    "gn:population":0,
    "gn:timezone":"Asia/Phnom_Penh",
    "iso:country":"KH",
    "name:khm_x_preferred":[
        "Phum D\u00e2mn\u0103k K\u00e2th\u0115n"
    ],
    "name:khm_x_variant":[
        "\u1797\u17bc\u1798\u17b7 \u178a\u17c6\u17c6\u178e\u17b6\u1780\u17cb\u1780\u1790\u17b7\u1793"
    ],
    "name:und_x_variant":[
        "Phum\u012d D\u00e2mn\u0103k K\u00e2th\u0115n"
    ],
    "wof:name":"Phum Damnak Kathen",
    "wof:placetype":"locality"
},
  "geometry": {"coordinates":[103.43521,12.85132],"type":"Point"}
}