{
  "type": "Feature",
  "properties": {
    "gn:admin1_code":"29",
    "gn:asciiname":"Phum Ra",
    "gn:country_code":"KH",
    "gn:dem":20,
    "gn:feature_class":"P",
    "gn:feature_code":"PPL",
    "gn:name":"Phum Ra",
    "gn:population":0,
    "gn:timezone":"Asia/Phnom_Penh",
    "iso:country":"KH",
    "name:khm_x_preferred":[
        "Phum Ra"
    ],
    "name:khm_x_variant":[
        "\u1797\u17bc\u1798\u17b7 \u179a\u17b6"
    ],
    "wof:name":"Phum Ra",
    "wof:placetype":"locality"
},
  "geometry": {"coordinates":[103.43777,12.76472],"type":"Point"}
}