{
  "type": "Feature",
  "properties": {
    "gn:admin1_code":"12",
    "gn:asciiname":"Rung",
    "gn:country_code":"KH",
    "gn:dem":17,
    "gn:feature_class":"P",
    "gn:feature_code":"PPL",
    "gn:name":"Rung",
    "gn:population":0,
    "gn:timezone":"Asia/Phnom_Penh",
    "iso:country":"KH",
    "name:deu_x_preferred":[
        "Rung"
    ],
    "name:khm_x_preferred":[
        "Rung"
    ],
    "name:swe_x_preferred":[
        "Rung"
    ],
    "name:und_x_variant":[
        "P\u2019um Rung",
        "Phum\u012d Rung"
    ],
    "wof:name":"Rung",
    "wof:placetype":"locality"
},
  "geometry": {"coordinates":[103.71684,12.67206],"type":"Point"}
}