{
  "type": "Feature",
  "properties": {
    "gn:admin1_code":"18",
    "gn:asciiname":"Phumi Prey Stieng",
    "gn:country_code":"KH",
    "gn:dem":7,
    "gn:feature_class":"P",
    "gn:feature_code":"PPL",
    "gn:name":"Phum\u012d Prey Sti\u0115ng",
    "gn:population":0,
    "gn:timezone":"Asia/Phnom_Penh",
    "iso:country":"KH",
    "name:und_x_variant":[
        "Prey St\u00e9ang",
        "Phum\u012d Prey Sti\u0115ng"
    ],
    "wof:name":"Phumi Prey Stieng",
    "wof:placetype":"locality"
},
  "geometry": {"coordinates":[105.96792000000001,11.00811],"type":"Point"}
}