{
  "type": "Feature",
  "properties": {
    "gn:admin1_code":"18.0",
    "gn:asciiname":"Bat Sloek",
    "gn:country_code":"KH",
    "gn:dem":5,
    "gn:feature_class":"P",
    "gn:feature_code":"PPL",
    "gn:name":"Bat Sloek",
    "gn:population":0,
    "gn:timezone":"Asia/Phnom_Penh",
    "iso:country":"KH",
    "name:khm_x_preferred":[
        "Bat Sloek"
    ],
    "name:khm_x_variant":[
        "\u1797\u17bc\u1798\u17b7 \u1798\u178f\u179f\u17d2\u179b\u17b9\u1780",
        "Phum B\u00e2t Sloek"
    ],
    "wof:name":"Bat Sloek",
    "wof:placetype":"locality"
},
  "geometry": {"coordinates":[106.06962,11.06415],"type":"Point"}
}