{
  "type": "Feature",
  "properties": {
    "gn:admin1_code":"18",
    "gn:asciiname":"Phumi Toear",
    "gn:country_code":"KH",
    "gn:dem":5,
    "gn:feature_class":"P",
    "gn:feature_code":"PPL",
    "gn:name":"Phum\u012d T\u0153\u0103r",
    "gn:population":0,
    "gn:timezone":"Asia/Phnom_Penh",
    "iso:country":"KH",
    "wof:name":"Phumi Toear",
    "wof:placetype":"locality"
},
  "geometry": {"coordinates":[105.86667,11.06667],"type":"Point"}
}