{
  "type": "Feature",
  "properties": {
    "gn:admin1_code":"07",
    "gn:asciiname":"Roka Kaong Pi",
    "gn:country_code":"KH",
    "gn:dem":15,
    "gn:feature_class":"P",
    "gn:feature_code":"PPL",
    "gn:name":"Roka Kaong Pi",
    "gn:population":0,
    "gn:timezone":"Asia/Phnom_Penh",
    "iso:country":"KH",
    "name:khm_x_preferred":[
        "Roka Kaong Pi"
    ],
    "wof:name":"Roka Kaong Pi",
    "wof:placetype":"locality"
},
  "geometry": {"coordinates":[104.9776,11.84142],"type":"Point"}
}