{
  "type": "Feature",
  "properties": {
    "gn:admin1_code":"12",
    "gn:asciiname":"Boeng Kantuot",
    "gn:country_code":"KH",
    "gn:dem":23,
    "gn:feature_class":"P",
    "gn:feature_code":"PPL",
    "gn:name":"Boeng Kantuot",
    "gn:population":0,
    "gn:timezone":"Asia/Phnom_Penh",
    "iso:country":"KH",
    "name:und_x_variant":[
        "Sala Kh\u016dm B\u0153\u0306ng K\u00e2ntu\u014ft"
    ],
    "wof:name":"Boeng Kantuot",
    "wof:placetype":"locality"
},
  "geometry": {"coordinates":[104.05784,12.53393],"type":"Point"}
}