{
  "type": "Feature",
  "properties": {
    "gn:admin1_code":"23.0",
    "gn:asciiname":"Aekapheap",
    "gn:country_code":"KH",
    "gn:dem":342,
    "gn:feature_class":"P",
    "gn:feature_code":"PPL",
    "gn:name":"Aekapheap",
    "gn:population":0,
    "gn:timezone":"Asia/Phnom_Penh",
    "iso:country":"KH",
    "name:khm_x_preferred":[
        "Aekapheap"
    ],
    "wof:name":"Aekapheap",
    "wof:placetype":"locality"
},
  "geometry": {"coordinates":[107.09608,13.74807],"type":"Point"}
}