{
  "type": "Feature",
  "properties": {
    "gn:admin1_code":"14",
    "gn:asciiname":"Krang Veaeng",
    "gn:country_code":"KH",
    "gn:dem":11,
    "gn:feature_class":"P",
    "gn:feature_code":"PPL",
    "gn:name":"Krang Veaeng",
    "gn:population":0,
    "gn:timezone":"Asia/Phnom_Penh",
    "iso:country":"KH",
    "name:khm_x_preferred":[
        "Krang Veaeng"
    ],
    "name:und_x_variant":[
        "Phum\u012d Kr\u0103ng V\u00eang"
    ],
    "wof:name":"Krang Veaeng",
    "wof:placetype":"locality"
},
  "geometry": {"coordinates":[105.52500999999999,10.99685],"type":"Point"}
}