{
  "type": "Feature",
  "properties": {
    "gn:admin1_code":"03",
    "gn:asciiname":"Tuk Chenh",
    "gn:country_code":"KH",
    "gn:dem":32,
    "gn:feature_class":"P",
    "gn:feature_code":"PPL",
    "gn:name":"Tuk Chenh",
    "gn:population":0,
    "gn:timezone":"Asia/Phnom_Penh",
    "iso:country":"KH",
    "name:und_x_variant":[
        "Phum\u012d T\u0153\u0306k Ch\u00e9nh"
    ],
    "wof:name":"Tuk Chenh",
    "wof:placetype":"locality"
},
  "geometry": {"coordinates":[104.62833000000001,12.13613],"type":"Point"}
}