{
  "type": "Feature",
  "properties": {
    "gn:admin1_code":"29",
    "gn:asciiname":"Phum Treas",
    "gn:country_code":"KH",
    "gn:dem":17,
    "gn:feature_class":"P",
    "gn:feature_code":"PPL",
    "gn:name":"Phum Tr\u00e9as",
    "gn:population":0,
    "gn:timezone":"Asia/Phnom_Penh",
    "iso:country":"KH",
    "name:khm_x_preferred":[
        "Phum Tr\u00e9as"
    ],
    "name:khm_x_variant":[
        "\u1797\u17bc\u1798\u17b7 \u1791\u17d2\u179a\u17b6\u179f"
    ],
    "wof:name":"Phum Treas",
    "wof:placetype":"locality"
},
  "geometry": {"coordinates":[103.22526000000001,13.13016],"type":"Point"}
}