{
  "type": "Feature",
  "properties": {
    "gn:admin1_code":"05",
    "gn:asciiname":"Trapeang Pring",
    "gn:country_code":"KH",
    "gn:dem":47,
    "gn:feature_class":"P",
    "gn:feature_code":"PPL",
    "gn:name":"Trapeang Pring",
    "gn:population":0,
    "gn:timezone":"Asia/Phnom_Penh",
    "iso:country":"KH",
    "name:khm_x_preferred":[
        "Trapeang Pring"
    ],
    "wof:name":"Trapeang Pring",
    "wof:placetype":"locality"
},
  "geometry": {"coordinates":[104.7769,13.27974],"type":"Point"}
}