{
  "type": "Feature",
  "properties": {
    "iso:country":"KH",
    "qs:gn_pop":0,
    "qs:name":"Phumi Snuol",
    "qs:name_adm0":"Cambodia",
    "qs:name_adm1":"Krachen",
    "qs:photos":7,
    "qs:photos_1k":1,
    "qs:photos_9k":1,
    "qs:photos_9r":1,
    "qs:photos_all":7,
    "qs:photos_sr":1,
    "qs:placetype":"Town",
    "qs:pop_sr":"0",
    "qs:woe_adm0":23424776,
    "wof:name":"Phumi Snuol",
    "wof:placetype":"locality"
},
  "geometry": {"coordinates":[106.421333,12.07035],"type":"Point"}
}