{
  "type": "Feature",
  "properties": {
    "gn:admin1_code":"13",
    "gn:asciiname":"Kampong Pou",
    "gn:country_code":"KH",
    "gn:dem":90,
    "gn:feature_class":"P",
    "gn:feature_code":"PPL",
    "gn:name":"Kampong Pou",
    "gn:population":0,
    "gn:timezone":"Asia/Phnom_Penh",
    "iso:country":"KH",
    "name:khm_x_preferred":[
        "Kampong Pou"
    ],
    "name:khm_x_variant":[
        "\u1797\u17bc\u1798\u17b7 \u1780\u17c6\u1796\u1784\u17cb\u1796\u17c4\u1792\u17b7"
    ],
    "name:und_x_variant":[
        "Ban Tapau",
        "Phum\u012d K\u00e2mp\u00f4ng Po\u016d",
        "Phum\u012d K\u00e2mp\u00f3ng Po\u016dth\u012d"
    ],
    "wof:name":"Kampong Pou",
    "wof:placetype":"locality"
},
  "geometry": {"coordinates":[105.7818,14.06848],"type":"Point"}
}