{
  "type": "Feature",
  "properties": {
    "gn:admin1_code":"23",
    "gn:asciiname":"Saom Trak",
    "gn:country_code":"KH",
    "gn:dem":226,
    "gn:feature_class":"P",
    "gn:feature_code":"PPL",
    "gn:name":"Saom Trak",
    "gn:population":0,
    "gn:timezone":"Asia/Phnom_Penh",
    "iso:country":"KH",
    "name:khm_x_preferred":[
        "Saom Trak"
    ],
    "name:und_x_variant":[
        "Phum\u012d Cham To\u0103l"
    ],
    "wof:name":"Saom Trak",
    "wof:placetype":"locality"
},
  "geometry": {"coordinates":[107.40606,13.70917],"type":"Point"}
}