{
  "type": "Feature",
  "properties": {
    "gn:admin1_code":"03",
    "gn:asciiname":"Phumi Kaoh Thum",
    "gn:country_code":"KH",
    "gn:dem":11,
    "gn:feature_class":"P",
    "gn:feature_code":"PPL",
    "gn:name":"Phum\u012d Ka\u00f4h Thum",
    "gn:population":0,
    "gn:timezone":"Asia/Phnom_Penh",
    "iso:country":"KH",
    "name:und_x_variant":[
        "Phum Trop",
        "Phum\u012d Ka\u00f4h Thom",
        "Phum Prek Trap",
        "Phum\u012d Ka\u00f4h Thum"
    ],
    "wof:name":"Phumi Kaoh Thum",
    "wof:placetype":"locality"
},
  "geometry": {"coordinates":[104.86286,12.14729],"type":"Point"}
}