{
  "type": "Feature",
  "properties": {
    "gn:admin1_code":"24.0",
    "gn:asciiname":"Trach Chrum",
    "gn:country_code":"KH",
    "gn:dem":27,
    "gn:feature_class":"P",
    "gn:feature_code":"PPL",
    "gn:name":"Trach Chrum",
    "gn:population":0,
    "gn:timezone":"Asia/Phnom_Penh",
    "iso:country":"KH",
    "name:khm_x_preferred":[
        "Trach Chrum"
    ],
    "name:khm_x_variant":[
        "Phum K\u00e2nt\u016dp Yan",
        "\u1797\u17bc\u1798\u17b7 \u1780\u1793\u17d2\u1791\u1794\u17cb\u1799\u17c9\u1784"
    ],
    "wof:name":"Trach Chrum",
    "wof:placetype":"locality"
},
  "geometry": {"coordinates":[103.93192999999999,13.41361],"type":"Point"}
}