{
  "type": "Feature",
  "properties": {
    "gn:admin1_code":"24",
    "gn:asciiname":"Trach",
    "gn:country_code":"KH",
    "gn:dem":28,
    "gn:feature_class":"P",
    "gn:feature_code":"PPL",
    "gn:name":"Trach",
    "gn:population":0,
    "gn:timezone":"Asia/Phnom_Penh",
    "iso:country":"KH",
    "name:khm_x_preferred":[
        "Trach"
    ],
    "name:khm_x_variant":[
        "\u1797\u17bc\u1798\u17b7 \u178f\u17d2\u179a\u17b6\u1785",
        "Phum Trach"
    ],
    "name:und_x_variant":[
        "Phum\u012d Trach"
    ],
    "wof:name":"Trach",
    "wof:placetype":"locality"
},
  "geometry": {"coordinates":[104.0097,13.41716],"type":"Point"}
}