{
  "type": "Feature",
  "properties": {
    "gn:admin1_code":"24",
    "gn:asciiname":"Ta Pang",
    "gn:country_code":"KH",
    "gn:dem":25,
    "gn:feature_class":"P",
    "gn:feature_code":"PPL",
    "gn:name":"Ta Pang",
    "gn:population":0,
    "gn:timezone":"Asia/Phnom_Penh",
    "iso:country":"KH",
    "name:khm_x_preferred":[
        "Ta Pang"
    ],
    "name:khm_x_variant":[
        "\u1797\u17bc\u1798\u17b7 \u178f\u17b6\u1794\u17c9\u17b6\u1784",
        "Phum Tapang"
    ],
    "name:und_x_variant":[
        "Ta Paing",
        "Phum\u012d Tapang"
    ],
    "wof:name":"Ta Pang",
    "wof:placetype":"locality"
},
  "geometry": {"coordinates":[103.62025,13.61009],"type":"Point"}
}