{
  "type": "Feature",
  "properties": {
    "gn:admin1_code":"22",
    "gn:asciiname":"Stueng Mean Chey",
    "gn:country_code":"KH",
    "gn:dem":13,
    "gn:feature_class":"P",
    "gn:feature_code":"PPL",
    "gn:name":"Stueng Mean Chey",
    "gn:population":0,
    "gn:timezone":"Asia/Phnom_Penh",
    "iso:country":"KH",
    "name:khm_x_preferred":[
        "Stueng Mean Chey"
    ],
    "name:und_x_variant":[
        "St\u0153\u0306ng M\u00e9an Che\u0103y",
        "Stung-Meanchey",
        "Stung Mean Chei",
        "Phum Stung Mean Chey",
        "St\u0153\u0306ng M\u00e9an Chey"
    ],
    "wof:name":"Stueng Mean Chey",
    "wof:placetype":"locality"
},
  "geometry": {"coordinates":[104.89413999999999,11.54341],"type":"Point"}
}