{
  "type": "Feature",
  "properties": {
    "gn:admin1_code":"02",
    "gn:asciiname":"Moha Khnhoung",
    "gn:country_code":"KH",
    "gn:dem":18,
    "gn:feature_class":"P",
    "gn:feature_code":"PPL",
    "gn:name":"Moha Khnhoung",
    "gn:population":0,
    "gn:timezone":"Asia/Phnom_Penh",
    "iso:country":"KH",
    "name:khm_x_preferred":[
        "Moha Khnhoung"
    ],
    "name:und_x_variant":[
        "Phum Khnhuong",
        "Phum\u012d Khnhung"
    ],
    "wof:name":"Moha Khnhoung",
    "wof:placetype":"locality"
},
  "geometry": {"coordinates":[105.32544,11.92758],"type":"Point"}
}