{
  "type": "Feature",
  "properties": {
    "gn:admin1_code":"24.0",
    "gn:asciiname":"Trapeang Phong",
    "gn:country_code":"KH",
    "gn:dem":48,
    "gn:feature_class":"P",
    "gn:feature_code":"PPL",
    "gn:name":"Trapeang Phong",
    "gn:population":0,
    "gn:timezone":"Asia/Phnom_Penh",
    "iso:country":"KH",
    "name:khm_x_preferred":[
        "Trapeang Phong"
    ],
    "wof:name":"Trapeang Phong",
    "wof:placetype":"locality"
},
  "geometry": {"coordinates":[104.15737,13.41145],"type":"Point"}
}