{
  "type": "Feature",
  "properties": {
    "gn:admin1_code":"08",
    "gn:asciiname":"Chheu Neang",
    "gn:country_code":"KH",
    "gn:dem":22,
    "gn:feature_class":"P",
    "gn:feature_code":"PPL",
    "gn:name":"Chheu Neang",
    "gn:population":0,
    "gn:timezone":"Asia/Phnom_Penh",
    "iso:country":"KH",
    "name:khm_x_preferred":[
        "Chheu Neang"
    ],
    "name:und_x_variant":[
        "Phum\u012d Chheu N\u00e9ang"
    ],
    "wof:name":"Chheu Neang",
    "wof:placetype":"locality"
},
  "geometry": {"coordinates":[103.733,11.05914],"type":"Point"}
}