{
  "type": "Feature",
  "properties": {
    "gn:admin1_code":"23.0",
    "gn:asciiname":"Pralai",
    "gn:country_code":"KH",
    "gn:dem":228,
    "gn:feature_class":"P",
    "gn:feature_code":"PPL",
    "gn:name":"Pralai",
    "gn:population":0,
    "gn:timezone":"Asia/Phnom_Penh",
    "iso:country":"KH",
    "name:khm_x_preferred":[
        "Pralai"
    ],
    "wof:name":"Pralai",
    "wof:placetype":"locality"
},
  "geometry": {"coordinates":[107.33152,13.71347],"type":"Point"}
}