{
  "type": "Feature",
  "properties": {
    "gn:admin1_code":"19",
    "gn:asciiname":"Tara Kom",
    "gn:country_code":"KH",
    "gn:dem":6,
    "gn:feature_class":"P",
    "gn:feature_code":"PPL",
    "gn:name":"Tara Kom",
    "gn:population":0,
    "gn:timezone":"Asia/Phnom_Penh",
    "iso:country":"KH",
    "name:khm_x_preferred":[
        "Tara Kom"
    ],
    "wof:name":"Tara Kom",
    "wof:placetype":"locality"
},
  "geometry": {"coordinates":[104.99616,10.69267],"type":"Point"}
}