{
  "type": "Feature",
  "properties": {
    "gn:admin1_code":"09",
    "gn:asciiname":"Phumi Chas Pak",
    "gn:country_code":"KH",
    "gn:dem":23,
    "gn:feature_class":"P",
    "gn:feature_code":"PPL",
    "gn:name":"Phum\u012d Ch\u0103s P\u00e2k",
    "gn:population":0,
    "gn:timezone":"Asia/Phnom_Penh",
    "iso:country":"KH",
    "name:und_x_variant":[
        "Chas Pok",
        "Phum\u012d Chas P\u014fk",
        "Phum\u012d Ch\u0103s P\u00e2k"
    ],
    "wof:name":"Phumi Chas Pak",
    "wof:placetype":"locality"
},
  "geometry": {"coordinates":[105.91494,12.53246],"type":"Point"}
}