{
  "type": "Feature",
  "properties": {
    "gn:admin1_code":"02",
    "gn:asciiname":"Phum Kdey Bera",
    "gn:country_code":"KH",
    "gn:dem":22,
    "gn:feature_class":"P",
    "gn:feature_code":"PPL",
    "gn:name":"Phum Kdey Bera",
    "gn:population":0,
    "gn:timezone":"Asia/Phnom_Penh",
    "iso:country":"KH",
    "name:und_x_variant":[
        "Phum Kdey Beng",
        "Phum Kdey Bera",
        "Phum\u012d Kdei B\u0153\u0306ng"
    ],
    "wof:name":"Phum Kdey Bera",
    "wof:placetype":"locality"
},
  "geometry": {"coordinates":[105.36756,11.99704],"type":"Point"}
}