{
  "type": "Feature",
  "properties": {
    "gn:admin1_code":"19",
    "gn:asciiname":"Phumi Tuol Pongro",
    "gn:country_code":"KH",
    "gn:dem":15,
    "gn:feature_class":"P",
    "gn:feature_code":"PPL",
    "gn:name":"Phum\u012d Tu\u014fl P\u00f4ngr\u00f4",
    "gn:population":0,
    "gn:timezone":"Asia/Phnom_Penh",
    "iso:country":"KH",
    "name:und_x_variant":[
        "Phum Tual Pongro",
        "Phum\u012d Tu\u014fl P\u016dngr\u00f4",
        "Phum\u012d Tu\u014fl P\u00f4ngr\u00f4"
    ],
    "wof:name":"Phumi Tuol Pongro",
    "wof:placetype":"locality"
},
  "geometry": {"coordinates":[104.87721999999999,10.58071],"type":"Point"}
}