{
  "type": "Feature",
  "properties": {
    "gn:admin1_code":"07",
    "gn:asciiname":"Phumi Chong Prek",
    "gn:country_code":"KH",
    "gn:dem":13,
    "gn:feature_class":"P",
    "gn:feature_code":"PPL",
    "gn:name":"Phum\u012d Ch\u014fng Pr\u00eak",
    "gn:population":0,
    "gn:timezone":"Asia/Phnom_Penh",
    "iso:country":"KH",
    "name:und_x_variant":[
        "Chong Pr\u00eak",
        "Phum\u012d Ch\u014fng Pr\u00eak"
    ],
    "wof:name":"Phumi Chong Prek",
    "wof:placetype":"locality"
},
  "geometry": {"coordinates":[104.97386000000002,11.8416],"type":"Point"}
}