{
  "type": "Feature",
  "properties": {
    "gn:admin1_code":"01",
    "gn:asciiname":"Phumi Ta Chan",
    "gn:country_code":"KH",
    "gn:dem":15,
    "gn:feature_class":"P",
    "gn:feature_code":"PPL",
    "gn:name":"Phum\u012d Ta Ch\u0103n",
    "gn:population":0,
    "gn:timezone":"Asia/Phnom_Penh",
    "iso:country":"KH",
    "name:und_x_variant":[
        "P\u2019um Ta Chan",
        "Phum\u012d Ta Ch\u0103n"
    ],
    "wof:name":"Phumi Ta Chan",
    "wof:placetype":"locality"
},
  "geometry": {"coordinates":[103.63514000000001,12.70034],"type":"Point"}
}