{
  "type": "Feature",
  "properties": {
    "gn:admin1_code":"14",
    "gn:asciiname":"Phum Samraong Thom",
    "gn:country_code":"KH",
    "gn:dem":13,
    "gn:feature_class":"P",
    "gn:feature_code":"PPL",
    "gn:name":"Phum S\u00e2mra\u00f4ng Thom",
    "gn:population":0,
    "gn:timezone":"Asia/Phnom_Penh",
    "iso:country":"KH",
    "name:khm_x_preferred":[
        "Phum S\u00e2mra\u00f4ng Thom"
    ],
    "name:khm_x_variant":[
        "\u1797\u17bc\u1798\u17b7 \u179f\u17c6\u179a\u17c4\u1784\u1792\u17c6"
    ],
    "name:und_x_variant":[
        "Phum Samrong Thom",
        "Phum\u012d S\u00e2mra\u00f4ng Thom",
        "Phum\u012d S\u00e2mra\u00f4ng Thum"
    ],
    "wof:name":"Phum Samraong Thom",
    "wof:placetype":"locality"
},
  "geometry": {"coordinates":[105.26322999999999,11.37298],"type":"Point"}
}