{
  "type": "Feature",
  "properties": {
    "gn:admin1_code":"29",
    "gn:asciiname":"Ou Lhong",
    "gn:country_code":"KH",
    "gn:dem":179,
    "gn:feature_class":"P",
    "gn:feature_code":"PPL",
    "gn:name":"Ou Lhong",
    "gn:population":0,
    "gn:timezone":"Asia/Phnom_Penh",
    "iso:country":"KH",
    "name:khm_x_preferred":[
        "Ou Lhong"
    ],
    "wof:name":"Ou Lhong",
    "wof:placetype":"locality"
},
  "geometry": {"coordinates":[102.37971,13.28177],"type":"Point"}
}