{
  "type": "Feature",
  "properties": {
    "gn:admin1_code":"25",
    "gn:asciiname":"Ta Srei",
    "gn:country_code":"KH",
    "gn:dem":27,
    "gn:feature_class":"P",
    "gn:feature_code":"PPL",
    "gn:name":"Ta Srei",
    "gn:population":0,
    "gn:timezone":"Asia/Phnom_Penh",
    "iso:country":"KH",
    "name:khm_x_preferred":[
        "Ta Srei"
    ],
    "name:khm_x_variant":[
        "\u1797\u17bc\u1798\u17b7 \u178f\u17b6\u179f\u17d2\u179a\u17b8",
        "Phum Ta Srei"
    ],
    "wof:name":"Ta Srei",
    "wof:placetype":"locality"
},
  "geometry": {"coordinates":[103.06574999999999,13.75841],"type":"Point"}
}