{
  "type": "Feature",
  "properties": {
    "gn:admin1_code":"07",
    "gn:asciiname":"Ponsang",
    "gn:country_code":"KH",
    "gn:dem":19,
    "gn:feature_class":"P",
    "gn:feature_code":"PPL",
    "gn:name":"Ponsang",
    "gn:population":0,
    "gn:timezone":"Asia/Phnom_Penh",
    "iso:country":"KH",
    "name:khm_x_preferred":[
        "Ponsang"
    ],
    "wof:name":"Ponsang",
    "wof:placetype":"locality"
},
  "geometry": {"coordinates":[104.75944,11.62601],"type":"Point"}
}