{
  "type": "Feature",
  "properties": {
    "gn:admin1_code":"03",
    "gn:asciiname":"Prea Koki",
    "gn:country_code":"KH",
    "gn:dem":12,
    "gn:feature_class":"P",
    "gn:feature_code":"PPL",
    "gn:name":"Prea Koki",
    "gn:population":0,
    "gn:timezone":"Asia/Phnom_Penh",
    "iso:country":"KH",
    "name:und_x_variant":[
        "Phum\u012d St\u0153\u0306ng Chr\u014fu"
    ],
    "wof:name":"Prea Koki",
    "wof:placetype":"locality"
},
  "geometry": {"coordinates":[104.60365,12.36338],"type":"Point"}
}