{
  "type": "Feature",
  "properties": {
    "gn:admin1_code":"18",
    "gn:asciiname":"Prey Damloung",
    "gn:country_code":"KH",
    "gn:dem":8,
    "gn:feature_class":"P",
    "gn:feature_code":"PPL",
    "gn:name":"Prey Damloung",
    "gn:population":0,
    "gn:timezone":"Asia/Phnom_Penh",
    "iso:country":"KH",
    "name:khm_x_preferred":[
        "Prey Damloung"
    ],
    "wof:name":"Prey Damloung",
    "wof:placetype":"locality"
},
  "geometry": {"coordinates":[105.73965,11.1617],"type":"Point"}
}