{
  "type": "Feature",
  "properties": {
    "gn:admin1_code":"18",
    "gn:asciiname":"Ta Suos",
    "gn:country_code":"KH",
    "gn:dem":20,
    "gn:feature_class":"P",
    "gn:feature_code":"PPL",
    "gn:name":"Ta Suos",
    "gn:population":0,
    "gn:timezone":"Asia/Phnom_Penh",
    "iso:country":"KH",
    "name:khm_x_preferred":[
        "Ta Suos"
    ],
    "name:und_x_variant":[
        "Phum\u012d Tasu\u014fs"
    ],
    "wof:name":"Ta Suos",
    "wof:placetype":"locality"
},
  "geometry": {"coordinates":[105.8361,11.53139],"type":"Point"}
}