{
  "type": "Feature",
  "properties": {
    "gn:admin1_code":"29",
    "gn:asciiname":"Phum Veal Poan Talei",
    "gn:country_code":"KH",
    "gn:dem":19,
    "gn:feature_class":"P",
    "gn:feature_code":"PPL",
    "gn:name":"Phum V\u00eaal Po\u00e2n Talei",
    "gn:population":0,
    "gn:timezone":"Asia/Phnom_Penh",
    "iso:country":"KH",
    "name:khm_x_preferred":[
        "Phum V\u00eaal Po\u00e2n Talei"
    ],
    "name:khm_x_variant":[
        "\u1797\u17bc\u1798\u17b7 \u179c\u17b6\u179b\u1796\u17b6\u1793\u17cb\u178f\u17b6\u17a1\u17b8"
    ],
    "name:und_x_variant":[
        "Phum\u012d V\u00e9al Po\u0103n Talei"
    ],
    "wof:name":"Phum Veal Poan Talei",
    "wof:placetype":"locality"
},
  "geometry": {"coordinates":[103.25596,12.89893],"type":"Point"}
}