{
  "type": "Feature",
  "properties": {
    "gn:admin1_code":"22",
    "gn:asciiname":"Preah Ponlea",
    "gn:country_code":"KH",
    "gn:dem":13,
    "gn:feature_class":"P",
    "gn:feature_code":"PPL",
    "gn:name":"Preah Ponlea",
    "gn:population":0,
    "gn:timezone":"Asia/Phnom_Penh",
    "iso:country":"KH",
    "name:khm_x_preferred":[
        "Preah Ponlea"
    ],
    "name:khm_x_variant":[
        "\u1783\u17bb\u17c6\u1796\u17d2\u179a\u17c7\u1796\u1793\u17d2\u179b\u17b6"
    ],
    "name:pol_x_preferred":[
        "Preah Ponlea"
    ],
    "name:und_x_variant":[
        "Phum Pr\u00e9a Banl\u00e9a",
        "Phum Prea Bantea",
        "Phum\u012d Pre\u0103h P\u00f4nl\u00e9a"
    ],
    "wof:name":"Preah Ponlea",
    "wof:placetype":"locality"
},
  "geometry": {"coordinates":[104.9461,11.51613],"type":"Point"}
}