{
  "type": "Feature",
  "properties": {
    "gn:admin1_code":"08",
    "gn:asciiname":"Ta Ngil",
    "gn:country_code":"KH",
    "gn:dem":192,
    "gn:feature_class":"P",
    "gn:feature_code":"PPL",
    "gn:name":"Ta Ngil",
    "gn:population":0,
    "gn:timezone":"Asia/Phnom_Penh",
    "iso:country":"KH",
    "name:khm_x_preferred":[
        "Ta Ngil"
    ],
    "name:und_x_variant":[
        "Phum\u012d Tang\u0115l"
    ],
    "wof:name":"Ta Ngil",
    "wof:placetype":"locality"
},
  "geometry": {"coordinates":[103.61078000000001,11.70937],"type":"Point"}
}