{
  "type": "Feature",
  "properties": {
    "gn:admin1_code":"14",
    "gn:asciiname":"Sou",
    "gn:country_code":"KH",
    "gn:dem":7,
    "gn:feature_class":"P",
    "gn:feature_code":"PPL",
    "gn:name":"Sou",
    "gn:population":0,
    "gn:timezone":"Asia/Phnom_Penh",
    "iso:country":"KH",
    "name:cat_x_preferred":[
        "Sou"
    ],
    "name:ceb_x_preferred":[
        "Sou"
    ],
    "name:fra_x_preferred":[
        "Sou"
    ],
    "name:khm_x_preferred":[
        "Sou"
    ],
    "name:spa_x_preferred":[
        "Sou"
    ],
    "name:swe_x_preferred":[
        "Sou"
    ],
    "wof:name":"Sou",
    "wof:placetype":"locality"
},
  "geometry": {"coordinates":[105.66836000000001,11.26709],"type":"Point"}
}