{
  "type": "Feature",
  "properties": {
    "gn:admin1_code":"10",
    "gn:asciiname":"Phumi Pu Rach Kraom (2)",
    "gn:country_code":"KH",
    "gn:dem":834,
    "gn:feature_class":"P",
    "gn:feature_code":"PPL",
    "gn:name":"Phum\u012d Pu R\u0103ch Kra\u00f4m (2)",
    "gn:population":0,
    "gn:timezone":"Asia/Phnom_Penh",
    "iso:country":"KH",
    "wof:name":"Phumi Pu Rach Kraom (2)",
    "wof:placetype":"locality"
},
  "geometry": {"coordinates":[107.33087,12.35478],"type":"Point"}
}