{
  "type": "Feature",
  "properties": {
    "gn:admin1_code":"29",
    "gn:asciiname":"Ta Haen Pir",
    "gn:country_code":"KH",
    "gn:dem":16,
    "gn:feature_class":"P",
    "gn:feature_code":"PPL",
    "gn:name":"Ta Haen Pir",
    "gn:population":0,
    "gn:timezone":"Asia/Phnom_Penh",
    "iso:country":"KH",
    "name:khm_x_preferred":[
        "Ta Haen Pir"
    ],
    "wof:name":"Ta Haen Pir",
    "wof:placetype":"locality"
},
  "geometry": {"coordinates":[103.285,13.09496],"type":"Point"}
}