{
  "type": "Feature",
  "properties": {
    "gn:admin1_code":"25",
    "gn:asciiname":"Khum Tuek Chour",
    "gn:country_code":"KH",
    "gn:dem":21,
    "gn:feature_class":"P",
    "gn:feature_code":"PPL",
    "gn:name":"Khum Tuek Chour",
    "gn:population":0,
    "gn:timezone":"Asia/Phnom_Penh",
    "iso:country":"KH",
    "name:khm_x_preferred":[
        "Khum Tuek Chour"
    ],
    "name:khm_x_variant":[
        "Phum T\u0153\u0306k Cho\u016d",
        "\u1797\u17bc\u1798\u17b7 \u1791\u17b9\u1780\u1787\u17c4"
    ],
    "name:und_x_variant":[
        "Tukchor",
        "Phumi Tik Cho\u016d",
        "Phum\u012d T\u0153\u0306k Cho\u016d"
    ],
    "wof:name":"Khum Tuek Chour",
    "wof:placetype":"locality"
},
  "geometry": {"coordinates":[103.39421,13.60788],"type":"Point"}
}