{
  "type": "Feature",
  "properties": {
    "gn:admin1_code":"29",
    "gn:asciiname":"Phum Svay Sar",
    "gn:country_code":"KH",
    "gn:dem":79,
    "gn:feature_class":"P",
    "gn:feature_code":"PPL",
    "gn:name":"Phum Svay S\u00e2r",
    "gn:population":0,
    "gn:timezone":"Asia/Phnom_Penh",
    "iso:country":"KH",
    "name:khm_x_preferred":[
        "Phum Svay S\u00e2r"
    ],
    "name:khm_x_variant":[
        "\u1797\u17bc\u1798\u17b7 \u179f\u17d2\u179c\u17b6\u1799\u179f\u179a"
    ],
    "name:und_x_variant":[
        "Phum Soay Sar",
        "Phum\u012d Svay S\u00e2r",
        "Svay Sa"
    ],
    "wof:name":"Phum Svay Sar",
    "wof:placetype":"locality"
},
  "geometry": {"coordinates":[102.81780000000001,12.85114],"type":"Point"}
}