{
  "type": "Feature",
  "properties": {
    "gn:admin1_code":"25",
    "gn:asciiname":"Totea",
    "gn:country_code":"KH",
    "gn:dem":36,
    "gn:feature_class":"P",
    "gn:feature_code":"PPL",
    "gn:name":"Totea",
    "gn:population":0,
    "gn:timezone":"Asia/Phnom_Penh",
    "iso:country":"KH",
    "name:khm_x_preferred":[
        "Totea"
    ],
    "name:khm_x_variant":[
        "\u1797\u17bc\u1798\u17b7 \u1791\u1791\u17b6\u179b",
        "Phum\u012d T\u00f4t\u00e9al",
        "Phum Sdau",
        "\u1797\u17bc\u1798\u17b7 \u179f\u17d2\u178f\u17c5"
    ],
    "wof:name":"Totea",
    "wof:placetype":"locality"
},
  "geometry": {"coordinates":[103.08743,13.86614],"type":"Point"}
}