{
  "type": "Feature",
  "properties": {
    "gn:admin1_code":"25",
    "gn:asciiname":"Mau",
    "gn:country_code":"KH",
    "gn:dem":30,
    "gn:feature_class":"P",
    "gn:feature_code":"PPL",
    "gn:name":"Mau",
    "gn:population":0,
    "gn:timezone":"Asia/Phnom_Penh",
    "iso:country":"KH",
    "name:azb_x_preferred":[
        "\u0645\u0627\u0648"
    ],
    "name:cat_x_preferred":[
        "Mau"
    ],
    "name:ceb_x_preferred":[
        "Mau"
    ],
    "name:deu_x_preferred":[
        "Mau"
    ],
    "name:fas_x_preferred":[
        "\u0645\u0627\u0648"
    ],
    "name:fra_x_preferred":[
        "Mau"
    ],
    "name:hin_x_preferred":[
        "\u092e\u090a"
    ],
    "name:ita_x_preferred":[
        "Mau"
    ],
    "name:khm_x_preferred":[
        "Mau"
    ],
    "name:khm_x_variant":[
        "\u1797\u17bc\u1798\u17b7 \u1798\u17c9\u17c5",
        "Phum\u012d Mau",
        "Phum Mau"
    ],
    "name:msa_x_preferred":[
        "Mau"
    ],
    "name:nld_x_preferred":[
        "Mau"
    ],
    "name:pnb_x_preferred":[
        "\u0645\u0626\u0648"
    ],
    "name:pol_x_preferred":[
        "Mau"
    ],
    "name:por_x_preferred":[
        "Maunath Bhanjan"
    ],
    "name:rus_x_preferred":[
        "\u041c\u0430\u0443"
    ],
    "name:san_x_preferred":[
        "\u092e\u0935\u0941"
    ],
    "name:srp_x_preferred":[
        "\u041c\u0430\u0443"
    ],
    "name:swe_x_preferred":[
        "Maunath Bhanjan"
    ],
    "name:urd_x_preferred":[
        "\u0645\u0626\u0648"
    ],
    "name:vie_x_preferred":[
        "Maunath Bhanjan"
    ],
    "name:war_x_preferred":[
        "Mau"
    ],
    "name:zho_x_preferred":[
        "\u6bdb\u7eb3\u7279\u73ed\u8a79"
    ],
    "wof:name":"Mau",
    "wof:placetype":"locality"
},
  "geometry": {"coordinates":[103.11199999999999,13.80733],"type":"Point"}
}