{
  "type": "Feature",
  "properties": {
    "gn:admin1_code":"02",
    "gn:asciiname":"Phumi Araks",
    "gn:country_code":"KH",
    "gn:dem":16,
    "gn:feature_class":"P",
    "gn:feature_code":"PPL",
    "gn:name":"Phum\u012d Ar\u0103ks",
    "gn:population":0,
    "gn:timezone":"Asia/Phnom_Penh",
    "iso:country":"KH",
    "name:und_x_variant":[
        "A Rac",
        "Phum\u012d Are\u0103k",
        "Phum\u012d Ar\u0103ks"
    ],
    "wof:name":"Phumi Araks",
    "wof:placetype":"locality"
},
  "geometry": {"coordinates":[105.09644,12.10689],"type":"Point"}
}