{
  "type": "Feature",
  "properties": {
    "gn:admin1_code":"08",
    "gn:asciiname":"Bak Khlang",
    "gn:country_code":"KH",
    "gn:dem":4,
    "gn:feature_class":"P",
    "gn:feature_code":"PPLA3",
    "gn:name":"Bak Khlang",
    "gn:population":0,
    "gn:timezone":"Asia/Phnom_Penh",
    "iso:country":"KH",
    "name:khm_x_preferred":[
        "Bak Khlang"
    ],
    "name:und_x_variant":[
        "Ban Snam Khwai",
        "Packlang",
        "Snon Khuai",
        "Phum Thn\u00e1l Kr\u00e2bei",
        "Snom Khuai",
        "Snom Craboeu",
        "Snom Crabeu",
        "Snam Krapeu",
        "Phum\u012d Thn\u00e1l Kr\u00e2bei"
    ],
    "wof:name":"Bak Khlang",
    "wof:placetype":"locality"
},
  "geometry": {"coordinates":[102.95542,11.56903],"type":"Point"}
}