{
  "type": "Feature",
  "properties": {
    "gn:admin1_code":"04",
    "gn:asciiname":"Phum Soriya",
    "gn:country_code":"KH",
    "gn:dem":221,
    "gn:feature_class":"P",
    "gn:feature_code":"PPL",
    "gn:name":"Phum Sor\u012dya",
    "gn:population":0,
    "gn:timezone":"Asia/Phnom_Penh",
    "iso:country":"KH",
    "name:khm_x_preferred":[
        "Phum Sor\u012dya"
    ],
    "name:khm_x_variant":[
        "\u1797\u17bc\u1798\u17b7 \u179f\u17bc\u179a\u17b7\u1799\u17c9\u17b6",
        "Phum\u012d Sor\u012dya"
    ],
    "wof:name":"Phum Soriya",
    "wof:placetype":"locality"
},
  "geometry": {"coordinates":[103.9147,11.77532],"type":"Point"}
}