{
  "type": "Feature",
  "properties": {
    "gn:admin1_code":"05",
    "gn:asciiname":"Odongk",
    "gn:country_code":"KH",
    "gn:dem":19,
    "gn:feature_class":"P",
    "gn:feature_code":"PPL",
    "gn:name":"\u014ed\u014fngk",
    "gn:population":0,
    "gn:timezone":"Asia/Phnom_Penh",
    "iso:country":"KH",
    "name:deu_x_preferred":[
        "Udong"
    ],
    "name:fra_x_preferred":[
        "Oudong"
    ],
    "name:ita_x_preferred":[
        "Oudong"
    ],
    "name:jpn_x_preferred":[
        "\u30a6\u30c9\u30f3"
    ],
    "name:khm_x_preferred":[
        "\u1797\u17d2\u1793\u17c6\u17a7\u178a\u17bb\u1784\u17d2\u1782"
    ],
    "name:kor_x_preferred":[
        "\uc6b0\ub3d9"
    ],
    "name:por_x_preferred":[
        "Oudong"
    ],
    "name:rus_x_preferred":[
        "\u0423\u0434\u043e\u043d\u0433"
    ],
    "name:swe_x_preferred":[
        "Oudong"
    ],
    "name:tha_x_preferred":[
        "\u0e2d\u0e38\u0e14\u0e07\u0e21\u0e35\u0e0a\u0e31\u0e22"
    ],
    "name:ukr_x_preferred":[
        "\u0423\u0434\u043e\u043d\u0433"
    ],
    "name:und_x_variant":[
        "Phum\u012d Odong",
        "Phum Sar Oudong",
        "Phum\u012d \u014ed\u014fngk",
        "Phsar Oudong",
        "Udon",
        "Phsar-Oudond",
        "\u014ed\u014fng",
        "\u014ed\u014fngk"
    ],
    "name:vie_x_preferred":[
        "Oudong"
    ],
    "wof:name":"Odongk",
    "wof:placetype":"locality"
},
  "geometry": {"coordinates":[104.74359,11.82252],"type":"Point"}
}