{
  "type": "Feature",
  "properties": {
    "gn:admin1_code":"05",
    "gn:asciiname":"Odongk",
    "gn:country_code":"KH",
    "gn:dem":19,
    "gn:feature_class":"P",
    "gn:feature_code":"PPL",
    "gn:name":"\u014ed\u014fngk",
    "gn:population":0,
    "gn:timezone":"Asia/Phnom_Penh",
    "iso:country":"KH",
    "name:und_x_variant":[
        "Phum\u012d Odong",
        "Phum Sar Oudong",
        "Phum\u012d \u014ed\u014fngk",
        "Phsar Oudong",
        "Udong",
        "Oudong",
        "Udon",
        "Phsar-Oudond",
        "\u014ed\u014fng",
        "\u014ed\u014fngk"
    ],
    "wof:name":"Odongk",
    "wof:placetype":"locality"
},
  "geometry": {"coordinates":[104.74359,11.82252],"type":"Point"}
}