{
  "type": "Feature",
  "properties": {
    "gn:admin1_code":"05",
    "gn:asciiname":"Phumi Trapeang Chhuk",
    "gn:country_code":"KH",
    "gn:dem":20,
    "gn:feature_class":"P",
    "gn:feature_code":"PPL",
    "gn:name":"Phum\u012d Tr\u00e2pe\u0103ng Chhuk",
    "gn:population":0,
    "gn:timezone":"Asia/Phnom_Penh",
    "iso:country":"KH",
    "name:und_x_variant":[
        "Trapeang Chhuk",
        "Phum\u012d Tr\u00e2pe\u0103ng Chhuk"
    ],
    "wof:name":"Phumi Trapeang Chhuk",
    "wof:placetype":"locality"
},
  "geometry": {"coordinates":[105.09442,12.43299],"type":"Point"}
}