{
  "type": "Feature",
  "properties": {
    "gn:admin1_code":"08",
    "gn:asciiname":"Ta Ni",
    "gn:country_code":"KH",
    "gn:dem":1,
    "gn:feature_class":"P",
    "gn:feature_code":"PPL",
    "gn:name":"Ta Ni",
    "gn:population":0,
    "gn:timezone":"Asia/Phnom_Penh",
    "iso:country":"KH",
    "name:khm_x_preferred":[
        "Ta Ni"
    ],
    "wof:name":"Ta Ni",
    "wof:placetype":"locality"
},
  "geometry": {"coordinates":[103.65724,11.15044],"type":"Point"}
}