{
  "type": "Feature",
  "properties": {
    "gn:admin1_code":"07",
    "gn:asciiname":"Chambak Meas",
    "gn:country_code":"KH",
    "gn:dem":18,
    "gn:feature_class":"P",
    "gn:feature_code":"PPL",
    "gn:name":"Chambak Meas",
    "gn:population":0,
    "gn:timezone":"Asia/Phnom_Penh",
    "iso:country":"KH",
    "name:und_x_variant":[
        "Phum\u012d Ch\u00e2mb\u00e1k M\u00e9as Leu"
    ],
    "wof:name":"Chambak Meas",
    "wof:placetype":"locality"
},
  "geometry": {"coordinates":[104.94611,11.70761],"type":"Point"}
}