{
  "type": "Feature",
  "properties": {
    "gn:admin1_code":"19",
    "gn:asciiname":"Phumi Chong Angkar",
    "gn:country_code":"KH",
    "gn:dem":7,
    "gn:feature_class":"P",
    "gn:feature_code":"PPL",
    "gn:name":"Phum\u012d Ch\u014fng \u00c2ngk\u00e2r",
    "gn:population":0,
    "gn:timezone":"Asia/Phnom_Penh",
    "iso:country":"KH",
    "name:und_x_variant":[
        "Phum Tabas",
        "Phum\u012d Ch\u014fng \u00c2ngk\u00e2r"
    ],
    "wof:name":"Phumi Chong Angkar",
    "wof:placetype":"locality"
},
  "geometry": {"coordinates":[104.85869,10.68613],"type":"Point"}
}