{
  "type": "Feature",
  "properties": {
    "gn:admin1_code":"22",
    "gn:asciiname":"Phumi Khva",
    "gn:country_code":"KH",
    "gn:dem":12,
    "gn:feature_class":"P",
    "gn:feature_code":"PPL",
    "gn:name":"Phum\u012d Khva",
    "gn:population":0,
    "gn:timezone":"Asia/Phnom_Penh",
    "iso:country":"KH",
    "name:und_x_variant":[
        "Khvan",
        "Phum\u012d Khva"
    ],
    "wof:name":"Phumi Khva",
    "wof:placetype":"locality"
},
  "geometry": {"coordinates":[104.89493,11.50449],"type":"Point"}
}