{
  "type": "Feature",
  "properties": {
    "gn:admin1_code":"27",
    "gn:asciiname":"Phumi Tnaot",
    "gn:country_code":"KH",
    "gn:dem":24,
    "gn:feature_class":"P",
    "gn:feature_code":"PPL",
    "gn:name":"Phum\u012d Tna\u00f4t",
    "gn:population":0,
    "gn:timezone":"Asia/Phnom_Penh",
    "iso:country":"KH",
    "name:und_x_variant":[
        "Phum\u012d Tha\u014fk",
        "Phum\u012d Tna\u00f4t"
    ],
    "wof:name":"Phumi Tnaot",
    "wof:placetype":"locality"
},
  "geometry": {"coordinates":[103.54273999999999,13.92426],"type":"Point"}
}