{
  "type": "Feature",
  "properties": {
    "gn:admin1_code":"29",
    "gn:asciiname":"Ou Kakir",
    "gn:country_code":"KH",
    "gn:dem":76,
    "gn:feature_class":"P",
    "gn:feature_code":"PPL",
    "gn:name":"Ou Kakir",
    "gn:population":0,
    "gn:timezone":"Asia/Phnom_Penh",
    "iso:country":"KH",
    "name:khm_x_preferred":[
        "Ou Kakir"
    ],
    "wof:name":"Ou Kakir",
    "wof:placetype":"locality"
},
  "geometry": {"coordinates":[102.50125,13.09898],"type":"Point"}
}