{
  "type": "Feature",
  "properties": {
    "gn:admin1_code":"29",
    "gn:asciiname":"Kbal Thnal",
    "gn:country_code":"KH",
    "gn:dem":14,
    "gn:feature_class":"P",
    "gn:feature_code":"PPL",
    "gn:name":"Kbal Thnal",
    "gn:population":0,
    "gn:timezone":"Asia/Phnom_Penh",
    "iso:country":"KH",
    "name:khm_x_preferred":[
        "Kbal Thnal"
    ],
    "name:khm_x_variant":[
        "Phum\u012d Kbal Thn\u00e2l",
        "\u1797\u17bc\u1798\u17b7 \u1780\u17d2\u1794\u17b6\u179b\u1790\u17d2\u1793\u179b\u17cb"
    ],
    "name:und_x_variant":[
        "Phum\u012d Kbal Thn\u00e1l"
    ],
    "wof:name":"Kbal Thnal",
    "wof:placetype":"locality"
},
  "geometry": {"coordinates":[103.32872999999999,12.97957],"type":"Point"}
}