{
  "type": "Feature",
  "properties": {
    "gn:admin1_code":"08",
    "gn:asciiname":"Phum Prek Tachan",
    "gn:country_code":"KH",
    "gn:dem":5,
    "gn:feature_class":"P",
    "gn:feature_code":"PPL",
    "gn:name":"Phum Pr\u00eak Tachan",
    "gn:population":0,
    "gn:timezone":"Asia/Phnom_Penh",
    "iso:country":"KH",
    "name:khm_x_preferred":[
        "Phum Pr\u00eak Tachan"
    ],
    "name:khm_x_variant":[
        "\u1797\u17bc\u1798\u17b7 \u1796\u17d2\u179a\u17c2\u1780\u178f\u17b6\u1785\u17b6\u1793\u17cb"
    ],
    "name:und_x_variant":[
        "Phum\u012d Pr\u00eak Tach\u0103n"
    ],
    "wof:name":"Phum Prek Tachan",
    "wof:placetype":"locality"
},
  "geometry": {"coordinates":[103.26367,11.35726],"type":"Point"}
}