{
  "type": "Feature",
  "properties": {
    "gn:admin1_code":"18",
    "gn:asciiname":"Prey Angkonh",
    "gn:country_code":"KH",
    "gn:dem":9,
    "gn:feature_class":"P",
    "gn:feature_code":"PPL",
    "gn:name":"Prey Angkonh",
    "gn:population":0,
    "gn:timezone":"Asia/Phnom_Penh",
    "iso:country":"KH",
    "name:khm_x_preferred":[
        "Prey Angkonh"
    ],
    "name:khm_x_variant":[
        "\u1797\u17bc\u1798\u17b7 \u1796\u17d2\u179a\u17c3\u17a2\u1784\u17d2\u1782\u17bb\u1789",
        "Phum Prey \u00c2ngk\u016dnh"
    ],
    "wof:name":"Prey Angkonh",
    "wof:placetype":"locality"
},
  "geometry": {"coordinates":[106.03193,11.02529],"type":"Point"}
}