{
  "type": "Feature",
  "properties": {
    "gn:admin1_code":"24.0",
    "gn:asciiname":"Prasat Pouth",
    "gn:country_code":"KH",
    "gn:dem":22,
    "gn:feature_class":"P",
    "gn:feature_code":"PPL",
    "gn:name":"Prasat Pouth",
    "gn:population":0,
    "gn:timezone":"Asia/Phnom_Penh",
    "iso:country":"KH",
    "name:khm_x_preferred":[
        "Prasat Pouth"
    ],
    "name:khm_x_variant":[
        "\u1794\u17d2\u179a\u17b6\u179f\u17b6\u1791\u1796\u17c4\u1792\u17b7"
    ],
    "wof:name":"Prasat Pouth",
    "wof:placetype":"locality"
},
  "geometry": {"coordinates":[104.00476999999999,13.38565],"type":"Point"}
}