{
  "type": "Feature",
  "properties": {
    "gn:admin1_code":"14",
    "gn:asciiname":"Preaek Chrey",
    "gn:country_code":"KH",
    "gn:dem":10,
    "gn:feature_class":"P",
    "gn:feature_code":"PPL",
    "gn:name":"Preaek Chrey",
    "gn:population":0,
    "gn:timezone":"Asia/Phnom_Penh",
    "iso:country":"KH",
    "name:khm_x_preferred":[
        "Preaek Chrey"
    ],
    "name:khm_x_variant":[
        "\u1797\u17bc\u1798\u17b7 \u1796\u17d2\u179a\u17c2\u1780\u1787\u17d2\u179a\u17c3",
        "Phum Pr\u00eak Chrey"
    ],
    "name:und_x_variant":[
        "Phum Prey Chrey",
        "Phum\u012d Pr\u00eak Chrey"
    ],
    "wof:name":"Preaek Chrey",
    "wof:placetype":"locality"
},
  "geometry": {"coordinates":[105.23521,11.46638],"type":"Point"}
}