{
  "type": "Feature",
  "properties": {
    "gn:admin1_code":"29",
    "gn:asciiname":"Phlov Meas",
    "gn:country_code":"KH",
    "gn:dem":50,
    "gn:feature_class":"P",
    "gn:feature_code":"PPL",
    "gn:name":"Phlov Meas",
    "gn:population":0,
    "gn:timezone":"Asia/Phnom_Penh",
    "iso:country":"KH",
    "name:khm_x_preferred":[
        "Phlov Meas"
    ],
    "name:khm_x_variant":[
        "\u1783\u17bb\u17c6\u1795\u17d2\u179b\u17bc\u179c\u1798\u17b6\u179f"
    ],
    "name:spa_x_preferred":[
        "Phlov Meas"
    ],
    "wof:name":"Phlov Meas",
    "wof:placetype":"locality"
},
  "geometry": {"coordinates":[102.99615,12.91938],"type":"Point"}
}