{
  "type": "Feature",
  "properties": {
    "gn:admin1_code":"14",
    "gn:asciiname":"Phumi Trapeang Pring",
    "gn:country_code":"KH",
    "gn:dem":12,
    "gn:feature_class":"P",
    "gn:feature_code":"PPL",
    "gn:name":"Phum\u012d Tr\u00e2pe\u0103ng Pring",
    "gn:population":0,
    "gn:timezone":"Asia/Phnom_Penh",
    "iso:country":"KH",
    "wof:name":"Phumi Trapeang Pring",
    "wof:placetype":"locality"
},
  "geometry": {"coordinates":[105.4778,11.49582],"type":"Point"}
}