{
  "type": "Feature",
  "properties": {
    "gn:admin1_code":"29",
    "gn:asciiname":"Thmei",
    "gn:country_code":"KH",
    "gn:dem":17,
    "gn:feature_class":"P",
    "gn:feature_code":"PPL",
    "gn:name":"Thmei",
    "gn:population":0,
    "gn:timezone":"Asia/Phnom_Penh",
    "iso:country":"KH",
    "name:khm_x_preferred":[
        "Thmei"
    ],
    "name:khm_x_variant":[
        "\u1797\u17bc\u1798\u17b7 \u1790\u17d2\u1798\u17b8",
        "Phum Thmei"
    ],
    "name:und_x_variant":[
        "Phum\u012d Thmei"
    ],
    "wof:name":"Thmei",
    "wof:placetype":"locality"
},
  "geometry": {"coordinates":[103.05636,13.06954],"type":"Point"}
}