{
  "type": "Feature",
  "properties": {
    "gn:admin1_code":"19",
    "gn:asciiname":"Phumi Bar Cham",
    "gn:country_code":"KH",
    "gn:dem":13,
    "gn:feature_class":"P",
    "gn:feature_code":"PPL",
    "gn:name":"Phum\u012d B\u00e2r Cham",
    "gn:population":0,
    "gn:timezone":"Asia/Phnom_Penh",
    "iso:country":"KH",
    "name:und_x_variant":[
        "Trapeang Treng",
        "Phum\u012d B\u00e2r Cham"
    ],
    "wof:name":"Phumi Bar Cham",
    "wof:placetype":"locality"
},
  "geometry": {"coordinates":[104.80453,11.24647],"type":"Point"}
}