{
  "type": "Feature",
  "properties": {
    "gn:admin1_code":"23",
    "gn:asciiname":"Malik",
    "gn:country_code":"KH",
    "gn:dem":150,
    "gn:feature_class":"P",
    "gn:feature_code":"PPL",
    "gn:name":"Malik",
    "gn:population":0,
    "gn:timezone":"Asia/Phnom_Penh",
    "iso:country":"KH",
    "name:khm_x_preferred":[
        "Malik"
    ],
    "name:und_x_variant":[
        "Phum\u012d Mal\u012dk"
    ],
    "wof:name":"Malik",
    "wof:placetype":"locality"
},
  "geometry": {"coordinates":[107.26531,13.84794],"type":"Point"}
}