{
  "type": "Feature",
  "properties": {
    "gn:admin1_code":"31",
    "gn:asciiname":"Phumi Cheung Angk",
    "gn:country_code":"KH",
    "gn:dem":28,
    "gn:feature_class":"P",
    "gn:feature_code":"PPL",
    "gn:name":"Phum\u012d Cheung \u00c2ngk",
    "gn:population":0,
    "gn:timezone":"Asia/Phnom_Penh",
    "iso:country":"KH",
    "name:und_x_variant":[
        "Phumi Cheung \u00c2ng",
        "Phum Ch\u0153ung Ang",
        "Phum\u012d Cheung \u00c2ngk"
    ],
    "wof:name":"Phumi Cheung Angk",
    "wof:placetype":"locality"
},
  "geometry": {"coordinates":[105.80983999999999,11.87808],"type":"Point"}
}