{
  "type": "Feature",
  "properties": {
    "gn:admin1_code":"24",
    "gn:asciiname":"Srae Khvav",
    "gn:country_code":"KH",
    "gn:dem":38,
    "gn:feature_class":"P",
    "gn:feature_code":"PPL",
    "gn:name":"Srae Khvav",
    "gn:population":0,
    "gn:timezone":"Asia/Phnom_Penh",
    "iso:country":"KH",
    "name:khm_x_preferred":[
        "Srae Khvav"
    ],
    "wof:name":"Srae Khvav",
    "wof:placetype":"locality"
},
  "geometry": {"coordinates":[103.66249999999999,13.7636],"type":"Point"}
}