{
  "type": "Feature",
  "properties": {
    "gn:admin1_code":"19",
    "gn:asciiname":"Phumi Kdol Chomrum",
    "gn:country_code":"KH",
    "gn:dem":4,
    "gn:feature_class":"P",
    "gn:feature_code":"PPL",
    "gn:name":"Phum\u012d Kd\u014fl Ch\u00f4mr\u016dm",
    "gn:population":0,
    "gn:timezone":"Asia/Phnom_Penh",
    "iso:country":"KH",
    "name:und_x_variant":[
        "Phum An Hoa",
        "Phum\u012d Kd\u014fl Ch\u016dmr\u016dm",
        "Phum\u012d Kd\u014fl Ch\u00f4mr\u016dm"
    ],
    "wof:name":"Phumi Kdol Chomrum",
    "wof:placetype":"locality"
},
  "geometry": {"coordinates":[105.06682000000001,10.76209],"type":"Point"}
}