{
  "type": "Feature",
  "properties": {
    "gn:admin1_code":"21",
    "gn:asciiname":"Phumi Trapeang Khnar",
    "gn:country_code":"KH",
    "gn:dem":7,
    "gn:feature_class":"P",
    "gn:feature_code":"PPL",
    "gn:name":"Phum\u012d Tr\u00e2pe\u0103ng Khnar",
    "gn:population":0,
    "gn:timezone":"Asia/Phnom_Penh",
    "iso:country":"KH",
    "name:und_x_variant":[
        "Phum Trapeang Kna",
        "Phum\u012d Tr\u00e2pe\u00e0ng Khna",
        "Phum\u012d Tr\u00e2pe\u0103ng Khnar"
    ],
    "wof:name":"Phumi Trapeang Khnar",
    "wof:placetype":"locality"
},
  "geometry": {"coordinates":[104.19144,10.65754],"type":"Point"}
}