{
  "type": "Feature",
  "properties": {
    "gn:admin1_code":"24.0",
    "gn:asciiname":"Chambak Thum",
    "gn:country_code":"KH",
    "gn:dem":22,
    "gn:feature_class":"P",
    "gn:feature_code":"PPL",
    "gn:name":"Chambak Thum",
    "gn:population":0,
    "gn:timezone":"Asia/Phnom_Penh",
    "iso:country":"KH",
    "name:khm_x_preferred":[
        "Chambak Thum"
    ],
    "name:khm_x_variant":[
        "\u1797\u17bc\u1798\u17b7 \u1785\u17c6\u1794\u1780\u17cb\u1792\u17c6",
        "Phum Ch\u00e2mb\u00e2k Thom"
    ],
    "wof:name":"Chambak Thum",
    "wof:placetype":"locality"
},
  "geometry": {"coordinates":[104.34295,13.15058],"type":"Point"}
}