{
  "type": "Feature",
  "properties": {
    "gn:admin1_code":"04",
    "gn:asciiname":"Phumi Krang Kroch",
    "gn:country_code":"KH",
    "gn:dem":48,
    "gn:feature_class":"P",
    "gn:feature_code":"PPL",
    "gn:name":"Phum\u012d Kr\u0103ng Kroch",
    "gn:population":0,
    "gn:timezone":"Asia/Phnom_Penh",
    "iso:country":"KH",
    "name:und_x_variant":[
        "Phum Krang Kr\u00e2uch",
        "Phum\u012d Kr\u0103ng Kroch"
    ],
    "wof:name":"Phumi Krang Kroch",
    "wof:placetype":"locality"
},
  "geometry": {"coordinates":[104.53504,11.40741],"type":"Point"}
}