{
  "type": "Feature",
  "properties": {
    "gn:admin1_code":"12",
    "gn:asciiname":"Phum Reang Khvav",
    "gn:country_code":"KH",
    "gn:dem":104,
    "gn:feature_class":"P",
    "gn:feature_code":"PPL",
    "gn:name":"Phum Re\u0103ng Khvav",
    "gn:population":0,
    "gn:timezone":"Asia/Phnom_Penh",
    "iso:country":"KH",
    "name:khm_x_preferred":[
        "Phum Re\u0103ng Khvav"
    ],
    "name:khm_x_variant":[
        "\u1797\u17bc\u1798\u17b7 \u179a\u17b6\u17c6\u1784\u1781\u17d2\u179c\u17b6\u179c"
    ],
    "name:und_x_variant":[
        "P\u2019um Reang K\u2019vav",
        "Phum\u012d Re\u0103ng Khvav"
    ],
    "wof:name":"Phum Reang Khvav",
    "wof:placetype":"locality"
},
  "geometry": {"coordinates":[104.00051999999999,12.19795],"type":"Point"}
}