{
  "type": "Feature",
  "properties": {
    "gn:admin1_code":"23.0",
    "gn:asciiname":"Kam Phlenh",
    "gn:country_code":"KH",
    "gn:dem":117,
    "gn:feature_class":"P",
    "gn:feature_code":"PPL",
    "gn:name":"Kam Phlenh",
    "gn:population":0,
    "gn:timezone":"Asia/Phnom_Penh",
    "iso:country":"KH",
    "name:khm_x_preferred":[
        "Kam Phlenh"
    ],
    "wof:name":"Kam Phlenh",
    "wof:placetype":"locality"
},
  "geometry": {"coordinates":[106.96111000000001,13.62568],"type":"Point"}
}