{
  "type": "Feature",
  "properties": {
    "gn:admin1_code":"04",
    "gn:asciiname":"Phumi Roluos",
    "gn:country_code":"KH",
    "gn:dem":92,
    "gn:feature_class":"P",
    "gn:feature_code":"PPL",
    "gn:name":"Phum\u012d R\u00f4lu\u014fs",
    "gn:population":0,
    "gn:timezone":"Asia/Phnom_Penh",
    "iso:country":"KH",
    "wof:name":"Phumi Roluos",
    "wof:placetype":"locality"
},
  "geometry": {"coordinates":[104.36132000000001,11.34298],"type":"Point"}
}