{
  "type": "Feature",
  "properties": {
    "gn:admin1_code":"24",
    "gn:asciiname":"Siem Reab",
    "gn:country_code":"KH",
    "gn:dem":19,
    "gn:feature_class":"P",
    "gn:feature_code":"PPL",
    "gn:name":"Siem Reab",
    "gn:population":0,
    "gn:timezone":"Asia/Phnom_Penh",
    "iso:country":"KH",
    "name:khm_x_preferred":[
        "Siem Reab"
    ],
    "name:khm_x_variant":[
        "Phum Sp\u00e9anchr\u00e9av",
        "\u1797\u17bc\u1798\u17b7 \u179f\u17d2\u1796\u17b6\u1793\u1787\u17d2\u179a\u17b6\u179c"
    ],
    "name:und_x_variant":[
        "Phum\u012d Sp\u00e9an Chr\u00e9av"
    ],
    "wof:name":"Siem Reab",
    "wof:placetype":"locality"
},
  "geometry": {"coordinates":[103.8515,13.31654],"type":"Point"}
}