{
  "type": "Feature",
  "properties": {
    "gn:admin1_code":"07",
    "gn:asciiname":"Phumi Damnak Kakaoh",
    "gn:country_code":"KH",
    "gn:dem":25,
    "gn:feature_class":"P",
    "gn:feature_code":"PPL",
    "gn:name":"Phum\u012d D\u00e2mn\u0103k K\u00e2ka\u00f4h",
    "gn:population":0,
    "gn:timezone":"Asia/Phnom_Penh",
    "iso:country":"KH",
    "wof:name":"Phumi Damnak Kakaoh",
    "wof:placetype":"locality"
},
  "geometry": {"coordinates":[104.6905,11.55789],"type":"Point"}
}