{
  "type": "Feature",
  "properties": {
    "gn:admin1_code":"13",
    "gn:asciiname":"Phumi Kamprak",
    "gn:country_code":"KH",
    "gn:dem":64,
    "gn:feature_class":"P",
    "gn:feature_code":"PPL",
    "gn:name":"Phum\u012d K\u00e2mpr\u0103k",
    "gn:population":0,
    "gn:timezone":"Asia/Phnom_Penh",
    "iso:country":"KH",
    "wof:name":"Phumi Kamprak",
    "wof:placetype":"locality"
},
  "geometry": {"coordinates":[104.58153,14.10124],"type":"Point"}
}