{
  "type": "Feature",
  "properties": {
    "gn:admin1_code":"04",
    "gn:asciiname":"Trapeang Veaeng",
    "gn:country_code":"KH",
    "gn:dem":40,
    "gn:feature_class":"P",
    "gn:feature_code":"PPL",
    "gn:name":"Trapeang Veaeng",
    "gn:population":0,
    "gn:timezone":"Asia/Phnom_Penh",
    "iso:country":"KH",
    "name:khm_x_preferred":[
        "Trapeang Veaeng"
    ],
    "wof:name":"Trapeang Veaeng",
    "wof:placetype":"locality"
},
  "geometry": {"coordinates":[104.63363,11.63183],"type":"Point"}
}