{
  "type": "Feature",
  "properties": {
    "gn:admin1_code":"13",
    "gn:asciiname":"Srayang Tboung",
    "gn:country_code":"KH",
    "gn:dem":137,
    "gn:feature_class":"P",
    "gn:feature_code":"PPL",
    "gn:name":"Srayang Tboung",
    "gn:population":0,
    "gn:timezone":"Asia/Phnom_Penh",
    "iso:country":"KH",
    "name:khm_x_preferred":[
        "Srayang Tboung"
    ],
    "wof:name":"Srayang Tboung",
    "wof:placetype":"locality"
},
  "geometry": {"coordinates":[104.55587,13.69913],"type":"Point"}
}