{
  "type": "Feature",
  "properties": {
    "gn:admin1_code":"02",
    "gn:asciiname":"Phumi Anlung Koki",
    "gn:country_code":"KH",
    "gn:dem":15,
    "gn:feature_class":"P",
    "gn:feature_code":"PPL",
    "gn:name":"Phum\u012d \u00c2nl\u016dng K\u00f4ki",
    "gn:population":0,
    "gn:timezone":"Asia/Phnom_Penh",
    "iso:country":"KH",
    "name:und_x_variant":[
        "Phum\u012d \u00c2nlong K\u00f4ki",
        "Phum\u012d \u00c2nl\u016dng K\u00f4ki"
    ],
    "wof:name":"Phumi Anlung Koki",
    "wof:placetype":"locality"
},
  "geometry": {"coordinates":[105.00498,11.87206],"type":"Point"}
}