{
  "type": "Feature",
  "properties": {
    "gn:admin1_code":"04",
    "gn:asciiname":"Ta Lak",
    "gn:country_code":"KH",
    "gn:dem":29,
    "gn:feature_class":"P",
    "gn:feature_code":"PPL",
    "gn:name":"Ta Lak",
    "gn:population":0,
    "gn:timezone":"Asia/Phnom_Penh",
    "iso:country":"KH",
    "name:khm_x_preferred":[
        "Ta Lak"
    ],
    "name:und_x_variant":[
        "Ta S\u00e2k",
        "Phum\u012d Ta L\u00e2k"
    ],
    "wof:name":"Ta Lak",
    "wof:placetype":"locality"
},
  "geometry": {"coordinates":[104.70894,11.72585],"type":"Point"}
}