{
  "type": "Feature",
  "properties": {
    "gn:admin1_code":"03",
    "gn:asciiname":"Chan Trak",
    "gn:country_code":"KH",
    "gn:dem":45,
    "gn:feature_class":"P",
    "gn:feature_code":"PPL",
    "gn:name":"Chan Trak",
    "gn:population":0,
    "gn:timezone":"Asia/Phnom_Penh",
    "iso:country":"KH",
    "name:khm_x_preferred":[
        "\u1797\u17bc\u1798\u17b7 \u1785\u17b6\u1793\u17cb\u178f\u17d2\u179a\u17c4\u1780"
    ],
    "name:khm_x_variant":[
        "Phum Ch\u0103n Tra\u00f4k"
    ],
    "name:und_x_variant":[
        "Phum\u012d Ch\u0103n Tra\u00f4k"
    ],
    "wof:name":"Chan Trak",
    "wof:placetype":"locality"
},
  "geometry": {"coordinates":[104.46249,12.21442],"type":"Point"}
}