{
  "type": "Feature",
  "properties": {
    "gn:admin1_code":"17",
    "gn:asciiname":"Phumi Kaoh Preal",
    "gn:country_code":"KH",
    "gn:dem":57,
    "gn:feature_class":"P",
    "gn:feature_code":"PPL",
    "gn:name":"Phum\u012d Ka\u00f4h Pr\u00e9al",
    "gn:population":0,
    "gn:timezone":"Asia/Phnom_Penh",
    "iso:country":"KH",
    "wof:name":"Phumi Kaoh Preal",
    "wof:placetype":"locality"
},
  "geometry": {"coordinates":[105.93217,13.25659],"type":"Point"}
}