{
  "type": "Feature",
  "properties": {
    "gn:admin1_code":"24",
    "gn:asciiname":"Damnak Slanh",
    "gn:country_code":"KH",
    "gn:dem":21,
    "gn:feature_class":"P",
    "gn:feature_code":"PPL",
    "gn:name":"Damnak Slanh",
    "gn:population":0,
    "gn:timezone":"Asia/Phnom_Penh",
    "iso:country":"KH",
    "name:khm_x_preferred":[
        "Damnak Slanh"
    ],
    "name:khm_x_variant":[
        "\u1797\u17bc\u1798\u17b7 \u178a\u17c6\u178e\u17b6\u1780\u17cb\u179f\u17d2\u179b\u17b6\u1789",
        "Phum D\u00e2mn\u0103k Slanh"
    ],
    "name:und_x_variant":[
        "D\u00e2mnak Slanh",
        "Phum\u012d D\u00e2mn\u0103k Slanh"
    ],
    "wof:name":"Damnak Slanh",
    "wof:placetype":"locality"
},
  "geometry": {"coordinates":[103.66462,13.48856],"type":"Point"}
}