{
  "type": "Feature",
  "properties": {
    "gn:admin1_code":"21",
    "gn:asciiname":"Phumi Trapeang Thngan",
    "gn:country_code":"KH",
    "gn:dem":13,
    "gn:feature_class":"P",
    "gn:feature_code":"PPL",
    "gn:name":"Phum\u012d Tr\u00e2pe\u0103ng Thng\u0103n",
    "gn:population":0,
    "gn:timezone":"Asia/Phnom_Penh",
    "iso:country":"KH",
    "name:und_x_variant":[
        "Phum Trapeang Tbngan",
        "Phum Trap Tbngan",
        "Phum\u012d Tr\u00e2pe\u0103ng Thng\u0103n"
    ],
    "wof:name":"Phumi Trapeang Thngan",
    "wof:placetype":"locality"
},
  "geometry": {"coordinates":[104.62535,10.85634],"type":"Point"}
}