{
  "type": "Feature",
  "properties": {
    "gn:admin1_code":"19",
    "gn:asciiname":"Phumi Prey Cheung",
    "gn:country_code":"KH",
    "gn:dem":9,
    "gn:feature_class":"P",
    "gn:feature_code":"PPL",
    "gn:name":"Phum\u012d Prey Cheung",
    "gn:population":0,
    "gn:timezone":"Asia/Phnom_Penh",
    "iso:country":"KH",
    "name:und_x_variant":[
        "Phum Prey Ch\u0153ng",
        "Phum\u012d Prey Cheung"
    ],
    "wof:name":"Phumi Prey Cheung",
    "wof:placetype":"locality"
},
  "geometry": {"coordinates":[104.75138,10.72624],"type":"Point"}
}