{
  "type": "Feature",
  "properties": {
    "gn:admin1_code":"12",
    "gn:asciiname":"Phumi Phat Sandaong (1)",
    "gn:country_code":"KH",
    "gn:dem":11,
    "gn:feature_class":"P",
    "gn:feature_code":"PPL",
    "gn:name":"Phum\u012d Ph\u0103t S\u00e2nda\u00f4ng (1)",
    "gn:population":0,
    "gn:timezone":"Asia/Phnom_Penh",
    "iso:country":"KH",
    "wof:name":"Phumi Phat Sandaong (1)",
    "wof:placetype":"locality"
},
  "geometry": {"coordinates":[104.07763,12.79627],"type":"Point"}
}