{
  "type": "Feature",
  "properties": {
    "gn:admin1_code":"04",
    "gn:asciiname":"Phumi Ampil Rung",
    "gn:country_code":"KH",
    "gn:dem":18,
    "gn:feature_class":"P",
    "gn:feature_code":"PPL",
    "gn:name":"Phum\u012d \u00c2mp\u012dl Rung",
    "gn:population":0,
    "gn:timezone":"Asia/Phnom_Penh",
    "iso:country":"KH",
    "name:und_x_variant":[
        "Phum Kas Ang",
        "Phum\u012d \u00c2mp\u012dl Rung"
    ],
    "wof:name":"Phumi Ampil Rung",
    "wof:placetype":"locality"
},
  "geometry": {"coordinates":[104.73917,11.77777],"type":"Point"}
}