{
  "type": "Feature",
  "properties": {
    "gn:admin1_code":"13",
    "gn:asciiname":"Svay Pak",
    "gn:country_code":"KH",
    "gn:dem":76,
    "gn:feature_class":"P",
    "gn:feature_code":"PPL",
    "gn:name":"Svay Pak",
    "gn:population":0,
    "gn:timezone":"Asia/Phnom_Penh",
    "iso:country":"KH",
    "name:khm_x_preferred":[
        "Svay Pak"
    ],
    "wof:name":"Svay Pak",
    "wof:placetype":"locality"
},
  "geometry": {"coordinates":[105.02442000000001,13.49202],"type":"Point"}
}