{
  "type": "Feature",
  "properties": {
    "gn:admin1_code":"03",
    "gn:asciiname":"Phumi Sanparai",
    "gn:country_code":"KH",
    "gn:dem":38,
    "gn:feature_class":"P",
    "gn:feature_code":"PPL",
    "gn:name":"Phum\u012d Sanparai",
    "gn:population":0,
    "gn:timezone":"Asia/Phnom_Penh",
    "iso:country":"KH",
    "name:und_x_variant":[
        "San Barai",
        "Phum\u012d Sanparai"
    ],
    "wof:name":"Phumi Sanparai",
    "wof:placetype":"locality"
},
  "geometry": {"coordinates":[104.59592000000001,12.04253],"type":"Point"}
}