{
  "type": "Feature",
  "properties": {
    "gn:admin1_code":"9.0",
    "gn:asciiname":"Phum Sandek Dei",
    "gn:country_code":"KH",
    "gn:dem":24,
    "gn:feature_class":"P",
    "gn:feature_code":"PPL",
    "gn:name":"Phum S\u00e2nd\u00eak Dei",
    "gn:population":0,
    "gn:timezone":"Asia/Phnom_Penh",
    "iso:country":"KH",
    "name:khm_x_preferred":[
        "Phum S\u00e2nd\u00eak Dei"
    ],
    "name:khm_x_variant":[
        "\u1797\u17bc\u1798\u17b7 \u179f\u178e\u17d2\u178a\u17c2\u1780\u178a\u17b8"
    ],
    "wof:name":"Phum Sandek Dei",
    "wof:placetype":"locality"
},
  "geometry": {"coordinates":[105.91213,12.2494],"type":"Point"}
}