{
  "type": "Feature",
  "properties": {
    "gn:admin1_code":"23",
    "gn:asciiname":"Phum Kang Nak",
    "gn:country_code":"KH",
    "gn:dem":103,
    "gn:feature_class":"P",
    "gn:feature_code":"PPL",
    "gn:name":"Phum K\u00e2ng N\u00e2k",
    "gn:population":0,
    "gn:timezone":"Asia/Phnom_Penh",
    "iso:country":"KH",
    "name:khm_x_preferred":[
        "Phum K\u00e2ng N\u00e2k"
    ],
    "name:khm_x_variant":[
        "\u1797\u17bc\u1798\u17b7 \u1780\u1784\u178e\u1780"
    ],
    "wof:name":"Phum Kang Nak",
    "wof:placetype":"locality"
},
  "geometry": {"coordinates":[106.81908,14.02199],"type":"Point"}
}