{
  "type": "Feature",
  "properties": {
    "gn:admin1_code":"29",
    "gn:asciiname":"Phum Michba",
    "gn:country_code":"KH",
    "gn:dem":18,
    "gn:feature_class":"P",
    "gn:feature_code":"PPL",
    "gn:name":"Phum Michba",
    "gn:population":0,
    "gn:timezone":"Asia/Phnom_Penh",
    "iso:country":"KH",
    "name:khm_x_preferred":[
        "Phum Michba"
    ],
    "name:khm_x_variant":[
        "\u1797\u17bc\u1798\u17b7 \u1798\u17b8\u1785\u17d2\u1794\u17b6"
    ],
    "name:und_x_variant":[
        "Phum\u012d Michba"
    ],
    "wof:name":"Phum Michba",
    "wof:placetype":"locality"
},
  "geometry": {"coordinates":[103.02459,13.37932],"type":"Point"}
}