{
  "type": "Feature",
  "properties": {
    "gn:admin1_code":"19",
    "gn:asciiname":"Phumi Kouk Pouthi",
    "gn:country_code":"KH",
    "gn:dem":5,
    "gn:feature_class":"P",
    "gn:feature_code":"PPL",
    "gn:name":"Phum\u012d Ko\u016dk Po\u016dth\u012d",
    "gn:population":0,
    "gn:timezone":"Asia/Phnom_Penh",
    "iso:country":"KH",
    "name:und_x_variant":[
        "Phum Kok Po",
        "Phum\u012d Ko\u016dk Po\u016d",
        "Phum\u012d Ko\u016dk Po\u016dth\u012d"
    ],
    "wof:name":"Phumi Kouk Pouthi",
    "wof:placetype":"locality"
},
  "geometry": {"coordinates":[104.90155,10.88641],"type":"Point"}
}