{
  "type": "Feature",
  "properties": {
    "gn:admin1_code":"14",
    "gn:asciiname":"Phum Prasat",
    "gn:country_code":"KH",
    "gn:dem":11,
    "gn:feature_class":"P",
    "gn:feature_code":"PPL",
    "gn:name":"Phum Prasat",
    "gn:population":0,
    "gn:timezone":"Asia/Phnom_Penh",
    "iso:country":"KH",
    "name:khm_x_preferred":[
        "Phum Prasat"
    ],
    "name:khm_x_variant":[
        "\u1797\u17bc\u1798\u17b7 \u1794\u17d2\u179a\u17b6\u179f\u17b6\u1791",
        "Phum\u012d Prasat"
    ],
    "wof:name":"Phum Prasat",
    "wof:placetype":"locality"
},
  "geometry": {"coordinates":[105.29819000000001,11.30929],"type":"Point"}
}