{
  "type": "Feature",
  "properties": {
    "gn:admin1_code":"03",
    "gn:asciiname":"Phumi Kbal Kaoh",
    "gn:country_code":"KH",
    "gn:dem":9,
    "gn:feature_class":"P",
    "gn:feature_code":"PPL",
    "gn:name":"Phum\u012d Kbal Ka\u00f4h",
    "gn:population":0,
    "gn:timezone":"Asia/Phnom_Penh",
    "iso:country":"KH",
    "name:und_x_variant":[
        "Phum Neak Ta Kang Val",
        "Phum\u012d Kbal Ka\u00f4h"
    ],
    "wof:name":"Phumi Kbal Kaoh",
    "wof:placetype":"locality"
},
  "geometry": {"coordinates":[104.84407,12.17902],"type":"Point"}
}