{
  "type": "Feature",
  "properties": {
    "gn:admin1_code":"31",
    "gn:asciiname":"Kbal Damrei",
    "gn:country_code":"KH",
    "gn:dem":41,
    "gn:feature_class":"P",
    "gn:feature_code":"PPL",
    "gn:name":"Kbal Damrei",
    "gn:population":0,
    "gn:timezone":"Asia/Phnom_Penh",
    "iso:country":"KH",
    "name:khm_x_preferred":[
        "Kbal Damrei"
    ],
    "name:und_x_variant":[
        "Phum Kabal Damrey",
        "Phum Khbal Damrey",
        "Phum\u012d Kbal D\u00e2mrei"
    ],
    "wof:name":"Kbal Damrei",
    "wof:placetype":"locality"
},
  "geometry": {"coordinates":[105.92955000000001,11.73812],"type":"Point"}
}