{
  "type": "Feature",
  "properties": {
    "gn:admin1_code":"04",
    "gn:asciiname":"Svay Rumpea",
    "gn:country_code":"KH",
    "gn:dem":51,
    "gn:feature_class":"P",
    "gn:feature_code":"PPL",
    "gn:name":"Svay Rumpea",
    "gn:population":0,
    "gn:timezone":"Asia/Phnom_Penh",
    "iso:country":"KH",
    "name:khm_x_preferred":[
        "Svay Rumpea"
    ],
    "wof:name":"Svay Rumpea",
    "wof:placetype":"locality"
},
  "geometry": {"coordinates":[104.57611,11.21281],"type":"Point"}
}