{
  "type": "Feature",
  "properties": {
    "gn:admin1_code":"5.0",
    "gn:asciiname":"Prolay",
    "gn:country_code":"KH",
    "gn:dem":16,
    "gn:feature_class":"P",
    "gn:feature_code":"PPL",
    "gn:name":"Prolay",
    "gn:population":0,
    "gn:timezone":"Asia/Phnom_Penh",
    "iso:country":"KH",
    "name:khm_x_preferred":[
        "Prolay"
    ],
    "wof:name":"Prolay",
    "wof:placetype":"locality"
},
  "geometry": {"coordinates":[104.49656,13.03735],"type":"Point"}
}