{
  "type": "Feature",
  "properties": {
    "gn:admin1_code":"24.0",
    "gn:asciiname":"Koun Sat",
    "gn:country_code":"KH",
    "gn:dem":20,
    "gn:feature_class":"P",
    "gn:feature_code":"PPL",
    "gn:name":"Koun Sat",
    "gn:population":0,
    "gn:timezone":"Asia/Phnom_Penh",
    "iso:country":"KH",
    "name:khm_x_preferred":[
        "Koun Sat"
    ],
    "wof:name":"Koun Sat",
    "wof:placetype":"locality"
},
  "geometry": {"coordinates":[104.06263,13.31375],"type":"Point"}
}