{
  "type": "Feature",
  "properties": {
    "gn:admin1_code":"29",
    "gn:asciiname":"Phum Tuol Svay",
    "gn:country_code":"KH",
    "gn:dem":20,
    "gn:feature_class":"P",
    "gn:feature_code":"PPL",
    "gn:name":"Phum Tu\u014fl Svay",
    "gn:population":0,
    "gn:timezone":"Asia/Phnom_Penh",
    "iso:country":"KH",
    "name:khm_x_preferred":[
        "Phum Tu\u014fl Svay"
    ],
    "name:khm_x_variant":[
        "\u1797\u17bc\u1798\u17b7 \u1791\u17bd\u179b\u179f\u17d2\u179c\u17b6\u1799"
    ],
    "wof:name":"Phum Tuol Svay",
    "wof:placetype":"locality"
},
  "geometry": {"coordinates":[103.32195,12.81079],"type":"Point"}
}