{
  "type": "Feature",
  "properties": {
    "gn:admin1_code":"14",
    "gn:asciiname":"Sena Reach Otdam",
    "gn:country_code":"KH",
    "gn:dem":9,
    "gn:feature_class":"P",
    "gn:feature_code":"PPL",
    "gn:name":"Sena Reach Otdam",
    "gn:population":0,
    "gn:timezone":"Asia/Phnom_Penh",
    "iso:country":"KH",
    "name:khm_x_preferred":[
        "Sena Reach Otdam"
    ],
    "wof:name":"Sena Reach Otdam",
    "wof:placetype":"locality"
},
  "geometry": {"coordinates":[105.41087,11.09195],"type":"Point"}
}