{
  "type": "Feature",
  "properties": {
    "gn:admin1_code":"22",
    "gn:asciiname":"Chres",
    "gn:country_code":"KH",
    "gn:dem":14,
    "gn:feature_class":"P",
    "gn:feature_code":"PPL",
    "gn:name":"Chres",
    "gn:population":0,
    "gn:timezone":"Asia/Phnom_Penh",
    "iso:country":"KH",
    "name:khm_x_preferred":[
        "Chres"
    ],
    "name:und_x_variant":[
        "Phum\u012d Chr\u00e9s"
    ],
    "wof:name":"Chres",
    "wof:placetype":"locality"
},
  "geometry": {"coordinates":[104.85339999999999,11.5921],"type":"Point"}
}