{
  "type": "Feature",
  "properties": {
    "gn:admin1_code":"04",
    "gn:asciiname":"Ou Angkum",
    "gn:country_code":"KH",
    "gn:dem":95,
    "gn:feature_class":"P",
    "gn:feature_code":"PPL",
    "gn:name":"Ou Angkum",
    "gn:population":0,
    "gn:timezone":"Asia/Phnom_Penh",
    "iso:country":"KH",
    "name:khm_x_preferred":[
        "Ou Angkum"
    ],
    "wof:name":"Ou Angkum",
    "wof:placetype":"locality"
},
  "geometry": {"coordinates":[104.32238,11.81189],"type":"Point"}
}