{
  "type": "Feature",
  "properties": {
    "gn:admin1_code":"3.0",
    "gn:asciiname":"Phum Snao",
    "gn:country_code":"KH",
    "gn:dem":22,
    "gn:feature_class":"P",
    "gn:feature_code":"PPL",
    "gn:name":"Phum Sna\u00f4",
    "gn:population":0,
    "gn:timezone":"Asia/Phnom_Penh",
    "iso:country":"KH",
    "name:khm_x_preferred":[
        "Phum Sna\u00f4"
    ],
    "name:khm_x_variant":[
        "\u1797\u17bc\u1798\u17b7 \u179f\u17d2\u1793\u17c4"
    ],
    "wof:name":"Phum Snao",
    "wof:placetype":"locality"
},
  "geometry": {"coordinates":[104.48005000000001,12.41062],"type":"Point"}
}