{
  "type": "Feature",
  "properties": {
    "gn:admin1_code":"23",
    "gn:asciiname":"Phumi Ba Lay",
    "gn:country_code":"KH",
    "gn:dem":227,
    "gn:feature_class":"P",
    "gn:feature_code":"PPL",
    "gn:name":"Phum\u012d B\u00e2 L\u00e2y",
    "gn:population":0,
    "gn:timezone":"Asia/Phnom_Penh",
    "iso:country":"KH",
    "name:und_x_variant":[
        "Boloy",
        "Phum\u012d B\u00e2 L\u00e2y"
    ],
    "wof:name":"Phumi Ba Lay",
    "wof:placetype":"locality"
},
  "geometry": {"coordinates":[107.19625000000001,13.83814],"type":"Point"}
}