{
  "type": "Feature",
  "properties": {
    "gn:admin1_code":"07",
    "gn:asciiname":"Ovlaok",
    "gn:country_code":"KH",
    "gn:dem":18,
    "gn:feature_class":"P",
    "gn:feature_code":"PPL",
    "gn:name":"Ovlaok",
    "gn:population":0,
    "gn:timezone":"Asia/Phnom_Penh",
    "iso:country":"KH",
    "name:khm_x_preferred":[
        "Ovlaok"
    ],
    "wof:name":"Ovlaok",
    "wof:placetype":"locality"
},
  "geometry": {"coordinates":[104.75304,11.5682],"type":"Point"}
}