{
  "type": "Feature",
  "properties": {
    "gn:admin1_code":"31",
    "gn:asciiname":"Phumi Ponnareay",
    "gn:country_code":"KH",
    "gn:dem":27,
    "gn:feature_class":"P",
    "gn:feature_code":"PPL",
    "gn:name":"Phum\u012d P\u00f4nn\u00e2r\u00e9ay",
    "gn:population":0,
    "gn:timezone":"Asia/Phnom_Penh",
    "iso:country":"KH",
    "name:und_x_variant":[
        "Phum Ponnoreay",
        "Phum Ponnorday",
        "Phum\u012d P\u00f4nn\u00e2r\u00e9ay"
    ],
    "wof:name":"Phumi Ponnareay",
    "wof:placetype":"locality"
},
  "geometry": {"coordinates":[105.69391,11.88776],"type":"Point"}
}