{
  "type": "Feature",
  "properties": {
    "gn:admin1_code":"22",
    "gn:asciiname":"Phumi Kbal Kaoh Leu",
    "gn:country_code":"KH",
    "gn:dem":8,
    "gn:feature_class":"P",
    "gn:feature_code":"PPL",
    "gn:name":"Phum\u012d Kbal Ka\u00f4h Leu",
    "gn:population":0,
    "gn:timezone":"Asia/Phnom_Penh",
    "iso:country":"KH",
    "name:und_x_variant":[
        "Khbal Kos",
        "Phum\u012d Kbal Ka\u00f4h Leu"
    ],
    "wof:name":"Phumi Kbal Kaoh Leu",
    "wof:placetype":"locality"
},
  "geometry": {"coordinates":[104.95511999999999,11.68664],"type":"Point"}
}