{
  "type": "Feature",
  "properties": {
    "gn:admin1_code":"25",
    "gn:asciiname":"Baray",
    "gn:country_code":"KH",
    "gn:dem":26,
    "gn:feature_class":"P",
    "gn:feature_code":"PPL",
    "gn:name":"Baray",
    "gn:population":0,
    "gn:timezone":"Asia/Phnom_Penh",
    "iso:country":"KH",
    "name:khm_x_preferred":[
        "Baray"
    ],
    "name:khm_x_variant":[
        "\u1797\u17bc\u1798\u17b7 \u1794\u17b6\u179a\u17b6\u1799",
        "Phum Baray"
    ],
    "name:und_x_variant":[
        "Phum\u012d Baray"
    ],
    "wof:name":"Baray",
    "wof:placetype":"locality"
},
  "geometry": {"coordinates":[103.02392999999999,13.74329],"type":"Point"}
}