{
  "type": "Feature",
  "properties": {
    "gn:admin1_code":"25",
    "gn:asciiname":"Baray",
    "gn:country_code":"KH",
    "gn:dem":26,
    "gn:feature_class":"P",
    "gn:feature_code":"PPL",
    "gn:name":"Baray",
    "gn:population":0,
    "gn:timezone":"Asia/Phnom_Penh",
    "iso:country":"KH",
    "name:afr_x_preferred":[
        "Baray"
    ],
    "name:deu_x_preferred":[
        "Baray"
    ],
    "name:fin_x_preferred":[
        "Baray"
    ],
    "name:fra_x_preferred":[
        "Baray"
    ],
    "name:ind_x_preferred":[
        "Baray"
    ],
    "name:ita_x_preferred":[
        "Baray"
    ],
    "name:jpn_x_preferred":[
        "\u30d0\u30e9\u30a4"
    ],
    "name:khm_x_preferred":[
        "Baray"
    ],
    "name:khm_x_variant":[
        "\u1797\u17bc\u1798\u17b7 \u1794\u17b6\u179a\u17b6\u1799",
        "Phum Baray"
    ],
    "name:msa_x_preferred":[
        "Baray"
    ],
    "name:rus_x_preferred":[
        "\u0411\u0430\u0440\u0430\u0439"
    ],
    "name:spa_x_preferred":[
        "Baray"
    ],
    "name:tha_x_preferred":[
        "\u0e1a\u0e32\u0e23\u0e32\u0e22"
    ],
    "name:ukr_x_preferred":[
        "\u0411\u0430\u0440\u0430\u0439"
    ],
    "name:und_x_variant":[
        "Phum\u012d Baray"
    ],
    "name:war_x_preferred":[
        "Baray"
    ],
    "wof:name":"Baray",
    "wof:placetype":"locality"
},
  "geometry": {"coordinates":[103.02392999999999,13.74329],"type":"Point"}
}