{
  "type": "Feature",
  "properties": {
    "gn:admin1_code":"31",
    "gn:asciiname":"Phum Ti Muoy",
    "gn:country_code":"KH",
    "gn:dem":26,
    "gn:feature_class":"P",
    "gn:feature_code":"PPL",
    "gn:name":"Phum Ti Muoy",
    "gn:population":0,
    "gn:timezone":"Asia/Phnom_Penh",
    "iso:country":"KH",
    "name:khm_x_preferred":[
        "Phum Ti Muoy"
    ],
    "wof:name":"Phum Ti Muoy",
    "wof:placetype":"locality"
},
  "geometry": {"coordinates":[105.68707000000001,12.25594],"type":"Point"}
}