{
  "type": "Feature",
  "properties": {
    "gn:admin1_code":"12",
    "gn:asciiname":"Phumi Kampeng",
    "gn:country_code":"KH",
    "gn:dem":33,
    "gn:feature_class":"P",
    "gn:feature_code":"PPL",
    "gn:name":"Phum\u012d K\u00e2mp\u00eang",
    "gn:population":0,
    "gn:timezone":"Asia/Phnom_Penh",
    "iso:country":"KH",
    "name:und_x_variant":[
        "Kompeng",
        "Kompong",
        "Phum\u012d K\u00e2mp\u00eang"
    ],
    "wof:name":"Phumi Kampeng",
    "wof:placetype":"locality"
},
  "geometry": {"coordinates":[103.81401,12.4163],"type":"Point"}
}