{
  "type": "Feature",
  "properties": {
    "gn:admin1_code":"24.0",
    "gn:asciiname":"Preaek Angkor Thmei",
    "gn:country_code":"KH",
    "gn:dem":16,
    "gn:feature_class":"P",
    "gn:feature_code":"PPL",
    "gn:name":"Preaek Angkor Thmei",
    "gn:population":0,
    "gn:timezone":"Asia/Phnom_Penh",
    "iso:country":"KH",
    "name:khm_x_preferred":[
        "Preaek Angkor Thmei"
    ],
    "wof:name":"Preaek Angkor Thmei",
    "wof:placetype":"locality"
},
  "geometry": {"coordinates":[104.26517,13.05316],"type":"Point"}
}