{
  "type": "Feature",
  "properties": {
    "gn:admin1_code":"27",
    "gn:asciiname":"Phum Bos",
    "gn:country_code":"KH",
    "gn:dem":65,
    "gn:feature_class":"P",
    "gn:feature_code":"PPL",
    "gn:name":"Phum B\u014fs",
    "gn:population":0,
    "gn:timezone":"Asia/Phnom_Penh",
    "iso:country":"KH",
    "name:khm_x_preferred":[
        "Phum B\u014fs"
    ],
    "name:khm_x_variant":[
        "Phum\u012d B\u014fs"
    ],
    "wof:name":"Phum Bos",
    "wof:placetype":"locality"
},
  "geometry": {"coordinates":[103.70742,14.27688],"type":"Point"}
}