{
  "type": "Feature",
  "properties": {
    "gn:admin1_code":"03",
    "gn:asciiname":"Phumi Peam",
    "gn:country_code":"KH",
    "gn:dem":44,
    "gn:feature_class":"P",
    "gn:feature_code":"PPL",
    "gn:name":"Phum\u012d P\u00e9am",
    "gn:population":0,
    "gn:timezone":"Asia/Phnom_Penh",
    "iso:country":"KH",
    "name:und_x_variant":[
        "Peam",
        "Phum\u012d P\u00e9am"
    ],
    "wof:name":"Phumi Peam",
    "wof:placetype":"locality"
},
  "geometry": {"coordinates":[104.50355999999999,12.13054],"type":"Point"}
}