{
  "type": "Feature",
  "properties": {
    "gn:admin1_code":"14",
    "gn:asciiname":"Pou",
    "gn:country_code":"KH",
    "gn:dem":7,
    "gn:feature_class":"P",
    "gn:feature_code":"PPL",
    "gn:name":"Pou",
    "gn:population":0,
    "gn:timezone":"Asia/Phnom_Penh",
    "iso:country":"KH",
    "name:khm_x_preferred":[
        "Pou"
    ],
    "wof:name":"Pou",
    "wof:placetype":"locality"
},
  "geometry": {"coordinates":[105.44143,11.13848],"type":"Point"}
}