{
  "type": "Feature",
  "properties": {
    "gn:admin1_code":"29",
    "gn:asciiname":"Phumi Boeng Sleb",
    "gn:country_code":"KH",
    "gn:dem":35,
    "gn:feature_class":"P",
    "gn:feature_code":"PPL",
    "gn:name":"Phum\u012d B\u0153\u0306ng Sl\u0115b",
    "gn:population":0,
    "gn:timezone":"Asia/Phnom_Penh",
    "iso:country":"KH",
    "name:und_x_variant":[
        "Phum\u012d B\u0153\u0306ng Slep",
        "Phum\u012d B\u0153\u0306ng Sl\u0115b"
    ],
    "wof:name":"Phumi Boeng Sleb",
    "wof:placetype":"locality"
},
  "geometry": {"coordinates":[102.83515,13.19962],"type":"Point"}
}