{
  "type": "Feature",
  "properties": {
    "gn:admin1_code":"29",
    "gn:asciiname":"Phum Chhvea Toch",
    "gn:country_code":"KH",
    "gn:dem":18,
    "gn:feature_class":"P",
    "gn:feature_code":"PPL",
    "gn:name":"Phum Chhv\u00eaa Toch",
    "gn:population":0,
    "gn:timezone":"Asia/Phnom_Penh",
    "iso:country":"KH",
    "name:khm_x_preferred":[
        "Phum Chhv\u00eaa Toch"
    ],
    "name:khm_x_variant":[
        "\u1797\u17bc\u1798\u17b7 \u1787\u17d2\u179c\u17b6\u178f\u17bc\u1785"
    ],
    "wof:name":"Phum Chhvea Toch",
    "wof:placetype":"locality"
},
  "geometry": {"coordinates":[103.21084999999999,13.11524],"type":"Point"}
}