{
  "type": "Feature",
  "properties": {
    "gn:admin1_code":"09",
    "gn:asciiname":"Phum Andong Tor",
    "gn:country_code":"KH",
    "gn:dem":28,
    "gn:feature_class":"P",
    "gn:feature_code":"PPL",
    "gn:name":"Phum \u00c2ndong T\u00f4r",
    "gn:population":0,
    "gn:timezone":"Asia/Phnom_Penh",
    "iso:country":"KH",
    "name:khm_x_preferred":[
        "Phum \u00c2ndong T\u00f4r"
    ],
    "name:khm_x_variant":[
        "\u1797\u17bc\u1798\u17b7 \u17a2\u178e\u17d2\u178f\u17bc\u1784\u1791\u179a"
    ],
    "name:und_x_variant":[
        "Phum Andon Tor"
    ],
    "wof:name":"Phum Andong Tor",
    "wof:placetype":"locality"
},
  "geometry": {"coordinates":[106.05967,12.26515],"type":"Point"}
}