{
  "type": "Feature",
  "properties": {
    "gn:admin1_code":"13",
    "gn:asciiname":"Sangkae Roung",
    "gn:country_code":"KH",
    "gn:dem":78,
    "gn:feature_class":"P",
    "gn:feature_code":"PPL",
    "gn:name":"Sangkae Roung",
    "gn:population":0,
    "gn:timezone":"Asia/Phnom_Penh",
    "iso:country":"KH",
    "name:khm_x_preferred":[
        "Sangkae Roung"
    ],
    "name:und_x_variant":[
        "Phum S\u00e2ngkerung",
        "Phum\u012d S\u00e2ngk\u00eara\u00f4ng",
        "Phum\u012d S\u00e2ngk\u00ea Ro\u016dng"
    ],
    "wof:name":"Sangkae Roung",
    "wof:placetype":"locality"
},
  "geometry": {"coordinates":[105.13511,13.35669],"type":"Point"}
}