{
  "type": "Feature",
  "properties": {
    "gn:admin1_code":"19",
    "gn:asciiname":"Phumi Sla",
    "gn:country_code":"KH",
    "gn:dem":12,
    "gn:feature_class":"P",
    "gn:feature_code":"PPL",
    "gn:name":"Phum\u012d Sla",
    "gn:population":0,
    "gn:timezone":"Asia/Phnom_Penh",
    "iso:country":"KH",
    "name:und_x_variant":[
        "Phum Tarok",
        "Phum\u012d Sla"
    ],
    "wof:name":"Phumi Sla",
    "wof:placetype":"locality"
},
  "geometry": {"coordinates":[104.75946,11.07814],"type":"Point"}
}