{
  "type": "Feature",
  "properties": {
    "gn:admin1_code":"29",
    "gn:asciiname":"Tuol Roka",
    "gn:country_code":"KH",
    "gn:dem":15,
    "gn:feature_class":"P",
    "gn:feature_code":"PPL",
    "gn:name":"Tuol Roka",
    "gn:population":0,
    "gn:timezone":"Asia/Phnom_Penh",
    "iso:country":"KH",
    "name:khm_x_preferred":[
        "Tuol Roka"
    ],
    "wof:name":"Tuol Roka",
    "wof:placetype":"locality"
},
  "geometry": {"coordinates":[103.57617,12.67822],"type":"Point"}
}