{
  "type": "Feature",
  "properties": {
    "gn:admin1_code":"13",
    "gn:asciiname":"Phum Stung",
    "gn:country_code":"KH",
    "gn:dem":78,
    "gn:feature_class":"P",
    "gn:feature_code":"PPL",
    "gn:name":"Phum Stung",
    "gn:population":0,
    "gn:timezone":"Asia/Phnom_Penh",
    "iso:country":"KH",
    "name:und_x_variant":[
        "Phum\u012d St\u0153\u0306ng"
    ],
    "wof:name":"Phum Stung",
    "wof:placetype":"locality"
},
  "geometry": {"coordinates":[104.93136,14.21654],"type":"Point"}
}