{
  "type": "Feature",
  "properties": {
    "gn:admin1_code":"08",
    "gn:asciiname":"Phum Prek Khyang",
    "gn:country_code":"KH",
    "gn:dem":12,
    "gn:feature_class":"P",
    "gn:feature_code":"PPL",
    "gn:name":"Phum Pr\u00eak Khy\u00e2ng",
    "gn:population":0,
    "gn:timezone":"Asia/Phnom_Penh",
    "iso:country":"KH",
    "name:khm_x_preferred":[
        "Phum Pr\u00eak Khy\u00e2ng"
    ],
    "name:khm_x_variant":[
        "\u1797\u17bc\u1798\u17b7 \u1796\u17d2\u179a\u17c2\u1780\u1781\u17d2\u1799\u1784"
    ],
    "name:und_x_variant":[
        "Phum\u012d Pr\u00eak Khy\u00e2ng"
    ],
    "wof:name":"Phum Prek Khyang",
    "wof:placetype":"locality"
},
  "geometry": {"coordinates":[103.20122000000001,10.91015],"type":"Point"}
}