{
  "type": "Feature",
  "properties": {
    "gn:admin1_code":"13",
    "gn:asciiname":"Rumchek",
    "gn:country_code":"KH",
    "gn:dem":97,
    "gn:feature_class":"P",
    "gn:feature_code":"PPL",
    "gn:name":"Rumchek",
    "gn:population":0,
    "gn:timezone":"Asia/Phnom_Penh",
    "iso:country":"KH",
    "name:khm_x_preferred":[
        "Rumchek"
    ],
    "name:und_x_variant":[
        "Phum Romchek",
        "Romchek",
        "Phum\u012d Rumch\u00e9k"
    ],
    "wof:name":"Rumchek",
    "wof:placetype":"locality"
},
  "geometry": {"coordinates":[105.00311000000001,13.27925],"type":"Point"}
}