{
  "type": "Feature",
  "properties": {
    "gn:admin1_code":"17",
    "gn:asciiname":"Santepheap",
    "gn:country_code":"KH",
    "gn:dem":71,
    "gn:feature_class":"P",
    "gn:feature_code":"PPL",
    "gn:name":"Santepheap",
    "gn:population":0,
    "gn:timezone":"Asia/Phnom_Penh",
    "iso:country":"KH",
    "name:khm_x_preferred":[
        "Santepheap"
    ],
    "name:khm_x_variant":[
        "\u1783\u17bb\u17c6\u179f\u1793\u17d2\u178f\u17b7\u1797\u17b6\u1796"
    ],
    "name:spa_x_preferred":[
        "Santepheap"
    ],
    "wof:name":"Santepheap",
    "wof:placetype":"locality"
},
  "geometry": {"coordinates":[106.43585,14.17796],"type":"Point"}
}