{
  "type": "Feature",
  "properties": {
    "gn:admin1_code":"14",
    "gn:asciiname":"Phumi Koam Pradaeus",
    "gn:country_code":"KH",
    "gn:dem":13,
    "gn:feature_class":"P",
    "gn:feature_code":"PPL",
    "gn:name":"Phum\u012d K\u014f\u00e2m Pr\u00e2daeus",
    "gn:population":0,
    "gn:timezone":"Asia/Phnom_Penh",
    "iso:country":"KH",
    "name:und_x_variant":[
        "Phum Krom Padeus",
        "Phum\u012d K\u00f4m Pr\u00e2daeus",
        "Phum\u012d K\u014f\u00e2m Pr\u00e2daeus"
    ],
    "wof:name":"Phumi Koam Pradaeus",
    "wof:placetype":"locality"
},
  "geometry": {"coordinates":[105.42909,11.51584],"type":"Point"}
}