{
  "type": "Feature",
  "properties": {
    "gn:admin1_code":"12",
    "gn:asciiname":"Prey Khlong",
    "gn:country_code":"KH",
    "gn:dem":34,
    "gn:feature_class":"P",
    "gn:feature_code":"PPL",
    "gn:name":"Prey Khlong",
    "gn:population":0,
    "gn:timezone":"Asia/Phnom_Penh",
    "iso:country":"KH",
    "name:khm_x_preferred":[
        "Prey Khlong"
    ],
    "wof:name":"Prey Khlong",
    "wof:placetype":"locality"
},
  "geometry": {"coordinates":[103.76334,12.34842],"type":"Point"}
}