{
  "type": "Feature",
  "properties": {
    "gn:admin1_code":"25",
    "gn:asciiname":"Kambaor",
    "gn:country_code":"KH",
    "gn:dem":16,
    "gn:feature_class":"P",
    "gn:feature_code":"PPL",
    "gn:name":"Kambaor",
    "gn:population":0,
    "gn:timezone":"Asia/Phnom_Penh",
    "iso:country":"KH",
    "name:khm_x_preferred":[
        "Kambaor"
    ],
    "name:khm_x_variant":[
        "\u1797\u17bc\u1798\u17b7 \u1780\u17c6\u1794\u17c4\u179a",
        "Phum K\u00e2mba\u00f4r"
    ],
    "name:und_x_variant":[
        "Phum Kambor",
        "Phum Kumbor",
        "Phum\u012d K\u00e2mba\u00f4r"
    ],
    "wof:name":"Kambaor",
    "wof:placetype":"locality"
},
  "geometry": {"coordinates":[103.28583999999999,13.532],"type":"Point"}
}