{
  "type": "Feature",
  "properties": {
    "gn:admin1_code":"31",
    "gn:asciiname":"Lou",
    "gn:country_code":"KH",
    "gn:dem":94,
    "gn:feature_class":"P",
    "gn:feature_code":"PPL",
    "gn:name":"Lou",
    "gn:population":0,
    "gn:timezone":"Asia/Phnom_Penh",
    "iso:country":"KH",
    "name:ceb_x_preferred":[
        "Lou"
    ],
    "name:ces_x_preferred":[
        "Lou"
    ],
    "name:deu_x_preferred":[
        "Lou"
    ],
    "name:fin_x_preferred":[
        "Lou"
    ],
    "name:fra_x_preferred":[
        "Lou"
    ],
    "name:hat_x_preferred":[
        "Lou"
    ],
    "name:khm_x_preferred":[
        "Lou"
    ],
    "name:nld_x_preferred":[
        "Lou"
    ],
    "name:spa_x_preferred":[
        "Lou"
    ],
    "name:swe_x_preferred":[
        "Lou"
    ],
    "name:und_x_variant":[
        "Phum Lor",
        "Phum\u012d Lo\u016d",
        "Phum\u012d Lo\u016dr"
    ],
    "wof:name":"Lou",
    "wof:placetype":"locality"
},
  "geometry": {"coordinates":[106.05531999999999,11.95465],"type":"Point"}
}