{
  "type": "Feature",
  "properties": {
    "gn:admin1_code":"21",
    "gn:asciiname":"Phumi Kaoh Tasai",
    "gn:country_code":"KH",
    "gn:dem":2,
    "gn:feature_class":"P",
    "gn:feature_code":"PPL",
    "gn:name":"Phum\u012d Ka\u00f4h Tasai",
    "gn:population":0,
    "gn:timezone":"Asia/Phnom_Penh",
    "iso:country":"KH",
    "name:und_x_variant":[
        "Phum K\u00e2s Tasa",
        "Phum\u012d Ka\u00f4h Tasai"
    ],
    "wof:name":"Phumi Kaoh Tasai",
    "wof:placetype":"locality"
},
  "geometry": {"coordinates":[104.15294,10.65882],"type":"Point"}
}