{
  "type": "Feature",
  "properties": {
    "gn:admin1_code":"24",
    "gn:asciiname":"Slaeng Spean",
    "gn:country_code":"KH",
    "gn:dem":29,
    "gn:feature_class":"P",
    "gn:feature_code":"PPL",
    "gn:name":"Slaeng Spean",
    "gn:population":0,
    "gn:timezone":"Asia/Phnom_Penh",
    "iso:country":"KH",
    "name:khm_x_preferred":[
        "Slaeng Spean"
    ],
    "name:und_x_variant":[
        "Spean Sleng",
        "Phum\u012d Sl\u00eang Sp\u00e9an"
    ],
    "wof:name":"Slaeng Spean",
    "wof:placetype":"locality"
},
  "geometry": {"coordinates":[103.54804,13.8656],"type":"Point"}
}