{
  "type": "Feature",
  "properties": {
    "gn:admin1_code":"02",
    "gn:asciiname":"Phumi O Thnong",
    "gn:country_code":"KH",
    "gn:dem":36,
    "gn:feature_class":"P",
    "gn:feature_code":"PPL",
    "gn:name":"Phum\u012d O Thn\u00f3ng",
    "gn:population":0,
    "gn:timezone":"Asia/Phnom_Penh",
    "iso:country":"KH",
    "name:und_x_variant":[
        "O Thnong",
        "Phum\u012d O Thn\u016dng",
        "Phum\u012d O Thn\u00f3ng"
    ],
    "wof:name":"Phumi O Thnong",
    "wof:placetype":"locality"
},
  "geometry": {"coordinates":[105.35379,12.07445],"type":"Point"}
}