{
  "type": "Feature",
  "properties": {
    "gn:admin1_code":"17",
    "gn:asciiname":"Phumi Roneam",
    "gn:country_code":"KH",
    "gn:dem":47,
    "gn:feature_class":"P",
    "gn:feature_code":"PPL",
    "gn:name":"Phum\u012d R\u00f4n\u00e9am",
    "gn:population":0,
    "gn:timezone":"Asia/Phnom_Penh",
    "iso:country":"KH",
    "wof:name":"Phumi Roneam",
    "wof:placetype":"locality"
},
  "geometry": {"coordinates":[105.94383999999999,13.23225],"type":"Point"}
}