{
  "type": "Feature",
  "properties": {
    "gn:admin1_code":"04",
    "gn:asciiname":"Vott Chambak",
    "gn:country_code":"KH",
    "gn:dem":93,
    "gn:feature_class":"P",
    "gn:feature_code":"PPL",
    "gn:name":"V\u00f4tt Ch\u00e2mb\u00e1k",
    "gn:population":0,
    "gn:timezone":"Asia/Phnom_Penh",
    "iso:country":"KH",
    "name:und_x_variant":[
        "Vatt Ch\u00e2mb\u00e2k",
        "Vat Chambah",
        "V\u00f4tt Ch\u00e2mb\u00e1k"
    ],
    "wof:name":"Vott Chambak",
    "wof:placetype":"locality"
},
  "geometry": {"coordinates":[104.11677,11.38639],"type":"Point"}
}