{
  "type": "Feature",
  "properties": {
    "gn:admin1_code":"04",
    "gn:asciiname":"Tang Krouch",
    "gn:country_code":"KH",
    "gn:dem":44,
    "gn:feature_class":"P",
    "gn:feature_code":"PPL",
    "gn:name":"Tang Krouch",
    "gn:population":0,
    "gn:timezone":"Asia/Phnom_Penh",
    "iso:country":"KH",
    "name:khm_x_preferred":[
        "Tang Krouch"
    ],
    "wof:name":"Tang Krouch",
    "wof:placetype":"locality"
},
  "geometry": {"coordinates":[104.44271999999999,11.4503],"type":"Point"}
}