{
  "type": "Feature",
  "properties": {
    "gn:admin1_code":"14",
    "gn:asciiname":"Phumi Angkor Preah Chen",
    "gn:country_code":"KH",
    "gn:dem":6,
    "gn:feature_class":"P",
    "gn:feature_code":"PPL",
    "gn:name":"Phum\u012d \u00c2ngk\u00f4r Pre\u0103h Ch\u0115n",
    "gn:population":0,
    "gn:timezone":"Asia/Phnom_Penh",
    "iso:country":"KH",
    "wof:name":"Phumi Angkor Preah Chen",
    "wof:placetype":"locality"
},
  "geometry": {"coordinates":[105.48112,11.13278],"type":"Point"}
}