{
  "type": "Feature",
  "properties": {
    "gn:admin1_code":"17",
    "gn:asciiname":"Lon",
    "gn:country_code":"KH",
    "gn:dem":73,
    "gn:feature_class":"P",
    "gn:feature_code":"PPL",
    "gn:name":"Lon",
    "gn:population":0,
    "gn:timezone":"Asia/Phnom_Penh",
    "iso:country":"KH",
    "name:ceb_x_preferred":[
        "Lon"
    ],
    "name:dan_x_preferred":[
        "L\u00f8n"
    ],
    "name:deu_x_preferred":[
        "Lon"
    ],
    "name:khm_x_preferred":[
        "Lon"
    ],
    "name:rus_x_preferred":[
        "\u041b\u043e\u043d"
    ],
    "name:swe_x_preferred":[
        "Lon"
    ],
    "name:ukr_x_preferred":[
        "\u041b\u043e\u043d"
    ],
    "name:vie_x_preferred":[
        "Lon"
    ],
    "wof:name":"Lon",
    "wof:placetype":"locality"
},
  "geometry": {"coordinates":[106.39572,14.12055],"type":"Point"}
}