{
  "type": "Feature",
  "properties": {
    "gn:admin1_code":"27",
    "gn:asciiname":"Reangsei",
    "gn:country_code":"KH",
    "gn:dem":41,
    "gn:feature_class":"P",
    "gn:feature_code":"PPL",
    "gn:name":"Reangsei",
    "gn:population":0,
    "gn:timezone":"Asia/Phnom_Penh",
    "iso:country":"KH",
    "name:khm_x_preferred":[
        "Reangsei"
    ],
    "wof:name":"Reangsei",
    "wof:placetype":"locality"
},
  "geometry": {"coordinates":[103.28774,14.11658],"type":"Point"}
}