{
  "type": "Feature",
  "properties": {
    "gn:admin1_code":"23.0",
    "gn:asciiname":"Nhang",
    "gn:country_code":"KH",
    "gn:dem":239,
    "gn:feature_class":"P",
    "gn:feature_code":"PPL",
    "gn:name":"Nhang",
    "gn:population":0,
    "gn:timezone":"Asia/Phnom_Penh",
    "iso:country":"KH",
    "name:khm_x_preferred":[
        "Nhang"
    ],
    "wof:name":"Nhang",
    "wof:placetype":"locality"
},
  "geometry": {"coordinates":[107.37663999999999,13.97792],"type":"Point"}
}