{
  "type": "Feature",
  "properties": {
    "gn:admin1_code":"04",
    "gn:asciiname":"Phumi Pongro",
    "gn:country_code":"KH",
    "gn:dem":52,
    "gn:feature_class":"P",
    "gn:feature_code":"PPL",
    "gn:name":"Phum\u012d P\u00f4ngr\u00f4",
    "gn:population":0,
    "gn:timezone":"Asia/Phnom_Penh",
    "iso:country":"KH",
    "name:und_x_variant":[
        "Phum Pong R\u00f4",
        "Phum\u012d P\u00f4ngr\u00f4"
    ],
    "wof:name":"Phumi Pongro",
    "wof:placetype":"locality"
},
  "geometry": {"coordinates":[104.62712999999999,11.31296],"type":"Point"}
}