{
  "type": "Feature",
  "properties": {
    "gn:admin1_code":"25",
    "gn:asciiname":"Doun Chaeng",
    "gn:country_code":"KH",
    "gn:dem":16,
    "gn:feature_class":"P",
    "gn:feature_code":"PPL",
    "gn:name":"Doun Chaeng",
    "gn:population":0,
    "gn:timezone":"Asia/Phnom_Penh",
    "iso:country":"KH",
    "name:khm_x_preferred":[
        "Doun Chaeng"
    ],
    "name:khm_x_variant":[
        "Phum B\u0153\u0306ng Khle\u0103ng",
        "\u1797\u17bc\u1798\u17b7 \u1794\u17b9\u1784\u1783\u17d2\u179b\u17b6\u17c6\u1784"
    ],
    "name:und_x_variant":[
        "Phnom Don Chneng",
        "Phum Don Chneng",
        "Phum\u012d B\u0153\u0306ng Khle\u0103ng (2)"
    ],
    "wof:name":"Doun Chaeng",
    "wof:placetype":"locality"
},
  "geometry": {"coordinates":[103.15076000000001,13.51576],"type":"Point"}
}