{
  "type": "Feature",
  "properties": {
    "gn:admin1_code":"05",
    "gn:asciiname":"Prasat",
    "gn:country_code":"KH",
    "gn:dem":22,
    "gn:feature_class":"P",
    "gn:feature_code":"PPL",
    "gn:name":"Prasat",
    "gn:population":0,
    "gn:timezone":"Asia/Phnom_Penh",
    "iso:country":"KH",
    "name:khm_x_preferred":[
        "Prasat"
    ],
    "name:und_x_variant":[
        "Pr\u00e2sat And\u00e8t",
        "Prasat-Andeth Pagoda",
        "Prasath Andet",
        "Prasath Andeb",
        "Phum\u012d Pr\u00e2sat"
    ],
    "wof:name":"Prasat",
    "wof:placetype":"locality"
},
  "geometry": {"coordinates":[104.71518,12.79028],"type":"Point"}
}