{
  "type": "Feature",
  "properties": {
    "gn:admin1_code":"21",
    "gn:asciiname":"Phumi Khchang",
    "gn:country_code":"KH",
    "gn:dem":11,
    "gn:feature_class":"P",
    "gn:feature_code":"PPL",
    "gn:name":"Phum\u012d Khch\u00e2ng",
    "gn:population":0,
    "gn:timezone":"Asia/Phnom_Penh",
    "iso:country":"KH",
    "name:und_x_variant":[
        "Phum Phnom Kchang",
        "Phum\u012d Khch\u00e2ng"
    ],
    "wof:name":"Phumi Khchang",
    "wof:placetype":"locality"
},
  "geometry": {"coordinates":[104.51076999999999,10.61781],"type":"Point"}
}