{
  "type": "Feature",
  "properties": {
    "gn:admin1_code":"29",
    "gn:asciiname":"Ta Khiev",
    "gn:country_code":"KH",
    "gn:dem":37,
    "gn:feature_class":"P",
    "gn:feature_code":"PPL",
    "gn:name":"Ta Khi\u0115v",
    "gn:population":0,
    "gn:timezone":"Asia/Phnom_Penh",
    "iso:country":"KH",
    "name:und_x_variant":[
        "Phum\u012d Ta Khiev",
        "Phum Takheo",
        "Ta Khi\u0115v"
    ],
    "wof:name":"Ta Khiev",
    "wof:placetype":"locality"
},
  "geometry": {"coordinates":[102.74388,13.26338],"type":"Point"}
}