{
  "type": "Feature",
  "properties": {
    "gn:admin1_code":"12",
    "gn:asciiname":"Ta Mom",
    "gn:country_code":"KH",
    "gn:dem":17,
    "gn:feature_class":"P",
    "gn:feature_code":"PPL",
    "gn:name":"Ta Mom",
    "gn:population":0,
    "gn:timezone":"Asia/Phnom_Penh",
    "iso:country":"KH",
    "name:khm_x_preferred":[
        "Ta Mom"
    ],
    "name:khm_x_variant":[
        "\u1797\u17bc\u1798\u17b7 \u178f\u17b6\u1798\u17bb\u17c6",
        "Phum Ta Mom"
    ],
    "name:und_x_variant":[
        "P\u2019um Tam\u016dm",
        "Phum\u012d Ta Mom",
        "Phum\u012d Ta M\u016dm"
    ],
    "wof:name":"Ta Mom",
    "wof:placetype":"locality"
},
  "geometry": {"coordinates":[103.76711,12.71153],"type":"Point"}
}