{
  "type": "Feature",
  "properties": {
    "gn:admin1_code":"28",
    "gn:asciiname":"Phum Prek Kranh",
    "gn:country_code":"KH",
    "gn:dem":3,
    "gn:feature_class":"P",
    "gn:feature_code":"PPL",
    "gn:name":"Phum Pr\u00eak Kr\u0103nh",
    "gn:population":0,
    "gn:timezone":"Asia/Phnom_Penh",
    "iso:country":"KH",
    "name:khm_x_preferred":[
        "Phum Pr\u00eak Kr\u0103nh"
    ],
    "name:khm_x_variant":[
        "\u1797\u17bc\u1798\u17b7 \u1796\u17d2\u179a\u17c2\u1780\u1780\u17d2\u179a\u17b6\u1789",
        "Phum\u012d Pr\u00eak Kr\u0103nh"
    ],
    "wof:name":"Phum Prek Kranh",
    "wof:placetype":"locality"
},
  "geometry": {"coordinates":[103.84734,10.74721],"type":"Point"}
}