{
  "type": "Feature",
  "properties": {
    "gn:admin1_code":"29",
    "gn:asciiname":"Doun Ent",
    "gn:country_code":"KH",
    "gn:dem":10,
    "gn:feature_class":"P",
    "gn:feature_code":"PPL",
    "gn:name":"Doun Ent",
    "gn:population":0,
    "gn:timezone":"Asia/Phnom_Penh",
    "iso:country":"KH",
    "name:khm_x_preferred":[
        "Doun Ent"
    ],
    "wof:name":"Doun Ent",
    "wof:placetype":"locality"
},
  "geometry": {"coordinates":[103.27970000000001,13.20178],"type":"Point"}
}