{
  "type": "Feature",
  "properties": {
    "gn:admin1_code":"27",
    "gn:asciiname":"Prasat Rovieng",
    "gn:country_code":"KH",
    "gn:dem":71,
    "gn:feature_class":"P",
    "gn:feature_code":"PPL",
    "gn:name":"Prasat R\u00f4vi\u0115ng",
    "gn:population":0,
    "gn:timezone":"Asia/Phnom_Penh",
    "iso:country":"KH",
    "name:und_x_variant":[
        "Rouieng",
        "Rovieng",
        "Prasat R\u00f4vi\u0115ng"
    ],
    "wof:name":"Prasat Rovieng",
    "wof:placetype":"locality"
},
  "geometry": {"coordinates":[103.71666999999999,14.23333],"type":"Point"}
}