{
  "type": "Feature",
  "properties": {
    "gn:admin1_code":"29",
    "gn:asciiname":"Phum Spong Chrov",
    "gn:country_code":"KH",
    "gn:dem":70,
    "gn:feature_class":"P",
    "gn:feature_code":"PPL",
    "gn:name":"Phum Sp\u00f4ng Chr\u014fv",
    "gn:population":0,
    "gn:timezone":"Asia/Phnom_Penh",
    "iso:country":"KH",
    "name:khm_x_preferred":[
        "Phum Sp\u00f4ng Chr\u014fv"
    ],
    "name:khm_x_variant":[
        "\u1797\u17bc\u1798\u17b7 \u179f\u1784\u1787\u17d2\u179a\u17c4"
    ],
    "name:und_x_variant":[
        "Phum Spong Chr\u00e9ou",
        "Phum\u012d Sp\u00f3ng Chr\u014fu"
    ],
    "wof:name":"Phum Spong Chrov",
    "wof:placetype":"locality"
},
  "geometry": {"coordinates":[102.93404,12.72992],"type":"Point"}
}