{
  "type": "Feature",
  "properties": {
    "gn:admin1_code":"05",
    "gn:asciiname":"Phumi Sanlab Popok",
    "gn:country_code":"KH",
    "gn:dem":19,
    "gn:feature_class":"P",
    "gn:feature_code":"PPL",
    "gn:name":"Phum\u012d S\u00e2nl\u00e1b P\u00f4p\u00f4k",
    "gn:population":0,
    "gn:timezone":"Asia/Phnom_Penh",
    "iso:country":"KH",
    "name:und_x_variant":[
        "Lov\u00e9a Chhom",
        "Phum\u012d S\u00e2nl\u00e2p P\u00f4p\u00f4k",
        "Phum\u012d S\u00e2nl\u00f3b P\u00f4p\u00f4k",
        "Phum\u012d S\u00e2nl\u00e1b P\u00f4p\u00f4k"
    ],
    "wof:name":"Phumi Sanlab Popok",
    "wof:placetype":"locality"
},
  "geometry": {"coordinates":[104.83223,12.74905],"type":"Point"}
}