{
  "type": "Feature",
  "properties": {
    "gn:admin1_code":"19",
    "gn:asciiname":"Tram Kak",
    "gn:country_code":"KH",
    "gn:dem":14,
    "gn:feature_class":"P",
    "gn:feature_code":"PPLA2",
    "gn:name":"Tram Kak",
    "gn:population":0,
    "gn:timezone":"Asia/Phnom_Penh",
    "iso:country":"KH",
    "name:khm_x_preferred":[
        "Tram Kak"
    ],
    "wof:name":"Tram Kak",
    "wof:placetype":"locality"
},
  "geometry": {"coordinates":[104.67631,11.01173],"type":"Point"}
}