{
  "type": "Feature",
  "properties": {
    "gn:admin1_code":"13",
    "gn:asciiname":"Chhean Mukh",
    "gn:country_code":"KH",
    "gn:dem":78,
    "gn:feature_class":"P",
    "gn:feature_code":"PPL",
    "gn:name":"Chhean Mukh",
    "gn:population":0,
    "gn:timezone":"Asia/Phnom_Penh",
    "iso:country":"KH",
    "name:khm_x_preferred":[
        "Chhean Mukh"
    ],
    "wof:name":"Chhean Mukh",
    "wof:placetype":"locality"
},
  "geometry": {"coordinates":[104.89700999999999,13.78131],"type":"Point"}
}