{
  "type": "Feature",
  "properties": {
    "gn:admin1_code":"19",
    "gn:asciiname":"Beng Khtom",
    "gn:country_code":"KH",
    "gn:dem":10,
    "gn:feature_class":"P",
    "gn:feature_code":"PPL",
    "gn:name":"Beng Khtom",
    "gn:population":0,
    "gn:timezone":"Asia/Phnom_Penh",
    "iso:country":"KH",
    "name:und_x_variant":[
        "Phum\u012d B\u0153\u0306ng Khtum"
    ],
    "wof:name":"Beng Khtom",
    "wof:placetype":"locality"
},
  "geometry": {"coordinates":[104.86715,11.31367],"type":"Point"}
}