{
  "type": "Feature",
  "properties": {
    "gn:admin1_code":"04",
    "gn:asciiname":"Phumi Prey Kdei",
    "gn:country_code":"KH",
    "gn:dem":46,
    "gn:feature_class":"P",
    "gn:feature_code":"PPL",
    "gn:name":"Phum\u012d Prey Kdei",
    "gn:population":0,
    "gn:timezone":"Asia/Phnom_Penh",
    "iso:country":"KH",
    "name:und_x_variant":[
        "Prey Kdey",
        "Phum Prei Kdei",
        "Phum\u012d Prey Kdei"
    ],
    "wof:name":"Phumi Prey Kdei",
    "wof:placetype":"locality"
},
  "geometry": {"coordinates":[104.47896,11.41802],"type":"Point"}
}