{
  "type": "Feature",
  "properties": {
    "gn:admin1_code":"04",
    "gn:asciiname":"Ou Lvea",
    "gn:country_code":"KH",
    "gn:dem":84,
    "gn:feature_class":"P",
    "gn:feature_code":"PPL",
    "gn:name":"Ou Lvea",
    "gn:population":0,
    "gn:timezone":"Asia/Phnom_Penh",
    "iso:country":"KH",
    "name:khm_x_preferred":[
        "Ou Lvea"
    ],
    "wof:name":"Ou Lvea",
    "wof:placetype":"locality"
},
  "geometry": {"coordinates":[104.34648,11.33094],"type":"Point"}
}