{
  "type": "Feature",
  "properties": {
    "gn:admin1_code":"7.0",
    "gn:asciiname":"Phum Pou Miev",
    "gn:country_code":"KH",
    "gn:dem":13,
    "gn:feature_class":"P",
    "gn:feature_code":"PPL",
    "gn:name":"Phum Po\u016d Mi\u0115v",
    "gn:population":0,
    "gn:timezone":"Asia/Phnom_Penh",
    "iso:country":"KH",
    "name:khm_x_preferred":[
        "Phum Po\u016d Mi\u0115v"
    ],
    "name:khm_x_variant":[
        "\u1797\u17bc\u1798\u17b7 \u1796\u17c4\u1798\u17c0\u179c"
    ],
    "wof:name":"Phum Pou Miev",
    "wof:placetype":"locality"
},
  "geometry": {"coordinates":[105.24826000000002,11.35321],"type":"Point"}
}