{
  "type": "Feature",
  "properties": {
    "gn:admin1_code":"02",
    "gn:asciiname":"Phumi Kampong Chambak",
    "gn:country_code":"KH",
    "gn:dem":19,
    "gn:feature_class":"P",
    "gn:feature_code":"PPL",
    "gn:name":"Phum\u012d K\u00e2mp\u00f3ng Ch\u00e2mb\u00e1k",
    "gn:population":0,
    "gn:timezone":"Asia/Phnom_Penh",
    "iso:country":"KH",
    "name:und_x_variant":[
        "Phum Kompong Sam Ba",
        "Phum\u012d K\u00e2mp\u00f3ng Ch\u00e2mb\u00e1k"
    ],
    "wof:name":"Phumi Kampong Chambak",
    "wof:placetype":"locality"
},
  "geometry": {"coordinates":[105.31404000000001,11.86487],"type":"Point"}
}