{
  "type": "Feature",
  "properties": {
    "gn:admin1_code":"31",
    "gn:asciiname":"Phumi Meak Khneu",
    "gn:country_code":"KH",
    "gn:dem":122,
    "gn:feature_class":"P",
    "gn:feature_code":"PPL",
    "gn:name":"Phum\u012d Me\u0103k Khneu",
    "gn:population":0,
    "gn:timezone":"Asia/Phnom_Penh",
    "iso:country":"KH",
    "wof:name":"Phumi Meak Khneu",
    "wof:placetype":"locality"
},
  "geometry": {"coordinates":[106.31426,11.82816],"type":"Point"}
}