{
  "type": "Feature",
  "properties": {
    "gn:admin1_code":"03",
    "gn:asciiname":"Phumi La",
    "gn:country_code":"KH",
    "gn:dem":28,
    "gn:feature_class":"P",
    "gn:feature_code":"PPL",
    "gn:name":"Phum\u012d L\u00e2",
    "gn:population":0,
    "gn:timezone":"Asia/Phnom_Penh",
    "iso:country":"KH",
    "wof:name":"Phumi La",
    "wof:placetype":"locality"
},
  "geometry": {"coordinates":[104.61503999999999,12.18887],"type":"Point"}
}