{
  "type": "Feature",
  "properties": {
    "gn:admin1_code":"07",
    "gn:asciiname":"Chrey Young",
    "gn:country_code":"KH",
    "gn:dem":12,
    "gn:feature_class":"P",
    "gn:feature_code":"PPL",
    "gn:name":"Chrey Young",
    "gn:population":0,
    "gn:timezone":"Asia/Phnom_Penh",
    "iso:country":"KH",
    "name:khm_x_preferred":[
        "Chrey Young"
    ],
    "wof:name":"Chrey Young",
    "wof:placetype":"locality"
},
  "geometry": {"coordinates":[104.90048,11.39489],"type":"Point"}
}