{
  "type": "Feature",
  "properties": {
    "gn:admin1_code":"05",
    "gn:asciiname":"Ou Sala",
    "gn:country_code":"KH",
    "gn:dem":15,
    "gn:feature_class":"P",
    "gn:feature_code":"PPL",
    "gn:name":"Ou Sala",
    "gn:population":0,
    "gn:timezone":"Asia/Phnom_Penh",
    "iso:country":"KH",
    "name:khm_x_preferred":[
        "Ou Sala"
    ],
    "name:khm_x_variant":[
        "\u1797\u17bc\u1798\u17b7 \u17a2\u17bc\u179f\u17b6\u179b\u17b6"
    ],
    "name:und_x_variant":[
        "Or Srala",
        "O Srala",
        "Phum\u012d O Sala"
    ],
    "wof:name":"Ou Sala",
    "wof:placetype":"locality"
},
  "geometry": {"coordinates":[104.99878,12.73234],"type":"Point"}
}