{
  "type": "Feature",
  "properties": {
    "gn:admin1_code":"29",
    "gn:asciiname":"Phum Prey Preal Tuol Skor",
    "gn:country_code":"KH",
    "gn:dem":24,
    "gn:feature_class":"P",
    "gn:feature_code":"PPL",
    "gn:name":"Phum Prey Pr\u00e9al Tu\u014fl Sk\u00f4r",
    "gn:population":0,
    "gn:timezone":"Asia/Phnom_Penh",
    "iso:country":"KH",
    "name:khm_x_preferred":[
        "Phum Prey Pr\u00e9al Tu\u014fl Sk\u00f4r"
    ],
    "name:khm_x_variant":[
        "\u1797\u17bc\u1798\u17b7 \u1796\u17d2\u179a\u17c3\u1796\u17d2\u179a\u17b6\u179b\u1791\u17bd\u179b\u179f\u17d2\u1782\u179a"
    ],
    "wof:name":"Phum Prey Preal Tuol Skor",
    "wof:placetype":"locality"
},
  "geometry": {"coordinates":[103.47617,12.70465],"type":"Point"}
}