{
  "type": "Feature",
  "properties": {
    "gn:admin1_code":"12",
    "gn:asciiname":"Chumrum Siem",
    "gn:country_code":"KH",
    "gn:dem":24,
    "gn:feature_class":"P",
    "gn:feature_code":"PPL",
    "gn:name":"Chumrum Siem",
    "gn:population":0,
    "gn:timezone":"Asia/Phnom_Penh",
    "iso:country":"KH",
    "name:khm_x_preferred":[
        "Chumrum Siem"
    ],
    "name:khm_x_variant":[
        "\u1797\u17bc\u1798\u17b7 \u1787\u17bb\u17c6\u179a\u17c6\u179f\u17c0\u1798",
        "Phum Ch\u016dmrum Si\u0115m"
    ],
    "name:und_x_variant":[
        "Ch\u016dn\u016dm Siem",
        "Phum\u012d Ch\u016dmr\u016dm Si\u0115m"
    ],
    "wof:name":"Chumrum Siem",
    "wof:placetype":"locality"
},
  "geometry": {"coordinates":[103.85285,12.51878],"type":"Point"}
}