{
  "type": "Feature",
  "properties": {
    "gn:admin1_code":"02",
    "gn:asciiname":"Me Sa",
    "gn:country_code":"KH",
    "gn:dem":14,
    "gn:feature_class":"P",
    "gn:feature_code":"PPL",
    "gn:name":"Me Sa",
    "gn:population":0,
    "gn:timezone":"Asia/Phnom_Penh",
    "iso:country":"KH",
    "name:khm_x_preferred":[
        "Me Sa"
    ],
    "name:und_x_variant":[
        "M\u00e9sar",
        "Phum\u012d M\u00e9s\u00e2r"
    ],
    "wof:name":"Me Sa",
    "wof:placetype":"locality"
},
  "geometry": {"coordinates":[104.99081,11.8997],"type":"Point"}
}