{
  "type": "Feature",
  "properties": {
    "gn:admin1_code":"10",
    "gn:asciiname":"Phumi Khlang Mil",
    "gn:country_code":"KH",
    "gn:dem":141,
    "gn:feature_class":"P",
    "gn:feature_code":"PPL",
    "gn:name":"Phum\u012d Khl\u00e2ng M\u012dl",
    "gn:population":0,
    "gn:timezone":"Asia/Phnom_Penh",
    "iso:country":"KH",
    "name:und_x_variant":[
        "Ban Klong Mil",
        "Phum\u012d Khl\u00e2ng M\u012dl"
    ],
    "wof:name":"Phumi Khlang Mil",
    "wof:placetype":"locality"
},
  "geometry": {"coordinates":[107.17616,13.08464],"type":"Point"}
}