{
  "type": "Feature",
  "properties": {
    "gn:admin1_code":"17",
    "gn:asciiname":"Man",
    "gn:country_code":"KH",
    "gn:dem":103,
    "gn:feature_class":"P",
    "gn:feature_code":"PPL",
    "gn:name":"Man",
    "gn:population":0,
    "gn:timezone":"Asia/Phnom_Penh",
    "iso:country":"KH",
    "name:khm_x_preferred":[
        "Man"
    ],
    "name:und_x_variant":[
        "Phum\u012d M\u00f4n"
    ],
    "wof:name":"Man",
    "wof:placetype":"locality"
},
  "geometry": {"coordinates":[105.71099,13.64182],"type":"Point"}
}