{
  "type": "Feature",
  "properties": {
    "gn:admin1_code":"3.0",
    "gn:asciiname":"Phum Kraoy Vatt",
    "gn:country_code":"KH",
    "gn:dem":67,
    "gn:feature_class":"P",
    "gn:feature_code":"PPL",
    "gn:name":"Phum Kra\u00f4y Vatt",
    "gn:population":0,
    "gn:timezone":"Asia/Phnom_Penh",
    "iso:country":"KH",
    "name:khm_x_preferred":[
        "Phum Kra\u00f4y Vatt"
    ],
    "name:khm_x_variant":[
        "\u1797\u17bc\u1798 \u1780\u17d2\u179a\u17c4\u1799\u179c\u178f\u17d2\u178f"
    ],
    "wof:name":"Phum Kraoy Vatt",
    "wof:placetype":"locality"
},
  "geometry": {"coordinates":[104.47042999999999,12.03467],"type":"Point"}
}