{
  "type": "Feature",
  "properties": {
    "gn:admin1_code":"29",
    "gn:asciiname":"Prey Touch",
    "gn:country_code":"KH",
    "gn:dem":15,
    "gn:feature_class":"P",
    "gn:feature_code":"PPL",
    "gn:name":"Prey Touch",
    "gn:population":0,
    "gn:timezone":"Asia/Phnom_Penh",
    "iso:country":"KH",
    "name:khm_x_preferred":[
        "Prey Touch"
    ],
    "name:khm_x_variant":[
        "Phum Prey Toch",
        "\u1797\u17bc\u1798\u17b7 \u1796\u17d2\u179a\u17c3\u178f\u17bc\u1785",
        "\u1783\u17bb\u17c6\u1796\u17d2\u179a\u17c3\u178f\u17bc\u1785"
    ],
    "name:spa_x_preferred":[
        "Prey Touch"
    ],
    "name:und_x_variant":[
        "Phum Tr\u00f2y Toch",
        "Phum\u012d Prey Toch"
    ],
    "wof:name":"Prey Touch",
    "wof:placetype":"locality"
},
  "geometry": {"coordinates":[103.3689,12.90172],"type":"Point"}
}