{
  "type": "Feature",
  "properties": {
    "gn:admin1_code":"29",
    "gn:asciiname":"Barang Thleak",
    "gn:country_code":"KH",
    "gn:dem":196,
    "gn:feature_class":"P",
    "gn:feature_code":"PPL",
    "gn:name":"Barang Thleak",
    "gn:population":0,
    "gn:timezone":"Asia/Bangkok",
    "iso:country":"KH",
    "name:khm_x_preferred":[
        "Barang Thleak"
    ],
    "name:khm_x_variant":[
        "\u1783\u17bb\u17c6\u1794\u17b6\u179a\u17b6\u17c6\u1784\u1792\u17d2\u179b\u17b6\u1780\u17cb"
    ],
    "name:spa_x_preferred":[
        "Barang Thleak"
    ],
    "wof:name":"Barang Thleak",
    "wof:placetype":"locality"
},
  "geometry": {"coordinates":[102.35155,13.35718],"type":"Point"}
}