{
  "type": "Feature",
  "properties": {
    "gn:admin1_code":"14",
    "gn:asciiname":"Phumi Prey Pouthi",
    "gn:country_code":"KH",
    "gn:dem":19,
    "gn:feature_class":"P",
    "gn:feature_code":"PPL",
    "gn:name":"Phum\u012d Prey Po\u016dth\u012d",
    "gn:population":0,
    "gn:timezone":"Asia/Phnom_Penh",
    "iso:country":"KH",
    "name:und_x_variant":[
        "Phum Prey Phanor",
        "Phum\u012d Prey Po\u016d",
        "Phum\u012d Prey Po\u016dth\u012d"
    ],
    "wof:name":"Phumi Prey Pouthi",
    "wof:placetype":"locality"
},
  "geometry": {"coordinates":[105.36376,11.83195],"type":"Point"}
}