{
  "type": "Feature",
  "properties": {
    "gn:admin1_code":"24",
    "gn:asciiname":"Reul",
    "gn:country_code":"KH",
    "gn:dem":22,
    "gn:feature_class":"P",
    "gn:feature_code":"PPL",
    "gn:name":"Reul",
    "gn:population":0,
    "gn:timezone":"Asia/Phnom_Penh",
    "iso:country":"KH",
    "name:khm_x_preferred":[
        "Reul"
    ],
    "name:khm_x_variant":[
        "\u1797\u17bc\u1798\u17b7 \u179a\u17be\u179b",
        "Phum Reul"
    ],
    "name:und_x_variant":[
        "Roeul",
        "Phum\u012d Reul"
    ],
    "wof:name":"Reul",
    "wof:placetype":"locality"
},
  "geometry": {"coordinates":[103.73589,13.54166],"type":"Point"}
}