{
  "type": "Feature",
  "properties": {
    "gn:admin1_code":"19",
    "gn:asciiname":"Phumi Veal",
    "gn:country_code":"KH",
    "gn:dem":6,
    "gn:feature_class":"P",
    "gn:feature_code":"PPL",
    "gn:name":"Phum\u012d V\u00e9al",
    "gn:population":0,
    "gn:timezone":"Asia/Phnom_Penh",
    "iso:country":"KH",
    "name:und_x_variant":[
        "Phum Veal",
        "Phum\u012d V\u00e9al"
    ],
    "wof:name":"Phumi Veal",
    "wof:placetype":"locality"
},
  "geometry": {"coordinates":[104.80116,11.22247],"type":"Point"}
}