{
  "type": "Feature",
  "properties": {
    "gn:admin1_code":"29",
    "gn:asciiname":"Phum O Prasat",
    "gn:country_code":"KH",
    "gn:dem":15,
    "gn:feature_class":"P",
    "gn:feature_code":"PPL",
    "gn:name":"Phum O Prasat",
    "gn:population":0,
    "gn:timezone":"Asia/Phnom_Penh",
    "iso:country":"KH",
    "name:khm_x_preferred":[
        "Phum O Prasat"
    ],
    "name:khm_x_variant":[
        "\u1797\u17bc\u1798\u17b7 \u17a2\u17bc\u1794\u17d2\u179a\u17b6\u179f\u17b6\u1791"
    ],
    "name:und_x_variant":[
        "Phum\u012d O Prasat"
    ],
    "wof:name":"Phum O Prasat",
    "wof:placetype":"locality"
},
  "geometry": {"coordinates":[103.06825000000001,13.2299],"type":"Point"}
}