{
  "type": "Feature",
  "properties": {
    "gn:admin1_code":"25",
    "gn:asciiname":"Kouk Samraong",
    "gn:country_code":"KH",
    "gn:dem":15,
    "gn:feature_class":"P",
    "gn:feature_code":"PPL",
    "gn:name":"Kouk Samraong",
    "gn:population":0,
    "gn:timezone":"Asia/Phnom_Penh",
    "iso:country":"KH",
    "name:khm_x_preferred":[
        "Kouk Samraong"
    ],
    "wof:name":"Kouk Samraong",
    "wof:placetype":"locality"
},
  "geometry": {"coordinates":[102.98371,13.37775],"type":"Point"}
}