{
  "type": "Feature",
  "properties": {
    "gn:admin1_code":"04",
    "gn:asciiname":"Bos Ta Ney",
    "gn:country_code":"KH",
    "gn:dem":39,
    "gn:feature_class":"P",
    "gn:feature_code":"PPL",
    "gn:name":"Bos Ta Ney",
    "gn:population":0,
    "gn:timezone":"Asia/Phnom_Penh",
    "iso:country":"KH",
    "name:khm_x_preferred":[
        "Bos Ta Ney"
    ],
    "wof:name":"Bos Ta Ney",
    "wof:placetype":"locality"
},
  "geometry": {"coordinates":[104.47987999999999,11.4425],"type":"Point"}
}