{
  "type": "Feature",
  "properties": {
    "gn:admin1_code":"5.0",
    "gn:asciiname":"Phum Kilo Thom",
    "gn:country_code":"KH",
    "gn:dem":18,
    "gn:feature_class":"P",
    "gn:feature_code":"PPL",
    "gn:name":"Phum Kilo Thom",
    "gn:population":0,
    "gn:timezone":"Asia/Phnom_Penh",
    "iso:country":"KH",
    "name:khm_x_preferred":[
        "Phum Kilo Thom"
    ],
    "name:khm_x_variant":[
        "\u1797\u17bc\u1798\u17b7 \u1782\u17b8\u17a1\u17bc\u1792\u17c6"
    ],
    "wof:name":"Phum Kilo Thom",
    "wof:placetype":"locality"
},
  "geometry": {"coordinates":[104.4697,13.04351],"type":"Point"}
}