{
  "type": "Feature",
  "properties": {
    "gn:admin1_code":"03",
    "gn:asciiname":"Kampong Hau",
    "gn:country_code":"KH",
    "gn:dem":13,
    "gn:feature_class":"P",
    "gn:feature_code":"PPL",
    "gn:name":"Kampong Hau",
    "gn:population":0,
    "gn:timezone":"Asia/Phnom_Penh",
    "iso:country":"KH",
    "name:khm_x_preferred":[
        "Kampong Hau"
    ],
    "name:und_x_variant":[
        "Kompong Hau",
        "Phum\u012d K\u00e2mp\u00f3ng Hau"
    ],
    "wof:name":"Kampong Hau",
    "wof:placetype":"locality"
},
  "geometry": {"coordinates":[104.72414999999999,12.27386],"type":"Point"}
}