{
  "type": "Feature",
  "properties": {
    "gn:admin1_code":"04",
    "gn:asciiname":"Boeng Tonloab",
    "gn:country_code":"KH",
    "gn:dem":40,
    "gn:feature_class":"P",
    "gn:feature_code":"PPL",
    "gn:name":"Boeng Tonloab",
    "gn:population":0,
    "gn:timezone":"Asia/Phnom_Penh",
    "iso:country":"KH",
    "name:khm_x_preferred":[
        "Boeng Tonloab"
    ],
    "wof:name":"Boeng Tonloab",
    "wof:placetype":"locality"
},
  "geometry": {"coordinates":[104.53115,11.511],"type":"Point"}
}