{
  "type": "Feature",
  "properties": {
    "gn:admin1_code":"02",
    "gn:asciiname":"Srangae",
    "gn:country_code":"KH",
    "gn:dem":15,
    "gn:feature_class":"P",
    "gn:feature_code":"PPL",
    "gn:name":"Srangae",
    "gn:population":0,
    "gn:timezone":"Asia/Phnom_Penh",
    "iso:country":"KH",
    "name:khm_x_preferred":[
        "Srangae"
    ],
    "name:und_x_variant":[
        "Phum Sra Nge",
        "Phum\u012d Sr\u00e2ng\u00ea"
    ],
    "wof:name":"Srangae",
    "wof:placetype":"locality"
},
  "geometry": {"coordinates":[105.14391999999999,12.05524],"type":"Point"}
}