{
  "type": "Feature",
  "properties": {
    "gn:admin1_code":"25",
    "gn:asciiname":"Ta Lam",
    "gn:country_code":"KH",
    "gn:dem":16,
    "gn:feature_class":"P",
    "gn:feature_code":"PPL",
    "gn:name":"Ta Lam",
    "gn:population":0,
    "gn:timezone":"Asia/Phnom_Penh",
    "iso:country":"KH",
    "name:khm_x_preferred":[
        "Ta Lam"
    ],
    "name:khm_x_variant":[
        "Phum Tal\u00e2m K\u00e2ndal",
        "\u1797\u17bc\u1798\u17b7 \u178f\u17b6\u17a1\u17c6\u1780\u178e\u17d2\u178a\u17b6\u179b",
        "\u1783\u17bb\u17c6\u178f\u17b6\u17a1\u17c6"
    ],
    "name:pol_x_preferred":[
        "Ta Lam"
    ],
    "name:spa_x_preferred":[
        "Ta Lam"
    ],
    "name:und_x_variant":[
        "Khum Talam",
        "Phum\u012d Tal\u00e2m K\u00e2ndal"
    ],
    "wof:name":"Ta Lam",
    "wof:placetype":"locality"
},
  "geometry": {"coordinates":[103.05612000000001,13.51615],"type":"Point"}
}