{
  "type": "Feature",
  "properties": {
    "gn:admin1_code":"29",
    "gn:asciiname":"Chrey Sema",
    "gn:country_code":"KH",
    "gn:dem":132,
    "gn:feature_class":"P",
    "gn:feature_code":"PPL",
    "gn:name":"Chrey Sema",
    "gn:population":0,
    "gn:timezone":"Asia/Bangkok",
    "iso:country":"KH",
    "name:khm_x_preferred":[
        "Chrey Sema"
    ],
    "wof:name":"Chrey Sema",
    "wof:placetype":"locality"
},
  "geometry": {"coordinates":[102.35974,13.47222],"type":"Point"}
}