{
  "type": "Feature",
  "properties": {
    "gn:admin1_code":"29",
    "gn:asciiname":"Chrey Sema",
    "gn:country_code":"KH",
    "gn:dem":132,
    "gn:feature_class":"P",
    "gn:feature_code":"PPL",
    "gn:name":"Chrey Sema",
    "gn:population":0,
    "gn:timezone":"Asia/Bangkok",
    "iso:country":"KH",
    "name:khm_x_preferred":[
        "Chrey Sema"
    ],
    "name:khm_x_variant":[
        "\u1783\u17bb\u17c6\u1787\u17d2\u179a\u17c3\u179f\u17b8\u1798\u17b6"
    ],
    "name:spa_x_preferred":[
        "Chrey Seima"
    ],
    "wof:name":"Chrey Sema",
    "wof:placetype":"locality"
},
  "geometry": {"coordinates":[102.35974,13.47222],"type":"Point"}
}