{
  "type": "Feature",
  "properties": {
    "gn:admin1_code":"25",
    "gn:asciiname":"Ta Sal",
    "gn:country_code":"KH",
    "gn:dem":19,
    "gn:feature_class":"P",
    "gn:feature_code":"PPL",
    "gn:name":"Ta Sal",
    "gn:population":0,
    "gn:timezone":"Asia/Phnom_Penh",
    "iso:country":"KH",
    "name:khm_x_preferred":[
        "Ta Sal"
    ],
    "name:und_x_variant":[
        "Tasal",
        "Phum\u012d Ta S\u00e2",
        "Phum\u012d Ta S\u00e1l"
    ],
    "wof:name":"Ta Sal",
    "wof:placetype":"locality"
},
  "geometry": {"coordinates":[102.93165999999999,13.42173],"type":"Point"}
}