{
  "type": "Feature",
  "properties": {
    "gn:admin1_code":"03",
    "gn:asciiname":"Phumi Anlung Pring",
    "gn:country_code":"KH",
    "gn:dem":62,
    "gn:feature_class":"P",
    "gn:feature_code":"PPL",
    "gn:name":"Phum\u012d \u00c2nl\u016dng Pring",
    "gn:population":0,
    "gn:timezone":"Asia/Phnom_Penh",
    "iso:country":"KH",
    "name:und_x_variant":[
        "Prey Nh\u00e9an",
        "Phum\u012d \u00c2nl\u016dng Pring"
    ],
    "wof:name":"Phumi Anlung Pring",
    "wof:placetype":"locality"
},
  "geometry": {"coordinates":[104.44875999999999,11.75802],"type":"Point"}
}