{
  "type": "Feature",
  "properties": {
    "gn:admin1_code":"07",
    "gn:asciiname":"Svay Otdam",
    "gn:country_code":"KH",
    "gn:dem":30,
    "gn:feature_class":"P",
    "gn:feature_code":"PPL",
    "gn:name":"Svay Otdam",
    "gn:population":0,
    "gn:timezone":"Asia/Phnom_Penh",
    "iso:country":"KH",
    "name:khm_x_preferred":[
        "Svay Otdam"
    ],
    "wof:name":"Svay Otdam",
    "wof:placetype":"locality"
},
  "geometry": {"coordinates":[104.69129,11.52637],"type":"Point"}
}