{
  "type": "Feature",
  "properties": {
    "gn:admin1_code":"12.0",
    "gn:asciiname":"Phum Sdok Svay Thmei",
    "gn:country_code":"KH",
    "gn:dem":23,
    "gn:feature_class":"P",
    "gn:feature_code":"PPL",
    "gn:name":"Phum Sd\u014fk Svay Thmei",
    "gn:population":0,
    "gn:timezone":"Asia/Phnom_Penh",
    "iso:country":"KH",
    "name:khm_x_preferred":[
        "Phum Sd\u014fk Svay Thmei"
    ],
    "name:khm_x_variant":[
        "\u1797\u17bc\u1798\u17b7 \u179f\u17d2\u178a\u17bb\u1780\u179f\u17d2\u179c\u17b6\u1799\u1790\u17d2\u1798\u17b8"
    ],
    "wof:name":"Phum Sdok Svay Thmei",
    "wof:placetype":"locality"
},
  "geometry": {"coordinates":[103.83332,12.58538],"type":"Point"}
}