{
  "type": "Feature",
  "properties": {
    "gn:admin1_code":"02",
    "gn:asciiname":"Phumi Khtum",
    "gn:country_code":"KH",
    "gn:dem":16,
    "gn:feature_class":"P",
    "gn:feature_code":"PPL",
    "gn:name":"Phum\u012d Kht\u016dm",
    "gn:population":0,
    "gn:timezone":"Asia/Phnom_Penh",
    "iso:country":"KH",
    "name:und_x_variant":[
        "Khtuom",
        "Phum\u012d Kht\u016dm"
    ],
    "wof:name":"Phumi Khtum",
    "wof:placetype":"locality"
},
  "geometry": {"coordinates":[105.06435999999999,11.92072],"type":"Point"}
}