{
  "type": "Feature",
  "properties": {
    "gn:admin1_code":"04",
    "gn:asciiname":"Thnal Bambaek",
    "gn:country_code":"KH",
    "gn:dem":92,
    "gn:feature_class":"P",
    "gn:feature_code":"PPL",
    "gn:name":"Thnal Bambaek",
    "gn:population":0,
    "gn:timezone":"Asia/Phnom_Penh",
    "iso:country":"KH",
    "name:khm_x_preferred":[
        "Thnal Bambaek"
    ],
    "wof:name":"Thnal Bambaek",
    "wof:placetype":"locality"
},
  "geometry": {"coordinates":[104.33358,11.80588],"type":"Point"}
}