{
  "type": "Feature",
  "properties": {
    "gn:admin1_code":"9.0",
    "gn:asciiname":"Phum O Thngar",
    "gn:country_code":"KH",
    "gn:dem":94,
    "gn:feature_class":"P",
    "gn:feature_code":"PPL",
    "gn:name":"Phum O Thng\u00e2r",
    "gn:population":0,
    "gn:timezone":"Asia/Phnom_Penh",
    "iso:country":"KH",
    "name:khm_x_preferred":[
        "Phum O Thng\u00e2r"
    ],
    "name:khm_x_variant":[
        "\u1797\u17bc\u1798\u17b7 \u17a2\u17bc\u1790\u17d2\u1784\u179a"
    ],
    "wof:name":"Phum O Thngar",
    "wof:placetype":"locality"
},
  "geometry": {"coordinates":[106.42789,12.03629],"type":"Point"}
}