{
  "type": "Feature",
  "properties": {
    "gn:admin1_code":"08",
    "gn:asciiname":"Srae Ambel",
    "gn:country_code":"KH",
    "gn:dem":16,
    "gn:feature_class":"P",
    "gn:feature_code":"PPLA2",
    "gn:name":"Srae Ambel",
    "gn:population":0,
    "gn:timezone":"Asia/Phnom_Penh",
    "iso:country":"KH",
    "name:fas_x_preferred":[
        "\u0633\u0631\u0647\u200c\u0622\u0645\u0628\u0644"
    ],
    "name:fra_x_preferred":[
        "Sre Ambel"
    ],
    "name:khm_x_preferred":[
        "Srae Ambel"
    ],
    "name:und_x_variant":[
        "Phum\u012d Sr\u00ea \u00c2mbel",
        "Sre Umbell",
        "Phum Sre Ambel",
        "Sreumbel",
        "Sr\u00ea \u00c2mb\u0115l"
    ],
    "wof:name":"Srae Ambel",
    "wof:placetype":"locality"
},
  "geometry": {"coordinates":[103.75382999999999,11.12212],"type":"Point"}
}