{
  "type": "Feature",
  "properties": {
    "gn:admin1_code":"02",
    "gn:asciiname":"Phumi Vihear Thum",
    "gn:country_code":"KH",
    "gn:dem":23,
    "gn:feature_class":"P",
    "gn:feature_code":"PPL",
    "gn:name":"Phum\u012d Vih\u00e9ar Thum",
    "gn:population":0,
    "gn:timezone":"Asia/Phnom_Penh",
    "iso:country":"KH",
    "name:und_x_variant":[
        "Phum\u012d Vih\u00e9a Thom",
        "Phum\u012d Vih\u00e9ar Thum"
    ],
    "wof:name":"Phumi Vihear Thum",
    "wof:placetype":"locality"
},
  "geometry": {"coordinates":[105.37085999999999,12.00303],"type":"Point"}
}