{
  "type": "Feature",
  "properties": {
    "gn:admin1_code":"24.0",
    "gn:asciiname":"Phum Kop",
    "gn:country_code":"KH",
    "gn:dem":18,
    "gn:feature_class":"P",
    "gn:feature_code":"PPL",
    "gn:name":"Phum Kop",
    "gn:population":0,
    "gn:timezone":"Asia/Phnom_Penh",
    "iso:country":"KH",
    "name:khm_x_preferred":[
        "Phum Kop"
    ],
    "name:khm_x_variant":[
        "\u1797\u17bc\u1798\u17b7 \u1780\u17bc\u1794"
    ],
    "wof:name":"Phum Kop",
    "wof:placetype":"locality"
},
  "geometry": {"coordinates":[104.01045999999999,13.31453],"type":"Point"}
}