{
  "type": "Feature",
  "properties": {
    "gn:admin1_code":"21",
    "gn:asciiname":"Phumi Sre",
    "gn:country_code":"KH",
    "gn:dem":3,
    "gn:feature_class":"P",
    "gn:feature_code":"PPL",
    "gn:name":"Phum\u012d Sr\u00ea",
    "gn:population":0,
    "gn:timezone":"Asia/Phnom_Penh",
    "iso:country":"KH",
    "name:und_x_variant":[
        "Phum Sre",
        "Phum Ta Ang",
        "Phum\u012d Sr\u00ea"
    ],
    "wof:name":"Phumi Sre",
    "wof:placetype":"locality"
},
  "geometry": {"coordinates":[104.17700000000001,10.58107],"type":"Point"}
}