{
  "type": "Feature",
  "properties": {
    "gn:admin1_code":"14",
    "gn:asciiname":"Phumi Samraong",
    "gn:country_code":"KH",
    "gn:dem":9,
    "gn:feature_class":"P",
    "gn:feature_code":"PPL",
    "gn:name":"Phum\u012d S\u00e2mra\u00f4ng",
    "gn:population":0,
    "gn:timezone":"Asia/Phnom_Penh",
    "iso:country":"KH",
    "name:und_x_variant":[
        "Phum Samrong",
        "Phum\u012d S\u00e2mra\u00f4ng"
    ],
    "wof:name":"Phumi Samraong",
    "wof:placetype":"locality"
},
  "geometry": {"coordinates":[105.58995,11.58389],"type":"Point"}
}