{
  "type": "Feature",
  "properties": {
    "gn:admin1_code":"19",
    "gn:asciiname":"Phumi Ta Ok",
    "gn:country_code":"KH",
    "gn:dem":9,
    "gn:feature_class":"P",
    "gn:feature_code":"PPL",
    "gn:name":"Phum\u012d Ta \u014ek",
    "gn:population":0,
    "gn:timezone":"Asia/Phnom_Penh",
    "iso:country":"KH",
    "wof:name":"Phumi Ta Ok",
    "wof:placetype":"locality"
},
  "geometry": {"coordinates":[104.74003999999999,10.60349],"type":"Point"}
}