{
  "type": "Feature",
  "properties": {
    "gn:admin1_code":"09",
    "gn:asciiname":"Sambok",
    "gn:country_code":"KH",
    "gn:dem":32,
    "gn:feature_class":"P",
    "gn:feature_code":"PPL",
    "gn:name":"Sambok",
    "gn:population":0,
    "gn:timezone":"Asia/Phnom_Penh",
    "iso:country":"KH",
    "name:khm_x_preferred":[
        "Sambok"
    ],
    "name:khm_x_variant":[
        "\u179f\u17c6\u1794\u17bb\u1780"
    ],
    "name:und_x_variant":[
        "Phum\u012d S\u00e2mb\u014fk",
        "Samboc",
        "S\u00e2mb\u014fk"
    ],
    "wof:name":"Sambok",
    "wof:placetype":"locality"
},
  "geometry": {"coordinates":[106.0243,12.58325],"type":"Point"}
}