{
  "type": "Feature",
  "properties": {
    "gn:admin1_code":"29",
    "gn:asciiname":"Phum Tmat Pong",
    "gn:country_code":"KH",
    "gn:dem":14,
    "gn:feature_class":"P",
    "gn:feature_code":"PPL",
    "gn:name":"Phum Tmat P\u00f4ng",
    "gn:population":0,
    "gn:timezone":"Asia/Phnom_Penh",
    "iso:country":"KH",
    "name:khm_x_preferred":[
        "Phum Tmat P\u00f4ng"
    ],
    "name:khm_x_variant":[
        "\u1797\u17bc\u1798\u17b7 \u178f\u17d2\u1798\u17b6\u178f\u1796\u1784"
    ],
    "name:und_x_variant":[
        "Phum Thmat Pong",
        "Phum\u012d Tmat P\u00f4ng"
    ],
    "wof:name":"Phum Tmat Pong",
    "wof:placetype":"locality"
},
  "geometry": {"coordinates":[103.03824,13.3033],"type":"Point"}
}