{
  "type": "Feature",
  "properties": {
    "gn:admin1_code":"14",
    "gn:asciiname":"Stueng Slout",
    "gn:country_code":"KH",
    "gn:dem":9,
    "gn:feature_class":"P",
    "gn:feature_code":"PPL",
    "gn:name":"Stueng Slout",
    "gn:population":0,
    "gn:timezone":"Asia/Phnom_Penh",
    "iso:country":"KH",
    "name:khm_x_preferred":[
        "Stueng Slout"
    ],
    "name:und_x_variant":[
        "Phum Stung Slot",
        "Phum\u012d St\u0153\u0306ng Slot"
    ],
    "wof:name":"Stueng Slout",
    "wof:placetype":"locality"
},
  "geometry": {"coordinates":[105.3193,11.24771],"type":"Point"}
}