{
  "type": "Feature",
  "properties": {
    "gn:admin1_code":"21",
    "gn:asciiname":"Tvear Thmei",
    "gn:country_code":"KH",
    "gn:dem":33,
    "gn:feature_class":"P",
    "gn:feature_code":"PPL",
    "gn:name":"Tvear Thmei",
    "gn:population":0,
    "gn:timezone":"Asia/Phnom_Penh",
    "iso:country":"KH",
    "name:khm_x_preferred":[
        "Tvear Thmei"
    ],
    "wof:name":"Tvear Thmei",
    "wof:placetype":"locality"
},
  "geometry": {"coordinates":[104.28783,10.71521],"type":"Point"}
}