{
  "type": "Feature",
  "properties": {
    "gn:admin1_code":"09",
    "gn:asciiname":"Doung",
    "gn:country_code":"KH",
    "gn:dem":77,
    "gn:feature_class":"P",
    "gn:feature_code":"PPL",
    "gn:name":"Doung",
    "gn:population":0,
    "gn:timezone":"Asia/Phnom_Penh",
    "iso:country":"KH",
    "name:khm_x_preferred":[
        "Phum Dong"
    ],
    "name:khm_x_variant":[
        "Doung",
        "\u1797\u17bc\u1798\u17b7 \u178a\u17bc\u1784"
    ],
    "name:und_x_variant":[
        "Khum Dong"
    ],
    "wof:name":"Doung",
    "wof:placetype":"locality"
},
  "geometry": {"coordinates":[106.49103999999998,12.14961],"type":"Point"}
}