{
  "type": "Feature",
  "properties": {
    "gn:admin1_code":"12.0",
    "gn:asciiname":"Phum Roleang",
    "gn:country_code":"KH",
    "gn:dem":21,
    "gn:feature_class":"P",
    "gn:feature_code":"PPL",
    "gn:name":"Phum R\u00f4le\u0103ng",
    "gn:population":0,
    "gn:timezone":"Asia/Phnom_Penh",
    "iso:country":"KH",
    "name:khm_x_preferred":[
        "Phum R\u00f4le\u0103ng"
    ],
    "name:khm_x_variant":[
        "\u1797\u17bc\u1798\u17b7 \u179a\u179b\u17b6\u17c6\u1784"
    ],
    "wof:name":"Phum Roleang",
    "wof:placetype":"locality"
},
  "geometry": {"coordinates":[103.84911,12.5624],"type":"Point"}
}