{
  "type": "Feature",
  "properties": {
    "gn:admin1_code":"05",
    "gn:asciiname":"Phumi Tang Krang",
    "gn:country_code":"KH",
    "gn:dem":22,
    "gn:feature_class":"P",
    "gn:feature_code":"PPL",
    "gn:name":"Phum\u012d T\u0103ng Kr\u00e2ng",
    "gn:population":0,
    "gn:timezone":"Asia/Phnom_Penh",
    "iso:country":"KH",
    "wof:name":"Phumi Tang Krang",
    "wof:placetype":"locality"
},
  "geometry": {"coordinates":[105.08692000000001,12.8531],"type":"Point"}
}