{
  "type": "Feature",
  "properties": {
    "gn:admin1_code":"03",
    "gn:asciiname":"Tuol Thlok",
    "gn:country_code":"KH",
    "gn:dem":20,
    "gn:feature_class":"P",
    "gn:feature_code":"PPL",
    "gn:name":"Tuol Thlok",
    "gn:population":0,
    "gn:timezone":"Asia/Phnom_Penh",
    "iso:country":"KH",
    "name:khm_x_preferred":[
        "Tuol Thlok"
    ],
    "name:und_x_variant":[
        "Phum\u012d Tu\u014fl Thl\u00f4k"
    ],
    "wof:name":"Tuol Thlok",
    "wof:placetype":"locality"
},
  "geometry": {"coordinates":[104.52325999999999,12.375],"type":"Point"}
}