{
  "type": "Feature",
  "properties": {
    "gn:admin1_code":"28",
    "gn:asciiname":"Phum Banteay Prei Leu",
    "gn:country_code":"KH",
    "gn:dem":6,
    "gn:feature_class":"P",
    "gn:feature_code":"PPL",
    "gn:name":"Phum B\u00e2nt\u00e9ay Prei Leu",
    "gn:population":0,
    "gn:timezone":"Asia/Phnom_Penh",
    "iso:country":"KH",
    "name:khm_x_preferred":[
        "Phum B\u00e2nt\u00e9ay Prei Leu"
    ],
    "name:khm_x_variant":[
        "\u1797\u17bc\u1798\u17b7 \u1794\u1793\u17d2\u1791\u17b6\u1799\u1794\u17d2\u179a\u17b8\u179b\u17be",
        "Phum\u012d B\u00e2nt\u00e9ay Prei Leu"
    ],
    "wof:name":"Phum Banteay Prei Leu",
    "wof:placetype":"locality"
},
  "geometry": {"coordinates":[103.79295999999999,10.66896],"type":"Point"}
}