{
  "type": "Feature",
  "properties": {
    "gn:admin1_code":"19",
    "gn:asciiname":"Phumi Krang Krachang",
    "gn:country_code":"KH",
    "gn:dem":12,
    "gn:feature_class":"P",
    "gn:feature_code":"PPL",
    "gn:name":"Phum\u012d Kr\u0103ng Kr\u00e2chang",
    "gn:population":0,
    "gn:timezone":"Asia/Phnom_Penh",
    "iso:country":"KH",
    "name:und_x_variant":[
        "Krachang",
        "Phum\u012d Kr\u0103ng Kr\u00e2chang"
    ],
    "wof:name":"Phumi Krang Krachang",
    "wof:placetype":"locality"
},
  "geometry": {"coordinates":[104.86830999999999,11.23691],"type":"Point"}
}