{
  "type": "Feature",
  "properties": {
    "gn:admin1_code":"03",
    "gn:asciiname":"Phumi Ta Yuos",
    "gn:country_code":"KH",
    "gn:dem":41,
    "gn:feature_class":"P",
    "gn:feature_code":"PPL",
    "gn:name":"Phum\u012d Ta Yu\u014fs",
    "gn:population":0,
    "gn:timezone":"Asia/Phnom_Penh",
    "iso:country":"KH",
    "name:und_x_variant":[
        "Ta Yuos",
        "Phum\u012d Ta Yu\u014fs"
    ],
    "wof:name":"Phumi Ta Yuos",
    "wof:placetype":"locality"
},
  "geometry": {"coordinates":[104.50973,12.14605],"type":"Point"}
}