{
  "type": "Feature",
  "properties": {
    "gn:admin1_code":"21",
    "gn:asciiname":"Kamraeng Krasang",
    "gn:country_code":"KH",
    "gn:dem":12,
    "gn:feature_class":"P",
    "gn:feature_code":"PPL",
    "gn:name":"Kamraeng Krasang",
    "gn:population":0,
    "gn:timezone":"Asia/Phnom_Penh",
    "iso:country":"KH",
    "name:khm_x_preferred":[
        "Kamraeng Krasang"
    ],
    "wof:name":"Kamraeng Krasang",
    "wof:placetype":"locality"
},
  "geometry": {"coordinates":[104.48121,10.6575],"type":"Point"}
}