{
  "type": "Feature",
  "properties": {
    "gn:admin1_code":"07",
    "gn:asciiname":"Phumi Trach Toul",
    "gn:country_code":"KH",
    "gn:dem":19,
    "gn:feature_class":"P",
    "gn:feature_code":"PPL",
    "gn:name":"Phum\u012d Trach To\u016dl",
    "gn:population":0,
    "gn:timezone":"Asia/Phnom_Penh",
    "iso:country":"KH",
    "name:und_x_variant":[
        "Trach Tol",
        "Phum\u012d Trach To\u016dl"
    ],
    "wof:name":"Phumi Trach Toul",
    "wof:placetype":"locality"
},
  "geometry": {"coordinates":[104.75805,11.52254],"type":"Point"}
}