{
  "type": "Feature",
  "properties": {
    "gn:admin1_code":"14",
    "gn:asciiname":"Prey Kuy",
    "gn:country_code":"KH",
    "gn:dem":7,
    "gn:feature_class":"P",
    "gn:feature_code":"PPL",
    "gn:name":"Prey Kuy",
    "gn:population":0,
    "gn:timezone":"Asia/Phnom_Penh",
    "iso:country":"KH",
    "name:khm_x_preferred":[
        "Prey Kuy"
    ],
    "name:und_x_variant":[
        "Phum Prey Kouy",
        "Phum\u012d Prey K\u016dy"
    ],
    "wof:name":"Prey Kuy",
    "wof:placetype":"locality"
},
  "geometry": {"coordinates":[105.55124000000001,11.25207],"type":"Point"}
}