{
  "type": "Feature",
  "properties": {
    "gn:admin1_code":"29",
    "gn:asciiname":"Phum Anlung Vil",
    "gn:country_code":"KH",
    "gn:dem":16,
    "gn:feature_class":"P",
    "gn:feature_code":"PPL",
    "gn:name":"Phum \u00c2nl\u016dng V\u012dl",
    "gn:population":0,
    "gn:timezone":"Asia/Phnom_Penh",
    "iso:country":"KH",
    "name:khm_x_preferred":[
        "Phum \u00c2nl\u016dng V\u012dl"
    ],
    "name:khm_x_variant":[
        "\u1797\u17bc\u1798\u17b7 \u17a2\u1793\u17d2\u179b\u1784\u17cb\u179c\u17b7\u179b",
        "\u1783\u17bb\u17c6\u17a2\u1793\u17d2\u179b\u1784\u17cb\u179c\u17b7\u179b"
    ],
    "name:spa_x_preferred":[
        "Anlong Vil"
    ],
    "name:und_x_variant":[
        "Phum\u012d \u00c2nl\u016dng V\u012dl",
        "Phum\u012d \u00c2nl\u00f3ng V\u012dl"
    ],
    "wof:name":"Phum Anlung Vil",
    "wof:placetype":"locality"
},
  "geometry": {"coordinates":[103.23502999999999,13.08339],"type":"Point"}
}