{
  "type": "Feature",
  "properties": {
    "gn:admin1_code":"07",
    "gn:asciiname":"Phumi Tuol Krang",
    "gn:country_code":"KH",
    "gn:dem":7,
    "gn:feature_class":"P",
    "gn:feature_code":"PPL",
    "gn:name":"Phum\u012d Tu\u014fl Kr\u0103ng",
    "gn:population":0,
    "gn:timezone":"Asia/Phnom_Penh",
    "iso:country":"KH",
    "name:und_x_variant":[
        "Tuol Krang",
        "Phum\u012d Tu\u014fl Kr\u0103ng"
    ],
    "wof:name":"Phumi Tuol Krang",
    "wof:placetype":"locality"
},
  "geometry": {"coordinates":[104.95756000000002,11.30851],"type":"Point"}
}