{
  "type": "Feature",
  "properties": {
    "gn:admin1_code":"05",
    "gn:asciiname":"Phumi Aksar Krahay",
    "gn:country_code":"KH",
    "gn:dem":18,
    "gn:feature_class":"P",
    "gn:feature_code":"PPL",
    "gn:name":"Phum\u012d \u00c2ks\u00e2r Kr\u00e2hay",
    "gn:population":0,
    "gn:timezone":"Asia/Phnom_Penh",
    "iso:country":"KH",
    "name:und_x_variant":[
        "Ansar Kranag",
        "Ansar Kr\u00e2hay",
        "Phum\u012d \u00c2ks\u00e2r Kr\u00e2hay"
    ],
    "wof:name":"Phumi Aksar Krahay",
    "wof:placetype":"locality"
},
  "geometry": {"coordinates":[105.10406,12.86784],"type":"Point"}
}