{
  "type": "Feature",
  "properties": {
    "gn:admin1_code":"19",
    "gn:asciiname":"Phumi Angk Chruk",
    "gn:country_code":"KH",
    "gn:dem":12,
    "gn:feature_class":"P",
    "gn:feature_code":"PPL",
    "gn:name":"Phum\u012d \u00c2ngk Chruk",
    "gn:population":0,
    "gn:timezone":"Asia/Phnom_Penh",
    "iso:country":"KH",
    "name:und_x_variant":[
        "Phum Tani",
        "Phum\u012d \u00c2ng Chruk",
        "Phum\u012d \u00c2ngk Chruk"
    ],
    "wof:name":"Phumi Angk Chruk",
    "wof:placetype":"locality"
},
  "geometry": {"coordinates":[104.87962,11.0968],"type":"Point"}
}