{
  "type": "Feature",
  "properties": {
    "gn:admin1_code":"13",
    "gn:asciiname":"Rotanak",
    "gn:country_code":"KH",
    "gn:dem":51,
    "gn:feature_class":"P",
    "gn:feature_code":"PPL",
    "gn:name":"Rotanak",
    "gn:population":0,
    "gn:timezone":"Asia/Phnom_Penh",
    "iso:country":"KH",
    "name:khm_x_preferred":[
        "Rotanak"
    ],
    "name:khm_x_variant":[
        "\u179f\u1784\u17d2\u1780\u17b6\u178f\u17cb\u179a\u178f\u1793\u17c8"
    ],
    "wof:name":"Rotanak",
    "wof:placetype":"locality"
},
  "geometry": {"coordinates":[105.20752,13.34862],"type":"Point"}
}