{
  "type": "Feature",
  "properties": {
    "gn:admin1_code":"24.0",
    "gn:asciiname":"Phum Kouk Vatt",
    "gn:country_code":"KH",
    "gn:dem":29,
    "gn:feature_class":"P",
    "gn:feature_code":"PPL",
    "gn:name":"Phum Ko\u016dk Vatt",
    "gn:population":0,
    "gn:timezone":"Asia/Phnom_Penh",
    "iso:country":"KH",
    "name:khm_x_preferred":[
        "Phum Ko\u016dk Vatt"
    ],
    "name:khm_x_variant":[
        "\u1797\u17bc\u1798\u17b7 \u1782\u17c4\u1780\u179c\u178f\u17d2\u178f"
    ],
    "wof:name":"Phum Kouk Vatt",
    "wof:placetype":"locality"
},
  "geometry": {"coordinates":[103.67256,13.70033],"type":"Point"}
}