{
  "type": "Feature",
  "properties": {
    "gn:admin1_code":"19",
    "gn:asciiname":"Phumi Tnaot",
    "gn:country_code":"KH",
    "gn:dem":10,
    "gn:feature_class":"P",
    "gn:feature_code":"PPL",
    "gn:name":"Phum\u012d Tna\u00f4t",
    "gn:population":0,
    "gn:timezone":"Asia/Phnom_Penh",
    "iso:country":"KH",
    "name:und_x_variant":[
        "Phum\u012d Tha\u00f4t",
        "Phum Thnot",
        "Phum\u012d Tna\u00f4t"
    ],
    "wof:name":"Phumi Tnaot",
    "wof:placetype":"locality"
},
  "geometry": {"coordinates":[104.70923999999999,10.57184],"type":"Point"}
}