{
  "type": "Feature",
  "properties": {
    "gn:admin1_code":"18",
    "gn:asciiname":"Svay Chek",
    "gn:country_code":"KH",
    "gn:dem":7,
    "gn:feature_class":"P",
    "gn:feature_code":"PPL",
    "gn:name":"Svay Chek",
    "gn:population":0,
    "gn:timezone":"Asia/Phnom_Penh",
    "iso:country":"KH",
    "name:khm_x_preferred":[
        "Svay Chek"
    ],
    "name:und_x_variant":[
        "Vat Svai Chek",
        "Khum Vat Svai Chek",
        "Phum\u012d Svay Ch\u00e9k"
    ],
    "wof:name":"Svay Chek",
    "wof:placetype":"locality"
},
  "geometry": {"coordinates":[105.78541,11.18347],"type":"Point"}
}