{
  "type": "Feature",
  "properties": {
    "gn:admin1_code":"31",
    "gn:asciiname":"Kdol Kandal",
    "gn:country_code":"KH",
    "gn:dem":23,
    "gn:feature_class":"P",
    "gn:feature_code":"PPL",
    "gn:name":"Kdol Kandal",
    "gn:population":0,
    "gn:timezone":"Asia/Phnom_Penh",
    "iso:country":"KH",
    "name:khm_x_preferred":[
        "Kdol Kandal"
    ],
    "wof:name":"Kdol Kandal",
    "wof:placetype":"locality"
},
  "geometry": {"coordinates":[105.55476000000002,12.26222],"type":"Point"}
}