{
  "type": "Feature",
  "properties": {
    "gn:admin1_code":"29",
    "gn:asciiname":"Phumi Krala Peah",
    "gn:country_code":"KH",
    "gn:dem":22,
    "gn:feature_class":"P",
    "gn:feature_code":"PPL",
    "gn:name":"Phum\u012d Kr\u00e2la Pe\u0103h",
    "gn:population":0,
    "gn:timezone":"Asia/Phnom_Penh",
    "iso:country":"KH",
    "name:und_x_variant":[
        "Phum Krala Peas",
        "Phum\u012d Kr\u00e2la Pe\u0103h"
    ],
    "wof:name":"Phumi Krala Peah",
    "wof:placetype":"locality"
},
  "geometry": {"coordinates":[103.152,12.98516],"type":"Point"}
}