{
  "type": "Feature",
  "properties": {
    "gn:admin1_code":"29",
    "gn:asciiname":"Phum Bat Samraong",
    "gn:country_code":"KH",
    "gn:dem":14,
    "gn:feature_class":"P",
    "gn:feature_code":"PPL",
    "gn:name":"Phum B\u00e2t S\u00e2mra\u00f4ng",
    "gn:population":0,
    "gn:timezone":"Asia/Phnom_Penh",
    "iso:country":"KH",
    "name:khm_x_preferred":[
        "Phum B\u00e2t S\u00e2mra\u00f4ng"
    ],
    "name:khm_x_variant":[
        "\u1797\u17bc\u1798\u17b7 \u1794\u178f\u17cb\u179f\u17c6\u179a\u17c4\u1784"
    ],
    "name:und_x_variant":[
        "Phum\u012d B\u00e1t S\u00e2mra\u00f4ng"
    ],
    "wof:name":"Phum Bat Samraong",
    "wof:placetype":"locality"
},
  "geometry": {"coordinates":[103.36595,12.85021],"type":"Point"}
}