{
  "type": "Feature",
  "properties": {
    "gn:admin1_code":"19",
    "gn:asciiname":"Phumi Chek",
    "gn:country_code":"KH",
    "gn:dem":12,
    "gn:feature_class":"P",
    "gn:feature_code":"PPL",
    "gn:name":"Phum\u012d Ch\u00e9k",
    "gn:population":0,
    "gn:timezone":"Asia/Phnom_Penh",
    "iso:country":"KH",
    "name:und_x_variant":[
        "Phum Romchek",
        "Phum\u012d Ch\u00e9k"
    ],
    "wof:name":"Phumi Chek",
    "wof:placetype":"locality"
},
  "geometry": {"coordinates":[104.84990000000001,11.22344],"type":"Point"}
}