{
  "type": "Feature",
  "properties": {
    "gn:admin1_code":"04",
    "gn:asciiname":"Phumi Prek Kanseng",
    "gn:cc2":"KH",
    "gn:country_code":"KH",
    "gn:dem":84,
    "gn:feature_class":"P",
    "gn:feature_code":"PPL",
    "gn:name":"Phum\u012d Pr\u00eak K\u00e2ns\u00eang",
    "gn:population":0,
    "gn:timezone":"Asia/Phnom_Penh",
    "iso:country":"KH",
    "name:und_x_variant":[
        "Wat Kanseng Sam",
        "Phum\u012d Pr\u00eak K\u00e2ns\u00eang"
    ],
    "wof:name":"Phumi Prek Kanseng",
    "wof:placetype":"locality"
},
  "geometry": {"coordinates":[104.36667,11.78333],"type":"Point"}
}