{
  "type": "Feature",
  "properties": {
    "gn:admin1_code":"02",
    "gn:asciiname":"Preaek Bak",
    "gn:country_code":"KH",
    "gn:dem":19,
    "gn:feature_class":"P",
    "gn:feature_code":"PPL",
    "gn:name":"Preaek Bak",
    "gn:population":0,
    "gn:timezone":"Asia/Phnom_Penh",
    "iso:country":"KH",
    "name:khm_x_preferred":[
        "Preaek Bak"
    ],
    "name:khm_x_variant":[
        "\u1797\u17bc\u1798\u17b7 \u1796\u17d2\u179a\u17c2\u1780\u1794\u17b6\u1780\u17cb",
        "Phum\u012d Pr\u00eak B\u0103k"
    ],
    "wof:name":"Preaek Bak",
    "wof:placetype":"locality"
},
  "geometry": {"coordinates":[105.52200999999999,12.1929],"type":"Point"}
}