{
  "type": "Feature",
  "properties": {
    "gn:admin1_code":"05",
    "gn:asciiname":"Roka",
    "gn:country_code":"KH",
    "gn:dem":16,
    "gn:feature_class":"P",
    "gn:feature_code":"PPL",
    "gn:name":"Roka",
    "gn:population":0,
    "gn:timezone":"Asia/Phnom_Penh",
    "iso:country":"KH",
    "name:und_x_variant":[
        "Boka",
        "Roka",
        "Phum\u012d R\u00f4ka",
        "Phum\u012d R\u00f4kar"
    ],
    "wof:name":"Roka",
    "wof:placetype":"locality"
},
  "geometry": {"coordinates":[104.91773000000001,12.62454],"type":"Point"}
}