{
  "type": "Feature",
  "properties": {
    "gn:admin1_code":"07",
    "gn:asciiname":"S'ang Phnu",
    "gn:country_code":"KH",
    "gn:dem":10,
    "gn:feature_class":"P",
    "gn:feature_code":"PPL",
    "gn:name":"S\u2019ang Phnu",
    "gn:population":0,
    "gn:timezone":"Asia/Phnom_Penh",
    "iso:country":"KH",
    "name:khm_x_preferred":[
        "S\u2019ang Phnu"
    ],
    "wof:name":"S'ang Phnu",
    "wof:placetype":"locality"
},
  "geometry": {"coordinates":[104.96254,11.34088],"type":"Point"}
}