{
  "type": "Feature",
  "properties": {
    "gn:admin1_code":"09",
    "gn:asciiname":"Ou Preah",
    "gn:country_code":"KH",
    "gn:dem":52,
    "gn:feature_class":"P",
    "gn:feature_code":"PPL",
    "gn:name":"Ou Preah",
    "gn:population":0,
    "gn:timezone":"Asia/Phnom_Penh",
    "iso:country":"KH",
    "name:khm_x_preferred":[
        "Ou Preah"
    ],
    "name:khm_x_variant":[
        "Phum\u012d Pr\u00eak Pre\u0103h",
        "\u1797\u17bc\u1798\u17b7 \u1796\u17d2\u179a\u17c2\u1780\u1796\u17d2\u179a\u17c7"
    ],
    "wof:name":"Ou Preah",
    "wof:placetype":"locality"
},
  "geometry": {"coordinates":[106.14838,13.14971],"type":"Point"}
}