{
  "type": "Feature",
  "properties": {
    "gn:admin1_code":"25",
    "gn:asciiname":"Pongro",
    "gn:country_code":"KH",
    "gn:dem":22,
    "gn:feature_class":"P",
    "gn:feature_code":"PPL",
    "gn:name":"Pongro",
    "gn:population":0,
    "gn:timezone":"Asia/Phnom_Penh",
    "iso:country":"KH",
    "name:khm_x_preferred":[
        "\u1797\u17bc\u1798\u17b7 \u1796\u1784\u17d2\u179a"
    ],
    "name:khm_x_variant":[
        "Phum P\u00f4ngr\u00f4"
    ],
    "name:und_x_variant":[
        "Phum Pongro",
        "Phum\u012d P\u00f4ngr\u00f4 (2)"
    ],
    "wof:name":"Pongro",
    "wof:placetype":"locality"
},
  "geometry": {"coordinates":[103.32854,13.82043],"type":"Point"}
}