{
  "type": "Feature",
  "properties": {
    "gn:admin1_code":"02",
    "gn:asciiname":"Phumi Anlong",
    "gn:country_code":"KH",
    "gn:dem":21,
    "gn:feature_class":"P",
    "gn:feature_code":"PPL",
    "gn:name":"Phum\u012d \u00c2nl\u00f3ng",
    "gn:population":0,
    "gn:timezone":"Asia/Phnom_Penh",
    "iso:country":"KH",
    "wof:name":"Phumi Anlong",
    "wof:placetype":"locality"
},
  "geometry": {"coordinates":[105.45408,11.88969],"type":"Point"}
}