{
  "type": "Feature",
  "properties": {
    "gn:admin1_code":"03",
    "gn:asciiname":"Phumi Toat Baoh",
    "gn:country_code":"KH",
    "gn:dem":43,
    "gn:feature_class":"P",
    "gn:feature_code":"PPL",
    "gn:name":"Phum\u012d To\u0103t Ba\u00f4h",
    "gn:population":0,
    "gn:timezone":"Asia/Phnom_Penh",
    "iso:country":"KH",
    "name:und_x_variant":[
        "Tat Bas",
        "F\u00e2t B\u00e2s",
        "Phum\u012d To\u0103t Ba\u00f4h"
    ],
    "wof:name":"Phumi Toat Baoh",
    "wof:placetype":"locality"
},
  "geometry": {"coordinates":[104.61315,11.95751],"type":"Point"}
}