{
  "type": "Feature",
  "properties": {
    "gn:admin1_code":"19",
    "gn:asciiname":"Phumi Chrey",
    "gn:country_code":"KH",
    "gn:dem":8,
    "gn:feature_class":"P",
    "gn:feature_code":"PPL",
    "gn:name":"Phum\u012d Chrey",
    "gn:population":0,
    "gn:timezone":"Asia/Phnom_Penh",
    "iso:country":"KH",
    "name:und_x_variant":[
        "Phum Chres",
        "Phum\u012d Chrey"
    ],
    "wof:name":"Phumi Chrey",
    "wof:placetype":"locality"
},
  "geometry": {"coordinates":[104.72096000000001,10.76929],"type":"Point"}
}