{
  "type": "Feature",
  "properties": {
    "gn:admin1_code":"05",
    "gn:asciiname":"Prasat",
    "gn:country_code":"KH",
    "gn:dem":23,
    "gn:feature_class":"P",
    "gn:feature_code":"PPL",
    "gn:name":"Prasat",
    "gn:population":0,
    "gn:timezone":"Asia/Phnom_Penh",
    "iso:country":"KH",
    "name:khm_x_preferred":[
        "Prasat"
    ],
    "name:und_x_variant":[
        "Phum Prasath",
        "Phum\u012d Pr\u00e2sat (1)"
    ],
    "wof:name":"Prasat",
    "wof:placetype":"locality"
},
  "geometry": {"coordinates":[104.69589000000001,12.95582],"type":"Point"}
}