{
  "type": "Feature",
  "properties": {
    "gn:admin1_code":"04",
    "gn:asciiname":"Phumi Srei Sampoung",
    "gn:country_code":"KH",
    "gn:dem":49,
    "gn:feature_class":"P",
    "gn:feature_code":"PPL",
    "gn:name":"Phum\u012d Srei S\u00e2mpo\u016dng",
    "gn:population":0,
    "gn:timezone":"Asia/Phnom_Penh",
    "iso:country":"KH",
    "name:und_x_variant":[
        "Sre Tumpung",
        "Phum Prei Tumpung",
        "Phum\u012d Srei S\u00e2mpo\u016dng"
    ],
    "wof:name":"Phumi Srei Sampoung",
    "wof:placetype":"locality"
},
  "geometry": {"coordinates":[104.50131,11.5222],"type":"Point"}
}