{
  "type": "Feature",
  "properties": {
    "gn:admin1_code":"24",
    "gn:asciiname":"Phumi Tum Tin",
    "gn:country_code":"KH",
    "gn:dem":45,
    "gn:feature_class":"P",
    "gn:feature_code":"PPL",
    "gn:name":"Phum\u012d T\u016dm T\u012dn",
    "gn:population":0,
    "gn:timezone":"Asia/Phnom_Penh",
    "iso:country":"KH",
    "name:und_x_variant":[
        "Phum\u012d T\u014fm T\u012dn",
        "Phum\u012d T\u016dm T\u012dn"
    ],
    "wof:name":"Phumi Tum Tin",
    "wof:placetype":"locality"
},
  "geometry": {"coordinates":[103.72814,13.85172],"type":"Point"}
}