{
  "type": "Feature",
  "properties": {
    "gn:admin1_code":"21",
    "gn:asciiname":"Phumi Phnum Tnaot",
    "gn:country_code":"KH",
    "gn:dem":39,
    "gn:feature_class":"P",
    "gn:feature_code":"PPL",
    "gn:name":"Phum\u012d Phnum Tna\u00f4t",
    "gn:population":0,
    "gn:timezone":"Asia/Phnom_Penh",
    "iso:country":"KH",
    "wof:name":"Phumi Phnum Tnaot",
    "wof:placetype":"locality"
},
  "geometry": {"coordinates":[104.3215,10.8109],"type":"Point"}
}