{
  "type": "Feature",
  "properties": {
    "gn:admin1_code":"24.0",
    "gn:asciiname":"Phum Trapeang Phloah",
    "gn:country_code":"KH",
    "gn:dem":32,
    "gn:feature_class":"P",
    "gn:feature_code":"PPL",
    "gn:name":"Phum Tr\u00e2pe\u0103ng Phl\u014f\u0103h",
    "gn:population":0,
    "gn:timezone":"Asia/Phnom_Penh",
    "iso:country":"KH",
    "name:khm_x_preferred":[
        "Phum Tr\u00e2pe\u0103ng Phl\u014f\u0103h"
    ],
    "name:khm_x_variant":[
        "\u1797\u17bc\u1798\u17b7 \u178f\u17d2\u179a\u1796\u17b6\u17c6\u1784\u1797\u17d2\u179b\u17c4\u17c7"
    ],
    "wof:name":"Phum Trapeang Phloah",
    "wof:placetype":"locality"
},
  "geometry": {"coordinates":[103.66786,13.70742],"type":"Point"}
}