{
  "type": "Feature",
  "properties": {
    "gn:admin1_code":"19",
    "gn:asciiname":"Pou Doh",
    "gn:country_code":"KH",
    "gn:dem":32,
    "gn:feature_class":"P",
    "gn:feature_code":"PPL",
    "gn:name":"Pou Doh",
    "gn:population":0,
    "gn:timezone":"Asia/Phnom_Penh",
    "iso:country":"KH",
    "name:khm_x_preferred":[
        "Pou Doh"
    ],
    "name:und_x_variant":[
        "Phum\u012d Po\u016d D\u014fh",
        "Phum\u012d Po\u016dth\u012d D\u014fh"
    ],
    "wof:name":"Pou Doh",
    "wof:placetype":"locality"
},
  "geometry": {"coordinates":[104.55791000000001,11.08654],"type":"Point"}
}