{
  "type": "Feature",
  "properties": {
    "gn:admin1_code":"12",
    "gn:asciiname":"Phum Chap",
    "gn:country_code":"KH",
    "gn:dem":32,
    "gn:feature_class":"P",
    "gn:feature_code":"PPL",
    "gn:name":"Phum Ch\u00e2p",
    "gn:population":0,
    "gn:timezone":"Asia/Phnom_Penh",
    "iso:country":"KH",
    "name:khm_x_preferred":[
        "Phum Ch\u00e2p"
    ],
    "name:khm_x_variant":[
        "\u1797\u17bc\u1798\u17b7 \u1785\u1794"
    ],
    "name:und_x_variant":[
        "Phum\u012d Ch\u00e2p",
        "Phum\u012d Ch\u00e2b"
    ],
    "wof:name":"Phum Chap",
    "wof:placetype":"locality"
},
  "geometry": {"coordinates":[104.00684,12.45],"type":"Point"}
}