{
  "type": "Feature",
  "properties": {
    "gn:admin1_code":"29",
    "gn:asciiname":"Prey Chaek",
    "gn:country_code":"KH",
    "gn:dem":14,
    "gn:feature_class":"P",
    "gn:feature_code":"PPL",
    "gn:name":"Prey Chaek",
    "gn:population":0,
    "gn:timezone":"Asia/Phnom_Penh",
    "iso:country":"KH",
    "name:khm_x_preferred":[
        "Prey Chaek"
    ],
    "name:und_x_variant":[
        "Phum\u012d Prey Ch\u00e9k"
    ],
    "wof:name":"Prey Chaek",
    "wof:placetype":"locality"
},
  "geometry": {"coordinates":[103.29235,13.04669],"type":"Point"}
}