{
  "type": "Feature",
  "properties": {
    "gn:admin1_code":"29",
    "gn:asciiname":"Phum Sla Kram",
    "gn:country_code":"KH",
    "gn:dem":19,
    "gn:feature_class":"P",
    "gn:feature_code":"PPL",
    "gn:name":"Phum Sl\u00e2 Kram",
    "gn:population":0,
    "gn:timezone":"Asia/Phnom_Penh",
    "iso:country":"KH",
    "name:khm_x_preferred":[
        "Phum Sl\u00e2 Kram"
    ],
    "name:khm_x_variant":[
        "\u1797\u17bc\u1798\u17b7 \u179f\u17d2\u179b\u1780\u17d2\u179a\u17b6\u1798"
    ],
    "name:und_x_variant":[
        "Phum\u012d Sl\u00e2 Kram (1)"
    ],
    "wof:name":"Phum Sla Kram",
    "wof:placetype":"locality"
},
  "geometry": {"coordinates":[103.20063,13.04353],"type":"Point"}
}