{
  "type": "Feature",
  "properties": {
    "gn:admin1_code":"02",
    "gn:asciiname":"Lve",
    "gn:country_code":"KH",
    "gn:dem":17,
    "gn:feature_class":"P",
    "gn:feature_code":"PPL",
    "gn:name":"Lve",
    "gn:population":0,
    "gn:timezone":"Asia/Phnom_Penh",
    "iso:country":"KH",
    "name:khm_x_preferred":[
        "Lve"
    ],
    "name:und_x_variant":[
        "Phum\u012d L\u00f4v\u00e9",
        "Phum\u012d Lv\u00e9"
    ],
    "wof:name":"Lve",
    "wof:placetype":"locality"
},
  "geometry": {"coordinates":[105.36508000000001,11.85633],"type":"Point"}
}