{
  "type": "Feature",
  "properties": {
    "gn:admin1_code":"13",
    "gn:asciiname":"Dar",
    "gn:country_code":"KH",
    "gn:dem":95,
    "gn:feature_class":"P",
    "gn:feature_code":"PPL",
    "gn:name":"Dar",
    "gn:population":0,
    "gn:timezone":"Asia/Phnom_Penh",
    "iso:country":"KH",
    "name:ceb_x_preferred":[
        "Dar"
    ],
    "name:ces_x_preferred":[
        "Dar"
    ],
    "name:fra_x_preferred":[
        "Dar"
    ],
    "name:hrv_x_preferred":[
        "Dar"
    ],
    "name:khm_x_preferred":[
        "Dar"
    ],
    "name:khm_x_variant":[
        "Phum Da",
        "\u1797\u17bc\u1798\u17b7 \u178a\u17b6\u179a"
    ],
    "name:pol_x_preferred":[
        "Dar"
    ],
    "name:slk_x_preferred":[
        "Dar"
    ],
    "name:swe_x_preferred":[
        "Dar"
    ],
    "name:und_x_variant":[
        "Phum\u012d Da",
        "Phum\u012d Dar"
    ],
    "wof:name":"Dar",
    "wof:placetype":"locality"
},
  "geometry": {"coordinates":[104.92407,13.56433],"type":"Point"}
}