{
  "type": "Feature",
  "properties": {
    "gn:admin1_code":"09",
    "gn:asciiname":"Khsach Leav",
    "gn:country_code":"KH",
    "gn:dem":49,
    "gn:feature_class":"P",
    "gn:feature_code":"PPL",
    "gn:name":"Khsach Leav",
    "gn:population":0,
    "gn:timezone":"Asia/Phnom_Penh",
    "iso:country":"KH",
    "name:khm_x_preferred":[
        "Phum Sr\u00ea K\u00f4ki"
    ],
    "name:khm_x_variant":[
        "Khsach Leav",
        "\u1797\u17bc\u1798\u17b7 \u179f\u17d2\u179a\u17c2\u1782\u1782\u17b8\u179a"
    ],
    "name:und_x_variant":[
        "Sre Koki",
        "Kompong Sre Koki",
        "Phum\u012d Sr\u00ea K\u00f4kir"
    ],
    "wof:name":"Khsach Leav",
    "wof:placetype":"locality"
},
  "geometry": {"coordinates":[106.06052,13.12847],"type":"Point"}
}