{
  "type": "Feature",
  "properties": {
    "gn:admin1_code":"24.0",
    "gn:asciiname":"Trapeang Thnal",
    "gn:country_code":"KH",
    "gn:dem":15,
    "gn:feature_class":"P",
    "gn:feature_code":"PPL",
    "gn:name":"Trapeang Thnal",
    "gn:population":0,
    "gn:timezone":"Asia/Phnom_Penh",
    "iso:country":"KH",
    "name:khm_x_preferred":[
        "Trapeang Thnal"
    ],
    "wof:name":"Trapeang Thnal",
    "wof:placetype":"locality"
},
  "geometry": {"coordinates":[103.83766,13.33101],"type":"Point"}
}