{
  "type": "Feature",
  "properties": {
    "gn:admin1_code":"09",
    "gn:asciiname":"Phum Khlampe",
    "gn:country_code":"KH",
    "gn:dem":30,
    "gn:feature_class":"P",
    "gn:feature_code":"PPL",
    "gn:name":"Phum Khl\u0103mp\u00ea",
    "gn:population":0,
    "gn:timezone":"Asia/Phnom_Penh",
    "iso:country":"KH",
    "name:khm_x_preferred":[
        "Phum Khl\u0103mp\u00ea"
    ],
    "name:khm_x_variant":[
        "\u1797\u17bc\u1798\u17b7 \u1781\u17d2\u179b\u17b6\u17c6\u1794\u17c9\u17c2"
    ],
    "wof:name":"Phum Khlampe",
    "wof:placetype":"locality"
},
  "geometry": {"coordinates":[106.01788000000001,12.76977],"type":"Point"}
}