{
  "type": "Feature",
  "properties": {
    "gn:admin1_code":"24",
    "gn:asciiname":"Ta Chranieng",
    "gn:country_code":"KH",
    "gn:dem":9,
    "gn:feature_class":"P",
    "gn:feature_code":"PPL",
    "gn:name":"Ta Chranieng",
    "gn:population":0,
    "gn:timezone":"Asia/Phnom_Penh",
    "iso:country":"KH",
    "name:khm_x_preferred":[
        "Ta Chranieng"
    ],
    "wof:name":"Ta Chranieng",
    "wof:placetype":"locality"
},
  "geometry": {"coordinates":[104.12072000000001,13.10008],"type":"Point"}
}