{
  "type": "Feature",
  "properties": {
    "gn:admin1_code":"04",
    "gn:asciiname":"Phumi Andong Krasang",
    "gn:country_code":"KH",
    "gn:dem":51,
    "gn:feature_class":"P",
    "gn:feature_code":"PPL",
    "gn:name":"Phum\u012d \u00c2ndong Kr\u00e2s\u0103ng",
    "gn:population":0,
    "gn:timezone":"Asia/Phnom_Penh",
    "iso:country":"KH",
    "name:und_x_variant":[
        "Phum Andoung Kr\u00e2s\u0103ng",
        "Phum\u012d \u00c2ndong Kr\u00e2s\u0103ng"
    ],
    "wof:name":"Phumi Andong Krasang",
    "wof:placetype":"locality"
},
  "geometry": {"coordinates":[104.56274000000001,11.64987],"type":"Point"}
}