{
  "type": "Feature",
  "properties": {
    "gn:admin1_code":"14",
    "gn:asciiname":"Phum Chheu Am",
    "gn:country_code":"KH",
    "gn:dem":9,
    "gn:feature_class":"P",
    "gn:feature_code":"PPL",
    "gn:name":"Phum Chheu Am",
    "gn:population":0,
    "gn:timezone":"Asia/Phnom_Penh",
    "iso:country":"KH",
    "name:khm_x_preferred":[
        "Phum Chheu Am"
    ],
    "name:khm_x_variant":[
        "\u1797\u17bc\u1798\u17b7 \u1788\u17be\u17a2\u17b6\u1798",
        "Phum\u012d Chheu Am"
    ],
    "wof:name":"Phum Chheu Am",
    "wof:placetype":"locality"
},
  "geometry": {"coordinates":[105.42089,11.28643],"type":"Point"}
}