{
  "type": "Feature",
  "properties": {
    "gn:admin1_code":"05",
    "gn:asciiname":"Bou Pueng",
    "gn:country_code":"KH",
    "gn:dem":16,
    "gn:feature_class":"P",
    "gn:feature_code":"PPL",
    "gn:name":"Bou Pueng",
    "gn:population":0,
    "gn:timezone":"Asia/Phnom_Penh",
    "iso:country":"KH",
    "name:khm_x_preferred":[
        "Bou Pueng"
    ],
    "wof:name":"Bou Pueng",
    "wof:placetype":"locality"
},
  "geometry": {"coordinates":[104.81404999999999,12.71243],"type":"Point"}
}