{
  "type": "Feature",
  "properties": {
    "gn:admin1_code":"25",
    "gn:asciiname":"Chong Kouk",
    "gn:country_code":"KH",
    "gn:dem":16,
    "gn:feature_class":"P",
    "gn:feature_code":"PPL",
    "gn:name":"Chong Kouk",
    "gn:population":0,
    "gn:timezone":"Asia/Phnom_Penh",
    "iso:country":"KH",
    "name:khm_x_preferred":[
        "Chong Kouk"
    ],
    "name:khm_x_variant":[
        "\u1797\u17bc\u1798\u17b7 \u1785\u17bb\u1784\u1782\u17c4\u1780",
        "Phum Ch\u014fng Ko\u016dk"
    ],
    "name:und_x_variant":[
        "Phum\u012d Ch\u014fng Ko\u016dk"
    ],
    "wof:name":"Chong Kouk",
    "wof:placetype":"locality"
},
  "geometry": {"coordinates":[103.09981000000001,13.52181],"type":"Point"}
}