{
  "type": "Feature",
  "properties": {
    "gn:admin1_code":"29",
    "gn:asciiname":"Phum Roleak",
    "gn:country_code":"KH",
    "gn:dem":14,
    "gn:feature_class":"P",
    "gn:feature_code":"PPL",
    "gn:name":"Phum R\u00f4l\u00e9ak",
    "gn:population":0,
    "gn:timezone":"Asia/Phnom_Penh",
    "iso:country":"KH",
    "name:khm_x_preferred":[
        "Phum R\u00f4l\u00e9ak"
    ],
    "name:khm_x_variant":[
        "\u1797\u17bc\u1798\u17b7 \u179a\u179b\u17b6\u1780"
    ],
    "wof:name":"Phum Roleak",
    "wof:placetype":"locality"
},
  "geometry": {"coordinates":[103.11748,13.12563],"type":"Point"}
}