{
  "type": "Feature",
  "properties": {
    "gn:admin1_code":"7.0",
    "gn:asciiname":"Phum Tuol Don Koam",
    "gn:country_code":"KH",
    "gn:dem":13,
    "gn:feature_class":"P",
    "gn:feature_code":"PPL",
    "gn:name":"Phum Tu\u014fl Don K\u014f\u00e2m",
    "gn:population":0,
    "gn:timezone":"Asia/Phnom_Penh",
    "iso:country":"KH",
    "name:khm_x_preferred":[
        "Phum Tu\u014fl Don K\u014f\u00e2m"
    ],
    "name:khm_x_variant":[
        "\u1797\u17bc\u1798\u17b7 \u1791\u17bd\u179b\u178a\u17bc\u1793\u1782\u17b6\u17c6"
    ],
    "wof:name":"Phum Tuol Don Koam",
    "wof:placetype":"locality"
},
  "geometry": {"coordinates":[105.07704,11.13364],"type":"Point"}
}