{
  "type": "Feature",
  "properties": {
    "gn:admin1_code":"17",
    "gn:asciiname":"Ban Bung",
    "gn:country_code":"KH",
    "gn:dem":65,
    "gn:feature_class":"P",
    "gn:feature_code":"PPL",
    "gn:name":"Ban Bung",
    "gn:population":0,
    "gn:timezone":"Asia/Phnom_Penh",
    "iso:country":"KH",
    "name:khm_x_preferred":[
        "Phum Ban B\u016dng"
    ],
    "name:khm_x_variant":[
        "Ban Bung",
        "\u1797\u17bc\u1798\u17b7 \u1794\u17b6\u1793\u1794\u17ca\u17bb\u1784"
    ],
    "name:und_x_variant":[
        "B\u00e0n Bung"
    ],
    "wof:name":"Ban Bung",
    "wof:placetype":"locality"
},
  "geometry": {"coordinates":[106.13717,13.55825],"type":"Point"}
}