{
  "type": "Feature",
  "properties": {
    "gn:admin1_code":"31",
    "gn:asciiname":"Phumi Thnong",
    "gn:country_code":"KH",
    "gn:dem":24,
    "gn:feature_class":"P",
    "gn:feature_code":"PPL",
    "gn:name":"Phum\u012d Thn\u00f3ng",
    "gn:population":0,
    "gn:timezone":"Asia/Phnom_Penh",
    "iso:country":"KH",
    "name:und_x_variant":[
        "Phum\u012d Thn\u016dng",
        "Phum\u012d Thn\u00f3ng"
    ],
    "wof:name":"Phumi Thnong",
    "wof:placetype":"locality"
},
  "geometry": {"coordinates":[105.62349,11.89495],"type":"Point"}
}