{
  "type": "Feature",
  "properties": {
    "gn:admin1_code":"19",
    "gn:asciiname":"Phumi Thma Kev",
    "gn:country_code":"KH",
    "gn:dem":31,
    "gn:feature_class":"P",
    "gn:feature_code":"PPL",
    "gn:name":"Phum\u012d Thm\u00e2 K\u00eav",
    "gn:population":0,
    "gn:timezone":"Asia/Phnom_Penh",
    "iso:country":"KH",
    "wof:name":"Phumi Thma Kev",
    "wof:placetype":"locality"
},
  "geometry": {"coordinates":[104.59696,10.89382],"type":"Point"}
}