{
  "type": "Feature",
  "properties": {
    "gn:admin1_code":"10",
    "gn:asciiname":"Mereuch",
    "gn:country_code":"KH",
    "gn:dem":148,
    "gn:feature_class":"P",
    "gn:feature_code":"PPL",
    "gn:name":"M\u00e9reuch",
    "gn:population":0,
    "gn:timezone":"Asia/Phnom_Penh",
    "iso:country":"KH",
    "name:und_x_variant":[
        "Phum\u012d M\u00e9reuch",
        "M\u00e9reuch"
    ],
    "wof:name":"Mereuch",
    "wof:placetype":"locality"
},
  "geometry": {"coordinates":[107.40877,13.06942],"type":"Point"}
}