{
  "type": "Feature",
  "properties": {
    "gn:admin1_code":"25",
    "gn:asciiname":"Phumi Boeng Nam",
    "gn:country_code":"KH",
    "gn:dem":16,
    "gn:feature_class":"P",
    "gn:feature_code":"PPL",
    "gn:name":"Phum\u012d B\u0153\u0306ng N\u0103m",
    "gn:population":0,
    "gn:timezone":"Asia/Phnom_Penh",
    "iso:country":"KH",
    "name:und_x_variant":[
        "Phum\u012d B\u0153\u0306n Nam",
        "Phum\u012d B\u0153\u0306ng N\u0103m"
    ],
    "wof:name":"Phumi Boeng Nam",
    "wof:placetype":"locality"
},
  "geometry": {"coordinates":[102.8272,13.44394],"type":"Point"}
}