{
  "type": "Feature",
  "properties": {
    "gn:admin1_code":"25",
    "gn:asciiname":"Phum Anlung Ta Uor",
    "gn:country_code":"KH",
    "gn:dem":12,
    "gn:feature_class":"P",
    "gn:feature_code":"PPL",
    "gn:name":"Phum Anlung Ta U\u014fr",
    "gn:population":0,
    "gn:timezone":"Asia/Phnom_Penh",
    "iso:country":"KH",
    "name:khm_x_preferred":[
        "Phum Anlung Ta U\u014fr"
    ],
    "name:khm_x_variant":[
        "\u1797\u17bc\u1798\u17b7 \u17a2\u1793\u17d2\u179b\u1784\u17cb\u178f\u17b6\u17a2\u17ca\u17bd\u179a"
    ],
    "name:und_x_variant":[
        "Phum\u012d Anl\u016dng Ta U\u014fr",
        "Phum\u012d \u00c2nl\u00f3ng Ta U\u014fr"
    ],
    "wof:name":"Phum Anlung Ta Uor",
    "wof:placetype":"locality"
},
  "geometry": {"coordinates":[103.09911,13.40601],"type":"Point"}
}