{
  "type": "Feature",
  "properties": {
    "gn:admin1_code":"30",
    "gn:asciiname":"Bahuy Khmaer Khang Cheu",
    "gn:country_code":"KH",
    "gn:dem":296,
    "gn:feature_class":"P",
    "gn:feature_code":"PPL",
    "gn:name":"Bahuy Khmaer Khang Cheu",
    "gn:population":0,
    "gn:timezone":"Asia/Phnom_Penh",
    "iso:country":"KH",
    "name:khm_x_preferred":[
        "Bahuy Khmaer Khang Cheu"
    ],
    "name:khm_x_variant":[
        "\u1797\u17bc\u1798\u17b7 \u1794\u17a0\u17bb\u1799\u1781\u17d2\u1798\u17c2\u179a"
    ],
    "name:und_x_variant":[
        "B\u00e2r Huey Khm\u00ear",
        "Phum B\u00e2 H\u016dy Khm\u00ear",
        "Phum\u012d B\u00e2 H\u016dy Khm\u00ear"
    ],
    "wof:name":"Bahuy Khmaer Khang Cheu",
    "wof:placetype":"locality"
},
  "geometry": {"coordinates":[102.52800000000001,12.85762],"type":"Point"}
}