{
  "type": "Feature",
  "properties": {
    "gn:admin1_code":"24.0",
    "gn:asciiname":"Phum Kampong Krakaoh",
    "gn:country_code":"KH",
    "gn:dem":20,
    "gn:feature_class":"P",
    "gn:feature_code":"PPL",
    "gn:name":"Phum K\u00e2mp\u00f4ng Kr\u00e2ka\u00f4h",
    "gn:population":0,
    "gn:timezone":"Asia/Phnom_Penh",
    "iso:country":"KH",
    "name:khm_x_preferred":[
        "Phum K\u00e2mp\u00f4ng Kr\u00e2ka\u00f4h"
    ],
    "name:khm_x_variant":[
        "\u1797\u17bc\u1798\u17b7 \u1780\u17c6\u1796\u1784\u17cb\u1780\u17d2\u179a\u1780\u17c4\u17c7"
    ],
    "wof:name":"Phum Kampong Krakaoh",
    "wof:placetype":"locality"
},
  "geometry": {"coordinates":[104.33781999999999,13.11519],"type":"Point"}
}