{
  "type": "Feature",
  "properties": {
    "gn:admin1_code":"24",
    "gn:asciiname":"Phumi Damrei Chhlang",
    "gn:country_code":"KH",
    "gn:dem":8,
    "gn:feature_class":"P",
    "gn:feature_code":"PPL",
    "gn:name":"Phum\u012d D\u00e2mrei Chhl\u00e2ng",
    "gn:population":0,
    "gn:timezone":"Asia/Phnom_Penh",
    "iso:country":"KH",
    "wof:name":"Phumi Damrei Chhlang",
    "wof:placetype":"locality"
},
  "geometry": {"coordinates":[104.09978,13.07336],"type":"Point"}
}