{
  "type": "Feature",
  "properties": {
    "gn:admin1_code":"02",
    "gn:asciiname":"Phumi Prek Rumdeng",
    "gn:country_code":"KH",
    "gn:dem":21,
    "gn:feature_class":"P",
    "gn:feature_code":"PPL",
    "gn:name":"Phum\u012d Pr\u00eak Rumd\u00e9ng",
    "gn:population":0,
    "gn:timezone":"Asia/Phnom_Penh",
    "iso:country":"KH",
    "name:und_x_variant":[
        "Phum Prek Romdeng",
        "Phum\u012d Pr\u00eak Rumd\u00e9ng"
    ],
    "wof:name":"Phumi Prek Rumdeng",
    "wof:placetype":"locality"
},
  "geometry": {"coordinates":[105.43989999999999,11.88631],"type":"Point"}
}