{
  "type": "Feature",
  "properties": {
    "gn:admin1_code":"29",
    "gn:asciiname":"Boeng Tuem",
    "gn:country_code":"KH",
    "gn:dem":13,
    "gn:feature_class":"P",
    "gn:feature_code":"PPL",
    "gn:name":"Boeng Tuem",
    "gn:population":0,
    "gn:timezone":"Asia/Phnom_Penh",
    "iso:country":"KH",
    "name:khm_x_preferred":[
        "Boeng Tuem"
    ],
    "name:und_x_variant":[
        "Phum\u012d B\u0153\u0306ng T\u0153\u0306m"
    ],
    "wof:name":"Boeng Tuem",
    "wof:placetype":"locality"
},
  "geometry": {"coordinates":[103.35352,13.15895],"type":"Point"}
}