{
  "type": "Feature",
  "properties": {
    "gn:admin1_code":"18",
    "gn:asciiname":"Phumi Lvea",
    "gn:country_code":"KH",
    "gn:dem":9,
    "gn:feature_class":"P",
    "gn:feature_code":"PPL",
    "gn:name":"Phum\u012d Lv\u00e9a",
    "gn:population":0,
    "gn:timezone":"Asia/Phnom_Penh",
    "iso:country":"KH",
    "name:und_x_variant":[
        "Phum Lovea",
        "Phum\u012d Lv\u00e9a"
    ],
    "wof:name":"Phumi Lvea",
    "wof:placetype":"locality"
},
  "geometry": {"coordinates":[105.66851,11.06731],"type":"Point"}
}