{
  "type": "Feature",
  "properties": {
    "gn:admin1_code":"19",
    "gn:asciiname":"Phumi Banteay Thleay",
    "gn:country_code":"KH",
    "gn:dem":7,
    "gn:feature_class":"P",
    "gn:feature_code":"PPL",
    "gn:name":"Phum\u012d B\u00e2nt\u00e9ay Thl\u00e9ay",
    "gn:population":0,
    "gn:timezone":"Asia/Phnom_Penh",
    "iso:country":"KH",
    "name:khm_x_preferred":[
        "Banteay Thleay"
    ],
    "name:und_x_variant":[
        "Phum\u012d B\u00e2nt\u00e9ay Thl\u00e9ay"
    ],
    "wof:name":"Phumi Banteay Thleay",
    "wof:placetype":"locality"
},
  "geometry": {"coordinates":[104.95905,10.73836],"type":"Point"}
}