{
  "type": "Feature",
  "properties": {
    "gn:admin1_code":"25",
    "gn:asciiname":"Phum Kouk Thai",
    "gn:country_code":"KH",
    "gn:dem":15,
    "gn:feature_class":"P",
    "gn:feature_code":"PPL",
    "gn:name":"Phum Ko\u016dk Thai",
    "gn:population":0,
    "gn:timezone":"Asia/Phnom_Penh",
    "iso:country":"KH",
    "name:khm_x_preferred":[
        "Phum Ko\u016dk Thai"
    ],
    "name:khm_x_variant":[
        "\u1797\u17bc\u1798\u17b7 \u1782\u17c4\u1780\u1790\u17c3"
    ],
    "name:und_x_variant":[
        "Rol Chrouk",
        "Phum\u012d Ko\u016dk Thai"
    ],
    "wof:name":"Phum Kouk Thai",
    "wof:placetype":"locality"
},
  "geometry": {"coordinates":[103.18621,13.62358],"type":"Point"}
}