{
  "type": "Feature",
  "properties": {
    "gn:admin1_code":"02",
    "gn:asciiname":"Phumi 'Neakta Snoeng",
    "gn:country_code":"KH",
    "gn:dem":24,
    "gn:feature_class":"P",
    "gn:feature_code":"PPL",
    "gn:name":"Phum\u012d \u2019Ne\u0103kta Sn\u0153\u0306ng",
    "gn:population":0,
    "gn:timezone":"Asia/Phnom_Penh",
    "iso:country":"KH",
    "wof:name":"Phumi 'Neakta Snoeng",
    "wof:placetype":"locality"
},
  "geometry": {"coordinates":[105.17628999999999,12.14622],"type":"Point"}
}