{
  "type": "Feature",
  "properties": {
    "gn:admin1_code":"31",
    "gn:asciiname":"Preaek Chik",
    "gn:country_code":"KH",
    "gn:dem":18,
    "gn:feature_class":"P",
    "gn:feature_code":"PPL",
    "gn:name":"Preaek Chik",
    "gn:population":0,
    "gn:timezone":"Asia/Phnom_Penh",
    "iso:country":"KH",
    "name:khm_x_preferred":[
        "Preaek Chik"
    ],
    "wof:name":"Preaek Chik",
    "wof:placetype":"locality"
},
  "geometry": {"coordinates":[105.47526999999999,11.93658],"type":"Point"}
}