{
  "type": "Feature",
  "properties": {
    "iso:country":"KH",
    "name:deu_x_preferred":[
        "Banteay Chhmar"
    ],
    "name:eng_x_preferred":[
        "Banteay Chhmar"
    ],
    "name:fra_x_preferred":[
        "Banteay Chhmar"
    ],
    "name:ita_x_preferred":[
        "Banteay Chhmar"
    ],
    "name:khm_x_preferred":[
        "\u1783\u17bb\u17c6\u1794\u1793\u17d2\u1791\u17b6\u1799\u1786\u17d2\u1798\u17b6\u179a"
    ],
    "name:nld_x_preferred":[
        "Banteay Chhmar"
    ],
    "name:nob_x_preferred":[
        "Banteay Chhmar"
    ],
    "name:nor_x_preferred":[
        "Banteay Chhmar"
    ],
    "name:pol_x_preferred":[
        "B\u00e2nt\u00e9ay Chhmar"
    ],
    "name:pol_x_variant":[
        "Banteay Chhmar"
    ],
    "name:rus_x_preferred":[
        "\u0411\u0430\u043d\u0442\u0435\u0430\u0439\u0447\u043c\u0430"
    ],
    "name:spa_x_preferred":[
        "Banteay Chhmar"
    ],
    "name:swe_x_preferred":[
        "Banteay Chhmar"
    ],
    "name:vie_x_preferred":[
        "Banteay Chhmar"
    ],
    "name:zho_x_preferred":[
        "\u535c\u8fed\u8272\u746a\u5bfa"
    ],
    "qs:gn_pop":0,
    "qs:name":"Banteai Chhmar",
    "qs:name_adm0":"Cambodia",
    "qs:name_adm1":"Banteay Mean Cheay",
    "qs:photos":69,
    "qs:photos_1k":14,
    "qs:photos_9k":1,
    "qs:photos_9r":2,
    "qs:photos_all":69,
    "qs:photos_sr":2,
    "qs:placetype":"Town",
    "qs:pop_sr":"0",
    "qs:woe_adm0":23424776,
    "wd:wordcount":774,
    "wof:name":"Banteai Chhmar",
    "wof:placetype":"locality"
},
  "geometry": {"coordinates":[103.099801,14.071812],"type":"Point"}
}