{
  "type": "Feature",
  "properties": {
    "gn:admin1_code":"14",
    "gn:asciiname":"Peam Mean Chey",
    "gn:country_code":"KH",
    "gn:dem":10,
    "gn:feature_class":"P",
    "gn:feature_code":"PPL",
    "gn:name":"Peam Mean Chey",
    "gn:population":0,
    "gn:timezone":"Asia/Phnom_Penh",
    "iso:country":"KH",
    "name:khm_x_preferred":[
        "Phum\u012d B\u0153\u0306ng Ka\u00eak"
    ],
    "name:khm_x_variant":[
        "Peam Mean Chey",
        "\u1797\u17bc\u1798\u17b7 \u1794\u17b9\u1784\u1780\u17d2\u17a2\u17c2\u1780"
    ],
    "name:und_x_variant":[
        "Phum Beng Kaet",
        "Phum\u012d B\u0153\u0306ng K\u2019\u00eak"
    ],
    "wof:name":"Peam Mean Chey",
    "wof:placetype":"locality"
},
  "geometry": {"coordinates":[105.27572000000001,11.33464],"type":"Point"}
}