{
  "type": "Feature",
  "properties": {
    "gn:admin1_code":"14",
    "gn:asciiname":"Khum Prey Chho",
    "gn:country_code":"KH",
    "gn:dem":8,
    "gn:feature_class":"P",
    "gn:feature_code":"PPL",
    "gn:name":"Kh\u016dm Prey Chh\u00f4",
    "gn:population":0,
    "gn:timezone":"Asia/Phnom_Penh",
    "iso:country":"KH",
    "name:und_x_variant":[
        "Phum Kompong Prey Chhor",
        "Kh\u016dm Prey Chh\u00f4"
    ],
    "wof:name":"Khum Prey Chho",
    "wof:placetype":"locality"
},
  "geometry": {"coordinates":[105.61024,11.15507],"type":"Point"}
}