{
  "type": "Feature",
  "properties": {
    "gn:admin1_code":"22",
    "gn:asciiname":"Phleung Chheh Roteh",
    "gn:country_code":"KH",
    "gn:dem":22,
    "gn:feature_class":"P",
    "gn:feature_code":"PPL",
    "gn:name":"Phleung Chheh Roteh",
    "gn:population":0,
    "gn:timezone":"Asia/Phnom_Penh",
    "iso:country":"KH",
    "name:khm_x_preferred":[
        "Phleung Chheh Roteh"
    ],
    "name:und_x_variant":[
        "Phl\u0153ung Chhes",
        "Phum\u012d Phleung Chh\u00e9h R\u00f4t\u00e9h"
    ],
    "wof:name":"Phleung Chheh Roteh",
    "wof:placetype":"locality"
},
  "geometry": {"coordinates":[104.79349999999999,11.48545],"type":"Point"}
}