{
  "type": "Feature",
  "properties": {
    "gn:admin1_code":"29",
    "gn:asciiname":"Tras",
    "gn:country_code":"KH",
    "gn:dem":16,
    "gn:feature_class":"P",
    "gn:feature_code":"PPL",
    "gn:name":"Tras",
    "gn:population":0,
    "gn:timezone":"Asia/Phnom_Penh",
    "iso:country":"KH",
    "name:khm_x_preferred":[
        "Tras"
    ],
    "name:khm_x_variant":[
        "Phum Tr\u0103s",
        "\u1797\u17bc\u1798\u17b7 \u178f\u17d2\u179a\u179f\u17cb"
    ],
    "name:und_x_variant":[
        "Phum Peam Tras",
        "Phum\u012d Tr\u00e1s"
    ],
    "wof:name":"Tras",
    "wof:placetype":"locality"
},
  "geometry": {"coordinates":[103.13323,13.17813],"type":"Point"}
}