{
  "type": "Feature",
  "properties": {
    "gn:admin1_code":"03",
    "gn:asciiname":"Vat Tuk Haut",
    "gn:country_code":"KH",
    "gn:dem":18,
    "gn:feature_class":"P",
    "gn:feature_code":"PPL",
    "gn:name":"Vat Tuk Haut",
    "gn:population":0,
    "gn:timezone":"Asia/Phnom_Penh",
    "iso:country":"KH",
    "name:und_x_variant":[
        "Tuk Haut",
        "Vat Tuk Haut",
        "Phum\u012d T\u0153\u0306k Hot"
    ],
    "wof:name":"Vat Tuk Haut",
    "wof:placetype":"locality"
},
  "geometry": {"coordinates":[104.73139999999999,12.11016],"type":"Point"}
}