{
  "type": "Feature",
  "properties": {
    "gn:admin1_code":"07",
    "gn:asciiname":"Kampong Thkol",
    "gn:country_code":"KH",
    "gn:dem":8,
    "gn:feature_class":"P",
    "gn:feature_code":"PPL",
    "gn:name":"Kampong Thkol",
    "gn:population":0,
    "gn:timezone":"Asia/Phnom_Penh",
    "iso:country":"KH",
    "name:khm_x_preferred":[
        "Kampong Thkol"
    ],
    "name:und_x_variant":[
        "Phum Kompong Phkol",
        "Phum\u012d K\u00e2mp\u00f3ng Phd\u014fl"
    ],
    "wof:name":"Kampong Thkol",
    "wof:placetype":"locality"
},
  "geometry": {"coordinates":[105.05540999999999,10.99327],"type":"Point"}
}