{
  "type": "Feature",
  "properties": {
    "gn:admin1_code":"25",
    "gn:asciiname":"Prohut",
    "gn:country_code":"KH",
    "gn:dem":17,
    "gn:feature_class":"P",
    "gn:feature_code":"PPL",
    "gn:name":"Prohut",
    "gn:population":0,
    "gn:timezone":"Asia/Phnom_Penh",
    "iso:country":"KH",
    "name:khm_x_preferred":[
        "Prohut"
    ],
    "wof:name":"Prohut",
    "wof:placetype":"locality"
},
  "geometry": {"coordinates":[102.95855,13.57764],"type":"Point"}
}