{
  "type": "Feature",
  "properties": {
    "gn:admin1_code":"23",
    "gn:asciiname":"Phumi Batang Svay",
    "gn:country_code":"KH",
    "gn:dem":253,
    "gn:feature_class":"P",
    "gn:feature_code":"PPL",
    "gn:name":"Phum\u012d Batang Svay",
    "gn:population":0,
    "gn:timezone":"Asia/Phnom_Penh",
    "iso:country":"KH",
    "wof:name":"Phumi Batang Svay",
    "wof:placetype":"locality"
},
  "geometry": {"coordinates":[107.06559,13.65904],"type":"Point"}
}