{
  "type": "Feature",
  "properties": {
    "gn:admin1_code":"29",
    "gn:asciiname":"Phum Boeng Khtum",
    "gn:country_code":"KH",
    "gn:dem":19,
    "gn:feature_class":"P",
    "gn:feature_code":"PPL",
    "gn:name":"Phum B\u0153\u0306ng Kht\u016dm",
    "gn:population":0,
    "gn:timezone":"Asia/Phnom_Penh",
    "iso:country":"KH",
    "name:khm_x_preferred":[
        "Phum B\u0153\u0306ng Kht\u016dm"
    ],
    "name:khm_x_variant":[
        "\u1797\u17bc\u1798\u17b7 \u1794\u17b9\u1784\u1781\u17d2\u1791"
    ],
    "wof:name":"Phum Boeng Khtum",
    "wof:placetype":"locality"
},
  "geometry": {"coordinates":[103.26502000000001,12.9198],"type":"Point"}
}