{
  "type": "Feature",
  "properties": {
    "gn:admin1_code":"7.0",
    "gn:asciiname":"Phum Chong Kaoh Khsach Tonlea Lech",
    "gn:country_code":"KH",
    "gn:dem":11,
    "gn:feature_class":"P",
    "gn:feature_code":"PPL",
    "gn:name":"Phum Ch\u014fng Ka\u00f4h Khsach T\u00f4nl\u00e9a L\u0115ch",
    "gn:population":0,
    "gn:timezone":"Asia/Phnom_Penh",
    "iso:country":"KH",
    "name:khm_x_preferred":[
        "Phum Ch\u014fng Ka\u00f4h Khsach T\u00f4nl\u00e9a L\u0115ch"
    ],
    "name:khm_x_variant":[
        "\u1797\u17bc\u1798\u17b7 \u1785\u17bb\u1784\u1780\u17c4\u17c7\u1781\u17d2\u179f\u17b6\u1785\u17cb\u1791\u1793\u17d2\u179b\u17b6\u179b\u17b7\u1785"
    ],
    "wof:name":"Phum Chong Kaoh Khsach Tonlea Lech",
    "wof:placetype":"locality"
},
  "geometry": {"coordinates":[105.03668,11.31433],"type":"Point"}
}