{
  "type": "Feature",
  "properties": {
    "gn:admin1_code":"19",
    "gn:asciiname":"Phumi Vott Dong",
    "gn:country_code":"KH",
    "gn:dem":14,
    "gn:feature_class":"P",
    "gn:feature_code":"PPL",
    "gn:name":"Phum\u012d V\u00f4tt D\u014fng",
    "gn:population":0,
    "gn:timezone":"Asia/Phnom_Penh",
    "iso:country":"KH",
    "name:und_x_variant":[
        "Phum Dong",
        "Phum\u012d Vatt D\u014fng",
        "Phum\u012d V\u00f4tt D\u014fng"
    ],
    "wof:name":"Phumi Vott Dong",
    "wof:placetype":"locality"
},
  "geometry": {"coordinates":[104.85748,11.16241],"type":"Point"}
}