{
  "type": "Feature",
  "properties": {
    "gn:admin1_code":"05",
    "gn:asciiname":"Neang Sa Lngeach",
    "gn:country_code":"KH",
    "gn:dem":12,
    "gn:feature_class":"P",
    "gn:feature_code":"PPL",
    "gn:name":"Neang Sa Lngeach",
    "gn:population":0,
    "gn:timezone":"Asia/Phnom_Penh",
    "iso:country":"KH",
    "name:khm_x_preferred":[
        "Neang Sa Lngeach"
    ],
    "name:und_x_variant":[
        "Phum\u012d N\u00e9ang S\u00e2 Sngach (1)",
        "Phum\u012d N\u00e9ang S\u00e2r Sngach (1)"
    ],
    "wof:name":"Neang Sa Lngeach",
    "wof:placetype":"locality"
},
  "geometry": {"coordinates":[104.51871,12.99061],"type":"Point"}
}