{
  "type": "Feature",
  "properties": {
    "gn:admin1_code":"9.0",
    "gn:asciiname":"Phum Kandal Kaoh Tasuy",
    "gn:country_code":"KH",
    "gn:dem":22,
    "gn:feature_class":"P",
    "gn:feature_code":"PPL",
    "gn:name":"Phum K\u00e2ndal Ka\u00f4h Tas\u016dy",
    "gn:population":0,
    "gn:timezone":"Asia/Phnom_Penh",
    "iso:country":"KH",
    "name:khm_x_preferred":[
        "Phum K\u00e2ndal Ka\u00f4h Tas\u016dy"
    ],
    "name:khm_x_variant":[
        "\u1797\u17bc\u1798\u17b7 \u1780\u178e\u17d2\u178a\u17b6\u179b\u1780\u17c4\u17c7\u178f\u17b6\u179f\u17ca\u17bb\u1799"
    ],
    "wof:name":"Phum Kandal Kaoh Tasuy",
    "wof:placetype":"locality"
},
  "geometry": {"coordinates":[105.90527,12.26996],"type":"Point"}
}