{
  "type": "Feature",
  "properties": {
    "gn:admin1_code":"29",
    "gn:asciiname":"Phumi Kanhcham",
    "gn:country_code":"KH",
    "gn:dem":5,
    "gn:feature_class":"P",
    "gn:feature_code":"PPL",
    "gn:name":"Phum\u012d K\u00e2nhch\u00e2m",
    "gn:population":0,
    "gn:timezone":"Asia/Phnom_Penh",
    "iso:country":"KH",
    "wof:name":"Phumi Kanhcham",
    "wof:placetype":"locality"
},
  "geometry": {"coordinates":[103.67589,13.2272],"type":"Point"}
}