{
  "type": "Feature",
  "properties": {
    "gn:admin1_code":"02",
    "gn:asciiname":"Klaeng Poar",
    "gn:country_code":"KH",
    "gn:dem":22,
    "gn:feature_class":"P",
    "gn:feature_code":"PPL",
    "gn:name":"Klaeng Poar",
    "gn:population":0,
    "gn:timezone":"Asia/Phnom_Penh",
    "iso:country":"KH",
    "name:khm_x_preferred":[
        "Klaeng Poar"
    ],
    "name:und_x_variant":[
        "Phum Khl\u0115ng Pear",
        "Phum\u012d Khl\u00eang P\u00f4r"
    ],
    "wof:name":"Klaeng Poar",
    "wof:placetype":"locality"
},
  "geometry": {"coordinates":[105.23267,12.01956],"type":"Point"}
}