{
  "type": "Feature",
  "properties": {
    "gn:admin1_code":"29",
    "gn:asciiname":"Phum Yen Dong",
    "gn:country_code":"KH",
    "gn:dem":18,
    "gn:feature_class":"P",
    "gn:feature_code":"PPL",
    "gn:name":"Phum Yen Dong",
    "gn:population":0,
    "gn:timezone":"Asia/Phnom_Penh",
    "iso:country":"KH",
    "name:khm_x_preferred":[
        "Phum Yen Dong"
    ],
    "name:khm_x_variant":[
        "\u1797\u17bc\u1798\u17b7 \u1799\u17c2\u1793\u178a\u17bc\u1784"
    ],
    "wof:name":"Phum Yen Dong",
    "wof:placetype":"locality"
},
  "geometry": {"coordinates":[103.38455999999999,12.82276],"type":"Point"}
}