{
  "type": "Feature",
  "properties": {
    "gn:admin1_code":"14",
    "gn:asciiname":"Sda Kdei",
    "gn:country_code":"KH",
    "gn:dem":19,
    "gn:feature_class":"P",
    "gn:feature_code":"PPL",
    "gn:name":"Sda Kdei",
    "gn:population":0,
    "gn:timezone":"Asia/Phnom_Penh",
    "iso:country":"KH",
    "name:khm_x_preferred":[
        "Sda Kdei"
    ],
    "name:und_x_variant":[
        "Phum Skea Kdey",
        "Phum\u012d Sk\u00e9ar Kdei",
        "Phum\u012d Sk\u00e9a Kdei"
    ],
    "wof:name":"Sda Kdei",
    "wof:placetype":"locality"
},
  "geometry": {"coordinates":[105.28737,11.77937],"type":"Point"}
}