{
  "type": "Feature",
  "properties": {
    "gn:admin1_code":"13",
    "gn:asciiname":"Phumi Prame",
    "gn:country_code":"KH",
    "gn:dem":82,
    "gn:feature_class":"P",
    "gn:feature_code":"PPL",
    "gn:name":"Phum\u012d Pr\u00e2m\u00e9",
    "gn:population":0,
    "gn:timezone":"Asia/Phnom_Penh",
    "iso:country":"KH",
    "name:und_x_variant":[
        "Phum\u012d Kamnap",
        "Phum\u012d Pr\u00e2m\u00e9"
    ],
    "wof:name":"Phumi Prame",
    "wof:placetype":"locality"
},
  "geometry": {"coordinates":[104.67137,14.17122],"type":"Point"}
}