{
  "type": "Feature",
  "properties": {
    "gn:admin1_code":"21",
    "gn:asciiname":"Boeng Sala Khang Cheung",
    "gn:country_code":"KH",
    "gn:dem":8,
    "gn:feature_class":"P",
    "gn:feature_code":"PPL",
    "gn:name":"Boeng Sala Khang Cheung",
    "gn:population":0,
    "gn:timezone":"Asia/Phnom_Penh",
    "iso:country":"KH",
    "name:khm_x_preferred":[
        "Boeng Sala Khang Cheung"
    ],
    "wof:name":"Boeng Sala Khang Cheung",
    "wof:placetype":"locality"
},
  "geometry": {"coordinates":[104.50714000000001,10.53264],"type":"Point"}
}