{
  "type": "Feature",
  "properties": {
    "gn:admin1_code":"21",
    "gn:asciiname":"Phumi Chrak Popel",
    "gn:country_code":"KH",
    "gn:dem":5,
    "gn:feature_class":"P",
    "gn:feature_code":"PPL",
    "gn:name":"Phum\u012d Chr\u00e2k P\u00f4p\u00e9l",
    "gn:population":0,
    "gn:timezone":"Asia/Phnom_Penh",
    "iso:country":"KH",
    "wof:name":"Phumi Chrak Popel",
    "wof:placetype":"locality"
},
  "geometry": {"coordinates":[104.23644,10.60124],"type":"Point"}
}