{
  "type": "Feature",
  "properties": {
    "gn:admin1_code":"02",
    "gn:asciiname":"Chamkar Leu",
    "gn:country_code":"KH",
    "gn:dem":52,
    "gn:feature_class":"P",
    "gn:feature_code":"PPLA2",
    "gn:name":"Chamkar Leu",
    "gn:population":0,
    "gn:timezone":"Asia/Phnom_Penh",
    "iso:country":"KH",
    "name:khm_x_preferred":[
        "Chamkar Leu"
    ],
    "wof:name":"Chamkar Leu",
    "wof:placetype":"locality"
},
  "geometry": {"coordinates":[105.28185999999999,12.30851],"type":"Point"}
}