{
  "type": "Feature",
  "properties": {
    "gn:admin1_code":"9.0",
    "gn:asciiname":"Preaek Ta Hub",
    "gn:country_code":"KH",
    "gn:dem":24,
    "gn:feature_class":"P",
    "gn:feature_code":"PPL",
    "gn:name":"Preaek Ta Hub",
    "gn:population":0,
    "gn:timezone":"Asia/Phnom_Penh",
    "iso:country":"KH",
    "name:khm_x_preferred":[
        "Preaek Ta Hub"
    ],
    "name:khm_x_variant":[
        "\u1797\u17bc\u1798\u17b7 \u1796\u17d2\u179a\u17c2\u1780\u178f\u17b6\u17a0\u17bb\u1794",
        "Phum Pr\u00eak Ta H\u014fp"
    ],
    "wof:name":"Preaek Ta Hub",
    "wof:placetype":"locality"
},
  "geometry": {"coordinates":[105.83619,12.25162],"type":"Point"}
}