{
  "type": "Feature",
  "properties": {
    "gn:admin1_code":"29",
    "gn:asciiname":"Phum Kao Krop Bay",
    "gn:country_code":"KH",
    "gn:dem":19,
    "gn:feature_class":"P",
    "gn:feature_code":"PPL",
    "gn:name":"Phum Ka\u00f4 Kr\u00f4p Bay",
    "gn:population":0,
    "gn:timezone":"Asia/Phnom_Penh",
    "iso:country":"KH",
    "name:khm_x_preferred":[
        "Phum Ka\u00f4 Kr\u00f4p Bay"
    ],
    "name:khm_x_variant":[
        "\u1797\u17bc\u1798\u17b7 \u1780\u17c4\u1782\u17d2\u179a\u1794\u1794\u17b6\u1799"
    ],
    "name:und_x_variant":[
        "Phum\u012d Ka\u00f4 Kr\u00f4p Bay",
        "Phum\u012d Ka\u00f4 Kr\u00f4b Bay"
    ],
    "wof:name":"Phum Kao Krop Bay",
    "wof:placetype":"locality"
},
  "geometry": {"coordinates":[103.40167,12.76369],"type":"Point"}
}