{
  "type": "Feature",
  "properties": {
    "gn:admin1_code":"12.0",
    "gn:asciiname":"Phum Kouk Samraong",
    "gn:country_code":"KH",
    "gn:dem":26,
    "gn:feature_class":"P",
    "gn:feature_code":"PPL",
    "gn:name":"Phum Ko\u016dk Samra\u00f4ng",
    "gn:population":0,
    "gn:timezone":"Asia/Phnom_Penh",
    "iso:country":"KH",
    "name:khm_x_preferred":[
        "Phum Ko\u016dk Samra\u00f4ng"
    ],
    "name:khm_x_variant":[
        "\u1797\u17bc\u1798\u17b7\u1782\u17c4\u1780\u179f\u17c6\u179a\u17c4\u1784"
    ],
    "wof:name":"Phum Kouk Samraong",
    "wof:placetype":"locality"
},
  "geometry": {"coordinates":[103.88651,12.58222],"type":"Point"}
}