{
  "type": "Feature",
  "properties": {
    "gn:admin1_code":"04",
    "gn:asciiname":"Wat Prey Phchek",
    "gn:country_code":"KH",
    "gn:dem":34,
    "gn:feature_class":"P",
    "gn:feature_code":"PPL",
    "gn:name":"Wat Prey Phchek",
    "gn:population":0,
    "gn:timezone":"Asia/Phnom_Penh",
    "iso:country":"KH",
    "name:und_x_variant":[
        "Vat Prei Phchek",
        "Wat Prey Phchek",
        "Phum\u012d Prey Phch\u0153\u0306k"
    ],
    "wof:name":"Wat Prey Phchek",
    "wof:placetype":"locality"
},
  "geometry": {"coordinates":[104.65054000000001,11.39599],"type":"Point"}
}