{
  "type": "Feature",
  "properties": {
    "gn:admin1_code":"24",
    "gn:asciiname":"Ta Prum",
    "gn:country_code":"KH",
    "gn:dem":20,
    "gn:feature_class":"P",
    "gn:feature_code":"PPL",
    "gn:name":"Ta Prum",
    "gn:population":0,
    "gn:timezone":"Asia/Phnom_Penh",
    "iso:country":"KH",
    "name:khm_x_preferred":[
        "Ta Prum"
    ],
    "wof:name":"Ta Prum",
    "wof:placetype":"locality"
},
  "geometry": {"coordinates":[104.23005000000001,13.20662],"type":"Point"}
}