{
  "type": "Feature",
  "properties": {
    "gn:admin1_code":"7.0",
    "gn:asciiname":"Phum Prek Yeay Hay",
    "gn:country_code":"KH",
    "gn:dem":11,
    "gn:feature_class":"P",
    "gn:feature_code":"PPL",
    "gn:name":"Phum Pr\u00eak Y\u00e9ay Hay",
    "gn:population":0,
    "gn:timezone":"Asia/Phnom_Penh",
    "iso:country":"KH",
    "name:khm_x_preferred":[
        "Phum Pr\u00eak Y\u00e9ay Hay"
    ],
    "name:khm_x_variant":[
        "\u1797\u17bc\u1798\u17b7 \u1796\u17d2\u179a\u17c2\u1780\u1799\u17b6\u1799\u17a0\u17b6\u1799"
    ],
    "wof:name":"Phum Prek Yeay Hay",
    "wof:placetype":"locality"
},
  "geometry": {"coordinates":[105.062,11.15859],"type":"Point"}
}