{
  "type": "Feature",
  "properties": {
    "gn:admin1_code":"21",
    "gn:asciiname":"Phumi Banteay Siem",
    "gn:country_code":"KH",
    "gn:dem":10,
    "gn:feature_class":"P",
    "gn:feature_code":"PPL",
    "gn:name":"Phum\u012d B\u00e2nt\u00e9ay Si\u0115m",
    "gn:population":0,
    "gn:timezone":"Asia/Phnom_Penh",
    "iso:country":"KH",
    "wof:name":"Phumi Banteay Siem",
    "wof:placetype":"locality"
},
  "geometry": {"coordinates":[104.28194000000001,10.5859],"type":"Point"}
}