{
  "type": "Feature",
  "properties": {
    "gn:admin1_code":"25",
    "gn:asciiname":"Prey Totueng",
    "gn:country_code":"KH",
    "gn:dem":16,
    "gn:feature_class":"P",
    "gn:feature_code":"PPL",
    "gn:name":"Prey Totueng",
    "gn:population":0,
    "gn:timezone":"Asia/Phnom_Penh",
    "iso:country":"KH",
    "name:khm_x_preferred":[
        "Prey Totueng"
    ],
    "name:khm_x_variant":[
        "Phum Prey T\u00f4t\u0153\u0306ng"
    ],
    "name:und_x_variant":[
        "Phum Prey Totung",
        "Phum\u012d Prey T\u00f4t\u0153\u0306ng"
    ],
    "wof:name":"Prey Totueng",
    "wof:placetype":"locality"
},
  "geometry": {"coordinates":[103.03597000000001,13.42769],"type":"Point"}
}