{
  "type": "Feature",
  "properties": {
    "gn:admin1_code":"23.0",
    "gn:asciiname":"Pa Toeng",
    "gn:country_code":"KH",
    "gn:dem":100,
    "gn:feature_class":"P",
    "gn:feature_code":"PPL",
    "gn:name":"Pa Toeng",
    "gn:population":0,
    "gn:timezone":"Asia/Phnom_Penh",
    "iso:country":"KH",
    "name:khm_x_preferred":[
        "Pa Toeng"
    ],
    "wof:name":"Pa Toeng",
    "wof:placetype":"locality"
},
  "geometry": {"coordinates":[106.98086000000001,14.04883],"type":"Point"}
}