{
  "type": "Feature",
  "properties": {
    "gn:admin1_code":"14.0",
    "gn:asciiname":"Phum Prek Krahe",
    "gn:country_code":"KH",
    "gn:dem":12,
    "gn:feature_class":"P",
    "gn:feature_code":"PPL",
    "gn:name":"Phum Pr\u00eak Kr\u00e2h\u00ea",
    "gn:population":0,
    "gn:timezone":"Asia/Phnom_Penh",
    "iso:country":"KH",
    "name:khm_x_preferred":[
        "Phum Pr\u00eak Kr\u00e2h\u00ea"
    ],
    "name:khm_x_variant":[
        "\u1797\u17bc\u1798\u17b7 \u1796\u17d2\u179a\u17c2\u1780\u1780\u17d2\u179a\u17a0\u17c2"
    ],
    "wof:name":"Phum Prek Krahe",
    "wof:placetype":"locality"
},
  "geometry": {"coordinates":[105.27976,11.32225],"type":"Point"}
}