{
  "type": "Feature",
  "properties": {
    "gn:admin1_code":"04",
    "gn:asciiname":"Phumi Trapeang Krasang",
    "gn:country_code":"KH",
    "gn:dem":70,
    "gn:feature_class":"P",
    "gn:feature_code":"PPL",
    "gn:name":"Phum\u012d Tr\u00e2pe\u0103ng Kr\u00e2s\u0103ng",
    "gn:population":0,
    "gn:timezone":"Asia/Phnom_Penh",
    "iso:country":"KH",
    "name:khm_x_preferred":[
        "Phum\u012d Tr\u00e2pe\u0103ng Kr\u00e2s\u0103ng"
    ],
    "name:khm_x_variant":[
        "\u1797\u17bc\u1798\u17b7 \u178f\u17d2\u179a\u1796\u17b6\u17c6\u1784\u1780\u17d2\u179a\u179f\u17b6\u17c6\u1784"
    ],
    "wof:name":"Phumi Trapeang Krasang",
    "wof:placetype":"locality"
},
  "geometry": {"coordinates":[104.49926000000001,11.35614],"type":"Point"}
}