{
  "type": "Feature",
  "properties": {
    "gn:admin1_code":"24.0",
    "gn:asciiname":"Ou Krouch",
    "gn:country_code":"KH",
    "gn:dem":89,
    "gn:feature_class":"P",
    "gn:feature_code":"PPL",
    "gn:name":"Ou Krouch",
    "gn:population":0,
    "gn:timezone":"Asia/Phnom_Penh",
    "iso:country":"KH",
    "name:khm_x_preferred":[
        "Ou Krouch"
    ],
    "wof:name":"Ou Krouch",
    "wof:placetype":"locality"
},
  "geometry": {"coordinates":[104.37521,13.98129],"type":"Point"}
}