{
  "type": "Feature",
  "properties": {
    "gn:admin1_code":"05",
    "gn:asciiname":"Phumi Khleng",
    "gn:country_code":"KH",
    "gn:dem":25,
    "gn:feature_class":"P",
    "gn:feature_code":"PPL",
    "gn:name":"Phum\u012d Khl\u00eang",
    "gn:population":0,
    "gn:timezone":"Asia/Phnom_Penh",
    "iso:country":"KH",
    "name:und_x_variant":[
        "Phum Kleng",
        "Phum\u012d Khl\u00eang"
    ],
    "wof:name":"Phumi Khleng",
    "wof:placetype":"locality"
},
  "geometry": {"coordinates":[105.21687,12.99208],"type":"Point"}
}