{
  "type": "Feature",
  "properties": {
    "gn:admin1_code":"07",
    "gn:asciiname":"Rumlich",
    "gn:country_code":"KH",
    "gn:dem":24,
    "gn:feature_class":"P",
    "gn:feature_code":"PPL",
    "gn:name":"Rumlich",
    "gn:population":0,
    "gn:timezone":"Asia/Phnom_Penh",
    "iso:country":"KH",
    "name:khm_x_preferred":[
        "Rumlich"
    ],
    "wof:name":"Rumlich",
    "wof:placetype":"locality"
},
  "geometry": {"coordinates":[104.73891,11.62759],"type":"Point"}
}