{
  "type": "Feature",
  "properties": {
    "gn:admin1_code":"3.0",
    "gn:asciiname":"Phum Peam Thlung",
    "gn:country_code":"KH",
    "gn:dem":60,
    "gn:feature_class":"P",
    "gn:feature_code":"PPL",
    "gn:name":"Phum P\u00e9am Thl\u016dng",
    "gn:population":0,
    "gn:timezone":"Asia/Phnom_Penh",
    "iso:country":"KH",
    "name:khm_x_preferred":[
        "Phum P\u00e9am Thl\u016dng"
    ],
    "wof:name":"Phum Peam Thlung",
    "wof:placetype":"locality"
},
  "geometry": {"coordinates":[104.4716,11.74998],"type":"Point"}
}