{
  "type": "Feature",
  "properties": {
    "gn:admin1_code":"19",
    "gn:asciiname":"Phumi Prey Ta Pong",
    "gn:country_code":"KH",
    "gn:dem":12,
    "gn:feature_class":"P",
    "gn:feature_code":"PPL",
    "gn:name":"Phum\u012d Prey Ta P\u00f4ng",
    "gn:population":0,
    "gn:timezone":"Asia/Phnom_Penh",
    "iso:country":"KH",
    "name:und_x_variant":[
        "Phum Prey Tapong",
        "Phum\u012d Prey Ta P\u00f4ng"
    ],
    "wof:name":"Phumi Prey Ta Pong",
    "wof:placetype":"locality"
},
  "geometry": {"coordinates":[104.97995,11.13716],"type":"Point"}
}