{
  "type": "Feature",
  "properties": {
    "gn:admin1_code":"04",
    "gn:asciiname":"Phumi Praprau",
    "gn:country_code":"KH",
    "gn:dem":25,
    "gn:feature_class":"P",
    "gn:feature_code":"PPL",
    "gn:name":"Phum\u012d Pr\u00e2prau",
    "gn:population":0,
    "gn:timezone":"Asia/Phnom_Penh",
    "iso:country":"KH",
    "name:und_x_variant":[
        "Phum Trapeang Pro\u0103",
        "Phum\u012d Pr\u00e2prau"
    ],
    "wof:name":"Phumi Praprau",
    "wof:placetype":"locality"
},
  "geometry": {"coordinates":[104.66049,11.78808],"type":"Point"}
}