{
  "type": "Feature",
  "properties": {
    "gn:admin1_code":"18",
    "gn:asciiname":"Prey Ta Nhay",
    "gn:country_code":"KH",
    "gn:dem":7,
    "gn:feature_class":"P",
    "gn:feature_code":"PPL",
    "gn:name":"Prey Ta Nhay",
    "gn:population":0,
    "gn:timezone":"Asia/Phnom_Penh",
    "iso:country":"KH",
    "name:khm_x_preferred":[
        "Prey Ta Nhay"
    ],
    "wof:name":"Prey Ta Nhay",
    "wof:placetype":"locality"
},
  "geometry": {"coordinates":[105.98039,10.95876],"type":"Point"}
}