{
  "type": "Feature",
  "properties": {
    "gn:admin1_code":"25",
    "gn:asciiname":"Phum Anlung Trabek",
    "gn:country_code":"KH",
    "gn:dem":12,
    "gn:feature_class":"P",
    "gn:feature_code":"PPL",
    "gn:name":"Phum Anl\u016dng Tr\u00e2b\u00eak",
    "gn:population":0,
    "gn:timezone":"Asia/Phnom_Penh",
    "iso:country":"KH",
    "name:khm_x_preferred":[
        "Phum Anl\u016dng Tr\u00e2b\u00eak"
    ],
    "name:khm_x_variant":[
        "\u1797\u17bc\u1798\u17b7 \u17a2\u1793\u17d2\u179b\u1784\u17cb\u178f\u17d2\u179a\u1794\u17c2\u1780"
    ],
    "wof:name":"Phum Anlung Trabek",
    "wof:placetype":"locality"
},
  "geometry": {"coordinates":[103.11982,13.56926],"type":"Point"}
}