{
  "type": "Feature",
  "properties": {
    "gn:admin1_code":"07",
    "gn:asciiname":"Chrey Muoy Roy",
    "gn:country_code":"KH",
    "gn:dem":15,
    "gn:feature_class":"P",
    "gn:feature_code":"PPL",
    "gn:name":"Chrey Muoy Roy",
    "gn:population":0,
    "gn:timezone":"Asia/Phnom_Penh",
    "iso:country":"KH",
    "name:khm_x_preferred":[
        "Chrey Muoy Roy"
    ],
    "name:und_x_variant":[
        "Phum\u012d Sr\u00ea Mu\u014fy R\u00f4y"
    ],
    "wof:name":"Chrey Muoy Roy",
    "wof:placetype":"locality"
},
  "geometry": {"coordinates":[104.91221000000002,11.73187],"type":"Point"}
}