{
  "type": "Feature",
  "properties": {
    "gn:admin1_code":"25",
    "gn:asciiname":"Dang Trang",
    "gn:country_code":"KH",
    "gn:dem":18,
    "gn:feature_class":"P",
    "gn:feature_code":"PPL",
    "gn:name":"Dang Trang",
    "gn:population":0,
    "gn:timezone":"Asia/Phnom_Penh",
    "iso:country":"KH",
    "name:khm_x_preferred":[
        "Dang Trang"
    ],
    "name:und_x_variant":[
        "Phum\u012d D\u00e2ng Trang"
    ],
    "wof:name":"Dang Trang",
    "wof:placetype":"locality"
},
  "geometry": {"coordinates":[102.98135000000001,13.41562],"type":"Point"}
}