{
  "type": "Feature",
  "properties": {
    "gn:admin1_code":"29",
    "gn:asciiname":"Prey Prum Pir",
    "gn:country_code":"KH",
    "gn:dem":25,
    "gn:feature_class":"P",
    "gn:feature_code":"PPL",
    "gn:name":"Prey Prum Pir",
    "gn:population":0,
    "gn:timezone":"Asia/Phnom_Penh",
    "iso:country":"KH",
    "wof:name":"Prey Prum Pir",
    "wof:placetype":"locality"
},
  "geometry": {"coordinates":[103.43021,12.71888],"type":"Point"}
}