{
  "type": "Feature",
  "properties": {
    "gn:admin1_code":"28",
    "gn:asciiname":"Tumnob Rolok",
    "gn:country_code":"KH",
    "gn:dem":13,
    "gn:feature_class":"P",
    "gn:feature_code":"PPL",
    "gn:name":"Tumnob Rolok",
    "gn:population":0,
    "gn:timezone":"Asia/Phnom_Penh",
    "iso:country":"KH",
    "name:khm_x_preferred":[
        "Tumnob Rolok"
    ],
    "wof:name":"Tumnob Rolok",
    "wof:placetype":"locality"
},
  "geometry": {"coordinates":[103.62736,10.74151],"type":"Point"}
}