{
  "type": "Feature",
  "properties": {
    "gn:admin1_code":"14",
    "gn:asciiname":"Phumi Damrei Prich A Steang",
    "gn:country_code":"KH",
    "gn:dem":8,
    "gn:feature_class":"P",
    "gn:feature_code":"PPL",
    "gn:name":"Phum\u012d D\u00e2mrei Pr\u012dch A Ste\u0103ng",
    "gn:population":0,
    "gn:timezone":"Asia/Phnom_Penh",
    "iso:country":"KH",
    "name:und_x_variant":[
        "Phum Domrey Prek Ateang",
        "Phum\u012d D\u00e2mrei Pr\u012dch A Ste\u0103ng"
    ],
    "wof:name":"Phumi Damrei Prich A Steang",
    "wof:placetype":"locality"
},
  "geometry": {"coordinates":[105.3917,11.07054],"type":"Point"}
}