{
  "type": "Feature",
  "properties": {
    "gn:admin1_code":"29",
    "gn:asciiname":"Ta Saen",
    "gn:country_code":"KH",
    "gn:dem":96,
    "gn:feature_class":"P",
    "gn:feature_code":"PPL",
    "gn:name":"Ta Saen",
    "gn:population":0,
    "gn:timezone":"Asia/Phnom_Penh",
    "iso:country":"KH",
    "name:khm_x_preferred":[
        "Ta Saen"
    ],
    "wof:name":"Ta Saen",
    "wof:placetype":"locality"
},
  "geometry": {"coordinates":[102.42531,13.12298],"type":"Point"}
}