{
  "type": "Feature",
  "properties": {
    "gn:admin1_code":"02",
    "gn:asciiname":"Phumi Sangker",
    "gn:country_code":"KH",
    "gn:dem":15,
    "gn:feature_class":"P",
    "gn:feature_code":"PPL",
    "gn:name":"Phum\u012d S\u00e2ngk\u00ear",
    "gn:population":0,
    "gn:timezone":"Asia/Phnom_Penh",
    "iso:country":"KH",
    "name:und_x_variant":[
        "Phum\u012d S\u00e2ngk\u00ea",
        "Phum\u012d S\u00e2ngk\u00ear"
    ],
    "wof:name":"Phumi Sangker",
    "wof:placetype":"locality"
},
  "geometry": {"coordinates":[105.08474,12.12304],"type":"Point"}
}