{
  "type": "Feature",
  "properties": {
    "gn:admin1_code":"25",
    "gn:asciiname":"Stueng",
    "gn:country_code":"KH",
    "gn:dem":26,
    "gn:feature_class":"P",
    "gn:feature_code":"PPL",
    "gn:name":"Stueng",
    "gn:population":0,
    "gn:timezone":"Asia/Phnom_Penh",
    "iso:country":"KH",
    "name:khm_x_preferred":[
        "Stueng"
    ],
    "wof:name":"Stueng",
    "wof:placetype":"locality"
},
  "geometry": {"coordinates":[102.96316,13.78879],"type":"Point"}
}