{
  "type": "Feature",
  "properties": {
    "gn:admin1_code":"23.0",
    "gn:asciiname":"Deh",
    "gn:country_code":"KH",
    "gn:dem":226,
    "gn:feature_class":"P",
    "gn:feature_code":"PPL",
    "gn:name":"Deh",
    "gn:population":0,
    "gn:timezone":"Asia/Phnom_Penh",
    "iso:country":"KH",
    "name:khm_x_preferred":[
        "Deh"
    ],
    "name:snd_x_preferred":[
        "\u062f\u064a\u06be"
    ],
    "wof:name":"Deh",
    "wof:placetype":"locality"
},
  "geometry": {"coordinates":[107.27200999999999,13.64869],"type":"Point"}
}