{
  "type": "Feature",
  "properties": {
    "gn:admin1_code":"08",
    "gn:asciiname":"Prang",
    "gn:country_code":"KH",
    "gn:dem":1,
    "gn:feature_class":"P",
    "gn:feature_code":"PPL",
    "gn:name":"Prang",
    "gn:population":0,
    "gn:timezone":"Asia/Phnom_Penh",
    "iso:country":"KH",
    "name:deu_x_preferred":[
        "Prang"
    ],
    "name:khm_x_preferred":[
        "Prang"
    ],
    "name:und_x_variant":[
        "Phum\u012d Pre\u0103ng"
    ],
    "wof:name":"Prang",
    "wof:placetype":"locality"
},
  "geometry": {"coordinates":[103.66585000000001,11.15641],"type":"Point"}
}