{
  "type": "Feature",
  "properties": {
    "gn:admin1_code":"19",
    "gn:asciiname":"Phumi Prey Ph'av",
    "gn:country_code":"KH",
    "gn:dem":8,
    "gn:feature_class":"P",
    "gn:feature_code":"PPL",
    "gn:name":"Phum\u012d Prey Ph\u2019av",
    "gn:population":0,
    "gn:timezone":"Asia/Phnom_Penh",
    "iso:country":"KH",
    "name:und_x_variant":[
        "Phum Prey Phaao",
        "Phum\u012d Prey Phaav",
        "Phum\u012d Prey Ph\u2019av"
    ],
    "wof:name":"Phumi Prey Ph'av",
    "wof:placetype":"locality"
},
  "geometry": {"coordinates":[104.77014,10.94127],"type":"Point"}
}