{
  "type": "Feature",
  "properties": {
    "gn:admin1_code":"18",
    "gn:asciiname":"Phumi Angk Sala",
    "gn:country_code":"KH",
    "gn:dem":5,
    "gn:feature_class":"P",
    "gn:feature_code":"PPL",
    "gn:name":"Phum\u012d \u00c2ngk Sala",
    "gn:population":0,
    "gn:timezone":"Asia/Phnom_Penh",
    "iso:country":"KH",
    "name:und_x_variant":[
        "Phum Ang Sala",
        "Phum\u012d \u00c2ngk Sala"
    ],
    "wof:name":"Phumi Angk Sala",
    "wof:placetype":"locality"
},
  "geometry": {"coordinates":[105.68601,11.0888],"type":"Point"}
}