{
  "type": "Feature",
  "properties": {
    "gn:admin1_code":"31",
    "gn:asciiname":"Phumi Chak",
    "gn:country_code":"KH",
    "gn:dem":20,
    "gn:feature_class":"P",
    "gn:feature_code":"PPL",
    "gn:name":"Phum\u012d Ch\u00e2k",
    "gn:population":0,
    "gn:timezone":"Asia/Phnom_Penh",
    "iso:country":"KH",
    "name:und_x_variant":[
        "Phum Cha",
        "Phum\u012d Ch\u00e2k"
    ],
    "wof:name":"Phumi Chak",
    "wof:placetype":"locality"
},
  "geometry": {"coordinates":[105.59493000000001,11.77497],"type":"Point"}
}