{
  "type": "Feature",
  "properties": {
    "gn:admin1_code":"14",
    "gn:asciiname":"Kaoh Chuor Ti Pir",
    "gn:country_code":"KH",
    "gn:dem":11,
    "gn:feature_class":"P",
    "gn:feature_code":"PPL",
    "gn:name":"Kaoh Chuor Ti Pir",
    "gn:population":0,
    "gn:timezone":"Asia/Phnom_Penh",
    "iso:country":"KH",
    "name:khm_x_preferred":[
        "Kaoh Chuor Ti Pir"
    ],
    "wof:name":"Kaoh Chuor Ti Pir",
    "wof:placetype":"locality"
},
  "geometry": {"coordinates":[105.43728,11.02772],"type":"Point"}
}