{
  "type": "Feature",
  "properties": {
    "gn:admin1_code":"21",
    "gn:asciiname":"Srae Chea Khang Cheung",
    "gn:country_code":"KH",
    "gn:dem":32,
    "gn:feature_class":"P",
    "gn:feature_code":"PPL",
    "gn:name":"Srae Chea Khang Cheung",
    "gn:population":0,
    "gn:timezone":"Asia/Phnom_Penh",
    "iso:country":"KH",
    "name:khm_x_preferred":[
        "Srae Chea Khang Cheung"
    ],
    "name:und_x_variant":[
        "Khum Sr\u00e8 Ch\u00e9a",
        "Khum Sne Chea",
        "Phum\u012d Sr\u00ea Ch\u00e9a"
    ],
    "wof:name":"Srae Chea Khang Cheung",
    "wof:placetype":"locality"
},
  "geometry": {"coordinates":[104.43501999999999,10.66366],"type":"Point"}
}