{
  "type": "Feature",
  "properties": {
    "gn:admin1_code":"05",
    "gn:asciiname":"Phumi Kampong Preah Ent",
    "gn:country_code":"KH",
    "gn:dem":93,
    "gn:feature_class":"P",
    "gn:feature_code":"PPL",
    "gn:name":"Phum\u012d K\u00e2mp\u00f3ng Pre\u0103h \u0114nt",
    "gn:population":0,
    "gn:timezone":"Asia/Phnom_Penh",
    "iso:country":"KH",
    "name:und_x_variant":[
        "Ban Thapa Eun",
        "Phum\u012d K\u00e2mp\u00f4ng Pre\u0103h \u0114n",
        "Phum\u012d K\u00e2mp\u00f3ng Pre\u0103h \u0114nt"
    ],
    "wof:name":"Phumi Kampong Preah Ent",
    "wof:placetype":"locality"
},
  "geometry": {"coordinates":[105.84845,13.97569],"type":"Point"}
}