{
  "type": "Feature",
  "properties": {
    "gn:admin1_code":"25",
    "gn:asciiname":"Phum Moal Srah",
    "gn:country_code":"KH",
    "gn:dem":21,
    "gn:feature_class":"P",
    "gn:feature_code":"PPL",
    "gn:name":"Phum Mo\u00e2l Srah",
    "gn:population":0,
    "gn:timezone":"Asia/Phnom_Penh",
    "iso:country":"KH",
    "name:khm_x_preferred":[
        "Phum Mo\u00e2l Srah"
    ],
    "name:khm_x_variant":[
        "\u1797\u17bc\u1798\u17b7 \u1798\u17b6\u178f\u17cb\u179f\u17d2\u179a\u17c7"
    ],
    "wof:name":"Phum Moal Srah",
    "wof:placetype":"locality"
},
  "geometry": {"coordinates":[103.33538,13.74455],"type":"Point"}
}