{
  "type": "Feature",
  "properties": {
    "gn:admin1_code":"04",
    "gn:asciiname":"Srah Thul",
    "gn:country_code":"KH",
    "gn:dem":59,
    "gn:feature_class":"P",
    "gn:feature_code":"PPL",
    "gn:name":"Srah Thul",
    "gn:population":0,
    "gn:timezone":"Asia/Phnom_Penh",
    "iso:country":"KH",
    "name:khm_x_preferred":[
        "Srah Thul"
    ],
    "name:und_x_variant":[
        "Phum Sras Sothul",
        "Phum\u012d Sr\u0103h Th\u016dl"
    ],
    "wof:name":"Srah Thul",
    "wof:placetype":"locality"
},
  "geometry": {"coordinates":[104.54895,11.67366],"type":"Point"}
}