{
  "type": "Feature",
  "properties": {
    "gn:admin1_code":"31",
    "gn:asciiname":"Kbal Slaeng",
    "gn:country_code":"KH",
    "gn:dem":120,
    "gn:feature_class":"P",
    "gn:feature_code":"PPL",
    "gn:name":"Kbal Slaeng",
    "gn:population":0,
    "gn:timezone":"Asia/Phnom_Penh",
    "iso:country":"KH",
    "name:khm_x_preferred":[
        "Kbal Slaeng"
    ],
    "wof:name":"Kbal Slaeng",
    "wof:placetype":"locality"
},
  "geometry": {"coordinates":[106.31310999999999,11.78887],"type":"Point"}
}