{
  "type": "Feature",
  "properties": {
    "gn:admin1_code":"25",
    "gn:asciiname":"Khnhaer",
    "gn:country_code":"KH",
    "gn:dem":15,
    "gn:feature_class":"P",
    "gn:feature_code":"PPL",
    "gn:name":"Khnhaer",
    "gn:population":0,
    "gn:timezone":"Asia/Phnom_Penh",
    "iso:country":"KH",
    "name:khm_x_preferred":[
        "Khnhaer"
    ],
    "name:khm_x_variant":[
        "\u1797\u17bc\u1798\u17b7 \u1781\u17d2\u1789\u17c2\u179a",
        "Phum Khy\u00ear"
    ],
    "name:und_x_variant":[
        "Phum\u012d Khy\u00ear",
        "Phum\u012d Khnh\u00ear"
    ],
    "wof:name":"Khnhaer",
    "wof:placetype":"locality"
},
  "geometry": {"coordinates":[103.10665,13.67198],"type":"Point"}
}