{
  "type": "Feature",
  "properties": {
    "gn:admin1_code":"04",
    "gn:asciiname":"Dak Por",
    "gn:country_code":"KH",
    "gn:dem":68,
    "gn:feature_class":"P",
    "gn:feature_code":"PPL",
    "gn:name":"Dak Por",
    "gn:population":0,
    "gn:timezone":"Asia/Phnom_Penh",
    "iso:country":"KH",
    "name:und_x_variant":[
        "Phum\u012d D\u00e2k P\u00f4r"
    ],
    "wof:name":"Dak Por",
    "wof:placetype":"locality"
},
  "geometry": {"coordinates":[104.18947,11.4498],"type":"Point"}
}