{
  "type": "Feature",
  "properties": {
    "gn:admin1_code":"13",
    "gn:asciiname":"Pou",
    "gn:country_code":"KH",
    "gn:dem":68,
    "gn:feature_class":"P",
    "gn:feature_code":"PPL",
    "gn:name":"Pou",
    "gn:population":0,
    "gn:timezone":"Asia/Phnom_Penh",
    "iso:country":"KH",
    "name:khm_x_preferred":[
        "Pou"
    ],
    "name:und_x_variant":[
        "Phum Pou",
        "Phum Por",
        "Pouh",
        "Phum\u012d Po\u016dth\u012d"
    ],
    "wof:name":"Pou",
    "wof:placetype":"locality"
},
  "geometry": {"coordinates":[105.01661,13.8642],"type":"Point"}
}