{
  "type": "Feature",
  "properties": {
    "gn:admin1_code":"21",
    "gn:asciiname":"Phumi Boeng Takev",
    "gn:country_code":"KH",
    "gn:dem":2,
    "gn:feature_class":"P",
    "gn:feature_code":"PPL",
    "gn:name":"Phum\u012d B\u0153\u0306ng Tak\u00eav",
    "gn:population":0,
    "gn:timezone":"Asia/Phnom_Penh",
    "iso:country":"KH",
    "name:und_x_variant":[
        "Phum Beng Tak\u00e9v",
        "Phum\u012d B\u0153\u0306ng Tak\u00eav"
    ],
    "wof:name":"Phumi Boeng Takev",
    "wof:placetype":"locality"
},
  "geometry": {"coordinates":[104.17041999999999,10.62951],"type":"Point"}
}