{
  "type": "Feature",
  "properties": {
    "gn:admin1_code":"12.0",
    "gn:asciiname":"Bakan",
    "gn:country_code":"KH",
    "gn:dem":18,
    "gn:feature_class":"P",
    "gn:feature_code":"PPLA2",
    "gn:name":"Bakan",
    "gn:population":0,
    "gn:timezone":"Asia/Phnom_Penh",
    "iso:country":"KH",
    "name:ceb_x_preferred":[
        "Bakan"
    ],
    "name:deu_x_preferred":[
        "Bakan"
    ],
    "name:khm_x_preferred":[
        "Bakan"
    ],
    "name:swe_x_preferred":[
        "Bakan"
    ],
    "wof:name":"Bakan",
    "wof:placetype":"locality"
},
  "geometry": {"coordinates":[103.78579000000001,12.60209],"type":"Point"}
}