{
  "type": "Feature",
  "properties": {
    "iso:country":"KH",
    "name:deu_x_preferred":[
        "Prasat"
    ],
    "name:fra_x_preferred":[
        "Prasat"
    ],
    "name:ita_x_preferred":[
        "Prasat"
    ],
    "name:khm_x_preferred":[
        "\u1783\u17bb\u17c6\u1794\u17d2\u179a\u17b6\u179f\u17b6\u1791"
    ],
    "qs:gn_pop":0,
    "qs:name":"Prasat",
    "qs:name_adm0":"Cambodia",
    "qs:name_adm1":"Takev",
    "qs:photos":259,
    "qs:photos_1k":52,
    "qs:photos_9k":1,
    "qs:photos_9r":4,
    "qs:photos_all":259,
    "qs:photos_sr":5,
    "qs:placetype":"Town",
    "qs:pop_sr":"0",
    "qs:woe_adm0":23424776,
    "wd:wordcount":59,
    "wof:name":"Prasat",
    "wof:placetype":"locality"
},
  "geometry": {"coordinates":[104.751548,10.99335],"type":"Point"}
}