{
  "type": "Feature",
  "properties": {
    "gn:admin1_code":"08",
    "gn:asciiname":"Chamkar Kraom",
    "gn:country_code":"KH",
    "gn:dem":2,
    "gn:feature_class":"P",
    "gn:feature_code":"PPL",
    "gn:name":"Chamkar Kraom",
    "gn:population":0,
    "gn:timezone":"Asia/Phnom_Penh",
    "iso:country":"KH",
    "name:khm_x_preferred":[
        "Chamkar Kraom"
    ],
    "wof:name":"Chamkar Kraom",
    "wof:placetype":"locality"
},
  "geometry": {"coordinates":[103.7165,11.11457],"type":"Point"}
}