{
  "type": "Feature",
  "properties": {
    "gn:admin1_code":"03",
    "gn:asciiname":"Phumi Kbal Kanlong",
    "gn:country_code":"KH",
    "gn:dem":10,
    "gn:feature_class":"P",
    "gn:feature_code":"PPL",
    "gn:name":"Phum\u012d Kbal K\u00e2nl\u00f3ng",
    "gn:population":0,
    "gn:timezone":"Asia/Phnom_Penh",
    "iso:country":"KH",
    "name:und_x_variant":[
        "Phum\u012d Kbal K\u00e2nl\u00e2ng",
        "Phum\u012d Kbal K\u00e2nl\u00f3ng"
    ],
    "wof:name":"Phumi Kbal Kanlong",
    "wof:placetype":"locality"
},
  "geometry": {"coordinates":[104.81264,12.24006],"type":"Point"}
}