{
  "type": "Feature",
  "properties": {
    "gn:admin1_code":"24",
    "gn:asciiname":"Tmat Pong",
    "gn:country_code":"KH",
    "gn:dem":33,
    "gn:feature_class":"P",
    "gn:feature_code":"PPL",
    "gn:name":"Tmat Pong",
    "gn:population":0,
    "gn:timezone":"Asia/Phnom_Penh",
    "iso:country":"KH",
    "name:khm_x_preferred":[
        "Tmat Pong"
    ],
    "name:khm_x_variant":[
        "\u1797\u17bc\u1798\u17b7 \u178f\u17d2\u1798\u17b6\u178f\u1796\u1784",
        "Phum Tmat P\u00f4ng"
    ],
    "name:und_x_variant":[
        "Phum\u012d Tmat P\u00f4ng"
    ],
    "wof:name":"Tmat Pong",
    "wof:placetype":"locality"
},
  "geometry": {"coordinates":[103.99902,13.44405],"type":"Point"}
}