{
  "type": "Feature",
  "properties": {
    "gn:admin1_code":"27",
    "gn:asciiname":"Aekakpheap",
    "gn:country_code":"KH",
    "gn:dem":61,
    "gn:feature_class":"P",
    "gn:feature_code":"PPL",
    "gn:name":"Aekakpheap",
    "gn:population":0,
    "gn:timezone":"Asia/Phnom_Penh",
    "iso:country":"KH",
    "name:khm_x_preferred":[
        "Aekakpheap"
    ],
    "wof:name":"Aekakpheap",
    "wof:placetype":"locality"
},
  "geometry": {"coordinates":[104.11973,14.28975],"type":"Point"}
}