{
  "type": "Feature",
  "properties": {
    "gn:admin1_code":"25",
    "gn:asciiname":"Kbal Tonsaong",
    "gn:country_code":"KH",
    "gn:dem":76,
    "gn:feature_class":"P",
    "gn:feature_code":"PPL",
    "gn:name":"Kbal Tonsaong",
    "gn:population":0,
    "gn:timezone":"Asia/Phnom_Penh",
    "iso:country":"KH",
    "name:khm_x_preferred":[
        "Kbal Tonsaong"
    ],
    "name:khm_x_variant":[
        "\u1797\u17bc\u1798\u17b7 \u1780\u17d2\u1794\u17b6\u179b\u1791\u1793\u17d2\u179f\u17c4\u1784",
        "Phum Kbal T\u00f4nsa\u00f4ng"
    ],
    "name:und_x_variant":[
        "Phum Kbol T\u00f4nsa\u00f4ng",
        "Phum\u012d Kbal T\u00f4nsa\u00f4ng"
    ],
    "wof:name":"Kbal Tonsaong",
    "wof:placetype":"locality"
},
  "geometry": {"coordinates":[103.07253,14.0807],"type":"Point"}
}