{
  "type": "Feature",
  "properties": {
    "gn:admin1_code":"21",
    "gn:asciiname":"Ruessei Srok Khang Lech",
    "gn:country_code":"KH",
    "gn:dem":3,
    "gn:feature_class":"P",
    "gn:feature_code":"PPL",
    "gn:name":"Ruessei Srok Khang Lech",
    "gn:population":0,
    "gn:timezone":"Asia/Phnom_Penh",
    "iso:country":"KH",
    "name:khm_x_preferred":[
        "Ruessei Srok Khang Lech"
    ],
    "wof:name":"Ruessei Srok Khang Lech",
    "wof:placetype":"locality"
},
  "geometry": {"coordinates":[104.44185,10.44143],"type":"Point"}
}