{
  "type": "Feature",
  "properties": {
    "gn:admin1_code":"12",
    "gn:asciiname":"Poulyum",
    "gn:country_code":"KH",
    "gn:dem":21,
    "gn:feature_class":"P",
    "gn:feature_code":"PPL",
    "gn:name":"Poulyum",
    "gn:population":0,
    "gn:timezone":"Asia/Phnom_Penh",
    "iso:country":"KH",
    "name:khm_x_preferred":[
        "Poulyum"
    ],
    "wof:name":"Poulyum",
    "wof:placetype":"locality"
},
  "geometry": {"coordinates":[103.73831,12.58099],"type":"Point"}
}