{
  "type": "Feature",
  "properties": {
    "gn:admin1_code":"14",
    "gn:asciiname":"Chey A Khaol",
    "gn:country_code":"KH",
    "gn:dem":8,
    "gn:feature_class":"P",
    "gn:feature_code":"PPL",
    "gn:name":"Chey A Khaol",
    "gn:population":0,
    "gn:timezone":"Asia/Phnom_Penh",
    "iso:country":"KH",
    "name:khm_x_preferred":[
        "Chey A Khaol"
    ],
    "wof:name":"Chey A Khaol",
    "wof:placetype":"locality"
},
  "geometry": {"coordinates":[105.43447999999999,11.05415],"type":"Point"}
}