{
  "type": "Feature",
  "properties": {
    "gn:admin1_code":"31",
    "gn:asciiname":"Phum Kampong Ratt",
    "gn:country_code":"KH",
    "gn:dem":13,
    "gn:feature_class":"P",
    "gn:feature_code":"PPL",
    "gn:name":"Phum K\u00e2mp\u00f4ng Ratt",
    "gn:population":0,
    "gn:timezone":"Asia/Phnom_Penh",
    "iso:country":"KH",
    "name:khm_x_preferred":[
        "Phum K\u00e2mp\u00f4ng Ratt"
    ],
    "name:khm_x_variant":[
        "\u1797\u17bc\u1798\u17b7 \u1780\u17c6\u1796\u1784\u17cb\u179a\u17d0\u178f\u17d2\u1793"
    ],
    "name:und_x_variant":[
        "Phum Kompong Rat",
        "Phum\u012d K\u00e2mp\u00f4ng Ratt",
        "Phum\u012d K\u00e2mp\u00f3ng Ro\u0103tn"
    ],
    "wof:name":"Phum Kampong Ratt",
    "wof:placetype":"locality"
},
  "geometry": {"coordinates":[105.65227,12.21903],"type":"Point"}
}