{
  "type": "Feature",
  "properties": {
    "gn:admin1_code":"19",
    "gn:asciiname":"Phumi Andong Samret",
    "gn:country_code":"KH",
    "gn:dem":9,
    "gn:feature_class":"P",
    "gn:feature_code":"PPL",
    "gn:name":"Phum\u012d \u00c2ndong S\u00e2mr\u0115t",
    "gn:population":0,
    "gn:timezone":"Asia/Phnom_Penh",
    "iso:country":"KH",
    "name:und_x_variant":[
        "Phum Anlong Samreth",
        "Phum\u012d \u00c2ndong S\u00e2mr\u0115th",
        "Phum\u012d \u00c2ndong S\u00e2mr\u0115t"
    ],
    "wof:name":"Phumi Andong Samret",
    "wof:placetype":"locality"
},
  "geometry": {"coordinates":[104.87864,10.79373],"type":"Point"}
}