{
  "type": "Feature",
  "properties": {
    "gn:admin1_code":"24",
    "gn:asciiname":"Phum Skov",
    "gn:country_code":"KH",
    "gn:dem":86,
    "gn:feature_class":"P",
    "gn:feature_code":"PPL",
    "gn:name":"Phum Skov",
    "gn:population":0,
    "gn:timezone":"Asia/Phnom_Penh",
    "iso:country":"KH",
    "name:khm_x_preferred":[
        "Phum Skov"
    ],
    "name:khm_x_variant":[
        "\u1797\u17bc\u1798\u17b7 \u179f\u17d2\u1780\u179c"
    ],
    "name:und_x_variant":[
        "Phum\u012d Skov"
    ],
    "wof:name":"Phum Skov",
    "wof:placetype":"locality"
},
  "geometry": {"coordinates":[104.40302,13.95972],"type":"Point"}
}