{
  "type": "Feature",
  "properties": {
    "gn:admin1_code":"05",
    "gn:asciiname":"Srae Thum",
    "gn:country_code":"KH",
    "gn:dem":82,
    "gn:feature_class":"P",
    "gn:feature_code":"PPL",
    "gn:name":"Srae Thum",
    "gn:population":0,
    "gn:timezone":"Asia/Phnom_Penh",
    "iso:country":"KH",
    "name:khm_x_preferred":[
        "Srae Thum"
    ],
    "name:und_x_variant":[
        "Sre Thom",
        "Phum Sre Thom",
        "Phum\u012d Sr\u00ea Thom",
        "Sr\u00ea Thum"
    ],
    "wof:name":"Srae Thum",
    "wof:placetype":"locality"
},
  "geometry": {"coordinates":[105.10853,13.31626],"type":"Point"}
}