{
  "type": "Feature",
  "properties": {
    "gn:admin1_code":"24",
    "gn:asciiname":"Kambaor",
    "gn:country_code":"KH",
    "gn:dem":24,
    "gn:feature_class":"P",
    "gn:feature_code":"PPL",
    "gn:name":"Kambaor",
    "gn:population":0,
    "gn:timezone":"Asia/Phnom_Penh",
    "iso:country":"KH",
    "name:khm_x_preferred":[
        "Kambaor"
    ],
    "name:khm_x_variant":[
        "Phum K\u00e2mp\u00f4s",
        "\u1797\u17bc\u1798\u17b7 \u1780\u17c6\u1796\u179f\u17cb"
    ],
    "name:und_x_variant":[
        "Phum Kompor",
        "Phum\u012d K\u00e2mp\u00f3s"
    ],
    "wof:name":"Kambaor",
    "wof:placetype":"locality"
},
  "geometry": {"coordinates":[103.499,13.6569],"type":"Point"}
}