{
  "type": "Feature",
  "properties": {
    "gn:admin1_code":"12.0",
    "gn:asciiname":"Phum Sdok Roung",
    "gn:country_code":"KH",
    "gn:dem":15,
    "gn:feature_class":"P",
    "gn:feature_code":"PPL",
    "gn:name":"Phum Sd\u014fk Ro\u016dng",
    "gn:population":0,
    "gn:timezone":"Asia/Phnom_Penh",
    "iso:country":"KH",
    "name:khm_x_preferred":[
        "Phum Sd\u014fk Ro\u016dng"
    ],
    "name:khm_x_variant":[
        "\u1797\u17bc\u1798\u17b7 \u179f\u17d2\u178a\u17bb\u1780\u179a\u17c4\u1784"
    ],
    "wof:name":"Phum Sdok Roung",
    "wof:placetype":"locality"
},
  "geometry": {"coordinates":[103.92791,12.63471],"type":"Point"}
}