{
  "type": "Feature",
  "properties": {
    "gn:admin1_code":"27",
    "gn:asciiname":"Ampil",
    "gn:country_code":"KH",
    "gn:dem":38,
    "gn:feature_class":"P",
    "gn:feature_code":"PPL",
    "gn:name":"Ampil",
    "gn:population":0,
    "gn:timezone":"Asia/Phnom_Penh",
    "iso:country":"KH",
    "name:khm_x_preferred":[
        "\u1797\u17bc\u1798\u17b7 \u17a2\u17c6\u1796\u17b7\u179b"
    ],
    "name:khm_x_variant":[
        "Phum \u00c2mp\u012dl"
    ],
    "name:und_x_variant":[
        "Phum\u012d \u00c2mp\u012dl"
    ],
    "wof:name":"Ampil",
    "wof:placetype":"locality"
},
  "geometry": {"coordinates":[103.54616,14.04652],"type":"Point"}
}