{
  "type": "Feature",
  "properties": {
    "gn:admin1_code":"21",
    "gn:asciiname":"Phumi Chheuteal",
    "gn:country_code":"KH",
    "gn:dem":33,
    "gn:feature_class":"P",
    "gn:feature_code":"PPL",
    "gn:name":"Phum\u012d Chheut\u00e9al",
    "gn:population":0,
    "gn:timezone":"Asia/Phnom_Penh",
    "iso:country":"KH",
    "name:und_x_variant":[
        "Phum\u012d Chheut\u00e9al"
    ],
    "wof:name":"Phumi Chheuteal",
    "wof:placetype":"locality"
},
  "geometry": {"coordinates":[104.45021,10.84715],"type":"Point"}
}