{
  "type": "Feature",
  "properties": {
    "gn:admin1_code":"9.0",
    "gn:asciiname":"Preaek Prang",
    "gn:country_code":"KH",
    "gn:dem":9,
    "gn:feature_class":"P",
    "gn:feature_code":"PPL",
    "gn:name":"Preaek Prang",
    "gn:population":0,
    "gn:timezone":"Asia/Phnom_Penh",
    "iso:country":"KH",
    "name:khm_x_preferred":[
        "Preaek Prang"
    ],
    "name:khm_x_variant":[
        "\u1797\u17bc\u1798\u17b7 \u1796\u17d2\u179a\u17c2\u1780 \u1794\u17d2\u179a\u17b6\u17c6\u1784",
        "Phum Pr\u00eak Pr\u0103ng"
    ],
    "wof:name":"Preaek Prang",
    "wof:placetype":"locality"
},
  "geometry": {"coordinates":[106.02298999999999,12.37771],"type":"Point"}
}