{
  "type": "Feature",
  "properties": {
    "gn:admin1_code":"31",
    "gn:asciiname":"Sampov Lun",
    "gn:country_code":"KH",
    "gn:dem":53,
    "gn:feature_class":"P",
    "gn:feature_code":"PPL",
    "gn:name":"Sampov Lun",
    "gn:population":0,
    "gn:timezone":"Asia/Phnom_Penh",
    "iso:country":"KH",
    "name:khm_x_preferred":[
        "Sampov Lun"
    ],
    "wof:name":"Sampov Lun",
    "wof:placetype":"locality"
},
  "geometry": {"coordinates":[106.22414000000001,11.91512],"type":"Point"}
}