{
  "type": "Feature",
  "properties": {
    "gn:admin1_code":"03",
    "gn:asciiname":"Kangkaeb",
    "gn:country_code":"KH",
    "gn:dem":26,
    "gn:feature_class":"P",
    "gn:feature_code":"PPL",
    "gn:name":"Kangkaeb",
    "gn:population":0,
    "gn:timezone":"Asia/Phnom_Penh",
    "iso:country":"KH",
    "name:khm_x_preferred":[
        "Kangkaeb"
    ],
    "name:und_x_variant":[
        "Sre Ket",
        "Phum\u012d Phn\u016dm K\u00e2ng\u00eap",
        "Phum\u012d Phnum K\u00e2ngk\u00eab"
    ],
    "wof:name":"Kangkaeb",
    "wof:placetype":"locality"
},
  "geometry": {"coordinates":[104.79222,12.41049],"type":"Point"}
}