{
  "type": "Feature",
  "properties": {
    "gn:admin1_code":"28",
    "gn:asciiname":"Phum Ta Thuok",
    "gn:country_code":"KH",
    "gn:dem":2,
    "gn:feature_class":"P",
    "gn:feature_code":"PPL",
    "gn:name":"Phum Ta Thu\u014fk",
    "gn:population":0,
    "gn:timezone":"Asia/Phnom_Penh",
    "iso:country":"KH",
    "name:khm_x_preferred":[
        "Phum Ta Thu\u014fk"
    ],
    "name:khm_x_variant":[
        "\u1797\u17bc\u1798\u17b7 \u178f\u17b6\u1786\u17bc\u1780"
    ],
    "name:und_x_variant":[
        "Phum\u012d Ta Chhu\u014fk"
    ],
    "wof:name":"Phum Ta Thuok",
    "wof:placetype":"locality"
},
  "geometry": {"coordinates":[103.83816,10.77917],"type":"Point"}
}