{
  "type": "Feature",
  "properties": {
    "gn:admin1_code":"7.0",
    "gn:asciiname":"Phum Daeum Pou Kraom",
    "gn:country_code":"KH",
    "gn:dem":7,
    "gn:feature_class":"P",
    "gn:feature_code":"PPL",
    "gn:name":"Phum Daeum Po\u016d Kra\u00f4m",
    "gn:population":0,
    "gn:timezone":"Asia/Phnom_Penh",
    "iso:country":"KH",
    "name:khm_x_preferred":[
        "Phum Daeum Po\u016d Kra\u00f4m"
    ],
    "name:khm_x_variant":[
        "\u1797\u17bc\u1798\u17b7 \u178a\u17be\u1798\u1796\u17c4\u1792\u17b7\u1780\u17d2\u179a\u17c4\u1798"
    ],
    "wof:name":"Phum Daeum Pou Kraom",
    "wof:placetype":"locality"
},
  "geometry": {"coordinates":[105.07451,11.06255],"type":"Point"}
}