{
  "type": "Feature",
  "properties": {
    "gn:admin1_code":"28",
    "gn:asciiname":"Phumi Tali",
    "gn:country_code":"KH",
    "gn:dem":19,
    "gn:feature_class":"P",
    "gn:feature_code":"PPL",
    "gn:name":"Phum\u012d Tali",
    "gn:population":0,
    "gn:timezone":"Asia/Phnom_Penh",
    "iso:country":"KH",
    "name:und_x_variant":[
        "Ta Ly",
        "Phum\u012d Taly",
        "Phum\u012d Tali"
    ],
    "wof:name":"Phumi Tali",
    "wof:placetype":"locality"
},
  "geometry": {"coordinates":[103.79532,10.49569],"type":"Point"}
}