{
  "type": "Feature",
  "properties": {
    "gn:admin1_code":"29",
    "gn:asciiname":"Ou Chrab",
    "gn:country_code":"KH",
    "gn:dem":195,
    "gn:feature_class":"P",
    "gn:feature_code":"PPL",
    "gn:name":"Ou Chrab",
    "gn:population":0,
    "gn:timezone":"Asia/Phnom_Penh",
    "iso:country":"KH",
    "name:khm_x_preferred":[
        "Ou Chrab"
    ],
    "name:khm_x_variant":[
        "\u1797\u17bc\u1798\u17b7 \u17a2\u17bc\u1785\u17d2\u179a\u17b6\u1798 \u1798\u17bd\u1799",
        "Phum O Chrap"
    ],
    "name:und_x_variant":[
        "Phum\u012d O Chrap (1)",
        "Phum\u012d O Chrab (1)"
    ],
    "wof:name":"Ou Chrab",
    "wof:placetype":"locality"
},
  "geometry": {"coordinates":[102.75136999999999,12.65066],"type":"Point"}
}