{
  "type": "Feature",
  "properties": {
    "gn:admin1_code":"09",
    "gn:asciiname":"Phum Prek Prasap Kraom",
    "gn:country_code":"KH",
    "gn:dem":26,
    "gn:feature_class":"P",
    "gn:feature_code":"PPL",
    "gn:name":"Phum Pr\u00eak Pr\u00e2s\u00e2p Kra\u00f4m",
    "gn:population":0,
    "gn:timezone":"Asia/Phnom_Penh",
    "iso:country":"KH",
    "name:khm_x_preferred":[
        "Phum Pr\u00eak Pr\u00e2s\u00e2p Kra\u00f4m"
    ],
    "name:khm_x_variant":[
        "\u1797\u17bc\u1798\u17b7 \u1796\u17d2\u179a\u17c2\u1780\u1794\u17d2\u179a\u179f\u1794\u17cb\u1780\u17d2\u179a\u17c4\u1798"
    ],
    "name:und_x_variant":[
        "Prek Prasap",
        "Phum\u012d Pr\u00eak Pr\u00e2s\u00e1b Kra\u00f4m"
    ],
    "wof:name":"Phum Prek Prasap Kraom",
    "wof:placetype":"locality"
},
  "geometry": {"coordinates":[106.03655999999999,12.35069],"type":"Point"}
}