{
  "type": "Feature",
  "properties": {
    "gn:admin1_code":"21",
    "gn:asciiname":"Svay Tong Khang Cheung",
    "gn:country_code":"KH",
    "gn:dem":4,
    "gn:feature_class":"P",
    "gn:feature_code":"PPL",
    "gn:name":"Svay Tong Khang Cheung",
    "gn:population":0,
    "gn:timezone":"Asia/Phnom_Penh",
    "iso:country":"KH",
    "name:khm_x_preferred":[
        "Svay Tong Khang Cheung"
    ],
    "wof:name":"Svay Tong Khang Cheung",
    "wof:placetype":"locality"
},
  "geometry": {"coordinates":[104.42524,10.4927],"type":"Point"}
}