{
  "type": "Feature",
  "properties": {
    "gn:admin1_code":"12",
    "gn:asciiname":"Damrei Sa",
    "gn:country_code":"KH",
    "gn:dem":20,
    "gn:feature_class":"P",
    "gn:feature_code":"PPL",
    "gn:name":"Damrei Sa",
    "gn:population":0,
    "gn:timezone":"Asia/Phnom_Penh",
    "iso:country":"KH",
    "name:khm_x_preferred":[
        "Damrei Sa"
    ],
    "name:khm_x_variant":[
        "\u1797\u17bc\u1798\u17b7 \u178a\u17c6\u179a\u17b8\u179f\u179a"
    ],
    "name:und_x_variant":[
        "P\u2019um D\u00e2mrei S\u00e2r",
        "Phum\u012d D\u00e2mrei S\u00e2r",
        "Phum D\u00e2mrei S\u00e2r"
    ],
    "wof:name":"Damrei Sa",
    "wof:placetype":"locality"
},
  "geometry": {"coordinates":[103.89658,12.63298],"type":"Point"}
}