{
  "type": "Feature",
  "properties": {
    "gn:admin1_code":"21",
    "gn:asciiname":"Phumi O Kandaol",
    "gn:country_code":"KH",
    "gn:dem":13,
    "gn:feature_class":"P",
    "gn:feature_code":"PPL",
    "gn:name":"Phum\u012d O K\u00e2nda\u00f4l",
    "gn:population":0,
    "gn:timezone":"Asia/Phnom_Penh",
    "iso:country":"KH",
    "name:und_x_variant":[
        "Phum Kandol",
        "Phum\u012d O K\u00e2nda\u00f4l"
    ],
    "wof:name":"Phumi O Kandaol",
    "wof:placetype":"locality"
},
  "geometry": {"coordinates":[104.48457999999999,10.71573],"type":"Point"}
}