{
  "type": "Feature",
  "properties": {
    "gn:admin1_code":"24",
    "gn:asciiname":"Phumi Chranieng",
    "gn:country_code":"KH",
    "gn:dem":28,
    "gn:feature_class":"P",
    "gn:feature_code":"PPL",
    "gn:name":"Phum\u012d Chr\u00e2ni\u0115ng",
    "gn:population":0,
    "gn:timezone":"Asia/Phnom_Penh",
    "iso:country":"KH",
    "name:und_x_variant":[
        "Chrameng",
        "Phum\u012d Chr\u00e2ni\u0115ng"
    ],
    "wof:name":"Phumi Chranieng",
    "wof:placetype":"locality"
},
  "geometry": {"coordinates":[103.55294000000001,13.89163],"type":"Point"}
}