{
  "type": "Feature",
  "properties": {
    "gn:admin1_code":"08",
    "gn:asciiname":"Chamlang Kor",
    "gn:country_code":"KH",
    "gn:dem":6,
    "gn:feature_class":"P",
    "gn:feature_code":"PPL",
    "gn:name":"Chamlang Kor",
    "gn:population":0,
    "gn:timezone":"Asia/Phnom_Penh",
    "iso:country":"KH",
    "name:khm_x_preferred":[
        "Chamlang Kor"
    ],
    "name:khm_x_variant":[
        "\u1785\u17c6\u17a1\u1784\u1782\u17c4",
        "Ch\u00e2ml\u00e2ng Ko\u016d Mu\u014fy"
    ],
    "name:und_x_variant":[
        "Phum Sachla",
        "Ch\u00e2ml\u00e2ng Ko\u016d"
    ],
    "wof:name":"Chamlang Kor",
    "wof:placetype":"locality"
},
  "geometry": {"coordinates":[103.37806,10.88169],"type":"Point"}
}