{
  "type": "Feature",
  "properties": {
    "gn:admin1_code":"05",
    "gn:asciiname":"Phumi Kdam Ha",
    "gn:country_code":"KH",
    "gn:dem":18,
    "gn:feature_class":"P",
    "gn:feature_code":"PPL",
    "gn:name":"Phum\u012d Kdam Ha",
    "gn:population":0,
    "gn:timezone":"Asia/Phnom_Penh",
    "iso:country":"KH",
    "name:und_x_variant":[
        "Phum Kadamha",
        "Phum Kadamba",
        "Phum\u012d Kdam Ha"
    ],
    "wof:name":"Phumi Kdam Ha",
    "wof:placetype":"locality"
},
  "geometry": {"coordinates":[105.11377,12.38127],"type":"Point"}
}