{
  "type": "Feature",
  "properties": {
    "gn:admin1_code":"24",
    "gn:asciiname":"Romiet",
    "gn:country_code":"KH",
    "gn:dem":31,
    "gn:feature_class":"P",
    "gn:feature_code":"PPL",
    "gn:name":"Romiet",
    "gn:population":0,
    "gn:timezone":"Asia/Phnom_Penh",
    "iso:country":"KH",
    "name:khm_x_preferred":[
        "Romiet"
    ],
    "name:khm_x_variant":[
        "\u1797\u17bc\u1798\u17b7 \u179a\u1798\u17c0\u178f",
        "Phum\u012d R\u00f4mi\u0115t",
        "Phum R\u00f4mi\u0115t"
    ],
    "wof:name":"Romiet",
    "wof:placetype":"locality"
},
  "geometry": {"coordinates":[103.72242,13.63518],"type":"Point"}
}