{
  "type": "Feature",
  "properties": {
    "gn:admin1_code":"22",
    "gn:asciiname":"Phumi Pratheat",
    "gn:country_code":"KH",
    "gn:dem":13,
    "gn:feature_class":"P",
    "gn:feature_code":"PPL",
    "gn:name":"Phum\u012d Pr\u00e2th\u00e9at",
    "gn:population":0,
    "gn:timezone":"Asia/Phnom_Penh",
    "iso:country":"KH",
    "name:und_x_variant":[
        "Pr\u00e9as Theat",
        "Phum\u012d Pr\u00e2th\u00e9at"
    ],
    "wof:name":"Phumi Pratheat",
    "wof:placetype":"locality"
},
  "geometry": {"coordinates":[104.87332000000001,11.43776],"type":"Point"}
}