{
  "type": "Feature",
  "properties": {
    "gn:admin1_code":"10",
    "gn:asciiname":"Phum Sre Thnaot",
    "gn:country_code":"KH",
    "gn:dem":92,
    "gn:feature_class":"P",
    "gn:feature_code":"PPL",
    "gn:name":"Phum Sr\u00ea Thna\u00f4t",
    "gn:population":0,
    "gn:timezone":"Asia/Phnom_Penh",
    "iso:country":"KH",
    "name:khm_x_preferred":[
        "Phum Sr\u00ea Thna\u00f4t"
    ],
    "name:khm_x_variant":[
        "\u1797\u17bc\u1798\u17b7 \u179f\u17d2\u179a\u17c2\u178f\u17d2\u1793\u17c4\u178f"
    ],
    "name:und_x_variant":[
        "Rer",
        "Phum\u012d Sr\u00ea Thno\u00e2t",
        "Phum\u012d Sr\u00ea Tna\u00f4t"
    ],
    "wof:name":"Phum Sre Thnaot",
    "wof:placetype":"locality"
},
  "geometry": {"coordinates":[106.42932999999999,13.17145],"type":"Point"}
}