{
  "type": "Feature",
  "properties": {
    "gn:admin1_code":"05",
    "gn:asciiname":"Phumi Trang Traeu",
    "gn:country_code":"KH",
    "gn:dem":18,
    "gn:feature_class":"P",
    "gn:feature_code":"PPL",
    "gn:name":"Phum\u012d Tr\u0103ng Traeu",
    "gn:population":0,
    "gn:timezone":"Asia/Phnom_Penh",
    "iso:country":"KH",
    "name:und_x_variant":[
        "Phum Tang Troeu",
        "Phum\u012d Tr\u0103ng Traeu"
    ],
    "wof:name":"Phumi Trang Traeu",
    "wof:placetype":"locality"
},
  "geometry": {"coordinates":[105.09993,12.23852],"type":"Point"}
}