{
  "type": "Feature",
  "properties": {
    "gn:admin1_code":"04",
    "gn:asciiname":"Phumi Pouthi Ta Deng",
    "gn:country_code":"KH",
    "gn:dem":37,
    "gn:feature_class":"P",
    "gn:feature_code":"PPL",
    "gn:name":"Phum\u012d Po\u016dth\u012d Ta D\u00eang",
    "gn:population":0,
    "gn:timezone":"Asia/Phnom_Penh",
    "iso:country":"KH",
    "name:und_x_variant":[
        "Phum Tadeng",
        "Phum\u012d Pa\u016d Ta D\u00eang",
        "Phum\u012d Po\u016dth\u012d Ta D\u00eang"
    ],
    "wof:name":"Phumi Pouthi Ta Deng",
    "wof:placetype":"locality"
},
  "geometry": {"coordinates":[104.55405,11.15349],"type":"Point"}
}