{
  "type": "Feature",
  "properties": {
    "gn:admin1_code":"31",
    "gn:asciiname":"Rumchek",
    "gn:country_code":"KH",
    "gn:dem":36,
    "gn:feature_class":"P",
    "gn:feature_code":"PPL",
    "gn:name":"Rumchek",
    "gn:population":0,
    "gn:timezone":"Asia/Phnom_Penh",
    "iso:country":"KH",
    "name:khm_x_preferred":[
        "Rumchek"
    ],
    "name:und_x_variant":[
        "Phum\u012d Khpop",
        "Phum Kpop",
        "Phum\u012d Khp\u00f4b"
    ],
    "wof:name":"Rumchek",
    "wof:placetype":"locality"
},
  "geometry": {"coordinates":[106.03830000000001,12.05908],"type":"Point"}
}