{
  "type": "Feature",
  "properties": {
    "gn:admin1_code":"04",
    "gn:asciiname":"Phumi Trapeang Sala",
    "gn:country_code":"KH",
    "gn:dem":32,
    "gn:feature_class":"P",
    "gn:feature_code":"PPL",
    "gn:name":"Phum\u012d Tr\u00e2pe\u0103ng Sala",
    "gn:population":0,
    "gn:timezone":"Asia/Phnom_Penh",
    "iso:country":"KH",
    "name:und_x_variant":[
        "Phum Trapeang Sla",
        "Phum\u012d Tr\u00e2pe\u0103ng Sala"
    ],
    "wof:name":"Phumi Trapeang Sala",
    "wof:placetype":"locality"
},
  "geometry": {"coordinates":[104.61569,11.16156],"type":"Point"}
}