{
  "type": "Feature",
  "properties": {
    "gn:admin1_code":"22",
    "gn:asciiname":"Preaek Thmei",
    "gn:country_code":"KH",
    "gn:dem":13,
    "gn:feature_class":"P",
    "gn:feature_code":"PPL",
    "gn:name":"Preaek Thmei",
    "gn:population":0,
    "gn:timezone":"Asia/Phnom_Penh",
    "iso:country":"KH",
    "name:khm_x_preferred":[
        "Preaek Thmei"
    ],
    "name:khm_x_variant":[
        "\u1797\u17bc\u1798\u17b7 \u1796\u17d2\u179a\u17c2\u1780\u1790\u17d2\u1798\u17b8",
        "Phum Pr\u00eak Thmei"
    ],
    "name:und_x_variant":[
        "Phum Prek Thmey",
        "Phum\u012d Pr\u00eak Thmei"
    ],
    "wof:name":"Preaek Thmei",
    "wof:placetype":"locality"
},
  "geometry": {"coordinates":[105.00312,11.46932],"type":"Point"}
}