{
  "type": "Feature",
  "properties": {
    "gn:admin1_code":"05",
    "gn:asciiname":"Phumi Svay Chek",
    "gn:country_code":"KH",
    "gn:dem":38,
    "gn:feature_class":"P",
    "gn:feature_code":"PPL",
    "gn:name":"Phum\u012d Svay Ch\u00e9k",
    "gn:population":0,
    "gn:timezone":"Asia/Phnom_Penh",
    "iso:country":"KH",
    "wof:name":"Phumi Svay Chek",
    "wof:placetype":"locality"
},
  "geometry": {"coordinates":[105.38333,12.43333],"type":"Point"}
}