{
  "type": "Feature",
  "properties": {
    "gn:admin1_code":"27",
    "gn:asciiname":"Samraong",
    "gn:country_code":"KH",
    "gn:dem":52,
    "gn:feature_class":"P",
    "gn:feature_code":"PPLA",
    "gn:name":"Samraong",
    "gn:population":18694,
    "gn:timezone":"Asia/Phnom_Penh",
    "iso:country":"KH",
    "name:fra_x_preferred":[
        "Phumi Samraong"
    ],
    "name:ind_x_preferred":[
        "Samraong"
    ],
    "name:ita_x_preferred":[
        "Samraong"
    ],
    "name:khm_x_preferred":[
        "\u1780\u17d2\u179a\u17bb\u1784\u179f\u17c6\u179a\u17c4\u1784"
    ],
    "name:kor_x_preferred":[
        "\uc0bc\ub77c\uc639"
    ],
    "name:nld_x_preferred":[
        "Phumi Samraong"
    ],
    "name:pnb_x_preferred":[
        "\u0633\u0627\u0645\u0631\u0627\u0624\u0646\u06af"
    ],
    "name:pol_x_preferred":[
        "Phumi Samraong"
    ],
    "name:por_x_preferred":[
        "Samraong"
    ],
    "name:ron_x_preferred":[
        "Phumi Samraong"
    ],
    "name:rus_x_preferred":[
        "\u0421\u0430\u043c\u0440\u043e\u0443\u043d\u0433"
    ],
    "name:tha_x_preferred":[
        "\u0e2a\u0e33\u0e42\u0e23\u0e07"
    ],
    "name:und_x_variant":[
        "Somrong",
        "Phumi S\u00e2mro\u016dng",
        "S\u00e2mra\u00f4ng",
        "Phum\u012d S\u00e2mr\u00f4ng",
        "Samrong",
        "Phum\u012d S\u00e2mra\u00f4ng"
    ],
    "name:vie_x_preferred":[
        "Samraong"
    ],
    "name:war_x_preferred":[
        "Samraong"
    ],
    "name:zho_x_preferred":[
        "\u4e09\u9686"
    ],
    "wof:name":"Samraong",
    "wof:placetype":"locality",
    "wof:population":18694
},
  "geometry": {"coordinates":[103.51761,14.18175],"type":"Point"}
}