{
  "type": "Feature",
  "properties": {
    "gn:admin1_code":"27",
    "gn:asciiname":"Samraong",
    "gn:country_code":"KH",
    "gn:dem":52,
    "gn:feature_class":"P",
    "gn:feature_code":"PPLA",
    "gn:name":"Samraong",
    "gn:population":18694,
    "gn:timezone":"Asia/Phnom_Penh",
    "iso:country":"KH",
    "name:und_x_variant":[
        "Somrong",
        "Phumi S\u00e2mro\u016dng",
        "S\u00e2mra\u00f4ng",
        "Phum\u012d S\u00e2mr\u00f4ng",
        "Samrong",
        "Phum\u012d S\u00e2mra\u00f4ng",
        "Samraong"
    ],
    "wof:name":"Samraong",
    "wof:placetype":"locality",
    "wof:population":18694
},
  "geometry": {"coordinates":[103.51761,14.18175],"type":"Point"}
}