{
  "type": "Feature",
  "properties": {
    "gn:admin1_code":"02",
    "gn:asciiname":"Kokor",
    "gn:country_code":"KH",
    "gn:dem":17,
    "gn:feature_class":"P",
    "gn:feature_code":"PPL",
    "gn:name":"Kokor",
    "gn:population":0,
    "gn:timezone":"Asia/Phnom_Penh",
    "iso:country":"KH",
    "name:khm_x_preferred":[
        "Kokor"
    ],
    "name:und_x_variant":[
        "Phum\u012d K\u00f4k\u00f4r"
    ],
    "wof:name":"Kokor",
    "wof:placetype":"locality"
},
  "geometry": {"coordinates":[105.37199,11.94062],"type":"Point"}
}