{
  "type": "Feature",
  "properties": {
    "gn:admin1_code":"28",
    "gn:asciiname":"Ou Oknha Heng",
    "gn:country_code":"KH",
    "gn:dem":8,
    "gn:feature_class":"P",
    "gn:feature_code":"PPL",
    "gn:name":"Ou Oknha Heng",
    "gn:population":0,
    "gn:timezone":"Asia/Phnom_Penh",
    "iso:country":"KH",
    "name:khm_x_preferred":[
        "Ou Oknha Heng"
    ],
    "wof:name":"Ou Oknha Heng",
    "wof:placetype":"locality"
},
  "geometry": {"coordinates":[103.74378,10.58246],"type":"Point"}
}