{
  "type": "Feature",
  "properties": {
    "gn:admin1_code":"19",
    "gn:asciiname":"Phumi Chambak",
    "gn:country_code":"KH",
    "gn:dem":11,
    "gn:feature_class":"P",
    "gn:feature_code":"PPL",
    "gn:name":"Phum\u012d Ch\u00e2mb\u00e1k",
    "gn:population":0,
    "gn:timezone":"Asia/Phnom_Penh",
    "iso:country":"KH",
    "name:und_x_variant":[
        "Chambak",
        "Phar Chambak",
        "Phai Chambak",
        "Phum\u012d Ch\u00e2mb\u00e1k"
    ],
    "wof:name":"Phumi Chambak",
    "wof:placetype":"locality"
},
  "geometry": {"coordinates":[104.81193,11.24233],"type":"Point"}
}