{
  "type": "Feature",
  "properties": {
    "gn:admin1_code":"07",
    "gn:asciiname":"Phumi Sa Romeang",
    "gn:country_code":"KH",
    "gn:dem":25,
    "gn:feature_class":"P",
    "gn:feature_code":"PPL",
    "gn:name":"Phum\u012d S\u00e2 R\u00f4me\u0103ng",
    "gn:population":0,
    "gn:timezone":"Asia/Phnom_Penh",
    "iso:country":"KH",
    "name:und_x_variant":[
        "Sar Romeang",
        "Phum\u012d S\u00e2 R\u00f4me\u0103ng"
    ],
    "wof:name":"Phumi Sa Romeang",
    "wof:placetype":"locality"
},
  "geometry": {"coordinates":[104.72358,11.46175],"type":"Point"}
}