{
  "type": "Feature",
  "properties": {
    "gn:admin1_code":"18",
    "gn:asciiname":"Phumi Tapang",
    "gn:country_code":"KH",
    "gn:dem":15,
    "gn:feature_class":"P",
    "gn:feature_code":"PPL",
    "gn:name":"Phum\u012d Tapang",
    "gn:population":0,
    "gn:timezone":"Asia/Phnom_Penh",
    "iso:country":"KH",
    "name:und_x_variant":[
        "Phum Taoang",
        "Phum\u012d Tapang"
    ],
    "wof:name":"Phumi Tapang",
    "wof:placetype":"locality"
},
  "geometry": {"coordinates":[105.67328000000001,11.31851],"type":"Point"}
}