{
  "type": "Feature",
  "properties": {
    "gn:admin1_code":"29",
    "gn:asciiname":"Tuol Ta Sokh",
    "gn:country_code":"KH",
    "gn:dem":18,
    "gn:feature_class":"P",
    "gn:feature_code":"PPL",
    "gn:name":"Tuol Ta Sokh",
    "gn:population":0,
    "gn:timezone":"Asia/Phnom_Penh",
    "iso:country":"KH",
    "name:khm_x_preferred":[
        "Tuol Ta Sokh"
    ],
    "name:khm_x_variant":[
        "\u1797\u17bc\u1798\u17b7 \u1791\u17bd\u179b\u178f\u17b6\u179f\u17bb\u1780",
        "Phum Tu\u014fl Tas\u014fk"
    ],
    "name:und_x_variant":[
        "Phum\u012d Tu\u014fl Tas\u014fk"
    ],
    "wof:name":"Tuol Ta Sokh",
    "wof:placetype":"locality"
},
  "geometry": {"coordinates":[103.0138,13.28729],"type":"Point"}
}