{
  "type": "Feature",
  "properties": {
    "gn:admin1_code":"13",
    "gn:asciiname":"Yeang",
    "gn:country_code":"KH",
    "gn:dem":73,
    "gn:feature_class":"P",
    "gn:feature_code":"PPL",
    "gn:name":"Yeang",
    "gn:population":0,
    "gn:timezone":"Asia/Phnom_Penh",
    "iso:country":"KH",
    "name:und_x_variant":[
        "Phum\u012d Y\u00e9ang"
    ],
    "wof:name":"Yeang",
    "wof:placetype":"locality"
},
  "geometry": {"coordinates":[104.6712,14.06334],"type":"Point"}
}