{
  "type": "Feature",
  "properties": {
    "gn:admin1_code":"13",
    "gn:asciiname":"Kampong Sralau Pir",
    "gn:country_code":"KH",
    "gn:dem":95,
    "gn:feature_class":"P",
    "gn:feature_code":"PPL",
    "gn:name":"Kampong Sralau Pir",
    "gn:population":0,
    "gn:timezone":"Asia/Phnom_Penh",
    "iso:country":"KH",
    "wof:name":"Kampong Sralau Pir",
    "wof:placetype":"locality"
},
  "geometry": {"coordinates":[105.80822000000001,14.00822],"type":"Point"}
}