{
  "type": "Feature",
  "properties": {
    "gn:admin1_code":"02",
    "gn:asciiname":"Phumi Svay Prey",
    "gn:country_code":"KH",
    "gn:dem":10,
    "gn:feature_class":"P",
    "gn:feature_code":"PPL",
    "gn:name":"Phum\u012d Svay Prey",
    "gn:population":0,
    "gn:timezone":"Asia/Phnom_Penh",
    "iso:country":"KH",
    "name:und_x_variant":[
        "San V\u00e9k",
        "Phum\u012d Svay Prey"
    ],
    "wof:name":"Phumi Svay Prey",
    "wof:placetype":"locality"
},
  "geometry": {"coordinates":[104.98569999999999,12.14097],"type":"Point"}
}