{
  "type": "Feature",
  "properties": {
    "gn:admin1_code":"27",
    "gn:asciiname":"Kaoh Thmei",
    "gn:country_code":"KH",
    "gn:dem":55,
    "gn:feature_class":"P",
    "gn:feature_code":"PPL",
    "gn:name":"Kaoh Thmei",
    "gn:population":0,
    "gn:timezone":"Asia/Phnom_Penh",
    "iso:country":"KH",
    "name:khm_x_preferred":[
        "Kaoh Thmei"
    ],
    "wof:name":"Kaoh Thmei",
    "wof:placetype":"locality"
},
  "geometry": {"coordinates":[104.08647999999999,14.24755],"type":"Point"}
}