{
  "type": "Feature",
  "properties": {
    "gn:admin1_code":"13",
    "gn:asciiname":"Svay Damnak Thmei",
    "gn:country_code":"KH",
    "gn:dem":86,
    "gn:feature_class":"P",
    "gn:feature_code":"PPL",
    "gn:name":"Svay Damnak Thmei",
    "gn:population":0,
    "gn:timezone":"Asia/Phnom_Penh",
    "iso:country":"KH",
    "name:khm_x_preferred":[
        "Svay Damnak Thmei"
    ],
    "name:und_x_variant":[
        "Phum Svay Dannac",
        "Phum\u012d Svay D\u00e2mn\u0103k"
    ],
    "wof:name":"Svay Damnak Thmei",
    "wof:placetype":"locality"
},
  "geometry": {"coordinates":[104.90577,13.32334],"type":"Point"}
}