{
  "type": "Feature",
  "properties": {
    "gn:admin1_code":"07",
    "gn:asciiname":"Svay Prey",
    "gn:country_code":"KH",
    "gn:dem":12,
    "gn:feature_class":"P",
    "gn:feature_code":"PPL",
    "gn:name":"Svay Prey",
    "gn:population":0,
    "gn:timezone":"Asia/Phnom_Penh",
    "iso:country":"KH",
    "name:khm_x_preferred":[
        "Svay Prey"
    ],
    "name:und_x_variant":[
        "Svai Prey",
        "Phum\u012d T\u0153\u0306k N\u0153\u0306m"
    ],
    "wof:name":"Svay Prey",
    "wof:placetype":"locality"
},
  "geometry": {"coordinates":[104.88634,11.3922],"type":"Point"}
}