{
  "type": "Feature",
  "properties": {
    "gn:admin1_code":"9.0",
    "gn:asciiname":"Srae Haen",
    "gn:country_code":"KH",
    "gn:dem":31,
    "gn:feature_class":"P",
    "gn:feature_code":"PPL",
    "gn:name":"Srae Haen",
    "gn:population":0,
    "gn:timezone":"Asia/Phnom_Penh",
    "iso:country":"KH",
    "name:khm_x_preferred":[
        "Srae Haen"
    ],
    "wof:name":"Srae Haen",
    "wof:placetype":"locality"
},
  "geometry": {"coordinates":[106.01931999999999,12.63504],"type":"Point"}
}