{
  "type": "Feature",
  "properties": {
    "gn:admin1_code":"25",
    "gn:asciiname":"Phum Kouk Svay",
    "gn:country_code":"KH",
    "gn:dem":37,
    "gn:feature_class":"P",
    "gn:feature_code":"PPL",
    "gn:name":"Phum Ko\u016dk Svay",
    "gn:population":0,
    "gn:timezone":"Asia/Phnom_Penh",
    "iso:country":"KH",
    "name:khm_x_preferred":[
        "Phum Ko\u016dk Svay"
    ],
    "name:khm_x_variant":[
        "\u1797\u17bc\u1798\u17b7 \u1782\u17c4\u1780\u179f\u17d2\u179c\u17b6\u1799"
    ],
    "name:und_x_variant":[
        "Phum\u012d Ko\u016dk Svay (2)"
    ],
    "wof:name":"Phum Kouk Svay",
    "wof:placetype":"locality"
},
  "geometry": {"coordinates":[103.01843,13.87438],"type":"Point"}
}