{
  "type": "Feature",
  "properties": {
    "gn:admin1_code":"14",
    "gn:asciiname":"Phumi Chambak Kaong",
    "gn:country_code":"KH",
    "gn:dem":14,
    "gn:feature_class":"P",
    "gn:feature_code":"PPL",
    "gn:name":"Phum\u012d Ch\u00e2mb\u00e1k Ka\u00f4ng",
    "gn:population":0,
    "gn:timezone":"Asia/Phnom_Penh",
    "iso:country":"KH",
    "name:und_x_variant":[
        "Phum Chombok Kong",
        "Phum\u012d Ch\u00e2mb\u00e1k Ka\u00f4ng"
    ],
    "wof:name":"Phumi Chambak Kaong",
    "wof:placetype":"locality"
},
  "geometry": {"coordinates":[105.58207,11.616],"type":"Point"}
}