{
  "type": "Feature",
  "properties": {
    "gn:admin1_code":"31",
    "gn:asciiname":"Srae Saom Chas",
    "gn:country_code":"KH",
    "gn:dem":43,
    "gn:feature_class":"P",
    "gn:feature_code":"PPL",
    "gn:name":"Srae Saom Chas",
    "gn:population":0,
    "gn:timezone":"Asia/Phnom_Penh",
    "iso:country":"KH",
    "name:khm_x_preferred":[
        "Srae Saom Chas"
    ],
    "name:und_x_variant":[
        "Phum\u012d Sr\u00ea Sa\u00f4m Chas"
    ],
    "wof:name":"Srae Saom Chas",
    "wof:placetype":"locality"
},
  "geometry": {"coordinates":[106.15118,11.95949],"type":"Point"}
}