{
  "type": "Feature",
  "properties": {
    "gn:admin1_code":"02",
    "gn:asciiname":"Phumi Takret",
    "gn:country_code":"KH",
    "gn:dem":16,
    "gn:feature_class":"P",
    "gn:feature_code":"PPL",
    "gn:name":"Phum\u012d Takr\u0115t",
    "gn:population":0,
    "gn:timezone":"Asia/Phnom_Penh",
    "iso:country":"KH",
    "name:und_x_variant":[
        "Takret",
        "Phum\u012d Takr\u0115t"
    ],
    "wof:name":"Phumi Takret",
    "wof:placetype":"locality"
},
  "geometry": {"coordinates":[105.13526,12.02067],"type":"Point"}
}