{
  "type": "Feature",
  "properties": {
    "gn:admin1_code":"24.0",
    "gn:asciiname":"Phum Sala Kanseng",
    "gn:country_code":"KH",
    "gn:dem":19,
    "gn:feature_class":"P",
    "gn:feature_code":"PPL",
    "gn:name":"Phum Sala K\u00e2ns\u00eang",
    "gn:population":0,
    "gn:timezone":"Asia/Phnom_Penh",
    "iso:country":"KH",
    "name:khm_x_preferred":[
        "Phum Sala K\u00e2ns\u00eang"
    ],
    "name:khm_x_variant":[
        "\u1797\u17bc\u1798\u17b7 \u179f\u17b6\u179b\u17b6\u1780\u1793\u17d2\u179f\u17c2\u1784"
    ],
    "wof:name":"Phum Sala Kanseng",
    "wof:placetype":"locality"
},
  "geometry": {"coordinates":[103.84739,13.36711],"type":"Point"}
}