{
  "type": "Feature",
  "properties": {
    "gn:admin1_code":"13",
    "gn:asciiname":"Ou Ta Louk",
    "gn:country_code":"KH",
    "gn:dem":69,
    "gn:feature_class":"P",
    "gn:feature_code":"PPL",
    "gn:name":"Ou Ta Louk",
    "gn:population":0,
    "gn:timezone":"Asia/Phnom_Penh",
    "iso:country":"KH",
    "name:khm_x_preferred":[
        "Ou Ta Louk"
    ],
    "wof:name":"Ou Ta Louk",
    "wof:placetype":"locality"
},
  "geometry": {"coordinates":[105.0247,13.4079],"type":"Point"}
}