{
  "type": "Feature",
  "properties": {
    "gn:admin1_code":"25",
    "gn:asciiname":"Kamping Puoy",
    "gn:country_code":"KH",
    "gn:dem":24,
    "gn:feature_class":"P",
    "gn:feature_code":"PPL",
    "gn:name":"Kamping Puoy",
    "gn:population":0,
    "gn:timezone":"Asia/Phnom_Penh",
    "iso:country":"KH",
    "name:khm_x_preferred":[
        "Kamping Puoy"
    ],
    "name:khm_x_variant":[
        "Phum K\u00e2mpring Pu\u014fy",
        "\u1797\u17bc\u1798\u17b7 \u1780\u17c6\u1796\u17b8\u1784\u1796\u17bd\u1799"
    ],
    "name:und_x_variant":[
        "Phum Pring Porey",
        "Phum\u012d K\u00e2mpring Pu\u014fy"
    ],
    "wof:name":"Kamping Puoy",
    "wof:placetype":"locality"
},
  "geometry": {"coordinates":[103.36874,13.78094],"type":"Point"}
}