{
  "type": "Feature",
  "properties": {
    "gn:admin1_code":"13",
    "gn:asciiname":"Kdol",
    "gn:country_code":"KH",
    "gn:dem":71,
    "gn:feature_class":"P",
    "gn:feature_code":"PPL",
    "gn:name":"Kdol",
    "gn:population":0,
    "gn:timezone":"Asia/Phnom_Penh",
    "iso:country":"KH",
    "name:khm_x_preferred":[
        "Kdol"
    ],
    "wof:name":"Kdol",
    "wof:placetype":"locality"
},
  "geometry": {"coordinates":[105.27503,13.80668],"type":"Point"}
}