{
  "type": "Feature",
  "properties": {
    "gn:admin1_code":"25",
    "gn:asciiname":"Phum Banchet Bos",
    "gn:country_code":"KH",
    "gn:dem":20,
    "gn:feature_class":"P",
    "gn:feature_code":"PPL",
    "gn:name":"Phum B\u00e2nch\u0115t Bos",
    "gn:population":0,
    "gn:timezone":"Asia/Phnom_Penh",
    "iso:country":"KH",
    "name:khm_x_preferred":[
        "Phum B\u00e2nch\u0115t Bos"
    ],
    "name:khm_x_variant":[
        "\u1797\u17bc\u1798\u17b7 \u1794\u1789\u17d2\u1785\u17b7\u178f\u1794\u17bb\u179f"
    ],
    "name:und_x_variant":[
        "Phum\u012d B\u00e2nch\u0115t Bos",
        "Phum\u012d B\u00e2nhch\u0115t B\u014fs"
    ],
    "wof:name":"Phum Banchet Bos",
    "wof:placetype":"locality"
},
  "geometry": {"coordinates":[103.25618,13.70249],"type":"Point"}
}