{
  "type": "Feature",
  "properties": {
    "gn:admin1_code":"19",
    "gn:asciiname":"Phumi Trabek Kamphaeum",
    "gn:country_code":"KH",
    "gn:dem":13,
    "gn:feature_class":"P",
    "gn:feature_code":"PPL",
    "gn:name":"Phum\u012d Tr\u00e2b\u00eak K\u00e2mphaeum",
    "gn:population":0,
    "gn:timezone":"Asia/Phnom_Penh",
    "iso:country":"KH",
    "name:und_x_variant":[
        "Trabek Komph\u00f3m",
        "Phum\u012d Tr\u00e2b\u00eak K\u00e2mphaeum"
    ],
    "wof:name":"Phumi Trabek Kamphaeum",
    "wof:placetype":"locality"
},
  "geometry": {"coordinates":[104.87336999999999,11.31028],"type":"Point"}
}