{
  "type": "Feature",
  "properties": {
    "gn:admin1_code":"14",
    "gn:asciiname":"Phum Tbong Kdei",
    "gn:country_code":"KH",
    "gn:dem":12,
    "gn:feature_class":"P",
    "gn:feature_code":"PPL",
    "gn:name":"Phum Tbong Kdei",
    "gn:population":0,
    "gn:timezone":"Asia/Phnom_Penh",
    "iso:country":"KH",
    "name:khm_x_preferred":[
        "Phum Tbong Kdei"
    ],
    "name:khm_x_variant":[
        "\u1797\u17bc\u1798\u17b7 \u178f\u17d2\u1794\u17bc\u1784\u1780\u17d2\u178a\u17b8"
    ],
    "name:und_x_variant":[
        "Phum Thbaung Kdey",
        "Phum\u012d Tbong Kdei"
    ],
    "wof:name":"Phum Tbong Kdei",
    "wof:placetype":"locality"
},
  "geometry": {"coordinates":[105.42910000000001,11.47282],"type":"Point"}
}