{
  "type": "Feature",
  "properties": {
    "gn:admin1_code":"24.0",
    "gn:asciiname":"Phum Popel",
    "gn:country_code":"KH",
    "gn:dem":14,
    "gn:feature_class":"P",
    "gn:feature_code":"PPL",
    "gn:name":"Phum P\u00f4p\u00e9l",
    "gn:population":0,
    "gn:timezone":"Asia/Phnom_Penh",
    "iso:country":"KH",
    "name:khm_x_preferred":[
        "Phum P\u00f4p\u00e9l"
    ],
    "name:khm_x_variant":[
        "\u1797\u17bc\u1798\u17b7 \u1796\u1796\u17c1\u179b"
    ],
    "wof:name":"Phum Popel",
    "wof:placetype":"locality"
},
  "geometry": {"coordinates":[104.39959,13.05263],"type":"Point"}
}