{
  "type": "Feature",
  "properties": {
    "gn:admin1_code":"18",
    "gn:asciiname":"Teahean Kraom",
    "gn:country_code":"KH",
    "gn:dem":10,
    "gn:feature_class":"P",
    "gn:feature_code":"PPL",
    "gn:name":"Teahean Kraom",
    "gn:population":0,
    "gn:timezone":"Asia/Phnom_Penh",
    "iso:country":"KH",
    "name:khm_x_preferred":[
        "Teahean Kraom"
    ],
    "wof:name":"Teahean Kraom",
    "wof:placetype":"locality"
},
  "geometry": {"coordinates":[105.86046,11.04491],"type":"Point"}
}