{
  "type": "Feature",
  "properties": {
    "gn:admin1_code":"29",
    "gn:asciiname":"Phum Boeng Trabek",
    "gn:country_code":"KH",
    "gn:dem":82,
    "gn:feature_class":"P",
    "gn:feature_code":"PPL",
    "gn:name":"Phum B\u0153\u0306ng Tr\u00e2b\u00eak",
    "gn:population":0,
    "gn:timezone":"Asia/Phnom_Penh",
    "iso:country":"KH",
    "name:khm_x_preferred":[
        "Phum B\u0153\u0306ng Tr\u00e2b\u00eak"
    ],
    "name:khm_x_variant":[
        "\u1797\u17bc\u1798\u17b7 \u1794\u17b9\u1784\u178f\u17d2\u179a\u1794\u17c2\u1780",
        "Phum\u012d B\u0153\u0306ng Tr\u00e2b\u00eak"
    ],
    "wof:name":"Phum Boeng Trabek",
    "wof:placetype":"locality"
},
  "geometry": {"coordinates":[102.81135999999999,12.8517],"type":"Point"}
}