{
  "type": "Feature",
  "properties": {
    "gn:admin1_code":"12",
    "gn:asciiname":"Phum Sala Khet",
    "gn:country_code":"KH",
    "gn:dem":22,
    "gn:feature_class":"P",
    "gn:feature_code":"PPL",
    "gn:name":"Phum Sala Kh\u00eat",
    "gn:population":0,
    "gn:timezone":"Asia/Phnom_Penh",
    "iso:country":"KH",
    "name:khm_x_preferred":[
        "Phum Sala Kh\u00eat"
    ],
    "name:khm_x_variant":[
        "\u1797\u17bc\u1798\u17b7 \u179f\u17b6\u179b\u17b6\u1781\u17c1\u178f\u17d2\u178f"
    ],
    "name:und_x_variant":[
        "P\u2019um Sal\u0103",
        "Phum\u012d Sala Kh\u00eat"
    ],
    "wof:name":"Phum Sala Khet",
    "wof:placetype":"locality"
},
  "geometry": {"coordinates":[103.86761,12.5979],"type":"Point"}
}