{
  "type": "Feature",
  "properties": {
    "gn:admin1_code":"03",
    "gn:asciiname":"Phumi Seh Slab",
    "gn:country_code":"KH",
    "gn:dem":5,
    "gn:feature_class":"P",
    "gn:feature_code":"PPL",
    "gn:name":"Phum\u012d S\u00e9h Sl\u0103b",
    "gn:population":0,
    "gn:timezone":"Asia/Phnom_Penh",
    "iso:country":"KH",
    "name:und_x_variant":[
        "Kompong Ses Slap",
        "Phum\u012d Sh\u00e9h Slap",
        "Phum\u012d S\u00e9h Sl\u0103b"
    ],
    "wof:name":"Phumi Seh Slab",
    "wof:placetype":"locality"
},
  "geometry": {"coordinates":[104.49717,12.49876],"type":"Point"}
}