{
  "type": "Feature",
  "properties": {
    "gn:admin1_code":"07",
    "gn:asciiname":"Teaen",
    "gn:country_code":"KH",
    "gn:dem":21,
    "gn:feature_class":"P",
    "gn:feature_code":"PPL",
    "gn:name":"Teaen",
    "gn:population":0,
    "gn:timezone":"Asia/Phnom_Penh",
    "iso:country":"KH",
    "name:khm_x_preferred":[
        "Teaen"
    ],
    "name:und_x_variant":[
        "Ti\u00e9n",
        "Phum\u012d T\u00ean"
    ],
    "wof:name":"Teaen",
    "wof:placetype":"locality"
},
  "geometry": {"coordinates":[104.76354000000001,11.45658],"type":"Point"}
}