{
  "type": "Feature",
  "properties": {
    "gn:admin1_code":"25.0",
    "gn:asciiname":"Tbaeng Chas",
    "gn:country_code":"KH",
    "gn:dem":53,
    "gn:feature_class":"P",
    "gn:feature_code":"PPL",
    "gn:name":"Tbaeng Chas",
    "gn:population":0,
    "gn:timezone":"Asia/Phnom_Penh",
    "iso:country":"KH",
    "name:khm_x_preferred":[
        "Tbaeng Chas"
    ],
    "wof:name":"Tbaeng Chas",
    "wof:placetype":"locality"
},
  "geometry": {"coordinates":[103.1498,14.10676],"type":"Point"}
}