{
  "type": "Feature",
  "properties": {
    "gn:admin1_code":"07",
    "gn:asciiname":"Phumi Thonmont",
    "gn:country_code":"KH",
    "gn:dem":10,
    "gn:feature_class":"P",
    "gn:feature_code":"PPL",
    "gn:name":"Phum\u012d Th\u00f3nm\u00f4nt",
    "gn:population":0,
    "gn:timezone":"Asia/Phnom_Penh",
    "iso:country":"KH",
    "name:und_x_variant":[
        "Tuol Kango",
        "Phum\u012d Th\u016dnm\u016dn",
        "Phum\u012d Th\u00f3nm\u00f4nt"
    ],
    "wof:name":"Phumi Thonmont",
    "wof:placetype":"locality"
},
  "geometry": {"coordinates":[104.98223,11.31787],"type":"Point"}
}