{
  "type": "Feature",
  "properties": {
    "gn:admin1_code":"19",
    "gn:asciiname":"Phumi Angkunh",
    "gn:country_code":"KH",
    "gn:dem":13,
    "gn:feature_class":"P",
    "gn:feature_code":"PPL",
    "gn:name":"Phum\u012d \u00c2ngk\u016dnh",
    "gn:population":0,
    "gn:timezone":"Asia/Phnom_Penh",
    "iso:country":"KH",
    "name:und_x_variant":[
        "Phum Ang Konh",
        "Phum\u012d \u00c2ngk\u016dnh"
    ],
    "wof:name":"Phumi Angkunh",
    "wof:placetype":"locality"
},
  "geometry": {"coordinates":[104.84011,10.83654],"type":"Point"}
}