{
  "type": "Feature",
  "properties": {
    "gn:admin1_code":"04",
    "gn:asciiname":"Phumi Svay Chrum",
    "gn:country_code":"KH",
    "gn:dem":76,
    "gn:feature_class":"P",
    "gn:feature_code":"PPL",
    "gn:name":"Phum\u012d Svay Chr\u016dm",
    "gn:population":0,
    "gn:timezone":"Asia/Phnom_Penh",
    "iso:country":"KH",
    "wof:name":"Phumi Svay Chrum",
    "wof:placetype":"locality"
},
  "geometry": {"coordinates":[104.55542,11.33101],"type":"Point"}
}