{
  "type": "Feature",
  "properties": {
    "gn:admin1_code":"24.0",
    "gn:asciiname":"Bos Lhong",
    "gn:country_code":"KH",
    "gn:dem":32,
    "gn:feature_class":"P",
    "gn:feature_code":"PPL",
    "gn:name":"Bos Lhong",
    "gn:population":0,
    "gn:timezone":"Asia/Phnom_Penh",
    "iso:country":"KH",
    "name:khm_x_preferred":[
        "Bos Lhong"
    ],
    "name:khm_x_variant":[
        "\u1797\u17bc\u1798\u17b7 \u1794\u17bb\u17c7\u179b\u17d2\u17a0\u17bb\u1784",
        "Phum\u012d B\u014fh L\u00f4hong"
    ],
    "wof:name":"Bos Lhong",
    "wof:placetype":"locality"
},
  "geometry": {"coordinates":[103.68795,13.7015],"type":"Point"}
}