{
  "type": "Feature",
  "properties": {
    "gn:admin1_code":"25",
    "gn:asciiname":"Ou Ampil",
    "gn:country_code":"KH",
    "gn:dem":44,
    "gn:feature_class":"P",
    "gn:feature_code":"PPL",
    "gn:name":"Ou Ampil",
    "gn:population":0,
    "gn:timezone":"Asia/Phnom_Penh",
    "iso:country":"KH",
    "name:khm_x_preferred":[
        "Ou Ampil"
    ],
    "wof:name":"Ou Ampil",
    "wof:placetype":"locality"
},
  "geometry": {"coordinates":[102.57523999999999,13.55208],"type":"Point"}
}