{
  "type": "Feature",
  "properties": {
    "gn:admin1_code":"07",
    "gn:asciiname":"Phumi Andong",
    "gn:country_code":"KH",
    "gn:dem":11,
    "gn:feature_class":"P",
    "gn:feature_code":"PPL",
    "gn:name":"Phum\u012d \u00c2ndong",
    "gn:population":0,
    "gn:timezone":"Asia/Phnom_Penh",
    "iso:country":"KH",
    "name:und_x_variant":[
        "Andong",
        "Phum\u012d \u00c2ndong"
    ],
    "wof:name":"Phumi Andong",
    "wof:placetype":"locality"
},
  "geometry": {"coordinates":[104.96777,11.29535],"type":"Point"}
}