{
  "type": "Feature",
  "properties": {
    "gn:admin1_code":"14",
    "gn:asciiname":"Peanea Kandal",
    "gn:country_code":"KH",
    "gn:dem":14,
    "gn:feature_class":"P",
    "gn:feature_code":"PPL",
    "gn:name":"Peanea Kandal",
    "gn:population":0,
    "gn:timezone":"Asia/Phnom_Penh",
    "iso:country":"KH",
    "name:khm_x_preferred":[
        "Peanea Kandal"
    ],
    "name:und_x_variant":[
        "Phum\u012d P\u00e9an\u00e9a"
    ],
    "wof:name":"Peanea Kandal",
    "wof:placetype":"locality"
},
  "geometry": {"coordinates":[105.46605,11.70325],"type":"Point"}
}