{
  "type": "Feature",
  "properties": {
    "gn:admin1_code":"29",
    "gn:asciiname":"Phumi Sang Reang Knong",
    "gn:country_code":"KH",
    "gn:dem":27,
    "gn:feature_class":"P",
    "gn:feature_code":"PPL",
    "gn:name":"Phum\u012d S\u0103ng Re\u0103ng Kn\u014fng",
    "gn:population":0,
    "gn:timezone":"Asia/Phnom_Penh",
    "iso:country":"KH",
    "name:und_x_variant":[
        "Khum Sang Rang",
        "Phum\u012d S\u0103ng R\u0103ng Kn\u014fng",
        "Phum\u012d S\u0103ng Re\u0103ng Kn\u014fng"
    ],
    "wof:name":"Phumi Sang Reang Knong",
    "wof:placetype":"locality"
},
  "geometry": {"coordinates":[103.09071,12.84558],"type":"Point"}
}