{
  "type": "Feature",
  "properties": {
    "gn:admin1_code":"12",
    "gn:asciiname":"Svay Sa",
    "gn:country_code":"KH",
    "gn:dem":56,
    "gn:feature_class":"P",
    "gn:feature_code":"PPL",
    "gn:name":"Svay Sa",
    "gn:population":0,
    "gn:timezone":"Asia/Phnom_Penh",
    "iso:country":"KH",
    "name:khm_x_preferred":[
        "Svay Sa"
    ],
    "name:khm_x_variant":[
        "\u1797\u17bc\u1798\u17b7 \u179f\u17d2\u179c\u17b6\u1799\u179f\u179a",
        "Phum Svay S\u00e2"
    ],
    "name:und_x_variant":[
        "Svay S\u0101r",
        "Phum\u012d Svay S\u00e2",
        "Phum\u012d Svay S\u00e2r"
    ],
    "wof:name":"Svay Sa",
    "wof:placetype":"locality"
},
  "geometry": {"coordinates":[104.11566999999999,12.35277],"type":"Point"}
}