{
  "type": "Feature",
  "properties": {
    "gn:admin1_code":"25",
    "gn:asciiname":"Phum Kouk Kieng",
    "gn:country_code":"KH",
    "gn:dem":21,
    "gn:feature_class":"P",
    "gn:feature_code":"PPL",
    "gn:name":"Phum Ko\u016dk Ki\u0115ng",
    "gn:population":0,
    "gn:timezone":"Asia/Phnom_Penh",
    "iso:country":"KH",
    "name:khm_x_preferred":[
        "Phum Ko\u016dk Ki\u0115ng"
    ],
    "name:khm_x_variant":[
        "\u1797\u17bc\u1798\u17b7 \u1782\u17c4\u1780\u17c0\u1784"
    ],
    "name:und_x_variant":[
        "Phum\u012d Ko\u016dk Ki\u0115ng"
    ],
    "wof:name":"Phum Kouk Kieng",
    "wof:placetype":"locality"
},
  "geometry": {"coordinates":[103.39876,13.8261],"type":"Point"}
}