{
  "type": "Feature",
  "properties": {
    "gn:admin1_code":"24.0",
    "gn:asciiname":"Trapeang Trom",
    "gn:country_code":"KH",
    "gn:dem":32,
    "gn:feature_class":"P",
    "gn:feature_code":"PPL",
    "gn:name":"Trapeang Trom",
    "gn:population":0,
    "gn:timezone":"Asia/Phnom_Penh",
    "iso:country":"KH",
    "name:khm_x_preferred":[
        "Trapeang Trom"
    ],
    "wof:name":"Trapeang Trom",
    "wof:placetype":"locality"
},
  "geometry": {"coordinates":[104.11074000000001,13.34559],"type":"Point"}
}