{
  "type": "Feature",
  "properties": {
    "gn:admin1_code":"27",
    "gn:asciiname":"Sala Reang",
    "gn:country_code":"KH",
    "gn:dem":51,
    "gn:feature_class":"P",
    "gn:feature_code":"PPL",
    "gn:name":"Sala Reang",
    "gn:population":0,
    "gn:timezone":"Asia/Phnom_Penh",
    "iso:country":"KH",
    "name:khm_x_preferred":[
        "Sala Reang"
    ],
    "wof:name":"Sala Reang",
    "wof:placetype":"locality"
},
  "geometry": {"coordinates":[103.30110999999999,14.18991],"type":"Point"}
}