{
  "type": "Feature",
  "properties": {
    "gn:admin1_code":"10.0",
    "gn:asciiname":"Spean Mean Chey",
    "gn:country_code":"KH",
    "gn:dem":696,
    "gn:feature_class":"P",
    "gn:feature_code":"PPL",
    "gn:name":"Spean Mean Chey",
    "gn:population":0,
    "gn:timezone":"Asia/Phnom_Penh",
    "iso:country":"KH",
    "name:khm_x_preferred":[
        "Spean Mean Chey"
    ],
    "wof:name":"Spean Mean Chey",
    "wof:placetype":"locality"
},
  "geometry": {"coordinates":[107.202,12.47764],"type":"Point"}
}