{
  "type": "Feature",
  "properties": {
    "gn:admin1_code":"29",
    "gn:asciiname":"Ou Samrel Kraom",
    "gn:country_code":"KH",
    "gn:dem":143,
    "gn:feature_class":"P",
    "gn:feature_code":"PPL",
    "gn:name":"Ou Samrel Kraom",
    "gn:population":0,
    "gn:timezone":"Asia/Phnom_Penh",
    "iso:country":"KH",
    "wof:name":"Ou Samrel Kraom",
    "wof:placetype":"locality"
},
  "geometry": {"coordinates":[102.84247999999999,12.51137],"type":"Point"}
}