{
  "type": "Feature",
  "properties": {
    "gn:admin1_code":"24.0",
    "gn:asciiname":"Spean Thmei",
    "gn:country_code":"KH",
    "gn:dem":39,
    "gn:feature_class":"P",
    "gn:feature_code":"PPL",
    "gn:name":"Spean Thmei",
    "gn:population":0,
    "gn:timezone":"Asia/Phnom_Penh",
    "iso:country":"KH",
    "name:khm_x_preferred":[
        "Spean Thmei"
    ],
    "wof:name":"Spean Thmei",
    "wof:placetype":"locality"
},
  "geometry": {"coordinates":[103.88064,13.53875],"type":"Point"}
}