{
  "type": "Feature",
  "properties": {
    "gn:admin1_code":"29",
    "gn:asciiname":"Phum Rolum",
    "gn:country_code":"KH",
    "gn:dem":63,
    "gn:feature_class":"P",
    "gn:feature_code":"PPL",
    "gn:name":"Phum R\u00f4lum",
    "gn:population":0,
    "gn:timezone":"Asia/Phnom_Penh",
    "iso:country":"KH",
    "name:khm_x_preferred":[
        "Phum R\u00f4lum"
    ],
    "name:khm_x_variant":[
        "\u1797\u17bc\u1798\u17b7 \u179a\u179b\u17c6"
    ],
    "wof:name":"Phum Rolum",
    "wof:placetype":"locality"
},
  "geometry": {"coordinates":[102.86404,12.83832],"type":"Point"}
}