{
  "type": "Feature",
  "properties": {
    "gn:admin1_code":"29",
    "gn:asciiname":"Phum Phlov Meas",
    "gn:country_code":"KH",
    "gn:dem":66,
    "gn:feature_class":"P",
    "gn:feature_code":"PPL",
    "gn:name":"Phum Phlov M\u00e9as",
    "gn:population":0,
    "gn:timezone":"Asia/Phnom_Penh",
    "iso:country":"KH",
    "name:khm_x_preferred":[
        "Phum Phlov M\u00e9as"
    ],
    "name:khm_x_variant":[
        "\u1797\u17bc\u1798\u17b7 \u1795\u17d2\u179b\u17bc\u179c\u1798\u17b6\u179f"
    ],
    "name:und_x_variant":[
        "Phum Phlauv Meas",
        "Phum Phlaux Meas",
        "Phum\u012d Phlov M\u00e9as",
        "Phlov Meas"
    ],
    "wof:name":"Phum Phlov Meas",
    "wof:placetype":"locality"
},
  "geometry": {"coordinates":[102.87745,12.75997],"type":"Point"}
}