{
  "type": "Feature",
  "properties": {
    "gn:admin1_code":"25",
    "gn:asciiname":"Ou Prasat",
    "gn:country_code":"KH",
    "gn:dem":20,
    "gn:feature_class":"P",
    "gn:feature_code":"PPL",
    "gn:name":"Ou Prasat",
    "gn:population":0,
    "gn:timezone":"Asia/Phnom_Penh",
    "iso:country":"KH",
    "name:khm_x_preferred":[
        "Ou Prasat"
    ],
    "name:khm_x_variant":[
        "\u1797\u17bc\u1798\u17b7 \u17a2 \u1794\u17d2\u179a\u17b6\u179f\u17b6\u1791",
        "Phum O Prasat",
        "\u1783\u17bb\u17c6\u17a2\u17bc\u179a\u1794\u17d2\u179a\u17b6\u179f\u17b6\u1791"
    ],
    "name:pol_x_preferred":[
        "\u2019\u00c2or Prasat"
    ],
    "name:spa_x_preferred":[
        "Ou Prasat"
    ],
    "name:und_x_variant":[
        "Khum O Prasath",
        "Khum Au Prasath",
        "Phum\u012d O Prasat"
    ],
    "wof:name":"Ou Prasat",
    "wof:placetype":"locality"
},
  "geometry": {"coordinates":[102.99875,13.46816],"type":"Point"}
}