{
  "type": "Feature",
  "properties": {
    "gn:admin1_code":"25",
    "gn:asciiname":"Nimitt",
    "gn:country_code":"KH",
    "gn:dem":24,
    "gn:feature_class":"P",
    "gn:feature_code":"PPL",
    "gn:name":"Nimitt",
    "gn:population":0,
    "gn:timezone":"Asia/Phnom_Penh",
    "iso:country":"KH",
    "name:khm_x_preferred":[
        "Nimitt"
    ],
    "name:khm_x_variant":[
        "\u1797\u17bc\u1798\u17b7 \u1793\u17b7\u1798\u17b7\u178f\u17d2\u178f",
        "Phum N\u012dm\u012dt"
    ],
    "name:und_x_variant":[
        "Nimith",
        "Phum\u012d Nimit",
        "Phum\u012d N\u012dm\u012dtt"
    ],
    "wof:name":"Nimitt",
    "wof:placetype":"locality"
},
  "geometry": {"coordinates":[102.74205000000001,13.61621],"type":"Point"}
}