{
  "type": "Feature",
  "properties": {
    "gn:admin1_code":"18",
    "gn:asciiname":"Khum Chambak",
    "gn:country_code":"KH",
    "gn:dem":11,
    "gn:feature_class":"P",
    "gn:feature_code":"PPL",
    "gn:name":"Kh\u016dm Ch\u00e2mb\u00e1k",
    "gn:population":0,
    "gn:timezone":"Asia/Phnom_Penh",
    "iso:country":"KH",
    "wof:name":"Khum Chambak",
    "wof:placetype":"locality"
},
  "geometry": {"coordinates":[105.65698,11.07079],"type":"Point"}
}