{
  "type": "Feature",
  "properties": {
    "gn:admin1_code":"25",
    "gn:asciiname":"Phumi Kamping",
    "gn:country_code":"KH",
    "gn:dem":16,
    "gn:feature_class":"P",
    "gn:feature_code":"PPL",
    "gn:name":"Phum\u012d K\u00e2mping",
    "gn:population":0,
    "gn:timezone":"Asia/Phnom_Penh",
    "iso:country":"KH",
    "name:und_x_variant":[
        "Phum Komping",
        "Phum\u012d K\u00e2mping"
    ],
    "wof:name":"Phumi Kamping",
    "wof:placetype":"locality"
},
  "geometry": {"coordinates":[102.98493999999999,13.42681],"type":"Point"}
}