{
  "type": "Feature",
  "properties": {
    "gn:admin1_code":"29",
    "gn:asciiname":"Ruessei Krang",
    "gn:country_code":"KH",
    "gn:dem":14,
    "gn:feature_class":"P",
    "gn:feature_code":"PPL",
    "gn:name":"Ruessei Krang",
    "gn:population":0,
    "gn:timezone":"Asia/Phnom_Penh",
    "iso:country":"KH",
    "name:khm_x_preferred":[
        "Ruessei Krang"
    ],
    "name:khm_x_variant":[
        "\u1783\u17bb\u17c6\u17ab\u179f\u17d2\u179f\u17b8\u1780\u17d2\u179a\u17b6\u17c6\u1784"
    ],
    "name:spa_x_preferred":[
        "Ruessei Krang"
    ],
    "wof:name":"Ruessei Krang",
    "wof:placetype":"locality"
},
  "geometry": {"coordinates":[103.60755,12.70347],"type":"Point"}
}