{
  "type": "Feature",
  "properties": {
    "gn:admin1_code":"13",
    "gn:asciiname":"Mlu Prey Pir",
    "gn:country_code":"KH",
    "gn:dem":65,
    "gn:feature_class":"P",
    "gn:feature_code":"PPL",
    "gn:name":"Mlu Prey Pir",
    "gn:population":0,
    "gn:timezone":"Asia/Phnom_Penh",
    "iso:country":"KH",
    "name:khm_x_preferred":[
        "Mlu Prey Pir"
    ],
    "wof:name":"Mlu Prey Pir",
    "wof:placetype":"locality"
},
  "geometry": {"coordinates":[105.26942,13.77737],"type":"Point"}
}