{
  "type": "Feature",
  "properties": {
    "gn:admin1_code":"31",
    "gn:asciiname":"Phumi Mong Riev",
    "gn:country_code":"KH",
    "gn:dem":22,
    "gn:feature_class":"P",
    "gn:feature_code":"PPL",
    "gn:name":"Phum\u012d M\u00f3ng Ri\u0115v",
    "gn:population":0,
    "gn:timezone":"Asia/Phnom_Penh",
    "iso:country":"KH",
    "name:und_x_variant":[
        "Phum Mong Reau",
        "Phum\u012d M\u016dng R\u00e9av",
        "Phum Mong Rieu",
        "Phum\u012d M\u00f3ng Ri\u0115v"
    ],
    "wof:name":"Phumi Mong Riev",
    "wof:placetype":"locality"
},
  "geometry": {"coordinates":[105.62414,11.90397],"type":"Point"}
}