{
  "type": "Feature",
  "properties": {
    "gn:admin1_code":"21",
    "gn:asciiname":"Phumi Kaoh Khlot",
    "gn:country_code":"KH",
    "gn:dem":5,
    "gn:feature_class":"P",
    "gn:feature_code":"PPL",
    "gn:name":"Phum\u012d Ka\u00f4h Khlot",
    "gn:population":0,
    "gn:timezone":"Asia/Phnom_Penh",
    "iso:country":"KH",
    "name:und_x_variant":[
        "Phum K\u00e2s Khlaut",
        "Phum\u012d Ka\u00f4h Khlot"
    ],
    "wof:name":"Phumi Kaoh Khlot",
    "wof:placetype":"locality"
},
  "geometry": {"coordinates":[104.46809,10.55589],"type":"Point"}
}