{
  "type": "Feature",
  "properties": {
    "gn:admin1_code":"29",
    "gn:asciiname":"Phum Anlung Puok",
    "gn:country_code":"KH",
    "gn:dem":145,
    "gn:feature_class":"P",
    "gn:feature_code":"PPL",
    "gn:name":"Phum \u00c2nl\u016dng Pu\u014fk",
    "gn:population":0,
    "gn:timezone":"Asia/Phnom_Penh",
    "iso:country":"KH",
    "name:khm_x_preferred":[
        "Phum \u00c2nl\u016dng Pu\u014fk"
    ],
    "name:khm_x_variant":[
        "\u1797\u17bc\u1798\u17b7 \u17a2\u1793\u17d2\u179b\u1784\u17cb\u1796\u17bc\u1780"
    ],
    "name:und_x_variant":[
        "Phum \u00c2nlong Puork",
        "Phum\u012d \u00c2nl\u00f3ng Pu\u014fk"
    ],
    "wof:name":"Phum Anlung Puok",
    "wof:placetype":"locality"
},
  "geometry": {"coordinates":[102.82338,12.60844],"type":"Point"}
}