{
  "type": "Feature",
  "properties": {
    "gn:admin1_code":"23.0",
    "gn:asciiname":"Kaoh Pang",
    "gn:country_code":"KH",
    "gn:dem":121,
    "gn:feature_class":"P",
    "gn:feature_code":"PPL",
    "gn:name":"Kaoh Pang",
    "gn:population":0,
    "gn:timezone":"Asia/Phnom_Penh",
    "iso:country":"KH",
    "name:khm_x_preferred":[
        "Kaoh Pang"
    ],
    "wof:name":"Kaoh Pang",
    "wof:placetype":"locality"
},
  "geometry": {"coordinates":[106.97369,14.06627],"type":"Point"}
}