{
  "type": "Feature",
  "properties": {
    "gn:admin1_code":"18",
    "gn:asciiname":"Prey Ph'av",
    "gn:country_code":"KH",
    "gn:dem":10,
    "gn:feature_class":"P",
    "gn:feature_code":"PPL",
    "gn:name":"Prey Ph\u2019av",
    "gn:population":0,
    "gn:timezone":"Asia/Phnom_Penh",
    "iso:country":"KH",
    "name:khm_x_preferred":[
        "Prey Ph\u2019av"
    ],
    "name:und_x_variant":[
        "Phum\u012d Prey Phaav",
        "Phum\u012d Prey Ph\u2019av"
    ],
    "wof:name":"Prey Ph'av",
    "wof:placetype":"locality"
},
  "geometry": {"coordinates":[106.03547,10.96612],"type":"Point"}
}