{
  "type": "Feature",
  "properties": {
    "gn:admin1_code":"12.0",
    "gn:asciiname":"Phum Phteah Svay",
    "gn:country_code":"KH",
    "gn:dem":14,
    "gn:feature_class":"P",
    "gn:feature_code":"PPL",
    "gn:name":"Phum Phte\u0103h Svay",
    "gn:population":0,
    "gn:timezone":"Asia/Phnom_Penh",
    "iso:country":"KH",
    "name:khm_x_preferred":[
        "Phum Phte\u0103h Svay"
    ],
    "name:khm_x_variant":[
        "\u1797\u17bc\u1798\u17b7 \u1795\u17d2\u1791\u17c7\u179f\u17d2\u179c\u17b6\u1799"
    ],
    "wof:name":"Phum Phteah Svay",
    "wof:placetype":"locality"
},
  "geometry": {"coordinates":[103.86783,12.64575],"type":"Point"}
}