{
  "type": "Feature",
  "properties": {
    "gn:admin1_code":"18",
    "gn:asciiname":"Sek Chrum",
    "gn:country_code":"KH",
    "gn:dem":9,
    "gn:feature_class":"P",
    "gn:feature_code":"PPL",
    "gn:name":"Sek Chrum",
    "gn:population":0,
    "gn:timezone":"Asia/Phnom_Penh",
    "iso:country":"KH",
    "name:khm_x_preferred":[
        "Sek Chrum"
    ],
    "wof:name":"Sek Chrum",
    "wof:placetype":"locality"
},
  "geometry": {"coordinates":[105.98645999999999,11.01466],"type":"Point"}
}