{
  "type": "Feature",
  "properties": {
    "gn:admin1_code":"25",
    "gn:asciiname":"Yeang Dangkum",
    "gn:country_code":"KH",
    "gn:dem":41,
    "gn:feature_class":"P",
    "gn:feature_code":"PPL",
    "gn:name":"Yeang Dangkum",
    "gn:population":0,
    "gn:timezone":"Asia/Phnom_Penh",
    "iso:country":"KH",
    "name:khm_x_preferred":[
        "Yeang Dangkum"
    ],
    "name:und_x_variant":[
        "Ban Yang",
        "Phum\u012d Y\u00e9ang D\u00e2ngk\u016dm (1)"
    ],
    "wof:name":"Yeang Dangkum",
    "wof:placetype":"locality"
},
  "geometry": {"coordinates":[102.75564,13.7547],"type":"Point"}
}