{
  "type": "Feature",
  "properties": {
    "iso:country":"KH",
    "qs:gn_pop":0,
    "qs:name":"Tuol Kork",
    "qs:name_adm0":"Cambodia",
    "qs:name_adm1":"Phnum Penh",
    "qs:photos":1,
    "qs:photos_1k":1,
    "qs:photos_9k":1,
    "qs:photos_9r":1,
    "qs:photos_all":1,
    "qs:photos_sr":1,
    "qs:placetype":"Suburb",
    "qs:pop_sr":"0",
    "qs:woe_adm0":23424776,
    "wof:name":"Tuol Kork",
    "wof:placetype":"neighbourhood"
},
  "geometry": {"coordinates":[104.919776,11.565975],"type":"Point"}
}