{
  "type": "Feature",
  "properties": {
    "gn:admin1_code":"12.0",
    "gn:asciiname":"Phum Prek Sdei",
    "gn:country_code":"KH",
    "gn:dem":24,
    "gn:feature_class":"P",
    "gn:feature_code":"PPL",
    "gn:name":"Phum Pr\u00eak Sdei",
    "gn:population":0,
    "gn:timezone":"Asia/Phnom_Penh",
    "iso:country":"KH",
    "name:khm_x_preferred":[
        "Phum Pr\u00eak Sdei"
    ],
    "name:khm_x_variant":[
        "\u1797\u17bc\u1798\u17b7 \u1796\u17d2\u179a\u17c2\u1780\u179f\u17d2\u178a\u17b8"
    ],
    "wof:name":"Phum Prek Sdei",
    "wof:placetype":"locality"
},
  "geometry": {"coordinates":[103.91304,12.5237],"type":"Point"}
}