{
  "type": "Feature",
  "properties": {
    "gn:admin1_code":"02",
    "gn:asciiname":"Kaoh Mitt",
    "gn:country_code":"KH",
    "gn:dem":14,
    "gn:feature_class":"P",
    "gn:feature_code":"PPL",
    "gn:name":"Kaoh Mitt",
    "gn:population":0,
    "gn:timezone":"Asia/Phnom_Penh",
    "iso:country":"KH",
    "name:khm_x_preferred":[
        "Kaoh Mitt"
    ],
    "wof:name":"Kaoh Mitt",
    "wof:placetype":"locality"
},
  "geometry": {"coordinates":[105.44447,11.95241],"type":"Point"}
}