{
  "type": "Feature",
  "properties": {
    "gn:admin1_code":"07",
    "gn:asciiname":"Smol",
    "gn:country_code":"KH",
    "gn:dem":20,
    "gn:feature_class":"P",
    "gn:feature_code":"PPL",
    "gn:name":"Smol",
    "gn:population":0,
    "gn:timezone":"Asia/Phnom_Penh",
    "iso:country":"KH",
    "name:und_x_variant":[
        "Phum\u012d Mo\u0103t B\u0153\u0306ng"
    ],
    "wof:name":"Smol",
    "wof:placetype":"locality"
},
  "geometry": {"coordinates":[104.81725,11.37431],"type":"Point"}
}