{
  "type": "Feature",
  "properties": {
    "gn:admin1_code":"03",
    "gn:asciiname":"Phumi Phlov Tuk",
    "gn:country_code":"KH",
    "gn:dem":9,
    "gn:feature_class":"P",
    "gn:feature_code":"PPL",
    "gn:name":"Phum\u012d Phlov Tuk",
    "gn:population":0,
    "gn:timezone":"Asia/Phnom_Penh",
    "iso:country":"KH",
    "wof:name":"Phumi Phlov Tuk",
    "wof:placetype":"locality"
},
  "geometry": {"coordinates":[104.56183,12.50371],"type":"Point"}
}