{
  "type": "Feature",
  "properties": {
    "gn:admin1_code":"09",
    "gn:asciiname":"Phumi Ansaong Thleak",
    "gn:country_code":"KH",
    "gn:dem":36,
    "gn:feature_class":"P",
    "gn:feature_code":"PPL",
    "gn:name":"Phum\u012d \u00c2nsa\u00f4ng Thle\u0103k",
    "gn:population":0,
    "gn:timezone":"Asia/Phnom_Penh",
    "iso:country":"KH",
    "wof:name":"Phumi Ansaong Thleak",
    "wof:placetype":"locality"
},
  "geometry": {"coordinates":[105.93333,12.86906],"type":"Point"}
}