{
  "type": "Feature",
  "properties": {
    "gn:admin1_code":"28",
    "gn:asciiname":"Phumi Chum Talan",
    "gn:country_code":"KH",
    "gn:dem":9,
    "gn:feature_class":"P",
    "gn:feature_code":"PPL",
    "gn:name":"Phum\u012d Ch\u016dm Tal\u0103n",
    "gn:population":0,
    "gn:timezone":"Asia/Phnom_Penh",
    "iso:country":"KH",
    "wof:name":"Phumi Chum Talan",
    "wof:placetype":"locality"
},
  "geometry": {"coordinates":[103.80143,11.00874],"type":"Point"}
}