{
  "type": "Feature",
  "properties": {
    "gn:admin1_code":"14",
    "gn:asciiname":"Sithor Kandal",
    "gn:country_code":"KH",
    "gn:dem":18,
    "gn:feature_class":"P",
    "gn:feature_code":"PPLA2",
    "gn:name":"Sithor Kandal",
    "gn:population":0,
    "gn:timezone":"Asia/Phnom_Penh",
    "iso:country":"KH",
    "name:khm_x_preferred":[
        "Sithor Kandal"
    ],
    "wof:name":"Sithor Kandal",
    "wof:placetype":"locality"
},
  "geometry": {"coordinates":[105.38273999999998,11.77264],"type":"Point"}
}