{
  "type": "Feature",
  "properties": {
    "gn:admin1_code":"25",
    "gn:asciiname":"Phum Trang",
    "gn:country_code":"KH",
    "gn:dem":15,
    "gn:feature_class":"P",
    "gn:feature_code":"PPL",
    "gn:name":"Phum Trang",
    "gn:population":0,
    "gn:timezone":"Asia/Phnom_Penh",
    "iso:country":"KH",
    "name:khm_x_preferred":[
        "Phum Trang"
    ],
    "name:khm_x_variant":[
        "\u1797\u17bc\u1798\u17b7 \u178f\u17d2\u179a\u17b6\u1784"
    ],
    "name:und_x_variant":[
        "Khum Trang",
        "Phum\u012d Trang"
    ],
    "wof:name":"Phum Trang",
    "wof:placetype":"locality"
},
  "geometry": {"coordinates":[103.01533000000001,13.50722],"type":"Point"}
}