{
  "type": "Feature",
  "properties": {
    "gn:admin1_code":"12",
    "gn:asciiname":"Phumi Mol",
    "gn:country_code":"KH",
    "gn:dem":75,
    "gn:feature_class":"P",
    "gn:feature_code":"PPL",
    "gn:name":"Phum\u012d M\u00f3l",
    "gn:population":0,
    "gn:timezone":"Asia/Phnom_Penh",
    "iso:country":"KH",
    "name:und_x_variant":[
        "P\u2019um M\u014fl",
        "Phum Morrh",
        "Phum\u012d M\u016dl",
        "Phum\u012d M\u00f3l"
    ],
    "wof:name":"Phumi Mol",
    "wof:placetype":"locality"
},
  "geometry": {"coordinates":[103.89788,12.18458],"type":"Point"}
}