{
  "type": "Feature",
  "properties": {
    "gn:admin1_code":"24.0",
    "gn:asciiname":"Kouk Ampil",
    "gn:country_code":"KH",
    "gn:dem":20,
    "gn:feature_class":"P",
    "gn:feature_code":"PPL",
    "gn:name":"Kouk Ampil",
    "gn:population":0,
    "gn:timezone":"Asia/Phnom_Penh",
    "iso:country":"KH",
    "name:khm_x_preferred":[
        "Kouk Ampil"
    ],
    "name:khm_x_variant":[
        "\u1797\u17bc\u1798\u17b7 \u1782\u17c4\u1780\u17a2\u17c6\u1796\u17b7\u179b",
        "Phum Ko\u016dk \u00c2mpil"
    ],
    "wof:name":"Kouk Ampil",
    "wof:placetype":"locality"
},
  "geometry": {"coordinates":[104.44346,13.05396],"type":"Point"}
}