{
  "type": "Feature",
  "properties": {
    "gn:admin1_code":"14",
    "gn:asciiname":"Phumi Pnou",
    "gn:country_code":"KH",
    "gn:dem":15,
    "gn:feature_class":"P",
    "gn:feature_code":"PPL",
    "gn:name":"Phum\u012d Pn\u014fu",
    "gn:population":0,
    "gn:timezone":"Asia/Phnom_Penh",
    "iso:country":"KH",
    "name:und_x_variant":[
        "Phum Phnou",
        "Phum\u012d Pn\u014fu"
    ],
    "wof:name":"Phumi Pnou",
    "wof:placetype":"locality"
},
  "geometry": {"coordinates":[105.50518,11.35491],"type":"Point"}
}