{
  "type": "Feature",
  "properties": {
    "gn:country":"KH",
    "gn:fcode":"ADMD",
    "gn:pop":111987,
    "iso:country":"KH",
    "name:unk_x_variant":[
        "Srok Stung Trang"
    ],
    "qs:name":"Sr\u014fk St\u0153\u0306ng Tr\u00e1ng",
    "qs:photos_9r":0,
    "qs:photos_sr":0,
    "qs:pop_sr":"9",
    "wof:name":"Sr\u014fk St\u0153\u0306ng Tr\u00e1ng",
    "wof:placetype":"localadmin",
    "wof:population":111987
},
  "geometry": {"coordinates":[105.58333,12.33333],"type":"Point"}
}