{
  "type": "Feature",
  "properties": {
    "gn:admin1_code":"03",
    "gn:asciiname":"Phumi Kampong Ta Ches",
    "gn:country_code":"KH",
    "gn:dem":12,
    "gn:feature_class":"P",
    "gn:feature_code":"PPL",
    "gn:name":"Phum\u012d K\u00e2mp\u00f3ng Ta Ch\u00e9s",
    "gn:population":0,
    "gn:timezone":"Asia/Phnom_Penh",
    "iso:country":"KH",
    "name:und_x_variant":[
        "Taches",
        "Kompong Taches",
        "Phum\u012d K\u00e2mp\u00f3ng Ta Ch\u00e9s"
    ],
    "wof:name":"Phumi Kampong Ta Ches",
    "wof:placetype":"locality"
},
  "geometry": {"coordinates":[104.77755000000001,12.01154],"type":"Point"}
}