{
  "type": "Feature",
  "properties": {
    "gn:admin1_code":"14.0",
    "gn:asciiname":"Phum Snuol",
    "gn:country_code":"KH",
    "gn:dem":10,
    "gn:feature_class":"P",
    "gn:feature_code":"PPL",
    "gn:name":"Phum Snu\u014fl",
    "gn:population":0,
    "gn:timezone":"Asia/Phnom_Penh",
    "iso:country":"KH",
    "name:khm_x_preferred":[
        "Phum Snu\u014fl"
    ],
    "name:khm_x_variant":[
        "\u1797\u17bc\u1798\u17b7 \u179f\u17d2\u1793\u17bd\u179b"
    ],
    "wof:name":"Phum Snuol",
    "wof:placetype":"locality"
},
  "geometry": {"coordinates":[105.41043000000001,11.36026],"type":"Point"}
}