{
  "type": "Feature",
  "properties": {
    "gn:admin1_code":"31",
    "gn:asciiname":"Phumi Chimoan",
    "gn:country_code":"KH",
    "gn:dem":38,
    "gn:feature_class":"P",
    "gn:feature_code":"PPL",
    "gn:name":"Phum\u012d Chimo\u0103n",
    "gn:population":0,
    "gn:timezone":"Asia/Phnom_Penh",
    "iso:country":"KH",
    "name:und_x_variant":[
        "Phum\u012d Chima\u00f4n",
        "Phum Chimean",
        "Phum\u012d Chimo\u0103n"
    ],
    "wof:name":"Phumi Chimoan",
    "wof:placetype":"locality"
},
  "geometry": {"coordinates":[105.93912,11.76538],"type":"Point"}
}