{
  "type": "Feature",
  "properties": {
    "gn:admin1_code":"14.0",
    "gn:asciiname":"Phum La Ed",
    "gn:country_code":"KH",
    "gn:dem":9,
    "gn:feature_class":"P",
    "gn:feature_code":"PPL",
    "gn:name":"Phum L\u00e2 \u0114d",
    "gn:population":0,
    "gn:timezone":"Asia/Phnom_Penh",
    "iso:country":"KH",
    "name:khm_x_preferred":[
        "Phum L\u00e2 \u0114d"
    ],
    "name:khm_x_variant":[
        "\u1797\u17bc\u1798\u17b7 \u17a1\u17a2\u17b7\u178a\u17d2\u178b"
    ],
    "wof:name":"Phum La Ed",
    "wof:placetype":"locality"
},
  "geometry": {"coordinates":[105.30665999999999,11.34648],"type":"Point"}
}