{
  "type": "Feature",
  "properties": {
    "gn:admin1_code":"24.0",
    "gn:asciiname":"Phum Chup",
    "gn:country_code":"KH",
    "gn:dem":37,
    "gn:feature_class":"P",
    "gn:feature_code":"PPL",
    "gn:name":"Phum Ch\u016dp",
    "gn:population":0,
    "gn:timezone":"Asia/Phnom_Penh",
    "iso:country":"KH",
    "name:khm_x_preferred":[
        "Phum Ch\u016dp"
    ],
    "name:khm_x_variant":[
        "\u1797\u17bc\u1798\u17b7 \u1787\u17bb\u1794"
    ],
    "wof:name":"Phum Chup",
    "wof:placetype":"locality"
},
  "geometry": {"coordinates":[104.10594,13.35785],"type":"Point"}
}