{
  "type": "Feature",
  "properties": {
    "gn:admin1_code":"05",
    "gn:asciiname":"Phumi Trapeang Chhuk",
    "gn:country_code":"KH",
    "gn:dem":43,
    "gn:feature_class":"P",
    "gn:feature_code":"PPL",
    "gn:name":"Phum\u012d Tr\u00e2pe\u0103ng Chhuk",
    "gn:population":0,
    "gn:timezone":"Asia/Phnom_Penh",
    "iso:country":"KH",
    "wof:name":"Phumi Trapeang Chhuk",
    "wof:placetype":"locality"
},
  "geometry": {"coordinates":[105.20193999999999,13.42318],"type":"Point"}
}