{
  "type": "Feature",
  "properties": {
    "gn:admin1_code":"23.0",
    "gn:asciiname":"Ta Nga",
    "gn:country_code":"KH",
    "gn:dem":253,
    "gn:feature_class":"P",
    "gn:feature_code":"PPL",
    "gn:name":"Ta Nga",
    "gn:population":0,
    "gn:timezone":"Asia/Phnom_Penh",
    "iso:country":"KH",
    "name:khm_x_preferred":[
        "Ta Nga"
    ],
    "wof:name":"Ta Nga",
    "wof:placetype":"locality"
},
  "geometry": {"coordinates":[107.38267,13.99001],"type":"Point"}
}