{
  "type": "Feature",
  "properties": {
    "gn:admin1_code":"03",
    "gn:asciiname":"Phumi Peam Tonlea",
    "gn:country_code":"KH",
    "gn:dem":10,
    "gn:feature_class":"P",
    "gn:feature_code":"PPL",
    "gn:name":"Phum\u012d P\u00e9am T\u00f4nl\u00e9a",
    "gn:population":0,
    "gn:timezone":"Asia/Phnom_Penh",
    "iso:country":"KH",
    "name:und_x_variant":[
        "Peam Tonlea",
        "Phum\u012d P\u00e9am T\u00f4nl\u00e9a"
    ],
    "wof:name":"Phumi Peam Tonlea",
    "wof:placetype":"locality"
},
  "geometry": {"coordinates":[104.69011,12.30201],"type":"Point"}
}