{
  "type": "Feature",
  "properties": {
    "gn:admin1_code":"29",
    "gn:asciiname":"Phum Thnam",
    "gn:country_code":"KH",
    "gn:dem":41,
    "gn:feature_class":"P",
    "gn:feature_code":"PPL",
    "gn:name":"Phum Thn\u00e2m",
    "gn:population":0,
    "gn:timezone":"Asia/Phnom_Penh",
    "iso:country":"KH",
    "name:khm_x_preferred":[
        "Phum Thn\u00e2m"
    ],
    "name:khm_x_variant":[
        "\u1797\u17bc\u1798\u17b7 \u1790\u17d2\u1793\u17c6"
    ],
    "name:und_x_variant":[
        "Khum Thn\u00e2m",
        "Phum\u012d Thn\u00e2m"
    ],
    "wof:name":"Phum Thnam",
    "wof:placetype":"locality"
},
  "geometry": {"coordinates":[103.37081000000001,12.60364],"type":"Point"}
}