{
  "type": "Feature",
  "properties": {
    "gn:admin1_code":"29",
    "gn:asciiname":"Phum Chrouy Motes",
    "gn:country_code":"KH",
    "gn:dem":15,
    "gn:feature_class":"P",
    "gn:feature_code":"PPL",
    "gn:name":"Phum Chro\u016dy M\u00f4t\u00e9s",
    "gn:population":0,
    "gn:timezone":"Asia/Phnom_Penh",
    "iso:country":"KH",
    "name:khm_x_preferred":[
        "Phum Chro\u016dy M\u00f4t\u00e9s"
    ],
    "name:khm_x_variant":[
        "\u1797\u17bc\u1798\u17b7 \u1787\u17d2\u179a\u17c4\u1799\u1798\u17d2\u1791\u17c1\u179f"
    ],
    "wof:name":"Phum Chrouy Motes",
    "wof:placetype":"locality"
},
  "geometry": {"coordinates":[103.09023000000001,13.27936],"type":"Point"}
}