{
  "type": "Feature",
  "properties": {
    "gn:admin1_code":"04",
    "gn:asciiname":"Phumi Beng",
    "gn:country_code":"KH",
    "gn:dem":95,
    "gn:feature_class":"P",
    "gn:feature_code":"PPL",
    "gn:name":"Phum\u012d B\u00e9ng",
    "gn:population":0,
    "gn:timezone":"Asia/Phnom_Penh",
    "iso:country":"KH",
    "name:und_x_variant":[
        "Thmar Kor",
        "Phum\u012d B\u00e9ng"
    ],
    "wof:name":"Phumi Beng",
    "wof:placetype":"locality"
},
  "geometry": {"coordinates":[104.11150000000001,11.38541],"type":"Point"}
}