{
  "type": "Feature",
  "properties": {
    "gn:admin1_code":"4.0",
    "gn:asciiname":"Haong Samnam",
    "gn:country_code":"KH",
    "gn:dem":69,
    "gn:feature_class":"P",
    "gn:feature_code":"PPL",
    "gn:name":"Haong Samnam",
    "gn:population":0,
    "gn:timezone":"Asia/Phnom_Penh",
    "iso:country":"KH",
    "name:khm_x_preferred":[
        "Haong Samnam"
    ],
    "wof:name":"Haong Samnam",
    "wof:placetype":"locality"
},
  "geometry": {"coordinates":[104.23424,11.57149],"type":"Point"}
}