{
  "type": "Feature",
  "properties": {
    "gn:admin1_code":"04",
    "gn:asciiname":"Phum Sre En",
    "gn:country_code":"KH",
    "gn:dem":165,
    "gn:feature_class":"P",
    "gn:feature_code":"PPL",
    "gn:name":"Phum Sr\u00ea \u0114n",
    "gn:population":0,
    "gn:timezone":"Asia/Phnom_Penh",
    "iso:country":"KH",
    "name:khm_x_preferred":[
        "Phum Sr\u00ea \u0114n"
    ],
    "name:khm_x_variant":[
        "\u1797\u17bc\u1798\u17b7 \u179f\u17d2\u179a\u17c2\u17a2\u17b7\u1793"
    ],
    "name:und_x_variant":[
        "Phum\u012d Sr\u00ea \u0114n"
    ],
    "wof:name":"Phum Sre En",
    "wof:placetype":"locality"
},
  "geometry": {"coordinates":[104.13441,11.90609],"type":"Point"}
}