{
  "type": "Feature",
  "properties": {
    "gn:admin1_code":"29",
    "gn:asciiname":"Phum Enth Chit",
    "gn:country_code":"KH",
    "gn:dem":22,
    "gn:feature_class":"P",
    "gn:feature_code":"PPL",
    "gn:name":"Phum \u0114nth Ch\u012dt",
    "gn:population":0,
    "gn:timezone":"Asia/Phnom_Penh",
    "iso:country":"KH",
    "name:khm_x_preferred":[
        "Phum \u0114nth Ch\u012dt"
    ],
    "name:khm_x_variant":[
        "\u1797\u17bc\u1798\u17b7 \u17a5\u1793\u17d2\u1791\u1787\u17b7\u178f"
    ],
    "wof:name":"Phum Enth Chit",
    "wof:placetype":"locality"
},
  "geometry": {"coordinates":[103.15898,13.0091],"type":"Point"}
}