{
  "type": "Feature",
  "properties": {
    "gn:admin1_code":"24",
    "gn:asciiname":"Phum Krachor",
    "gn:country_code":"KH",
    "gn:dem":54,
    "gn:feature_class":"P",
    "gn:feature_code":"PPL",
    "gn:name":"Phum Kr\u00e2ch\u00f4r",
    "gn:population":0,
    "gn:timezone":"Asia/Phnom_Penh",
    "iso:country":"KH",
    "name:khm_x_preferred":[
        "Phum Kr\u00e2ch\u00f4r"
    ],
    "name:und_x_variant":[
        "Krachar",
        "Phum\u012d Kr\u00e2ch\u00f4r"
    ],
    "wof:name":"Phum Krachor",
    "wof:placetype":"locality"
},
  "geometry": {"coordinates":[103.8917,13.86372],"type":"Point"}
}