{
  "type": "Feature",
  "properties": {
    "gn:admin1_code":"18",
    "gn:asciiname":"Phumi Kanhchhet",
    "gn:country_code":"KH",
    "gn:dem":5,
    "gn:feature_class":"P",
    "gn:feature_code":"PPL",
    "gn:name":"Phum\u012d K\u00e2nhchh\u00eat",
    "gn:population":0,
    "gn:timezone":"Asia/Phnom_Penh",
    "iso:country":"KH",
    "name:und_x_variant":[
        "Kan Chh\u00eat",
        "Phum\u012d K\u00e2nchh\u00eat",
        "Phum\u012d K\u00e2nhchh\u00eat"
    ],
    "wof:name":"Phumi Kanhchhet",
    "wof:placetype":"locality"
},
  "geometry": {"coordinates":[105.89570000000001,11.16105],"type":"Point"}
}