{
  "type": "Feature",
  "properties": {
    "gn:admin1_code":"23",
    "gn:asciiname":"Tak Mak",
    "gn:country_code":"KH",
    "gn:dem":109,
    "gn:feature_class":"P",
    "gn:feature_code":"PPL",
    "gn:name":"T\u00e1k M\u00e1k",
    "gn:population":0,
    "gn:timezone":"Asia/Phnom_Penh",
    "iso:country":"KH",
    "name:und_x_variant":[
        "Phum\u012d T\u00e2k M\u00e2k",
        "T\u00e1k M\u00e1k"
    ],
    "wof:name":"Tak Mak",
    "wof:placetype":"locality"
},
  "geometry": {"coordinates":[107.04483,14.07035],"type":"Point"}
}