{
  "type": "Feature",
  "properties": {
    "gn:admin1_code":"02",
    "gn:asciiname":"Phumi Thmei",
    "gn:country_code":"KH",
    "gn:dem":20,
    "gn:feature_class":"P",
    "gn:feature_code":"PPL",
    "gn:name":"Phum\u012d Thmei",
    "gn:population":0,
    "gn:timezone":"Asia/Phnom_Penh",
    "iso:country":"KH",
    "name:und_x_variant":[
        "Phum Thmey",
        "Phum\u012d Thmei"
    ],
    "wof:name":"Phumi Thmei",
    "wof:placetype":"locality"
},
  "geometry": {"coordinates":[105.41285999999999,11.9453],"type":"Point"}
}