{
  "type": "Feature",
  "properties": {
    "gn:admin1_code":"05",
    "gn:asciiname":"Pey",
    "gn:country_code":"KH",
    "gn:dem":15,
    "gn:feature_class":"P",
    "gn:feature_code":"PPL",
    "gn:name":"Pey",
    "gn:population":0,
    "gn:timezone":"Asia/Phnom_Penh",
    "iso:country":"KH",
    "name:khm_x_preferred":[
        "Pey"
    ],
    "name:und_x_variant":[
        "Phum\u012d Pey"
    ],
    "wof:name":"Pey",
    "wof:placetype":"locality"
},
  "geometry": {"coordinates":[104.56431000000001,12.89112],"type":"Point"}
}