{
  "type": "Feature",
  "properties": {
    "gn:admin1_code":"05",
    "gn:asciiname":"Pey",
    "gn:country_code":"KH",
    "gn:dem":15,
    "gn:feature_class":"P",
    "gn:feature_code":"PPL",
    "gn:name":"Pey",
    "gn:population":0,
    "gn:timezone":"Asia/Phnom_Penh",
    "iso:country":"KH",
    "name:cat_x_preferred":[
        "Pei"
    ],
    "name:ceb_x_preferred":[
        "Pey"
    ],
    "name:deu_x_preferred":[
        "Pey"
    ],
    "name:eus_x_preferred":[
        "Pey"
    ],
    "name:fas_x_preferred":[
        "\u067e\u06cc"
    ],
    "name:fra_x_preferred":[
        "Pey"
    ],
    "name:hun_x_preferred":[
        "Pey"
    ],
    "name:ita_x_preferred":[
        "Pey"
    ],
    "name:kaz_x_preferred":[
        "\u041f\u0435"
    ],
    "name:khm_x_preferred":[
        "Pey"
    ],
    "name:lat_x_preferred":[
        "Pey"
    ],
    "name:msa_x_preferred":[
        "Pey"
    ],
    "name:nld_x_preferred":[
        "Pey"
    ],
    "name:oci_x_preferred":[
        "Pei"
    ],
    "name:pms_x_preferred":[
        "Pey"
    ],
    "name:pol_x_preferred":[
        "Pey"
    ],
    "name:por_x_preferred":[
        "Pey"
    ],
    "name:ron_x_preferred":[
        "Pey"
    ],
    "name:slk_x_preferred":[
        "Pey"
    ],
    "name:slv_x_preferred":[
        "Pey"
    ],
    "name:spa_x_preferred":[
        "Pey"
    ],
    "name:swe_x_preferred":[
        "Pey"
    ],
    "name:ukr_x_preferred":[
        "\u041f\u0435"
    ],
    "name:und_x_variant":[
        "Phum\u012d Pey"
    ],
    "name:uzb_x_preferred":[
        "Pey"
    ],
    "name:vie_x_preferred":[
        "Pey"
    ],
    "name:vol_x_preferred":[
        "Pey"
    ],
    "name:war_x_preferred":[
        "Pey"
    ],
    "name:zho_x_preferred":[
        "\u4f69\u9547"
    ],
    "wof:name":"Pey",
    "wof:placetype":"locality"
},
  "geometry": {"coordinates":[104.56431000000001,12.89112],"type":"Point"}
}