{
  "type": "Feature",
  "properties": {
    "gn:admin1_code":"17",
    "gn:asciiname":"Phum Sre Nam Nay",
    "gn:country_code":"KH",
    "gn:dem":53,
    "gn:feature_class":"P",
    "gn:feature_code":"PPL",
    "gn:name":"Phum Sr\u00ea N\u0103m N\u00e2y",
    "gn:population":0,
    "gn:timezone":"Asia/Phnom_Penh",
    "iso:country":"KH",
    "name:khm_x_preferred":[
        "Phum Sr\u00ea N\u0103m N\u00e2y"
    ],
    "name:khm_x_variant":[
        "\u1797\u17bc\u1798\u17b7 \u179f\u17d2\u179a\u17c2\u178e\u17b6\u17c6\u178e\u1799"
    ],
    "name:und_x_variant":[
        "Ban Chan Din"
    ],
    "wof:name":"Phum Sre Nam Nay",
    "wof:placetype":"locality"
},
  "geometry": {"coordinates":[106.03883999999999,13.55682],"type":"Point"}
}