{
  "type": "Feature",
  "properties": {
    "gn:admin1_code":"12",
    "gn:asciiname":"Chamkar Khloy",
    "gn:country_code":"KH",
    "gn:dem":20,
    "gn:feature_class":"P",
    "gn:feature_code":"PPL",
    "gn:name":"Chamkar Khloy",
    "gn:population":0,
    "gn:timezone":"Asia/Phnom_Penh",
    "iso:country":"KH",
    "name:khm_x_preferred":[
        "Chamkar Khloy"
    ],
    "wof:name":"Chamkar Khloy",
    "wof:placetype":"locality"
},
  "geometry": {"coordinates":[103.67641999999999,12.64996],"type":"Point"}
}