{
  "type": "Feature",
  "properties": {
    "gn:admin1_code":"02",
    "gn:asciiname":"Phumi Phnum Thum",
    "gn:country_code":"KH",
    "gn:dem":20,
    "gn:feature_class":"P",
    "gn:feature_code":"PPL",
    "gn:name":"Phum\u012d Phnum Thum",
    "gn:population":0,
    "gn:timezone":"Asia/Phnom_Penh",
    "iso:country":"KH",
    "name:und_x_variant":[
        "Pnom Thom",
        "Phum\u012d Phn\u016dm Thom",
        "Phum\u012d Phnum Thum"
    ],
    "wof:name":"Phumi Phnum Thum",
    "wof:placetype":"locality"
},
  "geometry": {"coordinates":[104.93453999999998,11.89537],"type":"Point"}
}