{
  "type": "Feature",
  "properties": {
    "gn:admin1_code":"02",
    "gn:asciiname":"Chhuk Sa",
    "gn:country_code":"KH",
    "gn:dem":16,
    "gn:feature_class":"P",
    "gn:feature_code":"PPL",
    "gn:name":"Chhuk Sa",
    "gn:population":0,
    "gn:timezone":"Asia/Phnom_Penh",
    "iso:country":"KH",
    "name:khm_x_preferred":[
        "Chhuk Sa"
    ],
    "wof:name":"Chhuk Sa",
    "wof:placetype":"locality"
},
  "geometry": {"coordinates":[105.13992,12.13707],"type":"Point"}
}