{
  "type": "Feature",
  "properties": {
    "gn:admin1_code":"03",
    "gn:asciiname":"Phumi Tang Samraong",
    "gn:country_code":"KH",
    "gn:dem":165,
    "gn:feature_class":"P",
    "gn:feature_code":"PPL",
    "gn:name":"Phum\u012d T\u0103ng S\u00e2mra\u00f4ng",
    "gn:population":0,
    "gn:timezone":"Asia/Phnom_Penh",
    "iso:country":"KH",
    "wof:name":"Phumi Tang Samraong",
    "wof:placetype":"locality"
},
  "geometry": {"coordinates":[104.25462,11.93899],"type":"Point"}
}