{
  "type": "Feature",
  "properties": {
    "gn:admin1_code":"03",
    "gn:asciiname":"Phumi Pa Lang",
    "gn:country_code":"KH",
    "gn:dem":27,
    "gn:feature_class":"P",
    "gn:feature_code":"PPL",
    "gn:name":"Phum\u012d Pa Lang",
    "gn:population":0,
    "gn:timezone":"Asia/Phnom_Penh",
    "iso:country":"KH",
    "name:und_x_variant":[
        "Phum\u012d Pap Lang",
        "Phum\u012d Pa Lang"
    ],
    "wof:name":"Phumi Pa Lang",
    "wof:placetype":"locality"
},
  "geometry": {"coordinates":[104.57725000000001,12.24874],"type":"Point"}
}