{
  "type": "Feature",
  "properties": {
    "gn:admin1_code":"29",
    "gn:asciiname":"Phumi Kum Ta Sok",
    "gn:country_code":"KH",
    "gn:dem":7,
    "gn:feature_class":"P",
    "gn:feature_code":"PPL",
    "gn:name":"Phum\u012d K\u016dm Ta S\u014fk",
    "gn:population":0,
    "gn:timezone":"Asia/Phnom_Penh",
    "iso:country":"KH",
    "name:khm_x_preferred":[
        "Phum\u012d K\u016dm Ta S\u014fk"
    ],
    "name:khm_x_variant":[
        "\u1797\u17bc\u1798\u17b7\u178f\u17bb\u17c6\u178f\u17b6\u179f\u17bb\u1780"
    ],
    "wof:name":"Phumi Kum Ta Sok",
    "wof:placetype":"locality"
},
  "geometry": {"coordinates":[103.35545999999999,13.26445],"type":"Point"}
}