{
  "type": "Feature",
  "properties": {
    "gn:admin1_code":"03",
    "gn:asciiname":"Phumi Khnach Krakaoh",
    "gn:cc2":"KH",
    "gn:country_code":"KH",
    "gn:dem":22,
    "gn:feature_class":"P",
    "gn:feature_code":"PPL",
    "gn:name":"Phum\u012d Khn\u0103ch Kr\u00e2ka\u00f4h",
    "gn:population":0,
    "gn:timezone":"Asia/Phnom_Penh",
    "iso:country":"KH",
    "name:und_x_variant":[
        "Khnat Kak\u00f4s",
        "Phum\u012d Khnach\u00e2m Kr\u00e2ka\u00f4h",
        "Phum\u012d Khn\u0103ch Kr\u00e2ka\u00f4h"
    ],
    "wof:name":"Phumi Khnach Krakaoh",
    "wof:placetype":"locality"
},
  "geometry": {"coordinates":[104.68333,12.05],"type":"Point"}
}