{
  "type": "Feature",
  "properties": {
    "gn:admin1_code":"25",
    "gn:asciiname":"Ou Chuob",
    "gn:country_code":"KH",
    "gn:dem":18,
    "gn:feature_class":"P",
    "gn:feature_code":"PPL",
    "gn:name":"Ou Chuob",
    "gn:population":0,
    "gn:timezone":"Asia/Phnom_Penh",
    "iso:country":"KH",
    "name:khm_x_preferred":[
        "Ou Chuob"
    ],
    "wof:name":"Ou Chuob",
    "wof:placetype":"locality"
},
  "geometry": {"coordinates":[102.98067,13.44492],"type":"Point"}
}