{
  "type": "Feature",
  "properties": {
    "gn:admin1_code":"12",
    "gn:asciiname":"Trapong Pung",
    "gn:country_code":"KH",
    "gn:dem":60,
    "gn:feature_class":"P",
    "gn:feature_code":"PPL",
    "gn:name":"Tr\u00e2p\u00f4ng P\u016dng",
    "gn:population":0,
    "gn:timezone":"Asia/Phnom_Penh",
    "iso:country":"KH",
    "name:khm_x_preferred":[
        "\u178f\u17d2\u179a\u1796\u1784\u1796\u17bb\u1784"
    ],
    "name:und_x_variant":[
        "Tr\u00e2p\u00f4ng P\u016dng",
        "Tr\u00e2p\u00f4ng P\u00f4ng"
    ],
    "wof:name":"Trapong Pung",
    "wof:placetype":"locality"
},
  "geometry": {"coordinates":[103.48411,12.31439],"type":"Point"}
}