{
  "type": "Feature",
  "properties": {
    "gn:admin1_code":"19",
    "gn:asciiname":"Phumi Krasang",
    "gn:country_code":"KH",
    "gn:dem":11,
    "gn:feature_class":"P",
    "gn:feature_code":"PPL",
    "gn:name":"Phum\u012d Kr\u00e2s\u0103ng",
    "gn:population":0,
    "gn:timezone":"Asia/Phnom_Penh",
    "iso:country":"KH",
    "name:und_x_variant":[
        "Krasang",
        "Phum\u012d Kr\u00e2s\u0103ng"
    ],
    "wof:name":"Phumi Krasang",
    "wof:placetype":"locality"
},
  "geometry": {"coordinates":[104.85491,11.26957],"type":"Point"}
}