{
  "type": "Feature",
  "properties": {
    "gn:admin1_code":"24.0",
    "gn:asciiname":"Kouk Srama",
    "gn:country_code":"KH",
    "gn:dem":18,
    "gn:feature_class":"P",
    "gn:feature_code":"PPL",
    "gn:name":"Kouk Srama",
    "gn:population":0,
    "gn:timezone":"Asia/Phnom_Penh",
    "iso:country":"KH",
    "name:khm_x_preferred":[
        "Kouk Srama"
    ],
    "wof:name":"Kouk Srama",
    "wof:placetype":"locality"
},
  "geometry": {"coordinates":[103.69138,13.47001],"type":"Point"}
}