{
  "type": "Feature",
  "properties": {
    "gn:admin1_code":"31",
    "gn:asciiname":"Mong",
    "gn:country_code":"KH",
    "gn:dem":61,
    "gn:feature_class":"P",
    "gn:feature_code":"PPL",
    "gn:name":"Mong",
    "gn:population":0,
    "gn:timezone":"Asia/Phnom_Penh",
    "iso:country":"KH",
    "name:deu_x_preferred":[
        "Mong"
    ],
    "name:khm_x_preferred":[
        "Mong"
    ],
    "name:nor_x_preferred":[
        "Mong"
    ],
    "name:und_x_variant":[
        "Phum Mong",
        "Phum\u012d Mo\u016dng"
    ],
    "wof:name":"Mong",
    "wof:placetype":"locality"
},
  "geometry": {"coordinates":[106.34748,11.71001],"type":"Point"}
}