{
  "type": "Feature",
  "properties": {
    "gn:admin1_code":"05",
    "gn:asciiname":"Phumi Kokir Thum",
    "gn:cc2":"KH",
    "gn:country_code":"KH",
    "gn:dem":32,
    "gn:feature_class":"P",
    "gn:feature_code":"PPL",
    "gn:name":"Phum\u012d K\u00f4kir Thum",
    "gn:population":0,
    "gn:timezone":"Asia/Phnom_Penh",
    "iso:country":"KH",
    "name:und_x_variant":[
        "Phum Koki Thom",
        "Phum Koki Tham",
        "Phum\u012d K\u00f4kir Thum"
    ],
    "wof:name":"Phumi Kokir Thum",
    "wof:placetype":"locality"
},
  "geometry": {"coordinates":[105.40000000000001,12.46667],"type":"Point"}
}