{
  "type": "Feature",
  "properties": {
    "gn:admin1_code":"31.0",
    "gn:asciiname":"Phum Prammuoy",
    "gn:country_code":"KH",
    "gn:dem":20,
    "gn:feature_class":"P",
    "gn:feature_code":"PPL",
    "gn:name":"Phum Prammuoy",
    "gn:population":0,
    "gn:timezone":"Asia/Phnom_Penh",
    "iso:country":"KH",
    "name:khm_x_preferred":[
        "Phum Prammuoy"
    ],
    "wof:name":"Phum Prammuoy",
    "wof:placetype":"locality"
},
  "geometry": {"coordinates":[105.51962,12.05132],"type":"Point"}
}