{
  "type": "Feature",
  "properties": {
    "gn:admin1_code":"21",
    "gn:asciiname":"Phumi Phnum Toch",
    "gn:country_code":"KH",
    "gn:dem":9,
    "gn:feature_class":"P",
    "gn:feature_code":"PPL",
    "gn:name":"Phum\u012d Phnum Toch",
    "gn:population":0,
    "gn:timezone":"Asia/Phnom_Penh",
    "iso:country":"KH",
    "name:und_x_variant":[
        "Phum Phnom Toch",
        "Phum\u012d Phnum Toch"
    ],
    "wof:name":"Phumi Phnum Toch",
    "wof:placetype":"locality"
},
  "geometry": {"coordinates":[104.51315,10.70865],"type":"Point"}
}