{
  "type": "Feature",
  "properties": {
    "gn:admin1_code":"05",
    "gn:asciiname":"Phumi Kampeut",
    "gn:country_code":"KH",
    "gn:dem":35,
    "gn:feature_class":"P",
    "gn:feature_code":"PPL",
    "gn:name":"Phum\u012d K\u00e2mpeut",
    "gn:population":0,
    "gn:timezone":"Asia/Phnom_Penh",
    "iso:country":"KH",
    "name:und_x_variant":[
        "Phum Kompil",
        "Phum\u012d K\u00e2mpo\u0115t",
        "Phum\u012d K\u00e2mpeut"
    ],
    "wof:name":"Phumi Kampeut",
    "wof:placetype":"locality"
},
  "geometry": {"coordinates":[104.67805,13.09032],"type":"Point"}
}