{
  "type": "Feature",
  "properties": {
    "gn:admin1_code":"27.0",
    "gn:asciiname":"Tumnob Dach",
    "gn:country_code":"KH",
    "gn:dem":88,
    "gn:feature_class":"P",
    "gn:feature_code":"PPL",
    "gn:name":"Tumnob Dach",
    "gn:population":0,
    "gn:timezone":"Asia/Phnom_Penh",
    "iso:country":"KH",
    "name:khm_x_preferred":[
        "Tumnob Dach"
    ],
    "wof:name":"Tumnob Dach",
    "wof:placetype":"locality"
},
  "geometry": {"coordinates":[104.45823,14.28616],"type":"Point"}
}