{
  "type": "Feature",
  "properties": {
    "gn:admin1_code":"05",
    "gn:asciiname":"Phumi Tum Ar",
    "gn:country_code":"KH",
    "gn:dem":74,
    "gn:feature_class":"P",
    "gn:feature_code":"PPL",
    "gn:name":"Phum\u012d Tum \u00c2r",
    "gn:population":0,
    "gn:timezone":"Asia/Phnom_Penh",
    "iso:country":"KH",
    "name:und_x_variant":[
        "Phum Tumar",
        "Phum Thmar",
        "Phum Thmay",
        "Phum\u012d Tum \u00c2r"
    ],
    "wof:name":"Phumi Tum Ar",
    "wof:placetype":"locality"
},
  "geometry": {"coordinates":[105.42927,12.86364],"type":"Point"}
}