{
  "type": "Feature",
  "properties": {
    "gn:admin1_code":"03",
    "gn:asciiname":"Phumi Cheung Anhchrong",
    "gn:country_code":"KH",
    "gn:dem":10,
    "gn:feature_class":"P",
    "gn:feature_code":"PPL",
    "gn:name":"Phum\u012d Cheung \u00c2nhchrong",
    "gn:population":0,
    "gn:timezone":"Asia/Phnom_Penh",
    "iso:country":"KH",
    "wof:name":"Phumi Cheung Anhchrong",
    "wof:placetype":"locality"
},
  "geometry": {"coordinates":[104.64579000000001,12.43311],"type":"Point"}
}