{
  "type": "Feature",
  "properties": {
    "gn:admin1_code":"9.0",
    "gn:asciiname":"Phum Chhak Preah",
    "gn:country_code":"KH",
    "gn:dem":59,
    "gn:feature_class":"P",
    "gn:feature_code":"PPL",
    "gn:name":"Phum Chh\u00e2k Pre\u0103h",
    "gn:population":0,
    "gn:timezone":"Asia/Phnom_Penh",
    "iso:country":"KH",
    "name:khm_x_preferred":[
        "Phum Chh\u00e2k Pre\u0103h"
    ],
    "name:khm_x_variant":[
        "\u1797\u17bc\u1798\u17b7 \u1786\u1780\u17cb\u1796\u17d2\u179a\u17c7"
    ],
    "wof:name":"Phum Chhak Preah",
    "wof:placetype":"locality"
},
  "geometry": {"coordinates":[106.31865999999999,12.71586],"type":"Point"}
}