{
  "type": "Feature",
  "properties": {
    "gn:admin1_code":"05",
    "gn:asciiname":"Trapeang Chrey",
    "gn:country_code":"KH",
    "gn:dem":22,
    "gn:feature_class":"P",
    "gn:feature_code":"PPL",
    "gn:name":"Trapeang Chrey",
    "gn:population":0,
    "gn:timezone":"Asia/Phnom_Penh",
    "iso:country":"KH",
    "name:khm_x_preferred":[
        "Trapeang Chrey"
    ],
    "wof:name":"Trapeang Chrey",
    "wof:placetype":"locality"
},
  "geometry": {"coordinates":[105.14243,12.4662],"type":"Point"}
}