{
  "type": "Feature",
  "properties": {
    "gn:admin1_code":"25",
    "gn:asciiname":"Phum Stoeng Chas",
    "gn:country_code":"KH",
    "gn:dem":13,
    "gn:feature_class":"P",
    "gn:feature_code":"PPL",
    "gn:name":"Phum St\u0153\u0306ng Ch\u0103s",
    "gn:population":0,
    "gn:timezone":"Asia/Phnom_Penh",
    "iso:country":"KH",
    "name:khm_x_preferred":[
        "Phum St\u0153\u0306ng Ch\u0103s"
    ],
    "name:khm_x_variant":[
        "\u1797\u17bc\u1798\u17b7 \u179f\u17d2\u1791\u17b9\u1784\u1785\u17b6\u179f\u17cb"
    ],
    "name:und_x_variant":[
        "Phum\u012d St\u0153\u0306ng Ch\u0103s"
    ],
    "wof:name":"Phum Stoeng Chas",
    "wof:placetype":"locality"
},
  "geometry": {"coordinates":[103.09903,13.55954],"type":"Point"}
}