{
  "type": "Feature",
  "properties": {
    "gn:admin1_code":"14",
    "gn:asciiname":"Phum Bot Kong",
    "gn:country_code":"KH",
    "gn:dem":11,
    "gn:feature_class":"P",
    "gn:feature_code":"PPL",
    "gn:name":"Phum Bot K\u00f4ng",
    "gn:population":0,
    "gn:timezone":"Asia/Phnom_Penh",
    "iso:country":"KH",
    "name:khm_x_preferred":[
        "Phum Bot K\u00f4ng"
    ],
    "name:khm_x_variant":[
        "\u1797\u17bc\u1798\u17b7 \u1794\u17bc\u178f\u1782\u1784",
        "Phum\u012d Bot K\u00f4ng"
    ],
    "wof:name":"Phum Bot Kong",
    "wof:placetype":"locality"
},
  "geometry": {"coordinates":[105.46792000000001,11.4018],"type":"Point"}
}