{
  "type": "Feature",
  "properties": {
    "gn:admin1_code":"27",
    "gn:asciiname":"Chhuk",
    "gn:country_code":"KH",
    "gn:dem":40,
    "gn:feature_class":"P",
    "gn:feature_code":"PPL",
    "gn:name":"Chhuk",
    "gn:population":0,
    "gn:timezone":"Asia/Phnom_Penh",
    "iso:country":"KH",
    "name:khm_x_preferred":[
        "Chhuk"
    ],
    "name:und_x_variant":[
        "Phum\u012d Chhuk"
    ],
    "wof:name":"Chhuk",
    "wof:placetype":"locality"
},
  "geometry": {"coordinates":[103.43210999999999,14.08318],"type":"Point"}
}