{
  "type": "Feature",
  "properties": {
    "gn:admin1_code":"12.0",
    "gn:asciiname":"Phum Kampung Samna",
    "gn:country_code":"KH",
    "gn:dem":6,
    "gn:feature_class":"P",
    "gn:feature_code":"PPL",
    "gn:name":"Phum K\u00e2mp\u016dng S\u00e2mn\u00e2",
    "gn:population":0,
    "gn:timezone":"Asia/Phnom_Penh",
    "iso:country":"KH",
    "name:khm_x_preferred":[
        "Phum K\u00e2mp\u016dng S\u00e2mn\u00e2"
    ],
    "name:khm_x_variant":[
        "\u1797\u17bc\u1798\u17b7 \u1780\u17c6\u1796\u1784\u17cb\u179f\u17c6\u178e\u179a"
    ],
    "wof:name":"Phum Kampung Samna",
    "wof:placetype":"locality"
},
  "geometry": {"coordinates":[103.86394,12.82601],"type":"Point"}
}