{
  "type": "Feature",
  "properties": {
    "gn:admin1_code":"31",
    "gn:asciiname":"Pnov",
    "gn:country_code":"KH",
    "gn:dem":38,
    "gn:feature_class":"P",
    "gn:feature_code":"PPL",
    "gn:name":"Pnov",
    "gn:population":0,
    "gn:timezone":"Asia/Phnom_Penh",
    "iso:country":"KH",
    "name:khm_x_preferred":[
        "Pnov"
    ],
    "name:und_x_variant":[
        "Phum\u012d Phn\u014fu"
    ],
    "wof:name":"Pnov",
    "wof:placetype":"locality"
},
  "geometry": {"coordinates":[106.04246000000001,12.03629],"type":"Point"}
}