{
  "type": "Feature",
  "properties": {
    "gn:admin1_code":"25",
    "gn:asciiname":"Phum Santung",
    "gn:country_code":"KH",
    "gn:dem":15,
    "gn:feature_class":"P",
    "gn:feature_code":"PPL",
    "gn:name":"Phum S\u00e2ntung",
    "gn:population":0,
    "gn:timezone":"Asia/Phnom_Penh",
    "iso:country":"KH",
    "name:khm_x_preferred":[
        "Phum S\u00e2ntung"
    ],
    "name:khm_x_variant":[
        "\u1797\u17bc\u1798\u17b7 \u179f\u1793\u17d2\u1791\u17bc\u1784"
    ],
    "name:und_x_variant":[
        "Santoung",
        "Phum\u012d S\u00e2ntung"
    ],
    "wof:name":"Phum Santung",
    "wof:placetype":"locality"
},
  "geometry": {"coordinates":[103.42095,13.71363],"type":"Point"}
}