{
  "type": "Feature",
  "properties": {
    "gn:admin1_code":"19",
    "gn:asciiname":"Phumi Kandaol",
    "gn:country_code":"KH",
    "gn:dem":10,
    "gn:feature_class":"P",
    "gn:feature_code":"PPL",
    "gn:name":"Phum\u012d K\u00e2nda\u00f4l",
    "gn:population":0,
    "gn:timezone":"Asia/Phnom_Penh",
    "iso:country":"KH",
    "name:und_x_variant":[
        "Phum\u012d Kanda\u00f4i",
        "Phum\u012d K\u00e2nda\u00f4l"
    ],
    "wof:name":"Phumi Kandaol",
    "wof:placetype":"locality"
},
  "geometry": {"coordinates":[104.89554,10.87577],"type":"Point"}
}