{
  "type": "Feature",
  "properties": {
    "gn:admin1_code":"04",
    "gn:asciiname":"Phumi Angk Samraong",
    "gn:country_code":"KH",
    "gn:dem":36,
    "gn:feature_class":"P",
    "gn:feature_code":"PPL",
    "gn:name":"Phum\u012d \u00c2ngk S\u00e2mra\u00f4ng",
    "gn:population":0,
    "gn:timezone":"Asia/Phnom_Penh",
    "iso:country":"KH",
    "name:und_x_variant":[
        "Phum \u00c2ng S\u00e2mr\u00f4ng",
        "Phum\u012d \u00c2ng S\u00e2mra\u00f4ng",
        "Phum\u012d \u00c2ngk S\u00e2mra\u00f4ng"
    ],
    "wof:name":"Phumi Angk Samraong",
    "wof:placetype":"locality"
},
  "geometry": {"coordinates":[104.68226,11.3567],"type":"Point"}
}