{
  "type": "Feature",
  "properties": {
    "gn:admin1_code":"04",
    "gn:asciiname":"Phumi Tram Kang",
    "gn:country_code":"KH",
    "gn:dem":24,
    "gn:feature_class":"P",
    "gn:feature_code":"PPL",
    "gn:name":"Phum\u012d Tr\u0103m K\u00e1ng",
    "gn:population":0,
    "gn:timezone":"Asia/Phnom_Penh",
    "iso:country":"KH",
    "wof:name":"Phumi Tram Kang",
    "wof:placetype":"locality"
},
  "geometry": {"coordinates":[104.62658999999999,11.11885],"type":"Point"}
}