{
  "type": "Feature",
  "properties": {
    "gn:admin1_code":"04",
    "gn:asciiname":"Krang Mkak",
    "gn:country_code":"KH",
    "gn:dem":47,
    "gn:feature_class":"P",
    "gn:feature_code":"PPL",
    "gn:name":"Krang Mkak",
    "gn:population":0,
    "gn:timezone":"Asia/Phnom_Penh",
    "iso:country":"KH",
    "name:khm_x_preferred":[
        "Krang Mkak"
    ],
    "wof:name":"Krang Mkak",
    "wof:placetype":"locality"
},
  "geometry": {"coordinates":[104.42361,11.46878],"type":"Point"}
}