{
  "type": "Feature",
  "properties": {
    "gn:admin1_code":"05",
    "gn:asciiname":"Tboung Tuek",
    "gn:country_code":"KH",
    "gn:dem":35,
    "gn:feature_class":"P",
    "gn:feature_code":"PPL",
    "gn:name":"Tboung Tuek",
    "gn:population":0,
    "gn:timezone":"Asia/Phnom_Penh",
    "iso:country":"KH",
    "name:khm_x_preferred":[
        "Tboung Tuek"
    ],
    "wof:name":"Tboung Tuek",
    "wof:placetype":"locality"
},
  "geometry": {"coordinates":[105.27484,13.09855],"type":"Point"}
}