{
  "type": "Feature",
  "properties": {
    "gn:admin1_code":"07",
    "gn:asciiname":"Phumi Takev",
    "gn:country_code":"KH",
    "gn:dem":13,
    "gn:feature_class":"P",
    "gn:feature_code":"PPL",
    "gn:name":"Phum\u012d Tak\u00eav",
    "gn:population":0,
    "gn:timezone":"Asia/Phnom_Penh",
    "iso:country":"KH",
    "name:und_x_variant":[
        "Phum Takeo",
        "Phum\u012d Tak\u00eav"
    ],
    "wof:name":"Phumi Takev",
    "wof:placetype":"locality"
},
  "geometry": {"coordinates":[105.05568999999998,11.65415],"type":"Point"}
}