{
  "type": "Feature",
  "properties": {
    "gn:admin1_code":"12",
    "gn:asciiname":"Krakor",
    "gn:country_code":"KH",
    "gn:dem":18,
    "gn:feature_class":"P",
    "gn:feature_code":"PPL",
    "gn:name":"Kr\u00e2k\u00f4r",
    "gn:population":0,
    "gn:timezone":"Asia/Phnom_Penh",
    "iso:country":"KH",
    "name:khm_x_preferred":[
        "\u1780\u17d2\u179a\u1782\u179a"
    ],
    "name:und_x_variant":[
        "Phum\u012d Kr\u00e2k\u00f4r",
        "Kr\u00e2k\u00f4r"
    ],
    "wof:name":"Krakor",
    "wof:placetype":"locality"
},
  "geometry": {"coordinates":[104.20992,12.5325],"type":"Point"}
}