{
  "type": "Feature",
  "properties": {
    "gn:admin1_code":"25",
    "gn:asciiname":"Chhuk",
    "gn:country_code":"KH",
    "gn:dem":19,
    "gn:feature_class":"P",
    "gn:feature_code":"PPL",
    "gn:name":"Chhuk",
    "gn:population":0,
    "gn:timezone":"Asia/Phnom_Penh",
    "iso:country":"KH",
    "name:khm_x_preferred":[
        "Chhuk"
    ],
    "name:und_x_variant":[
        "Phum\u012d Chhuk (2)"
    ],
    "wof:name":"Chhuk",
    "wof:placetype":"locality"
},
  "geometry": {"coordinates":[102.86977,13.67403],"type":"Point"}
}