{
  "type": "Feature",
  "properties": {
    "gn:admin1_code":"31",
    "gn:asciiname":"Phum Andong Longieng",
    "gn:country_code":"KH",
    "gn:dem":40,
    "gn:feature_class":"P",
    "gn:feature_code":"PPL",
    "gn:name":"Phum \u00c2ndong L\u00f4ngi\u0115ng",
    "gn:population":0,
    "gn:timezone":"Asia/Phnom_Penh",
    "iso:country":"KH",
    "name:khm_x_preferred":[
        "Phum \u00c2ndong L\u00f4ngi\u0115ng"
    ],
    "name:khm_x_variant":[
        "\u1797\u17bc\u1798\u17b7 \u17a2\u178e\u17d2\u178a\u17bc\u1784\u179b\u17d2\u1784\u17c0\u1784"
    ],
    "name:und_x_variant":[
        "Phum\u012d \u00c2ndong L\u00f4ngi\u0115ng",
        "Phum \u00c2ndong Rongeang",
        "Phum\u012d \u00c2ndong Lngi\u0115ng"
    ],
    "wof:name":"Phum Andong Longieng",
    "wof:placetype":"locality"
},
  "geometry": {"coordinates":[105.9139,12.08335],"type":"Point"}
}