{
  "type": "Feature",
  "properties": {
    "gn:admin1_code":"31",
    "gn:asciiname":"Praphat",
    "gn:country_code":"KH",
    "gn:dem":20,
    "gn:feature_class":"P",
    "gn:feature_code":"PPL",
    "gn:name":"Praphat",
    "gn:population":0,
    "gn:timezone":"Asia/Phnom_Penh",
    "iso:country":"KH",
    "name:khm_x_preferred":[
        "Phum Pr\u00e2ph\u0103t"
    ],
    "name:khm_x_variant":[
        "Praphat",
        "\u1797\u17bc\u1798\u17b7 \u1794\u17d2\u179a\u1795\u17b6\u178f\u17cb"
    ],
    "name:und_x_variant":[
        "Phum Tuol Praphatt"
    ],
    "wof:name":"Praphat",
    "wof:placetype":"locality"
},
  "geometry": {"coordinates":[105.63873999999998,12.09437],"type":"Point"}
}