{
  "type": "Feature",
  "properties": {
    "iso:country":"KH",
    "name:ara_x_preferred":[
        "\u0628\u0648\u064a\u0628\u062a"
    ],
    "name:ben_x_preferred":[
        "\u09aa\u0987\u09aa\u09c7\u099f"
    ],
    "name:dan_x_preferred":[
        "Poipet"
    ],
    "name:deu_x_preferred":[
        "Poipet"
    ],
    "name:ell_x_preferred":[
        "\u03a0\u03bf\u03ca\u03c0\u03ad\u03c4"
    ],
    "name:eng_x_preferred":[
        "Poipet"
    ],
    "name:fin_x_preferred":[
        "Poipet"
    ],
    "name:fra_x_preferred":[
        "Poipet"
    ],
    "name:guj_x_preferred":[
        "\u0aaa\u0acb\u0a88\u0aaa\u0ac7\u0a9f"
    ],
    "name:hin_x_preferred":[
        "\u092a\u094b\u092a\u0947\u091f"
    ],
    "name:ind_x_preferred":[
        "Poipet"
    ],
    "name:ita_x_preferred":[
        "Poipet"
    ],
    "name:jpn_x_preferred":[
        "\u30dd\u30a4\u30da\u30c8"
    ],
    "name:kan_x_preferred":[
        "\u0caa\u0cca\u0caa\u0cbf\u0c9f\u0ccd"
    ],
    "name:khm_x_preferred":[
        "Paoy Paet"
    ],
    "name:khm_x_variant":[
        "\u1794\u17c9\u17c4\u1799\u1794\u17c9\u17c2\u178f",
        "\u1780\u17d2\u179a\u17bb\u1784\u1794\u17c9\u17c4\u1799\u1794\u17c9\u17c2\u178f"
    ],
    "name:kor_x_preferred":[
        "\ud3ec\uc774\ud3ab"
    ],
    "name:lav_x_preferred":[
        "Poipeta"
    ],
    "name:lit_x_preferred":[
        "Poipetas"
    ],
    "name:mar_x_preferred":[
        "\u092a\u094b\u0907\u092a\u0947\u091f"
    ],
    "name:msa_x_preferred":[
        "Poipet"
    ],
    "name:nld_x_preferred":[
        "Poipet"
    ],
    "name:nob_x_preferred":[
        "Poipet"
    ],
    "name:pol_x_preferred":[
        "Pa\u00f4yp\u00eat"
    ],
    "name:por_x_preferred":[
        "Poipet"
    ],
    "name:ron_x_preferred":[
        "Poipet"
    ],
    "name:rus_x_preferred":[
        "\u041f\u043e\u0439\u043f\u0435\u0442"
    ],
    "name:sin_x_preferred":[
        "\u0db4\u0ddc\u0dba\u0dd2\u0db4\u0dd9\u0da7\u0dca"
    ],
    "name:spa_x_preferred":[
        "Poipet"
    ],
    "name:swe_x_preferred":[
        "Poipet"
    ],
    "name:tam_x_preferred":[
        "\u0baa\u0bca\u0baf\u0bcd\u0baa\u0bcd\u0baa\u0bc7\u0b9f\u0bcd"
    ],
    "name:tel_x_preferred":[
        "\u0c2a\u0c4a\u0c2f\u0c4d\u0c2a\u0c4d\u0c1f\u0c4d"
    ],
    "name:tha_x_preferred":[
        "\u0e1b\u0e2d\u0e22\u0e40\u0e1b\u0e15"
    ],
    "name:tur_x_preferred":[
        "Poipet"
    ],
    "name:ukr_x_preferred":[
        "\u041f\u043e\u0439\u043f\u0435\u0442"
    ],
    "name:unk_x_variant":[
        "Phum\u012d Pa\u00f4y P\u00eat"
    ],
    "name:urd_x_preferred":[
        "\u067e\u0648\u0626\u06cc\u067e\u06cc\u062a"
    ],
    "name:vie_x_preferred":[
        "Poipet"
    ],
    "name:zho_x_preferred":[
        "\u6ce2\u5225"
    ],
    "qs:gn_country":"KH",
    "qs:gn_fcode":"PPL",
    "qs:gn_pop":79000,
    "qs:name":"Paoy Pet",
    "qs:name_adm0":"Thailand",
    "qs:name_adm1":"Sa Kaeo",
    "qs:photos":265,
    "qs:photos_1k":54,
    "qs:photos_9k":1,
    "qs:photos_9r":4,
    "qs:photos_all":265,
    "qs:photos_sr":5,
    "qs:placetype":"Town",
    "qs:pop_sr":"8",
    "qs:woe_adm0":23424960,
    "wof:name":"Paoy Pet",
    "wof:placetype":"locality",
    "wof:population":79000
},
  "geometry": {"coordinates":[102.5625,13.65611],"type":"Point"}
}