{
  "type": "Feature",
  "properties": {
    "gn:admin1_code":"04",
    "gn:asciiname":"Aoral",
    "gn:country_code":"KH",
    "gn:dem":162,
    "gn:feature_class":"P",
    "gn:feature_code":"PPL",
    "gn:name":"Aoral",
    "gn:population":0,
    "gn:timezone":"Asia/Phnom_Penh",
    "iso:country":"KH",
    "name:khm_x_preferred":[
        "Aoral"
    ],
    "name:khm_x_variant":[
        "\u17aa\u179a\u17b6\u179b"
    ],
    "name:und_x_variant":[
        "Phum\u012d Lomgim",
        "L\u00f4ng\u0153\u0306m",
        "Phum\u012d L\u00f4ng\u0153\u0306m",
        "Lng\u0153\u0306m"
    ],
    "wof:name":"Aoral",
    "wof:placetype":"locality"
},
  "geometry": {"coordinates":[104.16813999999999,11.87783],"type":"Point"}
}