{
  "type": "Feature",
  "properties": {
    "gn:admin1_code":"07",
    "gn:asciiname":"Snuol Khpos",
    "gn:country_code":"KH",
    "gn:dem":23,
    "gn:feature_class":"P",
    "gn:feature_code":"PPL",
    "gn:name":"Snuol Khpos",
    "gn:population":0,
    "gn:timezone":"Asia/Phnom_Penh",
    "iso:country":"KH",
    "name:khm_x_preferred":[
        "Snuol Khpos"
    ],
    "name:und_x_variant":[
        "Phum\u012d Snu\u014fl Khpu\u014fs",
        "Phum\u012d Snu\u014fl Khp\u00f3s"
    ],
    "wof:name":"Snuol Khpos",
    "wof:placetype":"locality"
},
  "geometry": {"coordinates":[104.76581,11.54271],"type":"Point"}
}