{
  "type": "Feature",
  "properties": {
    "gn:admin1_code":"13",
    "gn:asciiname":"Phumi Phlach",
    "gn:country_code":"KH",
    "gn:dem":91,
    "gn:feature_class":"P",
    "gn:feature_code":"PPL",
    "gn:name":"Phum\u012d Phl\u00e2ch",
    "gn:population":0,
    "gn:timezone":"Asia/Phnom_Penh",
    "iso:country":"KH",
    "wof:name":"Phumi Phlach",
    "wof:placetype":"locality"
},
  "geometry": {"coordinates":[105.40661,13.61069],"type":"Point"}
}