{
  "type": "Feature",
  "properties": {
    "gn:admin1_code":"03",
    "gn:asciiname":"Phum Prey Preal",
    "gn:country_code":"KH",
    "gn:dem":30,
    "gn:feature_class":"P",
    "gn:feature_code":"PPL",
    "gn:name":"Phum Prey Pr\u00e9al",
    "gn:population":0,
    "gn:timezone":"Asia/Phnom_Penh",
    "iso:country":"KH",
    "name:khm_x_preferred":[
        "Phum Prey Pr\u00e9al"
    ],
    "name:khm_x_variant":[
        "\u1797\u17bc\u1798\u17b7 \u1796\u17d2\u179a\u17c3\u1796\u17d2\u179a\u17b6\u179b"
    ],
    "name:und_x_variant":[
        "Phum Prei Pr\u00e9al",
        "Phum\u012d Prey Pr\u00e9al"
    ],
    "wof:name":"Phum Prey Preal",
    "wof:placetype":"locality"
},
  "geometry": {"coordinates":[104.44956999999999,12.3317],"type":"Point"}
}