{
  "type": "Feature",
  "properties": {
    "gn:admin1_code":"21",
    "gn:asciiname":"Phumi Trapeang Trav",
    "gn:country_code":"KH",
    "gn:dem":11,
    "gn:feature_class":"P",
    "gn:feature_code":"PPL",
    "gn:name":"Phum\u012d Tr\u00e2pe\u0103ng Trav",
    "gn:population":0,
    "gn:timezone":"Asia/Phnom_Penh",
    "iso:country":"KH",
    "name:und_x_variant":[
        "Phum Ta Ten",
        "Phum\u012d Tr\u00e2pe\u0103ng Trav"
    ],
    "wof:name":"Phumi Trapeang Trav",
    "wof:placetype":"locality"
},
  "geometry": {"coordinates":[104.57047,10.71159],"type":"Point"}
}