{
  "type": "Feature",
  "properties": {
    "gn:admin1_code":"12",
    "gn:asciiname":"Phumi Banlich Sdei",
    "gn:country_code":"KH",
    "gn:dem":14,
    "gn:feature_class":"P",
    "gn:feature_code":"PPL",
    "gn:name":"Phum\u012d B\u00e2nl\u012dch Sdei",
    "gn:population":0,
    "gn:timezone":"Asia/Phnom_Penh",
    "iso:country":"KH",
    "wof:name":"Phumi Banlich Sdei",
    "wof:placetype":"locality"
},
  "geometry": {"coordinates":[104.12612,12.67345],"type":"Point"}
}