{
  "type": "Feature",
  "properties": {
    "gn:admin1_code":"12",
    "gn:asciiname":"Phumi Dong Pol",
    "gn:country_code":"KH",
    "gn:dem":57,
    "gn:feature_class":"P",
    "gn:feature_code":"PPL",
    "gn:name":"Phum\u012d Dong P\u00f4l",
    "gn:population":0,
    "gn:timezone":"Asia/Phnom_Penh",
    "iso:country":"KH",
    "name:und_x_variant":[
        "P\u2019um D\u00e2ung P\u016dl",
        "Phum\u012d Dong P\u00f4l"
    ],
    "wof:name":"Phumi Dong Pol",
    "wof:placetype":"locality"
},
  "geometry": {"coordinates":[103.83714000000001,12.23882],"type":"Point"}
}