{
  "type": "Feature",
  "properties": {
    "gn:admin1_code":"02",
    "gn:asciiname":"Phumi Thkov",
    "gn:country_code":"KH",
    "gn:dem":14,
    "gn:feature_class":"P",
    "gn:feature_code":"PPL",
    "gn:name":"Phum\u012d Thkov",
    "gn:population":0,
    "gn:timezone":"Asia/Phnom_Penh",
    "iso:country":"KH",
    "name:und_x_variant":[
        "Phum Khnar",
        "Phum\u012d Thkov"
    ],
    "wof:name":"Phumi Thkov",
    "wof:placetype":"locality"
},
  "geometry": {"coordinates":[105.04198999999998,12.15038],"type":"Point"}
}