{
  "type": "Feature",
  "properties": {
    "gn:admin1_code":"14",
    "gn:asciiname":"Svay Phluoh",
    "gn:country_code":"KH",
    "gn:dem":12,
    "gn:feature_class":"P",
    "gn:feature_code":"PPL",
    "gn:name":"Svay Phluoh",
    "gn:population":0,
    "gn:timezone":"Asia/Phnom_Penh",
    "iso:country":"KH",
    "name:khm_x_preferred":[
        "Svay Phluoh"
    ],
    "name:khm_x_variant":[
        "Phum\u012d Sik\u014fk",
        "Phum Sik\u014fk",
        "\u1797\u17bc\u1798\u17b7 \u179f\u17ca\u17b8\u1780\u17bb\u1780"
    ],
    "wof:name":"Svay Phluoh",
    "wof:placetype":"locality"
},
  "geometry": {"coordinates":[105.23697,11.12684],"type":"Point"}
}