{
  "type": "Feature",
  "properties": {
    "gn:admin1_code":"4.0",
    "gn:asciiname":"Phum Chrak Terk",
    "gn:country_code":"KH",
    "gn:dem":120,
    "gn:feature_class":"P",
    "gn:feature_code":"PPL",
    "gn:name":"Phum Chr\u00e2k T\u00e9rk",
    "gn:population":0,
    "gn:timezone":"Asia/Phnom_Penh",
    "iso:country":"KH",
    "name:khm_x_preferred":[
        "Phum Chr\u00e2k T\u00e9rk"
    ],
    "name:khm_x_variant":[
        "\u1797\u17bc\u1798\u17b7 \u1785\u17d2\u179a\u1780\u1791\u17b6\u1780\u17cb"
    ],
    "wof:name":"Phum Chrak Terk",
    "wof:placetype":"locality"
},
  "geometry": {"coordinates":[104.13883,11.80175],"type":"Point"}
}