{
  "type": "Feature",
  "properties": {
    "gn:admin1_code":"25",
    "gn:asciiname":"Pring Chu",
    "gn:country_code":"KH",
    "gn:dem":18,
    "gn:feature_class":"P",
    "gn:feature_code":"PPL",
    "gn:name":"Pring Chu",
    "gn:population":0,
    "gn:timezone":"Asia/Phnom_Penh",
    "iso:country":"KH",
    "name:khm_x_preferred":[
        "Pring Chu"
    ],
    "name:khm_x_variant":[
        "\u1797\u17bc\u1798\u17b7 \u1796\u17d2\u179a\u17b8\u1784\u17bc",
        "Phum Pring Chu"
    ],
    "name:und_x_variant":[
        "Pring Tchou",
        "Phum\u012d Pring Chu",
        "Phum\u012d Pring Chur"
    ],
    "wof:name":"Pring Chu",
    "wof:placetype":"locality"
},
  "geometry": {"coordinates":[103.30213999999999,13.59617],"type":"Point"}
}