{
  "type": "Feature",
  "properties": {
    "gn:admin1_code":"29",
    "gn:asciiname":"Phum Kouk Thnung",
    "gn:country_code":"KH",
    "gn:dem":18,
    "gn:feature_class":"P",
    "gn:feature_code":"PPL",
    "gn:name":"Phum Ko\u016dk Thn\u016dng",
    "gn:population":0,
    "gn:timezone":"Asia/Phnom_Penh",
    "iso:country":"KH",
    "name:khm_x_preferred":[
        "Phum Ko\u016dk Thn\u016dng"
    ],
    "name:khm_x_variant":[
        "\u1797\u17bc\u1798\u17b7 \u1782\u17c4\u1780\u1792\u17d2\u1793\u1784\u17cb"
    ],
    "wof:name":"Phum Kouk Thnung",
    "wof:placetype":"locality"
},
  "geometry": {"coordinates":[103.31679,12.86247],"type":"Point"}
}