{
  "type": "Feature",
  "properties": {
    "gn:admin1_code":"13",
    "gn:asciiname":"Chhnuon",
    "gn:country_code":"KH",
    "gn:dem":46,
    "gn:feature_class":"P",
    "gn:feature_code":"PPL",
    "gn:name":"Chhnuon",
    "gn:population":0,
    "gn:timezone":"Asia/Phnom_Penh",
    "iso:country":"KH",
    "name:khm_x_preferred":[
        "Chhnuon"
    ],
    "name:und_x_variant":[
        "Kompong Chouang",
        "Phum Chnon",
        "Kompong Choan",
        "Phum\u012d Chhnu\u014fn"
    ],
    "wof:name":"Chhnuon",
    "wof:placetype":"locality"
},
  "geometry": {"coordinates":[105.21338,13.43002],"type":"Point"}
}