{
  "type": "Feature",
  "properties": {
    "gn:admin1_code":"04",
    "gn:asciiname":"Ou Veaeng",
    "gn:country_code":"KH",
    "gn:dem":43,
    "gn:feature_class":"P",
    "gn:feature_code":"PPL",
    "gn:name":"Ou Veaeng",
    "gn:population":0,
    "gn:timezone":"Asia/Phnom_Penh",
    "iso:country":"KH",
    "name:khm_x_preferred":[
        "Ou Veaeng"
    ],
    "wof:name":"Ou Veaeng",
    "wof:placetype":"locality"
},
  "geometry": {"coordinates":[104.45505,11.42631],"type":"Point"}
}