{
  "type": "Feature",
  "properties": {
    "gn:admin1_code":"29",
    "gn:asciiname":"Kaoh Char",
    "gn:country_code":"KH",
    "gn:dem":17,
    "gn:feature_class":"P",
    "gn:feature_code":"PPL",
    "gn:name":"Kaoh Char",
    "gn:population":0,
    "gn:timezone":"Asia/Phnom_Penh",
    "iso:country":"KH",
    "name:khm_x_preferred":[
        "Kaoh Char"
    ],
    "name:khm_x_variant":[
        "\u1797\u17bc\u1798\u17b7 \u1780\u17c4\u17c7\u1785\u17b6",
        "Phum Ka\u00f4h Char"
    ],
    "name:und_x_variant":[
        "Phum\u012d Ka\u00f4h Char",
        "Phum\u012d Ka\u00f4h Cha"
    ],
    "wof:name":"Kaoh Char",
    "wof:placetype":"locality"
},
  "geometry": {"coordinates":[103.36691999999999,12.7987],"type":"Point"}
}