{
  "type": "Feature",
  "properties": {
    "gn:admin1_code":"04",
    "gn:asciiname":"Phumi Prey Smach",
    "gn:country_code":"KH",
    "gn:dem":29,
    "gn:feature_class":"P",
    "gn:feature_code":"PPL",
    "gn:name":"Phum\u012d Prey Sm\u0103ch",
    "gn:population":0,
    "gn:timezone":"Asia/Phnom_Penh",
    "iso:country":"KH",
    "wof:name":"Phumi Prey Smach",
    "wof:placetype":"locality"
},
  "geometry": {"coordinates":[104.65992,11.20314],"type":"Point"}
}