{
  "type": "Feature",
  "properties": {
    "gn:admin1_code":"25",
    "gn:asciiname":"Phum Preah Ang",
    "gn:country_code":"KH",
    "gn:dem":17,
    "gn:feature_class":"P",
    "gn:feature_code":"PPL",
    "gn:name":"Phum Pre\u0103h Ang",
    "gn:population":0,
    "gn:timezone":"Asia/Phnom_Penh",
    "iso:country":"KH",
    "name:khm_x_preferred":[
        "Phum Pre\u0103h Ang"
    ],
    "name:khm_x_variant":[
        "\u1797\u17bc\u1798\u17b7 \u1796\u17d2\u179a\u17c7\u17a2\u1784\u17d2\u1782"
    ],
    "wof:name":"Phum Preah Ang",
    "wof:placetype":"locality"
},
  "geometry": {"coordinates":[103.03816999999999,13.58429],"type":"Point"}
}