{
  "type": "Feature",
  "properties": {
    "gn:admin1_code":"31",
    "gn:asciiname":"Phum Tukdach",
    "gn:country_code":"KH",
    "gn:dem":14,
    "gn:feature_class":"P",
    "gn:feature_code":"PPL",
    "gn:name":"Phum Tukdach",
    "gn:population":0,
    "gn:timezone":"Asia/Phnom_Penh",
    "iso:country":"KH",
    "name:khm_x_preferred":[
        "Phum T\u0153\u0306k D\u0103ch"
    ],
    "name:khm_x_variant":[
        "\u1797\u17bc\u1798\u17b7 \u1791\u17b9\u1780\u178a\u17b6\u1785\u17cb"
    ],
    "wof:name":"Phum Tukdach",
    "wof:placetype":"locality"
},
  "geometry": {"coordinates":[105.63748,12.21689],"type":"Point"}
}