{
  "type": "Feature",
  "properties": {
    "gn:admin1_code":"29",
    "gn:asciiname":"Phum Khsaoy",
    "gn:country_code":"KH",
    "gn:dem":12,
    "gn:feature_class":"P",
    "gn:feature_code":"PPL",
    "gn:name":"Phum Khsa\u00f4y",
    "gn:population":0,
    "gn:timezone":"Asia/Phnom_Penh",
    "iso:country":"KH",
    "name:khm_x_preferred":[
        "Phum Khsa\u00f4y"
    ],
    "name:khm_x_variant":[
        "\u1797\u17bc\u1798\u17b7 \u1781\u17d2\u179f\u17c4\u1799"
    ],
    "wof:name":"Phum Khsaoy",
    "wof:placetype":"locality"
},
  "geometry": {"coordinates":[103.37269000000001,12.99903],"type":"Point"}
}