{
  "type": "Feature",
  "properties": {
    "gn:admin1_code":"09",
    "gn:asciiname":"Phumi Chrouy Ampil Toek",
    "gn:country_code":"KH",
    "gn:dem":39,
    "gn:feature_class":"P",
    "gn:feature_code":"PPL",
    "gn:name":"Phum\u012d Chro\u016dy \u00c2mp\u012dl T\u0153\u0306k",
    "gn:population":0,
    "gn:timezone":"Asia/Phnom_Penh",
    "iso:country":"KH",
    "wof:name":"Phumi Chrouy Ampil Toek",
    "wof:placetype":"locality"
},
  "geometry": {"coordinates":[105.95501000000002,12.87703],"type":"Point"}
}