{
  "type": "Feature",
  "properties": {
    "gn:admin1_code":"24.0",
    "gn:asciiname":"Boeng Vien",
    "gn:country_code":"KH",
    "gn:dem":24,
    "gn:feature_class":"P",
    "gn:feature_code":"PPL",
    "gn:name":"Boeng Vien",
    "gn:population":0,
    "gn:timezone":"Asia/Phnom_Penh",
    "iso:country":"KH",
    "name:khm_x_preferred":[
        "Boeng Vien"
    ],
    "name:khm_x_variant":[
        "Phum\u012d B\u0153\u0306ng V\u00eang",
        "\u1797\u17bc\u1798\u17b7 \u1794\u17b9\u1784\u179c\u17c2\u1784"
    ],
    "wof:name":"Boeng Vien",
    "wof:placetype":"locality"
},
  "geometry": {"coordinates":[104.14888999999999,13.26925],"type":"Point"}
}