{
  "type": "Feature",
  "properties": {
    "gn:admin1_code":"24.0",
    "gn:asciiname":"Kaksekamm",
    "gn:country_code":"KH",
    "gn:dem":20,
    "gn:feature_class":"P",
    "gn:feature_code":"PPL",
    "gn:name":"Kaksekamm",
    "gn:population":0,
    "gn:timezone":"Asia/Phnom_Penh",
    "iso:country":"KH",
    "name:khm_x_preferred":[
        "Kaksekamm"
    ],
    "wof:name":"Kaksekamm",
    "wof:placetype":"locality"
},
  "geometry": {"coordinates":[103.82035999999999,13.38307],"type":"Point"}
}