{
  "type": "Feature",
  "properties": {
    "gn:admin1_code":"31",
    "gn:asciiname":"Phumi Veal",
    "gn:country_code":"KH",
    "gn:dem":18,
    "gn:feature_class":"P",
    "gn:feature_code":"PPL",
    "gn:name":"Phum\u012d V\u00e9al",
    "gn:population":0,
    "gn:timezone":"Asia/Phnom_Penh",
    "iso:country":"KH",
    "name:und_x_variant":[
        "Phum V\u00e9al Khtoum",
        "Phum\u012d V\u00e9al"
    ],
    "wof:name":"Phumi Veal",
    "wof:placetype":"locality"
},
  "geometry": {"coordinates":[105.63485,11.83702],"type":"Point"}
}