{
  "type": "Feature",
  "properties": {
    "gn:admin1_code":"29",
    "gn:asciiname":"Prey Totueng",
    "gn:country_code":"KH",
    "gn:dem":24,
    "gn:feature_class":"P",
    "gn:feature_code":"PPL",
    "gn:name":"Prey Totueng",
    "gn:population":0,
    "gn:timezone":"Asia/Phnom_Penh",
    "iso:country":"KH",
    "name:khm_x_preferred":[
        "Prey Totueng"
    ],
    "wof:name":"Prey Totueng",
    "wof:placetype":"locality"
},
  "geometry": {"coordinates":[103.20465,12.94731],"type":"Point"}
}