{
  "type": "Feature",
  "properties": {
    "gn:admin1_code":"28",
    "gn:asciiname":"Phum Mak Preng",
    "gn:country_code":"KH",
    "gn:dem":14,
    "gn:feature_class":"P",
    "gn:feature_code":"PPL",
    "gn:name":"Phum M\u0103k Pr\u00e9ng",
    "gn:population":0,
    "gn:timezone":"Asia/Phnom_Penh",
    "iso:country":"KH",
    "name:khm_x_preferred":[
        "Phum M\u0103k Pr\u00e9ng"
    ],
    "name:khm_x_variant":[
        "\u1797\u17bc\u1798\u17b7 \u1798\u17c9\u17b6\u1780\u17cb\u1796\u17d2\u179a\u17c1\u1784"
    ],
    "name:und_x_variant":[
        "Phum Ma Preng",
        "Phum\u012d M\u0103k Pr\u00e9ng"
    ],
    "wof:name":"Phum Mak Preng",
    "wof:placetype":"locality"
},
  "geometry": {"coordinates":[103.77509999999999,10.64902],"type":"Point"}
}