{
  "type": "Feature",
  "properties": {
    "gn:admin1_code":"05",
    "gn:asciiname":"Slaeng Khpos",
    "gn:country_code":"KH",
    "gn:dem":17,
    "gn:feature_class":"P",
    "gn:feature_code":"PPL",
    "gn:name":"Slaeng Khpos",
    "gn:population":0,
    "gn:timezone":"Asia/Phnom_Penh",
    "iso:country":"KH",
    "name:khm_x_preferred":[
        "Slaeng Khpos"
    ],
    "wof:name":"Slaeng Khpos",
    "wof:placetype":"locality"
},
  "geometry": {"coordinates":[104.70001999999999,12.79217],"type":"Point"}
}