{
  "type": "Feature",
  "properties": {
    "gn:admin1_code":"05",
    "gn:asciiname":"Thla",
    "gn:country_code":"KH",
    "gn:dem":17,
    "gn:feature_class":"P",
    "gn:feature_code":"PPL",
    "gn:name":"Thla",
    "gn:population":0,
    "gn:timezone":"Asia/Phnom_Penh",
    "iso:country":"KH",
    "name:khm_x_preferred":[
        "Thla"
    ],
    "name:und_x_variant":[
        "Phum\u012d Thla"
    ],
    "wof:name":"Thla",
    "wof:placetype":"locality"
},
  "geometry": {"coordinates":[105.12108000000001,12.25834],"type":"Point"}
}