{
  "type": "Feature",
  "properties": {
    "gn:admin1_code":"14",
    "gn:asciiname":"Phum Tama",
    "gn:country_code":"KH",
    "gn:dem":11,
    "gn:feature_class":"P",
    "gn:feature_code":"PPL",
    "gn:name":"Phum Tama",
    "gn:population":0,
    "gn:timezone":"Asia/Phnom_Penh",
    "iso:country":"KH",
    "name:khm_x_preferred":[
        "Phum Tama"
    ],
    "name:khm_x_variant":[
        "\u1797\u17bc\u1798\u17b7 \u178f\u17b6\u1798\u17c9\u17b6",
        "Phum\u012d Tama"
    ],
    "wof:name":"Phum Tama",
    "wof:placetype":"locality"
},
  "geometry": {"coordinates":[105.43210999999999,11.31381],"type":"Point"}
}