{
  "type": "Feature",
  "properties": {
    "gn:admin1_code":"19",
    "gn:asciiname":"Bourei Cholsar",
    "gn:country_code":"KH",
    "gn:dem":6,
    "gn:feature_class":"P",
    "gn:feature_code":"PPLA2",
    "gn:name":"Bourei Cholsar",
    "gn:population":0,
    "gn:timezone":"Asia/Phnom_Penh",
    "iso:country":"KH",
    "name:khm_x_preferred":[
        "Bourei Cholsar"
    ],
    "wof:name":"Bourei Cholsar",
    "wof:placetype":"locality"
},
  "geometry": {"coordinates":[105.01851000000001,10.83431],"type":"Point"}
}