{
  "type": "Feature",
  "properties": {
    "gn:admin1_code":"14",
    "gn:asciiname":"Vott Samraong Reach",
    "gn:country_code":"KH",
    "gn:dem":9,
    "gn:feature_class":"P",
    "gn:feature_code":"PPL",
    "gn:name":"V\u00f4tt S\u00e2mra\u00f4ng R\u00e9ach",
    "gn:population":0,
    "gn:timezone":"Asia/Phnom_Penh",
    "iso:country":"KH",
    "name:und_x_variant":[
        "Vat Samrong",
        "Vatt S\u00e2mra\u00f4ng R\u00e9ach",
        "V\u00f4tt S\u00e2mra\u00f4ng R\u00e9ach"
    ],
    "wof:name":"Vott Samraong Reach",
    "wof:placetype":"locality"
},
  "geometry": {"coordinates":[105.51408000000001,11.18204],"type":"Point"}
}