{
  "type": "Feature",
  "properties": {
    "gn:admin1_code":"27",
    "gn:asciiname":"Kouk Kabbas",
    "gn:country_code":"KH",
    "gn:dem":48,
    "gn:feature_class":"P",
    "gn:feature_code":"PPL",
    "gn:name":"Kouk Kabbas",
    "gn:population":0,
    "gn:timezone":"Asia/Phnom_Penh",
    "iso:country":"KH",
    "name:khm_x_preferred":[
        "Kouk Kabbas"
    ],
    "name:khm_x_variant":[
        "\u1797\u17bc\u1798\u17b7 \u1782\u17c4\u1780\u1780\u17d2\u179a\u1794\u17b6\u179f"
    ],
    "name:und_x_variant":[
        "Phum Ko\u016dk Kr\u00e2bas",
        "Phum\u012d Ko\u016dk Kr\u00e2bas"
    ],
    "wof:name":"Kouk Kabbas",
    "wof:placetype":"locality"
},
  "geometry": {"coordinates":[103.22597,14.10092],"type":"Point"}
}