{
  "type": "Feature",
  "properties": {
    "gn:admin1_code":"29",
    "gn:asciiname":"Phum Tram Seh",
    "gn:country_code":"KH",
    "gn:dem":36,
    "gn:feature_class":"P",
    "gn:feature_code":"PPL",
    "gn:name":"Phum Tr\u0103m S\u00e9h",
    "gn:population":0,
    "gn:timezone":"Asia/Phnom_Penh",
    "iso:country":"KH",
    "name:khm_x_preferred":[
        "Phum Tr\u0103m S\u00e9h"
    ],
    "name:khm_x_variant":[
        "\u1797\u17bc\u1798\u17b7 \u178f\u17d2\u179a\u17b6\u17c6\u179f\u17c1\u17c7"
    ],
    "name:und_x_variant":[
        "Phum Tram Ses",
        "Phum\u012d Tr\u0103m S\u00e9h"
    ],
    "wof:name":"Phum Tram Seh",
    "wof:placetype":"locality"
},
  "geometry": {"coordinates":[103.38964,12.62623],"type":"Point"}
}