{
  "type": "Feature",
  "properties": {
    "gn:admin1_code":"05",
    "gn:asciiname":"Phum Prei Totung",
    "gn:country_code":"KH",
    "gn:dem":53,
    "gn:feature_class":"P",
    "gn:feature_code":"PPL",
    "gn:name":"Phum Prei Totung",
    "gn:population":0,
    "gn:timezone":"Asia/Phnom_Penh",
    "iso:country":"KH",
    "name:und_x_variant":[
        "Phum\u012d Prey T\u00f4t\u0153\u0306ng"
    ],
    "wof:name":"Phum Prei Totung",
    "wof:placetype":"locality"
},
  "geometry": {"coordinates":[104.9504,13.06518],"type":"Point"}
}