{
  "type": "Feature",
  "properties": {
    "gn:admin1_code":"29",
    "gn:asciiname":"Kakaoh Kambot",
    "gn:country_code":"KH",
    "gn:dem":18,
    "gn:feature_class":"P",
    "gn:feature_code":"PPL",
    "gn:name":"Kakaoh Kambot",
    "gn:population":0,
    "gn:timezone":"Asia/Phnom_Penh",
    "iso:country":"KH",
    "name:khm_x_preferred":[
        "Kakaoh Kambot"
    ],
    "wof:name":"Kakaoh Kambot",
    "wof:placetype":"locality"
},
  "geometry": {"coordinates":[103.24659,12.96375],"type":"Point"}
}