{
  "type": "Feature",
  "properties": {
    "gn:admin1_code":"24",
    "gn:asciiname":"Toap Svay",
    "gn:country_code":"KH",
    "gn:dem":44,
    "gn:feature_class":"P",
    "gn:feature_code":"PPL",
    "gn:name":"Toap Svay",
    "gn:population":0,
    "gn:timezone":"Asia/Phnom_Penh",
    "iso:country":"KH",
    "name:khm_x_preferred":[
        "Toap Svay"
    ],
    "name:khm_x_variant":[
        "\u1797\u17bc\u1798\u17b7 \u1791\u17b6\u1794\u17cb\u179f\u17d2\u179c\u17b6\u1799",
        "Phum T\u00e9ap Svay"
    ],
    "name:und_x_variant":[
        "Tep Svay",
        "Phum\u012d T\u00e9ap Svay",
        "Tep Svai",
        "Top Svai",
        "Phum\u012d To\u0103b Svay"
    ],
    "wof:name":"Toap Svay",
    "wof:placetype":"locality"
},
  "geometry": {"coordinates":[103.79394000000001,13.63247],"type":"Point"}
}