{
  "type": "Feature",
  "properties": {
    "gn:admin1_code":"24",
    "gn:asciiname":"Tram Kang",
    "gn:country_code":"KH",
    "gn:dem":16,
    "gn:feature_class":"P",
    "gn:feature_code":"PPL",
    "gn:name":"Tram Kang",
    "gn:population":0,
    "gn:timezone":"Asia/Phnom_Penh",
    "iso:country":"KH",
    "name:khm_x_preferred":[
        "Tram Kang"
    ],
    "name:khm_x_variant":[
        "\u1797\u17bc\u1798\u17b7 \u178f\u17d2\u179a\u17b6\u17c6\u1780\u1784",
        "Phum Tr\u0103mk\u00e2ng"
    ],
    "name:und_x_variant":[
        "Phum\u012d Tr\u0103mk\u00e2ng"
    ],
    "wof:name":"Tram Kang",
    "wof:placetype":"locality"
},
  "geometry": {"coordinates":[103.45983,13.58991],"type":"Point"}
}