{
  "type": "Feature",
  "properties": {
    "gn:admin1_code":"17",
    "gn:asciiname":"Phum O Kau",
    "gn:country_code":"KH",
    "gn:dem":239,
    "gn:feature_class":"P",
    "gn:feature_code":"PPL",
    "gn:name":"Phum O Kau",
    "gn:population":0,
    "gn:timezone":"Asia/Phnom_Penh",
    "iso:country":"KH",
    "name:khm_x_preferred":[
        "Phum O Kau"
    ],
    "name:khm_x_variant":[
        "\u1797\u17bc\u1798\u17b7 \u17a2\u17bc\u1780\u17c5"
    ],
    "wof:name":"Phum O Kau",
    "wof:placetype":"locality"
},
  "geometry": {"coordinates":[106.65452999999999,14.17952],"type":"Point"}
}