{
  "type": "Feature",
  "properties": {
    "gn:admin1_code":"04",
    "gn:asciiname":"Char Aok",
    "gn:country_code":"KH",
    "gn:dem":44,
    "gn:feature_class":"P",
    "gn:feature_code":"PPL",
    "gn:name":"Char Aok",
    "gn:population":0,
    "gn:timezone":"Asia/Phnom_Penh",
    "iso:country":"KH",
    "name:khm_x_preferred":[
        "Char Aok"
    ],
    "wof:name":"Char Aok",
    "wof:placetype":"locality"
},
  "geometry": {"coordinates":[104.63639000000001,11.6114],"type":"Point"}
}