{
  "type": "Feature",
  "properties": {
    "gn:admin1_code":"4.0",
    "gn:asciiname":"Phum Thmei",
    "gn:country_code":"KH",
    "gn:dem":107,
    "gn:feature_class":"P",
    "gn:feature_code":"PPL",
    "gn:name":"Phum Thmei",
    "gn:population":0,
    "gn:timezone":"Asia/Phnom_Penh",
    "iso:country":"KH",
    "name:khm_x_preferred":[
        "Phum Thmei"
    ],
    "name:khm_x_variant":[
        "\u1797\u17bc\u1798\u17b7 \u1790\u17d2\u1798\u17b8",
        "\u1783\u17bb\u17c6\u1797\u17bc\u1798\u17b7\u1790\u17d2\u1798\u17b8"
    ],
    "name:pol_x_preferred":[
        "Phum Thmei"
    ],
    "name:spa_x_preferred":[
        "Phum Thmei"
    ],
    "wof:name":"Phum Thmei",
    "wof:placetype":"locality"
},
  "geometry": {"coordinates":[104.17704999999999,11.1658],"type":"Point"}
}