{
  "type": "Feature",
  "properties": {
    "gn:admin1_code":"03",
    "gn:asciiname":"Ou",
    "gn:country_code":"KH",
    "gn:dem":14,
    "gn:feature_class":"P",
    "gn:feature_code":"PPL",
    "gn:name":"Ou",
    "gn:population":0,
    "gn:timezone":"Asia/Phnom_Penh",
    "iso:country":"KH",
    "name:ara_x_preferred":[
        "\u0623\u0648\u064a"
    ],
    "name:ben_x_preferred":[
        "\u0993\u0989"
    ],
    "name:deu_x_preferred":[
        "Ou"
    ],
    "name:ell_x_preferred":[
        "\u039f\u03c5"
    ],
    "name:fas_x_preferred":[
        "\u0627\u0648"
    ],
    "name:fra_x_preferred":[
        "Ou"
    ],
    "name:heb_x_preferred":[
        "\u05d0\u05d5"
    ],
    "name:hin_x_preferred":[
        "\u0913\u090a "
    ],
    "name:hun_x_preferred":[
        "Ou"
    ],
    "name:ind_x_preferred":[
        "Ou"
    ],
    "name:ita_x_preferred":[
        "Ou"
    ],
    "name:jpn_x_preferred":[
        "\u30aa\u30a6\u5ddd"
    ],
    "name:khm_x_preferred":[
        "Ou"
    ],
    "name:kor_x_preferred":[
        "\uc624\uc6b0"
    ],
    "name:nld_x_preferred":[
        "Ou"
    ],
    "name:pol_x_preferred":[
        "Ou"
    ],
    "name:por_x_preferred":[
        "Ou"
    ],
    "name:rus_x_preferred":[
        "\u0440\u0435\u043a\u0430 \u0423"
    ],
    "name:spa_x_preferred":[
        "Ou"
    ],
    "name:swe_x_preferred":[
        "Ou"
    ],
    "name:tur_x_preferred":[
        "Ou"
    ],
    "name:ukr_x_preferred":[
        "\u041e\u0443"
    ],
    "name:urd_x_preferred":[
        "\u0627\u0648"
    ],
    "name:vie_x_preferred":[
        "S\u00f4ng Ou"
    ],
    "name:zho_cn_x_preferred":[
        "\u74ef\u6c5f"
    ],
    "name:zho_tw_x_preferred":[
        "\u750c\u6c5f"
    ],
    "wof:name":"Ou",
    "wof:placetype":"locality"
},
  "geometry": {"coordinates":[104.76611,11.97357],"type":"Point"}
}