{
  "type": "Feature",
  "properties": {
    "gn:admin1_code":"25",
    "gn:asciiname":"Tuol Pongro",
    "gn:country_code":"KH",
    "gn:dem":57,
    "gn:feature_class":"P",
    "gn:feature_code":"PPL",
    "gn:name":"Tuol Pongro",
    "gn:population":0,
    "gn:timezone":"Asia/Phnom_Penh",
    "iso:country":"KH",
    "name:epo_x_preferred":[
        "Tuol Pongro"
    ],
    "name:khm_x_preferred":[
        "Tuol Pongro"
    ],
    "name:khm_x_variant":[
        "\u1783\u17bb\u17c6\u1791\u17bd\u179b\u1796\u1784\u17d2\u179a"
    ],
    "name:pol_x_preferred":[
        "Tuol Pongro"
    ],
    "name:spa_x_preferred":[
        "Tuol Pongro"
    ],
    "wof:name":"Tuol Pongro",
    "wof:placetype":"locality"
},
  "geometry": {"coordinates":[102.62144000000001,13.68724],"type":"Point"}
}