{
  "type": "Feature",
  "properties": {
    "gn:admin1_code":"29",
    "gn:asciiname":"Dangkao Kramang",
    "gn:country_code":"KH",
    "gn:dem":30,
    "gn:feature_class":"P",
    "gn:feature_code":"PPL",
    "gn:name":"Dangkao Kramang",
    "gn:population":0,
    "gn:timezone":"Asia/Phnom_Penh",
    "iso:country":"KH",
    "name:khm_x_preferred":[
        "Dangkao Kramang"
    ],
    "wof:name":"Dangkao Kramang",
    "wof:placetype":"locality"
},
  "geometry": {"coordinates":[102.82838,13.24769],"type":"Point"}
}