{
  "type": "Feature",
  "properties": {
    "gn:admin1_code":"18",
    "gn:asciiname":"Phumi Sva Lout",
    "gn:country_code":"KH",
    "gn:dem":10,
    "gn:feature_class":"P",
    "gn:feature_code":"PPL",
    "gn:name":"Phum\u012d Sva Lo\u016dt",
    "gn:population":0,
    "gn:timezone":"Asia/Phnom_Penh",
    "iso:country":"KH",
    "name:und_x_variant":[
        "Phum Sva Lot",
        "Phum\u012d Sva Lo\u016dt"
    ],
    "wof:name":"Phumi Sva Lout",
    "wof:placetype":"locality"
},
  "geometry": {"coordinates":[105.71132,11.50812],"type":"Point"}
}