{
  "type": "Feature",
  "properties": {
    "gn:admin1_code":"02",
    "gn:asciiname":"Khum Pram Yam",
    "gn:country_code":"KH",
    "gn:dem":17,
    "gn:feature_class":"P",
    "gn:feature_code":"PPL",
    "gn:name":"Kh\u016dm Pr\u0103m Yam",
    "gn:population":0,
    "gn:timezone":"Asia/Phnom_Penh",
    "iso:country":"KH",
    "name:und_x_variant":[
        "Phum Pram Yeam",
        "Pram Yeam",
        "Kh\u016dm Pr\u0103m Yam"
    ],
    "wof:name":"Khum Pram Yam",
    "wof:placetype":"locality"
},
  "geometry": {"coordinates":[105.15533000000001,11.79135],"type":"Point"}
}