{
  "type": "Feature",
  "properties": {
    "gn:admin1_code":"21",
    "gn:asciiname":"Phumi Mlur",
    "gn:country_code":"KH",
    "gn:dem":71,
    "gn:feature_class":"P",
    "gn:feature_code":"PPL",
    "gn:name":"Phum\u012d Mlur",
    "gn:population":0,
    "gn:timezone":"Asia/Phnom_Penh",
    "iso:country":"KH",
    "name:und_x_variant":[
        "Phum\u012d M\u00f4lu",
        "Phum\u012d Mlur"
    ],
    "wof:name":"Phumi Mlur",
    "wof:placetype":"locality"
},
  "geometry": {"coordinates":[104.42377999999999,11.03563],"type":"Point"}
}