{
  "type": "Feature",
  "properties": {
    "gn:admin1_code":"17.0",
    "gn:asciiname":"Ta Lat",
    "gn:country_code":"KH",
    "gn:dem":84,
    "gn:feature_class":"P",
    "gn:feature_code":"PPL",
    "gn:name":"Ta Lat",
    "gn:population":0,
    "gn:timezone":"Asia/Phnom_Penh",
    "iso:country":"KH",
    "name:khm_x_preferred":[
        "Ta Lat"
    ],
    "wof:name":"Ta Lat",
    "wof:placetype":"locality"
},
  "geometry": {"coordinates":[106.52688999999999,13.70748],"type":"Point"}
}