{
  "type": "Feature",
  "properties": {
    "gn:admin1_code":"04",
    "gn:asciiname":"Prey Norea",
    "gn:country_code":"KH",
    "gn:dem":43,
    "gn:feature_class":"P",
    "gn:feature_code":"PPL",
    "gn:name":"Prey Norea",
    "gn:population":0,
    "gn:timezone":"Asia/Phnom_Penh",
    "iso:country":"KH",
    "name:khm_x_preferred":[
        "Prey Norea"
    ],
    "wof:name":"Prey Norea",
    "wof:placetype":"locality"
},
  "geometry": {"coordinates":[104.51446,11.56201],"type":"Point"}
}