{
  "type": "Feature",
  "properties": {
    "gn:admin1_code":"10.0",
    "gn:asciiname":"Phum Pu Lok",
    "gn:country_code":"KH",
    "gn:dem":372,
    "gn:feature_class":"P",
    "gn:feature_code":"PPL",
    "gn:name":"Phum Pu L\u00f4k",
    "gn:population":0,
    "gn:timezone":"Asia/Phnom_Penh",
    "iso:country":"KH",
    "name:khm_x_preferred":[
        "Phum Pu L\u00f4k"
    ],
    "name:khm_x_variant":[
        "\u1797\u17bc\u1798\u17b7 \u1796\u17bc\u179b\u1780"
    ],
    "wof:name":"Phum Pu Lok",
    "wof:placetype":"locality"
},
  "geometry": {"coordinates":[107.25839999999999,12.66837],"type":"Point"}
}