{
  "type": "Feature",
  "properties": {
    "gn:admin1_code":"25",
    "gn:asciiname":"Tonloab",
    "gn:country_code":"KH",
    "gn:dem":17,
    "gn:feature_class":"P",
    "gn:feature_code":"PPL",
    "gn:name":"Tonloab",
    "gn:population":0,
    "gn:timezone":"Asia/Phnom_Penh",
    "iso:country":"KH",
    "name:khm_x_preferred":[
        "Tonloab"
    ],
    "name:khm_x_variant":[
        "Phum T\u00f4nl\u00e9ap"
    ],
    "wof:name":"Tonloab",
    "wof:placetype":"locality"
},
  "geometry": {"coordinates":[103.40597,13.51108],"type":"Point"}
}