{
  "type": "Feature",
  "properties": {
    "gn:admin1_code":"12",
    "gn:asciiname":"Phumi Kampong Kdong",
    "gn:cc2":"KH",
    "gn:country_code":"KH",
    "gn:dem":10,
    "gn:feature_class":"P",
    "gn:feature_code":"PPL",
    "gn:name":"Phum\u012d K\u00e2mp\u00f3ng Kd\u014fng",
    "gn:population":0,
    "gn:timezone":"Asia/Phnom_Penh",
    "iso:country":"KH",
    "name:und_x_variant":[
        "K\u014fmpong P\u2019t\u00f3ng",
        "Phum\u012d K\u00e2mp\u00f3ng Kd\u014fng"
    ],
    "wof:name":"Phumi Kampong Kdong",
    "wof:placetype":"locality"
},
  "geometry": {"coordinates":[104.84999999999999,12.48333],"type":"Point"}
}