{
  "type": "Feature",
  "properties": {
    "gn:admin1_code":"07",
    "gn:asciiname":"Kaoh Oknha Tei",
    "gn:country_code":"KH",
    "gn:dem":12,
    "gn:feature_class":"P",
    "gn:feature_code":"PPL",
    "gn:name":"Kaoh Oknha Tei",
    "gn:population":0,
    "gn:timezone":"Asia/Phnom_Penh",
    "iso:country":"KH",
    "name:khm_x_preferred":[
        "Kaoh Oknha Tei"
    ],
    "wof:name":"Kaoh Oknha Tei",
    "wof:placetype":"locality"
},
  "geometry": {"coordinates":[104.94318,11.6328],"type":"Point"}
}