{
  "type": "Feature",
  "properties": {
    "gn:admin1_code":"28",
    "gn:asciiname":"Phumi Toek Sab",
    "gn:country_code":"KH",
    "gn:dem":1,
    "gn:feature_class":"P",
    "gn:feature_code":"PPL",
    "gn:name":"Phum\u012d T\u0153\u0306k Sab",
    "gn:population":0,
    "gn:timezone":"Asia/Phnom_Penh",
    "iso:country":"KH",
    "name:und_x_variant":[
        "Phum\u012d T\u0153\u0306k Sap",
        "Phum\u012d T\u0153\u0306k Sab"
    ],
    "wof:name":"Phumi Toek Sab",
    "wof:placetype":"locality"
},
  "geometry": {"coordinates":[103.72792,10.53077],"type":"Point"}
}