{
  "type": "Feature",
  "properties": {
    "gn:admin1_code":"12",
    "gn:asciiname":"Phumi Pratranh",
    "gn:country_code":"KH",
    "gn:dem":16,
    "gn:feature_class":"P",
    "gn:feature_code":"PPL",
    "gn:name":"Phum\u012d Pr\u00e2tr\u0103nh",
    "gn:population":0,
    "gn:timezone":"Asia/Phnom_Penh",
    "iso:country":"KH",
    "name:und_x_variant":[
        "P\u2019um Ta Tranh",
        "Phum\u012d Pr\u00e2tr\u0103nh"
    ],
    "wof:name":"Phumi Pratranh",
    "wof:placetype":"locality"
},
  "geometry": {"coordinates":[103.64276,12.67959],"type":"Point"}
}