{
  "type": "Feature",
  "properties": {
    "gn:admin1_code":"12.0",
    "gn:asciiname":"Phum Yeay Moan",
    "gn:country_code":"KH",
    "gn:dem":18,
    "gn:feature_class":"P",
    "gn:feature_code":"PPL",
    "gn:name":"Phum Y\u00e9ay Mo\u00e2n",
    "gn:population":0,
    "gn:timezone":"Asia/Phnom_Penh",
    "iso:country":"KH",
    "name:khm_x_preferred":[
        "Phum Y\u00e9ay Mo\u00e2n"
    ],
    "name:khm_x_variant":[
        "\u1797\u17bc\u1798\u17b7 \u1799\u17b6\u1799\u1798\u17b6\u1793\u17cb"
    ],
    "wof:name":"Phum Yeay Moan",
    "wof:placetype":"locality"
},
  "geometry": {"coordinates":[103.90203,12.64849],"type":"Point"}
}