{
  "type": "Feature",
  "properties": {
    "gn:admin1_code":"18",
    "gn:asciiname":"Tuol Vihear",
    "gn:country_code":"KH",
    "gn:dem":14,
    "gn:feature_class":"P",
    "gn:feature_code":"PPL",
    "gn:name":"Tuol Vihear",
    "gn:population":0,
    "gn:timezone":"Asia/Phnom_Penh",
    "iso:country":"KH",
    "name:khm_x_preferred":[
        "Tuol Vihear"
    ],
    "name:khm_x_variant":[
        "Phum\u012d Prey B\u00e2nt\u00e9ay Pir",
        "\u1797\u17bc\u1798\u17b7 \u1796\u17d2\u179a\u17c3\u1794\u1793\u17d2\u1791\u17b6\u1799 \u1796\u17b8\u179a"
    ],
    "wof:name":"Tuol Vihear",
    "wof:placetype":"locality"
},
  "geometry": {"coordinates":[105.63602,11.25042],"type":"Point"}
}