{
  "type": "Feature",
  "properties": {
    "gn:admin1_code":"09",
    "gn:asciiname":"Phum Tnaot Chrum",
    "gn:country_code":"KH",
    "gn:dem":32,
    "gn:feature_class":"P",
    "gn:feature_code":"PPL",
    "gn:name":"Phum Tna\u00f4t Chr\u016dm",
    "gn:population":0,
    "gn:timezone":"Asia/Phnom_Penh",
    "iso:country":"KH",
    "name:khm_x_preferred":[
        "Phum Tna\u00f4t Chr\u016dm"
    ],
    "name:khm_x_variant":[
        "\u1797\u17bc\u1798\u17b7 \u178f\u17d2\u1793\u17c4\u178f\u1787\u17d2\u179a\u17bb\u17c6"
    ],
    "name:und_x_variant":[
        "Phum Trot Chrum"
    ],
    "wof:name":"Phum Tnaot Chrum",
    "wof:placetype":"locality"
},
  "geometry": {"coordinates":[106.00453,12.81533],"type":"Point"}
}