{
  "type": "Feature",
  "properties": {
    "gn:admin1_code":"02",
    "gn:asciiname":"Phumi Chong Kaoh Cheung",
    "gn:country_code":"KH",
    "gn:dem":19,
    "gn:feature_class":"P",
    "gn:feature_code":"PPL",
    "gn:name":"Phum\u012d Ch\u014fng Ka\u00f4h Cheung",
    "gn:population":0,
    "gn:timezone":"Asia/Phnom_Penh",
    "iso:country":"KH",
    "name:und_x_variant":[
        "Phum Chong Kas Sautin",
        "Phum\u012d Ch\u014fng Ka\u00f4h Cheung"
    ],
    "wof:name":"Phumi Chong Kaoh Cheung",
    "wof:placetype":"locality"
},
  "geometry": {"coordinates":[105.39751,11.91764],"type":"Point"}
}