{
  "type": "Feature",
  "properties": {
    "gn:admin1_code":"04",
    "gn:asciiname":"Roka Thum",
    "gn:country_code":"KH",
    "gn:dem":63,
    "gn:feature_class":"P",
    "gn:feature_code":"PPL",
    "gn:name":"Roka Thum",
    "gn:population":0,
    "gn:timezone":"Asia/Phnom_Penh",
    "iso:country":"KH",
    "name:khm_x_preferred":[
        "Roka Thum"
    ],
    "name:und_x_variant":[
        "Phum\u012d R\u00f4kar Thom",
        "Phum\u012d R\u00f4ka Thom",
        "Phum\u012d R\u00f4ka Thum"
    ],
    "wof:name":"Roka Thum",
    "wof:placetype":"locality"
},
  "geometry": {"coordinates":[104.44771,11.16819],"type":"Point"}
}