{
  "type": "Feature",
  "properties": {
    "gn:admin1_code":"25",
    "gn:asciiname":"Phumi Toek Reak",
    "gn:country_code":"KH",
    "gn:dem":11,
    "gn:feature_class":"P",
    "gn:feature_code":"PPL",
    "gn:name":"Phum\u012d T\u0153\u0306k R\u00e9ak",
    "gn:population":0,
    "gn:timezone":"Asia/Phnom_Penh",
    "iso:country":"KH",
    "name:khm_x_preferred":[
        "Phum\u012d T\u0153\u0306k R\u00e9ak"
    ],
    "name:khm_x_variant":[
        "\u1797\u17bc\u1798\u17b7\u1791\u17b9\u1780\u179a\u17b6\u1780\u17cb"
    ],
    "name:und_x_variant":[
        "Phum\u012d T\u0153\u0306k Re\u0103k"
    ],
    "wof:name":"Phumi Toek Reak",
    "wof:placetype":"locality"
},
  "geometry": {"coordinates":[103.25207,13.43097],"type":"Point"}
}