{
  "type": "Feature",
  "properties": {
    "gn:admin1_code":"09",
    "gn:asciiname":"Phum Sre Prang",
    "gn:country_code":"KH",
    "gn:dem":36,
    "gn:feature_class":"P",
    "gn:feature_code":"PPL",
    "gn:name":"Phum Sr\u00ea Pr\u0103ng",
    "gn:population":0,
    "gn:timezone":"Asia/Phnom_Penh",
    "iso:country":"KH",
    "name:khm_x_preferred":[
        "Phum Sr\u00ea Pr\u0103ng"
    ],
    "name:khm_x_variant":[
        "\u1797\u17bc\u1798\u17b7 \u179f\u17d2\u179a\u17c2\u1794\u17d2\u179a\u17b6\u17c6\u1784"
    ],
    "wof:name":"Phum Sre Prang",
    "wof:placetype":"locality"
},
  "geometry": {"coordinates":[106.07536,12.32241],"type":"Point"}
}