{
  "type": "Feature",
  "properties": {
    "gn:admin1_code":"18",
    "gn:asciiname":"Trapeang Thkov",
    "gn:country_code":"KH",
    "gn:dem":9,
    "gn:feature_class":"P",
    "gn:feature_code":"PPL",
    "gn:name":"Trapeang Thkov",
    "gn:population":0,
    "gn:timezone":"Asia/Phnom_Penh",
    "iso:country":"KH",
    "name:khm_x_preferred":[
        "Trapeang Thkov"
    ],
    "wof:name":"Trapeang Thkov",
    "wof:placetype":"locality"
},
  "geometry": {"coordinates":[105.89424,11.17821],"type":"Point"}
}