{
  "type": "Feature",
  "properties": {
    "gn:admin1_code":"09",
    "gn:asciiname":"Voat",
    "gn:country_code":"KH",
    "gn:dem":31,
    "gn:feature_class":"P",
    "gn:feature_code":"PPL",
    "gn:name":"Voat",
    "gn:population":0,
    "gn:timezone":"Asia/Phnom_Penh",
    "iso:country":"KH",
    "name:khm_x_preferred":[
        "Phum Ch\u014fng Ka\u00f4h Chr\u00eang"
    ],
    "name:khm_x_variant":[
        "Voat",
        "\u1797\u17bc\u1798\u17b7 \u1785\u17bb\u1784\u1780\u17c4\u17c7\u1785\u17d2\u179a\u17c2\u1784"
    ],
    "name:nor_x_preferred":[
        "Voat"
    ],
    "name:und_x_variant":[
        "Phum Kos Chreng"
    ],
    "name:zho_x_preferred":[
        "Voat"
    ],
    "wof:name":"Voat",
    "wof:placetype":"locality"
},
  "geometry": {"coordinates":[106.04445,12.36112],"type":"Point"}
}