{
  "type": "Feature",
  "properties": {
    "gn:admin1_code":"27",
    "gn:asciiname":"Tuek Chum",
    "gn:country_code":"KH",
    "gn:dem":60,
    "gn:feature_class":"P",
    "gn:feature_code":"PPL",
    "gn:name":"Tuek Chum",
    "gn:population":0,
    "gn:timezone":"Asia/Phnom_Penh",
    "iso:country":"KH",
    "name:khm_x_preferred":[
        "Tuek Chum"
    ],
    "wof:name":"Tuek Chum",
    "wof:placetype":"locality"
},
  "geometry": {"coordinates":[104.07723,14.25656],"type":"Point"}
}