{
  "type": "Feature",
  "properties": {
    "gn:admin1_code":"22",
    "gn:asciiname":"Phumi Lvea Leu",
    "gn:country_code":"KH",
    "gn:dem":12,
    "gn:feature_class":"P",
    "gn:feature_code":"PPL",
    "gn:name":"Phum\u012d Lv\u00e9a Leu",
    "gn:population":0,
    "gn:timezone":"Asia/Phnom_Penh",
    "iso:country":"KH",
    "name:und_x_variant":[
        "Lovea",
        "Phum\u012d L\u00f4v\u00e9a Leu",
        "Phum\u012d Lv\u00e9a Leu"
    ],
    "wof:name":"Phumi Lvea Leu",
    "wof:placetype":"locality"
},
  "geometry": {"coordinates":[104.93664,11.68804],"type":"Point"}
}