{
  "type": "Feature",
  "properties": {
    "gn:admin1_code":"24.0",
    "gn:asciiname":"Mukh Paen",
    "gn:country_code":"KH",
    "gn:dem":12,
    "gn:feature_class":"P",
    "gn:feature_code":"PPL",
    "gn:name":"Mukh Paen",
    "gn:population":0,
    "gn:timezone":"Asia/Phnom_Penh",
    "iso:country":"KH",
    "name:khm_x_preferred":[
        "Mukh Paen"
    ],
    "name:khm_x_variant":[
        "Phum Ko\u016dk R\u016dn",
        "\u1797\u17bc\u1798\u17b7 \u1780\u17c4\u1780\u179a\u17bb\u1793"
    ],
    "wof:name":"Mukh Paen",
    "wof:placetype":"locality"
},
  "geometry": {"coordinates":[103.59511999999999,13.47956],"type":"Point"}
}