{
  "type": "Feature",
  "properties": {
    "gn:admin1_code":"21",
    "gn:asciiname":"Voat Angk Khang Tboung",
    "gn:country_code":"KH",
    "gn:dem":11,
    "gn:feature_class":"P",
    "gn:feature_code":"PPL",
    "gn:name":"Voat Angk Khang Tboung",
    "gn:population":0,
    "gn:timezone":"Asia/Phnom_Penh",
    "iso:country":"KH",
    "name:khm_x_preferred":[
        "Voat Angk Khang Tboung"
    ],
    "wof:name":"Voat Angk Khang Tboung",
    "wof:placetype":"locality"
},
  "geometry": {"coordinates":[104.52964,10.72095],"type":"Point"}
}