{
  "type": "Feature",
  "properties": {
    "gn:admin1_code":"28",
    "gn:asciiname":"Phum Beng Knang",
    "gn:country_code":"KH",
    "gn:dem":1,
    "gn:feature_class":"P",
    "gn:feature_code":"PPL",
    "gn:name":"Phum Beng Knang",
    "gn:population":0,
    "gn:timezone":"Asia/Phnom_Penh",
    "iso:country":"KH",
    "name:khm_x_preferred":[
        "Phum B\u0153\u0306ng Knang"
    ],
    "name:khm_x_variant":[
        "\u1797\u17bc\u1798\u17b7 \u1794\u17b9\u1784\u1780\u17d2\u1793\u17b6\u1784"
    ],
    "wof:name":"Phum Beng Knang",
    "wof:placetype":"locality"
},
  "geometry": {"coordinates":[103.82443000000001,10.62197],"type":"Point"}
}