{
  "type": "Feature",
  "properties": {
    "gn:admin1_code":"07",
    "gn:asciiname":"Phumi Svay",
    "gn:country_code":"KH",
    "gn:dem":19,
    "gn:feature_class":"P",
    "gn:feature_code":"PPL",
    "gn:name":"Phum\u012d Svay",
    "gn:population":0,
    "gn:timezone":"Asia/Phnom_Penh",
    "iso:country":"KH",
    "name:und_x_variant":[
        "Vat Svay",
        "Phum\u012d Svay"
    ],
    "wof:name":"Phumi Svay",
    "wof:placetype":"locality"
},
  "geometry": {"coordinates":[104.83525,11.40793],"type":"Point"}
}