{
  "type": "Feature",
  "properties": {
    "gn:admin1_code":"05",
    "gn:asciiname":"Phumi Kampong Veang",
    "gn:country_code":"KH",
    "gn:dem":13,
    "gn:feature_class":"P",
    "gn:feature_code":"PPL",
    "gn:name":"Phum\u012d K\u00e2mp\u00f3ng Ve\u0103ng",
    "gn:population":0,
    "gn:timezone":"Asia/Phnom_Penh",
    "iso:country":"KH",
    "name:und_x_variant":[
        "Phum Kog Veang",
        "Phum\u012d K\u00e2mp\u00f3ng Ve\u0103ng"
    ],
    "wof:name":"Phumi Kampong Veang",
    "wof:placetype":"locality"
},
  "geometry": {"coordinates":[104.51102,13.03496],"type":"Point"}
}