{
  "type": "Feature",
  "properties": {
    "gn:admin1_code":"24",
    "gn:asciiname":"Ta Ni",
    "gn:country_code":"KH",
    "gn:dem":43,
    "gn:feature_class":"P",
    "gn:feature_code":"PPL",
    "gn:name":"Ta Ni",
    "gn:population":0,
    "gn:timezone":"Asia/Phnom_Penh",
    "iso:country":"KH",
    "name:khm_x_preferred":[
        "Ta Ni"
    ],
    "name:khm_x_variant":[
        "\u1797\u17bc\u1798\u17b7 \u178f\u17b6\u1793\u17b8",
        "Phum Tani"
    ],
    "name:und_x_variant":[
        "Phum\u012d Tani"
    ],
    "wof:name":"Ta Ni",
    "wof:placetype":"locality"
},
  "geometry": {"coordinates":[104.0149,13.47601],"type":"Point"}
}