{
  "type": "Feature",
  "properties": {
    "gn:admin1_code":"29",
    "gn:asciiname":"Phum Boeng Chhay Balang",
    "gn:country_code":"KH",
    "gn:dem":27,
    "gn:feature_class":"P",
    "gn:feature_code":"PPL",
    "gn:name":"Phum B\u0153\u0306ng Chhay Balang",
    "gn:population":0,
    "gn:timezone":"Asia/Phnom_Penh",
    "iso:country":"KH",
    "name:khm_x_preferred":[
        "Phum B\u0153\u0306ng Chhay Balang"
    ],
    "wof:name":"Phum Boeng Chhay Balang",
    "wof:placetype":"locality"
},
  "geometry": {"coordinates":[103.25292,12.87291],"type":"Point"}
}