{
  "type": "Feature",
  "properties": {
    "gn:admin1_code":"05",
    "gn:asciiname":"Phum Phat Sanday",
    "gn:country_code":"KH",
    "gn:dem":7,
    "gn:feature_class":"P",
    "gn:feature_code":"PPL",
    "gn:name":"Phum Phat S\u00e2nday",
    "gn:population":0,
    "gn:timezone":"Asia/Phnom_Penh",
    "iso:country":"KH",
    "name:khm_x_preferred":[
        "Phum Phat S\u00e2nday"
    ],
    "name:khm_x_variant":[
        "\u1797\u17bc\u1798\u17b7 \u1795\u17b6\u178f\u17cb\u179f\u1793\u17d2\u178f\u17b6\u1799"
    ],
    "name:und_x_variant":[
        "Phum\u012d Ph\u0103t S\u00e2nday (2)"
    ],
    "wof:name":"Phum Phat Sanday",
    "wof:placetype":"locality"
},
  "geometry": {"coordinates":[104.44611,12.53168],"type":"Point"}
}