{
  "type": "Feature",
  "properties": {
    "gn:admin1_code":"14.0",
    "gn:asciiname":"Phum Khleang",
    "gn:country_code":"KH",
    "gn:dem":9,
    "gn:feature_class":"P",
    "gn:feature_code":"PPL",
    "gn:name":"Phum Khle\u0103ng",
    "gn:population":0,
    "gn:timezone":"Asia/Phnom_Penh",
    "iso:country":"KH",
    "name:khm_x_preferred":[
        "Phum Khle\u0103ng"
    ],
    "name:khm_x_variant":[
        "\u1797\u17bc\u1798\u17b7 \u1783\u17d2\u179b\u17b6\u17c6\u1784"
    ],
    "wof:name":"Phum Khleang",
    "wof:placetype":"locality"
},
  "geometry": {"coordinates":[105.49630000000001,11.3498],"type":"Point"}
}