{
  "type": "Feature",
  "properties": {
    "gn:admin1_code":"31",
    "gn:asciiname":"Phumi Dambang Peak",
    "gn:country_code":"KH",
    "gn:dem":59,
    "gn:feature_class":"P",
    "gn:feature_code":"PPL",
    "gn:name":"Phum\u012d D\u00e2mb\u00e2ng Pe\u0103k",
    "gn:population":0,
    "gn:timezone":"Asia/Phnom_Penh",
    "iso:country":"KH",
    "wof:name":"Phumi Dambang Peak",
    "wof:placetype":"locality"
},
  "geometry": {"coordinates":[105.91473000000001,11.85277],"type":"Point"}
}