{
  "type": "Feature",
  "properties": {
    "gn:admin1_code":"31",
    "gn:asciiname":"Chrey",
    "gn:country_code":"KH",
    "gn:dem":77,
    "gn:feature_class":"P",
    "gn:feature_code":"PPL",
    "gn:name":"Chrey",
    "gn:population":0,
    "gn:timezone":"Asia/Phnom_Penh",
    "iso:country":"KH",
    "name:khm_x_preferred":[
        "Chrey"
    ],
    "name:khm_x_variant":[
        "\u1783\u17bb\u17c6\u1787\u17d2\u179a\u17c3"
    ],
    "name:spa_x_preferred":[
        "Chrey"
    ],
    "wof:name":"Chrey",
    "wof:placetype":"locality"
},
  "geometry": {"coordinates":[106.22902000000001,11.86904],"type":"Point"}
}