{
  "type": "Feature",
  "properties": {
    "gn:admin1_code":"29",
    "gn:asciiname":"Phum Chong Samnay",
    "gn:country_code":"KH",
    "gn:dem":19,
    "gn:feature_class":"P",
    "gn:feature_code":"PPL",
    "gn:name":"Phum Ch\u014fng S\u00e2mnay",
    "gn:population":0,
    "gn:timezone":"Asia/Phnom_Penh",
    "iso:country":"KH",
    "name:khm_x_preferred":[
        "Phum Ch\u014fng S\u00e2mnay"
    ],
    "name:khm_x_variant":[
        "\u1797\u17bc\u1798\u17b7 \u1785\u17bb\u1784\u179f\u17c6\u178e\u17b6\u1799"
    ],
    "wof:name":"Phum Chong Samnay",
    "wof:placetype":"locality"
},
  "geometry": {"coordinates":[103.45972999999999,12.77876],"type":"Point"}
}