{
  "type": "Feature",
  "properties": {
    "gn:admin1_code":"17",
    "gn:asciiname":"Phum Batok",
    "gn:country_code":"KH",
    "gn:dem":486,
    "gn:feature_class":"P",
    "gn:feature_code":"PPL",
    "gn:name":"Phum Bat\u014fk",
    "gn:population":0,
    "gn:timezone":"Asia/Phnom_Penh",
    "iso:country":"KH",
    "name:khm_x_preferred":[
        "Phum Bat\u014fk"
    ],
    "wof:name":"Phum Batok",
    "wof:placetype":"locality"
},
  "geometry": {"coordinates":[106.73577,14.2635],"type":"Point"}
}