{
  "type": "Feature",
  "properties": {
    "gn:admin1_code":"25",
    "gn:asciiname":"Kaoh Char",
    "gn:country_code":"KH",
    "gn:dem":22,
    "gn:feature_class":"P",
    "gn:feature_code":"PPL",
    "gn:name":"Kaoh Char",
    "gn:population":0,
    "gn:timezone":"Asia/Phnom_Penh",
    "iso:country":"KH",
    "name:khm_x_preferred":[
        "Kaoh Char"
    ],
    "wof:name":"Kaoh Char",
    "wof:placetype":"locality"
},
  "geometry": {"coordinates":[102.74487999999999,13.58138],"type":"Point"}
}