{
  "type": "Feature",
  "properties": {
    "gn:admin1_code":"17",
    "gn:asciiname":"Spong",
    "gn:country_code":"KH",
    "gn:dem":119,
    "gn:feature_class":"P",
    "gn:feature_code":"PPL",
    "gn:name":"Sp\u00f3ng",
    "gn:population":0,
    "gn:timezone":"Asia/Phnom_Penh",
    "iso:country":"KH",
    "name:deu_x_preferred":[
        "Spong"
    ],
    "name:fra_x_preferred":[
        "Spong"
    ],
    "name:isl_x_preferred":[
        "Sp\u00f6ng"
    ],
    "name:nld_x_preferred":[
        "Spong"
    ],
    "name:rus_x_preferred":[
        "\u0421\u043f\u043e\u043d\u0433"
    ],
    "name:swe_x_preferred":[
        "Spong"
    ],
    "name:und_x_variant":[
        "Phum\u012d Sp\u016dng",
        "Sp\u016dng",
        "Phum\u012d Spong",
        "Sp\u00f3ng"
    ],
    "wof:name":"Spong",
    "wof:placetype":"locality"
},
  "geometry": {"coordinates":[105.54582000000001,13.45368],"type":"Point"}
}