{
  "type": "Feature",
  "properties": {
    "gn:admin1_code":"04",
    "gn:asciiname":"Phumi Run",
    "gn:country_code":"KH",
    "gn:dem":30,
    "gn:feature_class":"P",
    "gn:feature_code":"PPL",
    "gn:name":"Phum\u012d R\u016dn",
    "gn:population":0,
    "gn:timezone":"Asia/Phnom_Penh",
    "iso:country":"KH",
    "name:und_x_variant":[
        "Pun",
        "Phum\u012d R\u016dn"
    ],
    "wof:name":"Phumi Run",
    "wof:placetype":"locality"
},
  "geometry": {"coordinates":[104.60961,11.46055],"type":"Point"}
}