{
  "type": "Feature",
  "properties": {
    "gn:admin1_code":"09",
    "gn:asciiname":"Phumi Sre Pring",
    "gn:country_code":"KH",
    "gn:dem":35,
    "gn:feature_class":"P",
    "gn:feature_code":"PPL",
    "gn:name":"Phum\u012d Sr\u00ea Pring",
    "gn:population":0,
    "gn:timezone":"Asia/Phnom_Penh",
    "iso:country":"KH",
    "name:khm_x_preferred":[
        "\u1797\u17bc\u1798\u17b7 \u179f\u17d2\u179a\u17c2\u1796\u17d2\u179a\u17b8\u1784"
    ],
    "name:und_x_variant":[
        "Sre Pring",
        "Phum\u012d Sr\u00ea Pring"
    ],
    "wof:name":"Phumi Sre Pring",
    "wof:placetype":"locality"
},
  "geometry": {"coordinates":[106.04688,12.59487],"type":"Point"}
}