{
  "type": "Feature",
  "properties": {
    "gn:admin1_code":"24",
    "gn:asciiname":"Phum Sre Veal",
    "gn:country_code":"KH",
    "gn:dem":65,
    "gn:feature_class":"P",
    "gn:feature_code":"PPL",
    "gn:name":"Phum Sr\u00ea V\u00e9al",
    "gn:population":0,
    "gn:timezone":"Asia/Phnom_Penh",
    "iso:country":"KH",
    "name:khm_x_preferred":[
        "Phum Sr\u00ea V\u00e9al"
    ],
    "name:khm_x_variant":[
        "\u1797\u17bc\u1798\u17b7 \u179f\u17d2\u179a\u17c2\u179c\u17b6\u179b"
    ],
    "name:und_x_variant":[
        "Phum\u012d Sr\u00ea V\u00e9al"
    ],
    "wof:name":"Phum Sre Veal",
    "wof:placetype":"locality"
},
  "geometry": {"coordinates":[104.28767999999999,13.54483],"type":"Point"}
}