{
  "type": "Feature",
  "properties": {
    "iso:country":"KH",
    "qs:gn_pop":0,
    "qs:name":"Pousat",
    "qs:name_adm0":"Cambodia",
    "qs:name_adm1":"Pouthisat",
    "qs:photos":114,
    "qs:photos_1k":23,
    "qs:photos_9k":1,
    "qs:photos_9r":3,
    "qs:photos_all":114,
    "qs:photos_sr":3,
    "qs:placetype":"Town",
    "qs:pop_sr":"0",
    "qs:woe_adm0":23424776,
    "wof:name":"Pousat",
    "wof:placetype":"locality"
},
  "geometry": {"coordinates":[103.924083,12.528786],"type":"Point"}
}