{
  "type": "Feature",
  "properties": {
    "gn:admin1_code":"03",
    "gn:asciiname":"Utumpor",
    "gn:country_code":"KH",
    "gn:dem":21,
    "gn:feature_class":"P",
    "gn:feature_code":"PPL",
    "gn:name":"Utumpor",
    "gn:population":0,
    "gn:timezone":"Asia/Phnom_Penh",
    "iso:country":"KH",
    "name:khm_x_preferred":[
        "Utumpor"
    ],
    "wof:name":"Utumpor",
    "wof:placetype":"locality"
},
  "geometry": {"coordinates":[104.59931,12.29836],"type":"Point"}
}