{
  "type": "Feature",
  "properties": {
    "gn:admin1_code":"14",
    "gn:asciiname":"Preaek Chrey",
    "gn:country_code":"KH",
    "gn:dem":10,
    "gn:feature_class":"P",
    "gn:feature_code":"PPL",
    "gn:name":"Preaek Chrey",
    "gn:population":0,
    "gn:timezone":"Asia/Phnom_Penh",
    "iso:country":"KH",
    "name:khm_x_preferred":[
        "Phum\u012d Anl\u016dng Tr\u00eaa"
    ],
    "name:khm_x_variant":[
        "Preaek Chrey",
        "\u1797\u17bc\u1798\u17b7 \u17a2\u1793\u17d2\u179b\u1784\u17cb\u1791\u17d2\u179a\u17b6"
    ],
    "name:und_x_variant":[
        "Phum\u012d \u00c2nl\u00f3ng Tr\u00e9a"
    ],
    "wof:name":"Preaek Chrey",
    "wof:placetype":"locality"
},
  "geometry": {"coordinates":[105.28386999999999,11.45491],"type":"Point"}
}