{
  "type": "Feature",
  "properties": {
    "gn:admin1_code":"05",
    "gn:asciiname":"Phumi Pring",
    "gn:country_code":"KH",
    "gn:dem":68,
    "gn:feature_class":"P",
    "gn:feature_code":"PPL",
    "gn:name":"Phum\u012d Pring",
    "gn:population":0,
    "gn:timezone":"Asia/Phnom_Penh",
    "iso:country":"KH",
    "name:und_x_variant":[
        "Pring",
        "Phum\u012d Pring"
    ],
    "wof:name":"Phumi Pring",
    "wof:placetype":"locality"
},
  "geometry": {"coordinates":[105.01552,13.40189],"type":"Point"}
}