{
  "type": "Feature",
  "properties": {
    "gn:admin1_code":"00",
    "gn:asciiname":"Phumi Kampong Lvea",
    "gn:country_code":"KH",
    "gn:dem":13,
    "gn:feature_class":"P",
    "gn:feature_code":"PPL",
    "gn:name":"Phum\u012d K\u00e2mp\u00f3ng Lv\u00e9a",
    "gn:population":0,
    "gn:timezone":"Asia/Phnom_Penh",
    "iso:country":"KH",
    "name:und_x_variant":[
        "Kompong Lovea",
        "Phum\u012d K\u00e2mp\u00f4ng L\u00f4v\u00e9a",
        "Phum\u012d K\u00e2mp\u00f3ng Lv\u00e9a"
    ],
    "wof:name":"Phumi Kampong Lvea",
    "wof:placetype":"locality"
},
  "geometry": {"coordinates":[105.12649,11.69004],"type":"Point"}
}