{
  "type": "Feature",
  "properties": {
    "gn:admin1_code":"04",
    "gn:asciiname":"Trapeang Phlong",
    "gn:country_code":"KH",
    "gn:dem":38,
    "gn:feature_class":"P",
    "gn:feature_code":"PPL",
    "gn:name":"Trapeang Phlong",
    "gn:population":0,
    "gn:timezone":"Asia/Phnom_Penh",
    "iso:country":"KH",
    "name:khm_x_preferred":[
        "Trapeang Phlong"
    ],
    "wof:name":"Trapeang Phlong",
    "wof:placetype":"locality"
},
  "geometry": {"coordinates":[104.61096000000001,11.18806],"type":"Point"}
}