{
  "type": "Feature",
  "properties": {
    "gn:admin1_code":"03",
    "gn:asciiname":"Phumi Sre Veal",
    "gn:country_code":"KH",
    "gn:dem":31,
    "gn:feature_class":"P",
    "gn:feature_code":"PPL",
    "gn:name":"Phum\u012d Sr\u00ea V\u00e9al",
    "gn:population":0,
    "gn:timezone":"Asia/Phnom_Penh",
    "iso:country":"KH",
    "wof:name":"Phumi Sre Veal",
    "wof:placetype":"locality"
},
  "geometry": {"coordinates":[104.54839,12.21447],"type":"Point"}
}