{
  "type": "Feature",
  "properties": {
    "gn:admin1_code":"24",
    "gn:asciiname":"Phum Tanat",
    "gn:country_code":"KH",
    "gn:dem":47,
    "gn:feature_class":"P",
    "gn:feature_code":"PPL",
    "gn:name":"Phum Tanat",
    "gn:population":0,
    "gn:timezone":"Asia/Phnom_Penh",
    "iso:country":"KH",
    "name:khm_x_preferred":[
        "Phum Tanat"
    ],
    "name:khm_x_variant":[
        "Phum\u012d Tanat"
    ],
    "wof:name":"Phum Tanat",
    "wof:placetype":"locality"
},
  "geometry": {"coordinates":[103.82357,13.84824],"type":"Point"}
}