{
  "type": "Feature",
  "properties": {
    "gn:admin1_code":"22",
    "gn:asciiname":"Ta Lei",
    "gn:country_code":"KH",
    "gn:dem":12,
    "gn:feature_class":"P",
    "gn:feature_code":"PPL",
    "gn:name":"Ta Lei",
    "gn:population":0,
    "gn:timezone":"Asia/Phnom_Penh",
    "iso:country":"KH",
    "name:khm_x_preferred":[
        "Ta Lei"
    ],
    "wof:name":"Ta Lei",
    "wof:placetype":"locality"
},
  "geometry": {"coordinates":[104.89109000000001,11.49823],"type":"Point"}
}