{
  "type": "Feature",
  "properties": {
    "gn:admin1_code":"18",
    "gn:asciiname":"Phumi Andong Pouthi",
    "gn:country_code":"KH",
    "gn:dem":10,
    "gn:feature_class":"P",
    "gn:feature_code":"PPL",
    "gn:name":"Phum\u012d \u00c2ndong Po\u016dth\u012d",
    "gn:population":0,
    "gn:timezone":"Asia/Phnom_Penh",
    "iso:country":"KH",
    "name:und_x_variant":[
        "Andaung Por",
        "Phum Andong Por",
        "Phum Andaung Por",
        "Phum Andaung Pau",
        "Phum\u012d Andong Po\u016d",
        "Phum\u012d \u00c2ndong Po\u016dth\u012d"
    ],
    "wof:name":"Phumi Andong Pouthi",
    "wof:placetype":"locality"
},
  "geometry": {"coordinates":[105.80812,11.35975],"type":"Point"}
}