{
  "type": "Feature",
  "properties": {
    "gn:admin1_code":"14",
    "gn:asciiname":"Phum Kampong Sne",
    "gn:country_code":"KH",
    "gn:dem":13,
    "gn:feature_class":"P",
    "gn:feature_code":"PPL",
    "gn:name":"Phum K\u00e2mp\u00f4ng Sn\u00ea",
    "gn:population":0,
    "gn:timezone":"Asia/Phnom_Penh",
    "iso:country":"KH",
    "name:khm_x_preferred":[
        "Phum K\u00e2mp\u00f4ng Sn\u00ea"
    ],
    "name:khm_x_variant":[
        "\u1797\u17bc\u1798\u17b7 \u1780\u17c6\u1796\u1784\u17cb\u179f\u17d2\u1793\u17c1\u17a0\u17cd"
    ],
    "name:und_x_variant":[
        "Phum Kompong Sner",
        "Phum\u012d K\u00e2mp\u00f4ng Sn\u00ea",
        "Phum\u012d K\u00e2mp\u00f3ng Sn\u00e9h"
    ],
    "wof:name":"Phum Kampong Sne",
    "wof:placetype":"locality"
},
  "geometry": {"coordinates":[105.39337999999999,11.37698],"type":"Point"}
}