{
  "type": "Feature",
  "properties": {
    "gn:admin1_code":"12.0",
    "gn:asciiname":"Phum Kaoh Prateal",
    "gn:country_code":"KH",
    "gn:dem":20,
    "gn:feature_class":"P",
    "gn:feature_code":"PPL",
    "gn:name":"Phum Ka\u014fh Pr\u00e2t\u00e9al",
    "gn:population":0,
    "gn:timezone":"Asia/Phnom_Penh",
    "iso:country":"KH",
    "name:khm_x_preferred":[
        "Phum Ka\u014fh Pr\u00e2t\u00e9al"
    ],
    "name:khm_x_variant":[
        "\u1797\u17bc\u1798\u17b7 \u1780\u17c4\u17c7\u1794\u17d2\u179a\u1791\u17b6\u179b"
    ],
    "wof:name":"Phum Kaoh Prateal",
    "wof:placetype":"locality"
},
  "geometry": {"coordinates":[103.94061000000001,12.61179],"type":"Point"}
}