{
  "type": "Feature",
  "properties": {
    "gn:admin1_code":"14",
    "gn:asciiname":"Phumi Trapeang Prei",
    "gn:country_code":"KH",
    "gn:dem":13,
    "gn:feature_class":"P",
    "gn:feature_code":"PPL",
    "gn:name":"Phum\u012d Tr\u00e2pe\u0103ng Prei",
    "gn:population":0,
    "gn:timezone":"Asia/Phnom_Penh",
    "iso:country":"KH",
    "name:und_x_variant":[
        "Phum Trap\u00e9ang Prey",
        "Phum\u012d Tr\u00e2pe\u0103ng Prei"
    ],
    "wof:name":"Phumi Trapeang Prei",
    "wof:placetype":"locality"
},
  "geometry": {"coordinates":[105.57761000000001,11.61962],"type":"Point"}
}