{
  "type": "Feature",
  "properties": {
    "gn:admin1_code":"7.0",
    "gn:asciiname":"Phum Kaoh Chen",
    "gn:country_code":"KH",
    "gn:dem":9,
    "gn:feature_class":"P",
    "gn:feature_code":"PPL",
    "gn:name":"Phum Ka\u00f4h Ch\u0115n",
    "gn:population":0,
    "gn:timezone":"Asia/Phnom_Penh",
    "iso:country":"KH",
    "name:khm_x_preferred":[
        "Phum Ka\u00f4h Ch\u0115n"
    ],
    "name:khm_x_variant":[
        "\u1797\u17bc\u1798\u17b7 \u1780\u17c4\u17c7\u1785\u17b7\u1793"
    ],
    "wof:name":"Phum Kaoh Chen",
    "wof:placetype":"locality"
},
  "geometry": {"coordinates":[105.00303999999998,11.45754],"type":"Point"}
}