{
  "type": "Feature",
  "properties": {
    "gn:admin1_code":"07",
    "gn:asciiname":"Phumi Roka Thum",
    "gn:country_code":"KH",
    "gn:dem":21,
    "gn:feature_class":"P",
    "gn:feature_code":"PPL",
    "gn:name":"Phum\u012d R\u00f4ka Thum",
    "gn:population":0,
    "gn:timezone":"Asia/Phnom_Penh",
    "iso:country":"KH",
    "name:und_x_variant":[
        "Roka Thom",
        "Phum\u012d R\u00f4ka Thom",
        "Phum\u012d R\u00f4ka Thum"
    ],
    "wof:name":"Phumi Roka Thum",
    "wof:placetype":"locality"
},
  "geometry": {"coordinates":[104.75542,11.49371],"type":"Point"}
}