{
  "type": "Feature",
  "properties": {
    "gn:admin1_code":"14",
    "gn:asciiname":"Snay Phleung",
    "gn:country_code":"KH",
    "gn:dem":15,
    "gn:feature_class":"P",
    "gn:feature_code":"PPL",
    "gn:name":"Snay Phleung",
    "gn:population":0,
    "gn:timezone":"Asia/Phnom_Penh",
    "iso:country":"KH",
    "name:khm_x_preferred":[
        "Snay Phleung"
    ],
    "name:und_x_variant":[
        "Phum Sn\u00e2\u00ef-Phlung",
        "Phum\u012d Svay Phleung"
    ],
    "wof:name":"Snay Phleung",
    "wof:placetype":"locality"
},
  "geometry": {"coordinates":[105.34746,11.68427],"type":"Point"}
}