{
  "type": "Feature",
  "properties": {
    "iso:country":"KH",
    "qs:gn_pop":0,
    "qs:name":"Phumi Ronean",
    "qs:name_adm0":"Cambodia",
    "qs:name_adm1":"Kampong Thum",
    "qs:photos":28,
    "qs:photos_1k":6,
    "qs:photos_9k":1,
    "qs:photos_9r":2,
    "qs:photos_all":28,
    "qs:photos_sr":2,
    "qs:placetype":"Town",
    "qs:pop_sr":"0",
    "qs:woe_adm0":23424776,
    "wof:name":"Phumi Ronean",
    "wof:placetype":"locality"
},
  "geometry": {"coordinates":[105.22117799999999,12.999898],"type":"Point"}
}