{
  "type": "Feature",
  "properties": {
    "gn:admin1_code":"13",
    "gn:asciiname":"Phumi Kouk",
    "gn:country_code":"KH",
    "gn:dem":79,
    "gn:feature_class":"P",
    "gn:feature_code":"PPL",
    "gn:name":"Phum\u012d Ko\u016dk",
    "gn:population":0,
    "gn:timezone":"Asia/Phnom_Penh",
    "iso:country":"KH",
    "wof:name":"Phumi Kouk",
    "wof:placetype":"locality"
},
  "geometry": {"coordinates":[104.93161000000001,14.19772],"type":"Point"}
}