{
  "type": "Feature",
  "properties": {
    "gn:admin1_code":"26",
    "gn:asciiname":"Phumi Prey Thum",
    "gn:country_code":"KH",
    "gn:dem":19,
    "gn:feature_class":"P",
    "gn:feature_code":"PPL",
    "gn:name":"Phum\u012d Prey Thum",
    "gn:population":0,
    "gn:timezone":"Asia/Phnom_Penh",
    "iso:country":"KH",
    "name:und_x_variant":[
        "Phum\u012d Prey Thom",
        "Phum\u012d Prey Thum"
    ],
    "wof:name":"Phumi Prey Thum",
    "wof:placetype":"locality"
},
  "geometry": {"coordinates":[104.30833,10.57123],"type":"Point"}
}