{
  "type": "Feature",
  "properties": {
    "gn:admin1_code":"07",
    "gn:asciiname":"Phum Anlung San",
    "gn:country_code":"KH",
    "gn:dem":8,
    "gn:feature_class":"P",
    "gn:feature_code":"PPL",
    "gn:name":"Phum \u00c2nl\u016dng San",
    "gn:population":0,
    "gn:timezone":"Asia/Phnom_Penh",
    "iso:country":"KH",
    "name:khm_x_preferred":[
        "Phum \u00c2nl\u016dng San"
    ],
    "name:khm_x_variant":[
        "\u1797\u17bc\u1798\u17b7 \u17a2\u1793\u17d2\u179b\u1784\u17cb\u179f\u17b6\u1793"
    ],
    "name:und_x_variant":[
        "Phum Kas Anlong San",
        "Phum\u012d \u00c2nl\u016dng San",
        "Phum\u012d \u00c2nl\u00f3ng San"
    ],
    "wof:name":"Phum Anlung San",
    "wof:placetype":"locality"
},
  "geometry": {"coordinates":[105.06588000000001,11.07628],"type":"Point"}
}