{
  "type": "Feature",
  "properties": {
    "gn:admin1_code":"09",
    "gn:asciiname":"Phumi Sre Andeng",
    "gn:country_code":"KH",
    "gn:dem":50,
    "gn:feature_class":"P",
    "gn:feature_code":"PPL",
    "gn:name":"Phum\u012d Sr\u00ea \u00c2nd\u00eang",
    "gn:population":0,
    "gn:timezone":"Asia/Phnom_Penh",
    "iso:country":"KH",
    "name:khm_x_preferred":[
        "Phum\u012d Sr\u00ea \u00c2nd\u00eang"
    ],
    "name:khm_x_variant":[
        "\u1797\u17bc\u1798\u17b7 \u179f\u17d2\u179a\u17c2\u17a2\u178e\u17d2\u178a\u17c2\u1784"
    ],
    "wof:name":"Phumi Sre Andeng",
    "wof:placetype":"locality"
},
  "geometry": {"coordinates":[106.23589,13.05662],"type":"Point"}
}