{
  "type": "Feature",
  "properties": {
    "gn:admin1_code":"25",
    "gn:asciiname":"Ta Mang",
    "gn:country_code":"KH",
    "gn:dem":65,
    "gn:feature_class":"P",
    "gn:feature_code":"PPL",
    "gn:name":"Ta Mang",
    "gn:population":0,
    "gn:timezone":"Asia/Bangkok",
    "iso:country":"KH",
    "name:khm_x_preferred":[
        "Ta Mang"
    ],
    "wof:name":"Ta Mang",
    "wof:placetype":"locality"
},
  "geometry": {"coordinates":[102.90418,14.06377],"type":"Point"}
}