{
  "type": "Feature",
  "properties": {
    "gn:admin1_code":"21",
    "gn:asciiname":"Phumi Sre Chriet",
    "gn:country_code":"KH",
    "gn:dem":45,
    "gn:feature_class":"P",
    "gn:feature_code":"PPL",
    "gn:name":"Phum\u012d Sr\u00ea Chri\u0115t",
    "gn:population":0,
    "gn:timezone":"Asia/Phnom_Penh",
    "iso:country":"KH",
    "wof:name":"Phumi Sre Chriet",
    "wof:placetype":"locality"
},
  "geometry": {"coordinates":[104.24744,10.97715],"type":"Point"}
}