{
  "type": "Feature",
  "properties": {
    "gn:admin1_code":"09",
    "gn:asciiname":"Phum Kamlek",
    "gn:country_code":"KH",
    "gn:dem":167,
    "gn:feature_class":"P",
    "gn:feature_code":"PPL",
    "gn:name":"Phum K\u00e2ml\u00eak",
    "gn:population":0,
    "gn:timezone":"Asia/Phnom_Penh",
    "iso:country":"KH",
    "name:khm_x_preferred":[
        "Phum K\u00e2ml\u00eak"
    ],
    "name:und_x_variant":[
        "Phum Camlaik"
    ],
    "wof:name":"Phum Kamlek",
    "wof:placetype":"locality"
},
  "geometry": {"coordinates":[106.42740000000001,12.05168],"type":"Point"}
}