{
  "type": "Feature",
  "properties": {
    "gn:admin1_code":"28",
    "gn:asciiname":"Phumi Ta Ong",
    "gn:country_code":"KH",
    "gn:dem":35,
    "gn:feature_class":"P",
    "gn:feature_code":"PPL",
    "gn:name":"Phum\u012d Ta \u014eng",
    "gn:population":0,
    "gn:timezone":"Asia/Phnom_Penh",
    "iso:country":"KH",
    "wof:name":"Phumi Ta Ong",
    "wof:placetype":"locality"
},
  "geometry": {"coordinates":[103.58437000000001,10.56708],"type":"Point"}
}