{
  "type": "Feature",
  "properties": {
    "gn:admin1_code":"29",
    "gn:asciiname":"Phum Kouk Trap",
    "gn:country_code":"KH",
    "gn:dem":16,
    "gn:feature_class":"P",
    "gn:feature_code":"PPL",
    "gn:name":"Phum Ko\u016dk Tr\u00e2p",
    "gn:population":0,
    "gn:timezone":"Asia/Phnom_Penh",
    "iso:country":"KH",
    "name:khm_x_preferred":[
        "Phum Ko\u016dk Tr\u00e2p"
    ],
    "name:khm_x_variant":[
        "\u1797\u17bc\u1798\u17b7 \u1782\u17c4\u1780\u178f\u17d2\u179a\u1794\u17cb"
    ],
    "wof:name":"Phum Kouk Trap",
    "wof:placetype":"locality"
},
  "geometry": {"coordinates":[103.09005000000001,13.27514],"type":"Point"}
}