{
  "type": "Feature",
  "properties": {
    "gn:admin1_code":"24",
    "gn:asciiname":"Phlong",
    "gn:country_code":"KH",
    "gn:dem":27,
    "gn:feature_class":"P",
    "gn:feature_code":"PPL",
    "gn:name":"Phlong",
    "gn:population":0,
    "gn:timezone":"Asia/Phnom_Penh",
    "iso:country":"KH",
    "name:khm_x_preferred":[
        "Phlong"
    ],
    "name:khm_x_variant":[
        "\u1797\u17bc\u1798\u17b7 \u1795\u17d2\u179b\u17bb\u1784",
        "Phum Phl\u014fng"
    ],
    "name:und_x_variant":[
        "Phum Trapeang Phlong",
        "Phum\u012d Phl\u014fng"
    ],
    "wof:name":"Phlong",
    "wof:placetype":"locality"
},
  "geometry": {"coordinates":[104.40348,13.1674],"type":"Point"}
}