{
  "type": "Feature",
  "properties": {
    "gn:admin1_code":"19",
    "gn:asciiname":"Phumi Tuol Svay",
    "gn:country_code":"KH",
    "gn:dem":6,
    "gn:feature_class":"P",
    "gn:feature_code":"PPL",
    "gn:name":"Phum\u012d Tu\u014fl Svay",
    "gn:population":0,
    "gn:timezone":"Asia/Phnom_Penh",
    "iso:country":"KH",
    "name:und_x_variant":[
        "Phum Trapeang Tuol Svai",
        "Phum\u012d Tu\u014fl Svay"
    ],
    "wof:name":"Phumi Tuol Svay",
    "wof:placetype":"locality"
},
  "geometry": {"coordinates":[104.85393000000001,10.68217],"type":"Point"}
}