{
  "type": "Feature",
  "properties": {
    "gn:admin1_code":"10",
    "gn:asciiname":"Phumi Pu Lngiem",
    "gn:country_code":"KH",
    "gn:dem":170,
    "gn:feature_class":"P",
    "gn:feature_code":"PPL",
    "gn:name":"Phum\u012d Pu Lngi\u0115m",
    "gn:population":0,
    "gn:timezone":"Asia/Phnom_Penh",
    "iso:country":"KH",
    "name:und_x_variant":[
        "Bu L\u2019Nghi\u00eam",
        "Phum\u012d Pu L\u2019Nghi\u0115m (2)",
        "Phum\u012d Pu Lngi\u0115m"
    ],
    "wof:name":"Phumi Pu Lngiem",
    "wof:placetype":"locality"
},
  "geometry": {"coordinates":[106.92079,12.08681],"type":"Point"}
}