{
  "type": "Feature",
  "properties": {
    "gn:admin1_code":"08",
    "gn:asciiname":"Thma Bang",
    "gn:country_code":"KH",
    "gn:dem":188,
    "gn:feature_class":"P",
    "gn:feature_code":"PPLA2",
    "gn:name":"Thma Bang",
    "gn:population":0,
    "gn:timezone":"Asia/Phnom_Penh",
    "iso:country":"KH",
    "name:khm_x_preferred":[
        "Thma Bang"
    ],
    "wof:name":"Thma Bang",
    "wof:placetype":"locality"
},
  "geometry": {"coordinates":[103.52958,11.62925],"type":"Point"}
}