{
  "type": "Feature",
  "properties": {
    "gn:admin1_code":"14",
    "gn:asciiname":"Phum Prek Phkoam",
    "gn:country_code":"KH",
    "gn:dem":12,
    "gn:feature_class":"P",
    "gn:feature_code":"PPL",
    "gn:name":"Phum Pr\u00eak Phk\u014f\u00e2m",
    "gn:population":0,
    "gn:timezone":"Asia/Phnom_Penh",
    "iso:country":"KH",
    "name:khm_x_preferred":[
        "Phum Pr\u00eak Phk\u014f\u00e2m"
    ],
    "name:khm_x_variant":[
        "\u1797\u17bc\u1798\u17b7 \u1796\u17d2\u179a\u17c2\u1780\u1795\u17d2\u1782\u17b6\u17c6"
    ],
    "name:und_x_variant":[
        "Phum Prek Phkam",
        "Phum\u012d Pr\u00eak Phk\u014f\u00e2m"
    ],
    "wof:name":"Phum Prek Phkoam",
    "wof:placetype":"locality"
},
  "geometry": {"coordinates":[105.21266,11.49596],"type":"Point"}
}