{
  "type": "Feature",
  "properties": {
    "gn:admin1_code":"13.0",
    "gn:asciiname":"Dan",
    "gn:country_code":"KH",
    "gn:dem":74,
    "gn:feature_class":"P",
    "gn:feature_code":"PPL",
    "gn:name":"Dan",
    "gn:population":0,
    "gn:timezone":"Asia/Phnom_Penh",
    "iso:country":"KH",
    "name:aze_x_preferred":[
        "Dan"
    ],
    "name:bre_x_preferred":[
        "Dan"
    ],
    "name:bul_x_preferred":[
        "\u0414\u0430\u043d"
    ],
    "name:cat_x_preferred":[
        "Dan"
    ],
    "name:ceb_x_preferred":[
        "Dan"
    ],
    "name:ces_x_preferred":[
        "Dan"
    ],
    "name:dan_x_preferred":[
        "Dan"
    ],
    "name:deu_x_preferred":[
        "Dan"
    ],
    "name:epo_x_preferred":[
        "Dan"
    ],
    "name:fin_x_preferred":[
        "Dan"
    ],
    "name:fra_x_preferred":[
        "Dan"
    ],
    "name:fry_x_preferred":[
        "Dan"
    ],
    "name:glg_x_preferred":[
        "Dan"
    ],
    "name:hrv_x_preferred":[
        "Dan"
    ],
    "name:ind_x_preferred":[
        "Dan"
    ],
    "name:isl_x_preferred":[
        "DAN"
    ],
    "name:khm_x_preferred":[
        "Dan"
    ],
    "name:nld_x_preferred":[
        "Dan"
    ],
    "name:nor_x_preferred":[
        "Dan"
    ],
    "name:pol_x_preferred":[
        "Dan"
    ],
    "name:por_x_preferred":[
        "Dan"
    ],
    "name:rus_x_preferred":[
        "\u0414\u0430\u043d"
    ],
    "name:slk_x_preferred":[
        "Dan"
    ],
    "name:slv_x_preferred":[
        "Dan"
    ],
    "name:spa_x_preferred":[
        "Dan"
    ],
    "name:srp_x_preferred":[
        "\u0414\u0430\u043d"
    ],
    "name:swe_x_preferred":[
        "Dan"
    ],
    "name:tur_x_preferred":[
        "Dan"
    ],
    "name:ukr_x_preferred":[
        "\u0414\u0435\u043d"
    ],
    "name:ukr_x_variant":[
        "\u0414\u0430\u043d"
    ],
    "name:urd_x_preferred":[
        "\u0688\u06cc\u0646"
    ],
    "name:vie_x_preferred":[
        "S\u00f4ng Dan"
    ],
    "name:zho_cn_x_preferred":[
        "\u4e39\u6cb3"
    ],
    "name:zho_tw_x_preferred":[
        "\u9054\u6069\u6cb3"
    ],
    "wof:name":"Dan",
    "wof:placetype":"locality"
},
  "geometry": {"coordinates":[104.74908000000001,13.81912],"type":"Point"}
}