{
  "type": "Feature",
  "properties": {
    "gn:admin1_code":"04",
    "gn:asciiname":"Dei Chhnang",
    "gn:country_code":"KH",
    "gn:dem":68,
    "gn:feature_class":"P",
    "gn:feature_code":"PPL",
    "gn:name":"Dei Chhnang",
    "gn:population":0,
    "gn:timezone":"Asia/Phnom_Penh",
    "iso:country":"KH",
    "name:khm_x_preferred":[
        "Dei Chhnang"
    ],
    "name:khm_x_variant":[
        "\u1797\u17bc\u1798\u17b7 \u178a\u17b8\u1786\u17d2\u1793\u17b6\u17c6\u1784",
        "Phum Dei Chhn\u0103ng"
    ],
    "name:und_x_variant":[
        "Dei Chnang",
        "Phum\u012d Dei Chhn\u0103ng"
    ],
    "wof:name":"Dei Chhnang",
    "wof:placetype":"locality"
},
  "geometry": {"coordinates":[104.23737,11.56405],"type":"Point"}
}