{
  "type": "Feature",
  "properties": {
    "gn:admin1_code":"24",
    "gn:asciiname":"Ou",
    "gn:country_code":"KH",
    "gn:dem":55,
    "gn:feature_class":"P",
    "gn:feature_code":"PPL",
    "gn:name":"Ou",
    "gn:population":0,
    "gn:timezone":"Asia/Phnom_Penh",
    "iso:country":"KH",
    "name:khm_x_preferred":[
        "Ou"
    ],
    "name:khm_x_variant":[
        "Phum\u012d O",
        "Phum O"
    ],
    "wof:name":"Ou",
    "wof:placetype":"locality"
},
  "geometry": {"coordinates":[103.75944,13.8014],"type":"Point"}
}