{
  "type": "Feature",
  "properties": {
    "gn:admin1_code":"24.0",
    "gn:asciiname":"Bos Thum",
    "gn:country_code":"KH",
    "gn:dem":21,
    "gn:feature_class":"P",
    "gn:feature_code":"PPL",
    "gn:name":"Bos Thum",
    "gn:population":0,
    "gn:timezone":"Asia/Phnom_Penh",
    "iso:country":"KH",
    "name:khm_x_preferred":[
        "Bos Thum"
    ],
    "name:khm_x_variant":[
        "\u1797\u17bc\u1798\u17b7 \u1794\u17c4\u179f\u1792\u17c6",
        "Phum Ba\u00f4s Thom"
    ],
    "wof:name":"Bos Thum",
    "wof:placetype":"locality"
},
  "geometry": {"coordinates":[103.50976,13.59672],"type":"Point"}
}