{
  "type": "Feature",
  "properties": {
    "gn:admin1_code":"04",
    "gn:asciiname":"Phumi Tang Moung",
    "gn:country_code":"KH",
    "gn:dem":50,
    "gn:feature_class":"P",
    "gn:feature_code":"PPL",
    "gn:name":"Phum\u012d T\u0103ng Mo\u016dng",
    "gn:population":0,
    "gn:timezone":"Asia/Phnom_Penh",
    "iso:country":"KH",
    "wof:name":"Phumi Tang Moung",
    "wof:placetype":"locality"
},
  "geometry": {"coordinates":[104.30136,11.49766],"type":"Point"}
}