{
  "type": "Feature",
  "properties": {
    "gn:admin1_code":"31",
    "gn:asciiname":"Phum Tuol Roka",
    "gn:country_code":"KH",
    "gn:dem":16,
    "gn:feature_class":"P",
    "gn:feature_code":"PPL",
    "gn:name":"Phum Tu\u014fl R\u00f4ka",
    "gn:population":0,
    "gn:timezone":"Asia/Phnom_Penh",
    "iso:country":"KH",
    "name:khm_x_preferred":[
        "Phum Tu\u014fl R\u00f4ka"
    ],
    "name:khm_x_variant":[
        "\u1797\u17bc\u1798\u17b7 \u1791\u17bd\u179b\u179a\u1780\u17b6\u179a"
    ],
    "name:und_x_variant":[
        "Phum Tuol Aka",
        "Phum\u012d Tu\u014fl R\u00f4ke",
        "Phum\u012d Tu\u014fl R\u00f4kar"
    ],
    "wof:name":"Phum Tuol Roka",
    "wof:placetype":"locality"
},
  "geometry": {"coordinates":[105.66267999999999,12.18789],"type":"Point"}
}