{
  "type": "Feature",
  "properties": {
    "gn:admin1_code":"21",
    "gn:asciiname":"Phumi Reu Samroas",
    "gn:country_code":"KH",
    "gn:dem":13,
    "gn:feature_class":"P",
    "gn:feature_code":"PPL",
    "gn:name":"Phum\u012d Reu S\u00e2mro\u0103s",
    "gn:population":0,
    "gn:timezone":"Asia/Phnom_Penh",
    "iso:country":"KH",
    "name:und_x_variant":[
        "Phum\u012d Reu S\u00e2mras",
        "Phum\u012d Reu S\u00e2mro\u0103s"
    ],
    "wof:name":"Phumi Reu Samroas",
    "wof:placetype":"locality"
},
  "geometry": {"coordinates":[104.26618999999999,10.64485],"type":"Point"}
}