{
  "type": "Feature",
  "properties": {
    "gn:admin1_code":"27",
    "gn:asciiname":"Tuol Prasaeur",
    "gn:country_code":"KH",
    "gn:dem":81,
    "gn:feature_class":"P",
    "gn:feature_code":"PPL",
    "gn:name":"Tuol Prasaeur",
    "gn:population":0,
    "gn:timezone":"Asia/Phnom_Penh",
    "iso:country":"KH",
    "name:khm_x_preferred":[
        "Tuol Prasaeur"
    ],
    "wof:name":"Tuol Prasaeur",
    "wof:placetype":"locality"
},
  "geometry": {"coordinates":[104.37909000000001,14.21482],"type":"Point"}
}