{
  "type": "Feature",
  "properties": {
    "gn:admin1_code":"29",
    "gn:asciiname":"Tras",
    "gn:country_code":"KH",
    "gn:dem":20,
    "gn:feature_class":"P",
    "gn:feature_code":"PPL",
    "gn:name":"Tras",
    "gn:population":0,
    "gn:timezone":"Asia/Phnom_Penh",
    "iso:country":"KH",
    "name:khm_x_preferred":[
        "Tras"
    ],
    "name:khm_x_variant":[
        "\u1797\u17bc\u1798\u17b7 \u178f\u17d2\u179a\u179f\u17cb",
        "Phum Tr\u00e2s"
    ],
    "name:und_x_variant":[
        "P\u2019um Tros",
        "Phum\u012d Tr\u00e1s"
    ],
    "wof:name":"Tras",
    "wof:placetype":"locality"
},
  "geometry": {"coordinates":[103.47266999999999,12.79276],"type":"Point"}
}