{
  "type": "Feature",
  "properties": {
    "gn:admin1_code":"4.0",
    "gn:asciiname":"Peam Ros",
    "gn:country_code":"KH",
    "gn:dem":67,
    "gn:feature_class":"P",
    "gn:feature_code":"PPL",
    "gn:name":"Peam Ros",
    "gn:population":0,
    "gn:timezone":"Asia/Phnom_Penh",
    "iso:country":"KH",
    "name:khm_x_preferred":[
        "Peam Ros"
    ],
    "wof:name":"Peam Ros",
    "wof:placetype":"locality"
},
  "geometry": {"coordinates":[104.17740000000001,11.59308],"type":"Point"}
}