{
  "type": "Feature",
  "properties": {
    "gn:admin1_code":"21",
    "gn:asciiname":"Khpob Run",
    "gn:country_code":"KH",
    "gn:dem":52,
    "gn:feature_class":"P",
    "gn:feature_code":"PPL",
    "gn:name":"Khpob Run",
    "gn:population":0,
    "gn:timezone":"Asia/Phnom_Penh",
    "iso:country":"KH",
    "name:khm_x_preferred":[
        "Khpob Run"
    ],
    "name:und_x_variant":[
        "Phum\u012d Khp\u00f4p R\u016dn",
        "Phum\u012d Khp\u00f4b R\u016dn"
    ],
    "wof:name":"Khpob Run",
    "wof:placetype":"locality"
},
  "geometry": {"coordinates":[104.47022,11.05028],"type":"Point"}
}