{
  "type": "Feature",
  "properties": {
    "gn:admin1_code":"08",
    "gn:asciiname":"Phum Kaoh Andong Sdach",
    "gn:country_code":"KH",
    "gn:dem":-19,
    "gn:feature_class":"P",
    "gn:feature_code":"PPL",
    "gn:name":"Phum Ka\u00f4h \u00c2ndong Sdach",
    "gn:population":0,
    "gn:timezone":"Asia/Phnom_Penh",
    "iso:country":"KH",
    "name:khm_x_preferred":[
        "Phum Ka\u00f4h \u00c2ndong Sdach"
    ],
    "name:khm_x_variant":[
        "\u1797\u17bc\u1798\u17b7 \u1780\u17c4\u17c7\u17a2\u178e\u17d2\u178a\u17bc\u1784\u179f\u17d2\u178a\u17c1\u1785"
    ],
    "name:und_x_variant":[
        "Phum\u012d Ka\u00f4h \u00c2ndong Sdach",
        "Phum\u012d Ka\u00f4h \u00c2ndong Sd\u00e9ch"
    ],
    "wof:name":"Phum Kaoh Andong Sdach",
    "wof:placetype":"locality"
},
  "geometry": {"coordinates":[103.0767,10.93697],"type":"Point"}
}