{
  "type": "Feature",
  "properties": {
    "gn:admin1_code":"31.0",
    "gn:asciiname":"Phum Tamtoe",
    "gn:country_code":"KH",
    "gn:dem":42,
    "gn:feature_class":"P",
    "gn:feature_code":"PPL",
    "gn:name":"Phum Tamt\u0153",
    "gn:population":0,
    "gn:timezone":"Asia/Phnom_Penh",
    "iso:country":"KH",
    "name:khm_x_preferred":[
        "Phum Tamt\u0153"
    ],
    "name:khm_x_variant":[
        "\u1797\u17bc\u1798\u17b7 \u178f\u17b6\u1798\u178f\u17b9"
    ],
    "wof:name":"Phum Tamtoe",
    "wof:placetype":"locality"
},
  "geometry": {"coordinates":[105.59339,12.00194],"type":"Point"}
}