{
  "type": "Feature",
  "properties": {
    "gn:admin1_code":"18",
    "gn:asciiname":"Prey Kokir",
    "gn:country_code":"KH",
    "gn:dem":6,
    "gn:feature_class":"P",
    "gn:feature_code":"PPL",
    "gn:name":"Prey Kokir",
    "gn:population":0,
    "gn:timezone":"Asia/Phnom_Penh",
    "iso:country":"KH",
    "name:khm_x_preferred":[
        "Phum Prey K\u00f4ki"
    ],
    "name:khm_x_variant":[
        "Prey Kokir",
        "\u1797\u17bc\u1798\u17b7 \u1796\u17d2\u179a\u17c3\u1782\u1782\u17b8\u179a"
    ],
    "name:und_x_variant":[
        "Khum Prey Ko Ki",
        "Koki",
        "Khum Prei Koki",
        "Phum\u012d Prey K\u00f4kir"
    ],
    "wof:name":"Prey Kokir",
    "wof:placetype":"locality"
},
  "geometry": {"coordinates":[106.06428,11.01333],"type":"Point"}
}