{
  "type": "Feature",
  "properties": {
    "gn:admin1_code":"22",
    "gn:asciiname":"Phumi Banla S'et",
    "gn:country_code":"KH",
    "gn:dem":13,
    "gn:feature_class":"P",
    "gn:feature_code":"PPL",
    "gn:name":"Phum\u012d B\u00e2nla S\u2019\u0115t",
    "gn:population":0,
    "gn:timezone":"Asia/Phnom_Penh",
    "iso:country":"KH",
    "name:und_x_variant":[
        "Tuol Cham\u00e9ang Akpaig",
        "Phum\u012d B\u00e2nta S\u00e2\u00e9t",
        "Phum\u012d B\u00e2nla S\u2019\u0115t"
    ],
    "wof:name":"Phumi Banla S'et",
    "wof:placetype":"locality"
},
  "geometry": {"coordinates":[104.86805,11.60711],"type":"Point"}
}