{
  "type": "Feature",
  "properties": {
    "gn:admin1_code":"24.0",
    "gn:asciiname":"Phum Kouk Kroeal",
    "gn:country_code":"KH",
    "gn:dem":16,
    "gn:feature_class":"P",
    "gn:feature_code":"PPL",
    "gn:name":"Phum Ko\u016dk Kroe\u0103l",
    "gn:population":0,
    "gn:timezone":"Asia/Phnom_Penh",
    "iso:country":"KH",
    "name:khm_x_preferred":[
        "Phum Ko\u016dk Kroe\u0103l"
    ],
    "name:khm_x_variant":[
        "\u1797\u17bc\u1798\u17b7 \u1782\u17c4\u1780\u1782\u17d2\u179a\u17c0\u179b"
    ],
    "wof:name":"Phum Kouk Kroeal",
    "wof:placetype":"locality"
},
  "geometry": {"coordinates":[103.7363,13.38424],"type":"Point"}
}