{
  "type": "Feature",
  "properties": {
    "gn:admin1_code":"02",
    "gn:asciiname":"Phum Muoy",
    "gn:country_code":"KH",
    "gn:dem":21,
    "gn:feature_class":"P",
    "gn:feature_code":"PPL",
    "gn:name":"Phum Muoy",
    "gn:population":0,
    "gn:timezone":"Asia/Phnom_Penh",
    "iso:country":"KH",
    "name:khm_x_preferred":[
        "Phum Muoy"
    ],
    "wof:name":"Phum Muoy",
    "wof:placetype":"locality"
},
  "geometry": {"coordinates":[105.45056,11.92487],"type":"Point"}
}