{
  "type": "Feature",
  "properties": {
    "gn:admin1_code":"19",
    "gn:asciiname":"Phumi O Rung",
    "gn:country_code":"KH",
    "gn:dem":10,
    "gn:feature_class":"P",
    "gn:feature_code":"PPL",
    "gn:name":"Phum\u012d O Rung",
    "gn:population":0,
    "gn:timezone":"Asia/Phnom_Penh",
    "iso:country":"KH",
    "name:und_x_variant":[
        "Kok Sl\u00eang",
        "Phum\u012d O Rung"
    ],
    "wof:name":"Phumi O Rung",
    "wof:placetype":"locality"
},
  "geometry": {"coordinates":[104.86347000000001,11.33217],"type":"Point"}
}