{
  "type": "Feature",
  "properties": {
    "gn:admin1_code":"05",
    "gn:asciiname":"Sandan",
    "gn:country_code":"KH",
    "gn:dem":24,
    "gn:feature_class":"P",
    "gn:feature_code":"PPLA2",
    "gn:name":"Sandan",
    "gn:population":0,
    "gn:timezone":"Asia/Phnom_Penh",
    "iso:country":"KH",
    "name:khm_x_preferred":[
        "Sandan"
    ],
    "wof:name":"Sandan",
    "wof:placetype":"locality"
},
  "geometry": {"coordinates":[105.25407,13.10459],"type":"Point"}
}