{
  "type": "Feature",
  "properties": {
    "gn:admin1_code":"05",
    "gn:asciiname":"Phlaoch",
    "gn:country_code":"KH",
    "gn:dem":22,
    "gn:feature_class":"P",
    "gn:feature_code":"PPL",
    "gn:name":"Phlaoch",
    "gn:population":0,
    "gn:timezone":"Asia/Phnom_Penh",
    "iso:country":"KH",
    "name:khm_x_preferred":[
        "Phlaoch"
    ],
    "name:und_x_variant":[
        "Phum\u012d Phloch"
    ],
    "wof:name":"Phlaoch",
    "wof:placetype":"locality"
},
  "geometry": {"coordinates":[104.67666,12.91155],"type":"Point"}
}