{
  "type": "Feature",
  "properties": {
    "gn:admin1_code":"04",
    "gn:asciiname":"Phum Chambak",
    "gn:country_code":"KH",
    "gn:dem":102,
    "gn:feature_class":"P",
    "gn:feature_code":"PPL",
    "gn:name":"Phum Ch\u00e2mb\u00e2k",
    "gn:population":0,
    "gn:timezone":"Asia/Phnom_Penh",
    "iso:country":"KH",
    "name:khm_x_preferred":[
        "Phum Ch\u00e2mb\u00e2k"
    ],
    "name:khm_x_variant":[
        "\u1797\u17bc\u1798\u17b7 \u1785\u17c6\u1794\u1780\u17cb"
    ],
    "name:und_x_variant":[
        "Phum\u012d Ch\u00e2mb\u00e1k"
    ],
    "wof:name":"Phum Chambak",
    "wof:placetype":"locality"
},
  "geometry": {"coordinates":[104.07167,11.77102],"type":"Point"}
}