{
  "type": "Feature",
  "properties": {
    "gn:admin1_code":"08",
    "gn:asciiname":"Ta Tai Kraom",
    "gn:country_code":"KH",
    "gn:dem":5,
    "gn:feature_class":"P",
    "gn:feature_code":"PPL",
    "gn:name":"Ta Tai Kraom",
    "gn:population":0,
    "gn:timezone":"Asia/Phnom_Penh",
    "iso:country":"KH",
    "name:khm_x_preferred":[
        "Ta Tai Kraom"
    ],
    "wof:name":"Ta Tai Kraom",
    "wof:placetype":"locality"
},
  "geometry": {"coordinates":[103.12882999999999,11.56861],"type":"Point"}
}