{
  "type": "Feature",
  "properties": {
    "gn:admin1_code":"05",
    "gn:asciiname":"Phumi Kampong Sdech",
    "gn:country_code":"KH",
    "gn:dem":29,
    "gn:feature_class":"P",
    "gn:feature_code":"PPL",
    "gn:name":"Phum\u012d K\u00e2mp\u00f3ng Sd\u00e9ch",
    "gn:population":0,
    "gn:timezone":"Asia/Phnom_Penh",
    "iso:country":"KH",
    "name:und_x_variant":[
        "Phum Kompong Sdach",
        "Phum\u012d K\u00e2mp\u00f4ng Sdach",
        "Phum\u012d K\u00e2mp\u00f3ng Sd\u00e9ch"
    ],
    "wof:name":"Phumi Kampong Sdech",
    "wof:placetype":"locality"
},
  "geometry": {"coordinates":[105.23712,12.52741],"type":"Point"}
}