{
  "type": "Feature",
  "properties": {
    "gn:admin1_code":"09",
    "gn:asciiname":"Phumi Sre Sdech",
    "gn:country_code":"KH",
    "gn:dem":32,
    "gn:feature_class":"P",
    "gn:feature_code":"PPL",
    "gn:name":"Phum\u012d Sr\u00ea Sd\u00e9ch",
    "gn:population":0,
    "gn:timezone":"Asia/Phnom_Penh",
    "iso:country":"KH",
    "name:und_x_variant":[
        "Phum Sre Sde",
        "Phum\u012d Sr\u00ea Sdach",
        "Phum\u012d Sr\u00ea Sd\u00e9ch"
    ],
    "wof:name":"Phumi Sre Sdech",
    "wof:placetype":"locality"
},
  "geometry": {"coordinates":[106.07666999999999,12.17602],"type":"Point"}
}