{
  "type": "Feature",
  "properties": {
    "gn:admin1_code":"29",
    "gn:asciiname":"Phumi Roessei Prey",
    "gn:country_code":"KH",
    "gn:dem":19,
    "gn:feature_class":"P",
    "gn:feature_code":"PPL",
    "gn:name":"Phum\u012d R\u0153ssei Prey",
    "gn:population":0,
    "gn:timezone":"Asia/Phnom_Penh",
    "iso:country":"KH",
    "name:und_x_variant":[
        "Phum\u012d R\u016dssei Prey",
        "Phum\u012d R\u0153ssei Prey"
    ],
    "wof:name":"Phumi Roessei Prey",
    "wof:placetype":"locality"
},
  "geometry": {"coordinates":[103.24876,12.96478],"type":"Point"}
}