{
  "type": "Feature",
  "properties": {
    "gn:admin1_code":"13",
    "gn:asciiname":"Pongro",
    "gn:country_code":"KH",
    "gn:dem":73,
    "gn:feature_class":"P",
    "gn:feature_code":"PPL",
    "gn:name":"Pongro",
    "gn:population":0,
    "gn:timezone":"Asia/Phnom_Penh",
    "iso:country":"KH",
    "name:khm_x_preferred":[
        "Pongro"
    ],
    "wof:name":"Pongro",
    "wof:placetype":"locality"
},
  "geometry": {"coordinates":[104.76541,13.82286],"type":"Point"}
}