{
  "type": "Feature",
  "properties": {
    "gn:admin1_code":"25",
    "gn:asciiname":"Anlong Thmei",
    "gn:country_code":"KH",
    "gn:dem":18,
    "gn:feature_class":"P",
    "gn:feature_code":"PPL",
    "gn:name":"Anlong Thmei",
    "gn:population":0,
    "gn:timezone":"Asia/Phnom_Penh",
    "iso:country":"KH",
    "name:khm_x_preferred":[
        "Anlong Thmei"
    ],
    "name:khm_x_variant":[
        "\u1797\u17bc\u1798\u17b7 \u17a2\u1793\u17d2\u179b\u1784\u1790\u17d2\u1798",
        "Phum Anl\u016dng Thm\u00e2"
    ],
    "name:und_x_variant":[
        "Anlong Thmar",
        "Phum\u012d Anl\u016dng Thm\u00e2",
        "Phum\u012d \u00c2nl\u00f3ng Thm\u00e2"
    ],
    "wof:name":"Anlong Thmei",
    "wof:placetype":"locality"
},
  "geometry": {"coordinates":[103.20263,13.63886],"type":"Point"}
}