{
  "type": "Feature",
  "properties": {
    "gn:admin1_code":"29",
    "gn:asciiname":"Pech Changvar",
    "gn:country_code":"KH",
    "gn:dem":63,
    "gn:feature_class":"P",
    "gn:feature_code":"PPL",
    "gn:name":"Pech Changvar",
    "gn:population":0,
    "gn:timezone":"Asia/Phnom_Penh",
    "iso:country":"KH",
    "name:khm_x_preferred":[
        "Pech Changvar"
    ],
    "wof:name":"Pech Changvar",
    "wof:placetype":"locality"
},
  "geometry": {"coordinates":[102.88357999999999,12.96982],"type":"Point"}
}