{
  "type": "Feature",
  "properties": {
    "gn:admin1_code":"03",
    "gn:asciiname":"Bos Meas",
    "gn:country_code":"KH",
    "gn:dem":21,
    "gn:feature_class":"P",
    "gn:feature_code":"PPL",
    "gn:name":"Bos Meas",
    "gn:population":0,
    "gn:timezone":"Asia/Phnom_Penh",
    "iso:country":"KH",
    "name:khm_x_preferred":[
        "Bos Meas"
    ],
    "name:khm_x_variant":[
        "\u1797\u17bc\u1798\u17b7 \u1794\u17bb\u179f\u1798\u17b6\u179f",
        "Phum B\u014fs M\u00e9as"
    ],
    "name:und_x_variant":[
        "Ph\u016bm Vear Meas",
        "Phum\u012d B\u014fs M\u00e9as"
    ],
    "wof:name":"Bos Meas",
    "wof:placetype":"locality"
},
  "geometry": {"coordinates":[104.43809,12.40571],"type":"Point"}
}