{
  "type": "Feature",
  "properties": {
    "gn:admin1_code":"05",
    "gn:asciiname":"Aachar Leak",
    "gn:country_code":"KH",
    "gn:dem":22,
    "gn:feature_class":"P",
    "gn:feature_code":"PPL",
    "gn:name":"Aachar Leak",
    "gn:population":0,
    "gn:timezone":"Asia/Phnom_Penh",
    "iso:country":"KH",
    "name:khm_x_preferred":[
        "Aachar Leak"
    ],
    "name:und_x_variant":[
        "Phum\u012d Achar Lerk",
        "Phum Achaleak",
        "Phum\u012d Achary Le\u0103k"
    ],
    "wof:name":"Aachar Leak",
    "wof:placetype":"locality"
},
  "geometry": {"coordinates":[104.89426,12.72553],"type":"Point"}
}