{
  "type": "Feature",
  "properties": {
    "gn:admin1_code":"31",
    "gn:asciiname":"Chi Trun",
    "gn:country_code":"KH",
    "gn:dem":28,
    "gn:feature_class":"P",
    "gn:feature_code":"PPL",
    "gn:name":"Chi Trun",
    "gn:population":0,
    "gn:timezone":"Asia/Phnom_Penh",
    "iso:country":"KH",
    "name:khm_x_preferred":[
        "Chi Trun"
    ],
    "name:khm_x_variant":[
        "\u1797\u17bc\u1798\u17b7 \u1787\u17b8\u1791\u17d2\u179a\u17bb\u1793",
        "Phum Chitr\u016dn"
    ],
    "name:und_x_variant":[
        "Phum Chitron",
        "Phum\u012d Chitr\u016dn"
    ],
    "wof:name":"Chi Trun",
    "wof:placetype":"locality"
},
  "geometry": {"coordinates":[105.96735,12.17152],"type":"Point"}
}