{
  "type": "Feature",
  "properties": {
    "gn:admin1_code":"03",
    "gn:asciiname":"Longveaek",
    "gn:country_code":"KH",
    "gn:dem":14,
    "gn:feature_class":"P",
    "gn:feature_code":"PPL",
    "gn:name":"Longveaek",
    "gn:population":0,
    "gn:timezone":"Asia/Phnom_Penh",
    "iso:country":"KH",
    "name:khm_x_preferred":[
        "Longveaek"
    ],
    "name:und_x_variant":[
        "Phum\u012d P\u00e9am L\u00f4v\u00eak",
        "Peam Lovek",
        "Lovek",
        "Khum P\u00e9am L\u00f4v\u00eak",
        "Longvek",
        "Kh\u016dm P\u00e9am Lv\u00eak"
    ],
    "wof:name":"Longveaek",
    "wof:placetype":"locality"
},
  "geometry": {"coordinates":[104.75424,11.8688],"type":"Point"}
}