{
  "type": "Feature",
  "properties": {
    "gn:admin1_code":"03",
    "gn:asciiname":"Longveaek",
    "gn:country_code":"KH",
    "gn:dem":14,
    "gn:feature_class":"P",
    "gn:feature_code":"PPL",
    "gn:name":"Longveaek",
    "gn:population":0,
    "gn:timezone":"Asia/Phnom_Penh",
    "iso:country":"KH",
    "name:fra_x_preferred":[
        "Lovek"
    ],
    "name:ita_x_preferred":[
        "Lovek"
    ],
    "name:khm_x_preferred":[
        "Longveaek"
    ],
    "name:khm_x_variant":[
        "\u179f\u1798\u17d0\u1799\u179b\u1784\u17d2\u179c\u17c2\u1780"
    ],
    "name:nor_x_preferred":[
        "Lovek"
    ],
    "name:oci_x_preferred":[
        "Lovek"
    ],
    "name:por_x_preferred":[
        "Lovek"
    ],
    "name:spa_x_preferred":[
        "Lovek"
    ],
    "name:tha_x_preferred":[
        "\u0e2a\u0e21\u0e31\u0e22\u0e25\u0e30\u0e41\u0e27\u0e01"
    ],
    "name:und_x_variant":[
        "Phum\u012d P\u00e9am L\u00f4v\u00eak",
        "Peam Lovek",
        "Lovek",
        "Khum P\u00e9am L\u00f4v\u00eak",
        "Longvek",
        "Kh\u016dm P\u00e9am Lv\u00eak"
    ],
    "name:vie_x_preferred":[
        "Longvek"
    ],
    "wof:name":"Longveaek",
    "wof:placetype":"locality"
},
  "geometry": {"coordinates":[104.75424,11.8688],"type":"Point"}
}