{
  "type": "Feature",
  "properties": {
    "gn:admin1_code":"25",
    "gn:asciiname":"Kouk Srok",
    "gn:country_code":"KH",
    "gn:dem":20,
    "gn:feature_class":"P",
    "gn:feature_code":"PPL",
    "gn:name":"Kouk Srok",
    "gn:population":0,
    "gn:timezone":"Asia/Phnom_Penh",
    "iso:country":"KH",
    "name:khm_x_preferred":[
        "Kouk Srok"
    ],
    "wof:name":"Kouk Srok",
    "wof:placetype":"locality"
},
  "geometry": {"coordinates":[103.15582999999999,13.57893],"type":"Point"}
}