{
  "type": "Feature",
  "properties": {
    "gn:admin1_code":"24.0",
    "gn:asciiname":"Ta Lien",
    "gn:country_code":"KH",
    "gn:dem":27,
    "gn:feature_class":"P",
    "gn:feature_code":"PPL",
    "gn:name":"Ta Lien",
    "gn:population":0,
    "gn:timezone":"Asia/Phnom_Penh",
    "iso:country":"KH",
    "name:khm_x_preferred":[
        "Ta Lien"
    ],
    "name:khm_x_variant":[
        "Phum Ta Li\u0115ng",
        "\u1797\u17bc\u1798\u17b7 \u178f\u17b6\u179b\u17c0\u1784"
    ],
    "wof:name":"Ta Lien",
    "wof:placetype":"locality"
},
  "geometry": {"coordinates":[104.36479,13.20923],"type":"Point"}
}