{
  "type": "Feature",
  "properties": {
    "gn:admin1_code":"04",
    "gn:asciiname":"Phumi Snaor",
    "gn:country_code":"KH",
    "gn:dem":36,
    "gn:feature_class":"P",
    "gn:feature_code":"PPL",
    "gn:name":"Phum\u012d Sna\u00f4r",
    "gn:population":0,
    "gn:timezone":"Asia/Phnom_Penh",
    "iso:country":"KH",
    "name:und_x_variant":[
        "Snor",
        "Phum\u012d Sna\u00f4r"
    ],
    "wof:name":"Phumi Snaor",
    "wof:placetype":"locality"
},
  "geometry": {"coordinates":[104.54913000000001,11.47768],"type":"Point"}
}