{
  "type": "Feature",
  "properties": {
    "gn:admin1_code":"31",
    "gn:asciiname":"Phumi Mream Teak",
    "gn:country_code":"KH",
    "gn:dem":23,
    "gn:feature_class":"P",
    "gn:feature_code":"PPL",
    "gn:name":"Phum\u012d Mr\u00e9am T\u00e9ak",
    "gn:population":0,
    "gn:timezone":"Asia/Phnom_Penh",
    "iso:country":"KH",
    "name:und_x_variant":[
        "Phum Maream Teak",
        "Moream Teak",
        "Phum\u012d Mr\u00e9am T\u00e9ak"
    ],
    "wof:name":"Phumi Mream Teak",
    "wof:placetype":"locality"
},
  "geometry": {"coordinates":[105.54058999999999,11.93617],"type":"Point"}
}