{
  "type": "Feature",
  "properties": {
    "gn:admin1_code":"19",
    "gn:asciiname":"Phumi Teahean Dom",
    "gn:country_code":"KH",
    "gn:dem":10,
    "gn:feature_class":"P",
    "gn:feature_code":"PPL",
    "gn:name":"Phum\u012d T\u00e9ah\u00e9an Dom",
    "gn:population":0,
    "gn:timezone":"Asia/Phnom_Penh",
    "iso:country":"KH",
    "wof:name":"Phumi Teahean Dom",
    "wof:placetype":"locality"
},
  "geometry": {"coordinates":[104.78158999999999,11.18333],"type":"Point"}
}