{
  "type": "Feature",
  "properties": {
    "gn:admin1_code":"3.0",
    "gn:asciiname":"Dangkhau Mau",
    "gn:country_code":"KH",
    "gn:dem":21,
    "gn:feature_class":"P",
    "gn:feature_code":"PPL",
    "gn:name":"Dangkhau Mau",
    "gn:population":0,
    "gn:timezone":"Asia/Phnom_Penh",
    "iso:country":"KH",
    "name:khm_x_preferred":[
        "Dangkhau Mau"
    ],
    "wof:name":"Dangkhau Mau",
    "wof:placetype":"locality"
},
  "geometry": {"coordinates":[104.43895000000001,12.46586],"type":"Point"}
}