{
  "type": "Feature",
  "properties": {
    "gn:admin1_code":"29",
    "gn:asciiname":"Phum Chhke Kham Praeus",
    "gn:country_code":"KH",
    "gn:dem":32,
    "gn:feature_class":"P",
    "gn:feature_code":"PPL",
    "gn:name":"Phum Chhk\u00ea Kh\u00e1m Praeus",
    "gn:population":0,
    "gn:timezone":"Asia/Phnom_Penh",
    "iso:country":"KH",
    "name:khm_x_preferred":[
        "Phum Chhk\u00ea Kh\u00e1m Praeus"
    ],
    "name:khm_x_variant":[
        "\u1797\u17bc\u1798\u17b7 \u1786\u17d2\u1780\u17c2\u1781\u17b6\u17c6\u1794\u17d2\u179a\u17be\u179f"
    ],
    "wof:name":"Phum Chhke Kham Praeus",
    "wof:placetype":"locality"
},
  "geometry": {"coordinates":[103.41155000000001,12.66065],"type":"Point"}
}