{
  "type": "Feature",
  "properties": {
    "gn:admin1_code":"05",
    "gn:asciiname":"Phumi O Kroch",
    "gn:country_code":"KH",
    "gn:dem":30,
    "gn:feature_class":"P",
    "gn:feature_code":"PPL",
    "gn:name":"Phum\u012d O Kroch",
    "gn:population":0,
    "gn:timezone":"Asia/Phnom_Penh",
    "iso:country":"KH",
    "name:und_x_variant":[
        "Spean Trach",
        "Spoan Trach",
        "Phum\u012d O Kroch"
    ],
    "wof:name":"Phumi O Kroch",
    "wof:placetype":"locality"
},
  "geometry": {"coordinates":[104.94911,12.98837],"type":"Point"}
}