{
  "type": "Feature",
  "properties": {
    "gn:admin1_code":"25",
    "gn:asciiname":"Kouk Ta Reach",
    "gn:country_code":"KH",
    "gn:dem":19,
    "gn:feature_class":"P",
    "gn:feature_code":"PPL",
    "gn:name":"Kouk Ta Reach",
    "gn:population":0,
    "gn:timezone":"Asia/Phnom_Penh",
    "iso:country":"KH",
    "name:khm_x_preferred":[
        "Kouk Ta Reach"
    ],
    "name:khm_x_variant":[
        "Phum Ka\u00f4h Tr\u00e9k",
        "\u1797\u17bc\u1798\u17b7 \u1780\u17c4\u17c7\u178f\u17d2\u179a\u17c1\u1780"
    ],
    "name:und_x_variant":[
        "Phum\u012d Ka\u00f4h Tr\u00e9k"
    ],
    "wof:name":"Kouk Ta Reach",
    "wof:placetype":"locality"
},
  "geometry": {"coordinates":[103.33422,13.72159],"type":"Point"}
}