{
  "type": "Feature",
  "properties": {
    "gn:admin1_code":"21",
    "gn:asciiname":"Phumi Prey Rumduol",
    "gn:country_code":"KH",
    "gn:dem":37,
    "gn:feature_class":"P",
    "gn:feature_code":"PPL",
    "gn:name":"Phum\u012d Prey Rumdu\u014fl",
    "gn:population":0,
    "gn:timezone":"Asia/Phnom_Penh",
    "iso:country":"KH",
    "wof:name":"Phumi Prey Rumduol",
    "wof:placetype":"locality"
},
  "geometry": {"coordinates":[104.35163,10.8223],"type":"Point"}
}