{
  "type": "Feature",
  "properties": {
    "gn:admin1_code":"04",
    "gn:asciiname":"Andoung",
    "gn:country_code":"KH",
    "gn:dem":34,
    "gn:feature_class":"P",
    "gn:feature_code":"PPL",
    "gn:name":"Andoung",
    "gn:population":0,
    "gn:timezone":"Asia/Phnom_Penh",
    "iso:country":"KH",
    "name:khm_x_preferred":[
        "Andoung"
    ],
    "name:und_x_variant":[
        "Anlong",
        "Phum\u012d \u00c2ndong"
    ],
    "wof:name":"Andoung",
    "wof:placetype":"locality"
},
  "geometry": {"coordinates":[104.61219,11.5419],"type":"Point"}
}