{
  "type": "Feature",
  "properties": {
    "gn:admin1_code":"10.0",
    "gn:asciiname":"Phum Leekh Pir",
    "gn:country_code":"KH",
    "gn:dem":725,
    "gn:feature_class":"P",
    "gn:feature_code":"PPL",
    "gn:name":"Phum Leekh Pir",
    "gn:population":0,
    "gn:timezone":"Asia/Phnom_Penh",
    "iso:country":"KH",
    "name:khm_x_preferred":[
        "Phum Leekh Pir"
    ],
    "wof:name":"Phum Leekh Pir",
    "wof:placetype":"locality"
},
  "geometry": {"coordinates":[107.46392,12.45788],"type":"Point"}
}