{
  "type": "Feature",
  "properties": {
    "gn:admin1_code":"10",
    "gn:asciiname":"Phumi Damansai",
    "gn:country_code":"KH",
    "gn:dem":289,
    "gn:feature_class":"P",
    "gn:feature_code":"PPL",
    "gn:name":"Phum\u012d Dam\u0103nsai",
    "gn:population":0,
    "gn:timezone":"Asia/Phnom_Penh",
    "iso:country":"KH",
    "wof:name":"Phumi Damansai",
    "wof:placetype":"locality"
},
  "geometry": {"coordinates":[106.97377,12.2542],"type":"Point"}
}