{
  "type": "Feature",
  "properties": {
    "gn:admin1_code":"29",
    "gn:asciiname":"Phum Sre Punlu",
    "gn:country_code":"KH",
    "gn:dem":137,
    "gn:feature_class":"P",
    "gn:feature_code":"PPL",
    "gn:name":"Phum Sre Punlu",
    "gn:population":0,
    "gn:timezone":"Asia/Phnom_Penh",
    "iso:country":"KH",
    "name:khm_x_preferred":[
        "Phum Sr\u00ea P\u00f4nl\u0153\u0306"
    ],
    "name:khm_x_variant":[
        "\u1797\u17bc\u1798\u17b7 \u179f\u17d2\u179a\u17c2\u1797\u1793\u17b9\u17d2\u179b\u179a"
    ],
    "name:und_x_variant":[
        "Sr\u00ea P\u00f4nl\u0153r"
    ],
    "wof:name":"Phum Sre Punlu",
    "wof:placetype":"locality"
},
  "geometry": {"coordinates":[102.75830999999999,12.70012],"type":"Point"}
}