{
  "type": "Feature",
  "properties": {
    "gn:admin1_code":"05",
    "gn:asciiname":"Phumi Koh Bareng",
    "gn:country_code":"KH",
    "gn:dem":12,
    "gn:feature_class":"P",
    "gn:feature_code":"PPL",
    "gn:name":"Phum\u012d K\u014fh Bar\u00eang",
    "gn:population":0,
    "gn:timezone":"Asia/Phnom_Penh",
    "iso:country":"KH",
    "name:und_x_variant":[
        "Phum\u012d Ka\u00f4h Bar\u00eang",
        "Phum\u012d K\u014fh Bar\u00eang"
    ],
    "wof:name":"Phumi Koh Bareng",
    "wof:placetype":"locality"
},
  "geometry": {"coordinates":[105.09039,12.28163],"type":"Point"}
}