{
  "type": "Feature",
  "properties": {
    "gn:admin1_code":"18",
    "gn:asciiname":"Andoung Khmat",
    "gn:country_code":"KH",
    "gn:dem":15,
    "gn:feature_class":"P",
    "gn:feature_code":"PPL",
    "gn:name":"Andoung Khmat",
    "gn:population":0,
    "gn:timezone":"Asia/Phnom_Penh",
    "iso:country":"KH",
    "name:khm_x_preferred":[
        "Andoung Khmat"
    ],
    "wof:name":"Andoung Khmat",
    "wof:placetype":"locality"
},
  "geometry": {"coordinates":[105.67896,11.49386],"type":"Point"}
}