{
  "type": "Feature",
  "properties": {
    "gn:admin1_code":"17",
    "gn:asciiname":"Preah Angkoal",
    "gn:country_code":"KH",
    "gn:dem":66,
    "gn:feature_class":"P",
    "gn:feature_code":"PPL",
    "gn:name":"Pre\u0103h \u00c2ngko\u0103l",
    "gn:population":0,
    "gn:timezone":"Asia/Phnom_Penh",
    "iso:country":"KH",
    "name:und_x_variant":[
        "Phum\u012d Pre\u0103h \u00c2ngkoal",
        "Preas Anaka",
        "Pala Kan",
        "Preas Angkal",
        "Palaken",
        "Pre\u0103h \u00c2ngke\u0103l",
        "Pre\u0103h \u00c2ngko\u0103l"
    ],
    "wof:name":"Preah Angkoal",
    "wof:placetype":"locality"
},
  "geometry": {"coordinates":[105.96373,13.89799],"type":"Point"}
}