{
  "type": "Feature",
  "properties": {
    "gn:admin1_code":"05",
    "gn:asciiname":"Ballangk",
    "gn:country_code":"KH",
    "gn:dem":17,
    "gn:feature_class":"P",
    "gn:feature_code":"PPL",
    "gn:name":"Ballangk",
    "gn:population":0,
    "gn:timezone":"Asia/Phnom_Penh",
    "iso:country":"KH",
    "name:khm_x_preferred":[
        "Ballangk"
    ],
    "wof:name":"Ballangk",
    "wof:placetype":"locality"
},
  "geometry": {"coordinates":[105.12647,12.49637],"type":"Point"}
}