{
  "type": "Feature",
  "properties": {
    "gn:admin1_code":"24.0",
    "gn:asciiname":"Thea Sna",
    "gn:country_code":"KH",
    "gn:dem":24,
    "gn:feature_class":"P",
    "gn:feature_code":"PPL",
    "gn:name":"Thea Sna",
    "gn:population":0,
    "gn:timezone":"Asia/Phnom_Penh",
    "iso:country":"KH",
    "name:khm_x_preferred":[
        "Thea Sna"
    ],
    "name:khm_x_variant":[
        "Phum Kma\u00f4ch",
        "\u1797\u17bc\u1798\u17b7 \u1781\u17d2\u1798\u17c4\u1785"
    ],
    "wof:name":"Thea Sna",
    "wof:placetype":"locality"
},
  "geometry": {"coordinates":[103.56977000000001,13.61498],"type":"Point"}
}