{
  "type": "Feature",
  "properties": {
    "gn:admin1_code":"02",
    "gn:asciiname":"Phumi Angk Chey",
    "gn:country_code":"KH",
    "gn:dem":18,
    "gn:feature_class":"P",
    "gn:feature_code":"PPL",
    "gn:name":"Phum\u012d \u00c2ngk Chey",
    "gn:population":0,
    "gn:timezone":"Asia/Phnom_Penh",
    "iso:country":"KH",
    "name:und_x_variant":[
        "Phum Angkor Chey",
        "Phum\u012d Ang Chey",
        "Phum\u012d \u00c2ngk Chey"
    ],
    "wof:name":"Phumi Angk Chey",
    "wof:placetype":"locality"
},
  "geometry": {"coordinates":[105.29301,11.92158],"type":"Point"}
}