{
  "type": "Feature",
  "properties": {
    "gn:admin1_code":"24",
    "gn:asciiname":"Phum Boeng",
    "gn:country_code":"KH",
    "gn:dem":19,
    "gn:feature_class":"P",
    "gn:feature_code":"PPL",
    "gn:name":"Phum B\u0153\u0306ng",
    "gn:population":0,
    "gn:timezone":"Asia/Phnom_Penh",
    "iso:country":"KH",
    "name:khm_x_preferred":[
        "Phum B\u0153\u0306ng"
    ],
    "name:khm_x_variant":[
        "\u1797\u17bc\u1798\u17b7 \u1794\u17b9\u1784"
    ],
    "name:und_x_variant":[
        "Phum\u012d B\u0153\u0306ng (1)"
    ],
    "wof:name":"Phum Boeng",
    "wof:placetype":"locality"
},
  "geometry": {"coordinates":[103.85997999999999,13.32482],"type":"Point"}
}