{
  "type": "Feature",
  "properties": {
    "gn:admin1_code":"04",
    "gn:asciiname":"Phumi Krang Thum",
    "gn:country_code":"KH",
    "gn:dem":61,
    "gn:feature_class":"P",
    "gn:feature_code":"PPL",
    "gn:name":"Phum\u012d Kr\u0103ng Thum",
    "gn:population":0,
    "gn:timezone":"Asia/Phnom_Penh",
    "iso:country":"KH",
    "name:und_x_variant":[
        "Phum\u012d Kr\u0103ng Thom",
        "Phum\u012d Kr\u0103ng Thum"
    ],
    "wof:name":"Phumi Krang Thum",
    "wof:placetype":"locality"
},
  "geometry": {"coordinates":[104.24118,11.41742],"type":"Point"}
}