{
  "type": "Feature",
  "properties": {
    "gn:admin1_code":"05",
    "gn:asciiname":"Phumi Tang Krasau",
    "gn:country_code":"KH",
    "gn:dem":24,
    "gn:feature_class":"P",
    "gn:feature_code":"PPL",
    "gn:name":"Phum\u012d T\u0103ng Kr\u00e2sau",
    "gn:population":0,
    "gn:timezone":"Asia/Phnom_Penh",
    "iso:country":"KH",
    "name:und_x_variant":[
        "Tang Krasau",
        "Phum\u012d T\u0103ng Kr\u00e2sau"
    ],
    "wof:name":"Phumi Tang Krasau",
    "wof:placetype":"locality"
},
  "geometry": {"coordinates":[105.10214000000001,12.82521],"type":"Point"}
}