{
  "type": "Feature",
  "properties": {
    "gn:admin1_code":"29",
    "gn:asciiname":"Voat Kantueu",
    "gn:country_code":"KH",
    "gn:dem":26,
    "gn:feature_class":"P",
    "gn:feature_code":"PPL",
    "gn:name":"Voat Kantueu",
    "gn:population":0,
    "gn:timezone":"Asia/Phnom_Penh",
    "iso:country":"KH",
    "name:khm_x_preferred":[
        "Voat Kantueu"
    ],
    "wof:name":"Voat Kantueu",
    "wof:placetype":"locality"
},
  "geometry": {"coordinates":[103.14834,12.91486],"type":"Point"}
}