{
  "type": "Feature",
  "properties": {
    "gn:admin1_code":"02",
    "gn:asciiname":"Phumi Svay Meas",
    "gn:country_code":"KH",
    "gn:dem":122,
    "gn:feature_class":"P",
    "gn:feature_code":"PPL",
    "gn:name":"Phum\u012d Svay M\u00e9as",
    "gn:population":0,
    "gn:timezone":"Asia/Phnom_Penh",
    "iso:country":"KH",
    "name:und_x_variant":[
        "Phum Svai Meas",
        "Phum\u012d Svay M\u00e9as"
    ],
    "wof:name":"Phumi Svay Meas",
    "wof:placetype":"locality"
},
  "geometry": {"coordinates":[105.30455000000001,12.22273],"type":"Point"}
}