{
  "type": "Feature",
  "properties": {
    "gn:admin1_code":"05",
    "gn:asciiname":"Phumi Ta Paong",
    "gn:country_code":"KH",
    "gn:dem":18,
    "gn:feature_class":"P",
    "gn:feature_code":"PPL",
    "gn:name":"Phum\u012d Ta Pa\u00f4ng",
    "gn:population":0,
    "gn:timezone":"Asia/Phnom_Penh",
    "iso:country":"KH",
    "name:und_x_variant":[
        "Tabong",
        "Phum\u012d Ta Pa\u00f4ng"
    ],
    "wof:name":"Phumi Ta Paong",
    "wof:placetype":"locality"
},
  "geometry": {"coordinates":[105.01501,12.77789],"type":"Point"}
}