{
  "type": "Feature",
  "properties": {
    "gn:admin1_code":"12.0",
    "gn:asciiname":"Phum Syar Leu",
    "gn:country_code":"KH",
    "gn:dem":23,
    "gn:feature_class":"P",
    "gn:feature_code":"PPL",
    "gn:name":"Phum Syar Leu",
    "gn:population":0,
    "gn:timezone":"Asia/Phnom_Penh",
    "iso:country":"KH",
    "name:khm_x_preferred":[
        "Phum Syar Leu"
    ],
    "name:khm_x_variant":[
        "\u1797\u17bc\u1798\u17b7 \u179f\u17d2\u1799\u17b6\u179b\u17be"
    ],
    "wof:name":"Phum Syar Leu",
    "wof:placetype":"locality"
},
  "geometry": {"coordinates":[103.96935999999999,12.61361],"type":"Point"}
}