{
  "type": "Feature",
  "properties": {
    "gn:admin1_code":"08",
    "gn:asciiname":"Phumi Prek Pikar (1)",
    "gn:cc2":"KH",
    "gn:country_code":"KH",
    "gn:dem":4,
    "gn:feature_class":"P",
    "gn:feature_code":"PPL",
    "gn:name":"Phum\u012d Pr\u00eak Pikar (1)",
    "gn:population":0,
    "gn:timezone":"Asia/Phnom_Penh",
    "iso:country":"KH",
    "name:und_x_variant":[
        "Phum Pr\u00eak Pikar",
        "Phum\u012d Pr\u00eak Pikar (1)"
    ],
    "wof:name":"Phumi Prek Pikar (1)",
    "wof:placetype":"locality"
},
  "geometry": {"coordinates":[102.94056,11.66667],"type":"Point"}
}