{
  "type": "Feature",
  "properties": {
    "gn:admin1_code":"21",
    "gn:asciiname":"Phumi Tuol Kakaoh",
    "gn:country_code":"KH",
    "gn:dem":9,
    "gn:feature_class":"P",
    "gn:feature_code":"PPL",
    "gn:name":"Phum\u012d Tu\u014fl K\u00e2ka\u00f4h",
    "gn:population":0,
    "gn:timezone":"Asia/Phnom_Penh",
    "iso:country":"KH",
    "name:und_x_variant":[
        "Phum\u012d Tu\u014fl Kak\u00e2os",
        "Phum\u012d Tu\u014fl K\u00e2ka\u00f4h"
    ],
    "wof:name":"Phumi Tuol Kakaoh",
    "wof:placetype":"locality"
},
  "geometry": {"coordinates":[104.15663000000001,10.58437],"type":"Point"}
}