{
  "type": "Feature",
  "properties": {
    "gn:admin1_code":"03",
    "gn:asciiname":"Phumi Hong Tnaot",
    "gn:country_code":"KH",
    "gn:dem":52,
    "gn:feature_class":"P",
    "gn:feature_code":"PPL",
    "gn:name":"Phum\u012d H\u014fng Tna\u00f4t",
    "gn:population":0,
    "gn:timezone":"Asia/Phnom_Penh",
    "iso:country":"KH",
    "name:und_x_variant":[
        "Hong Thnot",
        "Phum\u012d H\u014fng Thna\u00f4t",
        "Phum\u012d H\u014fng Tna\u00f4t"
    ],
    "wof:name":"Phumi Hong Tnaot",
    "wof:placetype":"locality"
},
  "geometry": {"coordinates":[104.52906,11.77925],"type":"Point"}
}