{
  "type": "Feature",
  "properties": {
    "gn:admin1_code":"18",
    "gn:asciiname":"Phumi Traok",
    "gn:country_code":"KH",
    "gn:dem":8,
    "gn:feature_class":"P",
    "gn:feature_code":"PPL",
    "gn:name":"Phum\u012d Tra\u00f4k",
    "gn:population":0,
    "gn:timezone":"Asia/Phnom_Penh",
    "iso:country":"KH",
    "name:und_x_variant":[
        "Phum Trok",
        "Phum\u012d Tra\u00f4k"
    ],
    "wof:name":"Phumi Traok",
    "wof:placetype":"locality"
},
  "geometry": {"coordinates":[105.73545,11.05754],"type":"Point"}
}