{
  "type": "Feature",
  "properties": {
    "gn:admin1_code":"29",
    "gn:asciiname":"Chisang",
    "gn:country_code":"KH",
    "gn:dem":71,
    "gn:feature_class":"P",
    "gn:feature_code":"PPL",
    "gn:name":"Chisang",
    "gn:population":0,
    "gn:timezone":"Asia/Phnom_Penh",
    "iso:country":"KH",
    "name:khm_x_preferred":[
        "\u1787\u17b8\u179f\u17b6\u1784"
    ],
    "name:und_x_variant":[
        "Phum\u012d Chisang",
        "Khum Chisang",
        "Chisang"
    ],
    "wof:name":"Chisang",
    "wof:placetype":"locality"
},
  "geometry": {"coordinates":[102.83761,12.85052],"type":"Point"}
}