{
  "type": "Feature",
  "properties": {
    "gn:admin1_code":"08",
    "gn:asciiname":"Ta Ni",
    "gn:country_code":"KH",
    "gn:dem":9,
    "gn:feature_class":"P",
    "gn:feature_code":"PPL",
    "gn:name":"Ta Ni",
    "gn:population":0,
    "gn:timezone":"Asia/Phnom_Penh",
    "iso:country":"KH",
    "name:khm_x_preferred":[
        "Ta Ni"
    ],
    "name:und_x_variant":[
        "Ang",
        "Taney",
        "Phum\u012d Tanei"
    ],
    "wof:name":"Ta Ni",
    "wof:placetype":"locality"
},
  "geometry": {"coordinates":[103.12551000000001,11.11454],"type":"Point"}
}