{
  "type": "Feature",
  "properties": {
    "gn:admin1_code":"18",
    "gn:asciiname":"Phumi Preah Teyyea",
    "gn:country_code":"KH",
    "gn:dem":4,
    "gn:feature_class":"P",
    "gn:feature_code":"PPL",
    "gn:name":"Phum\u012d Pre\u0103h Teyy\u00e9a",
    "gn:population":0,
    "gn:timezone":"Asia/Phnom_Penh",
    "iso:country":"KH",
    "name:und_x_variant":[
        "Phum Kompong Prean Tyea",
        "Phum\u012d Pre\u0103h Teyy\u00e9a"
    ],
    "wof:name":"Phumi Preah Teyyea",
    "wof:placetype":"locality"
},
  "geometry": {"coordinates":[105.75117,11.17137],"type":"Point"}
}