{
  "type": "Feature",
  "properties": {
    "gn:admin1_code":"08",
    "gn:asciiname":"Kandaol",
    "gn:country_code":"KH",
    "gn:dem":22,
    "gn:feature_class":"P",
    "gn:feature_code":"PPL",
    "gn:name":"Kandaol",
    "gn:population":0,
    "gn:timezone":"Asia/Phnom_Penh",
    "iso:country":"KH",
    "name:khm_x_preferred":[
        "Kandaol"
    ],
    "name:und_x_variant":[
        "Phum\u012d K\u00e2nda\u00f4l"
    ],
    "wof:name":"Kandaol",
    "wof:placetype":"locality"
},
  "geometry": {"coordinates":[103.55473000000001,11.19345],"type":"Point"}
}