{
  "type": "Feature",
  "properties": {
    "gn:admin1_code":"24",
    "gn:asciiname":"Pongro Chas",
    "gn:country_code":"KH",
    "gn:dem":21,
    "gn:feature_class":"P",
    "gn:feature_code":"PPL",
    "gn:name":"Pongro Chas",
    "gn:population":0,
    "gn:timezone":"Asia/Phnom_Penh",
    "iso:country":"KH",
    "name:khm_x_preferred":[
        "Pongro Chas"
    ],
    "name:khm_x_variant":[
        "Phum\u012d P\u00f4ngr\u00f4",
        "\u1797\u17bc\u1798\u17b7 \u1796\u1784\u17d2\u179a"
    ],
    "name:und_x_variant":[
        "Phum\u012d P\u00f4ngr\u00f4 (1)"
    ],
    "wof:name":"Pongro Chas",
    "wof:placetype":"locality"
},
  "geometry": {"coordinates":[103.6217,13.5205],"type":"Point"}
}