{
  "type": "Feature",
  "properties": {
    "gn:admin1_code":"29",
    "gn:asciiname":"Phumi Ta Moas",
    "gn:country_code":"KH",
    "gn:dem":7,
    "gn:feature_class":"P",
    "gn:feature_code":"PPL",
    "gn:name":"Phum\u012d Ta Mo\u0103s",
    "gn:population":0,
    "gn:timezone":"Asia/Phnom_Penh",
    "iso:country":"KH",
    "name:und_x_variant":[
        "P\u2019um Bak Sn\u00e2r",
        "Phum\u012d Ta Mo\u0103s"
    ],
    "wof:name":"Phumi Ta Moas",
    "wof:placetype":"locality"
},
  "geometry": {"coordinates":[103.67614,12.93788],"type":"Point"}
}