{
  "type": "Feature",
  "properties": {
    "gn:admin1_code":"02",
    "gn:asciiname":"Phumi Prey Nhear",
    "gn:country_code":"KH",
    "gn:dem":22,
    "gn:feature_class":"P",
    "gn:feature_code":"PPL",
    "gn:name":"Phum\u012d Prey Nh\u00e9ar",
    "gn:population":0,
    "gn:timezone":"Asia/Phnom_Penh",
    "iso:country":"KH",
    "name:und_x_variant":[
        "Prey Nhea",
        "Phum\u012d Prey Nh\u00e9ar"
    ],
    "wof:name":"Phumi Prey Nhear",
    "wof:placetype":"locality"
},
  "geometry": {"coordinates":[104.96355,12.03717],"type":"Point"}
}