{
  "type": "Feature",
  "properties": {
    "gn:admin1_code":"05",
    "gn:asciiname":"Phumi Sampor",
    "gn:country_code":"KH",
    "gn:dem":15,
    "gn:feature_class":"P",
    "gn:feature_code":"PPL",
    "gn:name":"Phum\u012d S\u00e2mp\u00f4r",
    "gn:population":0,
    "gn:timezone":"Asia/Phnom_Penh",
    "iso:country":"KH",
    "name:und_x_variant":[
        "Sampoar",
        "Sampor",
        "Phum\u012d S\u00e2mp\u00f4r"
    ],
    "wof:name":"Phumi Sampor",
    "wof:placetype":"locality"
},
  "geometry": {"coordinates":[104.60875,12.8851],"type":"Point"}
}