{
  "type": "Feature",
  "properties": {
    "gn:admin1_code":"14.0",
    "gn:asciiname":"Kampong Leav",
    "gn:country_code":"KH",
    "gn:dem":9,
    "gn:feature_class":"P",
    "gn:feature_code":"PPLA2",
    "gn:name":"Kampong Leav",
    "gn:population":0,
    "gn:timezone":"Asia/Phnom_Penh",
    "iso:country":"KH",
    "name:khm_x_preferred":[
        "Kampong Leav"
    ],
    "wof:name":"Kampong Leav",
    "wof:placetype":"locality"
},
  "geometry": {"coordinates":[105.34318,11.49308],"type":"Point"}
}