{
  "type": "Feature",
  "properties": {
    "gn:admin1_code":"29",
    "gn:asciiname":"Phum Tuol Thngan",
    "gn:country_code":"KH",
    "gn:dem":13,
    "gn:feature_class":"P",
    "gn:feature_code":"PPL",
    "gn:name":"Phum Tu\u014fl Thngan",
    "gn:population":0,
    "gn:timezone":"Asia/Phnom_Penh",
    "iso:country":"KH",
    "name:khm_x_preferred":[
        "Phum Tu\u014fl Thngan"
    ],
    "name:khm_x_variant":[
        "\u1797\u17bc\u1798\u17b7 \u1791\u17bd\u179b\u1790\u17d2\u1784\u17b6\u1793\u17cb"
    ],
    "wof:name":"Phum Tuol Thngan",
    "wof:placetype":"locality"
},
  "geometry": {"coordinates":[103.4314,12.88688],"type":"Point"}
}