{
  "type": "Feature",
  "properties": {
    "gn:admin1_code":"07",
    "gn:asciiname":"Phumik Prek Ongpang",
    "gn:country_code":"KH",
    "gn:dem":10,
    "gn:feature_class":"P",
    "gn:feature_code":"PPL",
    "gn:name":"Phum\u012dk Pr\u00eak \u014engpang",
    "gn:population":0,
    "gn:timezone":"Asia/Phnom_Penh",
    "iso:country":"KH",
    "name:und_x_variant":[
        "Phum Prek Ta Ting",
        "Phum\u012dk Pr\u00eak \u014engpang"
    ],
    "wof:name":"Phumik Prek Ongpang",
    "wof:placetype":"locality"
},
  "geometry": {"coordinates":[104.98994,11.3026],"type":"Point"}
}