{
  "type": "Feature",
  "properties": {
    "gn:admin1_code":"03",
    "gn:asciiname":"Phumi Kouk Banteay",
    "gn:country_code":"KH",
    "gn:dem":25,
    "gn:feature_class":"P",
    "gn:feature_code":"PPL",
    "gn:name":"Phum\u012d Ko\u016dk B\u00e2nt\u00e9ay",
    "gn:population":0,
    "gn:timezone":"Asia/Phnom_Penh",
    "iso:country":"KH",
    "name:und_x_variant":[
        "Kou Banteay",
        "Phum\u012d Ko\u016dk B\u00e2nt\u00e9ay"
    ],
    "wof:name":"Phumi Kouk Banteay",
    "wof:placetype":"locality"
},
  "geometry": {"coordinates":[104.68147999999999,12.18519],"type":"Point"}
}