{
  "type": "Feature",
  "properties": {
    "gn:admin1_code":"21",
    "gn:asciiname":"Samraong Leu",
    "gn:country_code":"KH",
    "gn:dem":14,
    "gn:feature_class":"P",
    "gn:feature_code":"PPL",
    "gn:name":"Samraong Leu",
    "gn:population":0,
    "gn:timezone":"Asia/Phnom_Penh",
    "iso:country":"KH",
    "name:khm_x_preferred":[
        "Samraong Leu"
    ],
    "wof:name":"Samraong Leu",
    "wof:placetype":"locality"
},
  "geometry": {"coordinates":[104.59116,10.72828],"type":"Point"}
}