{
  "type": "Feature",
  "properties": {
    "gn:admin1_code":"24",
    "gn:asciiname":"Phum Moat Peam",
    "gn:country_code":"KH",
    "gn:dem":9,
    "gn:feature_class":"P",
    "gn:feature_code":"PPL",
    "gn:name":"Phum Mo\u00e2t P\u00e9am",
    "gn:population":0,
    "gn:timezone":"Asia/Phnom_Penh",
    "iso:country":"KH",
    "name:khm_x_preferred":[
        "Phum Mo\u00e2t P\u00e9am"
    ],
    "name:khm_x_variant":[
        "\u1797\u17bc\u1798\u17b7 \u1798\u17b6\u178f\u17cb\u1796\u17b6\u1798"
    ],
    "name:und_x_variant":[
        "Phum\u012d Mo\u0103t P\u00e9am"
    ],
    "wof:name":"Phum Moat Peam",
    "wof:placetype":"locality"
},
  "geometry": {"coordinates":[103.82492999999999,13.24018],"type":"Point"}
}