{
  "type": "Feature",
  "properties": {
    "gn:admin1_code":"02",
    "gn:asciiname":"Phumi Slaket",
    "gn:country_code":"KH",
    "gn:dem":27,
    "gn:feature_class":"P",
    "gn:feature_code":"PPL",
    "gn:name":"Phum\u012d Slak\u00eat",
    "gn:population":0,
    "gn:timezone":"Asia/Phnom_Penh",
    "iso:country":"KH",
    "wof:name":"Phumi Slaket",
    "wof:placetype":"locality"
},
  "geometry": {"coordinates":[105.01511000000001,12.04763],"type":"Point"}
}