{
  "type": "Feature",
  "properties": {
    "gn:admin1_code":"12.0",
    "gn:asciiname":"Phum Anlung Svay",
    "gn:country_code":"KH",
    "gn:dem":23,
    "gn:feature_class":"P",
    "gn:feature_code":"PPL",
    "gn:name":"Phum Anl\u016dng Svay",
    "gn:population":0,
    "gn:timezone":"Asia/Phnom_Penh",
    "iso:country":"KH",
    "name:khm_x_preferred":[
        "Phum Anl\u016dng Svay"
    ],
    "name:khm_x_variant":[
        "\u1797\u17bc\u1798\u17b7 \u17a2\u1793\u17d2\u179b\u1784\u17cb\u179f\u17d2\u179c\u17b6\u1799"
    ],
    "wof:name":"Phum Anlung Svay",
    "wof:placetype":"locality"
},
  "geometry": {"coordinates":[103.90358999999999,12.50857],"type":"Point"}
}