{
  "type": "Feature",
  "properties": {
    "gn:admin1_code":"07",
    "gn:asciiname":"Samraong Kandal",
    "gn:country_code":"KH",
    "gn:dem":9,
    "gn:feature_class":"P",
    "gn:feature_code":"PPL",
    "gn:name":"Samraong Kandal",
    "gn:population":0,
    "gn:timezone":"Asia/Phnom_Penh",
    "iso:country":"KH",
    "name:khm_x_preferred":[
        "Samraong Kandal"
    ],
    "wof:name":"Samraong Kandal",
    "wof:placetype":"locality"
},
  "geometry": {"coordinates":[104.83745999999999,11.68513],"type":"Point"}
}