{
  "type": "Feature",
  "properties": {
    "gn:admin1_code":"05",
    "gn:asciiname":"Phumi Pralay",
    "gn:country_code":"KH",
    "gn:dem":18,
    "gn:feature_class":"P",
    "gn:feature_code":"PPL",
    "gn:name":"Phum\u012d Pr\u00e2lay",
    "gn:population":0,
    "gn:timezone":"Asia/Phnom_Penh",
    "iso:country":"KH",
    "name:und_x_variant":[
        "Pralay",
        "Phum\u012d Pr\u00e2lay"
    ],
    "wof:name":"Phumi Pralay",
    "wof:placetype":"locality"
},
  "geometry": {"coordinates":[105.04318000000001,12.79766],"type":"Point"}
}