{
  "type": "Feature",
  "properties": {
    "gn:admin1_code":"17",
    "gn:asciiname":"Phum Kiribas Kraom",
    "gn:country_code":"KH",
    "gn:dem":255,
    "gn:feature_class":"P",
    "gn:feature_code":"PPL",
    "gn:name":"Phum Kiribas Kra\u00f4m",
    "gn:population":0,
    "gn:timezone":"Asia/Phnom_Penh",
    "iso:country":"KH",
    "name:khm_x_preferred":[
        "Phum Kiribas Kra\u00f4m"
    ],
    "name:khm_x_variant":[
        "\u1797\u17bc\u1798\u17b7 \u1782\u17b8\u179a\u17b8\u1794\u17b6\u179f\u17cb\u1780\u17d2\u179a\u17c4\u1798"
    ],
    "name:und_x_variant":[
        "Phum\u012d T\u0115irib\u0103s Kra\u00f4m",
        "Phum\u012d Kirib\u0103s kra\u00f4m"
    ],
    "wof:name":"Phum Kiribas Kraom",
    "wof:placetype":"locality"
},
  "geometry": {"coordinates":[106.68725000000001,14.16516],"type":"Point"}
}