{
  "type": "Feature",
  "properties": {
    "gn:admin1_code":"18",
    "gn:asciiname":"Tuol Sala",
    "gn:country_code":"KH",
    "gn:dem":9,
    "gn:feature_class":"P",
    "gn:feature_code":"PPL",
    "gn:name":"Tuol Sala",
    "gn:population":0,
    "gn:timezone":"Asia/Phnom_Penh",
    "iso:country":"KH",
    "name:khm_x_preferred":[
        "Tuol Sala"
    ],
    "wof:name":"Tuol Sala",
    "wof:placetype":"locality"
},
  "geometry": {"coordinates":[105.79455,11.22887],"type":"Point"}
}