{
  "type": "Feature",
  "properties": {
    "gn:admin1_code":"29",
    "gn:asciiname":"Phum Anlung Run",
    "gn:country_code":"KH",
    "gn:dem":16,
    "gn:feature_class":"P",
    "gn:feature_code":"PPL",
    "gn:name":"Phum \u00c2nl\u016dng R\u016dn",
    "gn:population":0,
    "gn:timezone":"Asia/Phnom_Penh",
    "iso:country":"KH",
    "name:khm_x_preferred":[
        "Phum \u00c2nl\u016dng R\u016dn"
    ],
    "name:khm_x_variant":[
        "\u1797\u17bc\u1798\u17b7 \u17a2\u1793\u17d2\u179b\u1784\u17cb\u179a\u17bb\u1793"
    ],
    "name:und_x_variant":[
        "Phum\u012d \u00c2nl\u016dng R\u016dn",
        "Phum\u012d \u00c2nl\u00f3ng R\u016dn (1)"
    ],
    "wof:name":"Phum Anlung Run",
    "wof:placetype":"locality"
},
  "geometry": {"coordinates":[103.06001000000001,13.14039],"type":"Point"}
}