{
  "type": "Feature",
  "properties": {
    "gn:admin1_code":"29",
    "gn:asciiname":"Prey Totueng Pir",
    "gn:country_code":"KH",
    "gn:dem":30,
    "gn:feature_class":"P",
    "gn:feature_code":"PPL",
    "gn:name":"Prey Totueng Pir",
    "gn:population":0,
    "gn:timezone":"Asia/Phnom_Penh",
    "iso:country":"KH",
    "name:khm_x_preferred":[
        "Prey Totueng Pir"
    ],
    "name:und_x_variant":[
        "Phum\u012d Prey T\u00f4t\u0153\u0306ng"
    ],
    "wof:name":"Prey Totueng Pir",
    "wof:placetype":"locality"
},
  "geometry": {"coordinates":[102.87135000000001,13.2674],"type":"Point"}
}