{
  "type": "Feature",
  "properties": {
    "gn:admin1_code":"07",
    "gn:asciiname":"Thommeak Treiy",
    "gn:country_code":"KH",
    "gn:dem":17,
    "gn:feature_class":"P",
    "gn:feature_code":"PPL",
    "gn:name":"Thommeak Treiy",
    "gn:population":0,
    "gn:timezone":"Asia/Phnom_Penh",
    "iso:country":"KH",
    "name:khm_x_preferred":[
        "Thommeak Treiy"
    ],
    "wof:name":"Thommeak Treiy",
    "wof:placetype":"locality"
},
  "geometry": {"coordinates":[104.76531,11.81743],"type":"Point"}
}