{
  "type": "Feature",
  "properties": {
    "gn:admin1_code":"17",
    "gn:asciiname":"Phum Kirivongsa",
    "gn:country_code":"KH",
    "gn:dem":77,
    "gn:feature_class":"P",
    "gn:feature_code":"PPL",
    "gn:name":"Phum Kiriv\u00f4ngsa",
    "gn:population":0,
    "gn:timezone":"Asia/Phnom_Penh",
    "iso:country":"KH",
    "name:khm_x_preferred":[
        "Phum Kiriv\u00f4ngsa"
    ],
    "name:khm_x_variant":[
        "\u1797\u17bc\u1798\u17b7 \u1782\u17b8\u179a\u17b8\u179c\u1784\u17d2\u179f\u17b6"
    ],
    "wof:name":"Phum Kirivongsa",
    "wof:placetype":"locality"
},
  "geometry": {"coordinates":[106.54841999999999,14.08521],"type":"Point"}
}