{
  "type": "Feature",
  "properties": {
    "gn:admin1_code":"24.0",
    "gn:asciiname":"Anlong Tnaot",
    "gn:country_code":"KH",
    "gn:dem":17,
    "gn:feature_class":"P",
    "gn:feature_code":"PPL",
    "gn:name":"Anlong Tnaot",
    "gn:population":0,
    "gn:timezone":"Asia/Phnom_Penh",
    "iso:country":"KH",
    "name:khm_x_preferred":[
        "Anlong Tnaot"
    ],
    "wof:name":"Anlong Tnaot",
    "wof:placetype":"locality"
},
  "geometry": {"coordinates":[104.28754000000001,13.06852],"type":"Point"}
}