{
  "type": "Feature",
  "properties": {
    "gn:admin1_code":"29",
    "gn:asciiname":"Trang",
    "gn:country_code":"KH",
    "gn:dem":95,
    "gn:feature_class":"P",
    "gn:feature_code":"PPL",
    "gn:name":"Trang",
    "gn:population":0,
    "gn:timezone":"Asia/Phnom_Penh",
    "iso:country":"KH",
    "name:khm_x_preferred":[
        "Trang"
    ],
    "wof:name":"Trang",
    "wof:placetype":"locality"
},
  "geometry": {"coordinates":[102.42998,13.11157],"type":"Point"}
}