{
  "type": "Feature",
  "properties": {
    "gn:admin1_code":"10.0",
    "gn:asciiname":"Srae Chhuk",
    "gn:country_code":"KH",
    "gn:dem":213,
    "gn:feature_class":"P",
    "gn:feature_code":"PPL",
    "gn:name":"Srae Chhuk",
    "gn:population":0,
    "gn:timezone":"Asia/Phnom_Penh",
    "iso:country":"KH",
    "name:khm_x_preferred":[
        "Srae Chhuk"
    ],
    "wof:name":"Srae Chhuk",
    "wof:placetype":"locality"
},
  "geometry": {"coordinates":[106.94316999999999,12.59213],"type":"Point"}
}