{
  "type": "Feature",
  "properties": {
    "gn:admin1_code":"29",
    "gn:asciiname":"Phum Khmer",
    "gn:country_code":"KH",
    "gn:dem":17,
    "gn:feature_class":"P",
    "gn:feature_code":"PPL",
    "gn:name":"Phum Khm\u00ear",
    "gn:population":0,
    "gn:timezone":"Asia/Phnom_Penh",
    "iso:country":"KH",
    "name:khm_x_preferred":[
        "Phum Khm\u00ear"
    ],
    "name:khm_x_variant":[
        "\u1797\u17bc\u1798\u17b7 \u1781\u17d2\u1798\u17c2\u179a"
    ],
    "wof:name":"Phum Khmer",
    "wof:placetype":"locality"
},
  "geometry": {"coordinates":[103.00676,13.24133],"type":"Point"}
}