{
  "type": "Feature",
  "properties": {
    "gn:admin1_code":"12",
    "gn:asciiname":"Kamnom",
    "gn:country_code":"KH",
    "gn:dem":77,
    "gn:feature_class":"P",
    "gn:feature_code":"PPL",
    "gn:name":"K\u00e2mn\u00f4m",
    "gn:population":0,
    "gn:timezone":"Asia/Phnom_Penh",
    "iso:country":"KH",
    "name:und_x_variant":[
        "P\u2019um K\u014fmn\u014fm",
        "Phum\u012d K\u00e2mn\u00f4n",
        "K\u00e2mn\u00f4m"
    ],
    "wof:name":"Kamnom",
    "wof:placetype":"locality"
},
  "geometry": {"coordinates":[103.80737000000001,12.12172],"type":"Point"}
}