{
  "type": "Feature",
  "properties": {
    "gn:admin1_code":"13",
    "gn:asciiname":"Phumi Trapeang S'ang",
    "gn:country_code":"KH",
    "gn:dem":65,
    "gn:feature_class":"P",
    "gn:feature_code":"PPL",
    "gn:name":"Phum\u012d Tr\u00e2pe\u0103ng S\u2019ang",
    "gn:population":0,
    "gn:timezone":"Asia/Phnom_Penh",
    "iso:country":"KH",
    "name:und_x_variant":[
        "Phum\u012d Tr\u00e2pe\u0103ng Saang",
        "Phum\u012d Tr\u00e2pe\u0103ng S\u2019ang"
    ],
    "wof:name":"Phumi Trapeang S'ang",
    "wof:placetype":"locality"
},
  "geometry": {"coordinates":[105.25915999999999,13.65176],"type":"Point"}
}