{
  "type": "Feature",
  "properties": {
    "gn:admin1_code":"09",
    "gn:asciiname":"Phum Kampi",
    "gn:country_code":"KH",
    "gn:dem":25,
    "gn:feature_class":"P",
    "gn:feature_code":"PPL",
    "gn:name":"Phum K\u0103mpi",
    "gn:population":0,
    "gn:timezone":"Asia/Phnom_Penh",
    "iso:country":"KH",
    "name:khm_x_preferred":[
        "Phum K\u0103mpi"
    ],
    "name:khm_x_variant":[
        "\u1797\u17bc\u1798\u17b7 \u1780\u17b6\u17c6\u1796\u17b8\u179a"
    ],
    "name:und_x_variant":[
        "Phum\u012d K\u00e2mpi",
        "Phum\u012d K\u0103mpir"
    ],
    "wof:name":"Phum Kampi",
    "wof:placetype":"locality"
},
  "geometry": {"coordinates":[106.02224,12.61192],"type":"Point"}
}