{
  "type": "Feature",
  "properties": {
    "gn:admin1_code":"07",
    "gn:asciiname":"Kapal Koeang",
    "gn:country_code":"KH",
    "gn:dem":8,
    "gn:feature_class":"P",
    "gn:feature_code":"PPL",
    "gn:name":"Kapal Koeang",
    "gn:population":0,
    "gn:timezone":"Asia/Phnom_Penh",
    "iso:country":"KH",
    "name:khm_x_preferred":[
        "Kapal Koeang"
    ],
    "name:und_x_variant":[
        "Phum\u012d K\u014fp\u0103l K\u0153\u0103ng"
    ],
    "wof:name":"Kapal Koeang",
    "wof:placetype":"locality"
},
  "geometry": {"coordinates":[105.0569,10.97331],"type":"Point"}
}