{
  "type": "Feature",
  "properties": {
    "gn:admin1_code":"29",
    "gn:asciiname":"Tuol Khpos",
    "gn:country_code":"KH",
    "gn:dem":223,
    "gn:feature_class":"P",
    "gn:feature_code":"PPL",
    "gn:name":"Tuol Khpos",
    "gn:population":0,
    "gn:timezone":"Asia/Phnom_Penh",
    "iso:country":"KH",
    "name:khm_x_preferred":[
        "Tuol Khpos"
    ],
    "wof:name":"Tuol Khpos",
    "wof:placetype":"locality"
},
  "geometry": {"coordinates":[102.36100999999999,13.3214],"type":"Point"}
}