{
  "type": "Feature",
  "properties": {
    "gn:admin1_code":"13.0",
    "gn:asciiname":"Sralay",
    "gn:country_code":"KH",
    "gn:dem":75,
    "gn:feature_class":"P",
    "gn:feature_code":"PPL",
    "gn:name":"Sralay",
    "gn:population":0,
    "gn:timezone":"Asia/Phnom_Penh",
    "iso:country":"KH",
    "name:khm_x_preferred":[
        "Sralay"
    ],
    "wof:name":"Sralay",
    "wof:placetype":"locality"
},
  "geometry": {"coordinates":[104.77518000000001,13.72798],"type":"Point"}
}