{
  "type": "Feature",
  "properties": {
    "gn:admin1_code":"27",
    "gn:asciiname":"Tuol Prasat",
    "gn:country_code":"KH",
    "gn:dem":52,
    "gn:feature_class":"P",
    "gn:feature_code":"PPL",
    "gn:name":"Tuol Prasat",
    "gn:population":0,
    "gn:timezone":"Asia/Phnom_Penh",
    "iso:country":"KH",
    "name:khm_x_preferred":[
        "Tuol Prasat"
    ],
    "wof:name":"Tuol Prasat",
    "wof:placetype":"locality"
},
  "geometry": {"coordinates":[104.04513,14.24349],"type":"Point"}
}