{
  "type": "Feature",
  "properties": {
    "gn:admin1_code":"07",
    "gn:asciiname":"Monourom",
    "gn:country_code":"KH",
    "gn:dem":24,
    "gn:feature_class":"P",
    "gn:feature_code":"PPL",
    "gn:name":"Monourom",
    "gn:population":0,
    "gn:timezone":"Asia/Phnom_Penh",
    "iso:country":"KH",
    "name:khm_x_preferred":[
        "Monourom"
    ],
    "wof:name":"Monourom",
    "wof:placetype":"locality"
},
  "geometry": {"coordinates":[104.74747000000001,11.51464],"type":"Point"}
}