{
  "type": "Feature",
  "properties": {
    "gn:admin1_code":"21",
    "gn:asciiname":"Phumi Bat Bantob",
    "gn:country_code":"KH",
    "gn:dem":22,
    "gn:feature_class":"P",
    "gn:feature_code":"PPL",
    "gn:name":"Phum\u012d B\u0103t B\u00e2nt\u00f3b",
    "gn:population":0,
    "gn:timezone":"Asia/Phnom_Penh",
    "iso:country":"KH",
    "name:und_x_variant":[
        "Phum Bat Kuntop",
        "Phum\u012d Bat B\u00e2nt\u00f4p",
        "Phum\u012d B\u0103t B\u00e2nt\u00f3b"
    ],
    "wof:name":"Phumi Bat Bantob",
    "wof:placetype":"locality"
},
  "geometry": {"coordinates":[104.64098,10.75298],"type":"Point"}
}