{
  "type": "Feature",
  "properties": {
    "gn:admin1_code":"7.0",
    "gn:asciiname":"Phum O Chrou",
    "gn:country_code":"KH",
    "gn:dem":11,
    "gn:feature_class":"P",
    "gn:feature_code":"PPL",
    "gn:name":"Phum O Chr\u014fu",
    "gn:population":0,
    "gn:timezone":"Asia/Phnom_Penh",
    "iso:country":"KH",
    "name:khm_x_preferred":[
        "Phum O Chr\u014fu"
    ],
    "name:khm_x_variant":[
        "\u1797\u17bc\u1798\u17b7 \u17a2\u17bc\u1787\u17d2\u179a\u17c5"
    ],
    "wof:name":"Phum O Chrou",
    "wof:placetype":"locality"
},
  "geometry": {"coordinates":[105.08582,11.30158],"type":"Point"}
}