{
  "type": "Feature",
  "properties": {
    "gn:admin1_code":"29",
    "gn:asciiname":"Kor",
    "gn:country_code":"KH",
    "gn:dem":16,
    "gn:feature_class":"P",
    "gn:feature_code":"PPL",
    "gn:name":"Kor",
    "gn:population":0,
    "gn:timezone":"Asia/Phnom_Penh",
    "iso:country":"KH",
    "name:khm_x_preferred":[
        "Kor"
    ],
    "name:und_x_variant":[
        "P\u2019um T\u00fbol K\u00f4",
        "Phum\u012d K\u00f4r"
    ],
    "wof:name":"Kor",
    "wof:placetype":"locality"
},
  "geometry": {"coordinates":[103.51040999999999,12.76801],"type":"Point"}
}