{
  "type": "Feature",
  "properties": {
    "gn:admin1_code":"19",
    "gn:asciiname":"Phumi Svay Roessei",
    "gn:country_code":"KH",
    "gn:dem":11,
    "gn:feature_class":"P",
    "gn:feature_code":"PPL",
    "gn:name":"Phum\u012d Svay R\u0153ssei",
    "gn:population":0,
    "gn:timezone":"Asia/Phnom_Penh",
    "iso:country":"KH",
    "name:und_x_variant":[
        "Phum\u012d Svay R\u016dssei",
        "Phum\u012d Svay R\u0153ssei"
    ],
    "wof:name":"Phumi Svay Roessei",
    "wof:placetype":"locality"
},
  "geometry": {"coordinates":[104.80194,11.01404],"type":"Point"}
}