{
  "type": "Feature",
  "properties": {
    "gn:admin1_code":"09",
    "gn:asciiname":"Ou Ta Noeng",
    "gn:country_code":"KH",
    "gn:dem":64,
    "gn:feature_class":"P",
    "gn:feature_code":"PPL",
    "gn:name":"Ou Ta Noeng",
    "gn:population":0,
    "gn:timezone":"Asia/Phnom_Penh",
    "iso:country":"KH",
    "name:khm_x_preferred":[
        "Ou Ta Noeng"
    ],
    "name:khm_x_variant":[
        "\u1797\u17bc\u1798\u17b7 \u17a2\u17bc\u178f\u17b6\u178e\u1784",
        "Phum\u012d O Tan\u0153\u0306ng"
    ],
    "wof:name":"Ou Ta Noeng",
    "wof:placetype":"locality"
},
  "geometry": {"coordinates":[106.17794000000001,12.84077],"type":"Point"}
}