{
  "type": "Feature",
  "properties": {
    "gn:admin1_code":"25",
    "gn:asciiname":"Ta Paen",
    "gn:country_code":"KH",
    "gn:dem":19,
    "gn:feature_class":"P",
    "gn:feature_code":"PPL",
    "gn:name":"Ta Paen",
    "gn:population":0,
    "gn:timezone":"Asia/Phnom_Penh",
    "iso:country":"KH",
    "name:khm_x_preferred":[
        "Ta Paen"
    ],
    "name:khm_x_variant":[
        "Phum Pa\u00f4y Ta P\u00ean",
        "\u1797\u17bc\u1798\u17b7 \u1794\u17c4\u1799\u178f\u17b6\u1794\u17c9\u17c2\u1793"
    ],
    "name:und_x_variant":[
        "Tapen",
        "Phum\u012d Pa\u00f4y Ta P\u00ean"
    ],
    "wof:name":"Ta Paen",
    "wof:placetype":"locality"
},
  "geometry": {"coordinates":[103.16333,13.59997],"type":"Point"}
}