{
  "type": "Feature",
  "properties": {
    "gn:admin1_code":"23",
    "gn:asciiname":"Phumi Phav",
    "gn:country_code":"KH",
    "gn:dem":407,
    "gn:feature_class":"P",
    "gn:feature_code":"PPL",
    "gn:name":"Phum\u012d Phav",
    "gn:population":0,
    "gn:timezone":"Asia/Phnom_Penh",
    "iso:country":"KH",
    "wof:name":"Phumi Phav",
    "wof:placetype":"locality"
},
  "geometry": {"coordinates":[107.10475,14.19724],"type":"Point"}
}