{
  "type": "Feature",
  "properties": {
    "gn:admin1_code":"31.0",
    "gn:asciiname":"Prambei Dabmuoy",
    "gn:country_code":"KH",
    "gn:dem":61,
    "gn:feature_class":"P",
    "gn:feature_code":"PPL",
    "gn:name":"Prambei Dabmuoy",
    "gn:population":0,
    "gn:timezone":"Asia/Phnom_Penh",
    "iso:country":"KH",
    "name:khm_x_preferred":[
        "Prambei Dabmuoy"
    ],
    "name:khm_x_variant":[
        "\u1797\u17bc\u1798\u17b7 \u179b\u17c1\u1781 \u1794\u17d2\u179a\u17b6\u17c6\u1794\u17b8 \u178a\u1794\u17cb\u1798\u17bd\u1799",
        "Phum L\u00e9k Pr\u0103mbei D\u00e2p Mu\u014fy"
    ],
    "wof:name":"Prambei Dabmuoy",
    "wof:placetype":"locality"
},
  "geometry": {"coordinates":[105.65881,12.00148],"type":"Point"}
}