{
  "type": "Feature",
  "properties": {
    "gn:admin1_code":"07",
    "gn:asciiname":"Melou Moeun",
    "gn:country_code":"KH",
    "gn:dem":19,
    "gn:feature_class":"P",
    "gn:feature_code":"PPL",
    "gn:name":"Melou Moeun",
    "gn:population":0,
    "gn:timezone":"Asia/Phnom_Penh",
    "iso:country":"KH",
    "name:und_x_variant":[
        "Malow Moeum",
        "Phum\u012d M\u00f4lu Mean",
        "Melou Moeun",
        "Phum\u012d Mlu M\u0153n"
    ],
    "wof:name":"Melou Moeun",
    "wof:placetype":"locality"
},
  "geometry": {"coordinates":[104.77323,11.81738],"type":"Point"}
}