{
  "type": "Feature",
  "properties": {
    "gn:admin1_code":"24",
    "gn:asciiname":"Phum Kouk Phnou",
    "gn:country_code":"KH",
    "gn:dem":39,
    "gn:feature_class":"P",
    "gn:feature_code":"PPL",
    "gn:name":"Phum Ko\u016dk Phno\u016d",
    "gn:population":0,
    "gn:timezone":"Asia/Phnom_Penh",
    "iso:country":"KH",
    "name:khm_x_preferred":[
        "Phum Ko\u016dk Phno\u016d"
    ],
    "name:khm_x_variant":[
        "\u1797\u17bc\u1798\u17b7 \u1782\u17c4\u1780\u1797\u17d2\u1793\u17c5"
    ],
    "name:und_x_variant":[
        "Phum\u012d Ko\u016dk Phn\u014fu"
    ],
    "wof:name":"Phum Kouk Phnou",
    "wof:placetype":"locality"
},
  "geometry": {"coordinates":[103.72114999999999,14.00395],"type":"Point"}
}