{
  "type": "Feature",
  "properties": {
    "gn:admin1_code":"03",
    "gn:asciiname":"Khum Thma Edth",
    "gn:country_code":"KH",
    "gn:dem":26,
    "gn:feature_class":"P",
    "gn:feature_code":"PPL",
    "gn:name":"Kh\u016dm Thm\u00e2 \u0114dth",
    "gn:population":0,
    "gn:timezone":"Asia/Phnom_Penh",
    "iso:country":"KH",
    "name:und_x_variant":[
        "Thm\u00e2 Et",
        "Kh\u016dm Thm\u00e2 Ed",
        "Kh\u016dm Thm\u00e2 \u0114dth"
    ],
    "wof:name":"Khum Thma Edth",
    "wof:placetype":"locality"
},
  "geometry": {"coordinates":[104.66439,11.96529],"type":"Point"}
}