{
  "type": "Feature",
  "properties": {
    "gn:admin1_code":"14",
    "gn:asciiname":"Trapeang Skon",
    "gn:country_code":"KH",
    "gn:dem":11,
    "gn:feature_class":"P",
    "gn:feature_code":"PPL",
    "gn:name":"Trapeang Skon",
    "gn:population":0,
    "gn:timezone":"Asia/Phnom_Penh",
    "iso:country":"KH",
    "name:khm_x_preferred":[
        "Trapeang Skon"
    ],
    "wof:name":"Trapeang Skon",
    "wof:placetype":"locality"
},
  "geometry": {"coordinates":[105.52815,11.32765],"type":"Point"}
}