{
  "type": "Feature",
  "properties": {
    "gn:admin1_code":"31",
    "gn:asciiname":"Phumi Kranhung",
    "gn:country_code":"KH",
    "gn:dem":40,
    "gn:feature_class":"P",
    "gn:feature_code":"PPL",
    "gn:name":"Phum\u012d Kr\u00e2nhung",
    "gn:population":0,
    "gn:timezone":"Asia/Phnom_Penh",
    "iso:country":"KH",
    "name:und_x_variant":[
        "Phum Kranhoung",
        "Phum\u012d Kr\u00e2nhung"
    ],
    "wof:name":"Phumi Kranhung",
    "wof:placetype":"locality"
},
  "geometry": {"coordinates":[105.88395,11.80092],"type":"Point"}
}