{
  "type": "Feature",
  "properties": {
    "gn:admin1_code":"14",
    "gn:asciiname":"Koun Pou",
    "gn:country_code":"KH",
    "gn:dem":10,
    "gn:feature_class":"P",
    "gn:feature_code":"PPL",
    "gn:name":"Koun Pou",
    "gn:population":0,
    "gn:timezone":"Asia/Phnom_Penh",
    "iso:country":"KH",
    "name:khm_x_preferred":[
        "Koun Pou"
    ],
    "wof:name":"Koun Pou",
    "wof:placetype":"locality"
},
  "geometry": {"coordinates":[105.50493,11.46244],"type":"Point"}
}