{
  "type": "Feature",
  "properties": {
    "gn:admin1_code":"02",
    "gn:asciiname":"Phumi Kaoh Rokar Cham",
    "gn:country_code":"KH",
    "gn:dem":20,
    "gn:feature_class":"P",
    "gn:feature_code":"PPL",
    "gn:name":"Phum\u012d Ka\u00f4h R\u00f4kar Cham",
    "gn:population":0,
    "gn:timezone":"Asia/Phnom_Penh",
    "iso:country":"KH",
    "wof:name":"Phumi Kaoh Rokar Cham",
    "wof:placetype":"locality"
},
  "geometry": {"coordinates":[105.38907,11.94523],"type":"Point"}
}