{
  "type": "Feature",
  "properties": {
    "gn:admin1_code":"02",
    "gn:asciiname":"Phumi Chbar Ampou",
    "gn:country_code":"KH",
    "gn:dem":15,
    "gn:feature_class":"P",
    "gn:feature_code":"PPL",
    "gn:name":"Phum\u012d Chbar \u00c2mp\u014fu",
    "gn:population":0,
    "gn:timezone":"Asia/Phnom_Penh",
    "iso:country":"KH",
    "wof:name":"Phumi Chbar Ampou",
    "wof:placetype":"locality"
},
  "geometry": {"coordinates":[104.97328,11.94788],"type":"Point"}
}