{
  "type": "Feature",
  "properties": {
    "gn:admin1_code":"05",
    "gn:asciiname":"Kien Teak",
    "gn:country_code":"KH",
    "gn:dem":37,
    "gn:feature_class":"P",
    "gn:feature_code":"PPL",
    "gn:name":"Kien Teak",
    "gn:population":0,
    "gn:timezone":"Asia/Phnom_Penh",
    "iso:country":"KH",
    "name:khm_x_preferred":[
        "Kien Teak"
    ],
    "name:und_x_variant":[
        "Phum Kieut\u00e9ac",
        "Phum\u012d Ki\u0115n Te\u0103k"
    ],
    "wof:name":"Kien Teak",
    "wof:placetype":"locality"
},
  "geometry": {"coordinates":[104.77294000000001,13.15785],"type":"Point"}
}