{
  "type": "Feature",
  "properties": {
    "gn:admin1_code":"22",
    "gn:asciiname":"Dei Thmei",
    "gn:country_code":"KH",
    "gn:dem":12,
    "gn:feature_class":"P",
    "gn:feature_code":"PPL",
    "gn:name":"Dei Thmei",
    "gn:population":0,
    "gn:timezone":"Asia/Phnom_Penh",
    "iso:country":"KH",
    "name:khm_x_preferred":[
        "Dei Thmei"
    ],
    "wof:name":"Dei Thmei",
    "wof:placetype":"locality"
},
  "geometry": {"coordinates":[104.85381,11.56884],"type":"Point"}
}