{
  "type": "Feature",
  "properties": {
    "gn:admin1_code":"12.0",
    "gn:asciiname":"Phum Kangan",
    "gn:country_code":"KH",
    "gn:dem":21,
    "gn:feature_class":"P",
    "gn:feature_code":"PPL",
    "gn:name":"Phum Kangan",
    "gn:population":0,
    "gn:timezone":"Asia/Phnom_Penh",
    "iso:country":"KH",
    "name:khm_x_preferred":[
        "Phum Kangan"
    ],
    "name:khm_x_variant":[
        "\u1797\u17bc\u1798\u17b7 \u1780\u17d2\u1784\u17b6\u1793"
    ],
    "wof:name":"Phum Kangan",
    "wof:placetype":"locality"
},
  "geometry": {"coordinates":[103.93774999999999,12.60703],"type":"Point"}
}