{
  "type": "Feature",
  "properties": {
    "gn:admin1_code":"29",
    "gn:asciiname":"Mreah Prov",
    "gn:country_code":"KH",
    "gn:dem":19,
    "gn:feature_class":"P",
    "gn:feature_code":"PPL",
    "gn:name":"Mreah Prov",
    "gn:population":0,
    "gn:timezone":"Asia/Phnom_Penh",
    "iso:country":"KH",
    "name:khm_x_preferred":[
        "Mreah Prov"
    ],
    "name:khm_x_variant":[
        "\u1797\u17bc\u1798\u17b7 \u1798\u17d2\u179a\u17c7\u1796\u17d2\u179a\u17c5",
        "Phum M\u00f4re\u0103h Pr\u014fu"
    ],
    "name:und_x_variant":[
        "P\u2019um Manea Pr\u0153u",
        "Phum\u012d M\u00f4re\u0103h Prou",
        "Phum\u012d Mre\u0103h Pr\u014fu"
    ],
    "wof:name":"Mreah Prov",
    "wof:placetype":"locality"
},
  "geometry": {"coordinates":[103.48845,12.78788],"type":"Point"}
}