{
  "type": "Feature",
  "properties": {
    "gn:admin1_code":"14",
    "gn:asciiname":"Trapeang Srae",
    "gn:country_code":"KH",
    "gn:dem":7,
    "gn:feature_class":"P",
    "gn:feature_code":"PPL",
    "gn:name":"Trapeang Srae",
    "gn:population":0,
    "gn:timezone":"Asia/Phnom_Penh",
    "iso:country":"KH",
    "name:khm_x_preferred":[
        "Trapeang Srae"
    ],
    "name:und_x_variant":[
        "Phum\u012d Tr\u00e2pe\u0103ng Sr\u00ea"
    ],
    "wof:name":"Trapeang Srae",
    "wof:placetype":"locality"
},
  "geometry": {"coordinates":[105.55802,11.2596],"type":"Point"}
}