{
  "type": "Feature",
  "properties": {
    "gn:admin1_code":"28",
    "gn:asciiname":"Phum Samraong Kandal",
    "gn:country_code":"KH",
    "gn:dem":8,
    "gn:feature_class":"P",
    "gn:feature_code":"PPL",
    "gn:name":"Phum S\u00e2mra\u00f4ng K\u00e2ndal",
    "gn:population":0,
    "gn:timezone":"Asia/Phnom_Penh",
    "iso:country":"KH",
    "name:khm_x_preferred":[
        "Phum S\u00e2mra\u00f4ng K\u00e2ndal"
    ],
    "name:khm_x_variant":[
        "\u1797\u17bc\u1798\u17b7 \u179f\u17c6\u179a\u17c4\u1784\u1780\u178e\u17d2\u178f\u17b6\u179b"
    ],
    "name:und_x_variant":[
        "Samrung",
        "Phum\u012d S\u00e2mra\u00f4ng K\u00e2ndal"
    ],
    "wof:name":"Phum Samraong Kandal",
    "wof:placetype":"locality"
},
  "geometry": {"coordinates":[103.81458000000001,10.69556],"type":"Point"}
}