{
  "type": "Feature",
  "properties": {
    "gn:admin1_code":"22",
    "gn:asciiname":"Chrang Chamreh Muoy",
    "gn:country_code":"KH",
    "gn:dem":11,
    "gn:feature_class":"P",
    "gn:feature_code":"PPL",
    "gn:name":"Chrang Chamreh Muoy",
    "gn:population":0,
    "gn:timezone":"Asia/Phnom_Penh",
    "iso:country":"KH",
    "name:khm_x_preferred":[
        "Chrang Chamreh Muoy"
    ],
    "wof:name":"Chrang Chamreh Muoy",
    "wof:placetype":"locality"
},
  "geometry": {"coordinates":[104.88542,11.63049],"type":"Point"}
}