{
  "type": "Feature",
  "properties": {
    "gn:admin1_code":"13",
    "gn:asciiname":"Krala Peas",
    "gn:country_code":"KH",
    "gn:dem":54,
    "gn:feature_class":"P",
    "gn:feature_code":"PPL",
    "gn:name":"Krala Peas",
    "gn:population":0,
    "gn:timezone":"Asia/Phnom_Penh",
    "iso:country":"KH",
    "name:khm_x_preferred":[
        "Krala Peas"
    ],
    "wof:name":"Krala Peas",
    "wof:placetype":"locality"
},
  "geometry": {"coordinates":[104.9841,13.97817],"type":"Point"}
}