{
  "type": "Feature",
  "properties": {
    "gn:admin1_code":"29",
    "gn:asciiname":"Phumi Tuol Rokar Khang Cheung",
    "gn:country_code":"KH",
    "gn:dem":19,
    "gn:feature_class":"P",
    "gn:feature_code":"PPL",
    "gn:name":"Phum\u012d Tu\u014fl R\u00f4kar Khang Cheung",
    "gn:population":0,
    "gn:timezone":"Asia/Phnom_Penh",
    "iso:country":"KH",
    "name:und_x_variant":[
        "Phum\u012d Tu\u014fl R\u00f4ka Khang Cheung",
        "Phum\u012d Tu\u014fl R\u00f4kar Khang Cheung"
    ],
    "wof:name":"Phumi Tuol Rokar Khang Cheung",
    "wof:placetype":"locality"
},
  "geometry": {"coordinates":[102.85978,13.35618],"type":"Point"}
}