{
  "type": "Feature",
  "properties": {
    "gn:admin1_code":"24",
    "gn:asciiname":"Phum Rovieng",
    "gn:country_code":"KH",
    "gn:dem":45,
    "gn:feature_class":"P",
    "gn:feature_code":"PPL",
    "gn:name":"Phum R\u00f4vi\u0115ng",
    "gn:population":0,
    "gn:timezone":"Asia/Phnom_Penh",
    "iso:country":"KH",
    "name:khm_x_preferred":[
        "Phum R\u00f4vi\u0115ng"
    ],
    "name:khm_x_variant":[
        "\u1797\u17bc\u1798\u17b7 \u179a\u179c\u17c0\u1784",
        "Phum\u012d R\u00f4vi\u0115ng"
    ],
    "wof:name":"Phum Rovieng",
    "wof:placetype":"locality"
},
  "geometry": {"coordinates":[103.99344000000001,13.51052],"type":"Point"}
}