{
  "type": "Feature",
  "properties": {
    "gn:admin1_code":"31.0",
    "gn:asciiname":"Chies Ti Muoy",
    "gn:country_code":"KH",
    "gn:dem":33,
    "gn:feature_class":"P",
    "gn:feature_code":"PPL",
    "gn:name":"Chies Ti Muoy",
    "gn:population":0,
    "gn:timezone":"Asia/Phnom_Penh",
    "iso:country":"KH",
    "name:khm_x_preferred":[
        "Chies Ti Muoy"
    ],
    "wof:name":"Chies Ti Muoy",
    "wof:placetype":"locality"
},
  "geometry": {"coordinates":[105.61530999999999,12.03446],"type":"Point"}
}