{
  "type": "Feature",
  "properties": {
    "gn:admin1_code":"24",
    "gn:asciiname":"Srae Nouy",
    "gn:country_code":"KH",
    "gn:dem":73,
    "gn:feature_class":"P",
    "gn:feature_code":"PPL",
    "gn:name":"Srae Nouy",
    "gn:population":0,
    "gn:timezone":"Asia/Phnom_Penh",
    "iso:country":"KH",
    "name:khm_x_preferred":[
        "Srae Nouy"
    ],
    "name:khm_x_variant":[
        "\u179f\u17d2\u179a\u17c2\u178e\u17bc\u1799"
    ],
    "name:und_x_variant":[
        "Phum\u012d Sr\u00ea Noy",
        "Khol",
        "Sr\u00ea Noy"
    ],
    "wof:name":"Srae Nouy",
    "wof:placetype":"locality"
},
  "geometry": {"coordinates":[104.02073,13.80274],"type":"Point"}
}