{
  "type": "Feature",
  "properties": {
    "gn:admin1_code":"00",
    "gn:asciiname":"Phumi Damnak Pring",
    "gn:country_code":"KH",
    "gn:dem":24,
    "gn:feature_class":"P",
    "gn:feature_code":"PPL",
    "gn:name":"Phum\u012d D\u00e2mn\u0103k Pring",
    "gn:population":0,
    "gn:timezone":"Asia/Phnom_Penh",
    "iso:country":"KH",
    "name:und_x_variant":[
        "Sn\u00e2ol",
        "Phum\u012d D\u00e2mn\u0103k Pring"
    ],
    "wof:name":"Phumi Damnak Pring",
    "wof:placetype":"locality"
},
  "geometry": {"coordinates":[104.73647,11.76146],"type":"Point"}
}