{
  "type": "Feature",
  "properties": {
    "gn:admin1_code":"12.0",
    "gn:asciiname":"Phum Veal Snao",
    "gn:country_code":"KH",
    "gn:dem":20,
    "gn:feature_class":"P",
    "gn:feature_code":"PPL",
    "gn:name":"Phum V\u00e9al Sna\u00f4",
    "gn:population":0,
    "gn:timezone":"Asia/Phnom_Penh",
    "iso:country":"KH",
    "name:khm_x_preferred":[
        "Phum V\u00e9al Sna\u00f4"
    ],
    "name:khm_x_variant":[
        "\u1797\u17bc\u1798\u17b7 \u179c\u17b6\u179b\u179f\u17d2\u1793\u17c4"
    ],
    "wof:name":"Phum Veal Snao",
    "wof:placetype":"locality"
},
  "geometry": {"coordinates":[103.79785,12.64675],"type":"Point"}
}