{
  "type": "Feature",
  "properties": {
    "gn:admin1_code":"23.0",
    "gn:asciiname":"Phum Muoy",
    "gn:country_code":"KH",
    "gn:dem":120,
    "gn:feature_class":"P",
    "gn:feature_code":"PPL",
    "gn:name":"Phum Muoy",
    "gn:population":0,
    "gn:timezone":"Asia/Phnom_Penh",
    "iso:country":"KH",
    "name:khm_x_preferred":[
        "Phum Muoy"
    ],
    "wof:name":"Phum Muoy",
    "wof:placetype":"locality"
},
  "geometry": {"coordinates":[106.73533999999999,13.57154],"type":"Point"}
}