{
  "type": "Feature",
  "properties": {
    "gn:admin1_code":"31",
    "gn:asciiname":"Khley",
    "gn:country_code":"KH",
    "gn:dem":59,
    "gn:feature_class":"P",
    "gn:feature_code":"PPL",
    "gn:name":"Khley",
    "gn:population":0,
    "gn:timezone":"Asia/Phnom_Penh",
    "iso:country":"KH",
    "name:khm_x_preferred":[
        "Khley"
    ],
    "name:und_x_variant":[
        "Phum\u012d Khley"
    ],
    "wof:name":"Khley",
    "wof:placetype":"locality"
},
  "geometry": {"coordinates":[106.12555,11.7772],"type":"Point"}
}