{
  "type": "Feature",
  "properties": {
    "gn:admin1_code":"19",
    "gn:asciiname":"Phumi Phnum Krapeu",
    "gn:country_code":"KH",
    "gn:dem":12,
    "gn:feature_class":"P",
    "gn:feature_code":"PPL",
    "gn:name":"Phum\u012d Phnum Kr\u00e2peu",
    "gn:population":0,
    "gn:timezone":"Asia/Phnom_Penh",
    "iso:country":"KH",
    "name:und_x_variant":[
        "Phum Krapoeu",
        "Phum\u012d Phnum Kr\u00e2peu"
    ],
    "wof:name":"Phumi Phnum Krapeu",
    "wof:placetype":"locality"
},
  "geometry": {"coordinates":[104.7308,10.59374],"type":"Point"}
}