{
  "type": "Feature",
  "properties": {
    "gn:admin1_code":"22",
    "gn:asciiname":"Prey Tea",
    "gn:country_code":"KH",
    "gn:dem":15,
    "gn:feature_class":"P",
    "gn:feature_code":"PPL",
    "gn:name":"Prey Tea",
    "gn:population":0,
    "gn:timezone":"Asia/Phnom_Penh",
    "iso:country":"KH",
    "name:khm_x_preferred":[
        "Prey Tea"
    ],
    "wof:name":"Prey Tea",
    "wof:placetype":"locality"
},
  "geometry": {"coordinates":[104.83644,11.54764],"type":"Point"}
}