{
  "type": "Feature",
  "properties": {
    "gn:admin1_code":"23.0",
    "gn:asciiname":"Plor",
    "gn:country_code":"KH",
    "gn:dem":232,
    "gn:feature_class":"P",
    "gn:feature_code":"PPL",
    "gn:name":"Plor",
    "gn:population":0,
    "gn:timezone":"Asia/Phnom_Penh",
    "iso:country":"KH",
    "name:khm_x_preferred":[
        "Plor"
    ],
    "wof:name":"Plor",
    "wof:placetype":"locality"
},
  "geometry": {"coordinates":[107.28543999999999,13.64266],"type":"Point"}
}