{
  "type": "Feature",
  "properties": {
    "gn:admin1_code":"27",
    "gn:asciiname":"Phum Kbal Sa",
    "gn:country_code":"KH",
    "gn:dem":82,
    "gn:feature_class":"P",
    "gn:feature_code":"PPL",
    "gn:name":"Phum Kbal S\u00e2",
    "gn:population":0,
    "gn:timezone":"Asia/Phnom_Penh",
    "iso:country":"KH",
    "name:khm_x_preferred":[
        "Phum Kbal S\u00e2"
    ],
    "name:khm_x_variant":[
        "\u1797\u17bc\u1798\u17b7 \u1780\u17d2\u1794\u17b6\u179b\u179f\u179a"
    ],
    "name:und_x_variant":[
        "Kbbal So",
        "Phum\u012d Kbal S\u00e2",
        "Khbal Sar",
        "Khbat Sat",
        "Khbal Sat",
        "Kbanso",
        "Phum\u012d Kbal S\u00e2r"
    ],
    "wof:name":"Phum Kbal Sa",
    "wof:placetype":"locality"
},
  "geometry": {"coordinates":[103.58118,14.33359],"type":"Point"}
}