{
  "type": "Feature",
  "properties": {
    "gn:admin1_code":"25",
    "gn:asciiname":"Phum Kouk Cha",
    "gn:country_code":"KH",
    "gn:dem":20,
    "gn:feature_class":"P",
    "gn:feature_code":"PPL",
    "gn:name":"Phum Ko\u016dk Cha",
    "gn:population":0,
    "gn:timezone":"Asia/Phnom_Penh",
    "iso:country":"KH",
    "name:khm_x_preferred":[
        "Phum Ko\u016dk Cha"
    ],
    "name:khm_x_variant":[
        "\u1797\u17bc\u1798\u17b7 \u1782\u17c4\u1780\u1790\u17b6"
    ],
    "name:und_x_variant":[
        "Phum\u012d Ko\u016dk Cha"
    ],
    "wof:name":"Phum Kouk Cha",
    "wof:placetype":"locality"
},
  "geometry": {"coordinates":[103.42422000000001,13.68017],"type":"Point"}
}