{
  "type": "Feature",
  "properties": {
    "gn:admin1_code":"14",
    "gn:asciiname":"Neak Loeang",
    "gn:country_code":"KH",
    "gn:dem":13,
    "gn:feature_class":"P",
    "gn:feature_code":"PPL",
    "gn:name":"Neak Loeang",
    "gn:population":0,
    "gn:timezone":"Asia/Phnom_Penh",
    "iso:country":"KH",
    "name:khm_x_preferred":[
        "Neak Loeang"
    ],
    "name:und_x_variant":[
        "Phum\u012d \u2019Ne\u0103k L\u0153\u0103ng"
    ],
    "wof:name":"Neak Loeang",
    "wof:placetype":"locality"
},
  "geometry": {"coordinates":[105.2829,11.24131],"type":"Point"}
}