{
  "type": "Feature",
  "properties": {
    "gn:admin1_code":"14",
    "gn:asciiname":"Neak Loeang",
    "gn:country_code":"KH",
    "gn:dem":13,
    "gn:feature_class":"P",
    "gn:feature_code":"PPL",
    "gn:name":"Neak Loeang",
    "gn:population":0,
    "gn:timezone":"Asia/Phnom_Penh",
    "iso:country":"KH",
    "name:ceb_x_preferred":[
        "Phum\u012d Pr\u00eak Khsay"
    ],
    "name:fra_x_preferred":[
        "Neak Luong"
    ],
    "name:ita_x_preferred":[
        "Neak Luong"
    ],
    "name:khm_x_preferred":[
        "Neak Loeang"
    ],
    "name:khm_x_variant":[
        "\u17a2\u17d2\u1793\u1780\u179b\u17bf\u1784"
    ],
    "name:ron_x_preferred":[
        "Net Leung"
    ],
    "name:swe_x_preferred":[
        "Neak Leung"
    ],
    "name:und_x_variant":[
        "Phum\u012d \u2019Ne\u0103k L\u0153\u0103ng"
    ],
    "name:vie_x_preferred":[
        "Neak Loeang"
    ],
    "wof:name":"Neak Loeang",
    "wof:placetype":"locality"
},
  "geometry": {"coordinates":[105.2829,11.24131],"type":"Point"}
}