{
  "type": "Feature",
  "properties": {
    "gn:admin1_code":"22",
    "gn:asciiname":"Phumi Krang Kor",
    "gn:country_code":"KH",
    "gn:dem":14,
    "gn:feature_class":"P",
    "gn:feature_code":"PPL",
    "gn:name":"Phum\u012d Kr\u0103ng K\u00f4r",
    "gn:population":0,
    "gn:timezone":"Asia/Phnom_Penh",
    "iso:country":"KH",
    "name:und_x_variant":[
        "Krang Thom",
        "Phum\u012d Kr\u0103ng K\u00f4",
        "Phum\u012d Kr\u0103ng K\u00f4r"
    ],
    "wof:name":"Phumi Krang Kor",
    "wof:placetype":"locality"
},
  "geometry": {"coordinates":[104.85803,11.43544],"type":"Point"}
}