{
  "type": "Feature",
  "properties": {
    "gn:admin1_code":"29",
    "gn:asciiname":"Prey Dach",
    "gn:country_code":"KH",
    "gn:dem":15,
    "gn:feature_class":"P",
    "gn:feature_code":"PPL",
    "gn:name":"Prey Dach",
    "gn:population":0,
    "gn:timezone":"Asia/Phnom_Penh",
    "iso:country":"KH",
    "wof:name":"Prey Dach",
    "wof:placetype":"locality"
},
  "geometry": {"coordinates":[103.16545000000001,13.16847],"type":"Point"}
}