{
  "type": "Feature",
  "properties": {
    "gn:admin1_code":"09",
    "gn:asciiname":"Meak Say",
    "gn:country_code":"KH",
    "gn:dem":84,
    "gn:feature_class":"P",
    "gn:feature_code":"PPL",
    "gn:name":"M\u00e9ak Say",
    "gn:population":0,
    "gn:timezone":"Asia/Phnom_Penh",
    "iso:country":"KH",
    "name:und_x_variant":[
        "Phum\u012d M\u00e9ak Say",
        "M\u00e9ak Say"
    ],
    "wof:name":"Meak Say",
    "wof:placetype":"locality"
},
  "geometry": {"coordinates":[106.49732,12.12746],"type":"Point"}
}