{
  "type": "Feature",
  "properties": {
    "gn:admin1_code":"29",
    "gn:asciiname":"Ou Da Leu",
    "gn:country_code":"KH",
    "gn:dem":86,
    "gn:feature_class":"P",
    "gn:feature_code":"PPL",
    "gn:name":"Ou Da Leu",
    "gn:population":0,
    "gn:timezone":"Asia/Phnom_Penh",
    "iso:country":"KH",
    "name:khm_x_preferred":[
        "Ou Da Leu"
    ],
    "wof:name":"Ou Da Leu",
    "wof:placetype":"locality"
},
  "geometry": {"coordinates":[102.44737000000001,13.08892],"type":"Point"}
}