{
  "type": "Feature",
  "properties": {
    "gn:admin1_code":"21",
    "gn:asciiname":"Damn",
    "gn:country_code":"KH",
    "gn:dem":6,
    "gn:feature_class":"P",
    "gn:feature_code":"PPL",
    "gn:name":"Damn",
    "gn:population":0,
    "gn:timezone":"Asia/Phnom_Penh",
    "iso:country":"KH",
    "name:khm_x_preferred":[
        "Damn"
    ],
    "name:und_x_variant":[
        "Phum\u012d Phnum D\u00e2mrei"
    ],
    "wof:name":"Damn",
    "wof:placetype":"locality"
},
  "geometry": {"coordinates":[104.48627999999999,10.59889],"type":"Point"}
}