{
  "type": "Feature",
  "properties": {
    "gn:admin1_code":"18",
    "gn:asciiname":"Phumi Trapeang Smach",
    "gn:country_code":"KH",
    "gn:dem":17,
    "gn:feature_class":"P",
    "gn:feature_code":"PPL",
    "gn:name":"Phum\u012d Tr\u00e2pe\u0103ng Sm\u0103ch",
    "gn:population":0,
    "gn:timezone":"Asia/Phnom_Penh",
    "iso:country":"KH",
    "name:und_x_variant":[
        "Phum Trap Smach",
        "Phum\u012d Tr\u00e2pe\u0103ng Sm\u0103ch"
    ],
    "wof:name":"Phumi Trapeang Smach",
    "wof:placetype":"locality"
},
  "geometry": {"coordinates":[105.77909,11.53204],"type":"Point"}
}