{
  "type": "Feature",
  "properties": {
    "gn:admin1_code":"02",
    "gn:asciiname":"Khum Prek Dambok",
    "gn:country_code":"KH",
    "gn:dem":18,
    "gn:feature_class":"P",
    "gn:feature_code":"PPL",
    "gn:name":"Kh\u016dm Pr\u00eak D\u00e2mbok",
    "gn:population":0,
    "gn:timezone":"Asia/Phnom_Penh",
    "iso:country":"KH",
    "name:und_x_variant":[
        "Phum Prek Dambok",
        "Kh\u016dm Pr\u00eak D\u00e2mbok"
    ],
    "wof:name":"Khum Prek Dambok",
    "wof:placetype":"locality"
},
  "geometry": {"coordinates":[105.16003000000001,11.89136],"type":"Point"}
}