{
  "type": "Feature",
  "properties": {
    "gn:admin1_code":"04",
    "gn:asciiname":"Phum Sopi",
    "gn:country_code":"KH",
    "gn:dem":65,
    "gn:feature_class":"P",
    "gn:feature_code":"PPL",
    "gn:name":"Phum Sopi",
    "gn:population":0,
    "gn:timezone":"Asia/Phnom_Penh",
    "iso:country":"KH",
    "name:khm_x_preferred":[
        "Phum Sopi"
    ],
    "name:khm_x_variant":[
        "\u1797\u17bc\u1798\u17b7 \u179f\u17bc\u1796\u17b8",
        "Phum\u012d Sopi"
    ],
    "wof:name":"Phum Sopi",
    "wof:placetype":"locality"
},
  "geometry": {"coordinates":[104.16586,11.60999],"type":"Point"}
}