{
  "type": "Feature",
  "properties": {
    "gn:admin1_code":"12.0",
    "gn:asciiname":"Phum O Prakang Khang Cheung",
    "gn:country_code":"KH",
    "gn:dem":23,
    "gn:feature_class":"P",
    "gn:feature_code":"PPL",
    "gn:name":"Phum O Pr\u00e2k\u00e2ng Khang Cheung",
    "gn:population":0,
    "gn:timezone":"Asia/Phnom_Penh",
    "iso:country":"KH",
    "name:khm_x_preferred":[
        "Phum O Pr\u00e2k\u00e2ng Khang Cheung"
    ],
    "name:khm_x_variant":[
        "\u1797\u17bc\u1798\u17b7 \u17a2\u17bc\u1794\u17d2\u179a\u1780\u1784\u1781\u17b6\u1784\u1787\u17be\u1784"
    ],
    "wof:name":"Phum O Prakang Khang Cheung",
    "wof:placetype":"locality"
},
  "geometry": {"coordinates":[103.93988,12.56597],"type":"Point"}
}