{
  "type": "Feature",
  "properties": {
    "gn:admin1_code":"05",
    "gn:asciiname":"Phumi Tumpech",
    "gn:country_code":"KH",
    "gn:dem":24,
    "gn:feature_class":"P",
    "gn:feature_code":"PPL",
    "gn:name":"Phum\u012d Tump\u00e9ch",
    "gn:population":0,
    "gn:timezone":"Asia/Phnom_Penh",
    "iso:country":"KH",
    "name:und_x_variant":[
        "Phum Tompech",
        "Phum\u012d Tump\u00e9ch"
    ],
    "wof:name":"Phumi Tumpech",
    "wof:placetype":"locality"
},
  "geometry": {"coordinates":[104.62302,13.02916],"type":"Point"}
}