{
  "type": "Feature",
  "properties": {
    "gn:admin1_code":"21",
    "gn:asciiname":"Srae Chrov",
    "gn:country_code":"KH",
    "gn:dem":43,
    "gn:feature_class":"P",
    "gn:feature_code":"PPL",
    "gn:name":"Srae Chrov",
    "gn:population":0,
    "gn:timezone":"Asia/Phnom_Penh",
    "iso:country":"KH",
    "name:khm_x_preferred":[
        "Srae Chrov"
    ],
    "wof:name":"Srae Chrov",
    "wof:placetype":"locality"
},
  "geometry": {"coordinates":[104.36946,10.82769],"type":"Point"}
}