{
  "type": "Feature",
  "properties": {
    "gn:admin1_code":"30",
    "gn:asciiname":"Sla",
    "gn:country_code":"KH",
    "gn:dem":169,
    "gn:feature_class":"P",
    "gn:feature_code":"PPL",
    "gn:name":"Sla",
    "gn:population":0,
    "gn:timezone":"Asia/Phnom_Penh",
    "iso:country":"KH",
    "name:khm_x_preferred":[
        "Sla"
    ],
    "wof:name":"Sla",
    "wof:placetype":"locality"
},
  "geometry": {"coordinates":[102.58743,12.90299],"type":"Point"}
}