{
  "type": "Feature",
  "properties": {
    "gn:admin1_code":"05",
    "gn:asciiname":"Trach",
    "gn:country_code":"KH",
    "gn:dem":17,
    "gn:feature_class":"P",
    "gn:feature_code":"PPL",
    "gn:name":"Trach",
    "gn:population":0,
    "gn:timezone":"Asia/Phnom_Penh",
    "iso:country":"KH",
    "name:khm_x_preferred":[
        "Trach"
    ],
    "name:und_x_variant":[
        "Phum\u012d K\u00e2mtrach"
    ],
    "wof:name":"Trach",
    "wof:placetype":"locality"
},
  "geometry": {"coordinates":[104.56407,12.98396],"type":"Point"}
}