{
  "type": "Feature",
  "properties": {
    "gn:admin1_code":"14",
    "gn:asciiname":"Phumi Kamchay Mea",
    "gn:country_code":"KH",
    "gn:dem":13,
    "gn:feature_class":"P",
    "gn:feature_code":"PPL",
    "gn:name":"Phum\u012d K\u00e2mchay M\u00e9a",
    "gn:population":0,
    "gn:timezone":"Asia/Phnom_Penh",
    "iso:country":"KH",
    "name:und_x_variant":[
        "Phum Komchai Meas",
        "Phum\u012d K\u00e2mchay M\u00e9a"
    ],
    "wof:name":"Phumi Kamchay Mea",
    "wof:placetype":"locality"
},
  "geometry": {"coordinates":[105.68729999999999,11.61344],"type":"Point"}
}