{
  "type": "Feature",
  "properties": {
    "gn:admin1_code":"24.0",
    "gn:asciiname":"Bos Kor",
    "gn:country_code":"KH",
    "gn:dem":17,
    "gn:feature_class":"P",
    "gn:feature_code":"PPL",
    "gn:name":"Bos Kor",
    "gn:population":0,
    "gn:timezone":"Asia/Phnom_Penh",
    "iso:country":"KH",
    "name:khm_x_preferred":[
        "Bos Kor"
    ],
    "wof:name":"Bos Kor",
    "wof:placetype":"locality"
},
  "geometry": {"coordinates":[104.25653,13.15092],"type":"Point"}
}