{
  "type": "Feature",
  "properties": {
    "gn:admin1_code":"25",
    "gn:asciiname":"Keab",
    "gn:country_code":"KH",
    "gn:dem":16,
    "gn:feature_class":"P",
    "gn:feature_code":"PPL",
    "gn:name":"Keab",
    "gn:population":0,
    "gn:timezone":"Asia/Phnom_Penh",
    "iso:country":"KH",
    "name:khm_x_preferred":[
        "Keab"
    ],
    "name:und_x_variant":[
        "Phum Anlong Keap",
        "Phum Amlong Keap",
        "Phum\u012d \u00c2nl\u016dng K\u00e9ap",
        "Phum\u012d \u00c2nl\u00f3ng K\u00e9ab"
    ],
    "wof:name":"Keab",
    "wof:placetype":"locality"
},
  "geometry": {"coordinates":[102.93411999999999,13.58046],"type":"Point"}
}