{
  "type": "Feature",
  "properties": {
    "gn:admin1_code":"02",
    "gn:asciiname":"Prey Khchay",
    "gn:country_code":"KH",
    "gn:dem":16,
    "gn:feature_class":"P",
    "gn:feature_code":"PPL",
    "gn:name":"Prey Khchay",
    "gn:population":0,
    "gn:timezone":"Asia/Phnom_Penh",
    "iso:country":"KH",
    "name:khm_x_preferred":[
        "Prey Khchay"
    ],
    "wof:name":"Prey Khchay",
    "wof:placetype":"locality"
},
  "geometry": {"coordinates":[105.11682999999999,12.03778],"type":"Point"}
}