{
  "type": "Feature",
  "properties": {
    "gn:admin1_code":"00",
    "gn:asciiname":"Phumi Sleng Hang",
    "gn:country_code":"KH",
    "gn:dem":10,
    "gn:feature_class":"P",
    "gn:feature_code":"PPL",
    "gn:name":"Phum\u012d Sl\u00eang H\u00e1ng",
    "gn:population":0,
    "gn:timezone":"Asia/Phnom_Penh",
    "iso:country":"KH",
    "wof:name":"Phumi Sleng Hang",
    "wof:placetype":"locality"
},
  "geometry": {"coordinates":[104.86996000000001,11.36035],"type":"Point"}
}