{
  "type": "Feature",
  "properties": {
    "gn:admin1_code":"03",
    "gn:asciiname":"Phumi Phnum Dom Pit",
    "gn:country_code":"KH",
    "gn:dem":33,
    "gn:feature_class":"P",
    "gn:feature_code":"PPL",
    "gn:name":"Phum\u012d Phnum Dom P\u012dt",
    "gn:population":0,
    "gn:timezone":"Asia/Phnom_Penh",
    "iso:country":"KH",
    "wof:name":"Phumi Phnum Dom Pit",
    "wof:placetype":"locality"
},
  "geometry": {"coordinates":[104.60655,11.92144],"type":"Point"}
}