{
  "type": "Feature",
  "properties": {
    "gn:admin1_code":"28.0",
    "gn:asciiname":"Tuek Thla",
    "gn:country_code":"KH",
    "gn:dem":6,
    "gn:feature_class":"P",
    "gn:feature_code":"PPL",
    "gn:name":"Tuek Thla",
    "gn:population":0,
    "gn:timezone":"Asia/Phnom_Penh",
    "iso:country":"KH",
    "name:khm_x_preferred":[
        "Tuek Thla"
    ],
    "wof:name":"Tuek Thla",
    "wof:placetype":"locality"
},
  "geometry": {"coordinates":[103.91289999999999,10.64548],"type":"Point"}
}