{
  "type": "Feature",
  "properties": {
    "gn:admin1_code":"02",
    "gn:asciiname":"Skon",
    "gn:country_code":"KH",
    "gn:dem":16,
    "gn:feature_class":"P",
    "gn:feature_code":"PPL",
    "gn:name":"Sk\u00f3n",
    "gn:population":0,
    "gn:timezone":"Asia/Phnom_Penh",
    "iso:country":"KH",
    "name:fra_x_preferred":[
        "Skun"
    ],
    "name:ita_x_preferred":[
        "Skoun"
    ],
    "name:rus_x_preferred":[
        "\u0421\u043a\u0443\u043e\u043d"
    ],
    "name:und_x_variant":[
        "Phum\u012d Sk\u00f3n",
        "Poste Skoun Pongro",
        "Skoun",
        "Sk\u00f3n"
    ],
    "wof:name":"Skon",
    "wof:placetype":"locality"
},
  "geometry": {"coordinates":[105.07378,12.0571],"type":"Point"}
}