{
  "type": "Feature",
  "properties": {
    "gn:admin1_code":"29",
    "gn:asciiname":"Phum Rumlech",
    "gn:country_code":"KH",
    "gn:dem":72,
    "gn:feature_class":"P",
    "gn:feature_code":"PPL",
    "gn:name":"Phum R\u016dml\u00e9ch",
    "gn:population":0,
    "gn:timezone":"Asia/Phnom_Penh",
    "iso:country":"KH",
    "name:khm_x_preferred":[
        "Phum R\u016dml\u00e9ch"
    ],
    "name:khm_x_variant":[
        "\u1797\u17bc\u1798\u17b7 \u179a\u17bb\u17c6\u179b\u17c1\u1785"
    ],
    "name:und_x_variant":[
        "Phum Sre Rumlich",
        "Phum\u012d R\u016dml\u00e9ch"
    ],
    "wof:name":"Phum Rumlech",
    "wof:placetype":"locality"
},
  "geometry": {"coordinates":[102.85423,12.86505],"type":"Point"}
}