{
  "type": "Feature",
  "properties": {
    "gn:admin1_code":"22",
    "gn:asciiname":"Phumi Prey Trach",
    "gn:country_code":"KH",
    "gn:dem":15,
    "gn:feature_class":"P",
    "gn:feature_code":"PPL",
    "gn:name":"Phum\u012d Prey Trach",
    "gn:population":0,
    "gn:timezone":"Asia/Phnom_Penh",
    "iso:country":"KH",
    "name:und_x_variant":[
        "Prey Trach",
        "Phum\u012d Prey Trach"
    ],
    "wof:name":"Phumi Prey Trach",
    "wof:placetype":"locality"
},
  "geometry": {"coordinates":[104.8271,11.54167],"type":"Point"}
}