{
  "type": "Feature",
  "properties": {
    "gn:admin1_code":"18",
    "gn:asciiname":"Thnal",
    "gn:country_code":"KH",
    "gn:dem":14,
    "gn:feature_class":"P",
    "gn:feature_code":"PPL",
    "gn:name":"Thnal",
    "gn:population":0,
    "gn:timezone":"Asia/Phnom_Penh",
    "iso:country":"KH",
    "name:khm_x_preferred":[
        "Thnal"
    ],
    "wof:name":"Thnal",
    "wof:placetype":"locality"
},
  "geometry": {"coordinates":[105.70251,11.42829],"type":"Point"}
}