{
  "type": "Feature",
  "properties": {
    "gn:admin1_code":"12.0",
    "gn:asciiname":"Sdok Chum",
    "gn:country_code":"KH",
    "gn:dem":23,
    "gn:feature_class":"P",
    "gn:feature_code":"PPL",
    "gn:name":"Sdok Chum",
    "gn:population":0,
    "gn:timezone":"Asia/Phnom_Penh",
    "iso:country":"KH",
    "name:khm_x_preferred":[
        "Sdok Chum"
    ],
    "wof:name":"Sdok Chum",
    "wof:placetype":"locality"
},
  "geometry": {"coordinates":[103.88782,12.59051],"type":"Point"}
}