{
  "type": "Feature",
  "properties": {
    "gn:admin1_code":"21",
    "gn:asciiname":"Phumi Chrak Sdau",
    "gn:country_code":"KH",
    "gn:dem":4,
    "gn:feature_class":"P",
    "gn:feature_code":"PPL",
    "gn:name":"Phum\u012d Chr\u00e2k Sdau",
    "gn:population":0,
    "gn:timezone":"Asia/Phnom_Penh",
    "iso:country":"KH",
    "wof:name":"Phumi Chrak Sdau",
    "wof:placetype":"locality"
},
  "geometry": {"coordinates":[104.59211999999999,10.65655],"type":"Point"}
}