{
  "type": "Feature",
  "properties": {
    "gn:admin1_code":"29",
    "gn:asciiname":"Phum Baoh Pou",
    "gn:country_code":"KH",
    "gn:dem":15,
    "gn:feature_class":"P",
    "gn:feature_code":"PPL",
    "gn:name":"Phum Ba\u00f4h Po\u016d",
    "gn:population":0,
    "gn:timezone":"Asia/Phnom_Penh",
    "iso:country":"KH",
    "name:khm_x_preferred":[
        "Phum Ba\u00f4h Po\u016d"
    ],
    "name:khm_x_variant":[
        "\u1797\u17bc\u1798\u17b7 \u1794\u17c4\u17c7\u1796\u17c4\u1792\u17b7"
    ],
    "wof:name":"Phum Baoh Pou",
    "wof:placetype":"locality"
},
  "geometry": {"coordinates":[103.21243,13.06015],"type":"Point"}
}