{
  "type": "Feature",
  "properties": {
    "gn:admin1_code":"14",
    "gn:asciiname":"Kanhcham",
    "gn:country_code":"KH",
    "gn:dem":19,
    "gn:feature_class":"P",
    "gn:feature_code":"PPL",
    "gn:name":"Kanhcham",
    "gn:population":0,
    "gn:timezone":"Asia/Phnom_Penh",
    "iso:country":"KH",
    "name:khm_x_preferred":[
        "Kanhcham"
    ],
    "name:und_x_variant":[
        "Phum Kacham",
        "Phum\u012d K\u00e2nch\u014fm",
        "Phum Kancham",
        "Phum\u012d K\u00e2nhchom"
    ],
    "wof:name":"Kanhcham",
    "wof:placetype":"locality"
},
  "geometry": {"coordinates":[105.30422,11.70597],"type":"Point"}
}