{
  "type": "Feature",
  "properties": {
    "gn:admin1_code":"31",
    "gn:asciiname":"Phumi Pouthi Preah Ent",
    "gn:country_code":"KH",
    "gn:dem":30,
    "gn:feature_class":"P",
    "gn:feature_code":"PPL",
    "gn:name":"Phum\u012d Po\u016dth\u012d Pre\u0103h \u0114nt",
    "gn:population":0,
    "gn:timezone":"Asia/Phnom_Penh",
    "iso:country":"KH",
    "name:und_x_variant":[
        "Phum Po Preas En",
        "Phum\u012d Po\u016d Pre\u0103h \u0114n",
        "Phum\u012d Po\u016dth\u012d Pre\u0103h \u0114nt"
    ],
    "wof:name":"Phumi Pouthi Preah Ent",
    "wof:placetype":"locality"
},
  "geometry": {"coordinates":[105.84381999999999,11.80406],"type":"Point"}
}