{
  "type": "Feature",
  "properties": {
    "gn:admin1_code":"02",
    "gn:asciiname":"Phumi Ta Nong Krau",
    "gn:country_code":"KH",
    "gn:dem":20,
    "gn:feature_class":"P",
    "gn:feature_code":"PPL",
    "gn:name":"Phum\u012d Ta N\u00f3ng Krau",
    "gn:population":0,
    "gn:timezone":"Asia/Phnom_Penh",
    "iso:country":"KH",
    "name:und_x_variant":[
        "Phum Deydos",
        "Phum\u012d Ta N\u00f3ng Krau"
    ],
    "wof:name":"Phumi Ta Nong Krau",
    "wof:placetype":"locality"
},
  "geometry": {"coordinates":[105.28534000000001,11.91432],"type":"Point"}
}