{
  "type": "Feature",
  "properties": {
    "gn:admin1_code":"14",
    "gn:asciiname":"Phumi Kaoh Kok",
    "gn:cc2":"KH",
    "gn:country_code":"KH",
    "gn:dem":1,
    "gn:feature_class":"P",
    "gn:feature_code":"PPL",
    "gn:name":"Phum\u012d Ka\u00f4h K\u014fk",
    "gn:population":0,
    "gn:timezone":"Asia/Phnom_Penh",
    "iso:country":"KH",
    "name:und_x_variant":[
        "Kas Kos",
        "Phum\u012d Ka\u00f4h K\u014fk"
    ],
    "wof:name":"Phumi Kaoh Kok",
    "wof:placetype":"locality"
},
  "geometry": {"coordinates":[105.31667,10.86667],"type":"Point"}
}