{
  "type": "Feature",
  "properties": {
    "gn:admin1_code":"02",
    "gn:asciiname":"Phum Veal",
    "gn:country_code":"KH",
    "gn:dem":14,
    "gn:feature_class":"P",
    "gn:feature_code":"PPL",
    "gn:name":"Phum V\u00e9al",
    "gn:population":0,
    "gn:timezone":"Asia/Phnom_Penh",
    "iso:country":"KH",
    "name:khm_x_preferred":[
        "Phum V\u00e9al"
    ],
    "name:khm_x_variant":[
        "\u1797\u17bc\u1798\u17b7\u179a\u17b6\u179b"
    ],
    "name:und_x_variant":[
        "Phum\u012d V\u00e9al"
    ],
    "wof:name":"Phum Veal",
    "wof:placetype":"locality"
},
  "geometry": {"coordinates":[105.01636999999999,12.00385],"type":"Point"}
}