{
  "type": "Feature",
  "properties": {
    "gn:admin1_code":"23",
    "gn:asciiname":"Lung Khung",
    "gn:country_code":"KH",
    "gn:dem":287,
    "gn:feature_class":"P",
    "gn:feature_code":"PPL",
    "gn:name":"Lung Khung",
    "gn:population":0,
    "gn:timezone":"Asia/Phnom_Penh",
    "iso:country":"KH",
    "name:khm_x_preferred":[
        "Lung Khung"
    ],
    "name:und_x_variant":[
        "Phum\u012d L\u016dng Kh\u016dng"
    ],
    "wof:name":"Lung Khung",
    "wof:placetype":"locality"
},
  "geometry": {"coordinates":[107.14581,13.67157],"type":"Point"}
}