{
  "type": "Feature",
  "properties": {
    "gn:admin1_code":"24.0",
    "gn:asciiname":"Phum Taroat",
    "gn:country_code":"KH",
    "gn:dem":24,
    "gn:feature_class":"P",
    "gn:feature_code":"PPL",
    "gn:name":"Phum Taro\u00e2t",
    "gn:population":0,
    "gn:timezone":"Asia/Phnom_Penh",
    "iso:country":"KH",
    "name:khm_x_preferred":[
        "Phum Taro\u00e2t"
    ],
    "name:khm_x_variant":[
        "\u1797\u17bc\u1798\u17b7 \u178f\u17b6\u179a\u17b6\u178f\u17cb"
    ],
    "wof:name":"Phum Taroat",
    "wof:placetype":"locality"
},
  "geometry": {"coordinates":[103.55629,13.61991],"type":"Point"}
}