{
  "type": "Feature",
  "properties": {
    "gn:admin1_code":"29",
    "gn:asciiname":"Phumi Pech Changva",
    "gn:country_code":"KH",
    "gn:dem":34,
    "gn:feature_class":"P",
    "gn:feature_code":"PPL",
    "gn:name":"Phum\u012d P\u00e9ch Ch\u00e2ngva",
    "gn:population":0,
    "gn:timezone":"Asia/Phnom_Penh",
    "iso:country":"KH",
    "wof:name":"Phumi Pech Changva",
    "wof:placetype":"locality"
},
  "geometry": {"coordinates":[102.87661,13.11956],"type":"Point"}
}