{
  "type": "Feature",
  "properties": {
    "gn:admin1_code":"24.0",
    "gn:asciiname":"Phum Prei",
    "gn:country_code":"KH",
    "gn:dem":40,
    "gn:feature_class":"P",
    "gn:feature_code":"PPL",
    "gn:name":"Phum Prei",
    "gn:population":0,
    "gn:timezone":"Asia/Phnom_Penh",
    "iso:country":"KH",
    "name:khm_x_preferred":[
        "Phum Prei"
    ],
    "name:khm_x_variant":[
        "\u1797\u17bc\u1798\u17b7 \u1794\u17d2\u179a\u17b8"
    ],
    "wof:name":"Phum Prei",
    "wof:placetype":"locality"
},
  "geometry": {"coordinates":[103.94240000000001,13.51204],"type":"Point"}
}