{
  "type": "Feature",
  "properties": {
    "gn:admin1_code":"05",
    "gn:asciiname":"Sralau Toung",
    "gn:country_code":"KH",
    "gn:dem":46,
    "gn:feature_class":"P",
    "gn:feature_code":"PPL",
    "gn:name":"Sralau Toung",
    "gn:population":0,
    "gn:timezone":"Asia/Phnom_Penh",
    "iso:country":"KH",
    "name:khm_x_preferred":[
        "Sralau Toung"
    ],
    "name:und_x_variant":[
        "Phum\u012d Sr\u00e2lau Tong"
    ],
    "wof:name":"Sralau Toung",
    "wof:placetype":"locality"
},
  "geometry": {"coordinates":[105.17394,12.42408],"type":"Point"}
}