{
  "type": "Feature",
  "properties": {
    "gn:admin1_code":"07",
    "gn:asciiname":"Kokir Thum",
    "gn:country_code":"KH",
    "gn:dem":12,
    "gn:feature_class":"P",
    "gn:feature_code":"PPL",
    "gn:name":"Kokir Thum",
    "gn:population":0,
    "gn:timezone":"Asia/Phnom_Penh",
    "iso:country":"KH",
    "name:khm_x_preferred":[
        "Kokir Thum"
    ],
    "name:khm_x_variant":[
        "\u1797\u17bc\u1798\u17b7 \u1782\u1782\u17b8\u179a\u1792\u17c6",
        "Phum K\u00f4ki Thom"
    ],
    "name:und_x_variant":[
        "Koky Thom",
        "Phum\u012d K\u00f4ki Thom",
        "Phum Koki Thom",
        "Koh Ky",
        "Phum\u012d K\u00f4kir Thum"
    ],
    "wof:name":"Kokir Thum",
    "wof:placetype":"locality"
},
  "geometry": {"coordinates":[105.24135,11.33272],"type":"Point"}
}