{
  "type": "Feature",
  "properties": {
    "gn:admin1_code":"05",
    "gn:asciiname":"Ba Lat",
    "gn:country_code":"KH",
    "gn:dem":4,
    "gn:feature_class":"P",
    "gn:feature_code":"PPL",
    "gn:name":"Ba Lat",
    "gn:population":0,
    "gn:timezone":"Asia/Phnom_Penh",
    "iso:country":"KH",
    "name:khm_x_preferred":[
        "Ba Lat"
    ],
    "name:khm_x_variant":[
        "\u1797\u17bc\u1798\u17b7 \u1794\u17b6\u17a1\u178f",
        "Phum Bal\u00e2t"
    ],
    "name:und_x_variant":[
        "Phum\u012d Bal\u00e2t"
    ],
    "wof:name":"Ba Lat",
    "wof:placetype":"locality"
},
  "geometry": {"coordinates":[104.3439,12.74614],"type":"Point"}
}