{
  "type": "Feature",
  "properties": {
    "gn:admin1_code":"29",
    "gn:asciiname":"Phum Russei Preah",
    "gn:country_code":"KH",
    "gn:dem":40,
    "gn:feature_class":"P",
    "gn:feature_code":"PPL",
    "gn:name":"Phum R\u016dssei Pre\u0103h",
    "gn:population":0,
    "gn:timezone":"Asia/Phnom_Penh",
    "iso:country":"KH",
    "name:khm_x_preferred":[
        "Phum R\u016dssei Pre\u0103h"
    ],
    "name:khm_x_variant":[
        "\u1797\u17bc\u1798\u17b7 \u17ac\u179f\u17d2\u179f\u17b8\u1796\u17d2\u179a\u17c7"
    ],
    "name:und_x_variant":[
        "Russey Preas",
        "Phum\u012d R\u016dssei Pre\u0103h",
        "Phum\u012d R\u0153ssei Pre\u0103h"
    ],
    "wof:name":"Phum Russei Preah",
    "wof:placetype":"locality"
},
  "geometry": {"coordinates":[103.22772999999999,12.71401],"type":"Point"}
}