{
  "type": "Feature",
  "properties": {
    "gn:admin1_code":"14",
    "gn:asciiname":"Phumi Dondaok",
    "gn:country_code":"KH",
    "gn:dem":20,
    "gn:feature_class":"P",
    "gn:feature_code":"PPL",
    "gn:name":"Phum\u012d Donda\u00f4k",
    "gn:population":0,
    "gn:timezone":"Asia/Phnom_Penh",
    "iso:country":"KH",
    "name:und_x_variant":[
        "Phum Andoi",
        "Phum\u012d Donda\u00f4k"
    ],
    "wof:name":"Phumi Dondaok",
    "wof:placetype":"locality"
},
  "geometry": {"coordinates":[105.65664,11.6944],"type":"Point"}
}