{
  "type": "Feature",
  "properties": {
    "gn:admin1_code":"03",
    "gn:asciiname":"Phumi Robang Thi",
    "gn:country_code":"KH",
    "gn:dem":21,
    "gn:feature_class":"P",
    "gn:feature_code":"PPL",
    "gn:name":"Phum\u012d R\u00f4b\u00e2ng Thi",
    "gn:population":0,
    "gn:timezone":"Asia/Phnom_Penh",
    "iso:country":"KH",
    "name:und_x_variant":[
        "Robang Thi",
        "Phum\u012d R\u00f4b\u00e2ng Thi"
    ],
    "wof:name":"Phumi Robang Thi",
    "wof:placetype":"locality"
},
  "geometry": {"coordinates":[104.59927,12.30001],"type":"Point"}
}