{
  "type": "Feature",
  "properties": {
    "gn:admin1_code":"25",
    "gn:asciiname":"Laote",
    "gn:country_code":"KH",
    "gn:dem":18,
    "gn:feature_class":"P",
    "gn:feature_code":"PPL",
    "gn:name":"Laote",
    "gn:population":0,
    "gn:timezone":"Asia/Phnom_Penh",
    "iso:country":"KH",
    "name:khm_x_preferred":[
        "Laote"
    ],
    "name:khm_x_variant":[
        "\u1797\u17bc\u1798\u17b7 \u17a1\u17c4\u1791\u17d2\u1799\u17c1",
        "Phum La\u00f4 Ti\u0115"
    ],
    "name:und_x_variant":[
        "Phum\u012d La\u00f4 Ti\u0115"
    ],
    "wof:name":"Laote",
    "wof:placetype":"locality"
},
  "geometry": {"coordinates":[103.3382,13.61428],"type":"Point"}
}