{
  "type": "Feature",
  "properties": {
    "gn:admin1_code":"02",
    "gn:asciiname":"Pramat Dei",
    "gn:country_code":"KH",
    "gn:dem":60,
    "gn:feature_class":"P",
    "gn:feature_code":"PPL",
    "gn:name":"Pramat Dei",
    "gn:population":0,
    "gn:timezone":"Asia/Phnom_Penh",
    "iso:country":"KH",
    "name:khm_x_preferred":[
        "Pramat Dei"
    ],
    "wof:name":"Pramat Dei",
    "wof:placetype":"locality"
},
  "geometry": {"coordinates":[105.28362,12.3018],"type":"Point"}
}