{
  "type": "Feature",
  "properties": {
    "gn:admin1_code":"29",
    "gn:asciiname":"Phnum Proek",
    "gn:country_code":"KH",
    "gn:dem":393,
    "gn:feature_class":"P",
    "gn:feature_code":"PPL",
    "gn:name":"Phnum Proek",
    "gn:population":0,
    "gn:timezone":"Asia/Phnom_Penh",
    "iso:country":"KH",
    "name:khm_x_preferred":[
        "Phn\u016dm Pr\u0153\u0306ks"
    ],
    "name:khm_x_variant":[
        "\u1797\u17d2\u1793\u17c6\u1796\u17d2\u179a\u17b9\u1780"
    ],
    "name:vie_x_preferred":[
        "Phnum Proek"
    ],
    "wof:name":"Phnum Proek",
    "wof:placetype":"locality"
},
  "geometry": {"coordinates":[102.37307,13.29715],"type":"Point"}
}