{
  "type": "Feature",
  "properties": {
    "gn:admin1_code":"24.0",
    "gn:asciiname":"Svay Dangkum",
    "gn:country_code":"KH",
    "gn:dem":19,
    "gn:feature_class":"P",
    "gn:feature_code":"PPL",
    "gn:name":"Svay Dangkum",
    "gn:population":0,
    "gn:timezone":"Asia/Phnom_Penh",
    "iso:country":"KH",
    "name:khm_x_preferred":[
        "Svay Dangkum"
    ],
    "name:khm_x_variant":[
        "\u1797\u17bc\u1798\u17b7 \u179f\u17d2\u179c\u17b6\u1799\u1787\u1784\u17d2\u1782\u17c6",
        "Phum Svay D\u00e2ngk\u016dm"
    ],
    "wof:name":"Svay Dangkum",
    "wof:placetype":"locality"
},
  "geometry": {"coordinates":[103.84918999999999,13.36269],"type":"Point"}
}