{
  "type": "Feature",
  "properties": {
    "gn:admin1_code":"29",
    "gn:asciiname":"Veal Trea",
    "gn:country_code":"KH",
    "gn:dem":17,
    "gn:feature_class":"P",
    "gn:feature_code":"PPL",
    "gn:name":"Veal Trea",
    "gn:population":0,
    "gn:timezone":"Asia/Phnom_Penh",
    "iso:country":"KH",
    "name:khm_x_preferred":[
        "\u1797\u17bc\u1798\u17b7 \u179c\u17b6\u179b\u1791\u17d2\u179a\u17b6"
    ],
    "name:khm_x_variant":[
        "Phum V\u00e9al Tr\u00e9a"
    ],
    "name:und_x_variant":[
        "Veal Trear",
        "Phum\u012d V\u00e9al Tr\u00e9a"
    ],
    "wof:name":"Veal Trea",
    "wof:placetype":"locality"
},
  "geometry": {"coordinates":[103.11044,13.19406],"type":"Point"}
}