{
  "type": "Feature",
  "properties": {
    "gn:admin1_code":"29",
    "gn:asciiname":"Phum Thma Phot",
    "gn:country_code":"KH",
    "gn:dem":17,
    "gn:feature_class":"P",
    "gn:feature_code":"PPL",
    "gn:name":"Phum Thm\u00e2 Ph\u014ft",
    "gn:population":0,
    "gn:timezone":"Asia/Phnom_Penh",
    "iso:country":"KH",
    "name:khm_x_preferred":[
        "Phum Thm\u00e2 Ph\u014ft"
    ],
    "name:khm_x_variant":[
        "\u1797\u17bc\u1798\u17b7 \u1790\u17d2\u1798\u1795\u17bb\u178f"
    ],
    "wof:name":"Phum Thma Phot",
    "wof:placetype":"locality"
},
  "geometry": {"coordinates":[103.20641999999999,13.06508],"type":"Point"}
}