{
  "type": "Feature",
  "properties": {
    "gn:admin1_code":"28",
    "gn:asciiname":"Phumi Bat Trang",
    "gn:country_code":"KH",
    "gn:dem":0,
    "gn:feature_class":"P",
    "gn:feature_code":"PPL",
    "gn:name":"Phum\u012d B\u00e1t Tr\u00e1ng",
    "gn:population":0,
    "gn:timezone":"Asia/Phnom_Penh",
    "iso:country":"KH",
    "wof:name":"Phumi Bat Trang",
    "wof:placetype":"locality"
},
  "geometry": {"coordinates":[103.63782,10.589],"type":"Point"}
}