{
  "type": "Feature",
  "properties": {
    "gn:admin1_code":"26",
    "gn:asciiname":"Phumi Phnum Asea",
    "gn:country_code":"KH",
    "gn:dem":6,
    "gn:feature_class":"P",
    "gn:feature_code":"PPL",
    "gn:name":"Phum\u012d Phnum As\u00e9a",
    "gn:population":0,
    "gn:timezone":"Asia/Phnom_Penh",
    "iso:country":"KH",
    "name:und_x_variant":[
        "Phum A Sea",
        "Phum\u012d Phnum As\u00e9a"
    ],
    "wof:name":"Phumi Phnum Asea",
    "wof:placetype":"locality"
},
  "geometry": {"coordinates":[104.28419,10.55684],"type":"Point"}
}