{
  "type": "Feature",
  "properties": {
    "gn:admin1_code":"18",
    "gn:asciiname":"Phumi Khuoch",
    "gn:country_code":"KH",
    "gn:dem":9,
    "gn:feature_class":"P",
    "gn:feature_code":"PPL",
    "gn:name":"Phum\u012d Khu\u014fch",
    "gn:population":0,
    "gn:timezone":"Asia/Phnom_Penh",
    "iso:country":"KH",
    "name:und_x_variant":[
        "Phum Khouch",
        "Phum\u012d Khu\u014fch"
    ],
    "wof:name":"Phumi Khuoch",
    "wof:placetype":"locality"
},
  "geometry": {"coordinates":[105.65682,11.16547],"type":"Point"}
}