{
  "type": "Feature",
  "properties": {
    "gn:admin1_code":"02",
    "gn:asciiname":"Phumi Kamreng",
    "gn:country_code":"KH",
    "gn:dem":13,
    "gn:feature_class":"P",
    "gn:feature_code":"PPL",
    "gn:name":"Phum\u012d K\u00e2mr\u00eang",
    "gn:population":0,
    "gn:timezone":"Asia/Phnom_Penh",
    "iso:country":"KH",
    "name:und_x_variant":[
        "Komreng",
        "Phum\u012d K\u00e2mr\u00eang"
    ],
    "wof:name":"Phumi Kamreng",
    "wof:placetype":"locality"
},
  "geometry": {"coordinates":[104.96211,12.06706],"type":"Point"}
}