{
  "type": "Feature",
  "properties": {
    "gn:admin1_code":"04",
    "gn:asciiname":"Tang Kumpir",
    "gn:country_code":"KH",
    "gn:dem":54,
    "gn:feature_class":"P",
    "gn:feature_code":"PPL",
    "gn:name":"Tang Kumpir",
    "gn:population":0,
    "gn:timezone":"Asia/Phnom_Penh",
    "iso:country":"KH",
    "name:khm_x_preferred":[
        "Tang Kumpir"
    ],
    "wof:name":"Tang Kumpir",
    "wof:placetype":"locality"
},
  "geometry": {"coordinates":[104.40452000000001,11.48434],"type":"Point"}
}