{
  "type": "Feature",
  "properties": {
    "gn:admin1_code":"18",
    "gn:asciiname":"Sambat Mean Chey",
    "gn:country_code":"KH",
    "gn:dem":13,
    "gn:feature_class":"P",
    "gn:feature_code":"PPL",
    "gn:name":"Sambat Mean Chey",
    "gn:population":0,
    "gn:timezone":"Asia/Phnom_Penh",
    "iso:country":"KH",
    "name:khm_x_preferred":[
        "Sambat Mean Chey"
    ],
    "wof:name":"Sambat Mean Chey",
    "wof:placetype":"locality"
},
  "geometry": {"coordinates":[105.67534999999999,11.44734],"type":"Point"}
}