{
  "type": "Feature",
  "properties": {
    "gn:admin1_code":"14.0",
    "gn:asciiname":"Phum Tileng",
    "gn:country_code":"KH",
    "gn:dem":13,
    "gn:feature_class":"P",
    "gn:feature_code":"PPL",
    "gn:name":"Phum Til\u00e9ng",
    "gn:population":0,
    "gn:timezone":"Asia/Phnom_Penh",
    "iso:country":"KH",
    "name:khm_x_preferred":[
        "Phum Til\u00e9ng"
    ],
    "name:khm_x_variant":[
        "\u1797\u17bc\u1798\u17b7 \u1791\u17b8\u179b\u17c1\u1784"
    ],
    "wof:name":"Phum Tileng",
    "wof:placetype":"locality"
},
  "geometry": {"coordinates":[105.39939,11.34385],"type":"Point"}
}