{
  "type": "Feature",
  "properties": {
    "gn:admin1_code":"14",
    "gn:asciiname":"Spueu Lech",
    "gn:country_code":"KH",
    "gn:dem":10,
    "gn:feature_class":"P",
    "gn:feature_code":"PPL",
    "gn:name":"Spueu Lech",
    "gn:population":0,
    "gn:timezone":"Asia/Phnom_Penh",
    "iso:country":"KH",
    "name:khm_x_preferred":[
        "Spueu Lech"
    ],
    "name:khm_x_variant":[
        "Phum Sp\u0153",
        "\u1797\u17bc\u1798\u17b7 \u179f\u17d2\u1796\u17ba"
    ],
    "name:und_x_variant":[
        "Phum Speu",
        "Phum\u012d Sp\u0153"
    ],
    "wof:name":"Spueu Lech",
    "wof:placetype":"locality"
},
  "geometry": {"coordinates":[105.46607,11.25986],"type":"Point"}
}