{
  "type": "Feature",
  "properties": {
    "gn:admin1_code":"29",
    "gn:asciiname":"Phum O Mat",
    "gn:country_code":"KH",
    "gn:dem":15,
    "gn:feature_class":"P",
    "gn:feature_code":"PPL",
    "gn:name":"Phum O Mat",
    "gn:population":0,
    "gn:timezone":"Asia/Phnom_Penh",
    "iso:country":"KH",
    "name:khm_x_preferred":[
        "Phum O Mat"
    ],
    "name:khm_x_variant":[
        "\u1797\u17bc\u1798\u17b7 \u17a2\u17bc\u1798\u17c9\u17b6\u178f"
    ],
    "name:und_x_variant":[
        "Phum\u012d O Mat"
    ],
    "wof:name":"Phum O Mat",
    "wof:placetype":"locality"
},
  "geometry": {"coordinates":[103.01231,13.24642],"type":"Point"}
}