{
  "type": "Feature",
  "properties": {
    "gn:admin1_code":"12",
    "gn:asciiname":"Phum Sre Peang",
    "gn:country_code":"KH",
    "gn:dem":227,
    "gn:feature_class":"P",
    "gn:feature_code":"PPL",
    "gn:name":"Phum Sr\u00ea Pe\u0103ng",
    "gn:population":0,
    "gn:timezone":"Asia/Phnom_Penh",
    "iso:country":"KH",
    "name:khm_x_preferred":[
        "Phum Sr\u00ea Pe\u0103ng"
    ],
    "name:khm_x_variant":[
        "\u1797\u17bc\u1798\u17b7 \u179f\u17d2\u179a\u17c2\u1796\u17b6\u1784\u17cb"
    ],
    "name:und_x_variant":[
        "Sre Poang",
        "Sa Peang",
        "Sre Peang",
        "Phum\u012d Sr\u00ea Pe\u0103ng",
        "Sr\u00ea Pe\u0103ng"
    ],
    "wof:name":"Phum Sre Peang",
    "wof:placetype":"locality"
},
  "geometry": {"coordinates":[103.24438000000001,12.37731],"type":"Point"}
}