{
  "type": "Feature",
  "properties": {
    "gn:admin1_code":"05",
    "gn:asciiname":"Phumi Preah Sneng",
    "gn:country_code":"KH",
    "gn:dem":11,
    "gn:feature_class":"P",
    "gn:feature_code":"PPL",
    "gn:name":"Phum\u012d Pre\u0103h Sn\u00eang",
    "gn:population":0,
    "gn:timezone":"Asia/Phnom_Penh",
    "iso:country":"KH",
    "name:und_x_variant":[
        "Beng Prah Sleng",
        "Phum\u012d Pre\u0103h Sn\u00eang"
    ],
    "wof:name":"Phumi Preah Sneng",
    "wof:placetype":"locality"
},
  "geometry": {"coordinates":[104.70594,12.68173],"type":"Point"}
}