{
  "type": "Feature",
  "properties": {
    "gn:admin1_code":"12",
    "gn:asciiname":"Doung Chuor",
    "gn:country_code":"KH",
    "gn:dem":17,
    "gn:feature_class":"P",
    "gn:feature_code":"PPL",
    "gn:name":"Doung Chuor",
    "gn:population":0,
    "gn:timezone":"Asia/Phnom_Penh",
    "iso:country":"KH",
    "name:khm_x_preferred":[
        "Doung Chuor"
    ],
    "wof:name":"Doung Chuor",
    "wof:placetype":"locality"
},
  "geometry": {"coordinates":[104.12188999999999,12.553],"type":"Point"}
}