{
  "type": "Feature",
  "properties": {
    "gn:admin1_code":"14",
    "gn:asciiname":"Chong Ampil",
    "gn:country_code":"KH",
    "gn:dem":20,
    "gn:feature_class":"P",
    "gn:feature_code":"PPL",
    "gn:name":"Chong Ampil",
    "gn:population":0,
    "gn:timezone":"Asia/Phnom_Penh",
    "iso:country":"KH",
    "name:khm_x_preferred":[
        "Chong Ampil"
    ],
    "name:und_x_variant":[
        "Phum\u012d Ch\u014fng \u00c2mp\u012dl"
    ],
    "wof:name":"Chong Ampil",
    "wof:placetype":"locality"
},
  "geometry": {"coordinates":[105.42046000000001,11.65896],"type":"Point"}
}