{
  "type": "Feature",
  "properties": {
    "gn:admin1_code":"27",
    "gn:asciiname":"Tumnob Leu",
    "gn:country_code":"KH",
    "gn:dem":72,
    "gn:feature_class":"P",
    "gn:feature_code":"PPL",
    "gn:name":"Tumnob Leu",
    "gn:population":0,
    "gn:timezone":"Asia/Phnom_Penh",
    "iso:country":"KH",
    "name:khm_x_preferred":[
        "Tumnob Leu"
    ],
    "wof:name":"Tumnob Leu",
    "wof:placetype":"locality"
},
  "geometry": {"coordinates":[104.10398000000001,14.30893],"type":"Point"}
}