{
  "type": "Feature",
  "properties": {
    "gn:admin1_code":"28",
    "gn:asciiname":"Phum Donghet",
    "gn:country_code":"KH",
    "gn:dem":6,
    "gn:feature_class":"P",
    "gn:feature_code":"PPL",
    "gn:name":"Phum Donghet",
    "gn:population":0,
    "gn:timezone":"Asia/Phnom_Penh",
    "iso:country":"KH",
    "name:khm_x_preferred":[
        "Phum D\u00e2ngh\u0153\u0306t"
    ],
    "name:khm_x_variant":[
        "\u1797\u17bc\u1798\u17b7 \u178a\u1784\u17d2\u17a0\u17b7\u178f"
    ],
    "name:und_x_variant":[
        "Phum\u012d D\u00e2ngh\u0115t"
    ],
    "wof:name":"Phum Donghet",
    "wof:placetype":"locality"
},
  "geometry": {"coordinates":[103.85021,10.76606],"type":"Point"}
}