{
  "type": "Feature",
  "properties": {
    "gn:admin1_code":"08",
    "gn:asciiname":"Veal",
    "gn:country_code":"KH",
    "gn:dem":8,
    "gn:feature_class":"P",
    "gn:feature_code":"PPL",
    "gn:name":"Veal",
    "gn:population":0,
    "gn:timezone":"Asia/Phnom_Penh",
    "iso:country":"KH",
    "name:khm_x_preferred":[
        "Veal"
    ],
    "name:und_x_variant":[
        "Phum\u012d V\u00e9al"
    ],
    "wof:name":"Veal",
    "wof:placetype":"locality"
},
  "geometry": {"coordinates":[103.90648,11.07793],"type":"Point"}
}