{
  "type": "Feature",
  "properties": {
    "gn:admin1_code":"19",
    "gn:asciiname":"Phumi Tram Kak",
    "gn:country_code":"KH",
    "gn:dem":29,
    "gn:feature_class":"P",
    "gn:feature_code":"PPL",
    "gn:name":"Phum\u012d Tr\u0103m K\u00e1k",
    "gn:population":0,
    "gn:timezone":"Asia/Phnom_Penh",
    "iso:country":"KH",
    "name:und_x_variant":[
        "Tram Kak",
        "Phum Tram Kok",
        "Tram Kok",
        "Phum\u012d Tr\u0103m K\u00e1k"
    ],
    "wof:name":"Phumi Tram Kak",
    "wof:placetype":"locality"
},
  "geometry": {"coordinates":[104.58932,10.91159],"type":"Point"}
}