{
  "type": "Feature",
  "properties": {
    "gn:admin1_code":"09",
    "gn:asciiname":"Dang Kdaong",
    "gn:country_code":"KH",
    "gn:dem":26,
    "gn:feature_class":"P",
    "gn:feature_code":"PPL",
    "gn:name":"Dang Kdaong",
    "gn:population":0,
    "gn:timezone":"Asia/Phnom_Penh",
    "iso:country":"KH",
    "name:khm_x_preferred":[
        "Dang Kdaong"
    ],
    "name:khm_x_variant":[
        "\u1797\u17bc\u1798\u17b7 \u178a\u1784\u1780\u17d2\u178f\u17c4\u1784",
        "Phum D\u00e2ng Kda\u00f4ng"
    ],
    "name:und_x_variant":[
        "Phum Dong Khdong",
        "Phum\u012d D\u00e2ng Kda\u00f4ng"
    ],
    "wof:name":"Dang Kdaong",
    "wof:placetype":"locality"
},
  "geometry": {"coordinates":[105.89942000000001,12.2546],"type":"Point"}
}