{
  "type": "Feature",
  "properties": {
    "gn:admin1_code":"24.0",
    "gn:asciiname":"Kanhchon Chrov",
    "gn:country_code":"KH",
    "gn:dem":17,
    "gn:feature_class":"P",
    "gn:feature_code":"PPL",
    "gn:name":"Kanhchon Chrov",
    "gn:population":0,
    "gn:timezone":"Asia/Phnom_Penh",
    "iso:country":"KH",
    "name:khm_x_preferred":[
        "Kanhchon Chrov"
    ],
    "wof:name":"Kanhchon Chrov",
    "wof:placetype":"locality"
},
  "geometry": {"coordinates":[103.52152,13.60886],"type":"Point"}
}