{
  "type": "Feature",
  "properties": {
    "gn:admin1_code":"05",
    "gn:asciiname":"Thnal Baek",
    "gn:country_code":"KH",
    "gn:dem":21,
    "gn:feature_class":"P",
    "gn:feature_code":"PPL",
    "gn:name":"Thnal Baek",
    "gn:population":0,
    "gn:timezone":"Asia/Phnom_Penh",
    "iso:country":"KH",
    "name:khm_x_preferred":[
        "Thnal Baek"
    ],
    "name:und_x_variant":[
        "Thnol Bek",
        "Phum\u012d Thn\u00e1l B\u00eak"
    ],
    "wof:name":"Thnal Baek",
    "wof:placetype":"locality"
},
  "geometry": {"coordinates":[104.90819,12.74735],"type":"Point"}
}