{
  "type": "Feature",
  "properties": {
    "gn:admin1_code":"12",
    "gn:asciiname":"Phum Kbal Teahean",
    "gn:country_code":"KH",
    "gn:dem":81,
    "gn:feature_class":"P",
    "gn:feature_code":"PPL",
    "gn:name":"Phum Kbal T\u00e9ah\u00e9an",
    "gn:population":0,
    "gn:timezone":"Asia/Phnom_Penh",
    "iso:country":"KH",
    "name:khm_x_preferred":[
        "Phum Kbal T\u00e9ah\u00e9an"
    ],
    "name:khm_x_variant":[
        "\u1797\u17bc\u1798\u17b7 \u1780\u17d2\u1794\u17b6\u179b\u1791\u17b6\u17a0\u17b6\u1793"
    ],
    "name:und_x_variant":[
        "Phum Kbal Tea Heam",
        "Phum\u012d Kbal T\u00e9ah\u00e9an"
    ],
    "wof:name":"Phum Kbal Teahean",
    "wof:placetype":"locality"
},
  "geometry": {"coordinates":[104.1557,12.24579],"type":"Point"}
}