{
  "type": "Feature",
  "properties": {
    "gn:admin1_code":"23",
    "gn:asciiname":"Srae Chhuk",
    "gn:country_code":"KH",
    "gn:dem":99,
    "gn:feature_class":"P",
    "gn:feature_code":"PPL",
    "gn:name":"Srae Chhuk",
    "gn:population":0,
    "gn:timezone":"Asia/Phnom_Penh",
    "iso:country":"KH",
    "name:khm_x_preferred":[
        "Srae Chhuk"
    ],
    "name:khm_x_variant":[
        "\u1797\u17bc\u1798\u17b7 \u179f\u17d2\u179a\u17c2\u1788\u17bc\u1780",
        "Phum\u012d Sr\u00ea Chhuk"
    ],
    "wof:name":"Srae Chhuk",
    "wof:placetype":"locality"
},
  "geometry": {"coordinates":[106.94025000000001,13.48916],"type":"Point"}
}