{
  "type": "Feature",
  "properties": {
    "gn:admin1_code":"02",
    "gn:asciiname":"Phumi Kev Romuol",
    "gn:country_code":"KH",
    "gn:dem":52,
    "gn:feature_class":"P",
    "gn:feature_code":"PPL",
    "gn:name":"Phum\u012d K\u00eav R\u00f4mu\u014fl",
    "gn:population":0,
    "gn:timezone":"Asia/Phnom_Penh",
    "iso:country":"KH",
    "name:und_x_variant":[
        "Vat Romeul",
        "Phum\u012d K\u00eav Ramu\u014fl",
        "Phum\u012d K\u00eav R\u00f4mu\u014fl"
    ],
    "wof:name":"Phumi Kev Romuol",
    "wof:placetype":"locality"
},
  "geometry": {"coordinates":[105.44607999999999,12.04174],"type":"Point"}
}