{
  "type": "Feature",
  "properties": {
    "gn:admin1_code":"14",
    "gn:asciiname":"Phumi Krala Meakh",
    "gn:country_code":"KH",
    "gn:dem":19,
    "gn:feature_class":"P",
    "gn:feature_code":"PPL",
    "gn:name":"Phum\u012d Kr\u00e2la M\u00e9akh",
    "gn:population":0,
    "gn:timezone":"Asia/Phnom_Penh",
    "iso:country":"KH",
    "name:und_x_variant":[
        "Phum Kralo Meas",
        "Phum\u012d Kr\u00e2la M\u00e9ak",
        "Phum\u012d Kr\u00e2la M\u00e9akh"
    ],
    "wof:name":"Phumi Krala Meakh",
    "wof:placetype":"locality"
},
  "geometry": {"coordinates":[105.52251,11.74631],"type":"Point"}
}