{
  "type": "Feature",
  "properties": {
    "gn:admin1_code":"28",
    "gn:asciiname":"Bet Trang",
    "gn:country_code":"KH",
    "gn:dem":30,
    "gn:feature_class":"P",
    "gn:feature_code":"PPL",
    "gn:name":"Bet Trang",
    "gn:population":0,
    "gn:timezone":"Asia/Phnom_Penh",
    "iso:country":"KH",
    "name:khm_x_preferred":[
        "Bet Trang"
    ],
    "name:und_x_variant":[
        "Batruong",
        "Phum\u012d B\u00e1t Tr\u00e1ng"
    ],
    "wof:name":"Bet Trang",
    "wof:placetype":"locality"
},
  "geometry": {"coordinates":[103.62246,10.60721],"type":"Point"}
}