{
  "type": "Feature",
  "properties": {
    "gn:admin1_code":"14",
    "gn:asciiname":"Phumi Pouthi Khpos",
    "gn:country_code":"KH",
    "gn:dem":11,
    "gn:feature_class":"P",
    "gn:feature_code":"PPL",
    "gn:name":"Phum\u012d Po\u016dth\u012d Khp\u00f3s",
    "gn:population":0,
    "gn:timezone":"Asia/Phnom_Penh",
    "iso:country":"KH",
    "name:und_x_variant":[
        "Phum Po Khpos",
        "Phum\u012d Po\u016d Khpu\u014fs",
        "Phum\u012d Po\u016dth\u012d Khp\u00f3s"
    ],
    "wof:name":"Phumi Pouthi Khpos",
    "wof:placetype":"locality"
},
  "geometry": {"coordinates":[105.3092,11.01602],"type":"Point"}
}