{
  "type": "Feature",
  "properties": {
    "gn:admin1_code":"02",
    "gn:asciiname":"Ta Ley",
    "gn:country_code":"KH",
    "gn:dem":27,
    "gn:feature_class":"P",
    "gn:feature_code":"PPL",
    "gn:name":"Ta Ley",
    "gn:population":0,
    "gn:timezone":"Asia/Phnom_Penh",
    "iso:country":"KH",
    "name:khm_x_preferred":[
        "Ta Ley"
    ],
    "name:und_x_variant":[
        "Phum\u012d Tak\u00eay",
        "Phum\u012d Tak\u00eav"
    ],
    "wof:name":"Ta Ley",
    "wof:placetype":"locality"
},
  "geometry": {"coordinates":[105.22337,12.11839],"type":"Point"}
}