{
  "type": "Feature",
  "properties": {
    "gn:admin1_code":"25",
    "gn:asciiname":"Tbaeng",
    "gn:country_code":"KH",
    "gn:dem":25,
    "gn:feature_class":"P",
    "gn:feature_code":"PPL",
    "gn:name":"Tbaeng",
    "gn:population":0,
    "gn:timezone":"Asia/Phnom_Penh",
    "iso:country":"KH",
    "name:khm_x_preferred":[
        "Tbaeng"
    ],
    "name:khm_x_variant":[
        "\u1797\u17bc\u1798\u17b7 \u178f\u17d2\u1794\u17c2\u1784",
        "Phum Tb\u00eang"
    ],
    "name:und_x_variant":[
        "Phum\u012d Tb\u00eang"
    ],
    "wof:name":"Tbaeng",
    "wof:placetype":"locality"
},
  "geometry": {"coordinates":[103.12402,13.69172],"type":"Point"}
}