{
  "type": "Feature",
  "properties": {
    "gn:admin1_code":"05",
    "gn:asciiname":"Phum Phtoul",
    "gn:country_code":"KH",
    "gn:dem":10,
    "gn:feature_class":"P",
    "gn:feature_code":"PPL",
    "gn:name":"Phum Phto\u016dl",
    "gn:population":0,
    "gn:timezone":"Asia/Phnom_Penh",
    "iso:country":"KH",
    "name:khm_x_preferred":[
        "Phum Phto\u016dl"
    ],
    "name:khm_x_variant":[
        "Phum\u012d Phto\u016dl"
    ],
    "wof:name":"Phum Phtoul",
    "wof:placetype":"locality"
},
  "geometry": {"coordinates":[104.47087000000001,12.74192],"type":"Point"}
}