{
  "type": "Feature",
  "properties": {
    "gn:admin1_code":"21",
    "gn:asciiname":"Phumi Kaoh Sla",
    "gn:country_code":"KH",
    "gn:dem":35,
    "gn:feature_class":"P",
    "gn:feature_code":"PPL",
    "gn:name":"Phum\u012d Ka\u00f4h Sla",
    "gn:population":0,
    "gn:timezone":"Asia/Phnom_Penh",
    "iso:country":"KH",
    "wof:name":"Phumi Kaoh Sla",
    "wof:placetype":"locality"
},
  "geometry": {"coordinates":[104.24888,10.91074],"type":"Point"}
}