{
  "type": "Feature",
  "properties": {
    "gn:admin1_code":"14",
    "gn:asciiname":"Phum Trapeang Ed",
    "gn:country_code":"KH",
    "gn:dem":12,
    "gn:feature_class":"P",
    "gn:feature_code":"PPL",
    "gn:name":"Phum Tr\u00e2pe\u0103ng \u0114d",
    "gn:population":0,
    "gn:timezone":"Asia/Phnom_Penh",
    "iso:country":"KH",
    "name:khm_x_preferred":[
        "Phum\u012d Tr\u00e2pe\u0103ng \u0114d"
    ],
    "name:khm_x_variant":[
        "Phum Tr\u00e2pe\u0103ng \u0114d",
        "\u1797\u17bc\u1798\u17b7 \u178f\u17d2\u179a\u1796\u17b6\u17c6\u1784\u17a2\u17b7\u178a\u17d2\u178b"
    ],
    "name:und_x_variant":[
        "Phum Trapeang Et",
        "Phum\u012d Tr\u00e2pe\u0103ng \u0114dth"
    ],
    "wof:name":"Phum Trapeang Ed",
    "wof:placetype":"locality"
},
  "geometry": {"coordinates":[105.46051,11.42991],"type":"Point"}
}