{
  "type": "Feature",
  "properties": {
    "gn:admin1_code":"24",
    "gn:asciiname":"Tnaot Chrum",
    "gn:country_code":"KH",
    "gn:dem":28,
    "gn:feature_class":"P",
    "gn:feature_code":"PPL",
    "gn:name":"Tnaot Chrum",
    "gn:population":0,
    "gn:timezone":"Asia/Phnom_Penh",
    "iso:country":"KH",
    "name:khm_x_preferred":[
        "Tnaot Chrum"
    ],
    "name:khm_x_variant":[
        "Phum Tna\u00f4t Chr\u016dm"
    ],
    "name:und_x_variant":[
        "Phum Thnot Chrum",
        "Phum Thnol Chrum",
        "Phum Thnel Carum",
        "Phum\u012d Tna\u00f4t Chr\u016dm"
    ],
    "wof:name":"Tnaot Chrum",
    "wof:placetype":"locality"
},
  "geometry": {"coordinates":[103.78740000000001,13.48554],"type":"Point"}
}