{
  "type": "Feature",
  "properties": {
    "gn:admin1_code":"04",
    "gn:asciiname":"Phum Svay",
    "gn:country_code":"KH",
    "gn:dem":46,
    "gn:feature_class":"P",
    "gn:feature_code":"PPL",
    "gn:name":"Phum Svay",
    "gn:population":0,
    "gn:timezone":"Asia/Phnom_Penh",
    "iso:country":"KH",
    "name:und_x_variant":[
        "Phum\u012d T\u0153\u0306k R\u016dssei",
        "Phum\u012d T\u0153\u0306k R\u0153ssei"
    ],
    "wof:name":"Phum Svay",
    "wof:placetype":"locality"
},
  "geometry": {"coordinates":[104.56717,11.67827],"type":"Point"}
}