{
  "type": "Feature",
  "properties": {
    "gn:admin1_code":"29",
    "gn:asciiname":"Phumi Don Ngin",
    "gn:country_code":"KH",
    "gn:dem":17,
    "gn:feature_class":"P",
    "gn:feature_code":"PPL",
    "gn:name":"Phum\u012d Don Ng\u012dn",
    "gn:population":0,
    "gn:timezone":"Asia/Phnom_Penh",
    "iso:country":"KH",
    "wof:name":"Phumi Don Ngin",
    "wof:placetype":"locality"
},
  "geometry": {"coordinates":[102.95652,13.23098],"type":"Point"}
}