{
  "type": "Feature",
  "properties": {
    "gn:admin1_code":"29",
    "gn:asciiname":"Beng Sat",
    "gn:country_code":"KH",
    "gn:dem":240,
    "gn:feature_class":"P",
    "gn:feature_code":"PPL",
    "gn:name":"Beng Sat",
    "gn:population":0,
    "gn:timezone":"Asia/Phnom_Penh",
    "iso:country":"KH",
    "name:khm_x_preferred":[
        "Beng Sat"
    ],
    "wof:name":"Beng Sat",
    "wof:placetype":"locality"
},
  "geometry": {"coordinates":[102.36355,13.30735],"type":"Point"}
}