{
  "type": "Feature",
  "properties": {
    "gn:admin1_code":"28.0",
    "gn:asciiname":"Phum Kampong Kranhung",
    "gn:country_code":"KH",
    "gn:dem":4,
    "gn:feature_class":"P",
    "gn:feature_code":"PPL",
    "gn:name":"Phum K\u00e2mp\u00f4ng Kr\u00e2nhung",
    "gn:population":0,
    "gn:timezone":"Asia/Phnom_Penh",
    "iso:country":"KH",
    "name:khm_x_preferred":[
        "Phum K\u00e2mp\u00f4ng Kr\u00e2nhung"
    ],
    "name:khm_x_variant":[
        "\u1797\u17bc\u1798\u17b7 \u1780\u17c6\u1796\u1784\u17cb\u1780\u17d2\u179a\u1789\u17bc\u1784"
    ],
    "wof:name":"Phum Kampong Kranhung",
    "wof:placetype":"locality"
},
  "geometry": {"coordinates":[103.84683,10.76012],"type":"Point"}
}