{
  "type": "Feature",
  "properties": {
    "gn:admin1_code":"19",
    "gn:asciiname":"Phumi Svay Chal",
    "gn:country_code":"KH",
    "gn:dem":14,
    "gn:feature_class":"P",
    "gn:feature_code":"PPL",
    "gn:name":"Phum\u012d Svay Ch\u0103l",
    "gn:population":0,
    "gn:timezone":"Asia/Phnom_Penh",
    "iso:country":"KH",
    "name:und_x_variant":[
        "Phum Sva\u00ef Chal",
        "Phum\u012d Svay Chall",
        "Phum\u012d Svay Ch\u0103l"
    ],
    "wof:name":"Phumi Svay Chal",
    "wof:placetype":"locality"
},
  "geometry": {"coordinates":[104.92052,11.19439],"type":"Point"}
}