{
  "type": "Feature",
  "properties": {
    "gn:admin1_code":"28",
    "gn:asciiname":"Phumi Kaoh Ta Kiev",
    "gn:country_code":"KH",
    "gn:dem":17,
    "gn:feature_class":"P",
    "gn:feature_code":"PPL",
    "gn:name":"Phum\u012d Ka\u00f4h Ta Ki\u0115v",
    "gn:population":0,
    "gn:timezone":"Asia/Phnom_Penh",
    "iso:country":"KH",
    "wof:name":"Phumi Kaoh Ta Kiev",
    "wof:placetype":"locality"
},
  "geometry": {"coordinates":[103.59524999999999,10.49669],"type":"Point"}
}