{
  "type": "Feature",
  "properties": {
    "gn:admin1_code":"07",
    "gn:asciiname":"Phumi Totol",
    "gn:country_code":"KH",
    "gn:dem":11,
    "gn:feature_class":"P",
    "gn:feature_code":"PPL",
    "gn:name":"Phum\u012d T\u00f4t\u00f3l",
    "gn:population":0,
    "gn:timezone":"Asia/Phnom_Penh",
    "iso:country":"KH",
    "name:und_x_variant":[
        "Phum\u012d T\u00f4t\u016dl",
        "Phum\u012d T\u00f4t\u00f3l"
    ],
    "wof:name":"Phumi Totol",
    "wof:placetype":"locality"
},
  "geometry": {"coordinates":[105.00431,11.66307],"type":"Point"}
}