{
  "type": "Feature",
  "properties": {
    "gn:admin1_code":"03",
    "gn:asciiname":"Ngoy",
    "gn:country_code":"KH",
    "gn:dem":116,
    "gn:feature_class":"P",
    "gn:feature_code":"PPL",
    "gn:name":"Ngoy",
    "gn:population":0,
    "gn:timezone":"Asia/Phnom_Penh",
    "iso:country":"KH",
    "name:khm_x_preferred":[
        "Ngoy"
    ],
    "name:und_x_variant":[
        "Phum\u012d Ng\u00f4y"
    ],
    "wof:name":"Ngoy",
    "wof:placetype":"locality"
},
  "geometry": {"coordinates":[104.3184,11.97527],"type":"Point"}
}