{
  "type": "Feature",
  "properties": {
    "gn:admin1_code":"29",
    "gn:asciiname":"Phum Samraong Ta Kok",
    "gn:country_code":"KH",
    "gn:dem":19,
    "gn:feature_class":"P",
    "gn:feature_code":"PPL",
    "gn:name":"Phum S\u00e2mra\u00f4ng Ta K\u014fk",
    "gn:population":0,
    "gn:timezone":"Asia/Phnom_Penh",
    "iso:country":"KH",
    "name:khm_x_preferred":[
        "Phum S\u00e2mra\u00f4ng Ta K\u014fk"
    ],
    "name:khm_x_variant":[
        "\u1797\u17bc\u1798\u17b7 \u179f\u17c6\u179a\u17c4\u1784\u178f\u17b6\u1780\u17bb\u1780"
    ],
    "wof:name":"Phum Samraong Ta Kok",
    "wof:placetype":"locality"
},
  "geometry": {"coordinates":[103.22047000000001,13.12655],"type":"Point"}
}