{
  "type": "Feature",
  "properties": {
    "gn:admin1_code":"02",
    "gn:asciiname":"Svay Pok",
    "gn:country_code":"KH",
    "gn:dem":22,
    "gn:feature_class":"P",
    "gn:feature_code":"PPL",
    "gn:name":"Svay Pok",
    "gn:population":0,
    "gn:timezone":"Asia/Phnom_Penh",
    "iso:country":"KH",
    "name:khm_x_preferred":[
        "Svay Pok"
    ],
    "name:und_x_variant":[
        "Sray Pok",
        "Svay P\u00f4k",
        "Phum\u012d Svay P\u00f4k"
    ],
    "wof:name":"Svay Pok",
    "wof:placetype":"locality"
},
  "geometry": {"coordinates":[104.95053,11.99813],"type":"Point"}
}