{
  "type": "Feature",
  "properties": {
    "gn:admin1_code":"14",
    "gn:asciiname":"Phum Beng Reach",
    "gn:country_code":"KH",
    "gn:dem":12,
    "gn:feature_class":"P",
    "gn:feature_code":"PPL",
    "gn:name":"Phum Beng Reach",
    "gn:population":0,
    "gn:timezone":"Asia/Phnom_Penh",
    "iso:country":"KH",
    "name:und_x_variant":[
        "Phum\u012d B\u0153\u0306ng Rach",
        "Phum Beng Reach",
        "Phum\u012d B\u0153\u0306ng R\u00e9ach"
    ],
    "wof:name":"Phum Beng Reach",
    "wof:placetype":"locality"
},
  "geometry": {"coordinates":[105.44356999999999,11.54096],"type":"Point"}
}