{
  "type": "Feature",
  "properties": {
    "gn:admin1_code":"03",
    "gn:asciiname":"Phumi Bes Phe",
    "gn:country_code":"KH",
    "gn:dem":29,
    "gn:feature_class":"P",
    "gn:feature_code":"PPL",
    "gn:name":"Phum\u012d B\u00eas Ph\u00e9",
    "gn:population":0,
    "gn:timezone":"Asia/Phnom_Penh",
    "iso:country":"KH",
    "name:und_x_variant":[
        "Phum\u012d B\u00e9h Ph\u00e9",
        "Phum\u012d B\u00eas Ph\u00e9"
    ],
    "wof:name":"Phumi Bes Phe",
    "wof:placetype":"locality"
},
  "geometry": {"coordinates":[104.51809,12.35379],"type":"Point"}
}