{
  "type": "Feature",
  "properties": {
    "gn:admin1_code":"02",
    "gn:asciiname":"Phumi Chamkar Samseb",
    "gn:country_code":"KH",
    "gn:dem":20,
    "gn:feature_class":"P",
    "gn:feature_code":"PPL",
    "gn:name":"Phum\u012d Ch\u00e2mkar Sams\u0115b",
    "gn:population":0,
    "gn:timezone":"Asia/Phnom_Penh",
    "iso:country":"KH",
    "name:und_x_variant":[
        "Phum Chamka Sam Sap",
        "Phumi Ch\u00e2mkar Sams\u0153\u0306p",
        "Phum Chamka Samsep",
        "Phum\u012d Ch\u00e2mkar Sams\u0115b"
    ],
    "wof:name":"Phumi Chamkar Samseb",
    "wof:placetype":"locality"
},
  "geometry": {"coordinates":[105.35684999999999,11.93762],"type":"Point"}
}