{
  "type": "Feature",
  "properties": {
    "gn:admin1_code":"05",
    "gn:asciiname":"Phumi Pouthi Khav",
    "gn:country_code":"KH",
    "gn:dem":15,
    "gn:feature_class":"P",
    "gn:feature_code":"PPL",
    "gn:name":"Phum\u012d Po\u016dth\u012d Khav",
    "gn:population":0,
    "gn:timezone":"Asia/Phnom_Penh",
    "iso:country":"KH",
    "name:und_x_variant":[
        "Phum Po Khao",
        "Phum\u012d Po\u016d Khav",
        "Phum\u012d Po\u016dth\u012d Khav"
    ],
    "wof:name":"Phumi Pouthi Khav",
    "wof:placetype":"locality"
},
  "geometry": {"coordinates":[104.94474,12.65512],"type":"Point"}
}