{
  "type": "Feature",
  "properties": {
    "gn:admin1_code":"23.0",
    "gn:asciiname":"Ka Tieng",
    "gn:country_code":"KH",
    "gn:dem":127,
    "gn:feature_class":"P",
    "gn:feature_code":"PPL",
    "gn:name":"Ka Tieng",
    "gn:population":0,
    "gn:timezone":"Asia/Phnom_Penh",
    "iso:country":"KH",
    "name:khm_x_preferred":[
        "Ka Tieng"
    ],
    "wof:name":"Ka Tieng",
    "wof:placetype":"locality"
},
  "geometry": {"coordinates":[106.97171000000002,13.64199],"type":"Point"}
}