{
  "type": "Feature",
  "properties": {
    "gn:admin1_code":"09",
    "gn:asciiname":"Phum Kaoh Enchey",
    "gn:country_code":"KH",
    "gn:dem":49,
    "gn:feature_class":"P",
    "gn:feature_code":"PPL",
    "gn:name":"Phum Ka\u00f4h \u0114nchey",
    "gn:population":0,
    "gn:timezone":"Asia/Phnom_Penh",
    "iso:country":"KH",
    "name:khm_x_preferred":[
        "Phum Ka\u00f4h \u0114nchey"
    ],
    "name:khm_x_variant":[
        "\u1797\u17bc\u1798\u17b7 \u1780\u17c4\u17c7\u17a5\u1793\u17d2\u1791\u1787\u17d0\u1799"
    ],
    "name:und_x_variant":[
        "Phum Kas Anichey",
        "Phum\u012d Ka\u00f4h \u0114nt Chey"
    ],
    "wof:name":"Phum Kaoh Enchey",
    "wof:placetype":"locality"
},
  "geometry": {"coordinates":[106.00884000000001,13.10574],"type":"Point"}
}