{
  "type": "Feature",
  "properties": {
    "gn:admin1_code":"14",
    "gn:asciiname":"Phumi Khsam Cheung",
    "gn:country_code":"KH",
    "gn:dem":16,
    "gn:feature_class":"P",
    "gn:feature_code":"PPL",
    "gn:name":"Phum\u012d Khs\u00e2m Cheung",
    "gn:population":0,
    "gn:timezone":"Asia/Phnom_Penh",
    "iso:country":"KH",
    "name:und_x_variant":[
        "Phum Ksom",
        "Phum\u012d Khs\u00e2m Cheung"
    ],
    "wof:name":"Phumi Khsam Cheung",
    "wof:placetype":"locality"
},
  "geometry": {"coordinates":[105.15331999999999,11.64716],"type":"Point"}
}