{
  "type": "Feature",
  "properties": {
    "gn:admin1_code":"02",
    "gn:asciiname":"Phumi Andong Chham Chha",
    "gn:country_code":"KH",
    "gn:dem":79,
    "gn:feature_class":"P",
    "gn:feature_code":"PPL",
    "gn:name":"Phum\u012d \u00c2ndong Chh\u0103m Chha",
    "gn:population":0,
    "gn:timezone":"Asia/Phnom_Penh",
    "iso:country":"KH",
    "wof:name":"Phumi Andong Chham Chha",
    "wof:placetype":"locality"
},
  "geometry": {"coordinates":[105.23333,12.21667],"type":"Point"}
}