{
  "type": "Feature",
  "properties": {
    "gn:admin1_code":"05",
    "gn:asciiname":"Samraong",
    "gn:country_code":"KH",
    "gn:dem":16,
    "gn:feature_class":"P",
    "gn:feature_code":"PPL",
    "gn:name":"Samraong",
    "gn:population":0,
    "gn:timezone":"Asia/Phnom_Penh",
    "iso:country":"KH",
    "name:ceb_x_preferred":[
        "Samraong"
    ],
    "name:khm_x_preferred":[
        "\u179f\u17c6\u179a\u17c4\u1784"
    ],
    "name:swe_x_preferred":[
        "Samraong"
    ],
    "name:und_x_variant":[
        "Phum\u012d S\u00e2mra\u00f4ng (1)"
    ],
    "wof:name":"Samraong",
    "wof:placetype":"locality"
},
  "geometry": {"coordinates":[105.08449,12.41215],"type":"Point"}
}