{
  "type": "Feature",
  "properties": {
    "gn:admin1_code":"17",
    "gn:asciiname":"Phumi Khsan",
    "gn:country_code":"KH",
    "gn:dem":107,
    "gn:feature_class":"P",
    "gn:feature_code":"PPL",
    "gn:name":"Phum\u012d Khsan",
    "gn:population":0,
    "gn:timezone":"Asia/Phnom_Penh",
    "iso:country":"KH",
    "name:und_x_variant":[
        "Chvang",
        "Phum\u012d Khsan"
    ],
    "wof:name":"Phumi Khsan",
    "wof:placetype":"locality"
},
  "geometry": {"coordinates":[105.77688999999999,13.72571],"type":"Point"}
}