{
  "type": "Feature",
  "properties": {
    "gn:admin1_code":"28",
    "gn:asciiname":"Phumi Ma U",
    "gn:country_code":"KH",
    "gn:dem":20,
    "gn:feature_class":"P",
    "gn:feature_code":"PPL",
    "gn:name":"Phum\u012d Ma U",
    "gn:population":0,
    "gn:timezone":"Asia/Phnom_Penh",
    "iso:country":"KH",
    "name:und_x_variant":[
        "Muhu",
        "Phum\u012d Ma Ou",
        "Phum\u012d Ma U"
    ],
    "wof:name":"Phumi Ma U",
    "wof:placetype":"locality"
},
  "geometry": {"coordinates":[103.74052,10.55086],"type":"Point"}
}