{
  "type": "Feature",
  "properties": {
    "gn:admin1_code":"03",
    "gn:asciiname":"Phum Russei Chrum",
    "gn:country_code":"KH",
    "gn:dem":30,
    "gn:feature_class":"P",
    "gn:feature_code":"PPL",
    "gn:name":"Phum R\u016dssei Chr\u016dm",
    "gn:population":0,
    "gn:timezone":"Asia/Phnom_Penh",
    "iso:country":"KH",
    "name:khm_x_preferred":[
        "Phum R\u016dssei Chr\u016dm"
    ],
    "name:khm_x_variant":[
        "\u1797\u17bc\u1798\u17b7 \u17ab\u179f\u17d2\u179f\u17b8\u1787\u17d2\u179a\u17bb\u17c6"
    ],
    "name:und_x_variant":[
        "Phum\u012d R\u016dssei Chr\u016dm",
        "Phum\u012d R\u0153ssei Chr\u016dm"
    ],
    "wof:name":"Phum Russei Chrum",
    "wof:placetype":"locality"
},
  "geometry": {"coordinates":[104.40783,12.36413],"type":"Point"}
}