{
  "type": "Feature",
  "properties": {
    "gn:admin1_code":"23",
    "gn:asciiname":"Banlung",
    "gn:country_code":"KH",
    "gn:dem":316,
    "gn:feature_class":"P",
    "gn:feature_code":"PPLA",
    "gn:name":"Banlung",
    "gn:population":17000,
    "gn:timezone":"Asia/Phnom_Penh",
    "iso:country":"KH",
    "name:und_x_variant":[
        "Soung Long",
        "B\u016dng L\u016dng",
        "Phum\u012d B\u016dng L\u016dng",
        "Boung Long",
        "Ban L\u016dng",
        "B\u00f4ng L\u00f4ng",
        "Banlung",
        "Krong Ban Lung"
    ],
    "wof:name":"Banlung",
    "wof:placetype":"locality",
    "wof:population":17000
},
  "geometry": {"coordinates":[106.98727,13.73939],"type":"Point"}
}