{
  "type": "Feature",
  "properties": {
    "gn:admin1_code":"19",
    "gn:asciiname":"Phumi Prey Kral",
    "gn:country_code":"KH",
    "gn:dem":32,
    "gn:feature_class":"P",
    "gn:feature_code":"PPL",
    "gn:name":"Phum\u012d Prey Kral",
    "gn:population":0,
    "gn:timezone":"Asia/Phnom_Penh",
    "iso:country":"KH",
    "name:und_x_variant":[
        "Prey Kray",
        "Phum\u012d Prey Kral"
    ],
    "wof:name":"Phumi Prey Kral",
    "wof:placetype":"locality"
},
  "geometry": {"coordinates":[104.72515,11.32609],"type":"Point"}
}