{
  "type": "Feature",
  "properties": {
    "gn:admin1_code":"07",
    "gn:asciiname":"K'am Samnar Leu",
    "gn:country_code":"KH",
    "gn:dem":11,
    "gn:feature_class":"P",
    "gn:feature_code":"PPL",
    "gn:name":"K\u2019am Samnar Leu",
    "gn:population":0,
    "gn:timezone":"Asia/Phnom_Penh",
    "iso:country":"KH",
    "name:khm_x_preferred":[
        "K\u2019am Samnar Leu"
    ],
    "name:und_x_variant":[
        "Hung L\u00f3i",
        "Phum\u012d K\u00e2\u00e2m S\u00e2mn\u00e2 Leu",
        "Hung Lo",
        "Phum\u012d K\u2019\u00e2m S\u00e2mn\u00e2 Leu"
    ],
    "wof:name":"K'am Samnar Leu",
    "wof:placetype":"locality"
},
  "geometry": {"coordinates":[105.1797,10.94462],"type":"Point"}
}