{
  "type": "Feature",
  "properties": {
    "gn:admin1_code":"13",
    "gn:asciiname":"Phum Kampong Ampil",
    "gn:country_code":"KH",
    "gn:dem":86,
    "gn:feature_class":"P",
    "gn:feature_code":"PPL",
    "gn:name":"Phum K\u00e2mp\u00f4ng \u00c2mpil",
    "gn:population":0,
    "gn:timezone":"Asia/Phnom_Penh",
    "iso:country":"KH",
    "name:khm_x_preferred":[
        "Phum K\u00e2mp\u00f4ng \u00c2mpil"
    ],
    "name:khm_x_variant":[
        "\u1797\u17bc\u1798\u17b7 \u1780\u17c6\u1796\u1784\u17cb\u17a2\u17c6\u1796\u17b7\u179b"
    ],
    "name:und_x_variant":[
        "Phum\u012d K\u00e2mp\u00f3ng \u00c2mp\u012dl"
    ],
    "wof:name":"Phum Kampong Ampil",
    "wof:placetype":"locality"
},
  "geometry": {"coordinates":[105.79192999999999,14.01894],"type":"Point"}
}