{
  "type": "Feature",
  "properties": {
    "gn:admin1_code":"07",
    "gn:asciiname":"Thnal Bat",
    "gn:country_code":"KH",
    "gn:dem":11,
    "gn:feature_class":"P",
    "gn:feature_code":"PPL",
    "gn:name":"Thnal Bat",
    "gn:population":0,
    "gn:timezone":"Asia/Phnom_Penh",
    "iso:country":"KH",
    "name:khm_x_preferred":[
        "Thnal Bat"
    ],
    "wof:name":"Thnal Bat",
    "wof:placetype":"locality"
},
  "geometry": {"coordinates":[104.8141,11.83457],"type":"Point"}
}