{
  "type": "Feature",
  "properties": {
    "gn:admin1_code":"31",
    "gn:asciiname":"Phum Pir",
    "gn:country_code":"KH",
    "gn:dem":21,
    "gn:feature_class":"P",
    "gn:feature_code":"PPL",
    "gn:name":"Phum Pir",
    "gn:population":0,
    "gn:timezone":"Asia/Phnom_Penh",
    "iso:country":"KH",
    "name:khm_x_preferred":[
        "Phum Ka\u00f4h Toch"
    ],
    "name:khm_x_variant":[
        "Phum Pir",
        "\u1797\u17bc\u1798\u17b7 \u1780\u17c4\u17c7\u178f\u17bc\u1785"
    ],
    "name:und_x_variant":[
        "Phum K\u00e2s Toch"
    ],
    "wof:name":"Phum Pir",
    "wof:placetype":"locality"
},
  "geometry": {"coordinates":[105.52418,12.07766],"type":"Point"}
}