{
  "type": "Feature",
  "properties": {
    "gn:admin1_code":"12",
    "gn:asciiname":"Cham Thmei",
    "gn:country_code":"KH",
    "gn:dem":69,
    "gn:feature_class":"P",
    "gn:feature_code":"PPL",
    "gn:name":"Cham Thmei",
    "gn:population":0,
    "gn:timezone":"Asia/Phnom_Penh",
    "iso:country":"KH",
    "name:khm_x_preferred":[
        "Cham Thmei"
    ],
    "name:khm_x_variant":[
        "\u1797\u17bc\u1798\u17b7 \u1785\u17b6\u1798\u1790\u17d2\u1798\u17b8",
        "Phum Cham Thmei"
    ],
    "name:und_x_variant":[
        "Phum Tmei",
        "Phum\u012d Cham Thmei"
    ],
    "wof:name":"Cham Thmei",
    "wof:placetype":"locality"
},
  "geometry": {"coordinates":[104.18413,12.3082],"type":"Point"}
}