{
  "type": "Feature",
  "properties": {
    "gn:admin1_code":"13",
    "gn:asciiname":"Samret",
    "gn:country_code":"KH",
    "gn:dem":58,
    "gn:feature_class":"P",
    "gn:feature_code":"PPL",
    "gn:name":"Samret",
    "gn:population":0,
    "gn:timezone":"Asia/Phnom_Penh",
    "iso:country":"KH",
    "name:khm_x_preferred":[
        "Samret"
    ],
    "name:und_x_variant":[
        "Phum Samret",
        "Phum\u012d Samr\u0115th",
        "Phum\u012d S\u00e2mr\u012dtth\u012d"
    ],
    "wof:name":"Samret",
    "wof:placetype":"locality"
},
  "geometry": {"coordinates":[105.19843,13.36477],"type":"Point"}
}