{
  "type": "Feature",
  "properties": {
    "gn:admin1_code":"07",
    "gn:asciiname":"Khum Lumhach",
    "gn:country_code":"KH",
    "gn:dem":24,
    "gn:feature_class":"P",
    "gn:feature_code":"PPL",
    "gn:name":"Kh\u016dm Lumhach",
    "gn:population":0,
    "gn:timezone":"Asia/Phnom_Penh",
    "iso:country":"KH",
    "name:und_x_variant":[
        "Lomhaeh",
        "Kh\u016dm Lumhach"
    ],
    "wof:name":"Khum Lumhach",
    "wof:placetype":"locality"
},
  "geometry": {"coordinates":[104.68226,11.46923],"type":"Point"}
}