{
  "type": "Feature",
  "properties": {
    "gn:admin1_code":"02",
    "gn:asciiname":"Phumi Chras",
    "gn:country_code":"KH",
    "gn:dem":17,
    "gn:feature_class":"P",
    "gn:feature_code":"PPL",
    "gn:name":"Phum\u012d Chr\u00e1s",
    "gn:population":0,
    "gn:timezone":"Asia/Phnom_Penh",
    "iso:country":"KH",
    "name:und_x_variant":[
        "Chr\u00e2s",
        "Phum\u012d Chr\u00e1s"
    ],
    "wof:name":"Phumi Chras",
    "wof:placetype":"locality"
},
  "geometry": {"coordinates":[105.09841000000002,11.82808],"type":"Point"}
}