{
  "type": "Feature",
  "properties": {
    "gn:admin1_code":"12",
    "gn:asciiname":"Phumi Chumteav Meas",
    "gn:country_code":"KH",
    "gn:dem":25,
    "gn:feature_class":"P",
    "gn:feature_code":"PPL",
    "gn:name":"Phum\u012d Chumt\u00e9av M\u00e9as",
    "gn:population":0,
    "gn:timezone":"Asia/Phnom_Penh",
    "iso:country":"KH",
    "name:und_x_variant":[
        "Chumteav Meas",
        "Phum\u012d Chumt\u00e9av M\u00e9as"
    ],
    "wof:name":"Phumi Chumteav Meas",
    "wof:placetype":"locality"
},
  "geometry": {"coordinates":[103.83511,12.47676],"type":"Point"}
}