{
  "type": "Feature",
  "properties": {
    "gn:admin1_code":"04",
    "gn:asciiname":"Khum Snam Krapeu",
    "gn:country_code":"KH",
    "gn:dem":43,
    "gn:feature_class":"P",
    "gn:feature_code":"PPL",
    "gn:name":"Kh\u016dm Sn\u00e2m Kr\u00e2peu",
    "gn:population":0,
    "gn:timezone":"Asia/Phnom_Penh",
    "iso:country":"KH",
    "name:und_x_variant":[
        "Phum Sn\u00e2m Krapeu",
        "Kh\u016dm Sn\u00e2m Kr\u00e2peu"
    ],
    "wof:name":"Khum Snam Krapeu",
    "wof:placetype":"locality"
},
  "geometry": {"coordinates":[104.65184000000001,11.28091],"type":"Point"}
}