{
  "type": "Feature",
  "properties": {
    "gn:admin1_code":"08",
    "gn:asciiname":"Chrouy",
    "gn:country_code":"KH",
    "gn:dem":23,
    "gn:feature_class":"P",
    "gn:feature_code":"PPL",
    "gn:name":"Chrouy",
    "gn:population":0,
    "gn:timezone":"Asia/Phnom_Penh",
    "iso:country":"KH",
    "name:khm_x_preferred":[
        "Chrouy"
    ],
    "name:und_x_variant":[
        "Phum\u012d Chro\u016dy"
    ],
    "wof:name":"Chrouy",
    "wof:placetype":"locality"
},
  "geometry": {"coordinates":[103.77113,11.08017],"type":"Point"}
}