{
  "type": "Feature",
  "properties": {
    "gn:admin1_code":"12",
    "gn:asciiname":"Boeng Chhuk",
    "gn:country_code":"KH",
    "gn:dem":25,
    "gn:feature_class":"P",
    "gn:feature_code":"PPL",
    "gn:name":"Boeng Chhuk",
    "gn:population":0,
    "gn:timezone":"Asia/Phnom_Penh",
    "iso:country":"KH",
    "name:khm_x_preferred":[
        "Boeng Chhuk"
    ],
    "wof:name":"Boeng Chhuk",
    "wof:placetype":"locality"
},
  "geometry": {"coordinates":[103.72166,12.58664],"type":"Point"}
}