{
  "type": "Feature",
  "properties": {
    "gn:admin1_code":"22",
    "gn:asciiname":"Phumi Trapeang Leuk",
    "gn:country_code":"KH",
    "gn:dem":16,
    "gn:feature_class":"P",
    "gn:feature_code":"PPL",
    "gn:name":"Phum\u012d Tr\u00e2pe\u0103ng Leuk",
    "gn:population":0,
    "gn:timezone":"Asia/Phnom_Penh",
    "iso:country":"KH",
    "name:und_x_variant":[
        "Trapeang Loueuk",
        "Phum\u012d Tr\u00e2pe\u0103ng Leuk"
    ],
    "wof:name":"Phumi Trapeang Leuk",
    "wof:placetype":"locality"
},
  "geometry": {"coordinates":[104.80587,11.56181],"type":"Point"}
}