{
  "type": "Feature",
  "properties": {
    "gn:admin1_code":"09",
    "gn:asciiname":"Phumi Sev",
    "gn:country_code":"KH",
    "gn:dem":53,
    "gn:feature_class":"P",
    "gn:feature_code":"PPL",
    "gn:name":"Phum\u012d S\u00eav",
    "gn:population":0,
    "gn:timezone":"Asia/Phnom_Penh",
    "iso:country":"KH",
    "name:und_x_variant":[
        "Phum Seo",
        "Phum\u012d S\u00eav"
    ],
    "wof:name":"Phumi Sev",
    "wof:placetype":"locality"
},
  "geometry": {"coordinates":[105.84377000000001,12.93036],"type":"Point"}
}