{
  "type": "Feature",
  "properties": {
    "gn:admin1_code":"27",
    "gn:asciiname":"Keab",
    "gn:country_code":"KH",
    "gn:dem":57,
    "gn:feature_class":"P",
    "gn:feature_code":"PPL",
    "gn:name":"Keab",
    "gn:population":0,
    "gn:timezone":"Asia/Phnom_Penh",
    "iso:country":"KH",
    "name:khm_x_preferred":[
        "Keab"
    ],
    "wof:name":"Keab",
    "wof:placetype":"locality"
},
  "geometry": {"coordinates":[103.35158,14.22862],"type":"Point"}
}