{
  "type": "Feature",
  "properties": {
    "gn:admin1_code":"12.0",
    "gn:asciiname":"Ou Rumchek",
    "gn:country_code":"KH",
    "gn:dem":21,
    "gn:feature_class":"P",
    "gn:feature_code":"PPL",
    "gn:name":"Ou Rumchek",
    "gn:population":0,
    "gn:timezone":"Asia/Phnom_Penh",
    "iso:country":"KH",
    "name:khm_x_preferred":[
        "Ou Rumchek"
    ],
    "wof:name":"Ou Rumchek",
    "wof:placetype":"locality"
},
  "geometry": {"coordinates":[103.77029,12.57984],"type":"Point"}
}