{
  "type": "Feature",
  "properties": {
    "gn:admin1_code":"19",
    "gn:asciiname":"Phumi Ta Trak",
    "gn:country_code":"KH",
    "gn:dem":12,
    "gn:feature_class":"P",
    "gn:feature_code":"PPL",
    "gn:name":"Phum\u012d Ta Tr\u00e2k",
    "gn:population":0,
    "gn:timezone":"Asia/Phnom_Penh",
    "iso:country":"KH",
    "name:und_x_variant":[
        "P\u00f4u S\u00e2mpor",
        "Phum\u012d Ta Tr\u00e2k"
    ],
    "wof:name":"Phumi Ta Trak",
    "wof:placetype":"locality"
},
  "geometry": {"coordinates":[104.80911999999999,11.25813],"type":"Point"}
}