{
  "type": "Feature",
  "properties": {
    "gn:admin1_code":"18",
    "gn:asciiname":"Phumi Roessei Totoeng",
    "gn:country_code":"KH",
    "gn:dem":5,
    "gn:feature_class":"P",
    "gn:feature_code":"PPL",
    "gn:name":"Phum\u012d R\u0153ssei T\u00f4t\u0153\u0306ng",
    "gn:population":0,
    "gn:timezone":"Asia/Phnom_Penh",
    "iso:country":"KH",
    "name:und_x_variant":[
        "Phum\u012d R\u016dssei Toto\u0115ng",
        "Phum\u012d R\u0153ssei T\u00f4t\u0153\u0306ng"
    ],
    "wof:name":"Phumi Roessei Totoeng",
    "wof:placetype":"locality"
},
  "geometry": {"coordinates":[105.64585,11.15609],"type":"Point"}
}