{
  "type": "Feature",
  "properties": {
    "gn:admin1_code":"08",
    "gn:asciiname":"Phum Dong",
    "gn:country_code":"KH",
    "gn:dem":6,
    "gn:feature_class":"P",
    "gn:feature_code":"PPL",
    "gn:name":"Phum Dong",
    "gn:population":0,
    "gn:timezone":"Asia/Phnom_Penh",
    "iso:country":"KH",
    "wof:name":"Phum Dong",
    "wof:placetype":"locality"
},
  "geometry": {"coordinates":[103.13115000000001,11.57865],"type":"Point"}
}