{
  "type": "Feature",
  "properties": {
    "gn:admin1_code":"14.0",
    "gn:asciiname":"Phum Cheung Toek",
    "gn:country_code":"KH",
    "gn:dem":10,
    "gn:feature_class":"P",
    "gn:feature_code":"PPL",
    "gn:name":"Phum Cheung T\u0153\u0306k",
    "gn:population":0,
    "gn:timezone":"Asia/Phnom_Penh",
    "iso:country":"KH",
    "name:khm_x_preferred":[
        "Phum Cheung T\u0153\u0306k"
    ],
    "name:khm_x_variant":[
        "\u1797\u17bc\u1798\u17b7 \u1787\u17be\u1784\u1791\u17b9\u1780"
    ],
    "wof:name":"Phum Cheung Toek",
    "wof:placetype":"locality"
},
  "geometry": {"coordinates":[105.38764,11.28803],"type":"Point"}
}