{
  "type": "Feature",
  "properties": {
    "gn:admin1_code":"14",
    "gn:asciiname":"Veal Robang Kraom",
    "gn:country_code":"KH",
    "gn:dem":17,
    "gn:feature_class":"P",
    "gn:feature_code":"PPL",
    "gn:name":"Veal Robang Kraom",
    "gn:population":0,
    "gn:timezone":"Asia/Phnom_Penh",
    "iso:country":"KH",
    "name:khm_x_preferred":[
        "Veal Robang Kraom"
    ],
    "name:und_x_variant":[
        "Vat V\u00e9allabeng",
        "Phum\u012d V\u00e9al R\u00f4b\u00e2ng"
    ],
    "wof:name":"Veal Robang Kraom",
    "wof:placetype":"locality"
},
  "geometry": {"coordinates":[105.31056,11.17372],"type":"Point"}
}