{
  "type": "Feature",
  "properties": {
    "gn:admin1_code":"29",
    "gn:asciiname":"Souphi",
    "gn:country_code":"KH",
    "gn:dem":17,
    "gn:feature_class":"P",
    "gn:feature_code":"PPL",
    "gn:name":"Souphi",
    "gn:population":0,
    "gn:timezone":"Asia/Phnom_Penh",
    "iso:country":"KH",
    "name:khm_x_preferred":[
        "Souphi"
    ],
    "name:khm_x_variant":[
        "\u1797\u17bc\u1798\u17b7 \u179f\u17bc\u1797\u17b8",
        "Phum Sophi"
    ],
    "name:und_x_variant":[
        "Phum\u012d Sophi"
    ],
    "wof:name":"Souphi",
    "wof:placetype":"locality"
},
  "geometry": {"coordinates":[103.02767,13.17661],"type":"Point"}
}