{
  "type": "Feature",
  "properties": {
    "gn:admin1_code":"28",
    "gn:asciiname":"Phum Tapou",
    "gn:country_code":"KH",
    "gn:dem":4,
    "gn:feature_class":"P",
    "gn:feature_code":"PPL",
    "gn:name":"Phum Tap\u014fu",
    "gn:population":0,
    "gn:timezone":"Asia/Phnom_Penh",
    "iso:country":"KH",
    "name:khm_x_preferred":[
        "Phum Tap\u014fu"
    ],
    "name:khm_x_variant":[
        "\u1797\u17bc\u1798\u17b7 \u178f\u17b6\u1796\u17c5"
    ],
    "name:und_x_variant":[
        "Phum\u012d Tapeou"
    ],
    "wof:name":"Phum Tapou",
    "wof:placetype":"locality"
},
  "geometry": {"coordinates":[103.80831999999999,10.81077],"type":"Point"}
}