{
  "type": "Feature",
  "properties": {
    "gn:admin1_code":"03",
    "gn:asciiname":"Thma Kaev",
    "gn:country_code":"KH",
    "gn:dem":23,
    "gn:feature_class":"P",
    "gn:feature_code":"PPL",
    "gn:name":"Thma Kaev",
    "gn:population":0,
    "gn:timezone":"Asia/Phnom_Penh",
    "iso:country":"KH",
    "name:khm_x_preferred":[
        "Thma Kaev"
    ],
    "name:und_x_variant":[
        "Wat Thnna Keo",
        "Vat Thnna K\u00e9o",
        "Phum\u012d Thm\u00e2 K\u00eav"
    ],
    "wof:name":"Thma Kaev",
    "wof:placetype":"locality"
},
  "geometry": {"coordinates":[104.57261,12.31922],"type":"Point"}
}