{
  "type": "Feature",
  "properties": {
    "gn:admin1_code":"05",
    "gn:asciiname":"Sampoar Thum",
    "gn:country_code":"KH",
    "gn:dem":32,
    "gn:feature_class":"P",
    "gn:feature_code":"PPL",
    "gn:name":"Sampoar Thum",
    "gn:population":0,
    "gn:timezone":"Asia/Phnom_Penh",
    "iso:country":"KH",
    "name:khm_x_preferred":[
        "Sampoar Thum"
    ],
    "wof:name":"Sampoar Thum",
    "wof:placetype":"locality"
},
  "geometry": {"coordinates":[105.25957,13.18986],"type":"Point"}
}