{
  "type": "Feature",
  "properties": {
    "gn:admin1_code":"24",
    "gn:asciiname":"Ta Saeng",
    "gn:country_code":"KH",
    "gn:dem":24,
    "gn:feature_class":"P",
    "gn:feature_code":"PPL",
    "gn:name":"Ta Saeng",
    "gn:population":0,
    "gn:timezone":"Asia/Phnom_Penh",
    "iso:country":"KH",
    "name:khm_x_preferred":[
        "Ta Saeng"
    ],
    "name:khm_x_variant":[
        "\u1797\u17bc\u1798\u17b7 \u178f\u17b6\u179f\u17c2\u1784",
        "Phum Tas\u00eang"
    ],
    "name:und_x_variant":[
        "Ta Seng",
        "Phum\u012d Tas\u00eang"
    ],
    "wof:name":"Ta Saeng",
    "wof:placetype":"locality"
},
  "geometry": {"coordinates":[103.56995000000001,13.62722],"type":"Point"}
}