{
  "type": "Feature",
  "properties": {
    "gn:admin1_code":"03",
    "gn:asciiname":"Chres",
    "gn:country_code":"KH",
    "gn:dem":18,
    "gn:feature_class":"P",
    "gn:feature_code":"PPL",
    "gn:name":"Chres",
    "gn:population":0,
    "gn:timezone":"Asia/Phnom_Penh",
    "iso:country":"KH",
    "name:khm_x_preferred":[
        "Chres"
    ],
    "name:und_x_variant":[
        "Kh\u016dm Chr\u00e9s"
    ],
    "wof:name":"Chres",
    "wof:placetype":"locality"
},
  "geometry": {"coordinates":[104.7606,11.94849],"type":"Point"}
}