{
  "type": "Feature",
  "properties": {
    "gn:admin1_code":"03",
    "gn:asciiname":"Damnak Reach",
    "gn:country_code":"KH",
    "gn:dem":6,
    "gn:feature_class":"P",
    "gn:feature_code":"PPL",
    "gn:name":"Damnak Reach",
    "gn:population":0,
    "gn:timezone":"Asia/Phnom_Penh",
    "iso:country":"KH",
    "name:khm_x_preferred":[
        "Damnak Reach"
    ],
    "wof:name":"Damnak Reach",
    "wof:placetype":"locality"
},
  "geometry": {"coordinates":[104.61918,12.37458],"type":"Point"}
}