{
  "type": "Feature",
  "properties": {
    "gn:admin1_code":"26",
    "gn:asciiname":"Phumi Khvav",
    "gn:country_code":"KH",
    "gn:dem":8,
    "gn:feature_class":"P",
    "gn:feature_code":"PPL",
    "gn:name":"Phum\u012d Khvav",
    "gn:population":0,
    "gn:timezone":"Asia/Phnom_Penh",
    "iso:country":"KH",
    "name:und_x_variant":[
        "Phum Kvag",
        "Phum Kvao",
        "Phum\u012d Khvav"
    ],
    "wof:name":"Phumi Khvav",
    "wof:placetype":"locality"
},
  "geometry": {"coordinates":[104.37161,10.52522],"type":"Point"}
}