{
  "type": "Feature",
  "properties": {
    "gn:admin1_code":"19",
    "gn:asciiname":"Phumi Trapeang Thma",
    "gn:country_code":"KH",
    "gn:dem":37,
    "gn:feature_class":"P",
    "gn:feature_code":"PPL",
    "gn:name":"Phum\u012d Tr\u00e2pe\u0103ng Thm\u00e2",
    "gn:population":0,
    "gn:timezone":"Asia/Phnom_Penh",
    "iso:country":"KH",
    "wof:name":"Phumi Trapeang Thma",
    "wof:placetype":"locality"
},
  "geometry": {"coordinates":[104.58179,10.95102],"type":"Point"}
}