{
  "type": "Feature",
  "properties": {
    "gn:admin1_code":"05",
    "gn:asciiname":"Phumi Phlong",
    "gn:country_code":"KH",
    "gn:dem":20,
    "gn:feature_class":"P",
    "gn:feature_code":"PPL",
    "gn:name":"Phum\u012d Phl\u00f4ng",
    "gn:population":0,
    "gn:timezone":"Asia/Phnom_Penh",
    "iso:country":"KH",
    "name:und_x_variant":[
        "Phlong",
        "Phum\u012d Phl\u00f4ng"
    ],
    "wof:name":"Phumi Phlong",
    "wof:placetype":"locality"
},
  "geometry": {"coordinates":[104.81103,12.84658],"type":"Point"}
}