{
  "type": "Feature",
  "properties": {
    "gn:admin1_code":"03",
    "gn:asciiname":"Phum Kreang Sleng",
    "gn:country_code":"KH",
    "gn:dem":33,
    "gn:feature_class":"P",
    "gn:feature_code":"PPL",
    "gn:name":"Phum Kre\u0103ng Sl\u00eang",
    "gn:population":0,
    "gn:timezone":"Asia/Phnom_Penh",
    "iso:country":"KH",
    "name:khm_x_preferred":[
        "Phum Kre\u0103ng Sl\u00eang"
    ],
    "name:khm_x_variant":[
        "\u1797\u17bc\u1798\u17b7 \u1782\u17d2\u179a\u17b6\u17c6\u1784\u179f\u17d2\u179b\u17c2\u1784"
    ],
    "name:und_x_variant":[
        "Phum\u012d Kre\u0103ng Sl\u00eang"
    ],
    "wof:name":"Phum Kreang Sleng",
    "wof:placetype":"locality"
},
  "geometry": {"coordinates":[104.38648000000001,12.34357],"type":"Point"}
}