{
  "type": "Feature",
  "properties": {
    "gn:admin1_code":"02",
    "gn:asciiname":"Phumi Pana",
    "gn:cc2":"KH",
    "gn:country_code":"KH",
    "gn:dem":15,
    "gn:feature_class":"P",
    "gn:feature_code":"PPL",
    "gn:name":"Phum\u012d Pana",
    "gn:population":0,
    "gn:timezone":"Asia/Phnom_Penh",
    "iso:country":"KH",
    "name:und_x_variant":[
        "Bana",
        "Phum\u012d Pana"
    ],
    "wof:name":"Phumi Pana",
    "wof:placetype":"locality"
},
  "geometry": {"coordinates":[105.08333,12.06667],"type":"Point"}
}