{
  "type": "Feature",
  "properties": {
    "gn:admin1_code":"09",
    "gn:asciiname":"Preaek Kov",
    "gn:country_code":"KH",
    "gn:dem":25,
    "gn:feature_class":"P",
    "gn:feature_code":"PPL",
    "gn:name":"Preaek Kov",
    "gn:population":0,
    "gn:timezone":"Asia/Phnom_Penh",
    "iso:country":"KH",
    "name:khm_x_preferred":[
        "Preaek Kov"
    ],
    "name:khm_x_variant":[
        "\u1797\u17bc\u1798\u17b7 \u1796\u17d2\u179a\u17c2\u1780\u1780\u17bc\u179c"
    ],
    "name:und_x_variant":[
        "Phum Prek Koeu",
        "Phum\u012d Pr\u00eak Kov"
    ],
    "wof:name":"Preaek Kov",
    "wof:placetype":"locality"
},
  "geometry": {"coordinates":[106.07234,12.42721],"type":"Point"}
}