{
  "type": "Feature",
  "properties": {
    "gn:admin1_code":"04",
    "gn:asciiname":"Peang Lvea",
    "gn:country_code":"KH",
    "gn:dem":38,
    "gn:feature_class":"P",
    "gn:feature_code":"PPL",
    "gn:name":"Peang Lvea",
    "gn:population":0,
    "gn:timezone":"Asia/Phnom_Penh",
    "iso:country":"KH",
    "name:khm_x_preferred":[
        "Peang Lvea"
    ],
    "name:und_x_variant":[
        "Phum Peang Lovea",
        "Phum\u012d Pe\u00e2ng Lv\u00e9a"
    ],
    "wof:name":"Peang Lvea",
    "wof:placetype":"locality"
},
  "geometry": {"coordinates":[104.59932000000001,11.582],"type":"Point"}
}