{
  "type": "Feature",
  "properties": {
    "gn:admin1_code":"04",
    "gn:asciiname":"Kandal",
    "gn:country_code":"KH",
    "gn:dem":51,
    "gn:feature_class":"P",
    "gn:feature_code":"PPL",
    "gn:name":"Kandal",
    "gn:population":0,
    "gn:timezone":"Asia/Phnom_Penh",
    "iso:country":"KH",
    "name:khm_x_preferred":[
        "Kandal"
    ],
    "wof:name":"Kandal",
    "wof:placetype":"locality"
},
  "geometry": {"coordinates":[104.56820999999999,11.70406],"type":"Point"}
}