{
  "type": "Feature",
  "properties": {
    "gn:admin1_code":"18",
    "gn:asciiname":"Svay Rumpea",
    "gn:country_code":"KH",
    "gn:dem":7,
    "gn:feature_class":"P",
    "gn:feature_code":"PPL",
    "gn:name":"Svay Rumpea",
    "gn:population":0,
    "gn:timezone":"Asia/Phnom_Penh",
    "iso:country":"KH",
    "name:khm_x_preferred":[
        "Svay Rumpea"
    ],
    "name:und_x_variant":[
        "Phum Svay Rompea",
        "Phum\u012d Svay Rump\u00e9a"
    ],
    "wof:name":"Svay Rumpea",
    "wof:placetype":"locality"
},
  "geometry": {"coordinates":[105.79508,11.21248],"type":"Point"}
}