{
  "type": "Feature",
  "properties": {
    "gn:admin1_code":"25",
    "gn:asciiname":"Ta Siev",
    "gn:country_code":"KH",
    "gn:dem":28,
    "gn:feature_class":"P",
    "gn:feature_code":"PPL",
    "gn:name":"Ta Siev",
    "gn:population":0,
    "gn:timezone":"Asia/Phnom_Penh",
    "iso:country":"KH",
    "name:khm_x_preferred":[
        "Ta Siev"
    ],
    "wof:name":"Ta Siev",
    "wof:placetype":"locality"
},
  "geometry": {"coordinates":[103.15432,13.87628],"type":"Point"}
}