{
  "type": "Feature",
  "properties": {
    "gn:admin1_code":"9.0",
    "gn:asciiname":"Ou Lung",
    "gn:country_code":"KH",
    "gn:dem":28,
    "gn:feature_class":"P",
    "gn:feature_code":"PPL",
    "gn:name":"Ou Lung",
    "gn:population":0,
    "gn:timezone":"Asia/Phnom_Penh",
    "iso:country":"KH",
    "name:khm_x_preferred":[
        "Ou Lung"
    ],
    "wof:name":"Ou Lung",
    "wof:placetype":"locality"
},
  "geometry": {"coordinates":[106.01133,12.30487],"type":"Point"}
}