{
  "type": "Feature",
  "properties": {
    "gn:admin1_code":"31",
    "gn:asciiname":"Chong Ou",
    "gn:country_code":"KH",
    "gn:dem":34,
    "gn:feature_class":"P",
    "gn:feature_code":"PPL",
    "gn:name":"Chong Ou",
    "gn:population":0,
    "gn:timezone":"Asia/Phnom_Penh",
    "iso:country":"KH",
    "name:khm_x_preferred":[
        "Chong Ou"
    ],
    "name:khm_x_variant":[
        "\u1797\u17bc\u1798\u17b7 \u1785\u17bb\u1784\u17a2\u17bc",
        "Phum Ch\u014fng O"
    ],
    "wof:name":"Chong Ou",
    "wof:placetype":"locality"
},
  "geometry": {"coordinates":[105.70289,12.03146],"type":"Point"}
}