{
  "type": "Feature",
  "properties": {
    "gn:admin1_code":"09",
    "gn:asciiname":"Prahuot",
    "gn:country_code":"KH",
    "gn:dem":32,
    "gn:feature_class":"P",
    "gn:feature_code":"PPL",
    "gn:name":"Prahuot",
    "gn:population":0,
    "gn:timezone":"Asia/Phnom_Penh",
    "iso:country":"KH",
    "name:khm_x_preferred":[
        "Prahuot"
    ],
    "wof:name":"Prahuot",
    "wof:placetype":"locality"
},
  "geometry": {"coordinates":[106.0749,12.18007],"type":"Point"}
}