{
  "type": "Feature",
  "properties": {
    "gn:admin1_code":"29",
    "gn:asciiname":"Sala Trav",
    "gn:country_code":"KH",
    "gn:dem":15,
    "gn:feature_class":"P",
    "gn:feature_code":"PPL",
    "gn:name":"Sala Trav",
    "gn:population":0,
    "gn:timezone":"Asia/Phnom_Penh",
    "iso:country":"KH",
    "name:khm_x_preferred":[
        "Sala Trav"
    ],
    "wof:name":"Sala Trav",
    "wof:placetype":"locality"
},
  "geometry": {"coordinates":[103.3565,12.93497],"type":"Point"}
}