{
  "type": "Feature",
  "properties": {
    "gn:admin1_code":"29",
    "gn:asciiname":"Phum Chamkar Chak",
    "gn:country_code":"KH",
    "gn:dem":90,
    "gn:feature_class":"P",
    "gn:feature_code":"PPL",
    "gn:name":"Phum Ch\u00e2mkar Ch\u00e2k",
    "gn:population":0,
    "gn:timezone":"Asia/Phnom_Penh",
    "iso:country":"KH",
    "name:khm_x_preferred":[
        "Phum Ch\u00e2mkar Ch\u00e2k"
    ],
    "name:khm_x_variant":[
        "\u1797\u17bc\u1798\u17b7 \u1785\u17c6\u1780\u17b6\u179a\u1785\u1780"
    ],
    "wof:name":"Phum Chamkar Chak",
    "wof:placetype":"locality"
},
  "geometry": {"coordinates":[102.93843,12.8908],"type":"Point"}
}