{
  "type": "Feature",
  "properties": {
    "gn:admin1_code":"29",
    "gn:asciiname":"Ou Krabau",
    "gn:country_code":"KH",
    "gn:dem":21,
    "gn:feature_class":"P",
    "gn:feature_code":"PPL",
    "gn:name":"Ou Krabau",
    "gn:population":0,
    "gn:timezone":"Asia/Phnom_Penh",
    "iso:country":"KH",
    "name:khm_x_preferred":[
        "\u1797\u17bc\u1798\u17b7 \u17a2\u17bc\u179a\u1780\u17d2\u179a\u1794\u17c4"
    ],
    "name:khm_x_variant":[
        "Phum O Kr\u00e2bau"
    ],
    "name:und_x_variant":[
        "Okbao",
        "Phum\u012d O Kr\u00e2bau",
        "Ou Krabau"
    ],
    "wof:name":"Ou Krabau",
    "wof:placetype":"locality"
},
  "geometry": {"coordinates":[103.36709999999999,12.78327],"type":"Point"}
}