{
  "type": "Feature",
  "properties": {
    "gn:admin1_code":"05",
    "gn:asciiname":"Phumi Balangk Tuol",
    "gn:country_code":"KH",
    "gn:dem":30,
    "gn:feature_class":"P",
    "gn:feature_code":"PPL",
    "gn:name":"Phum\u012d Bal\u0103ngk Tu\u014fl",
    "gn:population":0,
    "gn:timezone":"Asia/Phnom_Penh",
    "iso:country":"KH",
    "name:und_x_variant":[
        "Phum Toul",
        "Phum Bal\u0103ng Tu\u014fl",
        "Phum\u012d Bal\u0103ngk Tu\u014fl"
    ],
    "wof:name":"Phumi Balangk Tuol",
    "wof:placetype":"locality"
},
  "geometry": {"coordinates":[105.16280999999999,12.47397],"type":"Point"}
}