{
  "type": "Feature",
  "properties": {
    "gn:admin1_code":"23.0",
    "gn:asciiname":"Pa Ar",
    "gn:country_code":"KH",
    "gn:dem":238,
    "gn:feature_class":"P",
    "gn:feature_code":"PPL",
    "gn:name":"Pa Ar",
    "gn:population":0,
    "gn:timezone":"Asia/Phnom_Penh",
    "iso:country":"KH",
    "name:khm_x_preferred":[
        "Pa Ar"
    ],
    "wof:name":"Pa Ar",
    "wof:placetype":"locality"
},
  "geometry": {"coordinates":[107.252,13.77169],"type":"Point"}
}