{
  "type": "Feature",
  "properties": {
    "gn:admin1_code":"04",
    "gn:asciiname":"Phumi Suos Ney",
    "gn:country_code":"KH",
    "gn:dem":49,
    "gn:feature_class":"P",
    "gn:feature_code":"PPL",
    "gn:name":"Phum\u012d Su\u014fs Ney",
    "gn:population":0,
    "gn:timezone":"Asia/Phnom_Penh",
    "iso:country":"KH",
    "name:und_x_variant":[
        "Phum Su\u00f4s Ney",
        "Phum\u012d Su\u014fs Ney"
    ],
    "wof:name":"Phumi Suos Ney",
    "wof:placetype":"locality"
},
  "geometry": {"coordinates":[104.56525000000001,11.61878],"type":"Point"}
}