{
  "type": "Feature",
  "properties": {
    "gn:admin1_code":"04",
    "gn:asciiname":"Prey Rumdael",
    "gn:country_code":"KH",
    "gn:dem":68,
    "gn:feature_class":"P",
    "gn:feature_code":"PPL",
    "gn:name":"Prey Rumdael",
    "gn:population":0,
    "gn:timezone":"Asia/Phnom_Penh",
    "iso:country":"KH",
    "name:khm_x_preferred":[
        "Prey Rumdael"
    ],
    "name:und_x_variant":[
        "Phum\u012d Prey Rumd\u00e9l"
    ],
    "wof:name":"Prey Rumdael",
    "wof:placetype":"locality"
},
  "geometry": {"coordinates":[104.41003000000001,11.17242],"type":"Point"}
}