{
  "type": "Feature",
  "properties": {
    "gn:admin1_code":"12.0",
    "gn:asciiname":"Bat Trach",
    "gn:country_code":"KH",
    "gn:dem":18,
    "gn:feature_class":"P",
    "gn:feature_code":"PPL",
    "gn:name":"Bat Trach",
    "gn:population":0,
    "gn:timezone":"Asia/Phnom_Penh",
    "iso:country":"KH",
    "name:khm_x_preferred":[
        "Bat Trach"
    ],
    "wof:name":"Bat Trach",
    "wof:placetype":"locality"
},
  "geometry": {"coordinates":[103.82420999999999,12.69021],"type":"Point"}
}