{
  "type": "Feature",
  "properties": {
    "gn:admin1_code":"14",
    "gn:asciiname":"Phniet",
    "gn:country_code":"KH",
    "gn:dem":17,
    "gn:feature_class":"P",
    "gn:feature_code":"PPL",
    "gn:name":"Phniet",
    "gn:population":0,
    "gn:timezone":"Asia/Phnom_Penh",
    "iso:country":"KH",
    "name:khm_x_preferred":[
        "Phniet"
    ],
    "name:khm_x_variant":[
        "\u1783\u17bb\u17c6\u1797\u17d2\u1793\u17c0\u178f"
    ],
    "name:pol_x_preferred":[
        "Phniet"
    ],
    "name:und_x_variant":[
        "Phum\u012d Phni\u0115t"
    ],
    "wof:name":"Phniet",
    "wof:placetype":"locality"
},
  "geometry": {"coordinates":[105.55987,11.39086],"type":"Point"}
}