{
  "type": "Feature",
  "properties": {
    "gn:admin1_code":"23",
    "gn:asciiname":"Phumi Pachun Nang Kung",
    "gn:country_code":"KH",
    "gn:dem":369,
    "gn:feature_class":"P",
    "gn:feature_code":"PPL",
    "gn:name":"Phum\u012d Pach\u016dn N\u00e2ng Kung",
    "gn:population":0,
    "gn:timezone":"Asia/Phnom_Penh",
    "iso:country":"KH",
    "name:und_x_variant":[
        "Phum\u012d Pach\u016dn N\u00e2ng Gung",
        "Phum\u012d Pach\u016dn N\u00e2ng Kung"
    ],
    "wof:name":"Phumi Pachun Nang Kung",
    "wof:placetype":"locality"
},
  "geometry": {"coordinates":[107.05967,13.75106],"type":"Point"}
}