{
  "type": "Feature",
  "properties": {
    "gn:admin1_code":"29",
    "gn:asciiname":"Chamcar Stung",
    "gn:country_code":"KH",
    "gn:dem":99,
    "gn:feature_class":"P",
    "gn:feature_code":"PPL",
    "gn:name":"Chamcar Stung",
    "gn:population":0,
    "gn:timezone":"Asia/Phnom_Penh",
    "iso:country":"KH",
    "name:khm_x_preferred":[
        "Phum Ch\u00e2mcar St\u0153\u0306ng"
    ],
    "name:khm_x_variant":[
        "\u1797\u17bc\u1798\u17b7 \u1785\u17c6\u1780\u17b6\u179a\u179f\u17d2\u1791\u17b9\u1784 \u1798\u17bd\u1799"
    ],
    "name:und_x_variant":[
        "Phum\u012d Ch\u00e2mcar St\u0153\u0306ng",
        "Phum\u012d Ch\u00e2mkar St\u0153\u0306ng (1)"
    ],
    "wof:name":"Chamcar Stung",
    "wof:placetype":"locality"
},
  "geometry": {"coordinates":[102.91121,12.60521],"type":"Point"}
}