{
  "type": "Feature",
  "properties": {
    "gn:admin1_code":"29",
    "gn:asciiname":"Phumi Anlong Krabau (1)",
    "gn:country_code":"KH",
    "gn:dem":30,
    "gn:feature_class":"P",
    "gn:feature_code":"PPL",
    "gn:name":"Phum\u012d \u00c2nl\u00f3ng Kr\u00e2bau (1)",
    "gn:population":0,
    "gn:timezone":"Asia/Phnom_Penh",
    "iso:country":"KH",
    "name:und_x_variant":[
        "Phum\u012d \u00c2nl\u016dng Kr\u00e2bau (1)",
        "Phum\u012d \u00c2nl\u00f3ng Kr\u00e2bau (1)"
    ],
    "wof:name":"Phumi Anlong Krabau (1)",
    "wof:placetype":"locality"
},
  "geometry": {"coordinates":[103.15000000000001,12.88333],"type":"Point"}
}