{
  "type": "Feature",
  "properties": {
    "gn:admin1_code":"14",
    "gn:asciiname":"Phum Barach",
    "gn:country_code":"KH",
    "gn:dem":10,
    "gn:feature_class":"P",
    "gn:feature_code":"PPL",
    "gn:name":"Phum Barach",
    "gn:population":0,
    "gn:timezone":"Asia/Phnom_Penh",
    "iso:country":"KH",
    "name:khm_x_preferred":[
        "\u1797\u17bc\u1798\u17b7 \u1794\u17b6\u179a\u17b6\u1785"
    ],
    "name:khm_x_variant":[
        "Phum\u012d Barach"
    ],
    "name:und_x_variant":[
        "Phum\u012d Bar\u00e9ach"
    ],
    "wof:name":"Phum Barach",
    "wof:placetype":"locality"
},
  "geometry": {"coordinates":[105.47423999999999,11.37106],"type":"Point"}
}