{
  "type": "Feature",
  "properties": {
    "gn:admin1_code":"24.0",
    "gn:asciiname":"Phum Anlung Thma",
    "gn:country_code":"KH",
    "gn:dem":16,
    "gn:feature_class":"P",
    "gn:feature_code":"PPL",
    "gn:name":"Phum Anl\u016dng Thm\u00e2",
    "gn:population":0,
    "gn:timezone":"Asia/Phnom_Penh",
    "iso:country":"KH",
    "name:khm_x_preferred":[
        "Phum Anl\u016dng Thm\u00e2"
    ],
    "name:khm_x_variant":[
        "\u1797\u17bc\u1798\u17b7 \u17a2\u1793\u17d2\u179b\u1784\u17cb\u1790\u17d2\u1798"
    ],
    "wof:name":"Phum Anlung Thma",
    "wof:placetype":"locality"
},
  "geometry": {"coordinates":[104.29734000000001,13.1449],"type":"Point"}
}