{
  "type": "Feature",
  "properties": {
    "gn:admin1_code":"07",
    "gn:asciiname":"Phumi Kouk Popel",
    "gn:country_code":"KH",
    "gn:dem":25,
    "gn:feature_class":"P",
    "gn:feature_code":"PPL",
    "gn:name":"Phum\u012d Ko\u016dk P\u00f4p\u00e9l",
    "gn:population":0,
    "gn:timezone":"Asia/Phnom_Penh",
    "iso:country":"KH",
    "name:und_x_variant":[
        "Kokpop\u00e9l",
        "Phum\u012d Ko\u016dk P\u00f4p\u00e9l"
    ],
    "wof:name":"Phumi Kouk Popel",
    "wof:placetype":"locality"
},
  "geometry": {"coordinates":[104.68462,11.45706],"type":"Point"}
}