{
  "type": "Feature",
  "properties": {
    "gn:admin1_code":"13",
    "gn:asciiname":"Tnaot Mlu",
    "gn:country_code":"KH",
    "gn:dem":63,
    "gn:feature_class":"P",
    "gn:feature_code":"PPL",
    "gn:name":"Tnaot Mlu",
    "gn:population":0,
    "gn:timezone":"Asia/Phnom_Penh",
    "iso:country":"KH",
    "name:khm_x_preferred":[
        "Tnaot Mlu"
    ],
    "wof:name":"Tnaot Mlu",
    "wof:placetype":"locality"
},
  "geometry": {"coordinates":[105.11524,13.36005],"type":"Point"}
}