{
  "type": "Feature",
  "properties": {
    "gn:admin1_code":"12",
    "gn:asciiname":"Sanlung",
    "gn:country_code":"KH",
    "gn:dem":20,
    "gn:feature_class":"P",
    "gn:feature_code":"PPL",
    "gn:name":"Sanlung",
    "gn:population":0,
    "gn:timezone":"Asia/Phnom_Penh",
    "iso:country":"KH",
    "name:khm_x_preferred":[
        "Sanlung"
    ],
    "name:khm_x_variant":[
        "\u1797\u17bc\u1798\u17b7 \u179f\u1793\u17d2\u179b\u1784",
        "Phum S\u00e2nl\u014fng"
    ],
    "name:und_x_variant":[
        "P\u2019um S\u00e2nl\u0115ng",
        "Phum\u012d S\u00e2nl\u014fng",
        "Phum\u012d S\u00e2nl\u016dng"
    ],
    "wof:name":"Sanlung",
    "wof:placetype":"locality"
},
  "geometry": {"coordinates":[103.93301,12.59356],"type":"Point"}
}