{
  "type": "Feature",
  "properties": {
    "gn:admin1_code":"09",
    "gn:asciiname":"Srae Tnaot",
    "gn:country_code":"KH",
    "gn:dem":81,
    "gn:feature_class":"P",
    "gn:feature_code":"PPL",
    "gn:name":"Srae Tnaot",
    "gn:population":0,
    "gn:timezone":"Asia/Phnom_Penh",
    "iso:country":"KH",
    "name:khm_x_preferred":[
        "Phum Sr\u00ea Tna\u00f4t"
    ],
    "name:khm_x_variant":[
        "Srae Tnaot",
        "\u1797\u17bc\u1798\u17b7 \u179f\u17d2\u179a\u17c2\u178f\u17d2\u1793\u17c4\u178f"
    ],
    "name:und_x_variant":[
        "Thmot"
    ],
    "wof:name":"Srae Tnaot",
    "wof:placetype":"locality"
},
  "geometry": {"coordinates":[106.46952,12.94065],"type":"Point"}
}