{
  "type": "Feature",
  "properties": {
    "gn:admin1_code":"24",
    "gn:asciiname":"Phum Trapeang Thlok",
    "gn:country_code":"KH",
    "gn:dem":29,
    "gn:feature_class":"P",
    "gn:feature_code":"PPL",
    "gn:name":"Phum Tr\u00e2pe\u0103ng Thl\u00f4k",
    "gn:population":0,
    "gn:timezone":"Asia/Phnom_Penh",
    "iso:country":"KH",
    "name:khm_x_preferred":[
        "Phum Tr\u00e2pe\u0103ng Thl\u00f4k"
    ],
    "name:khm_x_variant":[
        "\u1797\u17bc\u1798\u17b7 \u178f\u17d2\u179a\u1796\u17b6\u17c6\u1784\u1792\u17d2\u179b\u1780",
        "Phum\u012d Tr\u00e2pe\u0103ng Thl\u00f4k"
    ],
    "wof:name":"Phum Trapeang Thlok",
    "wof:placetype":"locality"
},
  "geometry": {"coordinates":[103.93513,13.43359],"type":"Point"}
}