{
  "type": "Feature",
  "properties": {
    "gn:admin1_code":"12",
    "gn:asciiname":"Phumi Phteah Sdau",
    "gn:country_code":"KH",
    "gn:dem":41,
    "gn:feature_class":"P",
    "gn:feature_code":"PPL",
    "gn:name":"Phum\u012d Phte\u0103h Sdau",
    "gn:population":0,
    "gn:timezone":"Asia/Phnom_Penh",
    "iso:country":"KH",
    "name:und_x_variant":[
        "Phum Phteas Sdau",
        "Phum\u012d Phte\u0103h Sdau"
    ],
    "wof:name":"Phumi Phteah Sdau",
    "wof:placetype":"locality"
},
  "geometry": {"coordinates":[103.75463999999999,12.31553],"type":"Point"}
}