{
  "type": "Feature",
  "properties": {
    "gn:admin1_code":"3.0",
    "gn:asciiname":"Phum Bak Angrut",
    "gn:country_code":"KH",
    "gn:dem":49,
    "gn:feature_class":"P",
    "gn:feature_code":"PPL",
    "gn:name":"Phum Bak \u00c2ngr\u016dt",
    "gn:population":0,
    "gn:timezone":"Asia/Phnom_Penh",
    "iso:country":"KH",
    "name:khm_x_preferred":[
        "Phum Bak \u00c2ngr\u016dt"
    ],
    "name:khm_x_variant":[
        "\u1797\u17bc\u1798\u17b7 \u1794\u17b6\u1780\u17a2\u1784\u17d2\u179a\u17bb\u178f"
    ],
    "wof:name":"Phum Bak Angrut",
    "wof:placetype":"locality"
},
  "geometry": {"coordinates":[104.46905,12.1946],"type":"Point"}
}