{
  "type": "Feature",
  "properties": {
    "gn:admin1_code":"12",
    "gn:asciiname":"Ta Nuk",
    "gn:country_code":"KH",
    "gn:dem":33,
    "gn:feature_class":"P",
    "gn:feature_code":"PPL",
    "gn:name":"Ta Nuk",
    "gn:population":0,
    "gn:timezone":"Asia/Phnom_Penh",
    "iso:country":"KH",
    "name:khm_x_preferred":[
        "Ta Nuk"
    ],
    "wof:name":"Ta Nuk",
    "wof:placetype":"locality"
},
  "geometry": {"coordinates":[103.77403,12.36737],"type":"Point"}
}