{
  "type": "Feature",
  "properties": {
    "gn:admin1_code":"29",
    "gn:asciiname":"Phumi Kong Hak",
    "gn:country_code":"KH",
    "gn:dem":27,
    "gn:feature_class":"P",
    "gn:feature_code":"PPL",
    "gn:name":"Phum\u012d K\u00f3ng H\u00e2k",
    "gn:population":0,
    "gn:timezone":"Asia/Phnom_Penh",
    "iso:country":"KH",
    "name:und_x_variant":[
        "Phum Kang H\u00e2t",
        "Phum\u012d K\u016dng H\u00e2k",
        "Phum\u012d K\u00f3ng H\u00e2k"
    ],
    "wof:name":"Phumi Kong Hak",
    "wof:placetype":"locality"
},
  "geometry": {"coordinates":[103.1443,12.86569],"type":"Point"}
}