{
  "type": "Feature",
  "properties": {
    "gn:admin1_code":"14",
    "gn:asciiname":"Phumi Tabot",
    "gn:country_code":"KH",
    "gn:dem":3,
    "gn:feature_class":"P",
    "gn:feature_code":"PPL",
    "gn:name":"Phum\u012d Tab\u014ft",
    "gn:population":0,
    "gn:timezone":"Asia/Phnom_Penh",
    "iso:country":"KH",
    "name:und_x_variant":[
        "Phum Taboi",
        "Phum\u012d Tab\u014ft"
    ],
    "wof:name":"Phumi Tabot",
    "wof:placetype":"locality"
},
  "geometry": {"coordinates":[105.51466000000001,10.97027],"type":"Point"}
}