{
  "type": "Feature",
  "properties": {
    "gn:country":"KH",
    "gn:fcode":"PPLX",
    "gn:population":0,
    "iso:country":"KH",
    "name:eng_x_preferred":[
        "Tuk Laak"
    ],
    "name:und_x_variant":[
        "T\u0153\u0306k L\u00f4\u00e2k"
    ],
    "qs_pg:aaroncc":"KH",
    "qs_pg:gn_country":"KH",
    "qs_pg:gn_fcode":"PPLX",
    "qs_pg:gn_pop":0,
    "qs_pg:name":"Tuk Laak",
    "qs_pg:name_adm0":"Cambodia",
    "qs_pg:name_adm1":"Phnum Penh",
    "qs_pg:photos":3184,
    "qs_pg:photos_1k":645,
    "qs_pg:photos_9k":14,
    "qs_pg:photos_9r":11,
    "qs_pg:photos_all":3184,
    "qs_pg:photos_sr":20,
    "qs_pg:pop_sr":0,
    "qs_pg:qs_pg_placetype":"neighbourhood",
    "qs_pg:qs_pg_placetype_gp":"Suburb",
    "qs_pg:woe_adm0":23424776,
    "woe:adm0_id":23424776,
    "woe:name_adm0":"Cambodia",
    "woe:name_adm1":"Phnum Penh",
    "woe:placetype":"Suburb",
    "wof:name":"Tuk Laak",
    "wof:placetype":"neighbourhood"
},
  "geometry": {"coordinates":[104.90472,11.56717],"type":"Point"}
}