{
  "type": "Feature",
  "properties": {
    "gn:admin1_code":"12",
    "gn:asciiname":"Dang Tuek Leach",
    "gn:country_code":"KH",
    "gn:dem":33,
    "gn:feature_class":"P",
    "gn:feature_code":"PPL",
    "gn:name":"Dang Tuek Leach",
    "gn:population":0,
    "gn:timezone":"Asia/Phnom_Penh",
    "iso:country":"KH",
    "name:khm_x_preferred":[
        "Dang Tuek Leach"
    ],
    "name:khm_x_variant":[
        "Phum Dong L\u00e9ak",
        "\u1797\u17bc\u1798\u17b7 \u178a\u17bc\u1784\u179b\u17b6\u1780\u17cb"
    ],
    "name:und_x_variant":[
        "Totung T\u2019ngai",
        "Phum\u012d Dong L\u00e9ak"
    ],
    "wof:name":"Dang Tuek Leach",
    "wof:placetype":"locality"
},
  "geometry": {"coordinates":[104.02134,12.46888],"type":"Point"}
}