{
  "type": "Feature",
  "properties": {
    "gn:admin1_code":"28",
    "gn:asciiname":"Kaoh Khyang",
    "gn:country_code":"KH",
    "gn:dem":4,
    "gn:feature_class":"P",
    "gn:feature_code":"PPL",
    "gn:name":"Kaoh Khyang",
    "gn:population":0,
    "gn:timezone":"Asia/Phnom_Penh",
    "iso:country":"KH",
    "name:khm_x_preferred":[
        "Kaoh Khyang"
    ],
    "name:khm_x_variant":[
        "Phum Ka\u00f4h Khch\u00e2ng",
        "\u1797\u17bc\u1798\u17b7 \u1780\u17c4\u17c7\u1781\u17d2\u1785\u1784"
    ],
    "name:und_x_variant":[
        "Kas Khchong",
        "Phum\u012d Ka\u00f4h Khch\u00e2ng"
    ],
    "wof:name":"Kaoh Khyang",
    "wof:placetype":"locality"
},
  "geometry": {"coordinates":[103.78816,10.53615],"type":"Point"}
}