{
  "type": "Feature",
  "properties": {
    "gn:admin1_code":"14",
    "gn:asciiname":"Phumi Prey Anchan",
    "gn:country_code":"KH",
    "gn:dem":8,
    "gn:feature_class":"P",
    "gn:feature_code":"PPL",
    "gn:name":"Phum\u012d Prey \u00c2nch\u0103n",
    "gn:population":0,
    "gn:timezone":"Asia/Phnom_Penh",
    "iso:country":"KH",
    "name:und_x_variant":[
        "Phum Preang Chan",
        "Phum\u012d Prey \u00c2nch\u0103n"
    ],
    "wof:name":"Phumi Prey Anchan",
    "wof:placetype":"locality"
},
  "geometry": {"coordinates":[105.36931,11.08702],"type":"Point"}
}