{
  "type": "Feature",
  "properties": {
    "gn:admin1_code":"23.0",
    "gn:asciiname":"Ka Te",
    "gn:country_code":"KH",
    "gn:dem":267,
    "gn:feature_class":"P",
    "gn:feature_code":"PPL",
    "gn:name":"Ka Te",
    "gn:population":0,
    "gn:timezone":"Asia/Phnom_Penh",
    "iso:country":"KH",
    "name:khm_x_preferred":[
        "Ka Te"
    ],
    "wof:name":"Ka Te",
    "wof:placetype":"locality"
},
  "geometry": {"coordinates":[107.30135,13.69141],"type":"Point"}
}