{
  "type": "Feature",
  "properties": {
    "gn:admin1_code":"07",
    "gn:asciiname":"Chrey Loas",
    "gn:country_code":"KH",
    "gn:dem":18,
    "gn:feature_class":"P",
    "gn:feature_code":"PPL",
    "gn:name":"Chrey Loas",
    "gn:population":0,
    "gn:timezone":"Asia/Phnom_Penh",
    "iso:country":"KH",
    "name:khm_x_preferred":[
        "Chrey Loas"
    ],
    "name:und_x_variant":[
        "Wat chrey Leas",
        "Kh\u016dm Chreg Le\u0103s",
        "Kh\u016dm Chrey Lo\u0103s"
    ],
    "wof:name":"Chrey Loas",
    "wof:placetype":"locality"
},
  "geometry": {"coordinates":[104.78719,11.72547],"type":"Point"}
}