{
  "type": "Feature",
  "properties": {
    "gn:admin1_code":"23",
    "gn:asciiname":"Srae Pok Touch",
    "gn:country_code":"KH",
    "gn:dem":99,
    "gn:feature_class":"P",
    "gn:feature_code":"PPL",
    "gn:name":"Srae Pok Touch",
    "gn:population":0,
    "gn:timezone":"Asia/Phnom_Penh",
    "iso:country":"KH",
    "name:khm_x_preferred":[
        "Srae Pok Touch"
    ],
    "name:khm_x_variant":[
        "\u1797\u17bc\u1798\u17b7 \u179f\u17d2\u179a\u17c2\u1796\u1780\u178f\u17bc\u1785",
        "Phum Sr\u00eap\u00f4k Toch"
    ],
    "name:und_x_variant":[
        "Ban Thong Sepok",
        "Phum Veal Sepok",
        "Phum V\u00e9al Sr\u00e9pok",
        "Phum\u012d Sr\u00eap\u00f4k Toch (1)"
    ],
    "wof:name":"Srae Pok Touch",
    "wof:placetype":"locality"
},
  "geometry": {"coordinates":[106.87103,13.47394],"type":"Point"}
}