{
  "type": "Feature",
  "properties": {
    "gn:admin1_code":"10",
    "gn:asciiname":"Phum Sre Chrey",
    "gn:country_code":"KH",
    "gn:dem":99,
    "gn:feature_class":"P",
    "gn:feature_code":"PPL",
    "gn:name":"Phum Sr\u00ea Chrey",
    "gn:population":0,
    "gn:timezone":"Asia/Phnom_Penh",
    "iso:country":"KH",
    "name:khm_x_preferred":[
        "Phum Sr\u00ea Chrey"
    ],
    "name:khm_x_variant":[
        "\u1797\u17bc\u1798\u17b7 \u179f\u17d2\u179a\u17c2\u1787\u17d2\u179a\u17c3"
    ],
    "wof:name":"Phum Sre Chrey",
    "wof:placetype":"locality"
},
  "geometry": {"coordinates":[106.66025,12.57635],"type":"Point"}
}