{
  "type": "Feature",
  "properties": {
    "gn:admin1_code":"12.0",
    "gn:asciiname":"Phum Anlung Moan",
    "gn:country_code":"KH",
    "gn:dem":18,
    "gn:feature_class":"P",
    "gn:feature_code":"PPL",
    "gn:name":"Phum Anl\u016dng Mo\u00e2n",
    "gn:population":0,
    "gn:timezone":"Asia/Phnom_Penh",
    "iso:country":"KH",
    "name:khm_x_preferred":[
        "Phum Anl\u016dng Mo\u00e2n"
    ],
    "name:khm_x_variant":[
        "\u1797\u17bc\u1798\u17b7 \u17a2\u1793\u17d2\u179b\u1784\u17cb\u1798\u17b6\u1793\u17cb"
    ],
    "wof:name":"Phum Anlung Moan",
    "wof:placetype":"locality"
},
  "geometry": {"coordinates":[103.88059,12.57405],"type":"Point"}
}