{
  "type": "Feature",
  "properties": {
    "gn:admin1_code":"07",
    "gn:asciiname":"Phumi Chey Otdam",
    "gn:country_code":"KH",
    "gn:dem":27,
    "gn:feature_class":"P",
    "gn:feature_code":"PPL",
    "gn:name":"Phum\u012d Chey \u014etd\u00e2m",
    "gn:population":0,
    "gn:timezone":"Asia/Phnom_Penh",
    "iso:country":"KH",
    "name:und_x_variant":[
        "Wat Kuc",
        "Phum\u012d Chey Od\u00e2m",
        "Vat Kuc",
        "Wat Kut",
        "Phum\u012d Chey \u014etd\u00e2m"
    ],
    "wof:name":"Phumi Chey Otdam",
    "wof:placetype":"locality"
},
  "geometry": {"coordinates":[104.77137999999999,11.79679],"type":"Point"}
}