{
  "type": "Feature",
  "properties": {
    "gn:admin1_code":"08",
    "gn:asciiname":"Kaoh Rong",
    "gn:country_code":"KH",
    "gn:dem":7,
    "gn:feature_class":"P",
    "gn:feature_code":"PPL",
    "gn:name":"Ka\u00f4h R\u014fng",
    "gn:population":0,
    "gn:timezone":"Asia/Phnom_Penh",
    "iso:country":"KH",
    "name:khm_x_preferred":[
        "Ka\u00f4h R\u014fng"
    ],
    "name:khm_x_variant":[
        "\u1780\u17c4\u17c7\u179a\u17bb\u1784 \u1794"
    ],
    "name:und_x_variant":[
        "Phum\u012d K\u00e2oh R\u014fng",
        "Koh Rong",
        "Ka\u00f4h R\u016dng"
    ],
    "wof:name":"Kaoh Rong",
    "wof:placetype":"locality"
},
  "geometry": {"coordinates":[103.27995,10.67763],"type":"Point"}
}