{
  "type": "Feature",
  "properties": {
    "gn:admin1_code":"05",
    "gn:asciiname":"Anlong Krasang",
    "gn:country_code":"KH",
    "gn:dem":12,
    "gn:feature_class":"P",
    "gn:feature_code":"PPL",
    "gn:name":"Anlong Kr\u00e2sang",
    "gn:population":0,
    "gn:timezone":"Asia/Phnom_Penh",
    "iso:country":"KH",
    "name:und_x_variant":[
        "Anlong Kr\u00e2sang",
        "Phum\u012d Anl\u016dng Kr\u00e2s\u0103ng",
        "Phum\u012d \u00c2nl\u00f3ng Kr\u00e2s\u0103ng"
    ],
    "wof:name":"Anlong Krasang",
    "wof:placetype":"locality"
},
  "geometry": {"coordinates":[104.98626000000002,12.72266],"type":"Point"}
}