{
  "type": "Feature",
  "properties": {
    "gn:admin1_code":"10",
    "gn:asciiname":"Phum Chhung",
    "gn:country_code":"KH",
    "gn:dem":80,
    "gn:feature_class":"P",
    "gn:feature_code":"PPL",
    "gn:name":"Phum Chhung",
    "gn:population":0,
    "gn:timezone":"Asia/Phnom_Penh",
    "iso:country":"KH",
    "name:khm_x_preferred":[
        "Phum Chhung"
    ],
    "name:khm_x_variant":[
        "\u1797\u17bc\u1798\u17b7 \u1788\u17bc\u1784"
    ],
    "name:und_x_variant":[
        "Phum\u012d Chhung (1)"
    ],
    "wof:name":"Phum Chhung",
    "wof:placetype":"locality"
},
  "geometry": {"coordinates":[106.56426999999999,12.61472],"type":"Point"}
}