{
  "type": "Feature",
  "properties": {
    "gn:admin1_code":"18",
    "gn:asciiname":"Prey Totueng",
    "gn:country_code":"KH",
    "gn:dem":9,
    "gn:feature_class":"P",
    "gn:feature_code":"PPL",
    "gn:name":"Prey Totueng",
    "gn:population":0,
    "gn:timezone":"Asia/Phnom_Penh",
    "iso:country":"KH",
    "name:khm_x_preferred":[
        "Prey Totueng"
    ],
    "name:und_x_variant":[
        "Phum Prey Thatum",
        "Phum\u012d Prey T\u00f4t\u0153\u0306ng"
    ],
    "wof:name":"Prey Totueng",
    "wof:placetype":"locality"
},
  "geometry": {"coordinates":[105.93073,11.09957],"type":"Point"}
}