{
  "type": "Feature",
  "properties": {
    "gn:admin1_code":"19",
    "gn:asciiname":"Phumi Prey Phkoam",
    "gn:country_code":"KH",
    "gn:dem":8,
    "gn:feature_class":"P",
    "gn:feature_code":"PPL",
    "gn:name":"Phum\u012d Prey Phk\u014f\u00e2m",
    "gn:population":0,
    "gn:timezone":"Asia/Phnom_Penh",
    "iso:country":"KH",
    "name:und_x_variant":[
        "Phum Prey Phkom",
        "Phum\u012d Prey Phk\u014f\u00e2m"
    ],
    "wof:name":"Phumi Prey Phkoam",
    "wof:placetype":"locality"
},
  "geometry": {"coordinates":[104.91269,11.00954],"type":"Point"}
}