{
  "type": "Feature",
  "properties": {
    "gn:admin1_code":"18",
    "gn:asciiname":"Tnaot",
    "gn:country_code":"KH",
    "gn:dem":6,
    "gn:feature_class":"P",
    "gn:feature_code":"PPL",
    "gn:name":"Tnaot",
    "gn:population":0,
    "gn:timezone":"Asia/Phnom_Penh",
    "iso:country":"KH",
    "name:khm_x_preferred":[
        "Tnaot"
    ],
    "name:und_x_variant":[
        "Phum Tnut",
        "Phum Tn\u00f4t",
        "Phum\u012d Tna\u00f4t"
    ],
    "wof:name":"Tnaot",
    "wof:placetype":"locality"
},
  "geometry": {"coordinates":[106.05051,10.89949],"type":"Point"}
}