{
  "type": "Feature",
  "properties": {
    "gn:admin1_code":"12",
    "gn:asciiname":"Phum Yon",
    "gn:country_code":"KH",
    "gn:dem":18,
    "gn:feature_class":"P",
    "gn:feature_code":"PPL",
    "gn:name":"Phum Y\u014fn",
    "gn:population":0,
    "gn:timezone":"Asia/Phnom_Penh",
    "iso:country":"KH",
    "name:khm_x_preferred":[
        "Phum Y\u014fn"
    ],
    "name:khm_x_variant":[
        "\u1797\u17bc\u1798\u17b7 \u1799\u17bb\u1793"
    ],
    "name:und_x_variant":[
        "P\u2019um T\u2019n\u014ft",
        "Phum\u012d Y\u014fn",
        "Phum\u012d Y\u016dn"
    ],
    "wof:name":"Phum Yon",
    "wof:placetype":"locality"
},
  "geometry": {"coordinates":[103.83745,12.62336],"type":"Point"}
}