{
  "type": "Feature",
  "properties": {
    "gn:admin1_code":"04",
    "gn:asciiname":"Veal Lvieng",
    "gn:country_code":"KH",
    "gn:dem":60,
    "gn:feature_class":"P",
    "gn:feature_code":"PPL",
    "gn:name":"Veal Lvieng",
    "gn:population":0,
    "gn:timezone":"Asia/Phnom_Penh",
    "iso:country":"KH",
    "name:khm_x_preferred":[
        "Veal Lvieng"
    ],
    "wof:name":"Veal Lvieng",
    "wof:placetype":"locality"
},
  "geometry": {"coordinates":[104.46314,11.18273],"type":"Point"}
}