{
  "type": "Feature",
  "properties": {
    "gn:admin1_code":"07",
    "gn:asciiname":"Kampong Kong",
    "gn:country_code":"KH",
    "gn:dem":9,
    "gn:feature_class":"P",
    "gn:feature_code":"PPL",
    "gn:name":"Kampong Kong",
    "gn:population":0,
    "gn:timezone":"Asia/Phnom_Penh",
    "iso:country":"KH",
    "name:khm_x_preferred":[
        "Kampong Kong"
    ],
    "name:khm_x_variant":[
        "Phum K\u00e2mp\u00f4ng K\u014fng",
        "\u1797\u17bc\u1798\u17b7 \u1780\u17c6\u1796\u17bb\u1784\u1780\u1784"
    ],
    "name:und_x_variant":[
        "Phum\u012d K\u00e2mp\u00f3ng K\u014fng"
    ],
    "wof:name":"Kampong Kong",
    "wof:placetype":"locality"
},
  "geometry": {"coordinates":[105.07876,11.14845],"type":"Point"}
}