{
  "type": "Feature",
  "properties": {
    "gn:admin1_code":"03",
    "gn:asciiname":"Phum Veal Pe",
    "gn:country_code":"KH",
    "gn:dem":18,
    "gn:feature_class":"P",
    "gn:feature_code":"PPL",
    "gn:name":"Phum V\u00e9al P\u00e9",
    "gn:population":0,
    "gn:timezone":"Asia/Phnom_Penh",
    "iso:country":"KH",
    "name:khm_x_preferred":[
        "Phum V\u00e9al P\u00e9"
    ],
    "name:khm_x_variant":[
        "\u1797\u17bc\u1798\u17b7 \u179c\u17b6\u179b\u1796\u17c1"
    ],
    "name:und_x_variant":[
        "Phum\u012d V\u00e9al P\u00e9"
    ],
    "wof:name":"Phum Veal Pe",
    "wof:placetype":"locality"
},
  "geometry": {"coordinates":[104.48833,12.32041],"type":"Point"}
}