{
  "type": "Feature",
  "properties": {
    "gn:admin1_code":"24",
    "gn:asciiname":"Kralanh",
    "gn:country_code":"KH",
    "gn:dem":21,
    "gn:feature_class":"P",
    "gn:feature_code":"PPLA2",
    "gn:name":"Kralanh",
    "gn:population":0,
    "gn:timezone":"Asia/Phnom_Penh",
    "iso:country":"KH",
    "name:khm_x_preferred":[
        "Kralanh"
    ],
    "name:khm_x_variant":[
        "Sala Sr\u014fk Kr\u00e2lanh"
    ],
    "wof:name":"Kralanh",
    "wof:placetype":"locality"
},
  "geometry": {"coordinates":[103.41903000000001,13.60535],"type":"Point"}
}