{
  "type": "Feature",
  "properties": {
    "gn:admin1_code":"21",
    "gn:asciiname":"Srae Knong",
    "gn:country_code":"KH",
    "gn:dem":61,
    "gn:feature_class":"P",
    "gn:feature_code":"PPL",
    "gn:name":"Srae Knong",
    "gn:population":0,
    "gn:timezone":"Asia/Phnom_Penh",
    "iso:country":"KH",
    "name:khm_x_preferred":[
        "Srae Knong"
    ],
    "name:und_x_variant":[
        "Phum\u012d Sr\u00ea Kn\u014fng"
    ],
    "wof:name":"Srae Knong",
    "wof:placetype":"locality"
},
  "geometry": {"coordinates":[104.47177000000001,10.96743],"type":"Point"}
}