{
  "type": "Feature",
  "properties": {
    "gn:admin1_code":"12",
    "gn:asciiname":"Ta Kaev Leu",
    "gn:country_code":"KH",
    "gn:dem":26,
    "gn:feature_class":"P",
    "gn:feature_code":"PPL",
    "gn:name":"Ta Kaev Leu",
    "gn:population":0,
    "gn:timezone":"Asia/Phnom_Penh",
    "iso:country":"KH",
    "name:khm_x_preferred":[
        "Ta Kaev Leu"
    ],
    "name:und_x_variant":[
        "Tak\u00e8v",
        "Phum\u012d Tak\u00eav"
    ],
    "wof:name":"Ta Kaev Leu",
    "wof:placetype":"locality"
},
  "geometry": {"coordinates":[104.00870999999999,12.52499],"type":"Point"}
}