{
  "type": "Feature",
  "properties": {
    "gn:admin1_code":"24.0",
    "gn:asciiname":"Lvea",
    "gn:country_code":"KH",
    "gn:dem":19,
    "gn:feature_class":"P",
    "gn:feature_code":"PPL",
    "gn:name":"Lvea",
    "gn:population":0,
    "gn:timezone":"Asia/Phnom_Penh",
    "iso:country":"KH",
    "name:khm_x_preferred":[
        "Lvea"
    ],
    "name:khm_x_variant":[
        "\u1797\u17bc\u1798\u17b7 \u179b\u17d2\u179c\u17b6",
        "Phum L\u00f4v\u00e9a"
    ],
    "wof:name":"Lvea",
    "wof:placetype":"locality"
},
  "geometry": {"coordinates":[104.34864,13.07699],"type":"Point"}
}