{
  "type": "Feature",
  "properties": {
    "gn:admin1_code":"14",
    "gn:asciiname":"Krouch",
    "gn:country_code":"KH",
    "gn:dem":13,
    "gn:feature_class":"P",
    "gn:feature_code":"PPL",
    "gn:name":"Krouch",
    "gn:population":0,
    "gn:timezone":"Asia/Phnom_Penh",
    "iso:country":"KH",
    "name:khm_x_preferred":[
        "Krouch"
    ],
    "wof:name":"Krouch",
    "wof:placetype":"locality"
},
  "geometry": {"coordinates":[105.48453000000001,11.19147],"type":"Point"}
}