{
  "type": "Feature",
  "properties": {
    "gn:admin1_code":"14",
    "gn:asciiname":"Cham",
    "gn:country_code":"KH",
    "gn:dem":11,
    "gn:feature_class":"P",
    "gn:feature_code":"PPL",
    "gn:name":"Cham",
    "gn:population":0,
    "gn:timezone":"Asia/Phnom_Penh",
    "iso:country":"KH",
    "name:khm_x_preferred":[
        "Cham"
    ],
    "name:und_x_variant":[
        "Phum Cham",
        "Kh\u016dm Cham"
    ],
    "wof:name":"Cham",
    "wof:placetype":"locality"
},
  "geometry": {"coordinates":[105.5436,10.99235],"type":"Point"}
}