{
  "type": "Feature",
  "properties": {
    "gn:admin1_code":"03",
    "gn:asciiname":"Voat",
    "gn:country_code":"KH",
    "gn:dem":98,
    "gn:feature_class":"P",
    "gn:feature_code":"PPL",
    "gn:name":"Voat",
    "gn:population":0,
    "gn:timezone":"Asia/Phnom_Penh",
    "iso:country":"KH",
    "name:khm_x_preferred":[
        "Voat"
    ],
    "name:nor_x_preferred":[
        "Voat"
    ],
    "name:zho_x_preferred":[
        "Voat"
    ],
    "wof:name":"Voat",
    "wof:placetype":"locality"
},
  "geometry": {"coordinates":[104.35675000000001,11.97613],"type":"Point"}
}