{
  "type": "Feature",
  "properties": {
    "gn:admin1_code":"14",
    "gn:asciiname":"Phumi Angk Nuon",
    "gn:country_code":"KH",
    "gn:dem":-2,
    "gn:feature_class":"P",
    "gn:feature_code":"PPL",
    "gn:name":"Phum\u012d \u00c2ngk Nu\u014fn",
    "gn:population":0,
    "gn:timezone":"Asia/Phnom_Penh",
    "iso:country":"KH",
    "name:und_x_variant":[
        "An Nhom",
        "Phum\u012d \u00c2ng Nu\u014fn",
        "An Nhon",
        "Phum\u012d \u00c2ngk Nu\u014fn"
    ],
    "wof:name":"Phumi Angk Nuon",
    "wof:placetype":"locality"
},
  "geometry": {"coordinates":[105.2467,10.9513],"type":"Point"}
}