{
  "type": "Feature",
  "properties": {
    "gn:admin1_code":"10",
    "gn:asciiname":"Chbar",
    "gn:country_code":"KH",
    "gn:dem":408,
    "gn:feature_class":"P",
    "gn:feature_code":"PPL",
    "gn:name":"Chbar",
    "gn:population":0,
    "gn:timezone":"Asia/Phnom_Penh",
    "iso:country":"KH",
    "name:und_x_variant":[
        "Phum\u012d Chbar",
        "Poste Deshayes",
        "Nouveau Poste Deshayes",
        "Chbar"
    ],
    "wof:name":"Chbar",
    "wof:placetype":"locality"
},
  "geometry": {"coordinates":[107.15349000000001,12.77166],"type":"Point"}
}