{
  "type": "Feature",
  "properties": {
    "gn:admin1_code":"12.0",
    "gn:asciiname":"Phum Totoeng",
    "gn:country_code":"KH",
    "gn:dem":24,
    "gn:feature_class":"P",
    "gn:feature_code":"PPL",
    "gn:name":"Phum T\u00f4t\u0153\u0306ng",
    "gn:population":0,
    "gn:timezone":"Asia/Phnom_Penh",
    "iso:country":"KH",
    "name:khm_x_preferred":[
        "Phum T\u00f4t\u0153\u0306ng"
    ],
    "name:khm_x_variant":[
        "\u1797\u17bc\u1798\u17b7 \u1791\u1791\u17b9\u1784"
    ],
    "wof:name":"Phum Totoeng",
    "wof:placetype":"locality"
},
  "geometry": {"coordinates":[103.88142000000001,12.54095],"type":"Point"}
}