{
  "type": "Feature",
  "properties": {
    "gn:admin1_code":"14",
    "gn:asciiname":"Phum Prey Russey",
    "gn:country_code":"KH",
    "gn:dem":16,
    "gn:feature_class":"P",
    "gn:feature_code":"PPL",
    "gn:name":"Phum Prey Russey",
    "gn:population":0,
    "gn:timezone":"Asia/Phnom_Penh",
    "iso:country":"KH",
    "name:und_x_variant":[
        "Phum Prey R\u016dssei",
        "Phum\u012d Prey R\u0153ssei"
    ],
    "wof:name":"Phum Prey Russey",
    "wof:placetype":"locality"
},
  "geometry": {"coordinates":[105.46989000000001,11.57395],"type":"Point"}
}