{
  "type": "Feature",
  "properties": {
    "gn:admin1_code":"23.0",
    "gn:asciiname":"Pa Dal",
    "gn:country_code":"KH",
    "gn:dem":139,
    "gn:feature_class":"P",
    "gn:feature_code":"PPL",
    "gn:name":"Pa Dal",
    "gn:population":0,
    "gn:timezone":"Asia/Phnom_Penh",
    "iso:country":"KH",
    "name:khm_x_preferred":[
        "Pa Dal"
    ],
    "wof:name":"Pa Dal",
    "wof:placetype":"locality"
},
  "geometry": {"coordinates":[107.42018,13.76891],"type":"Point"}
}