{
  "type": "Feature",
  "properties": {
    "gn:admin1_code":"03",
    "gn:asciiname":"Kampong Tralach",
    "gn:country_code":"KH",
    "gn:dem":18,
    "gn:feature_class":"P",
    "gn:feature_code":"PPL",
    "gn:name":"Kampong Tralach",
    "gn:population":0,
    "gn:timezone":"Asia/Phnom_Penh",
    "iso:country":"KH",
    "name:khm_x_preferred":[
        "Kampong Tralach"
    ],
    "name:und_x_variant":[
        "Kompong Tralach",
        "Phum\u012d K\u00e2mp\u00f3ng Tr\u00e2lach"
    ],
    "wof:name":"Kampong Tralach",
    "wof:placetype":"locality"
},
  "geometry": {"coordinates":[104.76334,11.91913],"type":"Point"}
}