{
  "type": "Feature",
  "properties": {
    "gn:admin1_code":"14",
    "gn:asciiname":"Kruoh",
    "gn:country_code":"KH",
    "gn:dem":17,
    "gn:feature_class":"P",
    "gn:feature_code":"PPL",
    "gn:name":"Kruoh",
    "gn:population":0,
    "gn:timezone":"Asia/Phnom_Penh",
    "iso:country":"KH",
    "name:khm_x_preferred":[
        "Kruoh"
    ],
    "name:und_x_variant":[
        "Phum\u012d Kru\u014fs"
    ],
    "wof:name":"Kruoh",
    "wof:placetype":"locality"
},
  "geometry": {"coordinates":[105.36703,11.63054],"type":"Point"}
}