{
  "type": "Feature",
  "properties": {
    "gn:admin1_code":"28.0",
    "gn:asciiname":"Prey Nob",
    "gn:country_code":"KH",
    "gn:dem":7,
    "gn:feature_class":"P",
    "gn:feature_code":"PPLA2",
    "gn:name":"Prey Nob",
    "gn:population":0,
    "gn:timezone":"Asia/Phnom_Penh",
    "iso:country":"KH",
    "name:khm_x_preferred":[
        "Prey Nob"
    ],
    "wof:name":"Prey Nob",
    "wof:placetype":"locality"
},
  "geometry": {"coordinates":[103.82091,10.70939],"type":"Point"}
}