{
  "type": "Feature",
  "properties": {
    "gn:admin1_code":"19",
    "gn:asciiname":"Phumi Prey Khla",
    "gn:country_code":"KH",
    "gn:dem":11,
    "gn:feature_class":"P",
    "gn:feature_code":"PPL",
    "gn:name":"Phum\u012d Prey Khla",
    "gn:population":0,
    "gn:timezone":"Asia/Phnom_Penh",
    "iso:country":"KH",
    "name:und_x_variant":[
        "Phum\u012d K\u00e2nga\u00f4k M\u00e9as",
        "Phum K\u00e2n Ngok M\u00e9as",
        "Phum\u012d Prey Khla"
    ],
    "wof:name":"Phumi Prey Khla",
    "wof:placetype":"locality"
},
  "geometry": {"coordinates":[104.88372,10.76012],"type":"Point"}
}