{
  "type": "Feature",
  "properties": {
    "gn:admin1_code":"19",
    "gn:asciiname":"Phumi Prambei Mum",
    "gn:country_code":"KH",
    "gn:dem":11,
    "gn:feature_class":"P",
    "gn:feature_code":"PPL",
    "gn:name":"Phum\u012d Pr\u0103mbei M\u016dm",
    "gn:population":0,
    "gn:timezone":"Asia/Phnom_Penh",
    "iso:country":"KH",
    "name:und_x_variant":[
        "Phum Prambey Mom",
        "Phum\u012d Pr\u0103mbei M\u016dm"
    ],
    "wof:name":"Phumi Prambei Mum",
    "wof:placetype":"locality"
},
  "geometry": {"coordinates":[104.78872,10.84425],"type":"Point"}
}