{
  "type": "Feature",
  "properties": {
    "gn:admin1_code":"19",
    "gn:asciiname":"Phumi Kus",
    "gn:country_code":"KH",
    "gn:dem":10,
    "gn:feature_class":"P",
    "gn:feature_code":"PPL",
    "gn:name":"Phum\u012d K\u016ds",
    "gn:population":0,
    "gn:timezone":"Asia/Phnom_Penh",
    "iso:country":"KH",
    "name:und_x_variant":[
        "Phnom Kus",
        "Phum\u012d K\u016dss",
        "Khum K\u016dss",
        "Kus",
        "Phum\u012d K\u016ds"
    ],
    "wof:name":"Phumi Kus",
    "wof:placetype":"locality"
},
  "geometry": {"coordinates":[104.65313,10.93944],"type":"Point"}
}