{
  "type": "Feature",
  "properties": {
    "gn:admin1_code":"07",
    "gn:asciiname":"Kampong Pou",
    "gn:country_code":"KH",
    "gn:dem":9,
    "gn:feature_class":"P",
    "gn:feature_code":"PPL",
    "gn:name":"Kampong Pou",
    "gn:population":0,
    "gn:timezone":"Asia/Phnom_Penh",
    "iso:country":"KH",
    "name:khm_x_preferred":[
        "Kampong Pou"
    ],
    "name:khm_x_variant":[
        "Phum\u012d K\u00e2mp\u00f4ng Phn\u016dm",
        "Phum K\u00e2mp\u00f4ng Phn\u016dm",
        "\u1797\u17bc\u1798\u17b7 \u1780\u17c6\u1796\u1784\u17cb\u1797\u17d2\u1793\u17c6"
    ],
    "name:und_x_variant":[
        "Phum\u012d K\u00e2mp\u00f3ng Phnum"
    ],
    "wof:name":"Kampong Pou",
    "wof:placetype":"locality"
},
  "geometry": {"coordinates":[105.25957,11.29897],"type":"Point"}
}