{
  "type": "Feature",
  "properties": {
    "gn:admin1_code":"02",
    "gn:asciiname":"Prek Pouthi",
    "gn:country_code":"KH",
    "gn:dem":18,
    "gn:feature_class":"P",
    "gn:feature_code":"PPL",
    "gn:name":"Pr\u00eak Po\u016dth\u012d",
    "gn:population":0,
    "gn:timezone":"Asia/Phnom_Penh",
    "iso:country":"KH",
    "name:und_x_variant":[
        "Prek Po",
        "Prek Po\u016dch\u0115",
        "Pr\u00eak Po\u016d",
        "P\u00f4r",
        "Prek Por",
        "Pr\u00eak Po\u016dth\u012d"
    ],
    "wof:name":"Prek Pouthi",
    "wof:placetype":"locality"
},
  "geometry": {"coordinates":[105.11293000000001,11.83451],"type":"Point"}
}