{
  "type": "Feature",
  "properties": {
    "gn:admin1_code":"24",
    "gn:asciiname":"Phumi Chub Leu",
    "gn:country_code":"KH",
    "gn:dem":88,
    "gn:feature_class":"P",
    "gn:feature_code":"PPL",
    "gn:name":"Phum\u012d Ch\u016db Leu",
    "gn:population":0,
    "gn:timezone":"Asia/Phnom_Penh",
    "iso:country":"KH",
    "name:und_x_variant":[
        "Soan Khmeng",
        "Phum\u012d Ch\u016dp Leu",
        "Spean Khmeng",
        "Phum\u012d Ch\u016db Leu"
    ],
    "wof:name":"Phumi Chub Leu",
    "wof:placetype":"locality"
},
  "geometry": {"coordinates":[104.24531,13.54963],"type":"Point"}
}