{
  "type": "Feature",
  "properties": {
    "gn:admin1_code":"05",
    "gn:asciiname":"Phumi Trapeang Roessei",
    "gn:country_code":"KH",
    "gn:dem":16,
    "gn:feature_class":"P",
    "gn:feature_code":"PPL",
    "gn:name":"Phum\u012d Tr\u00e2pe\u0103ng R\u0153ssei",
    "gn:population":0,
    "gn:timezone":"Asia/Phnom_Penh",
    "iso:country":"KH",
    "name:und_x_variant":[
        "Phum\u012d Tr\u00e2pe\u0103ng R\u016dssei",
        "Phum\u012d Tr\u00e2pe\u0103ng R\u0153ssei"
    ],
    "wof:name":"Phumi Trapeang Roessei",
    "wof:placetype":"locality"
},
  "geometry": {"coordinates":[104.76754,12.80088],"type":"Point"}
}