{
  "type": "Feature",
  "properties": {
    "gn:admin1_code":"18",
    "gn:asciiname":"Phumi Dangkieb Kdam",
    "gn:country_code":"KH",
    "gn:dem":12,
    "gn:feature_class":"P",
    "gn:feature_code":"PPL",
    "gn:name":"Phum\u012d D\u00e2ngki\u0115b Kdam",
    "gn:population":0,
    "gn:timezone":"Asia/Phnom_Penh",
    "iso:country":"KH",
    "name:und_x_variant":[
        "Phum D\u00e2ngki\u0115p Kdam",
        "Phum Dang Klep Kdam",
        "Phum\u012d D\u00e2ngki\u0115b Kdam"
    ],
    "wof:name":"Phumi Dangkieb Kdam",
    "wof:placetype":"locality"
},
  "geometry": {"coordinates":[105.7722,11.38536],"type":"Point"}
}