{
  "type": "Feature",
  "properties": {
    "gn:admin1_code":"31",
    "gn:asciiname":"Salang Pir",
    "gn:country_code":"KH",
    "gn:dem":140,
    "gn:feature_class":"P",
    "gn:feature_code":"PPL",
    "gn:name":"Salang Pir",
    "gn:population":0,
    "gn:timezone":"Asia/Phnom_Penh",
    "iso:country":"KH",
    "name:khm_x_preferred":[
        "Salang Pir"
    ],
    "wof:name":"Salang Pir",
    "wof:placetype":"locality"
},
  "geometry": {"coordinates":[106.09877,11.83577],"type":"Point"}
}