{
  "type": "Feature",
  "properties": {
    "gn:admin1_code":"23",
    "gn:asciiname":"Phumi Phleu Kraom",
    "gn:country_code":"KH",
    "gn:dem":105,
    "gn:feature_class":"P",
    "gn:feature_code":"PPL",
    "gn:name":"Phum\u012d Phleu Kra\u00f4m",
    "gn:population":0,
    "gn:timezone":"Asia/Phnom_Penh",
    "iso:country":"KH",
    "wof:name":"Phumi Phleu Kraom",
    "wof:placetype":"locality"
},
  "geometry": {"coordinates":[107.10872999999999,14.05885],"type":"Point"}
}