{
  "type": "Feature",
  "properties": {
    "gn:admin1_code":"31",
    "gn:asciiname":"Kampong Treas",
    "gn:country_code":"KH",
    "gn:dem":21,
    "gn:feature_class":"P",
    "gn:feature_code":"PPL",
    "gn:name":"Kampong Treas",
    "gn:population":0,
    "gn:timezone":"Asia/Phnom_Penh",
    "iso:country":"KH",
    "name:khm_x_preferred":[
        "Kampong Treas"
    ],
    "name:khm_x_variant":[
        "\u1797\u17bc\u1798\u17b7 \u1780\u17c6\u1796\u1784\u17cb\u1791\u17d2\u179a\u17b6\u179f",
        "Phum K\u00e2mp\u00f4ng Tr\u00e9as"
    ],
    "name:und_x_variant":[
        "Kompong Treas",
        "Phum\u012d K\u00e2mp\u00f3ng Tr\u00e9as"
    ],
    "wof:name":"Kampong Treas",
    "wof:placetype":"locality"
},
  "geometry": {"coordinates":[105.54572,12.1217],"type":"Point"}
}