{
  "type": "Feature",
  "properties": {
    "gn:admin1_code":"25",
    "gn:asciiname":"Pradak",
    "gn:country_code":"KH",
    "gn:dem":17,
    "gn:feature_class":"P",
    "gn:feature_code":"PPL",
    "gn:name":"Pradak",
    "gn:population":0,
    "gn:timezone":"Asia/Phnom_Penh",
    "iso:country":"KH",
    "name:khm_x_preferred":[
        "Pradak"
    ],
    "name:khm_x_variant":[
        "\u1797\u17bc\u1798\u17b7 \u1794\u17d2\u179a\u178a\u17b6\u1780",
        "Phum Pr\u00e2d\u0103k"
    ],
    "name:und_x_variant":[
        "Phum\u012d Pr\u00e2d\u0103k"
    ],
    "wof:name":"Pradak",
    "wof:placetype":"locality"
},
  "geometry": {"coordinates":[103.2017,13.65317],"type":"Point"}
}