{
  "type": "Feature",
  "properties": {
    "gn:admin1_code":"24",
    "gn:asciiname":"Ta Chet",
    "gn:country_code":"KH",
    "gn:dem":14,
    "gn:feature_class":"P",
    "gn:feature_code":"PPL",
    "gn:name":"Ta Chet",
    "gn:population":0,
    "gn:timezone":"Asia/Phnom_Penh",
    "iso:country":"KH",
    "name:khm_x_preferred":[
        "Ta Chet"
    ],
    "name:khm_x_variant":[
        "\u1797\u17bc\u1798\u17b7 \u178f\u17b6\u1787\u17c1\u178f",
        "Phum\u012d Ta Ch\u00e9t",
        "Phum Ta Ch\u00e9t"
    ],
    "wof:name":"Ta Chet",
    "wof:placetype":"locality"
},
  "geometry": {"coordinates":[103.74057999999999,13.40445],"type":"Point"}
}