{
  "type": "Feature",
  "properties": {
    "gn:admin1_code":"24",
    "gn:asciiname":"Doun Miev",
    "gn:country_code":"KH",
    "gn:dem":34,
    "gn:feature_class":"P",
    "gn:feature_code":"PPL",
    "gn:name":"Doun Miev",
    "gn:population":0,
    "gn:timezone":"Asia/Phnom_Penh",
    "iso:country":"KH",
    "name:khm_x_preferred":[
        "Doun Miev"
    ],
    "name:khm_x_variant":[
        "\u1797\u17bc\u1798\u17b7 \u178a\u17bc\u1793\u1798\u17c0\u179c",
        "Phum\u012d Don Mi\u0115v",
        "Phum Don Mi\u0115v"
    ],
    "wof:name":"Doun Miev",
    "wof:placetype":"locality"
},
  "geometry": {"coordinates":[103.646,13.72279],"type":"Point"}
}