{
  "type": "Feature",
  "properties": {
    "gn:admin1_code":"24",
    "gn:asciiname":"Sala",
    "gn:country_code":"KH",
    "gn:dem":22,
    "gn:feature_class":"P",
    "gn:feature_code":"PPL",
    "gn:name":"Sala",
    "gn:population":0,
    "gn:timezone":"Asia/Phnom_Penh",
    "iso:country":"KH",
    "name:khm_x_preferred":[
        "Sala"
    ],
    "name:khm_x_variant":[
        "\u1797\u17bc\u1798\u17b7 \u179f\u17b6\u179b\u17b6",
        "Phum Sala"
    ],
    "name:und_x_variant":[
        "Phum\u012d Sala"
    ],
    "wof:name":"Sala",
    "wof:placetype":"locality"
},
  "geometry": {"coordinates":[104.34993,13.16768],"type":"Point"}
}