{
  "type": "Feature",
  "properties": {
    "gn:admin1_code":"05",
    "gn:asciiname":"Mreak Kha",
    "gn:country_code":"KH",
    "gn:dem":35,
    "gn:feature_class":"P",
    "gn:feature_code":"PPL",
    "gn:name":"Mreak Kha",
    "gn:population":0,
    "gn:timezone":"Asia/Phnom_Penh",
    "iso:country":"KH",
    "name:khm_x_preferred":[
        "Mreak Kha"
    ],
    "wof:name":"Mreak Kha",
    "wof:placetype":"locality"
},
  "geometry": {"coordinates":[104.95119,13.01086],"type":"Point"}
}