{
  "type": "Feature",
  "properties": {
    "gn:admin1_code":"19",
    "gn:asciiname":"Phumi Krang Thum",
    "gn:country_code":"KH",
    "gn:dem":23,
    "gn:feature_class":"P",
    "gn:feature_code":"PPL",
    "gn:name":"Phum\u012d Kr\u0103ng Thum",
    "gn:population":0,
    "gn:timezone":"Asia/Phnom_Penh",
    "iso:country":"KH",
    "name:und_x_variant":[
        "Kr\u00e9ang Th\u00f4m",
        "Phum\u012d Krang Thom",
        "Phum\u012d Kr\u0103ng Thum"
    ],
    "wof:name":"Phumi Krang Thum",
    "wof:placetype":"locality"
},
  "geometry": {"coordinates":[104.75595,11.33311],"type":"Point"}
}