{
  "type": "Feature",
  "properties": {
    "gn:admin1_code":"25",
    "gn:asciiname":"Pou Roam Bon",
    "gn:country_code":"KH",
    "gn:dem":21,
    "gn:feature_class":"P",
    "gn:feature_code":"PPL",
    "gn:name":"Pou Roam Bon",
    "gn:population":0,
    "gn:timezone":"Asia/Phnom_Penh",
    "iso:country":"KH",
    "name:khm_x_preferred":[
        "Pou Roam Bon"
    ],
    "name:khm_x_variant":[
        "Phum Pouthib\u014fn",
        "\u1797\u17bc\u1798\u17b7 \u1796\u17c4\u1792\u17b7\u1794\u17bb\u178e\u17d2\u1799"
    ],
    "name:und_x_variant":[
        "Phum\u012d Pouthib\u014fn",
        "Phum\u012d Po\u016dth\u012d B\u014fny"
    ],
    "wof:name":"Pou Roam Bon",
    "wof:placetype":"locality"
},
  "geometry": {"coordinates":[103.24405,13.73519],"type":"Point"}
}