{
  "type": "Feature",
  "properties": {
    "gn:admin1_code":"02",
    "gn:asciiname":"Phumi Tuol",
    "gn:country_code":"KH",
    "gn:dem":12,
    "gn:feature_class":"P",
    "gn:feature_code":"PPL",
    "gn:name":"Phum\u012d Tu\u014fl",
    "gn:population":0,
    "gn:timezone":"Asia/Phnom_Penh",
    "iso:country":"KH",
    "wof:name":"Phumi Tuol",
    "wof:placetype":"locality"
},
  "geometry": {"coordinates":[104.96294,11.99729],"type":"Point"}
}