{
  "type": "Feature",
  "properties": {
    "gn:admin1_code":"24",
    "gn:asciiname":"Ta Yaek",
    "gn:country_code":"KH",
    "gn:dem":32,
    "gn:feature_class":"P",
    "gn:feature_code":"PPL",
    "gn:name":"Ta Yaek",
    "gn:population":0,
    "gn:timezone":"Asia/Phnom_Penh",
    "iso:country":"KH",
    "name:khm_x_preferred":[
        "Ta Yaek"
    ],
    "name:khm_x_variant":[
        "\u1797\u17bc\u1798\u17b7 \u178f\u17b6\u1799\u17c9\u17c2\u1780",
        "Phum Ta Y\u00eak"
    ],
    "name:und_x_variant":[
        "Phum\u012d Ta Y\u00eak (1)"
    ],
    "wof:name":"Ta Yaek",
    "wof:placetype":"locality"
},
  "geometry": {"coordinates":[104.17138,13.29566],"type":"Point"}
}