{
  "type": "Feature",
  "properties": {
    "gn:admin1_code":"12.0",
    "gn:asciiname":"Phum Kouk Ta Kun",
    "gn:country_code":"KH",
    "gn:dem":18,
    "gn:feature_class":"P",
    "gn:feature_code":"PPL",
    "gn:name":"Phum Ko\u016dk Ta K\u016dn",
    "gn:population":0,
    "gn:timezone":"Asia/Phnom_Penh",
    "iso:country":"KH",
    "name:khm_x_preferred":[
        "Phum Ko\u016dk Ta K\u016dn"
    ],
    "name:khm_x_variant":[
        "\u1797\u17bc\u1798\u17b7 \u1782\u17c4\u1780\u178f\u17b6\u1782\u17bb\u1793"
    ],
    "wof:name":"Phum Kouk Ta Kun",
    "wof:placetype":"locality"
},
  "geometry": {"coordinates":[103.82572,12.63974],"type":"Point"}
}