{
  "type": "Feature",
  "properties": {
    "gn:admin1_code":"23.0",
    "gn:asciiname":"Ou Plong",
    "gn:country_code":"KH",
    "gn:dem":115,
    "gn:feature_class":"P",
    "gn:feature_code":"PPL",
    "gn:name":"Ou Plong",
    "gn:population":0,
    "gn:timezone":"Asia/Phnom_Penh",
    "iso:country":"KH",
    "name:khm_x_preferred":[
        "Ou Plong"
    ],
    "wof:name":"Ou Plong",
    "wof:placetype":"locality"
},
  "geometry": {"coordinates":[106.77739,13.58459],"type":"Point"}
}