{
  "type": "Feature",
  "properties": {
    "gn:admin1_code":"31",
    "gn:asciiname":"Phumi Krasang",
    "gn:country_code":"KH",
    "gn:dem":121,
    "gn:feature_class":"P",
    "gn:feature_code":"PPL",
    "gn:name":"Phum\u012d Kr\u00e2s\u0103ng",
    "gn:population":0,
    "gn:timezone":"Asia/Phnom_Penh",
    "iso:country":"KH",
    "name:und_x_variant":[
        "Phum Krassang",
        "Phum\u012d Kr\u00e2s\u0103ng"
    ],
    "wof:name":"Phumi Krasang",
    "wof:placetype":"locality"
},
  "geometry": {"coordinates":[105.98333,11.88333],"type":"Point"}
}