{
  "type": "Feature",
  "properties": {
    "gn:admin1_code":"12",
    "gn:asciiname":"Krouch Chhmar",
    "gn:country_code":"KH",
    "gn:dem":32,
    "gn:feature_class":"P",
    "gn:feature_code":"PPL",
    "gn:name":"Krouch Chhmar",
    "gn:population":0,
    "gn:timezone":"Asia/Phnom_Penh",
    "iso:country":"KH",
    "name:khm_x_preferred":[
        "Krouch Chhmar"
    ],
    "wof:name":"Krouch Chhmar",
    "wof:placetype":"locality"
},
  "geometry": {"coordinates":[103.78256,12.36326],"type":"Point"}
}