{
  "type": "Feature",
  "properties": {
    "gn:admin1_code":"29",
    "gn:asciiname":"Kantueu Pir",
    "gn:country_code":"KH",
    "gn:dem":28,
    "gn:feature_class":"P",
    "gn:feature_code":"PPL",
    "gn:name":"Kantueu Pir",
    "gn:population":0,
    "gn:timezone":"Asia/Phnom_Penh",
    "iso:country":"KH",
    "name:khm_x_preferred":[
        "Kantueu Pir"
    ],
    "name:khm_x_variant":[
        "\u1783\u17bb\u17c6\u1780\u1793\u17d2\u1791\u17ba \u17e2"
    ],
    "name:pol_x_preferred":[
        "Kantueu Pir"
    ],
    "name:spa_x_preferred":[
        "Kantueu Pir"
    ],
    "wof:name":"Kantueu Pir",
    "wof:placetype":"locality"
},
  "geometry": {"coordinates":[103.13821,12.93163],"type":"Point"}
}