{
  "type": "Feature",
  "properties": {
    "gn:admin1_code":"29",
    "gn:asciiname":"Kampong Pnov",
    "gn:country_code":"KH",
    "gn:dem":32,
    "gn:feature_class":"P",
    "gn:feature_code":"PPL",
    "gn:name":"Kampong Pnov",
    "gn:population":0,
    "gn:timezone":"Asia/Phnom_Penh",
    "iso:country":"KH",
    "name:khm_x_preferred":[
        "Kampong Pnov"
    ],
    "name:und_x_variant":[
        "Phum\u012d K\u00e2mp\u00f3ng Phn\u014fu"
    ],
    "wof:name":"Kampong Pnov",
    "wof:placetype":"locality"
},
  "geometry": {"coordinates":[102.87121999999999,13.22816],"type":"Point"}
}