{
  "type": "Feature",
  "properties": {
    "gn:admin1_code":"14",
    "gn:asciiname":"Preaek Pnov",
    "gn:country_code":"KH",
    "gn:dem":18,
    "gn:feature_class":"P",
    "gn:feature_code":"PPL",
    "gn:name":"Preaek Pnov",
    "gn:population":0,
    "gn:timezone":"Asia/Phnom_Penh",
    "iso:country":"KH",
    "name:khm_x_preferred":[
        "Preaek Pnov"
    ],
    "name:und_x_variant":[
        "Phum\u012d Pr\u00eak Pn\u014fu"
    ],
    "wof:name":"Preaek Pnov",
    "wof:placetype":"locality"
},
  "geometry": {"coordinates":[105.32749,11.86893],"type":"Point"}
}