{
  "type": "Feature",
  "properties": {
    "gn:admin1_code":"12.0",
    "gn:asciiname":"Phum Barivas",
    "gn:country_code":"KH",
    "gn:dem":22,
    "gn:feature_class":"P",
    "gn:feature_code":"PPL",
    "gn:name":"Phum B\u00e2rivas",
    "gn:population":0,
    "gn:timezone":"Asia/Phnom_Penh",
    "iso:country":"KH",
    "name:khm_x_preferred":[
        "Phum B\u00e2rivas"
    ],
    "name:khm_x_variant":[
        "\u1797\u17bc\u1798\u17b7 \u1794\u179a\u17b7\u179c\u17c9\u17b6\u179f"
    ],
    "wof:name":"Phum Barivas",
    "wof:placetype":"locality"
},
  "geometry": {"coordinates":[103.85574,12.51151],"type":"Point"}
}