{
  "type": "Feature",
  "properties": {
    "gn:admin1_code":"09",
    "gn:asciiname":"Phum Khsatt",
    "gn:country_code":"KH",
    "gn:dem":26,
    "gn:feature_class":"P",
    "gn:feature_code":"PPL",
    "gn:name":"Phum Khsatt",
    "gn:population":0,
    "gn:timezone":"Asia/Phnom_Penh",
    "iso:country":"KH",
    "name:khm_x_preferred":[
        "Phum Khsatt"
    ],
    "name:khm_x_variant":[
        "\u1797\u17bc\u1798\u17b7 \u1781\u17d2\u179f\u17b6\u178f\u17cb"
    ],
    "name:und_x_variant":[
        "Phum Ksat",
        "Phum\u012d Khs\u00e2t"
    ],
    "wof:name":"Phum Khsatt",
    "wof:placetype":"locality"
},
  "geometry": {"coordinates":[105.92255,12.33419],"type":"Point"}
}