{
  "type": "Feature",
  "properties": {
    "gn:admin1_code":"07",
    "gn:asciiname":"Krang Yov",
    "gn:country_code":"KH",
    "gn:dem":13,
    "gn:feature_class":"P",
    "gn:feature_code":"PPL",
    "gn:name":"Krang Yov",
    "gn:population":0,
    "gn:timezone":"Asia/Phnom_Penh",
    "iso:country":"KH",
    "name:khm_x_preferred":[
        "Krang Yov"
    ],
    "name:und_x_variant":[
        "Krang You",
        "Phum\u012d \u00c2mp\u012dl Kr\u00e2nh\u0115nh"
    ],
    "wof:name":"Krang Yov",
    "wof:placetype":"locality"
},
  "geometry": {"coordinates":[104.94092999999999,11.28364],"type":"Point"}
}