{
  "type": "Feature",
  "properties": {
    "gn:admin1_code":"23",
    "gn:asciiname":"Phumi Kes Chong Nay",
    "gn:country_code":"KH",
    "gn:dem":299,
    "gn:feature_class":"P",
    "gn:feature_code":"PPL",
    "gn:name":"Phum\u012d K\u00eas Ch\u014fng N\u00e2y",
    "gn:population":0,
    "gn:timezone":"Asia/Phnom_Penh",
    "iso:country":"KH",
    "wof:name":"Phumi Kes Chong Nay",
    "wof:placetype":"locality"
},
  "geometry": {"coordinates":[107.21666999999999,13.76667],"type":"Point"}
}