{
  "type": "Feature",
  "properties": {
    "gn:admin1_code":"17",
    "gn:asciiname":"Dan Loung",
    "gn:country_code":"KH",
    "gn:dem":67,
    "gn:feature_class":"P",
    "gn:feature_code":"PPL",
    "gn:name":"Dan Loung",
    "gn:population":0,
    "gn:timezone":"Asia/Phnom_Penh",
    "iso:country":"KH",
    "name:khm_x_preferred":[
        "Dan Loung"
    ],
    "name:und_x_variant":[
        "Ban Thalavang",
        "Phum\u012d D\u00e2n Lo\u016dng (2)"
    ],
    "wof:name":"Dan Loung",
    "wof:placetype":"locality"
},
  "geometry": {"coordinates":[106.35936,14.03697],"type":"Point"}
}