{
  "type": "Feature",
  "properties": {
    "gn:admin1_code":"29",
    "gn:asciiname":"Phum Tuol Sneng",
    "gn:country_code":"KH",
    "gn:dem":19,
    "gn:feature_class":"P",
    "gn:feature_code":"PPL",
    "gn:name":"Phum Tu\u014fl Sn\u00eang",
    "gn:population":0,
    "gn:timezone":"Asia/Phnom_Penh",
    "iso:country":"KH",
    "name:khm_x_preferred":[
        "Phum Tu\u014fl Sn\u00eang"
    ],
    "name:khm_x_variant":[
        "\u1797\u17bc\u1798\u17b7 \u1791\u17bd\u179b\u179f\u17d2\u1793\u17c2\u1784"
    ],
    "name:und_x_variant":[
        "Phum\u012d Tu\u014fl Sn\u00eang"
    ],
    "wof:name":"Phum Tuol Sneng",
    "wof:placetype":"locality"
},
  "geometry": {"coordinates":[103.29583,12.84412],"type":"Point"}
}