{
  "type": "Feature",
  "properties": {
    "gn:admin1_code":"19",
    "gn:asciiname":"Phumi Kampong Youl",
    "gn:country_code":"KH",
    "gn:dem":9,
    "gn:feature_class":"P",
    "gn:feature_code":"PPL",
    "gn:name":"Phum\u012d K\u00e2mp\u00f3ng Yo\u016dl",
    "gn:population":0,
    "gn:timezone":"Asia/Phnom_Penh",
    "iso:country":"KH",
    "name:und_x_variant":[
        "Phum Kompong Vol",
        "Phum Kompong Yol",
        "Phum\u012d K\u00e2mp\u00f3ng Yo\u016dl"
    ],
    "wof:name":"Phumi Kampong Youl",
    "wof:placetype":"locality"
},
  "geometry": {"coordinates":[104.93589,10.90225],"type":"Point"}
}