{
  "type": "Feature",
  "properties": {
    "gn:admin1_code":"14",
    "gn:asciiname":"Phumi Svay Teab",
    "gn:country_code":"KH",
    "gn:dem":19,
    "gn:feature_class":"P",
    "gn:feature_code":"PPL",
    "gn:name":"Phum\u012d Svay T\u00e9ab",
    "gn:population":0,
    "gn:timezone":"Asia/Phnom_Penh",
    "iso:country":"KH",
    "name:und_x_variant":[
        "Phum\u012d Svay T\u00e9ap",
        "Phum\u012d Svay T\u00e9ab"
    ],
    "wof:name":"Phumi Svay Teab",
    "wof:placetype":"locality"
},
  "geometry": {"coordinates":[105.43556,11.71919],"type":"Point"}
}