{
  "type": "Feature",
  "properties": {
    "gn:admin1_code":"14",
    "gn:asciiname":"Phum Ngik Ngouk",
    "gn:country_code":"KH",
    "gn:dem":7,
    "gn:feature_class":"P",
    "gn:feature_code":"PPL",
    "gn:name":"Phum Ngik Ngo\u016dk",
    "gn:population":0,
    "gn:timezone":"Asia/Phnom_Penh",
    "iso:country":"KH",
    "name:khm_x_preferred":[
        "Phum Ngik Ngo\u016dk"
    ],
    "name:khm_x_variant":[
        "\u1797\u17bc\u1798\u17b7 \u1784\u17b8\u1780\u1784\u17c4\u1780",
        "Phum\u012d Ngik Ngo\u016dk"
    ],
    "wof:name":"Phum Ngik Ngouk",
    "wof:placetype":"locality"
},
  "geometry": {"coordinates":[105.31518,11.25272],"type":"Point"}
}