{
  "type": "Feature",
  "properties": {
    "gn:admin1_code":"09",
    "gn:asciiname":"Kampong Damrei",
    "gn:country_code":"KH",
    "gn:dem":29,
    "gn:feature_class":"P",
    "gn:feature_code":"PPL",
    "gn:name":"Kampong Damrei",
    "gn:population":0,
    "gn:timezone":"Asia/Phnom_Penh",
    "iso:country":"KH",
    "name:khm_x_preferred":[
        "Kampong Damrei"
    ],
    "wof:name":"Kampong Damrei",
    "wof:placetype":"locality"
},
  "geometry": {"coordinates":[106.07727,12.11433],"type":"Point"}
}