{
  "type": "Feature",
  "properties": {
    "gn:admin1_code":"29",
    "gn:asciiname":"Phumi Kamping Puoy",
    "gn:country_code":"KH",
    "gn:dem":29,
    "gn:feature_class":"P",
    "gn:feature_code":"PPL",
    "gn:name":"Phum\u012d K\u00e2mping Pu\u014fy",
    "gn:population":0,
    "gn:timezone":"Asia/Phnom_Penh",
    "iso:country":"KH",
    "name:und_x_variant":[
        "Phum\u012d K\u00e2mp\u0153ng Pu\u014fy",
        "Phum\u012d K\u00e2mping Pu\u014fy"
    ],
    "wof:name":"Phumi Kamping Puoy",
    "wof:placetype":"locality"
},
  "geometry": {"coordinates":[102.89803000000001,13.12183],"type":"Point"}
}