{
  "type": "Feature",
  "properties": {
    "gn:admin1_code":"25",
    "gn:asciiname":"Anlong Thngan Lech",
    "gn:country_code":"KH",
    "gn:dem":15,
    "gn:feature_class":"P",
    "gn:feature_code":"PPL",
    "gn:name":"Anlong Thngan Lech",
    "gn:population":0,
    "gn:timezone":"Asia/Phnom_Penh",
    "iso:country":"KH",
    "name:khm_x_preferred":[
        "Anlong Thngan Lech"
    ],
    "name:und_x_variant":[
        "Phum\u012d \u00c2nl\u016dng Thngan",
        "Phum Anlong Thngon",
        "Phum\u012d \u00c2nl\u00f3ng Thng\u0103n"
    ],
    "wof:name":"Anlong Thngan Lech",
    "wof:placetype":"locality"
},
  "geometry": {"coordinates":[102.98649,13.51414],"type":"Point"}
}