{
  "type": "Feature",
  "properties": {
    "gn:admin1_code":"4.0",
    "gn:asciiname":"Phum Prey Chheuteal",
    "gn:country_code":"KH",
    "gn:dem":48,
    "gn:feature_class":"P",
    "gn:feature_code":"PPL",
    "gn:name":"Phum Prey Chheut\u00e9al",
    "gn:population":0,
    "gn:timezone":"Asia/Phnom_Penh",
    "iso:country":"KH",
    "name:khm_x_preferred":[
        "Phum Prey Chheut\u00e9al"
    ],
    "name:khm_x_variant":[
        "\u1797\u17bc\u1798\u17b7 \u1796\u17d2\u179a\u17c3\u1788\u17be\u1791\u17b6\u179b"
    ],
    "wof:name":"Phum Prey Chheuteal",
    "wof:placetype":"locality"
},
  "geometry": {"coordinates":[104.49276999999999,11.50823],"type":"Point"}
}