{
  "type": "Feature",
  "properties": {
    "gn:admin1_code":"04",
    "gn:asciiname":"Pheari Mean Chey",
    "gn:country_code":"KH",
    "gn:dem":39,
    "gn:feature_class":"P",
    "gn:feature_code":"PPL",
    "gn:name":"Pheari Mean Chey",
    "gn:population":0,
    "gn:timezone":"Asia/Phnom_Penh",
    "iso:country":"KH",
    "name:khm_x_preferred":[
        "Pheari Mean Chey"
    ],
    "wof:name":"Pheari Mean Chey",
    "wof:placetype":"locality"
},
  "geometry": {"coordinates":[104.61391999999999,11.19972],"type":"Point"}
}