{
  "type": "Feature",
  "properties": {
    "gn:admin1_code":"18.0",
    "gn:asciiname":"Trapeang Phlong",
    "gn:country_code":"KH",
    "gn:dem":10,
    "gn:feature_class":"P",
    "gn:feature_code":"PPL",
    "gn:name":"Trapeang Phlong",
    "gn:population":0,
    "gn:timezone":"Asia/Phnom_Penh",
    "iso:country":"KH",
    "name:khm_x_preferred":[
        "Trapeang Phlong"
    ],
    "name:khm_x_variant":[
        "\u1797\u17bc\u1798\u17b7 \u178f\u17d2\u179a\u1796\u17b6\u17c6\u1784\u1795\u17d2\u179b\u17bb\u1784",
        "Phum Tr\u00e2pe\u0103ng Phl\u014fng"
    ],
    "wof:name":"Trapeang Phlong",
    "wof:placetype":"locality"
},
  "geometry": {"coordinates":[106.10187000000001,11.0052],"type":"Point"}
}