{
  "type": "Feature",
  "properties": {
    "gn:admin1_code":"21",
    "gn:asciiname":"Phumi Krang Sbov",
    "gn:country_code":"KH",
    "gn:dem":25,
    "gn:feature_class":"P",
    "gn:feature_code":"PPL",
    "gn:name":"Phum\u012d Kr\u0103ng Sbov",
    "gn:population":0,
    "gn:timezone":"Asia/Phnom_Penh",
    "iso:country":"KH",
    "name:und_x_variant":[
        "Phum Krang Sbau",
        "Phum\u012d Kr\u0103ng Sbov"
    ],
    "wof:name":"Phumi Krang Sbov",
    "wof:placetype":"locality"
},
  "geometry": {"coordinates":[104.50360999999999,10.7942],"type":"Point"}
}