{
  "type": "Feature",
  "properties": {
    "gn:admin1_code":"24.0",
    "gn:asciiname":"Kouk Snuol",
    "gn:country_code":"KH",
    "gn:dem":40,
    "gn:feature_class":"P",
    "gn:feature_code":"PPL",
    "gn:name":"Kouk Snuol",
    "gn:population":0,
    "gn:timezone":"Asia/Phnom_Penh",
    "iso:country":"KH",
    "name:khm_x_preferred":[
        "Kouk Snuol"
    ],
    "name:khm_x_variant":[
        "Phum Thmei",
        "\u1797\u17bc\u1798\u17b7 \u1790\u17d2\u1798\u17b8"
    ],
    "wof:name":"Kouk Snuol",
    "wof:placetype":"locality"
},
  "geometry": {"coordinates":[103.74468,13.68351],"type":"Point"}
}