{
  "type": "Feature",
  "properties": {
    "gn:admin1_code":"29",
    "gn:asciiname":"Phum Prey Khleng",
    "gn:country_code":"KH",
    "gn:dem":22,
    "gn:feature_class":"P",
    "gn:feature_code":"PPL",
    "gn:name":"Phum Prey Khl\u00eang",
    "gn:population":0,
    "gn:timezone":"Asia/Phnom_Penh",
    "iso:country":"KH",
    "name:khm_x_preferred":[
        "Phum Prey Khl\u00eang"
    ],
    "name:khm_x_variant":[
        "\u1797\u17bc\u1798\u17b7 \u1796\u17d2\u179a\u17c3\u1781\u17d2\u179b\u17c2\u1784"
    ],
    "name:und_x_variant":[
        "Prey Khling",
        "Phum\u012d Prey Khl\u00eang"
    ],
    "wof:name":"Phum Prey Khleng",
    "wof:placetype":"locality"
},
  "geometry": {"coordinates":[103.29617,12.76561],"type":"Point"}
}