{
  "type": "Feature",
  "properties": {
    "gn:admin1_code":"12",
    "gn:asciiname":"Phumi Banhnha Khel",
    "gn:country_code":"KH",
    "gn:dem":11,
    "gn:feature_class":"P",
    "gn:feature_code":"PPL",
    "gn:name":"Phum\u012d B\u00e2nhnha Kh\u00eal",
    "gn:population":0,
    "gn:timezone":"Asia/Phnom_Penh",
    "iso:country":"KH",
    "name:und_x_variant":[
        "Phum\u012d Panha Kh\u00eal",
        "P\u2019um Ph\u0115i Kel",
        "Phum\u012d B\u00e2nhnha Kh\u00eal"
    ],
    "wof:name":"Phumi Banhnha Khel",
    "wof:placetype":"locality"
},
  "geometry": {"coordinates":[104.07158,12.67842],"type":"Point"}
}