{
  "type": "Feature",
  "properties": {
    "gn:admin1_code":"24.0",
    "gn:asciiname":"Kouk Thlok Leu",
    "gn:country_code":"KH",
    "gn:dem":24,
    "gn:feature_class":"P",
    "gn:feature_code":"PPL",
    "gn:name":"Kouk Thlok Leu",
    "gn:population":0,
    "gn:timezone":"Asia/Phnom_Penh",
    "iso:country":"KH",
    "name:khm_x_preferred":[
        "Kouk Thlok Leu"
    ],
    "name:khm_x_variant":[
        "Ko\u016dk Thl\u014fk"
    ],
    "wof:name":"Kouk Thlok Leu",
    "wof:placetype":"locality"
},
  "geometry": {"coordinates":[104.34567,13.19868],"type":"Point"}
}