{
  "type": "Feature",
  "properties": {
    "gn:admin1_code":"19",
    "gn:asciiname":"Otdam Souriya",
    "gn:country_code":"KH",
    "gn:dem":17,
    "gn:feature_class":"P",
    "gn:feature_code":"PPL",
    "gn:name":"Otdam Souriya",
    "gn:population":0,
    "gn:timezone":"Asia/Phnom_Penh",
    "iso:country":"KH",
    "name:khm_x_preferred":[
        "Otdam Souriya"
    ],
    "wof:name":"Otdam Souriya",
    "wof:placetype":"locality"
},
  "geometry": {"coordinates":[104.70636,11.06365],"type":"Point"}
}