{
  "type": "Feature",
  "properties": {
    "gn:admin1_code":"31",
    "gn:asciiname":"Phumi Trapeang Sangke",
    "gn:country_code":"KH",
    "gn:dem":31,
    "gn:feature_class":"P",
    "gn:feature_code":"PPL",
    "gn:name":"Phum\u012d Tr\u00e2pe\u0103ng S\u00e2ngk\u00ea",
    "gn:population":0,
    "gn:timezone":"Asia/Phnom_Penh",
    "iso:country":"KH",
    "name:und_x_variant":[
        "Phum Trapeang Sangker",
        "Phum\u012d Tr\u00e2pe\u0103ng S\u00e2ngk\u00ea"
    ],
    "wof:name":"Phumi Trapeang Sangke",
    "wof:placetype":"locality"
},
  "geometry": {"coordinates":[105.78534000000001,11.86805],"type":"Point"}
}