{
  "type": "Feature",
  "properties": {
    "gn:admin1_code":"02",
    "gn:asciiname":"Sdaeung Chey",
    "gn:country_code":"KH",
    "gn:dem":24,
    "gn:feature_class":"P",
    "gn:feature_code":"PPL",
    "gn:name":"Sdaeung Chey",
    "gn:population":0,
    "gn:timezone":"Asia/Phnom_Penh",
    "iso:country":"KH",
    "name:khm_x_preferred":[
        "Sdaeung Chey"
    ],
    "name:und_x_variant":[
        "Sdong Chei",
        "Sdong Chey",
        "Phum\u012d Sdaeung Chey"
    ],
    "wof:name":"Sdaeung Chey",
    "wof:placetype":"locality"
},
  "geometry": {"coordinates":[105.06838,12.10089],"type":"Point"}
}