{
  "type": "Feature",
  "properties": {
    "gn:admin1_code":"31",
    "gn:asciiname":"Romeas Choul",
    "gn:country_code":"KH",
    "gn:dem":58,
    "gn:feature_class":"P",
    "gn:feature_code":"PPL",
    "gn:name":"Romeas Choul",
    "gn:population":0,
    "gn:timezone":"Asia/Phnom_Penh",
    "iso:country":"KH",
    "name:khm_x_preferred":[
        "Romeas Choul"
    ],
    "name:und_x_variant":[
        "Phum\u012d R\u00f4m\u00e9as Chol"
    ],
    "wof:name":"Romeas Choul",
    "wof:placetype":"locality"
},
  "geometry": {"coordinates":[106.14530999999999,11.78078],"type":"Point"}
}