{
  "type": "Feature",
  "properties": {
    "gn:admin1_code":"18",
    "gn:asciiname":"Prey Thum",
    "gn:country_code":"KH",
    "gn:dem":9,
    "gn:feature_class":"P",
    "gn:feature_code":"PPL",
    "gn:name":"Prey Thum",
    "gn:population":0,
    "gn:timezone":"Asia/Phnom_Penh",
    "iso:country":"KH",
    "name:khm_x_preferred":[
        "Prey Thum"
    ],
    "name:und_x_variant":[
        "Phum\u012d Prey Thom",
        "Kh\u016dm Prey Thum"
    ],
    "wof:name":"Prey Thum",
    "wof:placetype":"locality"
},
  "geometry": {"coordinates":[105.86875000000001,10.98619],"type":"Point"}
}