{
  "type": "Feature",
  "properties": {
    "gn:admin1_code":"25",
    "gn:asciiname":"Phum Khai Dan",
    "gn:country_code":"KH",
    "gn:dem":32,
    "gn:feature_class":"P",
    "gn:feature_code":"PPL",
    "gn:name":"Phum Khai D\u00e2n",
    "gn:population":0,
    "gn:timezone":"Asia/Phnom_Penh",
    "iso:country":"KH",
    "name:khm_x_preferred":[
        "\u1797\u17bc\u1798\u17b7 \u1781\u17c3\u178a\u1793"
    ],
    "name:und_x_variant":[
        "Phum Khai D\u00e2n",
        "Phum Thmei",
        "Phum\u012d Khai D\u00e2n"
    ],
    "wof:name":"Phum Khai Dan",
    "wof:placetype":"locality"
},
  "geometry": {"coordinates":[102.65307,13.6031],"type":"Point"}
}