{
  "type": "Feature",
  "properties": {
    "gn:admin1_code":"09",
    "gn:asciiname":"Phum Roloch",
    "gn:country_code":"KH",
    "gn:dem":34,
    "gn:feature_class":"P",
    "gn:feature_code":"PPL",
    "gn:name":"Phum R\u00f4l\u00f4ch",
    "gn:population":0,
    "gn:timezone":"Asia/Phnom_Penh",
    "iso:country":"KH",
    "name:khm_x_preferred":[
        "Phum R\u00f4l\u00f4ch"
    ],
    "name:khm_x_variant":[
        "\u1797\u17bc\u1798\u17b7 \u179a\u179b\u1785"
    ],
    "wof:name":"Phum Roloch",
    "wof:placetype":"locality"
},
  "geometry": {"coordinates":[106.23257,12.41059],"type":"Point"}
}