{
  "type": "Feature",
  "properties": {
    "gn:admin1_code":"02",
    "gn:asciiname":"Roveang",
    "gn:country_code":"KH",
    "gn:dem":25,
    "gn:feature_class":"P",
    "gn:feature_code":"PPL",
    "gn:name":"Roveang",
    "gn:population":0,
    "gn:timezone":"Asia/Phnom_Penh",
    "iso:country":"KH",
    "name:khm_x_preferred":[
        "Roveang"
    ],
    "name:und_x_variant":[
        "Robeang",
        "Phum\u012d R\u00f4vi\u0115ng"
    ],
    "wof:name":"Roveang",
    "wof:placetype":"locality"
},
  "geometry": {"coordinates":[105.01922999999999,12.03927],"type":"Point"}
}