{
  "type": "Feature",
  "properties": {
    "gn:admin1_code":"29",
    "gn:asciiname":"Phum Kam Chat",
    "gn:country_code":"KH",
    "gn:dem":152,
    "gn:feature_class":"P",
    "gn:feature_code":"PPL",
    "gn:name":"Phum K\u00e2m Ch\u0103t",
    "gn:population":0,
    "gn:timezone":"Asia/Phnom_Penh",
    "iso:country":"KH",
    "name:khm_x_preferred":[
        "Phum K\u00e2m Ch\u0103t"
    ],
    "name:khm_x_variant":[
        "\u1797\u17bc\u1798\u17b7 \u1780\u17c6\u1785\u17b6\u178f\u17cb"
    ],
    "name:und_x_variant":[
        "Phum Kom Chat"
    ],
    "wof:name":"Phum Kam Chat",
    "wof:placetype":"locality"
},
  "geometry": {"coordinates":[102.81511999999999,12.69153],"type":"Point"}
}