{
  "type": "Feature",
  "properties": {
    "gn:admin1_code":"04",
    "gn:asciiname":"Prey Rumduol",
    "gn:country_code":"KH",
    "gn:dem":72,
    "gn:feature_class":"P",
    "gn:feature_code":"PPL",
    "gn:name":"Prey Rumduol",
    "gn:population":0,
    "gn:timezone":"Asia/Phnom_Penh",
    "iso:country":"KH",
    "name:khm_x_preferred":[
        "Prey Rumduol"
    ],
    "wof:name":"Prey Rumduol",
    "wof:placetype":"locality"
},
  "geometry": {"coordinates":[104.32143000000001,11.38603],"type":"Point"}
}