{
  "type": "Feature",
  "properties": {
    "gn:admin1_code":"24",
    "gn:asciiname":"Phumi O Kraom",
    "gn:country_code":"KH",
    "gn:dem":19,
    "gn:feature_class":"P",
    "gn:feature_code":"PPL",
    "gn:name":"Phum\u012d O Kra\u00f4m",
    "gn:population":0,
    "gn:timezone":"Asia/Phnom_Penh",
    "iso:country":"KH",
    "name:khm_x_preferred":[
        "Ou"
    ],
    "name:und_x_variant":[
        "Phum\u012d O Kra\u00f4m"
    ],
    "wof:name":"Phumi O Kraom",
    "wof:placetype":"locality"
},
  "geometry": {"coordinates":[104.21666999999999,13.18333],"type":"Point"}
}