{
  "type": "Feature",
  "properties": {
    "gn:admin1_code":"19",
    "gn:asciiname":"Phumi Peaream",
    "gn:country_code":"KH",
    "gn:dem":10,
    "gn:feature_class":"P",
    "gn:feature_code":"PPL",
    "gn:name":"Phum\u012d P\u00e9ar\u00e9am",
    "gn:population":0,
    "gn:timezone":"Asia/Phnom_Penh",
    "iso:country":"KH",
    "name:und_x_variant":[
        "Vat Bant\u00e9aiciy",
        "Phum\u012d P\u00e9ar\u00e9am"
    ],
    "wof:name":"Phumi Peaream",
    "wof:placetype":"locality"
},
  "geometry": {"coordinates":[104.85554,11.23428],"type":"Point"}
}