{
  "type": "Feature",
  "properties": {
    "gn:admin1_code":"31",
    "gn:asciiname":"Phumi O Popul",
    "gn:country_code":"KH",
    "gn:dem":26,
    "gn:feature_class":"P",
    "gn:feature_code":"PPL",
    "gn:name":"Phum\u012d O P\u00f4pul",
    "gn:population":0,
    "gn:timezone":"Asia/Phnom_Penh",
    "iso:country":"KH",
    "name:und_x_variant":[
        "Phum \u00d4 Popil",
        "Phum\u012d O P\u00f4pul"
    ],
    "wof:name":"Phumi O Popul",
    "wof:placetype":"locality"
},
  "geometry": {"coordinates":[105.53958,11.77515],"type":"Point"}
}