{
  "type": "Feature",
  "properties": {
    "gn:admin1_code":"12",
    "gn:asciiname":"Paen",
    "gn:country_code":"KH",
    "gn:dem":33,
    "gn:feature_class":"P",
    "gn:feature_code":"PPL",
    "gn:name":"Paen",
    "gn:population":0,
    "gn:timezone":"Asia/Phnom_Penh",
    "iso:country":"KH",
    "name:khm_x_preferred":[
        "Paen"
    ],
    "name:und_x_variant":[
        "Phum\u012d P\u00ean"
    ],
    "wof:name":"Paen",
    "wof:placetype":"locality"
},
  "geometry": {"coordinates":[103.7872,12.36737],"type":"Point"}
}