{
  "type": "Feature",
  "properties": {
    "gn:admin1_code":"27",
    "gn:asciiname":"Ta Bun",
    "gn:country_code":"KH",
    "gn:dem":66,
    "gn:feature_class":"P",
    "gn:feature_code":"PPL",
    "gn:name":"Ta Bun",
    "gn:population":0,
    "gn:timezone":"Asia/Phnom_Penh",
    "iso:country":"KH",
    "name:khm_x_preferred":[
        "Ta Bun"
    ],
    "wof:name":"Ta Bun",
    "wof:placetype":"locality"
},
  "geometry": {"coordinates":[104.17708,14.31207],"type":"Point"}
}