{
  "type": "Feature",
  "properties": {
    "gn:admin1_code":"14",
    "gn:asciiname":"Ta Mouy",
    "gn:country_code":"KH",
    "gn:dem":8,
    "gn:feature_class":"P",
    "gn:feature_code":"PPL",
    "gn:name":"Ta Mouy",
    "gn:population":0,
    "gn:timezone":"Asia/Phnom_Penh",
    "iso:country":"KH",
    "name:khm_x_preferred":[
        "Ta Mouy"
    ],
    "wof:name":"Ta Mouy",
    "wof:placetype":"locality"
},
  "geometry": {"coordinates":[105.38432,11.0556],"type":"Point"}
}