{
  "type": "Feature",
  "properties": {
    "gn:admin1_code":"23.0",
    "gn:asciiname":"Mai Hie",
    "gn:country_code":"KH",
    "gn:dem":128,
    "gn:feature_class":"P",
    "gn:feature_code":"PPL",
    "gn:name":"Mai Hie",
    "gn:population":0,
    "gn:timezone":"Asia/Phnom_Penh",
    "iso:country":"KH",
    "name:khm_x_preferred":[
        "Mai Hie"
    ],
    "wof:name":"Mai Hie",
    "wof:placetype":"locality"
},
  "geometry": {"coordinates":[107.35318999999998,13.88022],"type":"Point"}
}