{
  "type": "Feature",
  "properties": {
    "gn:admin1_code":"07",
    "gn:asciiname":"Preaek Andoung",
    "gn:country_code":"KH",
    "gn:dem":9,
    "gn:feature_class":"P",
    "gn:feature_code":"PPL",
    "gn:name":"Preaek Andoung",
    "gn:population":0,
    "gn:timezone":"Asia/Phnom_Penh",
    "iso:country":"KH",
    "name:khm_x_preferred":[
        "Preaek Andoung"
    ],
    "name:khm_x_variant":[
        "Phum\u012d Pr\u00eak \u00c2ndong",
        "Phum Pr\u00eak \u00c2ndong",
        "\u1797\u17bc\u1798\u17b7 \u1796\u17d2\u179a\u17c2\u1780\u17a2\u178e\u17d2\u178a\u17bc\u1784"
    ],
    "wof:name":"Preaek Andoung",
    "wof:placetype":"locality"
},
  "geometry": {"coordinates":[105.14394,11.12577],"type":"Point"}
}