{
  "type": "Feature",
  "properties": {
    "gn:admin1_code":"13",
    "gn:asciiname":"Kampot",
    "gn:country_code":"KH",
    "gn:dem":64,
    "gn:feature_class":"P",
    "gn:feature_code":"PPL",
    "gn:name":"Kampot",
    "gn:population":0,
    "gn:timezone":"Asia/Phnom_Penh",
    "iso:country":"KH",
    "name:khm_x_preferred":[
        "Kampot"
    ],
    "wof:name":"Kampot",
    "wof:placetype":"locality"
},
  "geometry": {"coordinates":[105.12623000000001,13.36281],"type":"Point"}
}