{
  "type": "Feature",
  "properties": {
    "gn:admin1_code":"22",
    "gn:asciiname":"Sangkat Boeng Salang",
    "gn:country_code":"KH",
    "gn:dem":14,
    "gn:feature_class":"P",
    "gn:feature_code":"PPL",
    "gn:name":"Sangkat Boeng Salang",
    "gn:population":0,
    "gn:timezone":"Asia/Phnom_Penh",
    "iso:country":"KH",
    "wof:name":"Sangkat Boeng Salang",
    "wof:placetype":"locality"
},
  "geometry": {"coordinates":[104.89472000000001,11.55278],"type":"Point"}
}