{
  "type": "Feature",
  "properties": {
    "gn:admin1_code":"04",
    "gn:asciiname":"Phumi Bak Ka",
    "gn:country_code":"KH",
    "gn:dem":51,
    "gn:feature_class":"P",
    "gn:feature_code":"PPL",
    "gn:name":"Phum\u012d B\u0103k K\u00e2",
    "gn:population":0,
    "gn:timezone":"Asia/Phnom_Penh",
    "iso:country":"KH",
    "name:und_x_variant":[
        "Vat Bakka",
        "Phum\u012d B\u0103k K\u00e2"
    ],
    "wof:name":"Phumi Bak Ka",
    "wof:placetype":"locality"
},
  "geometry": {"coordinates":[104.63728,11.31215],"type":"Point"}
}