{
  "type": "Feature",
  "properties": {
    "gn:admin1_code":"23",
    "gn:asciiname":"Phumi Mong Toch",
    "gn:country_code":"KH",
    "gn:dem":234,
    "gn:feature_class":"P",
    "gn:feature_code":"PPL",
    "gn:name":"Phum\u012d M\u00f4ng Toch",
    "gn:population":0,
    "gn:timezone":"Asia/Phnom_Penh",
    "iso:country":"KH",
    "wof:name":"Phumi Mong Toch",
    "wof:placetype":"locality"
},
  "geometry": {"coordinates":[107.10592,13.5985],"type":"Point"}
}