{
  "type": "Feature",
  "properties": {
    "gn:admin1_code":"12.0",
    "gn:asciiname":"Phum Sdok Khtom",
    "gn:country_code":"KH",
    "gn:dem":24,
    "gn:feature_class":"P",
    "gn:feature_code":"PPL",
    "gn:name":"Phum Sd\u014fk Kht\u014fm",
    "gn:population":0,
    "gn:timezone":"Asia/Phnom_Penh",
    "iso:country":"KH",
    "name:khm_x_preferred":[
        "Phum Sd\u014fk Kht\u014fm"
    ],
    "name:khm_x_variant":[
        "\u1797\u17bc\u1798\u17b7 \u179f\u17d2\u178a\u1780\u1781\u17d2\u1791\u17c6"
    ],
    "wof:name":"Phum Sdok Khtom",
    "wof:placetype":"locality"
},
  "geometry": {"coordinates":[103.84010000000001,12.55566],"type":"Point"}
}