{
  "type": "Feature",
  "properties": {
    "gn:admin1_code":"31",
    "gn:asciiname":"Tuol Kruos",
    "gn:country_code":"KH",
    "gn:dem":83,
    "gn:feature_class":"P",
    "gn:feature_code":"PPL",
    "gn:name":"Tuol Kruos",
    "gn:population":0,
    "gn:timezone":"Asia/Phnom_Penh",
    "iso:country":"KH",
    "name:khm_x_preferred":[
        "Tuol Kruos"
    ],
    "wof:name":"Tuol Kruos",
    "wof:placetype":"locality"
},
  "geometry": {"coordinates":[106.26062,11.89261],"type":"Point"}
}