{
  "type": "Feature",
  "properties": {
    "gn:admin1_code":"05",
    "gn:asciiname":"Phumi Prey Nutthea",
    "gn:country_code":"KH",
    "gn:dem":22,
    "gn:feature_class":"P",
    "gn:feature_code":"PPL",
    "gn:name":"Phum\u012d Prey N\u016dtth\u00e9a",
    "gn:population":0,
    "gn:timezone":"Asia/Phnom_Penh",
    "iso:country":"KH",
    "name:und_x_variant":[
        "Kasom\u00e2k",
        "Phum\u012d Prey N\u016dth\u00e9a",
        "Phum\u012d Prey N\u016dtth\u00e9a"
    ],
    "wof:name":"Phumi Prey Nutthea",
    "wof:placetype":"locality"
},
  "geometry": {"coordinates":[104.95717999999999,12.81845],"type":"Point"}
}