{
  "type": "Feature",
  "properties": {
    "gn:admin1_code":"24",
    "gn:asciiname":"Phum Snaor",
    "gn:country_code":"KH",
    "gn:dem":17,
    "gn:feature_class":"P",
    "gn:feature_code":"PPL",
    "gn:name":"Phum Sna\u00f4r",
    "gn:population":0,
    "gn:timezone":"Asia/Phnom_Penh",
    "iso:country":"KH",
    "name:khm_x_preferred":[
        "Phum Sna\u00f4r"
    ],
    "name:khm_x_variant":[
        "\u1797\u17bc\u1798\u17b7 \u179f\u17d2\u1793\u17c4\u179a"
    ],
    "name:und_x_variant":[
        "Phum\u012d Sna\u00f4r"
    ],
    "wof:name":"Phum Snaor",
    "wof:placetype":"locality"
},
  "geometry": {"coordinates":[104.32167,13.09533],"type":"Point"}
}