{
  "type": "Feature",
  "properties": {
    "gn:admin1_code":"31",
    "gn:asciiname":"Phumi Damnak Chrey",
    "gn:country_code":"KH",
    "gn:dem":17,
    "gn:feature_class":"P",
    "gn:feature_code":"PPL",
    "gn:name":"Phum\u012d D\u00e2mn\u0103k Chrey",
    "gn:population":0,
    "gn:timezone":"Asia/Phnom_Penh",
    "iso:country":"KH",
    "name:und_x_variant":[
        "Damnek Chrey",
        "Phum\u012d D\u00e2mn\u0103k Chrey"
    ],
    "wof:name":"Phumi Damnak Chrey",
    "wof:placetype":"locality"
},
  "geometry": {"coordinates":[105.5615,11.97349],"type":"Point"}
}