{
  "type": "Feature",
  "properties": {
    "gn:admin1_code":"22",
    "gn:asciiname":"Prey Thum",
    "gn:country_code":"KH",
    "gn:dem":18,
    "gn:feature_class":"P",
    "gn:feature_code":"PPL",
    "gn:name":"Prey Thum",
    "gn:population":0,
    "gn:timezone":"Asia/Phnom_Penh",
    "iso:country":"KH",
    "name:khm_x_preferred":[
        "Prey Thum"
    ],
    "wof:name":"Prey Thum",
    "wof:placetype":"locality"
},
  "geometry": {"coordinates":[104.84519,11.50446],"type":"Point"}
}