{
  "type": "Feature",
  "properties": {
    "gn:admin1_code":"29",
    "gn:asciiname":"Phum Tuol Ta Aon",
    "gn:country_code":"KH",
    "gn:dem":10,
    "gn:feature_class":"P",
    "gn:feature_code":"PPL",
    "gn:name":"Phum Tu\u014fl Ta A\u00f4n",
    "gn:population":0,
    "gn:timezone":"Asia/Phnom_Penh",
    "iso:country":"KH",
    "name:khm_x_preferred":[
        "Phum Tu\u014fl Ta A\u00f4n"
    ],
    "name:khm_x_variant":[
        "\u1797\u17bc\u1798\u17b7 \u1791\u17bd\u179b\u178f\u17b6\u17b1\u1793"
    ],
    "wof:name":"Phum Tuol Ta Aon",
    "wof:placetype":"locality"
},
  "geometry": {"coordinates":[103.41682,12.8884],"type":"Point"}
}