{
  "type": "Feature",
  "properties": {
    "gn:admin1_code":"14.0",
    "gn:asciiname":"Phum O Leay",
    "gn:country_code":"KH",
    "gn:dem":14,
    "gn:feature_class":"P",
    "gn:feature_code":"PPL",
    "gn:name":"Phum O L\u00e9ay",
    "gn:population":0,
    "gn:timezone":"Asia/Phnom_Penh",
    "iso:country":"KH",
    "name:khm_x_preferred":[
        "Phum O L\u00e9ay"
    ],
    "name:khm_x_variant":[
        "\u1797\u17bc\u1798\u17b7 \u17a2\u17bc\u179b\u17b6\u179c"
    ],
    "wof:name":"Phum O Leay",
    "wof:placetype":"locality"
},
  "geometry": {"coordinates":[105.32451,11.47878],"type":"Point"}
}