{
  "type": "Feature",
  "properties": {
    "gn:admin1_code":"24",
    "gn:asciiname":"Phum Phleung Chheh",
    "gn:country_code":"KH",
    "gn:dem":19,
    "gn:feature_class":"P",
    "gn:feature_code":"PPL",
    "gn:name":"Phum Phleung Chh\u0115h",
    "gn:population":0,
    "gn:timezone":"Asia/Phnom_Penh",
    "iso:country":"KH",
    "name:khm_x_preferred":[
        "Phum Phleung Chh\u0115h"
    ],
    "name:khm_x_variant":[
        "\u1797\u17bc\u1798\u17b7 \u1797\u17d2\u179b\u17be\u1784\u1786\u17c1\u17c7"
    ],
    "name:und_x_variant":[
        "Phum Flungche",
        "Phum\u012d Phleung Chh\u00e9h"
    ],
    "wof:name":"Phum Phleung Chheh",
    "wof:placetype":"locality"
},
  "geometry": {"coordinates":[104.32908999999999,13.12],"type":"Point"}
}