{
  "type": "Feature",
  "properties": {
    "gn:admin1_code":"03",
    "gn:asciiname":"Srae Andoung",
    "gn:country_code":"KH",
    "gn:dem":54,
    "gn:feature_class":"P",
    "gn:feature_code":"PPL",
    "gn:name":"Srae Andoung",
    "gn:population":0,
    "gn:timezone":"Asia/Phnom_Penh",
    "iso:country":"KH",
    "name:khm_x_preferred":[
        "Srae Andoung"
    ],
    "wof:name":"Srae Andoung",
    "wof:placetype":"locality"
},
  "geometry": {"coordinates":[104.51669,11.7416],"type":"Point"}
}