{
  "type": "Feature",
  "properties": {
    "gn:admin1_code":"31",
    "gn:asciiname":"Phumi Tep Pranamm",
    "gn:country_code":"KH",
    "gn:dem":18,
    "gn:feature_class":"P",
    "gn:feature_code":"PPL",
    "gn:name":"Phum\u012d T\u00e9p Pr\u00e2n\u00e2mm",
    "gn:population":0,
    "gn:timezone":"Asia/Phnom_Penh",
    "iso:country":"KH",
    "name:und_x_variant":[
        "Wat Tep Pronom",
        "Tep Pranam",
        "Phum\u012d T\u00e9p Pr\u00e2n\u00e2mm"
    ],
    "wof:name":"Phumi Tep Pranamm",
    "wof:placetype":"locality"
},
  "geometry": {"coordinates":[105.76667,11.81667],"type":"Point"}
}