{
  "type": "Feature",
  "properties": {
    "gn:admin1_code":"18",
    "gn:asciiname":"Phumi Andong",
    "gn:country_code":"KH",
    "gn:dem":5,
    "gn:feature_class":"P",
    "gn:feature_code":"PPL",
    "gn:name":"Phum\u012d \u00c2ndong",
    "gn:population":0,
    "gn:timezone":"Asia/Phnom_Penh",
    "iso:country":"KH",
    "name:und_x_variant":[
        "Phum Audong",
        "Phum Amdong",
        "Phum\u012d \u00c2ndong"
    ],
    "wof:name":"Phumi Andong",
    "wof:placetype":"locality"
},
  "geometry": {"coordinates":[105.63481000000002,11.13269],"type":"Point"}
}