{
  "type": "Feature",
  "properties": {
    "gn:admin1_code":"28",
    "gn:asciiname":"Veal Renh",
    "gn:country_code":"KH",
    "gn:dem":10,
    "gn:feature_class":"P",
    "gn:feature_code":"PPL",
    "gn:name":"Veal Renh",
    "gn:population":0,
    "gn:timezone":"Asia/Phnom_Penh",
    "iso:country":"KH",
    "name:khm_x_preferred":[
        "Veal Renh"
    ],
    "name:khm_x_variant":[
        "\u1797\u17bc\u1798\u17b7 \u179c\u17b6\u179b\u179a\u17c1\u1789",
        "Phum V\u00e9al R\u00e9nh"
    ],
    "name:und_x_variant":[
        "V\u00e9al R\u00e9nh",
        "Phum\u012d V\u00e9al R\u00e9nh"
    ],
    "wof:name":"Veal Renh",
    "wof:placetype":"locality"
},
  "geometry": {"coordinates":[103.81583999999999,10.71714],"type":"Point"}
}