{
  "type": "Feature",
  "properties": {
    "gn:admin1_code":"29",
    "gn:asciiname":"Koun K'aek Pir",
    "gn:country_code":"KH",
    "gn:dem":22,
    "gn:feature_class":"P",
    "gn:feature_code":"PPL",
    "gn:name":"Koun K\u2019aek Pir",
    "gn:population":0,
    "gn:timezone":"Asia/Phnom_Penh",
    "iso:country":"KH",
    "name:khm_x_preferred":[
        "Koun K\u2019aek Pir"
    ],
    "wof:name":"Koun K'aek Pir",
    "wof:placetype":"locality"
},
  "geometry": {"coordinates":[103.43248,12.73291],"type":"Point"}
}