{
  "type": "Feature",
  "properties": {
    "gn:admin1_code":"24.0",
    "gn:asciiname":"Srah",
    "gn:country_code":"KH",
    "gn:dem":32,
    "gn:feature_class":"P",
    "gn:feature_code":"PPL",
    "gn:name":"Srah",
    "gn:population":0,
    "gn:timezone":"Asia/Phnom_Penh",
    "iso:country":"KH",
    "name:khm_x_preferred":[
        "Srah"
    ],
    "wof:name":"Srah",
    "wof:placetype":"locality"
},
  "geometry": {"coordinates":[103.77742000000001,13.55845],"type":"Point"}
}