{
  "type": "Feature",
  "properties": {
    "gn:admin1_code":"14.0",
    "gn:asciiname":"Phum Prey Damrei",
    "gn:country_code":"KH",
    "gn:dem":13,
    "gn:feature_class":"P",
    "gn:feature_code":"PPL",
    "gn:name":"Phum Prey D\u00e2mrei",
    "gn:population":0,
    "gn:timezone":"Asia/Phnom_Penh",
    "iso:country":"KH",
    "name:khm_x_preferred":[
        "Phum Prey D\u00e2mrei"
    ],
    "name:khm_x_variant":[
        "\u1797\u17bc\u1798\u17b7 \u1796\u17d2\u179a\u17c3\u178a\u17c6\u179a\u17b8"
    ],
    "wof:name":"Phum Prey Damrei",
    "wof:placetype":"locality"
},
  "geometry": {"coordinates":[105.39421000000002,11.27751],"type":"Point"}
}