{
  "type": "Feature",
  "properties": {
    "gn:admin1_code":"07",
    "gn:asciiname":"Chheu Tea",
    "gn:country_code":"KH",
    "gn:dem":14,
    "gn:feature_class":"P",
    "gn:feature_code":"PPL",
    "gn:name":"Chheu Tea",
    "gn:population":0,
    "gn:timezone":"Asia/Phnom_Penh",
    "iso:country":"KH",
    "name:khm_x_preferred":[
        "Chheu Tea"
    ],
    "wof:name":"Chheu Tea",
    "wof:placetype":"locality"
},
  "geometry": {"coordinates":[104.98090999999999,11.75513],"type":"Point"}
}