{
  "type": "Feature",
  "properties": {
    "gn:admin1_code":"18",
    "gn:asciiname":"Angk Sala",
    "gn:country_code":"KH",
    "gn:dem":12,
    "gn:feature_class":"P",
    "gn:feature_code":"PPL",
    "gn:name":"Angk Sala",
    "gn:population":0,
    "gn:timezone":"Asia/Phnom_Penh",
    "iso:country":"KH",
    "name:khm_x_preferred":[
        "Angk Sala"
    ],
    "name:khm_x_variant":[
        "\u1797\u17bc\u1798\u17b7 \u17a2\u1784\u17d2\u1782\u179f\u17b6\u179b\u17b6"
    ],
    "name:und_x_variant":[
        "Phum\u012d \u00c2ng Sala",
        "Phum\u012d \u00c2ngk Sala"
    ],
    "wof:name":"Angk Sala",
    "wof:placetype":"locality"
},
  "geometry": {"coordinates":[106.05866,11.03537],"type":"Point"}
}