{
  "type": "Feature",
  "properties": {
    "gn:admin1_code":"03",
    "gn:asciiname":"Phum O Svay",
    "gn:country_code":"KH",
    "gn:dem":48,
    "gn:feature_class":"P",
    "gn:feature_code":"PPL",
    "gn:name":"Phum O Svay",
    "gn:population":0,
    "gn:timezone":"Asia/Phnom_Penh",
    "iso:country":"KH",
    "name:khm_x_preferred":[
        "Phum O Svay"
    ],
    "name:khm_x_variant":[
        "\u1797\u17bc\u1798\u17b7 \u17a2\u17bc\u179a\u179f\u17d2\u179c\u17b6\u1799"
    ],
    "name:und_x_variant":[
        "Phum\u012d O Svay"
    ],
    "wof:name":"Phum O Svay",
    "wof:placetype":"locality"
},
  "geometry": {"coordinates":[104.42595,12.23689],"type":"Point"}
}