{
  "type": "Feature",
  "properties": {
    "gn:admin1_code":"27.0",
    "gn:asciiname":"Chamkar Chek",
    "gn:country_code":"KH",
    "gn:dem":241,
    "gn:feature_class":"P",
    "gn:feature_code":"PPL",
    "gn:name":"Chamkar Chek",
    "gn:population":0,
    "gn:timezone":"Asia/Phnom_Penh",
    "iso:country":"KH",
    "name:khm_x_preferred":[
        "Chamkar Chek"
    ],
    "wof:name":"Chamkar Chek",
    "wof:placetype":"locality"
},
  "geometry": {"coordinates":[103.69193,14.41623],"type":"Point"}
}