{
  "type": "Feature",
  "properties": {
    "gn:admin1_code":"03",
    "gn:asciiname":"Phumi Kaoh Bor",
    "gn:country_code":"KH",
    "gn:dem":11,
    "gn:feature_class":"P",
    "gn:feature_code":"PPL",
    "gn:name":"Phum\u012d Ka\u00f4h Bor",
    "gn:population":0,
    "gn:timezone":"Asia/Phnom_Penh",
    "iso:country":"KH",
    "name:und_x_variant":[
        "Phum\u012d Ka\u00f4h Bo",
        "Phum\u012d Ka\u00f4h Bor"
    ],
    "wof:name":"Phumi Kaoh Bor",
    "wof:placetype":"locality"
},
  "geometry": {"coordinates":[104.85833,12.37018],"type":"Point"}
}