{
  "type": "Feature",
  "properties": {
    "gn:admin1_code":"19",
    "gn:asciiname":"Phumi Sdok",
    "gn:country_code":"KH",
    "gn:dem":33,
    "gn:feature_class":"P",
    "gn:feature_code":"PPL",
    "gn:name":"Phum\u012d Sd\u014fk",
    "gn:population":0,
    "gn:timezone":"Asia/Phnom_Penh",
    "iso:country":"KH",
    "name:und_x_variant":[
        "Sdok",
        "Phum\u012d Sd\u014fk"
    ],
    "wof:name":"Phumi Sdok",
    "wof:placetype":"locality"
},
  "geometry": {"coordinates":[104.75145000000001,11.27965],"type":"Point"}
}