{
  "type": "Feature",
  "properties": {
    "gn:admin1_code":"07",
    "gn:asciiname":"Phumi Thmei",
    "gn:country_code":"KH",
    "gn:dem":14,
    "gn:feature_class":"P",
    "gn:feature_code":"PPL",
    "gn:name":"Phum\u012d Thmei",
    "gn:population":0,
    "gn:timezone":"Asia/Phnom_Penh",
    "iso:country":"KH",
    "name:und_x_variant":[
        "Thmey",
        "Phum\u012d Thmei"
    ],
    "wof:name":"Phumi Thmei",
    "wof:placetype":"locality"
},
  "geometry": {"coordinates":[104.93686,11.79383],"type":"Point"}
}