{
  "type": "Feature",
  "properties": {
    "gn:admin1_code":"29",
    "gn:asciiname":"Phum Prey Khlot",
    "gn:country_code":"KH",
    "gn:dem":28,
    "gn:feature_class":"P",
    "gn:feature_code":"PPL",
    "gn:name":"Phum Prey Khlot",
    "gn:population":0,
    "gn:timezone":"Asia/Phnom_Penh",
    "iso:country":"KH",
    "name:khm_x_preferred":[
        "Phum Prey Khlot"
    ],
    "name:khm_x_variant":[
        "\u1797\u17bc\u1798\u17b7 \u1796\u17d2\u179a\u17c3\u1780\u17d2\u179b\u17bc\u178f"
    ],
    "wof:name":"Phum Prey Khlot",
    "wof:placetype":"locality"
},
  "geometry": {"coordinates":[103.48685999999999,12.6034],"type":"Point"}
}