{
  "type": "Feature",
  "properties": {
    "gn:admin1_code":"22",
    "gn:asciiname":"Phumi Chrouy Ampil",
    "gn:country_code":"KH",
    "gn:dem":17,
    "gn:feature_class":"P",
    "gn:feature_code":"PPL",
    "gn:name":"Phum\u012d Chro\u016dy \u00c2mp\u012dl",
    "gn:population":0,
    "gn:timezone":"Asia/Phnom_Penh",
    "iso:country":"KH",
    "name:und_x_variant":[
        "Phum Chruy Ampil",
        "Phum\u012d Chro\u016dy \u00c2mp\u012dl"
    ],
    "wof:name":"Phumi Chrouy Ampil",
    "wof:placetype":"locality"
},
  "geometry": {"coordinates":[105.0044,11.53279],"type":"Point"}
}