{
  "type": "Feature",
  "properties": {
    "gn:admin1_code":"23",
    "gn:asciiname":"Phumi Lum Bang",
    "gn:country_code":"KH",
    "gn:dem":293,
    "gn:feature_class":"P",
    "gn:feature_code":"PPL",
    "gn:name":"Phum\u012d Lum Bang",
    "gn:population":0,
    "gn:timezone":"Asia/Phnom_Penh",
    "iso:country":"KH",
    "wof:name":"Phumi Lum Bang",
    "wof:placetype":"locality"
},
  "geometry": {"coordinates":[107.10259000000001,13.80433],"type":"Point"}
}