{
  "type": "Feature",
  "properties": {
    "gn:admin1_code":"24.0",
    "gn:asciiname":"Phum Trapeang Putrea",
    "gn:country_code":"KH",
    "gn:dem":16,
    "gn:feature_class":"P",
    "gn:feature_code":"PPL",
    "gn:name":"Phum Tr\u00e2pe\u0103ng P\u016dtrea",
    "gn:population":0,
    "gn:timezone":"Asia/Phnom_Penh",
    "iso:country":"KH",
    "name:khm_x_preferred":[
        "Phum Tr\u00e2pe\u0103ng P\u016dtrea"
    ],
    "name:khm_x_variant":[
        "\u1797\u17bc\u1798\u17b7 \u178f\u17d2\u179a\u1796\u17b6\u17c6\u1784\u1796\u17bb\u1791\u17d2\u179a\u17b6"
    ],
    "wof:name":"Phum Trapeang Putrea",
    "wof:placetype":"locality"
},
  "geometry": {"coordinates":[103.87222,13.33462],"type":"Point"}
}