{
  "type": "Feature",
  "properties": {
    "gn:admin1_code":"02",
    "gn:asciiname":"Trapeang Lpov",
    "gn:country_code":"KH",
    "gn:dem":55,
    "gn:feature_class":"P",
    "gn:feature_code":"PPL",
    "gn:name":"Trapeang Lpov",
    "gn:population":0,
    "gn:timezone":"Asia/Phnom_Penh",
    "iso:country":"KH",
    "name:khm_x_preferred":[
        "Trapeang Lpov"
    ],
    "wof:name":"Trapeang Lpov",
    "wof:placetype":"locality"
},
  "geometry": {"coordinates":[105.38661999999999,12.31111],"type":"Point"}
}