{
  "type": "Feature",
  "properties": {
    "gn:admin1_code":"05",
    "gn:asciiname":"Phumi Preal",
    "gn:country_code":"KH",
    "gn:dem":56,
    "gn:feature_class":"P",
    "gn:feature_code":"PPL",
    "gn:name":"Phum\u012d Pr\u00e9al",
    "gn:population":0,
    "gn:timezone":"Asia/Phnom_Penh",
    "iso:country":"KH",
    "name:und_x_variant":[
        "Priel",
        "Phum\u012d Pr\u00e9al"
    ],
    "wof:name":"Phumi Preal",
    "wof:placetype":"locality"
},
  "geometry": {"coordinates":[105.08401000000001,13.5882],"type":"Point"}
}