{
  "type": "Feature",
  "properties": {
    "gn:admin1_code":"05",
    "gn:asciiname":"Phumi Trapeang Thvea",
    "gn:country_code":"KH",
    "gn:dem":76,
    "gn:feature_class":"P",
    "gn:feature_code":"PPL",
    "gn:name":"Phum\u012d Tr\u00e2pe\u0103ng Thv\u00e9a",
    "gn:population":0,
    "gn:timezone":"Asia/Phnom_Penh",
    "iso:country":"KH",
    "name:und_x_variant":[
        "Ban Trapeang Sva",
        "Phum Trapeang Sra",
        "Phum Trapeang Sva",
        "Phum Trapeang Svay",
        "Phum\u012d Tr\u00e2pe\u0103ng Thv\u00e9a"
    ],
    "wof:name":"Phumi Trapeang Thvea",
    "wof:placetype":"locality"
},
  "geometry": {"coordinates":[105.39704,12.69848],"type":"Point"}
}