{
  "type": "Feature",
  "properties": {
    "gn:admin1_code":"04",
    "gn:asciiname":"Phumi Thmei",
    "gn:country_code":"KH",
    "gn:dem":41,
    "gn:feature_class":"P",
    "gn:feature_code":"PPL",
    "gn:name":"Phum\u012d Thmei",
    "gn:population":0,
    "gn:timezone":"Asia/Phnom_Penh",
    "iso:country":"KH",
    "name:und_x_variant":[
        "Phum Tr\u00e2peang Chr\u00e2ni\u00e9ng",
        "Phum\u012d Thmei"
    ],
    "wof:name":"Phumi Thmei",
    "wof:placetype":"locality"
},
  "geometry": {"coordinates":[104.59249,11.53922],"type":"Point"}
}