{
  "type": "Feature",
  "properties": {
    "gn:admin1_code":"22",
    "gn:asciiname":"Kab Phluk",
    "gn:country_code":"KH",
    "gn:dem":21,
    "gn:feature_class":"P",
    "gn:feature_code":"PPL",
    "gn:name":"Kab Phluk",
    "gn:population":0,
    "gn:timezone":"Asia/Phnom_Penh",
    "iso:country":"KH",
    "name:khm_x_preferred":[
        "Kab Phluk"
    ],
    "name:und_x_variant":[
        "K\u0103p Phlouk",
        "Phum\u012d K\u00e2p Phl\u016dk",
        "Phum\u012d K\u00e1b Phl\u016dk"
    ],
    "wof:name":"Kab Phluk",
    "wof:placetype":"locality"
},
  "geometry": {"coordinates":[104.80816,11.50367],"type":"Point"}
}