{
  "type": "Feature",
  "properties": {
    "gn:admin1_code":"29",
    "gn:asciiname":"Phum Tuol Sanlang",
    "gn:country_code":"KH",
    "gn:dem":12,
    "gn:feature_class":"P",
    "gn:feature_code":"PPL",
    "gn:name":"Phum Tu\u014fl S\u00e2nl\u00e2ng",
    "gn:population":0,
    "gn:timezone":"Asia/Phnom_Penh",
    "iso:country":"KH",
    "name:khm_x_preferred":[
        "Phum Tu\u014fl S\u00e2nl\u00e2ng"
    ],
    "name:khm_x_variant":[
        "\u1797\u17bc\u1798\u17b7 \u1791\u17bd\u179b\u179f\u1793\u17cb\u17a1\u1784\u17cb"
    ],
    "name:und_x_variant":[
        "Phum\u012d Tu\u014fl S\u00e1nl\u00e1ng"
    ],
    "wof:name":"Phum Tuol Sanlang",
    "wof:placetype":"locality"
},
  "geometry": {"coordinates":[103.41042,12.88111],"type":"Point"}
}