{
  "type": "Feature",
  "properties": {
    "gn:admin1_code":"28",
    "gn:asciiname":"Phum O Chamna Leu",
    "gn:country_code":"KH",
    "gn:dem":6,
    "gn:feature_class":"P",
    "gn:feature_code":"PPL",
    "gn:name":"Phum O Ch\u00e2mna Leu",
    "gn:population":0,
    "gn:timezone":"Asia/Phnom_Penh",
    "iso:country":"KH",
    "name:khm_x_preferred":[
        "Phum O Ch\u00e2mna Leu"
    ],
    "name:khm_x_variant":[
        "\u1797\u17bc\u1798\u17b7 \u17a2\u17bc\u1785\u17c6\u178e\u17b6\u179a\u179b\u17be"
    ],
    "name:und_x_variant":[
        "Phum\u012d O Ch\u00e2mnar Leu"
    ],
    "wof:name":"Phum O Chamna Leu",
    "wof:placetype":"locality"
},
  "geometry": {"coordinates":[103.75605,10.592],"type":"Point"}
}