{
  "type": "Feature",
  "properties": {
    "gn:admin1_code":"29",
    "gn:asciiname":"Koun Khlong",
    "gn:country_code":"KH",
    "gn:dem":16,
    "gn:feature_class":"P",
    "gn:feature_code":"PPL",
    "gn:name":"Koun Khlong",
    "gn:population":0,
    "gn:timezone":"Asia/Phnom_Penh",
    "iso:country":"KH",
    "name:khm_x_preferred":[
        "Koun Khlong"
    ],
    "name:khm_x_variant":[
        "Phum Prey D\u00e2mrei",
        "\u1797\u17bc\u1798\u17b7 \u1796\u17d2\u179a\u17c3\u178a\u17c6\u179a\u17b8"
    ],
    "name:und_x_variant":[
        "Phum\u012d Prey D\u00e2mrei"
    ],
    "wof:name":"Koun Khlong",
    "wof:placetype":"locality"
},
  "geometry": {"coordinates":[103.36508000000001,12.91949],"type":"Point"}
}