{
  "type": "Feature",
  "properties": {
    "gn:admin1_code":"27.0",
    "gn:asciiname":"Ou Smach",
    "gn:country_code":"KH",
    "gn:dem":231,
    "gn:feature_class":"P",
    "gn:feature_code":"PPL",
    "gn:name":"Ou Smach",
    "gn:population":0,
    "gn:timezone":"Asia/Phnom_Penh",
    "iso:country":"KH",
    "name:khm_x_preferred":[
        "Ou Smach"
    ],
    "wof:name":"Ou Smach",
    "wof:placetype":"locality"
},
  "geometry": {"coordinates":[103.69571000000001,14.42479],"type":"Point"}
}