{
  "type": "Feature",
  "properties": {
    "gn:admin1_code":"12.0",
    "gn:asciiname":"Phum Trapeang Chhuk",
    "gn:country_code":"KH",
    "gn:dem":58,
    "gn:feature_class":"P",
    "gn:feature_code":"PPL",
    "gn:name":"Phum Tr\u00e2pe\u0103ng Chhuk",
    "gn:population":0,
    "gn:timezone":"Asia/Phnom_Penh",
    "iso:country":"KH",
    "name:khm_x_preferred":[
        "Phum Tr\u00e2pe\u0103ng Chhuk"
    ],
    "name:khm_x_variant":[
        "\u1797\u17bc\u1798\u17b7 \u178f\u17d2\u179a\u1796\u17b6\u17c6\u1784\u1788\u17bc\u1780"
    ],
    "wof:name":"Phum Trapeang Chhuk",
    "wof:placetype":"locality"
},
  "geometry": {"coordinates":[104.12485,12.33074],"type":"Point"}
}