{
  "type": "Feature",
  "properties": {
    "gn:admin1_code":"18",
    "gn:asciiname":"Tuol Angk",
    "gn:country_code":"KH",
    "gn:dem":9,
    "gn:feature_class":"P",
    "gn:feature_code":"PPL",
    "gn:name":"Tuol Angk",
    "gn:population":0,
    "gn:timezone":"Asia/Phnom_Penh",
    "iso:country":"KH",
    "name:khm_x_preferred":[
        "Tuol Angk"
    ],
    "wof:name":"Tuol Angk",
    "wof:placetype":"locality"
},
  "geometry": {"coordinates":[105.93474999999999,11.15973],"type":"Point"}
}