{
  "type": "Feature",
  "properties": {
    "gn:admin1_code":"24",
    "gn:asciiname":"Prey Chhkar",
    "gn:country_code":"KH",
    "gn:dem":58,
    "gn:feature_class":"P",
    "gn:feature_code":"PPL",
    "gn:name":"Prey Chhkar",
    "gn:population":0,
    "gn:timezone":"Asia/Phnom_Penh",
    "iso:country":"KH",
    "name:khm_x_preferred":[
        "Prey Chhkar"
    ],
    "name:und_x_variant":[
        "Phum\u012d Prey Chhka"
    ],
    "wof:name":"Prey Chhkar",
    "wof:placetype":"locality"
},
  "geometry": {"coordinates":[104.35106,13.31191],"type":"Point"}
}