{
  "type": "Feature",
  "properties": {
    "gn:admin1_code":"03",
    "gn:asciiname":"Phum Hansriev",
    "gn:country_code":"KH",
    "gn:dem":59,
    "gn:feature_class":"P",
    "gn:feature_code":"PPL",
    "gn:name":"Phum H\u0103nsri\u0115v",
    "gn:population":0,
    "gn:timezone":"Asia/Phnom_Penh",
    "iso:country":"KH",
    "name:khm_x_preferred":[
        "Phum H\u0103nsri\u0115v"
    ],
    "name:khm_x_variant":[
        "\u1797\u17bc\u1798\u17b7 \u17a0\u17b6\u1793\u17cb\u179f\u17d2\u179a\u17c0\u179c"
    ],
    "name:und_x_variant":[
        "Hann Sreou",
        "Phum\u012d H\u0103nsri\u0115v"
    ],
    "wof:name":"Phum Hansriev",
    "wof:placetype":"locality"
},
  "geometry": {"coordinates":[104.47401000000001,12.14651],"type":"Point"}
}