{
  "type": "Feature",
  "properties": {
    "gn:admin1_code":"3.0",
    "gn:asciiname":"Tang Thnong",
    "gn:country_code":"KH",
    "gn:dem":69,
    "gn:feature_class":"P",
    "gn:feature_code":"PPL",
    "gn:name":"Tang Thnong",
    "gn:population":0,
    "gn:timezone":"Asia/Phnom_Penh",
    "iso:country":"KH",
    "name:khm_x_preferred":[
        "Tang Thnong"
    ],
    "wof:name":"Tang Thnong",
    "wof:placetype":"locality"
},
  "geometry": {"coordinates":[104.44257,12.03348],"type":"Point"}
}