{
  "type": "Feature",
  "properties": {
    "gn:admin1_code":"29",
    "gn:asciiname":"Run",
    "gn:country_code":"KH",
    "gn:dem":26,
    "gn:feature_class":"P",
    "gn:feature_code":"PPL",
    "gn:name":"Run",
    "gn:population":0,
    "gn:timezone":"Asia/Phnom_Penh",
    "iso:country":"KH",
    "name:ceb_x_preferred":[
        "Run"
    ],
    "name:dan_x_preferred":[
        "Run"
    ],
    "name:deu_x_preferred":[
        "Run"
    ],
    "name:fin_x_preferred":[
        "Run"
    ],
    "name:fra_x_preferred":[
        "Run"
    ],
    "name:khm_x_preferred":[
        "Run"
    ],
    "name:khm_x_variant":[
        "\u1797\u17bc\u1798\u17b7 \u179a\u17bb\u1793"
    ],
    "name:nld_x_preferred":[
        "Run"
    ],
    "name:pol_x_preferred":[
        "Run"
    ],
    "name:por_x_preferred":[
        "Run"
    ],
    "name:slk_x_preferred":[
        "Run"
    ],
    "name:swe_x_preferred":[
        "Run"
    ],
    "name:tam_x_preferred":[
        "\u0b93\u0b9f\u0bcd\u0b9f\u0bae\u0bcd"
    ],
    "name:und_x_variant":[
        "P\u2019um Run",
        "Phum\u012d R\u016dn"
    ],
    "wof:name":"Run",
    "wof:placetype":"locality"
},
  "geometry": {"coordinates":[103.47412,12.69538],"type":"Point"}
}