{
  "type": "Feature",
  "properties": {
    "gn:admin1_code":"13",
    "gn:asciiname":"Stueng Khnar",
    "gn:country_code":"KH",
    "gn:dem":87,
    "gn:feature_class":"P",
    "gn:feature_code":"PPL",
    "gn:name":"Stueng Khnar",
    "gn:population":0,
    "gn:timezone":"Asia/Phnom_Penh",
    "iso:country":"KH",
    "name:khm_x_preferred":[
        "Stueng Khnar"
    ],
    "name:khm_x_variant":[
        "Phum\u012d St\u0153\u0306ng",
        "\u1797\u17bc\u1798\u17b7 \u179f\u17d2\u1791\u17ba\u1784"
    ],
    "wof:name":"Stueng Khnar",
    "wof:placetype":"locality"
},
  "geometry": {"coordinates":[104.86997,13.5928],"type":"Point"}
}