{
  "type": "Feature",
  "properties": {
    "gn:admin1_code":"24",
    "gn:asciiname":"Sranal",
    "gn:country_code":"KH",
    "gn:dem":19,
    "gn:feature_class":"P",
    "gn:feature_code":"PPL",
    "gn:name":"Sranal",
    "gn:population":0,
    "gn:timezone":"Asia/Phnom_Penh",
    "iso:country":"KH",
    "name:khm_x_preferred":[
        "Sranal"
    ],
    "name:khm_x_variant":[
        "\u1797\u17bc\u1798\u17b7 \u179f\u17d2\u179a\u178e\u179b\u17cb",
        "Phum Sr\u00e2n\u0103l"
    ],
    "name:und_x_variant":[
        "Phum\u012d Sr\u00e2n\u0103l"
    ],
    "wof:name":"Sranal",
    "wof:placetype":"locality"
},
  "geometry": {"coordinates":[103.46871,13.55405],"type":"Point"}
}