{
  "type": "Feature",
  "properties": {
    "gn:admin1_code":"18",
    "gn:asciiname":"Phumi Don Leb",
    "gn:country_code":"KH",
    "gn:dem":8,
    "gn:feature_class":"P",
    "gn:feature_code":"PPL",
    "gn:name":"Phum\u012d Don L\u00eab",
    "gn:population":0,
    "gn:timezone":"Asia/Phnom_Penh",
    "iso:country":"KH",
    "name:und_x_variant":[
        "Phum Tonleap",
        "Phumi Don L\u00eap",
        "Phum\u012d Don L\u00eab"
    ],
    "wof:name":"Phumi Don Leb",
    "wof:placetype":"locality"
},
  "geometry": {"coordinates":[105.67253999999998,11.1417],"type":"Point"}
}