{
  "type": "Feature",
  "properties": {
    "gn:admin1_code":"31",
    "gn:asciiname":"Phumi Thma Kanhchom",
    "gn:country_code":"KH",
    "gn:dem":19,
    "gn:feature_class":"P",
    "gn:feature_code":"PPL",
    "gn:name":"Phum\u012d Thm\u00e2 K\u00e2nhchom",
    "gn:population":0,
    "gn:timezone":"Asia/Phnom_Penh",
    "iso:country":"KH",
    "name:und_x_variant":[
        "Phum\u012d Thm\u00e2 K\u00e2nch\u014fm",
        "Phum Thmar Kanchum",
        "Phum\u012d Thm\u00e2 K\u00e2nhchom"
    ],
    "wof:name":"Phumi Thma Kanhchom",
    "wof:placetype":"locality"
},
  "geometry": {"coordinates":[105.44965000000001,11.77296],"type":"Point"}
}