{
  "type": "Feature",
  "properties": {
    "gn:admin1_code":"18",
    "gn:asciiname":"Phumi Kampong Krasang",
    "gn:country_code":"KH",
    "gn:dem":18,
    "gn:feature_class":"P",
    "gn:feature_code":"PPL",
    "gn:name":"Phum\u012d K\u00e2mp\u00f3ng Kr\u00e2s\u0103ng",
    "gn:population":0,
    "gn:timezone":"Asia/Phnom_Penh",
    "iso:country":"KH",
    "name:und_x_variant":[
        "Kompong Krassang",
        "Kompong Krassaing",
        "Phum\u012d K\u00e2mp\u00f3ng Kr\u00e2s\u0103ng"
    ],
    "wof:name":"Phumi Kampong Krasang",
    "wof:placetype":"locality"
},
  "geometry": {"coordinates":[105.71528000000001,11.53441],"type":"Point"}
}