{
  "type": "Feature",
  "properties": {
    "gn:admin1_code":"14",
    "gn:asciiname":"Prey Chek",
    "gn:country_code":"KH",
    "gn:dem":16,
    "gn:feature_class":"P",
    "gn:feature_code":"PPL",
    "gn:name":"Prey Chek",
    "gn:population":0,
    "gn:timezone":"Asia/Phnom_Penh",
    "iso:country":"KH",
    "name:khm_x_preferred":[
        "Prey Chek"
    ],
    "name:und_x_variant":[
        "Phum\u012d Prey Ch\u00e9k"
    ],
    "wof:name":"Prey Chek",
    "wof:placetype":"locality"
},
  "geometry": {"coordinates":[105.64472000000001,11.31402],"type":"Point"}
}