{
  "type": "Feature",
  "properties": {
    "gn:admin1_code":"00",
    "gn:asciiname":"Phumi Chong Kaoh",
    "gn:country_code":"KH",
    "gn:dem":11,
    "gn:feature_class":"P",
    "gn:feature_code":"PPL",
    "gn:name":"Phum\u012d Ch\u014fng Ka\u00f4h",
    "gn:population":0,
    "gn:timezone":"Asia/Phnom_Penh",
    "iso:country":"KH",
    "name:und_x_variant":[
        "Tan L\u00f4ng",
        "Phum\u012d Ch\u014fng Ka\u00f4h"
    ],
    "wof:name":"Phumi Chong Kaoh",
    "wof:placetype":"locality"
},
  "geometry": {"coordinates":[105.17597000000001,10.9717],"type":"Point"}
}