{
  "type": "Feature",
  "properties": {
    "gn:admin1_code":"07",
    "gn:asciiname":"Phumi Traeuy Neay",
    "gn:country_code":"KH",
    "gn:dem":13,
    "gn:feature_class":"P",
    "gn:feature_code":"PPL",
    "gn:name":"Phum\u012d Traeuy N\u00e9ay",
    "gn:population":0,
    "gn:timezone":"Asia/Phnom_Penh",
    "iso:country":"KH",
    "name:und_x_variant":[
        "Takou",
        "Phum\u012d Traeuy N\u00e9ay"
    ],
    "wof:name":"Phumi Traeuy Neay",
    "wof:placetype":"locality"
},
  "geometry": {"coordinates":[104.83150000000001,11.37646],"type":"Point"}
}