{
  "type": "Feature",
  "properties": {
    "gn:admin1_code":"17",
    "gn:asciiname":"Rumdeng",
    "gn:country_code":"KH",
    "gn:dem":74,
    "gn:feature_class":"P",
    "gn:feature_code":"PPL",
    "gn:name":"Rumdeng",
    "gn:population":0,
    "gn:timezone":"Asia/Phnom_Penh",
    "iso:country":"KH",
    "name:khm_x_preferred":[
        "Rumdeng"
    ],
    "name:und_x_variant":[
        "Phum\u012d Rumd\u00e9ng"
    ],
    "wof:name":"Rumdeng",
    "wof:placetype":"locality"
},
  "geometry": {"coordinates":[105.74102000000001,13.50338],"type":"Point"}
}