{
  "type": "Feature",
  "properties": {
    "gn:admin1_code":"24",
    "gn:asciiname":"Kanhchan Run",
    "gn:country_code":"KH",
    "gn:dem":48,
    "gn:feature_class":"P",
    "gn:feature_code":"PPL",
    "gn:name":"Kanhchan Run",
    "gn:population":0,
    "gn:timezone":"Asia/Phnom_Penh",
    "iso:country":"KH",
    "name:khm_x_preferred":[
        "Kanhchan Run"
    ],
    "name:khm_x_variant":[
        "Phum Kom Phlaeup"
    ],
    "name:und_x_variant":[
        "Phum\u012d Kom Phlaeup",
        "Phum\u012d Kom Phlaeub"
    ],
    "wof:name":"Kanhchan Run",
    "wof:placetype":"locality"
},
  "geometry": {"coordinates":[103.79125000000001,13.8522],"type":"Point"}
}