{
  "type": "Feature",
  "properties": {
    "gn:admin1_code":"03",
    "gn:asciiname":"Phum Damnak Khlong",
    "gn:country_code":"KH",
    "gn:dem":68,
    "gn:feature_class":"P",
    "gn:feature_code":"PPL",
    "gn:name":"Phum D\u00e2mn\u0103k Khl\u014fng",
    "gn:population":0,
    "gn:timezone":"Asia/Phnom_Penh",
    "iso:country":"KH",
    "name:khm_x_preferred":[
        "Phum D\u00e2mn\u0103k Khl\u014fng"
    ],
    "name:khm_x_variant":[
        "\u1797\u17bc\u1798\u17b7 \u178a\u17c6\u178e\u17b6\u1780\u17cb\u1781\u17d2\u179b\u17bb\u1784"
    ],
    "name:und_x_variant":[
        "Phum\u012d D\u00e2mn\u0103k Khl\u014fng"
    ],
    "wof:name":"Phum Damnak Khlong",
    "wof:placetype":"locality"
},
  "geometry": {"coordinates":[104.22614,12.26678],"type":"Point"}
}