{
  "type": "Feature",
  "properties": {
    "gn:admin1_code":"24.0",
    "gn:asciiname":"Kansaeng",
    "gn:country_code":"KH",
    "gn:dem":16,
    "gn:feature_class":"P",
    "gn:feature_code":"PPL",
    "gn:name":"Kansaeng",
    "gn:population":0,
    "gn:timezone":"Asia/Phnom_Penh",
    "iso:country":"KH",
    "name:khm_x_preferred":[
        "Kansaeng"
    ],
    "name:khm_x_variant":[
        "\u1797\u17bc\u1798\u17b7 \u1780\u1793\u17d2\u179f\u17c2\u1784",
        "Phum K\u00e2ns\u00eang"
    ],
    "wof:name":"Kansaeng",
    "wof:placetype":"locality"
},
  "geometry": {"coordinates":[104.25621,13.19403],"type":"Point"}
}