{
  "type": "Feature",
  "properties": {
    "gn:admin1_code":"21",
    "gn:asciiname":"Phumi Daeum Svay",
    "gn:country_code":"KH",
    "gn:dem":7,
    "gn:feature_class":"P",
    "gn:feature_code":"PPL",
    "gn:name":"Phum\u012d Daeum Svay",
    "gn:population":0,
    "gn:timezone":"Asia/Phnom_Penh",
    "iso:country":"KH",
    "name:und_x_variant":[
        "Phum\u012d Daeum Svey",
        "Phum\u012d Daeum Svay"
    ],
    "wof:name":"Phumi Daeum Svay",
    "wof:placetype":"locality"
},
  "geometry": {"coordinates":[104.52282,10.59676],"type":"Point"}
}