{
  "type": "Feature",
  "properties": {
    "gn:admin1_code":"21",
    "gn:asciiname":"Phumi Chamkar Chek",
    "gn:country_code":"KH",
    "gn:dem":16,
    "gn:feature_class":"P",
    "gn:feature_code":"PPL",
    "gn:name":"Phum\u012d Ch\u00e2mkar Ch\u00e9k",
    "gn:population":0,
    "gn:timezone":"Asia/Phnom_Penh",
    "iso:country":"KH",
    "wof:name":"Phumi Chamkar Chek",
    "wof:placetype":"locality"
},
  "geometry": {"coordinates":[104.39781000000001,10.53864],"type":"Point"}
}