{
  "type": "Feature",
  "properties": {
    "gn:admin1_code":"7.0",
    "gn:asciiname":"Phum Peam Khla Trei",
    "gn:country_code":"KH",
    "gn:dem":9,
    "gn:feature_class":"P",
    "gn:feature_code":"PPL",
    "gn:name":"Phum P\u00e9am Khla Trei",
    "gn:population":0,
    "gn:timezone":"Asia/Phnom_Penh",
    "iso:country":"KH",
    "name:khm_x_preferred":[
        "Phum P\u00e9am Khla Trei"
    ],
    "name:khm_x_variant":[
        "\u1797\u17bc\u1798\u17b7 \u1796\u17b6\u1798\u1781\u17d2\u179b\u17b6\u178f\u17d2\u179a\u17b8"
    ],
    "wof:name":"Phum Peam Khla Trei",
    "wof:placetype":"locality"
},
  "geometry": {"coordinates":[105.01675,11.16454],"type":"Point"}
}