{
  "type": "Feature",
  "properties": {
    "gn:admin1_code":"13",
    "gn:asciiname":"Krasang",
    "gn:country_code":"KH",
    "gn:dem":91,
    "gn:feature_class":"P",
    "gn:feature_code":"PPL",
    "gn:name":"Krasang",
    "gn:population":0,
    "gn:timezone":"Asia/Phnom_Penh",
    "iso:country":"KH",
    "name:khm_x_preferred":[
        "Krasang"
    ],
    "wof:name":"Krasang",
    "wof:placetype":"locality"
},
  "geometry": {"coordinates":[105.41719999999999,13.75981],"type":"Point"}
}