{
  "type": "Feature",
  "properties": {
    "gn:admin1_code":"12",
    "gn:asciiname":"Phum Phsar Leu",
    "gn:country_code":"KH",
    "gn:dem":25,
    "gn:feature_class":"P",
    "gn:feature_code":"PPL",
    "gn:name":"Phum Phsar Leu",
    "gn:population":0,
    "gn:timezone":"Asia/Phnom_Penh",
    "iso:country":"KH",
    "name:khm_x_preferred":[
        "Phum Phsar Leu"
    ],
    "name:khm_x_variant":[
        "\u1797\u17bc\u1798\u17b7 \u1795\u17d2\u179f\u17b6\u179a\u179b\u17be"
    ],
    "name:und_x_variant":[
        "Psar Lo",
        "Phum\u012d Phsar Leu",
        "Phum\u012d Phsa Leu"
    ],
    "wof:name":"Phum Phsar Leu",
    "wof:placetype":"locality"
},
  "geometry": {"coordinates":[103.87551999999999,12.50873],"type":"Point"}
}