{
  "type": "Feature",
  "properties": {
    "gn:admin1_code":"12",
    "gn:asciiname":"Pring Khpos",
    "gn:country_code":"KH",
    "gn:dem":15,
    "gn:feature_class":"P",
    "gn:feature_code":"PPL",
    "gn:name":"Pring Khpos",
    "gn:population":0,
    "gn:timezone":"Asia/Phnom_Penh",
    "iso:country":"KH",
    "name:khm_x_preferred":[
        "Pring Khpos"
    ],
    "name:khm_x_variant":[
        "\u1797\u17bc\u1798\u17b7 \u1796\u17d2\u179a\u17b8\u1784\u1781\u17d2\u1796\u179f\u17cb",
        "Phum Pring Khpu\u014fs"
    ],
    "name:und_x_variant":[
        "P\u2019um Pring K\u2019p\u014fs",
        "Phum\u012d Pring Khpu\u014fs",
        "Phum\u012d Pring Khp\u00f3s"
    ],
    "wof:name":"Pring Khpos",
    "wof:placetype":"locality"
},
  "geometry": {"coordinates":[103.95777,12.67357],"type":"Point"}
}