{
  "type": "Feature",
  "properties": {
    "gn:admin1_code":"04",
    "gn:asciiname":"Phumi Kouk Trab",
    "gn:country_code":"KH",
    "gn:dem":45,
    "gn:feature_class":"P",
    "gn:feature_code":"PPL",
    "gn:name":"Phum\u012d Ko\u016dk Tr\u00e1b",
    "gn:population":0,
    "gn:timezone":"Asia/Phnom_Penh",
    "iso:country":"KH",
    "name:und_x_variant":[
        "Phum Prey Kantr\u00e2p",
        "Phum\u012d Ko\u016dk Tr\u00e2p",
        "Kantrap",
        "Phum\u012d Ko\u016dk Tr\u00e1b"
    ],
    "wof:name":"Phumi Kouk Trab",
    "wof:placetype":"locality"
},
  "geometry": {"coordinates":[104.5564,11.17444],"type":"Point"}
}