{
  "type": "Feature",
  "properties": {
    "gn:admin1_code":"19",
    "gn:asciiname":"Phumi Trong Phumi",
    "gn:country_code":"KH",
    "gn:dem":10,
    "gn:feature_class":"P",
    "gn:feature_code":"PPL",
    "gn:name":"Phum\u012d Tr\u00f3ng Phum\u012d",
    "gn:population":0,
    "gn:timezone":"Asia/Phnom_Penh",
    "iso:country":"KH",
    "name:und_x_variant":[
        "Phum Trong Phum",
        "Phum\u012d Tr\u016dng Phum",
        "Phum\u012d Tr\u00f3ng Phum\u012d"
    ],
    "wof:name":"Phumi Trong Phumi",
    "wof:placetype":"locality"
},
  "geometry": {"coordinates":[104.89988,11.01802],"type":"Point"}
}