{
  "type": "Feature",
  "properties": {
    "gn:admin1_code":"14",
    "gn:asciiname":"Pou Ta Mom",
    "gn:country_code":"KH",
    "gn:dem":15,
    "gn:feature_class":"P",
    "gn:feature_code":"PPL",
    "gn:name":"Pou Ta Mom",
    "gn:population":0,
    "gn:timezone":"Asia/Phnom_Penh",
    "iso:country":"KH",
    "name:khm_x_preferred":[
        "Pou Ta Mom"
    ],
    "wof:name":"Pou Ta Mom",
    "wof:placetype":"locality"
},
  "geometry": {"coordinates":[105.56716000000002,11.36699],"type":"Point"}
}