{
  "type": "Feature",
  "properties": {
    "gn:admin1_code":"31",
    "gn:asciiname":"Trapeang Phlong Muoy",
    "gn:country_code":"KH",
    "gn:dem":31,
    "gn:feature_class":"P",
    "gn:feature_code":"PPL",
    "gn:name":"Trapeang Phlong Muoy",
    "gn:population":0,
    "gn:timezone":"Asia/Phnom_Penh",
    "iso:country":"KH",
    "name:khm_x_preferred":[
        "Trapeang Phlong Muoy"
    ],
    "wof:name":"Trapeang Phlong Muoy",
    "wof:placetype":"locality"
},
  "geometry": {"coordinates":[105.96923,11.6995],"type":"Point"}
}