{
  "type": "Feature",
  "properties": {
    "gn:admin1_code":"24",
    "gn:asciiname":"Phum Changaeur Leav",
    "gn:country_code":"KH",
    "gn:dem":19,
    "gn:feature_class":"P",
    "gn:feature_code":"PPL",
    "gn:name":"Phum Ch\u00e2ngaeur L\u00e9av",
    "gn:population":0,
    "gn:timezone":"Asia/Phnom_Penh",
    "iso:country":"KH",
    "name:khm_x_preferred":[
        "Phum Ch\u00e2ngaeur L\u00e9av"
    ],
    "name:khm_x_variant":[
        "\u1797\u17bc\u1798\u17b7 \u1785\u1784\u17d2\u17a2\u17be\u179a\u179b\u17b6\u179c"
    ],
    "name:und_x_variant":[
        "Phum\u012d Ch\u00e2ng\u2019aeur L\u00e9av"
    ],
    "wof:name":"Phum Changaeur Leav",
    "wof:placetype":"locality"
},
  "geometry": {"coordinates":[103.67185000000001,13.53179],"type":"Point"}
}