{
  "type": "Feature",
  "properties": {
    "gn:admin1_code":"07",
    "gn:asciiname":"Beng",
    "gn:country_code":"KH",
    "gn:dem":32,
    "gn:feature_class":"P",
    "gn:feature_code":"PPL",
    "gn:name":"Beng",
    "gn:population":0,
    "gn:timezone":"Asia/Phnom_Penh",
    "iso:country":"KH",
    "name:ceb_x_preferred":[
        "Beng"
    ],
    "name:deu_x_preferred":[
        "Beng"
    ],
    "name:fra_x_preferred":[
        "Beng"
    ],
    "name:nld_x_preferred":[
        "Beng"
    ],
    "name:swe_x_preferred":[
        "Beng"
    ],
    "name:und_x_variant":[
        "Phum\u012d B\u0153\u0306ng T\u00f4t\u0153\u0306ng"
    ],
    "wof:name":"Beng",
    "wof:placetype":"locality"
},
  "geometry": {"coordinates":[104.69208999999999,11.57984],"type":"Point"}
}