{
  "type": "Feature",
  "properties": {
    "gn:admin1_code":"04",
    "gn:asciiname":"Phumi Trapeang Angkrong",
    "gn:cc2":"KH",
    "gn:country_code":"KH",
    "gn:dem":35,
    "gn:feature_class":"P",
    "gn:feature_code":"PPL",
    "gn:name":"Phum\u012d Tr\u00e2pe\u0103ng \u00c2ngkr\u00f4ng",
    "gn:population":0,
    "gn:timezone":"Asia/Phnom_Penh",
    "iso:country":"KH",
    "name:und_x_variant":[
        "Trapeang Ang Krong",
        "Phum\u012d Tr\u00e2pe\u0103ng \u00c2ngkr\u00f4ng"
    ],
    "wof:name":"Phumi Trapeang Angkrong",
    "wof:placetype":"locality"
},
  "geometry": {"coordinates":[104.63333,11.78333],"type":"Point"}
}