{
  "type": "Feature",
  "properties": {
    "gn:admin1_code":"04",
    "gn:asciiname":"Phumi Prey Rumduol Toch",
    "gn:country_code":"KH",
    "gn:dem":37,
    "gn:feature_class":"P",
    "gn:feature_code":"PPL",
    "gn:name":"Phum\u012d Prey Rumdu\u014fl Toch",
    "gn:population":0,
    "gn:timezone":"Asia/Phnom_Penh",
    "iso:country":"KH",
    "wof:name":"Phumi Prey Rumduol Toch",
    "wof:placetype":"locality"
},
  "geometry": {"coordinates":[104.50385,11.13656],"type":"Point"}
}