{
  "type": "Feature",
  "properties": {
    "gn:admin1_code":"21",
    "gn:asciiname":"Phumi Toanhan",
    "gn:country_code":"KH",
    "gn:dem":6,
    "gn:feature_class":"P",
    "gn:feature_code":"PPL",
    "gn:name":"Phum\u012d To\u0103nh\u00e1n",
    "gn:population":0,
    "gn:timezone":"Asia/Phnom_Penh",
    "iso:country":"KH",
    "name:und_x_variant":[
        "Tonhon",
        "Phum\u012d Tonhon (1)",
        "Phum\u012d To\u0103nh\u00e1n"
    ],
    "wof:name":"Phumi Toanhan",
    "wof:placetype":"locality"
},
  "geometry": {"coordinates":[104.58524,10.54285],"type":"Point"}
}