{
  "type": "Feature",
  "properties": {
    "gn:admin1_code":"5.0",
    "gn:asciiname":"Preaek Damrei Koun",
    "gn:country_code":"KH",
    "gn:dem":4,
    "gn:feature_class":"P",
    "gn:feature_code":"PPL",
    "gn:name":"Preaek Damrei Koun",
    "gn:population":0,
    "gn:timezone":"Asia/Phnom_Penh",
    "iso:country":"KH",
    "name:khm_x_preferred":[
        "Preaek Damrei Koun"
    ],
    "name:khm_x_variant":[
        "\u1796\u17d2\u179a\u17c2\u1780\u178a\u17c6\u179a\u17b8\u1780\u17bc\u1793",
        "Pr\u00eak D\u00e2mrei Kon"
    ],
    "wof:name":"Preaek Damrei Koun",
    "wof:placetype":"locality"
},
  "geometry": {"coordinates":[104.25357,12.73433],"type":"Point"}
}