{
  "type": "Feature",
  "properties": {
    "gn:admin1_code":"14",
    "gn:asciiname":"Phumi Ta Meng",
    "gn:country_code":"KH",
    "gn:dem":11,
    "gn:feature_class":"P",
    "gn:feature_code":"PPL",
    "gn:name":"Phum\u012d Ta M\u00eang",
    "gn:population":0,
    "gn:timezone":"Asia/Phnom_Penh",
    "iso:country":"KH",
    "name:und_x_variant":[
        "Phum Trameng",
        "Phum\u012d Ta M\u00eang"
    ],
    "wof:name":"Phumi Ta Meng",
    "wof:placetype":"locality"
},
  "geometry": {"coordinates":[105.21189,11.53347],"type":"Point"}
}