{
  "type": "Feature",
  "properties": {
    "gn:admin1_code":"31",
    "gn:asciiname":"Phum Ti Bei",
    "gn:country_code":"KH",
    "gn:dem":24,
    "gn:feature_class":"P",
    "gn:feature_code":"PPL",
    "gn:name":"Phum Ti Bei",
    "gn:population":0,
    "gn:timezone":"Asia/Phnom_Penh",
    "iso:country":"KH",
    "name:khm_x_preferred":[
        "Phum Ti Bei"
    ],
    "wof:name":"Phum Ti Bei",
    "wof:placetype":"locality"
},
  "geometry": {"coordinates":[105.67104999999999,12.26029],"type":"Point"}
}