{
  "type": "Feature",
  "properties": {
    "gn:admin1_code":"17",
    "gn:asciiname":"Phumi Lung Thmei",
    "gn:country_code":"KH",
    "gn:dem":53,
    "gn:feature_class":"P",
    "gn:feature_code":"PPL",
    "gn:name":"Phum\u012d L\u016dng Thmei",
    "gn:population":0,
    "gn:timezone":"Asia/Phnom_Penh",
    "iso:country":"KH",
    "wof:name":"Phumi Lung Thmei",
    "wof:placetype":"locality"
},
  "geometry": {"coordinates":[105.92761000000002,13.2487],"type":"Point"}
}