{
  "type": "Feature",
  "properties": {
    "gn:admin1_code":"09",
    "gn:asciiname":"Doun Mea",
    "gn:country_code":"KH",
    "gn:dem":67,
    "gn:feature_class":"P",
    "gn:feature_code":"PPL",
    "gn:name":"Doun Mea",
    "gn:population":0,
    "gn:timezone":"Asia/Phnom_Penh",
    "iso:country":"KH",
    "name:khm_x_preferred":[
        "Doun Mea"
    ],
    "name:khm_x_variant":[
        "\u1797\u17bc\u1798\u17b7 \u178a\u17bc\u1793\u1798\u17b6",
        "Phum Don M\u00e9a"
    ],
    "wof:name":"Doun Mea",
    "wof:placetype":"locality"
},
  "geometry": {"coordinates":[106.29242000000001,12.24329],"type":"Point"}
}