{
  "type": "Feature",
  "properties": {
    "gn:admin1_code":"12",
    "gn:asciiname":"Roluos Kandal",
    "gn:country_code":"KH",
    "gn:dem":22,
    "gn:feature_class":"P",
    "gn:feature_code":"PPL",
    "gn:name":"Roluos Kandal",
    "gn:population":0,
    "gn:timezone":"Asia/Phnom_Penh",
    "iso:country":"KH",
    "name:khm_x_preferred":[
        "Roluos Kandal"
    ],
    "wof:name":"Roluos Kandal",
    "wof:placetype":"locality"
},
  "geometry": {"coordinates":[104.05034000000001,12.58999],"type":"Point"}
}