{
  "type": "Feature",
  "properties": {
    "gn:admin1_code":"31",
    "gn:asciiname":"Doung",
    "gn:country_code":"KH",
    "gn:dem":151,
    "gn:feature_class":"P",
    "gn:feature_code":"PPL",
    "gn:name":"Doung",
    "gn:population":0,
    "gn:timezone":"Asia/Phnom_Penh",
    "iso:country":"KH",
    "name:khm_x_preferred":[
        "Doung"
    ],
    "name:und_x_variant":[
        "Phum\u012d Khch\u00e9ay",
        "Phum\u012d Dong"
    ],
    "wof:name":"Doung",
    "wof:placetype":"locality"
},
  "geometry": {"coordinates":[106.22908,11.81963],"type":"Point"}
}