{
  "type": "Feature",
  "properties": {
    "gn:admin1_code":"21",
    "gn:asciiname":"Phumi Kaoh Tonsay",
    "gn:country_code":"KH",
    "gn:dem":10,
    "gn:feature_class":"P",
    "gn:feature_code":"PPL",
    "gn:name":"Phum\u012d Ka\u00f4h T\u00f4nsay",
    "gn:population":0,
    "gn:timezone":"Asia/Phnom_Penh",
    "iso:country":"KH",
    "name:und_x_variant":[
        "Phum\u012d Ka\u00f4h T\u016dnsay",
        "Phum\u012d Ka\u00f4h T\u00f4nsay"
    ],
    "wof:name":"Phumi Kaoh Tonsay",
    "wof:placetype":"locality"
},
  "geometry": {"coordinates":[104.322,10.43793],"type":"Point"}
}