{
  "type": "Feature",
  "properties": {
    "gn:admin1_code":"02",
    "gn:asciiname":"Phumi Andong Chroah",
    "gn:country_code":"KH",
    "gn:dem":51,
    "gn:feature_class":"P",
    "gn:feature_code":"PPL",
    "gn:name":"Phum\u012d \u00c2ndong Chr\u014f\u0103h",
    "gn:population":0,
    "gn:timezone":"Asia/Phnom_Penh",
    "iso:country":"KH",
    "name:und_x_variant":[
        "Phum Andong Chros",
        "Phum\u012d \u00c2ndong Chru\u014fh",
        "Phum\u012d \u00c2ndong Chr\u014f\u0103h"
    ],
    "wof:name":"Phumi Andong Chroah",
    "wof:placetype":"locality"
},
  "geometry": {"coordinates":[105.41240000000001,12.02652],"type":"Point"}
}