{
  "type": "Feature",
  "properties": {
    "gn:admin1_code":"12.0",
    "gn:asciiname":"Phum Toul Puos",
    "gn:country_code":"KH",
    "gn:dem":21,
    "gn:feature_class":"P",
    "gn:feature_code":"PPL",
    "gn:name":"Phum To\u016dl Pu\u014fs",
    "gn:population":0,
    "gn:timezone":"Asia/Phnom_Penh",
    "iso:country":"KH",
    "name:khm_x_preferred":[
        "Phum To\u016dl Pu\u014fs"
    ],
    "name:khm_x_variant":[
        "\u1797\u17bc\u1798\u17b7 \u1791\u17bd\u179b\u1796\u179f\u17cb"
    ],
    "wof:name":"Phum Toul Puos",
    "wof:placetype":"locality"
},
  "geometry": {"coordinates":[103.91748,12.57368],"type":"Point"}
}