{
  "type": "Feature",
  "properties": {
    "gn:admin1_code":"02",
    "gn:asciiname":"Phumi Prey Kbeh",
    "gn:country_code":"KH",
    "gn:dem":19,
    "gn:feature_class":"P",
    "gn:feature_code":"PPL",
    "gn:name":"Phum\u012d Prey Kb\u00e9h",
    "gn:population":0,
    "gn:timezone":"Asia/Phnom_Penh",
    "iso:country":"KH",
    "name:und_x_variant":[
        "Prey Khbes",
        "Phum\u012d Prey Kb\u00e9h"
    ],
    "wof:name":"Phumi Prey Kbeh",
    "wof:placetype":"locality"
},
  "geometry": {"coordinates":[105.09405,11.81535],"type":"Point"}
}