{
  "type": "Feature",
  "properties": {
    "gn:admin1_code":"13",
    "gn:asciiname":"Damnak Chen",
    "gn:country_code":"KH",
    "gn:dem":57,
    "gn:feature_class":"P",
    "gn:feature_code":"PPL",
    "gn:name":"Damnak Chen",
    "gn:population":0,
    "gn:timezone":"Asia/Phnom_Penh",
    "iso:country":"KH",
    "name:khm_x_preferred":[
        "Damnak Chen"
    ],
    "wof:name":"Damnak Chen",
    "wof:placetype":"locality"
},
  "geometry": {"coordinates":[105.12441,13.37635],"type":"Point"}
}