{
  "type": "Feature",
  "properties": {
    "gn:admin1_code":"05",
    "gn:asciiname":"Phumi Kong Yeam",
    "gn:country_code":"KH",
    "gn:dem":19,
    "gn:feature_class":"P",
    "gn:feature_code":"PPL",
    "gn:name":"Phum\u012d K\u00f3ng Y\u00e9am",
    "gn:population":0,
    "gn:timezone":"Asia/Phnom_Penh",
    "iso:country":"KH",
    "name:und_x_variant":[
        "Konyeam",
        "Phum\u012d K\u00f3ng Y\u00e9am"
    ],
    "wof:name":"Phumi Kong Yeam",
    "wof:placetype":"locality"
},
  "geometry": {"coordinates":[105.02582,12.7876],"type":"Point"}
}