{
  "type": "Feature",
  "properties": {
    "gn:admin1_code":"31.0",
    "gn:asciiname":"Phum Bei",
    "gn:country_code":"KH",
    "gn:dem":23,
    "gn:feature_class":"P",
    "gn:feature_code":"PPL",
    "gn:name":"Phum Bei",
    "gn:population":0,
    "gn:timezone":"Asia/Phnom_Penh",
    "iso:country":"KH",
    "name:khm_x_preferred":[
        "Phum Bei"
    ],
    "wof:name":"Phum Bei",
    "wof:placetype":"locality"
},
  "geometry": {"coordinates":[105.53175,12.07821],"type":"Point"}
}