{
  "type": "Feature",
  "properties": {
    "gn:admin1_code":"04",
    "gn:asciiname":"Khleang",
    "gn:country_code":"KH",
    "gn:dem":27,
    "gn:feature_class":"P",
    "gn:feature_code":"PPL",
    "gn:name":"Khleang",
    "gn:population":0,
    "gn:timezone":"Asia/Phnom_Penh",
    "iso:country":"KH",
    "name:khm_x_preferred":[
        "Khleang"
    ],
    "name:und_x_variant":[
        "Khlang",
        "Phum\u012d Khle\u0103ng"
    ],
    "wof:name":"Khleang",
    "wof:placetype":"locality"
},
  "geometry": {"coordinates":[104.69652000000001,11.73156],"type":"Point"}
}