{
  "type": "Feature",
  "properties": {
    "gn:admin1_code":"29",
    "gn:asciiname":"Phum Kampong Pou",
    "gn:country_code":"KH",
    "gn:dem":11,
    "gn:feature_class":"P",
    "gn:feature_code":"PPL",
    "gn:name":"Phum K\u00e2mp\u00f4ng Po\u016d",
    "gn:population":0,
    "gn:timezone":"Asia/Phnom_Penh",
    "iso:country":"KH",
    "name:khm_x_preferred":[
        "Phum K\u00e2mp\u00f4ng Po\u016d"
    ],
    "name:khm_x_variant":[
        "\u1797\u17bc\u1798\u17b7 \u1780\u17c6\u1796\u1784\u17cb\u1796\u17c4"
    ],
    "wof:name":"Phum Kampong Pou",
    "wof:placetype":"locality"
},
  "geometry": {"coordinates":[103.16061000000001,13.2022],"type":"Point"}
}